Workbook

Sheet Gap Trace
A1: BRACKET-GAP LEDGER TRACE 2019 — every Recon row where Stock > Challan
A2: Each ledger sale behind the Stock figure was traced to its challan (Pivot Data, cancellations applied). No Recon values changed.
B4: VERDICT | C4: Rows | D4: Gap (pcs)
B5: Explained – issued inside SDN assemblies | C5: 31 | D5: -548
B6: Explained – ledger posting not backed by a live challan line | C6: 44 | D6: -593
B7: Recon Challan short – challan lines exist | C7: 59 | D7: -3395
B8: Partly explained | C8: 16 | D8: -857
B9: Ledger postings ≠ Stock total | C9: 3 | D9: -113
B10: Total | C10: =SUM(C5:C9) -> 153 | D10: =SUM(D5:D9) -> -5506
A13: # | B13: Verdict | C13: Recon cell (Gap) | D13: Section | E13: Part | F13: Code | G13: Challan | H13: Stock | I13: Gap | J13: Ledger trace | K13: Action
A14: 1 | B14: Explained – issued inside SDN assemblies | C14: X323 | D14: PART 10 – HOSE & TUBE ASSEMBLIES | E14: SD-1020ACCD-CP | F14: INNOVA DUAL | G14: 0 | H14: 95 | I14: -95 | J14: 95 pcs issued inside assemblies | K14: No change — assembly sold on challan, component issued in ledger.
A15: 2 | B15: Explained – issued inside SDN assemblies | C15: X331 | D15: PART 10 – HOSE & TUBE ASSEMBLIES | E15: SD-228CP/BLR | F15: BOLERO | G15: 0 | H15: 54 | I15: -54 | J15: 54 pcs issued inside assemblies | K15: No change — assembly sold on challan, component issued in ledger.
A16: 3 | B16: Explained – issued inside SDN assemblies | C16: X156 | D16: PART 7 – COILS | E16: LOGAN DSL | F16: SD-145MC/LGN.DSL | G16: 30 | H16: 71 | I16: -41 | J16: 41 pcs issued inside assemblies | K16: No change — assembly sold on challan, component issued in ledger.
A17: 4 | B17: Explained – issued inside SDN assemblies | C17: X354 | D17: PART 10 – HOSE & TUBE ASSEMBLIES | E17: SD240CP/LGN.DSL | F17: LOGAN DSL | G17: 0 | H17: 41 | I17: -41 | J17: 41 pcs issued inside assemblies | K17: No change — assembly sold on challan, component issued in ledger.
A18: 5 | B18: Explained – issued inside SDN assemblies | C18: X336 | D18: PART 10 – HOSE & TUBE ASSEMBLIES | E18: SD-222VP/HT4ZXDSL | F18: HONDA ZX/T4 | G18: 0 | H18: 32 | I18: -32 | J18: 32 pcs issued inside assemblies | K18: No change — assembly sold on challan, component issued in ledger.
A19: 6 | B19: Explained – issued inside SDN assemblies | C19: X165 | D19: PART 7 – COILS | E19: XUV 500 | F19: SD153MC/MX5 | G19: 0 | H19: 30 | I19: -30 | J19: 30 pcs issued inside assemblies | K19: No change — assembly sold on challan, component issued in ledger.
A20: 7 | B20: Explained – issued inside SDN assemblies | C20: X317 | D20: PART 10 – HOSE & TUBE ASSEMBLIES | E20: SD-1008WR-CP | F20: WR INNOVA SINGLE | G20: 0 | H20: 30 | I20: -30 | J20: 30 pcs issued inside assemblies | K20: No change — assembly sold on challan, component issued in ledger.
A21: 8 | B21: Explained – issued inside SDN assemblies | C21: X154 | D21: PART 7 – COILS | E21: FIGO | F21: SD148MC/FIGO | G21: 0 | H21: 28 | I21: -28 | J21: 28 pcs issued inside assemblies | K21: No change — assembly sold on challan, component issued in ledger.
A22: 9 | B22: Explained – issued inside SDN assemblies | C22: X352 | D22: PART 10 – HOSE & TUBE ASSEMBLIES | E22: (no description) | F22: FIGO | G22: 0 | H22: 28 | I22: -28 | J22: 28 pcs issued inside assemblies | K22: No change — assembly sold on challan, component issued in ledger.
A23: 10 | B23: Explained – issued inside SDN assemblies | C23: X164 | D23: PART 7 – COILS | E23: SWIFT NEW 2012 | G23: 0 | H23: 20 | I23: -20 | J23: 20 pcs issued inside assemblies | K23: No change — assembly sold on challan, component issued in ledger.
A24: 11 | B24: Explained – issued inside SDN assemblies | C24: X359 | D24: PART 10 – HOSE & TUBE ASSEMBLIES | E24: (no description) | F24: SWIFT NEW 2012 | G24: 0 | H24: 20 | I24: -20 | J24: 20 pcs issued inside assemblies | K24: No change — assembly sold on challan, component issued in ledger.
A25: 12 | B25: Explained – issued inside SDN assemblies | C25: X112 | D25: PART 7 – COILS | E25: SD-1005ND-MC | F25: MAGNETIC COIL SUBROS ND ESTEEM | G25: 0 | H25: 17 | I25: -17 | J25: 17 pcs issued inside assemblies | K25: No change — assembly sold on challan, component issued in ledger.
A26: 13 | B26: Explained – issued inside SDN assemblies | C26: X108 | D26: PART 7 – COILS | E26: SD-1003-MC QUALIS | F26: MAGNATTE COIL QUALIS | G26: 0 | H26: 10 | I26: -10 | J26: 10 pcs issued inside assemblies | K26: No change — assembly sold on challan, component issued in ledger.
A27: 14 | B27: Explained – issued inside SDN assemblies | C27: X144 | D27: PART 7 – COILS | E27: TEMPO TRAVELLER | F27: SD139MC/TT | G27: 5 | H27: 15 | I27: -10 | J27: 10 pcs issued inside assemblies | K27: No change — assembly sold on challan, component issued in ledger.
A28: 15 | B28: Explained – issued inside SDN assemblies | C28: X157 | D28: PART 7 – COILS | E28: POLO | G28: 0 | H28: 10 | I28: -10 | J28: 10 pcs issued inside assemblies | K28: No change — assembly sold on challan, component issued in ledger.
A29: 16 | B29: Explained – issued inside SDN assemblies | C29: X312 | D29: PART 10 – HOSE & TUBE ASSEMBLIES | E29: SD-1003-CP/QUALIS | F29: SD-1003-MC | G29: 0 | H29: 10 | I29: -10 | J29: 10 pcs issued inside assemblies | K29: No change — assembly sold on challan, component issued in ledger.
A30: 17 | B30: Explained – issued inside SDN assemblies | C30: X332 | D30: PART 10 – HOSE & TUBE ASSEMBLIES | E30: SD-231CP/HT3 | F30: HONDA T3 | G30: 0 | H30: 10 | I30: -10 | J30: 10 pcs issued inside assemblies | K30: No change — assembly sold on challan, component issued in ledger.
A31: 18 | B31: Explained – issued inside SDN assemblies | C31: X345 | D31: PART 10 – HOSE & TUBE ASSEMBLIES | E31: SD234CP/TT | F31: TEMPO TRAVELLER | G31: 0 | H31: 10 | I31: -10 | J31: 10 pcs issued inside assemblies | K31: No change — assembly sold on challan, component issued in ledger.
A32: 19 | B32: Explained – issued inside SDN assemblies | C32: X355 | D32: PART 10 – HOSE & TUBE ASSEMBLIES | E32: (no description) | F32: POLO | G32: 0 | H32: 10 | I32: -10 | J32: 10 pcs issued inside assemblies | K32: No change — assembly sold on challan, component issued in ledger.
A33: 20 | B33: Explained – issued inside SDN assemblies | C33: X168 | D33: PART 7 – COILS | E33: VISTA 5PK | F33: SD-156MC/VS.5PK | G33: 0 | H33: 9 | I33: -9 | J33: 9 pcs issued inside assemblies | K33: No change — assembly sold on challan, component issued in ledger.
A34: 21 | B34: Explained – issued inside SDN assemblies | C34: X113 | D34: PART 7 – COILS | E34: SD-1007SKD-MC | F34: MAGNETIC COIL SKODA | G34: 0 | H34: 8 | I34: -8 | J34: 8 pcs issued inside assemblies | K34: No change — assembly sold on challan, component issued in ledger.
A35: 22 | B35: Explained – issued inside SDN assemblies | C35: X134 | D35: PART 7 – COILS | E35: CIVIC | F35: SD-106/CIVIC | G35: 0 | H35: 6 | I35: -6 | J35: 6 pcs issued inside assemblies | K35: No change — assembly sold on challan, component issued in ledger.
A36: 23 | B36: Explained – issued inside SDN assemblies | C36: X339 | D36: PART 10 – HOSE & TUBE ASSEMBLIES | E36: SD-229CP/CIVIC | F36: HONDA CIVIC | G36: 0 | H36: 4 | I36: -4 | J36: 4 pcs issued inside assemblies | K36: No change — assembly sold on challan, component issued in ledger.
A37: 24 | B37: Explained – issued inside SDN assemblies | C37: X158 | D37: PART 7 – COILS | E37: ZEN ESTILO | G37: 0 | H37: 3 | I37: -3 | J37: 3 pcs issued inside assemblies | K37: No change — assembly sold on challan, component issued in ledger.
A38: 25 | B38: Explained – issued inside SDN assemblies | C38: X116 | D38: PART 7 – COILS | E38: SD-1010LNR-MMC-MC | F38: MAGNETIC COIL LANCER MMC | G38: 0 | H38: 2 | I38: -2 | J38: 2 pcs issued inside assemblies | K38: No change — assembly sold on challan, component issued in ledger.
A39: 26 | B39: Explained – issued inside SDN assemblies | C39: X142 | D39: PART 7 – COILS | E39: ENDEAVOUR | F39: SD-131MC/END | G39: 0 | H39: 2 | I39: -2 | J39: 2 pcs issued inside assemblies | K39: No change — assembly sold on challan, component issued in ledger.
A40: 27 | B40: Explained – issued inside SDN assemblies | C40: X319 | D40: PART 10 – HOSE & TUBE ASSEMBLIES | E40: SD-1010LNR -MMC-CP | F40: SD-1010LNR-MMC-MC | G40: 0 | H40: 2 | I40: -2 | J40: 2 pcs issued inside assemblies | K40: No change — assembly sold on challan, component issued in ledger.
A41: 28 | B41: Explained – issued inside SDN assemblies | C41: X329 | D41: PART 10 – HOSE & TUBE ASSEMBLIES | E41: (no description) | F41: FEISTA DSL | G41: 0 | H41: 2 | I41: -2 | J41: 2 pcs issued inside assemblies | K41: No change — assembly sold on challan, component issued in ledger.
A42: 29 | B42: Explained – issued inside SDN assemblies | C42: X343 | D42: PART 10 – HOSE & TUBE ASSEMBLIES | E42: SD-220CP/END | F42: ENDEAVOUR | G42: 0 | H42: 2 | I42: -2 | J42: 2 pcs issued inside assemblies | K42: No change — assembly sold on challan, component issued in ledger.
A43: 30 | B43: Explained – issued inside SDN assemblies | C43: X152 | D43: PART 7 – COILS | E43: I-20 PTL | G43: 0 | H43: 1 | I43: -1 | J43: 1 pcs issued inside assemblies | K43: No change — assembly sold on challan, component issued in ledger.
A44: 31 | B44: Explained – issued inside SDN assemblies | C44: X349 | D44: PART 10 – HOSE & TUBE ASSEMBLIES | E44: SD221CP/I20 PTL | F44: I-20 PTL | G44: 0 | H44: 1 | I44: -1 | J44: 1 pcs issued inside assemblies | K44: No change — assembly sold on challan, component issued in ledger.
A45: 32 | B45: Explained – ledger posting not backed by a live challan line | C45: P228 | D45: 23 | E45: VARNA (CRDI) | F45: PC-013 | G45: 0 | H45: 50 | I45: -50 | J45: no such line on: 2019-0117:50 | K45: Correct the ledger (wrong / cancelled / missing challan).
A46: 33 | B46: Explained – ledger posting not backed by a live challan line | C46: X361 | D46: PART 10 – HOSE & TUBE ASSEMBLIES | E46: SD248CP/CRZ | F46: CRUZE | G46: 0 | H46: 36 | I46: -36 | J46: 26 pcs issued inside assemblies; challan not in book: 2019-0271:10 | K46: Correct the ledger (wrong / cancelled / missing challan).
A47: 34 | B47: Explained – ledger posting not backed by a live challan line | C47: AE144 | D47: PART 8 – HOSE & TUBE ASSEMBLIES | E47: HYUNDAI GETZ DISCHARGE HOSE 2ND PART | F47: PC-255 | G47: 0 | H47: 34 | I47: -34 | J47: prior-year challans: 2017-464:20, 2017-489:3, 2017-618:5, 2017-643:6 | K47: Correct the ledger (wrong / cancelled / missing challan).
A48: 35 | B48: Explained – ledger posting not backed by a live challan line | C48: X141 | D48: PART 7 – COILS | E48: SWIFT PTL | F48: SD-124MC/ SWIFT-PTL | G48: 5 | H48: 38 | I48: -33 | J48: 23 pcs issued inside assemblies; no such line on: 2019-0152:10 | K48: Correct the ledger (wrong / cancelled / missing challan).
A49: 36 | B49: Explained – ledger posting not backed by a live challan line | C49: X337 | D49: PART 10 – HOSE & TUBE ASSEMBLIES | E49: SD-225CP/SWT PTL | F49: SWIFT PTL | G49: 0 | H49: 33 | I49: -33 | J49: 23 pcs issued inside assemblies; no such line on: 2019-0152:10 | K49: Correct the ledger (wrong / cancelled / missing challan).
A50: 37 | B50: Explained – ledger posting not backed by a live challan line | C50: AE145 | D50: PART 8 – HOSE & TUBE ASSEMBLIES | E50: HYUNDAI GETZ DISCHARGE 1ST PART | F50: PC-256 | G50: 0 | H50: 33 | I50: -33 | J50: prior-year challans: 2017-464:20, 2017-489:3, 2017-643:10 | K50: Correct the ledger (wrong / cancelled / missing challan).
A51: 38 | B51: Explained – ledger posting not backed by a live challan line | C51: AE22 | D51: PART 8 – HOSE & TUBE ASSEMBLIES | E51: MARUTI SX4 SUCTION HOSE | F51: PC-120 | G51: 0 | H51: 30 | I51: -30 | J51: prior-year challans: 2017-128:30 | K51: Correct the ledger (wrong / cancelled / missing challan).
A52: 39 | B52: Explained – ledger posting not backed by a live challan line | C52: AE35 | D52: PART 8 – HOSE & TUBE ASSEMBLIES | E52: MARUTI BALENO LIQUID TUBE | F52: PC-128 | G52: 0 | H52: 30 | I52: -30 | J52: prior-year challans: 2018-815:30 | K52: Correct the ledger (wrong / cancelled / missing challan).
A53: 40 | B53: Explained – ledger posting not backed by a live challan line | C53: AE264 | D53: PART 9 – HOSE & TUBE ASSEMBLIES | E53: SAFARI DICOR DISCHARGE HOSE NEW. | F53: PC-375C | G53: 0 | H53: 29 | I53: -29 | J53: prior-year challans: 2017-040:2, 2017-574:5, 2017-618:2, 2017-640:15 … | K53: Correct the ledger (wrong / cancelled / missing challan).
A54: 41 | B54: Explained – ledger posting not backed by a live challan line | C54: AE155 | D54: PART 8 – HOSE & TUBE ASSEMBLIES | E54: INNOVA LID TUBE | F54: PC-274 | G54: 0 | H54: 25 | I54: -25 | J54: prior-year challans: 2017-286:20, 2017-473:5 | K54: Correct the ledger (wrong / cancelled / missing challan).
A55: 42 | B55: Explained – ledger posting not backed by a live challan line | C55: AE200 | D55: PART 9 – HOSE & TUBE ASSEMBLIES | E55: SCORPIO LIQUD TUBE RD TO JOINT SMALL | F55: PC-316 | G55: 0 | H55: 18 | I55: -18 | J55: prior-year challans: 2017-040:3, 2017-473:10, 2017-574:5 | K55: Correct the ledger (wrong / cancelled / missing challan).
... A73: 60 | B73: Explained – ledger posting not backed by a live challan line | C73: AE294 | D73: PART 9 – HOSE & TUBE ASSEMBLIES | E73: INDICA SUBROS R134 SUCTION HOSE. | F73: PC-399 | G73: 0 | H73: 6 | I73: -6 | J73: prior-year challans: 2017-574:5, 2017-292:1 | K73: Correct the ledger (wrong / cancelled / missing challan).
A74: 61 | B74: Explained – ledger posting not backed by a live challan line | C74: P295 | D74: RESISTANCE | E74: METALOC | G74: 1 | H74: 6 | I74: -5 | J74: no such line on: 2019-0012:5 | K74: Correct the ledger (wrong / cancelled / missing challan).
A75: 62 | B75: Explained – ledger posting not backed by a live challan line | C75: AE7 | D75: PART 8 – HOSE & TUBE ASSEMBLIES | E75: MARUTI 800 LIQUID T'" RD TO COIL R12 | F75: PC-105 | G75: 0 | H75: 5 | I75: -5 | J75: prior-year challans: 2017-574:5 | K75: Correct the ledger (wrong / cancelled / missing challan).
A76: 63 | B76: Explained – ledger posting not backed by a live challan line | C76: AE13 | D76: PART 8 – HOSE & TUBE ASSEMBLIES | E76: MARUTI 800 LIQUID TUBE RD TO COND R134A (PAD & NUT) | F76: PC-111 | G76: 0 | H76: 5 | I76: -5 | J76: prior-year challans: 2017-574:5 | K76: Correct the ledger (wrong / cancelled / missing challan).
A77: 64 | B77: Explained – ledger posting not backed by a live challan line | C77: AE15 | D77: PART 8 – HOSE & TUBE ASSEMBLIES | E77: MARUTI 800 R134A LIQUID TUBE RD TO COIL HP | F77: PC-113 | G77: 0 | H77: 5 | I77: -5 | J77: prior-year challans: 2017-574:5 | K77: Correct the ledger (wrong / cancelled / missing challan).
A78: 65 | B78: Explained – ledger posting not backed by a live challan line | C78: AE39 | D78: PART 8 – HOSE & TUBE ASSEMBLIES | E78: MARUTI SWIFT LIQUID TUBE RD TO COIL | F78: PC-132 | G78: 0 | H78: 5 | I78: -5 | J78: prior-year challans: 2017-574:5 | K78: Correct the ledger (wrong / cancelled / missing challan).
A79: 66 | B79: Explained – ledger posting not backed by a live challan line | C79: AE69 | D79: PART 8 – HOSE & TUBE ASSEMBLIES | E79: MARUTI ESTEEM PTL R134A SUCTION HOSE LX | F79: PC-160 | G79: 0 | H79: 5 | I79: -5 | J79: prior-year challans: 2017-574:5 | K79: Correct the ledger (wrong / cancelled / missing challan).
A80: 67 | B80: Explained – ledger posting not backed by a live challan line | C80: AE72 | D80: PART 8 – HOSE & TUBE ASSEMBLIES | E80: MARUTI ESTEEM PTL 134A DISCHARE HOSE VX | F80: PC-163 | G80: 0 | H80: 5 | I80: -5 | J80: prior-year challans: 2017-504:5 | K80: Correct the ledger (wrong / cancelled / missing challan).
A81: 68 | B81: Explained – ledger posting not backed by a live challan line | C81: AE132 | D81: PART 8 – HOSE & TUBE ASSEMBLIES | E81: SANTRO LID TUBE | F81: PC-233 | G81: 0 | H81: 5 | I81: -5 | J81: prior-year challans: 2017-574:5 | K81: Correct the ledger (wrong / cancelled / missing challan).
A82: 69 | B82: Explained – ledger posting not backed by a live challan line | C82: AE153 | D82: PART 8 – HOSE & TUBE ASSEMBLIES | E82: TOYOTA INNOVA SUCTION HOSE | F82: PC-272 | G82: 0 | H82: 5 | I82: -5 | J82: prior-year challans: 2017-618:5 | K82: Correct the ledger (wrong / cancelled / missing challan).
A83: 70 | B83: Explained – ledger posting not backed by a live challan line | C83: AE202 | D83: PART 9 – HOSE & TUBE ASSEMBLIES | E83: SCORPIO LIQUID TUBE RD TO COND. SMALL | F83: PC-318 | G83: 0 | H83: 5 | I83: -5 | J83: prior-year challans: 2017-574:5 | K83: Correct the ledger (wrong / cancelled / missing challan).
A84: 71 | B84: Explained – ledger posting not backed by a live challan line | C84: AE88 | D84: PART 8 – HOSE & TUBE ASSEMBLIES | E84: MARUTI ZEN PTL R12 DISCHARGE HOSE | F84: PC-179 | G84: 0 | H84: 3 | I84: -3 | J84: prior-year challans: 2017-295:3 | K84: Correct the ledger (wrong / cancelled / missing challan).
A85: 72 | B85: Explained – ledger posting not backed by a live challan line | C85: AE117 | D85: PART 8 – HOSE & TUBE ASSEMBLIES | E85: MARUTI ZEN PTL SUBROS R134A DISCHARGE HOSE | F85: PC-208 | G85: 0 | H85: 3 | I85: -3 | J85: prior-year challans: 2017-295:3 | K85: Correct the ledger (wrong / cancelled / missing challan).
A86: 73 | B86: Explained – ledger posting not backed by a live challan line | C86: AE247 | D86: PART 9 – HOSE & TUBE ASSEMBLIES | E86: SAFARI LE DISCHARGE HOSE ANGLE CHANGE | F86: PC-362 | G86: 0 | H86: 3 | I86: -3 | J86: prior-year challans: 2017-040:2, 2017-618:1 | K86: Correct the ledger (wrong / cancelled / missing challan).
... A88: 75 | B88: Explained – ledger posting not backed by a live challan line | C88: AE280 | D88: PART 9 – HOSE & TUBE ASSEMBLIES | E88: INDICA BHR OLD LIQUID TUBE JOINT TO COIL | F88: PC-386 | G88: 0 | H88: 2 | I88: -2 | J88: prior-year challans: 2017-040:2 | K88: Correct the ledger (wrong / cancelled / missing challan).
A89: 76 | B89: Recon Challan short – challan lines exist | C89: X149 | D89: PART 7 – COILS | E89: SWIFT DSL | G89: 0 | H89: 329 | I89: -329 | J89: 204 pcs issued inside assemblies; lines found: 2019-0022:30 'SWIFT (DSL) | SD-123MC/SWIFT (DSL)'; 2019-0090:30 'SWIFT (DSL) | SD-123MC/SWIFT (DSL)'; 2019-0116:30 'SWIFT (DSL) | SD-123MC/SWIFT (DSL)'; 2019-0272:5 'SWIFT (NEW) | PC-86539' | K89: Review the listed challan lines; add to Challan if they belong to this part.
A90: 77 | B90: Recon Challan short – challan lines exist | C90: X373 | D90: PART 10 – HOSE & TUBE ASSEMBLIES | E90: 30BD40DU | F90: FORD IKON/TRAVERA/ACCENT | G90: 0 | H90: 282 | I90: -282 | J90: lines found: 2019-0022:100 'FORD IKON/TRAVERA / SCORPIO | 30BD40DU 305523'; 2019-0023:20 'FORD IKON/TRAVERA / SCORPIO | 30BD40DU 305523'; 2019-0052:100 'FORD IKON/TRAVERA / SCORPIO | 30BD40DU 305523'; 2019-0097:27 'TRAVERA | 30BD40DU 305523' | K90: Review the listed challan lines; add to Challan if they belong to this part.
A91: 78 | B91: Recon Challan short – challan lines exist | C91: X356 | D91: PART 10 – HOSE & TUBE ASSEMBLIES | E91: SD208CP/WR | F91: WR/INNOVA SIGNLE | G91: 0 | H91: 258 | I91: -258 | J91: 162 pcs issued inside assemblies; no such line on: 2019-0072:10, 2019-0167:20; lines found: 2019-0133:4 'WAGON-R / INNOVA SMALL | SD-1008WR-MC /WR, SD'; 2019-0141:5 'INNOVA SINGLE A/C | SD-125MC/WR // SD142'; 2019-0026:10 'WAGON R / ALTO-SUBROS | PCP-E10208'; 2019-0090:10 'WAGON R / ALTO-SUBROS | PCP-E10208' | K91: Review the listed challan lines; add to Challan if they belong to this part.
A92: 79 | B92: Recon Challan short – challan lines exist | C92: X139 | D92: PART 7 – COILS | E92: A-STAR | F92: SD-136MC/A-STAR | G92: 65 | H92: 305 | I92: -240 | J92: 120 pcs issued inside assemblies; no such line on: 2019-0068:5, 2019-0089:10, 2019-0113:10, 2019-0166:10; lines found: 2019-0022:30 'A-STAR | SD-136MC/A-STAR'; 2019-0151:3 'WAGON-R (K-10) | SD-136MC/A-STAR SD-1'; 2019-0223:30 'WAGON-R (K-10) | SD-136MC/A-STAR'; 2019-0085:11 'A-STAR | SD-136MC/A-STAR' | K92: Review the listed challan lines; add to Challan if they belong to this part.
A93: 80 | B93: Recon Challan short – challan lines exist | C93: X333 | D93: PART 10 – HOSE & TUBE ASSEMBLIES | E93: SD-226CP/A-STAR | F93: A-STAR | G93: 0 | H93: 220 | I93: -220 | J93: 110 pcs issued inside assemblies; no such line on: 2019-0068:5, 2019-0085:6, 2019-0089:10, 2019-0090:20; lines found: 2019-0103:10 'ND-Subros | PC-7031A PC-7226'; 2019-0151:3 'ETIOS (DSL) | SD-226CP/A-STAR, SD2' | K93: Review the listed challan lines; add to Challan if they belong to this part.
A94: 81 | B94: Recon Challan short – challan lines exist | C94: P34 | D94: Drier | E94: ADOPTER ORING 5/16 TO 3/8 FLARE | G94: 0 | H94: 170 | I94: -170 | J94: no such line on: 2019-0309:50; lines found: 2019-0109:50 'Universal-F 5/16" WITH ADOPTER | PC-6002'; 2019-0167:20 'ADOPTER 6002 | '; 2019-0227:50 'Universal-O 5/16" WITH FLARE C | PC-6002' | K94: Review the listed challan lines; add to Challan if they belong to this part.
A95: 82 | B95: Recon Challan short – challan lines exist | C95: X146 | D95: PART 7 – COILS | E95: SANTRO XING-some qty of xing pkd with i-20ptl sticker | F95: SD121MC/ XING | G95: 155 | H95: 316 | I95: -161 | J95: 156 pcs issued inside assemblies; lines found: 2019-0022:30 'SANTRO XING-NEW | SD-121MC/SANTRO (NEW'; 2019-0026:30 'SANTRO XING-NEW | SD-121MC/SANTRO (NEW'; 2019-0090:30 'SANTRO XING-NEW | SD-121MC/SANTRO (NEW'; 2019-0141:5 'SANTRO XING-NEW | SD-121MC/SANTRO (NEW' | K95: Review the listed challan lines; add to Challan if they belong to this part.
A96: 83 | B96: Recon Challan short – challan lines exist | C96: X159 | D96: PART 7 – COILS | E96: INNOVA DUAL | F96: SD-101MC/INNOVA DUAL | G96: 185 | H96: 330 | I96: -145 | J96: 135 pcs issued inside assemblies; lines found: 2019-0020:30 'INNOVA DUAL | SD-101MC/INNOVA DUAL'; 2019-0022:30 'INNOVA DUAL | SD-101MC/INNOVA DUAL'; 2019-0141:5 'INNOVA DUAL | SD-101MC/INNOVA DUAL'; 2019-0223:30 'INNOVA DUAL | SD-101MC/INNOVA DUAL' | K96: Review the listed challan lines; add to Challan if they belong to this part.
A97: 84 | B97: Recon Challan short – challan lines exist | C97: X350 | D97: PART 10 – HOSE & TUBE ASSEMBLIES | E97: SD238CP/ETOS-DSL | F97: ETIOS DSL | G97: 0 | H97: 141 | I97: -141 | J97: 104 pcs issued inside assemblies; prior-year challans: 2018-0183:20; lines found: 2019-0133:5 'ETIOS (DSL) | SD-226CP/A-STAR, SD-'; 2019-0151:2 'ETIOS (DSL) | SD-226CP/A-STAR, SD2'; 2019-0243:5 'ETIOS (DSL) | SD143MC/ETOS DSL'; 2019-0270:5 'ETIOS (DSL) | SD143MC/ETOS DSL' | K97: Review the listed challan lines; add to Challan if they belong to this part.
A98: 85 | B98: Recon Challan short – challan lines exist | C98: P52 | D98: COMPRESSOR | E98: 507-MG | G98: 0 | H98: 115 | I98: -115 | J98: lines found: 2019-0086:2 '507 IN MULTIGROOVE | 5H11-507MG'; 2019-0154:12 '507 IN MULTIGROOVE | 5H11-507MG'; 2019-0243:1 '507 IN MULTIGROOVE | 5H11-507MG'; 2019-0274:4 '507 IN MULTIGROOVE | 5H11-507MG' | K98: Review the listed challan lines; add to Challan if they belong to this part.
A99: 86 | B99: Recon Challan short – challan lines exist | C99: X313 | D99: PART 10 – HOSE & TUBE ASSEMBLIES | E99: SD-1004-CP (OLD)-XING | F99: SD-1004-MC(OLD) | G99: 1 | H99: 108 | I99: -107 | J99: 81 pcs issued inside assemblies; lines found: 2019-0133:2 'SANTRO XING | SD-1004-MC (DELPHI) '; 2019-0362:10 'ENJOY-REAR | PC-R004'; 2019-0276:5 'SANTRO XING (BLOCK TYPE) | FK-C906'; 2019-0348:10 'ETIOS-MMF TECH | PCP-E10004' | K99: Review the listed challan lines; add to Challan if they belong to this part.
A100: 87 | B100: Recon Challan short – challan lines exist | C100: X143 | D100: PART 7 – COILS | E100: MHAWK | F100: SD-138MC/MHWK | G100: 0 | H100: 86 | I100: -86 | J100: 84 pcs issued inside assemblies; lines found: 2019-0151:2 'M-HWAK | SD-1002-MC // SDN- 1' | K100: Review the listed challan lines; add to Challan if they belong to this part.
A101: 88 | B101: Recon Challan short – challan lines exist | C101: X338 | D101: PART 10 – HOSE & TUBE ASSEMBLIES | E101: SD-227CP/SWT DSL | F101: SWIFT DSL | G101: 0 | H101: 77 | I101: -77 | J101: 72 pcs issued inside assemblies; lines found: 2019-0151:5 'SWIFT DSL | SD-227CP/SWT-DSL' | K101: Review the listed challan lines; add to Challan if they belong to this part.
A102: 89 | B102: Recon Challan short – challan lines exist | C102: X328 | D102: PART 10 – HOSE & TUBE ASSEMBLIES | E102: SD-216CP/SCR-sanden | F102: SCORPIO SANDEN | G102: 0 | H102: 71 | I102: -71 | J102: 10 pcs issued inside assemblies; lines found: 2019-0061:60 'SCORPIO (SANDEN) | SD-216CP/SCR-SANDEN'; 2019-0151:1 'SCORPIO (SANDEN) | SD-216CP/SCR-SANDEN' | K102: Review the listed challan lines; add to Challan if they belong to this part.
A103: 90 | B103: Recon Challan short – challan lines exist | C103: X130 | D103: PART 7 – COILS | E103: VISTA BEHR 6PK Q.JET | F103: SD129MC/QJET6PK | G103: 30 | H103: 100 | I103: -70 | J103: lines found: 2019-0022:30 'VISTA-BEHR Q.JET 6PK | SD-129MC/V.Q.JET6PK'; 2019-0057:10 'VISTA-BEHR Q.JET 6PK | SDN-025/VISTA Q.JET '; 2019-0066:10 'VISTA-BEHR Q.JET 6PK | SDN-025/VISTA Q.JET '; 2019-0072:10 'INDICA VISTA SUBROS 7PK Q.JET | SDN040/I.V.7PK Q.JET' | K103: Review the listed challan lines; add to Challan if they belong to this part.
A104: 91 | B104: Recon Challan short – challan lines exist | C104: X327 | D104: PART 10 – HOSE & TUBE ASSEMBLIES | E104: (no description) | F104: VISTA BEHR 6PK Q.JET | G104: 0 | H104: 70 | I104: -70 | J104: lines found: 2019-0057:10 'VISTA-BEHR Q.JET 6PK | SDN-025/VISTA Q.JET '; 2019-0066:10 'VISTA-BEHR Q.JET 6PK | SDN-025/VISTA Q.JET '; 2019-0072:10 'INDICA VISTA SUBROS 7PK Q.JET | SDN040/I.V.7PK Q.JET'; 2019-0085:3 'INDICA VISTA SUBROS 7PK Q.JET | SDN040/I.V.7PK Q.JET' | K104: Review the listed challan lines; add to Challan if they belong to this part.
A105: 92 | B105: Recon Challan short – challan lines exist | C105: X344 | D105: PART 10 – HOSE & TUBE ASSEMBLIES | E105: SD-233CP/MHWK | F105: MHAWK | G105: 0 | H105: 67 | I105: -67 | J105: 64 pcs issued inside assemblies; lines found: 2019-0133:2 'M-HWAK | SD-233CP/MHWK / SD-2'; 2019-0151:1 'M-HWAK | SD-233CP/MHWK' | K105: Review the listed challan lines; add to Challan if they belong to this part.
A106: 93 | B106: Recon Challan short – challan lines exist | C106: X140 | D106: PART 7 – COILS | E106: I-10 KAPPA | F106: SD-132MC/I20PTL | G106: 0 | H106: 64 | I106: -64 | J106: 47 pcs issued inside assemblies; posted on cancelled challans: 2019-0260:15; lines found: 2019-0151:2 'I-10 KAPPA | SD-1004-MC(OLD) // S' | K106: Review the listed challan lines; add to Challan if they belong to this part.
A107: 94 | B107: Recon Challan short – challan lines exist | C107: X330 | D107: PART 10 – HOSE & TUBE ASSEMBLIES | E107: SD-206CP/SCR-B | F107: SCORPIO HCC-B | G107: 0 | H107: 58 | I107: -58 | J107: 43 pcs issued inside assemblies; no such line on: 2019-0084:10; lines found: 2019-0177:5 'ACCENT HUB / TRAVERA | SD-1011ACRDI-MC // S' | K107: Review the listed challan lines; add to Challan if they belong to this part.
A108: 95 | B108: Recon Challan short – challan lines exist | C108: X348 | D108: PART 10 – HOSE & TUBE ASSEMBLIES | E108: SD237CP/XYLO-D2 | F108: XYLO D2-small | G108: 0 | H108: 58 | I108: -58 | J108: 26 pcs issued inside assemblies; no such line on: 2019-0148:2; lines found: 2019-0043:30 'XYLO D2 | SD208CP' | K108: Review the listed challan lines; add to Challan if they belong to this part.
A109: 96 | B109: Recon Challan short – challan lines exist | C109: P40 | D109: Drier | E109: Desiccant Drier/Filter | F109: PC-20242 | G109: 190 | H109: 240 | I109: -50 | J109: lines found: 2019-0062:100 'Desiccant Drier/Filter (Medium | PC-20242'; 2019-0090:50 'Desiccant Drier/Filter (Large) | PC-20243'; 2019-0180:20 'Desiccant Drier/Filter (Medium | PC-20242'; 2019-0276:10 'Desiccant Drier/Filter (Medium | PC-20242' | K109: Review the listed challan lines; add to Challan if they belong to this part.
A110: 97 | B110: Recon Challan short – challan lines exist | C110: X335 | D110: PART 10 – HOSE & TUBE ASSEMBLIES | E110: SD-221CP/I20PTL | F110: I-10 KAPPA | G110: 0 | H110: 46 | I110: -46 | J110: 44 pcs issued inside assemblies; lines found: 2019-0151:2 'I-10 KAPPA | SD-219CP/I-10-KAPPA' | K110: Review the listed challan lines; add to Challan if they belong to this part.
A111: 98 | B111: Recon Challan short – challan lines exist | C111: X151 | D111: PART 7 – COILS | E111: XYLO D2 (small) | F111: SD142MC/XYLO D2 | G111: 0 | H111: 43 | I111: -43 | J111: 26 pcs issued inside assemblies; no such line on: 2019-0090:10, 2019-0148:2; lines found: 2019-0243:5 'XYLO SUBROS 3680 -BIG | PC-86449' | K111: Review the listed challan lines; add to Challan if they belong to this part.
A112: 99 | B112: Recon Challan short – challan lines exist | C112: P129 | D112: COMPRESSOR OIL | E112: COMPRESSOR OIL 20LTR | G112: 2 | H112: 40 | I112: -38 | J112: lines found: 2019-0482:40 'COMPRESSOR OIL-20tr | UNICLA' | K112: Review the listed challan lines; add to Challan if they belong to this part.
A113: 100 | B113: Recon Challan short – challan lines exist | C113: X169 | D113: PART 7 – COILS | E113: CRUZE | F113: SD157MC/CRZ | G113: 0 | H113: 36 | I113: -36 | J113: 16 pcs issued inside assemblies; challan not in book: 2019-0271:10; lines found: 2019-0090:10 'SCORPIO | PC-7157' | K113: Review the listed challan lines; add to Challan if they belong to this part.
A114: 101 | B114: Recon Challan short – challan lines exist | C114: X360 | D114: PART 10 – HOSE & TUBE ASSEMBLIES | E114: (no description) | F114: XUV 500 | G114: 0 | H114: 35 | I114: -35 | J114: 30 pcs issued inside assemblies; lines found: 2019-0177:5 'XUV 500 | SD247CP/MX5' | K114: Review the listed challan lines; add to Challan if they belong to this part.
A115: 102 | B115: Recon Challan short – challan lines exist | C115: X351 | D115: PART 10 – HOSE & TUBE ASSEMBLIES | E115: (no description) | F115: IND.MMC | G115: 0 | H115: 34 | I115: -34 | J115: 2 pcs issued inside assemblies; lines found: 2019-0061:30 'INDICA MMC (MITSUBISHI) | SD239CP/IND.MMC'; 2019-0068:2 'INDICA MMC (MITSUBISHI) | SD144MC/IND.MMC' | K115: Review the listed challan lines; add to Challan if they belong to this part.
A116: 103 | B116: Recon Challan short – challan lines exist | C116: P84 | D116: MOTOR | E116: SK MOTOR-12V | F116: TD-7800 | G116: 0 | H116: 30 | I116: -30 | J116: lines found: 2019-0314:10 'SUPERKING-12V | SK 12V'; 2019-0473:20 'SUPERKING-12V | SK 12V' | K116: Review the listed challan lines; add to Challan if they belong to this part.
A117: 104 | B117: Recon Challan short – challan lines exist | C117: P297 | D117: FAN | E117: 10"X10 (St.) | F117: TST-8801 | G117: 0 | H117: 30 | I117: -30 | J117: lines found: 2019-0379:30 '10"X6 B- ('S' Type Blade) | TS-8805' | K117: Review the listed challan lines; add to Challan if they belong to this part.
A118: 105 | B118: Recon Challan short – challan lines exist | C118: X346 | D118: PART 10 – HOSE & TUBE ASSEMBLIES | E118: SD235CP/XYLO-B | F118: XYLO BIG | G118: 0 | H118: 25 | I118: -25 | J118: 23 pcs issued inside assemblies; lines found: 2019-0133:2 'XYLO BIG | SD235CP/XYLO-B' | K118: Review the listed challan lines; add to Challan if they belong to this part.
A119: 106 | B119: Recon Challan short – challan lines exist | C119: X325 | D119: PART 10 – HOSE & TUBE ASSEMBLIES | E119: SDN-214B/CP | F119: VISTA SUBROS | G119: 0 | H119: 24 | I119: -24 | J119: lines found: 2019-0029:2 'VISTA-SUBROS-5PK | SDN-007/I.V.SUBROS'; 2019-0085:4 'VISTA-SUBROS-5PK | SDN-007/I.V.SUBROS'; 2019-0243:5 'VISTA-SUBROS-5PK | SDN-007/I.V.SUBROS'; 2019-0339:3 'VISTA-SUBROS-5PK | SDN-007/I.V.SUBROS' | K119: Review the listed challan lines; add to Challan if they belong to this part.
A120: 107 | B120: Recon Challan short – challan lines exist | C120: X357 | D120: PART 10 – HOSE & TUBE ASSEMBLIES | E120: (no description) | F120: ALTO 800 | G120: 0 | H120: 24 | I120: -24 | J120: 21 pcs issued inside assemblies; lines found: 2019-0133:3 'ALTO 800 | SD150MC/ALTO 800' | K120: Review the listed challan lines; add to Challan if they belong to this part.
A121: 108 | B121: Recon Challan short – challan lines exist | C121: P53 | D121: COMPRESSOR | E121: 508 | G121: 0 | H121: 22 | I121: -22 | J121: lines found: 2019-0029:4 '508-V GROVE PULLEY | 5H14'; 2019-0134:4 '508-V GROVE PULLEY | 5H14'; 2019-0205:8 '508-V GROVE PULLEY | 5H14'; 2019-0246:4 '508-V GROVE PULLEY | 5H14' | K121: Review the listed challan lines; add to Challan if they belong to this part.
...

Sheet Recon
A1: Group | B1: Item | C1: Part Code | D1: Challan | E1: Stock | F1: Gap | G1: Total Available | K1: Group | L1: Item | M1: Part Code | N1: Challan | O1: Stock | P1: Gap | Q1: Total Available | S1: Group | T1: Item | U1: Part Code | V1: Challan | W1: Stock | X1: Gap | Y1: Total Available | Z1: Group | AA1: Item | AB1: Part Code | AC1: Challan | AD1: Stock | AE1: Gap | AF1: Total Available
A2: PART 1 – CONDENSERS | B2: ACCENT CRD-I | C2: PC-86064B | D2: 22 | E2: {=IF($B2="","",IF(TRIM(INDEX('Part 1'!$L$2:$IV$2,1,ROW()-1))=TRIM($B2),INDEX('Part 1'!$L$1250:$IV$1250,1,ROW()-1),"CHECK"))} -> 22 | F2: =IFERROR(D2-E2,"") -> 0 | G2: ='Part 1'!L30 -> 95 | K2: Drier | L2: Ambasdor /Bolero | M2: PC-8120 | N2: 0 | O2: =IF($L2="","",IF(TRIM(INDEX('Part 4'!$E$2:$AY$2,1,ROW()-1))=TRIM($L2),INDEX('Part 4'!$E$778:$AY$778,1,ROW()-1),"CHECK")) -> 0 | P2: =IFERROR(N2-O2,"") -> 0 | Q2: ='Part 4'!E20 -> 280 | T2: PULLEY | X2: =IFERROR(V2-W2,"") -> 0 | Z2: PART 8 – HOSE & TUBE ASSEMBLIES | AA2: MARUTI 800 R12 DISCHARGE HOSE | AB2: PC-101 | AC2: 0 | AD2: =IF($AB2="","",IF(TRIM(INDEX('Part 8'!$F$2:$IV$2,1,ROW()-1))=TRIM($AB2),INDEX('Part 8'!$F$244:$IV$244,1,ROW()-1),"CHECK")) -> 0 | AE2: =IFERROR(AC2-AD2,"") -> 0 | AF2: ='Part 8'!F9 -> 0
B3: ACCENT-PETROL | C3: PC-86248 | D3: 0 | E3: {=IF($B3="","",IF(TRIM(INDEX('Part 1'!$L$2:$IV$2,1,ROW()-1))=TRIM($B3),INDEX('Part 1'!$L$1250:$IV$1250,1,ROW()-1),"CHECK"))} -> 0 | F3: =IFERROR(D3-E3,"") -> 0 | G3: ='Part 1'!M30 -> 120 | L3: Ambasdor /Bolero-corrected | M3: PC-8120 | N3: 50 | O3: =IF($L3="","",IF(TRIM(INDEX('Part 4'!$E$2:$AY$2,1,ROW()-1))=TRIM($L3),INDEX('Part 4'!$E$778:$AY$778,1,ROW()-1),"CHECK")) -> 50 | P3: =IFERROR(N3-O3,"") -> 0 | Q3: ='Part 4'!F20 -> 95 | S3: PART 7 – PULLEYS | T3: QUALIS | U3: SD-1003-MC/SD-304PL/QUALIS | V3: 12 | W3: =IFERROR('Part 7'!EI690+0,0) -> 10 | X3: =IFERROR(V3-W3,"") -> 2 | Y3: ='Part 7'!EI18 -> 312 | AA3: MARUTI 800 SUCTION HOSE R12 | AB3: PC-102 | AC3: 0 | AD3: =IF($AB3="","",IF(TRIM(INDEX('Part 8'!$F$2:$IV$2,1,ROW()-1))=TRIM($AB3),INDEX('Part 8'!$F$244:$IV$244,1,ROW()-1),"CHECK")) -> 0 | AE3: =IFERROR(AC3-AD3,"") -> 0 | AF3: ='Part 8'!G9 -> 0
B4: ALTIS | C4: PC-86032 | D4: 4 | E4: {=IF($B4="","",IF(TRIM(INDEX('Part 1'!$L$2:$IV$2,1,ROW()-1))=TRIM($B4),INDEX('Part 1'!$L$1250:$IV$1250,1,ROW()-1),"CHECK"))} -> 9 | F4: =IFERROR(D4-E4,"") -> -5 | G4: ='Part 1'!N30 -> -6 | L4: Aveo | M4: PC-8797 | N4: 0 | O4: =IF($L4="","",IF(TRIM(INDEX('Part 4'!$E$2:$AY$2,1,ROW()-1))=TRIM($L4),INDEX('Part 4'!$E$778:$AY$778,1,ROW()-1),"CHECK")) -> 0 | P4: =IFERROR(N4-O4,"") -> 0 | Q4: ='Part 4'!G20 -> 348 | T4: SD-1004-MC(OLD) | U4: SD-1004-PL (OLD) | V4: 0 | W4: =IFERROR('Part 7'!EJ690+0,0) -> 0 | X4: =IFERROR(V4-W4,"") -> 0 | Y4: ='Part 7'!EJ18 -> 94 | AA4: MARUTI 800 SUCTION HOSE R12 N/TYPE | AB4: PC-103 | AC4: 0 | AD4: =IF($AB4="","",IF(TRIM(INDEX('Part 8'!$F$2:$IV$2,1,ROW()-1))=TRIM($AB4),INDEX('Part 8'!$F$244:$IV$244,1,ROW()-1),"CHECK")) -> 0 | AE4: =IFERROR(AC4-AD4,"") -> 0 | AF4: ='Part 8'!H9 -> 0
B5: ALTIS-CORRECTED | C5: PC-86083 | D5: 29 | E5: {=IF($B5="","",IF(TRIM(INDEX('Part 1'!$L$2:$IV$2,1,ROW()-1))=TRIM($B5),INDEX('Part 1'!$L$1250:$IV$1250,1,ROW()-1),"CHECK"))} -> 23 | F5: =IFERROR(D5-E5,"") -> 6 | G5: ='Part 1'!O30 -> 57 | L5: Daewoo Cielo | M5: PC-8263 | N5: 0 | O5: =IF($L5="","",IF(TRIM(INDEX('Part 4'!$E$2:$AY$2,1,ROW()-1))=TRIM($L5),INDEX('Part 4'!$E$778:$AY$778,1,ROW()-1),"CHECK")) -> 0 | P5: =IFERROR(N5-O5,"") -> 0 | Q5: ='Part 4'!H20 -> 40 | T5: SD-1004-MC (NEW) | U5: SD-1004-PL (NEW) | V5: 0 | W5: =IFERROR('Part 7'!EK690+0,0) -> 10 | X5: =IFERROR(V5-W5,"") -> -10 | Y5: ='Part 7'!EK18 -> -176 | AA5: MARUTI 800 LIQUID TUBE RD TO COND R12 | AB5: PC-104 | AC5: 0 | AD5: =IF($AB5="","",IF(TRIM(INDEX('Part 8'!$F$2:$IV$2,1,ROW()-1))=TRIM($AB5),INDEX('Part 8'!$F$244:$IV$244,1,ROW()-1),"CHECK")) -> 0 | AE5: =IFERROR(AC5-AD5,"") -> 0 | AF5: ='Part 8'!I9 -> 0
B6: ALTIS-Q5 | C6: PC-86083-Q5 | D6: 39 | E6: {=IF($B6="","",IF(TRIM(INDEX('Part 1'!$L$2:$IV$2,1,ROW()-1))=TRIM($B6),INDEX('Part 1'!$L$1250:$IV$1250,1,ROW()-1),"CHECK"))} -> 17 | F6: =IFERROR(D6-E6,"") -> 22 | G6: ='Part 1'!P30 -> 172 | L6: Desiccant Drier/Filter | M6: PC-20241 | N6: 1040 | O6: =IF($L6="","",IF(TRIM(INDEX('Part 4'!$E$2:$AY$2,1,ROW()-1))=TRIM($L6),INDEX('Part 4'!$E$778:$AY$778,1,ROW()-1),"CHECK")) -> 990 | P6: =IFERROR(N6-O6,"") -> 50 | Q6: ='Part 4'!I20 -> 17032 | T6: SD-1004-MC (DELPHI) | U6: SD-1004-PL (DELPHI) | V6: 0 | W6: =IFERROR('Part 7'!EL690+0,0) -> 0 | X6: =IFERROR(V6-W6,"") -> 0 | Y6: ='Part 7'!EL18 -> 0 | AA6: MARUTI 800 ALU. LIQ TUBE 27" WITHOUT VALVE | AB6: PC-104A | AC6: 0 | AD6: =IF($AB6="","",IF(TRIM(INDEX('Part 8'!$F$2:$IV$2,1,ROW()-1))=TRIM($AB6),INDEX('Part 8'!$F$244:$IV$244,1,ROW()-1),"CHECK")) -> 0 | AE6: =IFERROR(AC6-AD6,"") -> 0 | AF6: ='Part 8'!J9 -> 0
B7: ALTO 800 NEW | C7: PC-86634 | D7: 11 | E7: {=IF($B7="","",IF(TRIM(INDEX('Part 1'!$L$2:$IV$2,1,ROW()-1))=TRIM($B7),INDEX('Part 1'!$L$1250:$IV$1250,1,ROW()-1),"CHECK"))} -> 8 | F7: =IFERROR(D7-E7,"") -> 3 | G7: ='Part 1'!Q30 -> 218 | L7: Esteem-R12 | M7: PC-8005 | N7: 144 | O7: =IF($L7="","",IF(TRIM(INDEX('Part 4'!$E$2:$AY$2,1,ROW()-1))=TRIM($L7),INDEX('Part 4'!$E$778:$AY$778,1,ROW()-1),"CHECK")) -> 115 | P7: =IFERROR(N7-O7,"") -> 29 | Q7: ='Part 4'!J20 -> 201 | T7: XING | U7: SD-1004E | V7: 121 | W7: =IFERROR('Part 7'!EM690+0,0) -> 108 | X7: =IFERROR(V7-W7,"") -> 13 | Y7: ='Part 7'!EM18 -> 654 | AA7: MARUTI 800 LIQUID T'" RD TO COIL R12 | AB7: PC-105 | AC7: 0 | AD7: =IF($AB7="","",IF(TRIM(INDEX('Part 8'!$F$2:$IV$2,1,ROW()-1))=TRIM($AB7),INDEX('Part 8'!$F$244:$IV$244,1,ROW()-1),"CHECK")) -> 5 | AE7: =IFERROR(AC7-AD7,"") -> -5 | AF7: ='Part 8'!K9 -> 0
B8: AMBASDOR | C8: PC-86041 | D8: 7 | E8: {=IF($B8="","",IF(TRIM(INDEX('Part 1'!$L$2:$IV$2,1,ROW()-1))=TRIM($B8),INDEX('Part 1'!$L$1250:$IV$1250,1,ROW()-1),"CHECK"))} -> 7 | F8: =IFERROR(D8-E8,"") -> 0 | G8: ='Part 1'!R30 -> 63 | L8: Esteem-R134A | M8: PC-8006 | N8: 635 | O8: =IF($L8="","",IF(TRIM(INDEX('Part 4'!$E$2:$AY$2,1,ROW()-1))=TRIM($L8),INDEX('Part 4'!$E$778:$AY$778,1,ROW()-1),"CHECK")) -> 400 | P8: =IFERROR(N8-O8,"") -> 235 | Q8: ='Part 4'!K20 -> 844 | T8: SD-1005ND-MC | U8: SD-1005ND-PL | V8: 19 | W8: =IFERROR('Part 7'!EN690+0,0) -> 17 | X8: =IFERROR(V8-W8,"") -> 2 | Y8: ='Part 7'!EN18 -> 740 | AA8: MARUTI 800 R12 COOLING COIL TUBE LIQUID | AB8: PC-106 | AC8: 0 | AD8: =IF($AB8="","",IF(TRIM(INDEX('Part 8'!$F$2:$IV$2,1,ROW()-1))=TRIM($AB8),INDEX('Part 8'!$F$244:$IV$244,1,ROW()-1),"CHECK")) -> 0 | AE8: =IFERROR(AC8-AD8,"") -> 0 | AF8: ='Part 8'!L9 -> 0
B9: A-STAR | C9: PC-86274 | D9: 3 | E9: {=IF($B9="","",IF(TRIM(INDEX('Part 1'!$L$2:$IV$2,1,ROW()-1))=TRIM($B9),INDEX('Part 1'!$L$1250:$IV$1250,1,ROW()-1),"CHECK"))} -> 6 | F9: =IFERROR(D9-E9,"") -> -3 | G9: ='Part 1'!S30 -> 108 | L9: Ford | M9: PC-8321 | N9: 0 | O9: =IF($L9="","",IF(TRIM(INDEX('Part 4'!$E$2:$AY$2,1,ROW()-1))=TRIM($L9),INDEX('Part 4'!$E$778:$AY$778,1,ROW()-1),"CHECK")) -> 0 | P9: =IFERROR(N9-O9,"") -> 0 | Q9: ='Part 4'!L20 -> 51 | T9: SD-1007SKD-MC | U9: SD-1007SKD-PL | V9: 14 | W9: =IFERROR('Part 7'!EO690+0,0) -> 13 | X9: =IFERROR(V9-W9,"") -> 1 | Y9: ='Part 7'!EO18 -> 316 | AA9: MARUTI 800 R12 SUCTION TUBE COOLING COIL | AB9: PC-107 | AC9: 0 | AD9: =IF($AB9="","",IF(TRIM(INDEX('Part 8'!$F$2:$IV$2,1,ROW()-1))=TRIM($AB9),INDEX('Part 8'!$F$244:$IV$244,1,ROW()-1),"CHECK")) -> 0 | AE9: =IFERROR(AC9-AD9,"") -> 0 | AF9: ='Part 8'!M9 -> 0
B10: AUDI A3 | C10: PCP-C86283Q5 | D10: 14 | E10: {=IF($B10="","",IF(TRIM(INDEX('Part 1'!$L$2:$IV$2,1,ROW()-1))=TRIM($B10),INDEX('Part 1'!$L$1250:$IV$1250,1,ROW()-1),"CHECK"))} -> 14 | F10: =IFERROR(D10-E10,"") -> 0 | G10: ='Part 1'!T30 -> 96 | L10: Honda City | M10: PC-8020 | N10: 48 | O10: =IF($L10="","",IF(TRIM(INDEX('Part 4'!$E$2:$AY$2,1,ROW()-1))=TRIM($L10),INDEX('Part 4'!$E$778:$AY$778,1,ROW()-1),"CHECK")) -> 38 | P10: =IFERROR(N10-O10,"") -> 10 | Q10: ='Part 4'!M20 -> 1299 | T10: SD-1008WR-MC | U10: SD-1008WR-PL // SD-303PL/WR | V10: 238 | W10: =IFERROR('Part 7'!EP690+0,0) -> 226 | X10: =IFERROR(V10-W10,"") -> 12 | Y10: ='Part 7'!EP18 -> 404 | AA10: MARUTI 800 R134A DISCHARGE HOSE | AB10: PC-108 | AC10: 0 | AD10: =IF($AB10="","",IF(TRIM(INDEX('Part 8'!$F$2:$IV$2,1,ROW()-1))=TRIM($AB10),INDEX('Part 8'!$F$244:$IV$244,1,ROW()-1),"CHECK")) -> 0 | AE10: =IFERROR(AC10-AD10,"") -> 0 | AF10: ='Part 8'!N9 -> 0
B11: AUDI A4 | C11: PCP-C86001 | D11: 0 | E11: {=IF($B11="","",IF(TRIM(INDEX('Part 1'!$L$2:$IV$2,1,ROW()-1))=TRIM($B11),INDEX('Part 1'!$L$1250:$IV$1250,1,ROW()-1),"CHECK"))} -> 0 | F11: =IFERROR(D11-E11,"") -> 0 | G11: ='Part 1'!U30 -> 37 | L11: Honda Civic | M11: PC-65076 | N11: 10 | O11: =IF($L11="","",IF(TRIM(INDEX('Part 4'!$E$2:$AY$2,1,ROW()-1))=TRIM($L11),INDEX('Part 4'!$E$778:$AY$778,1,ROW()-1),"CHECK")) -> 5 | P11: =IFERROR(N11-O11,"") -> 5 | Q11: ='Part 4'!N20 -> -131 | T11: SD-1009IKN1.8-MC | U11: SD-1009IKN1.8-PL | V11: 0 | W11: =IFERROR('Part 7'!EQ690+0,0) -> 0 | X11: =IFERROR(V11-W11,"") -> 0 | Y11: ='Part 7'!EQ18 -> 180 | AA11: MARUTI 800 DISCHARGE HOSE R134A | AB11: PC-109 | AC11: 0 | AD11: =IF($AB11="","",IF(TRIM(INDEX('Part 8'!$F$2:$IV$2,1,ROW()-1))=TRIM($AB11),INDEX('Part 8'!$F$244:$IV$244,1,ROW()-1),"CHECK")) -> 6 | AE11: =IFERROR(AC11-AD11,"") -> -6 | AF11: ='Part 8'!O9 -> 0
B12: AUDI A6 | C12: PCP-C86082 | D12: 5 | E12: {=IF($B12="","",IF(TRIM(INDEX('Part 1'!$L$2:$IV$2,1,ROW()-1))=TRIM($B12),INDEX('Part 1'!$L$1250:$IV$1250,1,ROW()-1),"CHECK"))} -> 5 | F12: =IFERROR(D12-E12,"") -> 0 | G12: ='Part 1'!V30 -> 39 | L12: Indica Behr | M12: PC-8115 | N12: 0 | O12: =IF($L12="","",IF(TRIM(INDEX('Part 4'!$E$2:$AY$2,1,ROW()-1))=TRIM($L12),INDEX('Part 4'!$E$778:$AY$778,1,ROW()-1),"CHECK")) -> 0 | P12: =IFERROR(N12-O12,"") -> 0 | Q12: ='Part 4'!O20 -> 436 | T12: SD-1010LNR-MMC-MC | U12: SD-1010LNR-MMC-PL | V12: 2 | W12: =IFERROR('Part 7'!ER690+0,0) -> 2 | X12: =IFERROR(V12-W12,"") -> 0 | Y12: ='Part 7'!ER18 -> 22 | AA12: MARUTI 800 R134A SUCTION HOSE | AB12: PC-110 | AC12: 0 | AD12: =IF($AB12="","",IF(TRIM(INDEX('Part 8'!$F$2:$IV$2,1,ROW()-1))=TRIM($AB12),INDEX('Part 8'!$F$244:$IV$244,1,ROW()-1),"CHECK")) -> 0 | AE12: =IFERROR(AC12-AD12,"") -> 0 | AF12: ='Part 8'!P9 -> 0
B13: AUDI Q3 | C13: PCP-C86020 | D13: 28 | E13: {=IF($B13="","",IF(TRIM(INDEX('Part 1'!$L$2:$IV$2,1,ROW()-1))=TRIM($B13),INDEX('Part 1'!$L$1250:$IV$1250,1,ROW()-1),"CHECK"))} -> 20 | F13: =IFERROR(D13-E13,"") -> 8 | G13: ='Part 1'!W30 -> 65 | L13: Lancer | M13: PC-8017 | N13: 1 | O13: =IF($L13="","",IF(TRIM(INDEX('Part 4'!$E$2:$AY$2,1,ROW()-1))=TRIM($L13),INDEX('Part 4'!$E$778:$AY$778,1,ROW()-1),"CHECK")) -> 1 | P13: =IFERROR(N13-O13,"") -> 0 | Q13: ='Part 4'!P20 -> 28 | T13: SD-1011ACRDI-MC | U13: SD-1011ACRDI-PL | V13: 0 | W13: =IFERROR('Part 7'!ES690+0,0) -> 0 | X13: =IFERROR(V13-W13,"") -> 0 | Y13: ='Part 7'!ES18 -> 279 | AA13: MARUTI 800 LIQUID TUBE RD TO COND R134A (PAD & NUT) | AB13: PC-111 | AC13: 0 | AD13: =IF($AB13="","",IF(TRIM(INDEX('Part 8'!$F$2:$IV$2,1,ROW()-1))=TRIM($AB13),INDEX('Part 8'!$F$244:$IV$244,1,ROW()-1),"CHECK")) -> 5 | AE13: =IFERROR(AC13-AD13,"") -> -5 | AF13: ='Part 8'!Q9 -> 0
B14: AUDI Q7 | C14: PCP-C86832 | D14: 3 | E14: {=IF($B14="","",IF(TRIM(INDEX('Part 1'!$L$2:$IV$2,1,ROW()-1))=TRIM($B14),INDEX('Part 1'!$L$1250:$IV$1250,1,ROW()-1),"CHECK"))} -> 3 | F14: =IFERROR(D14-E14,"") -> 0 | G14: ='Part 1'!X30 -> 20 | L14: Logan (DSL) | M14: PC-20233-A | N14: 0 | O14: =IF($L14="","",IF(TRIM(INDEX('Part 4'!$E$2:$AY$2,1,ROW()-1))=TRIM($L14),INDEX('Part 4'!$E$778:$AY$778,1,ROW()-1),"CHECK")) -> 0 | P14: =IFERROR(N14-O14,"") -> 0 | Q14: ='Part 4'!Q20 -> 75 | T14: SD-1012SCR-MC | U14: SD-1012SCR-PL | V14: 0 | W14: =IFERROR('Part 7'!ET690+0,0) -> 0 | X14: =IFERROR(V14-W14,"") -> 0 | Y14: ='Part 7'!ET18 -> 440 | AA14: MARUTI 800 R134A LIQUID TUBE RD (BOTH SIDE PAD) | AB14: PC-112 | AC14: 0 | AD14: =IF($AB14="","",IF(TRIM(INDEX('Part 8'!$F$2:$IV$2,1,ROW()-1))=TRIM($AB14),INDEX('Part 8'!$F$244:$IV$244,1,ROW()-1),"CHECK")) -> 0 | AE14: =IFERROR(AC14-AD14,"") -> 0 | AF14: ='Part 8'!R9 -> 0
B15: AVEO | C15: PC-86177 | D15: 27 | E15: {=IF($B15="","",IF(TRIM(INDEX('Part 1'!$L$2:$IV$2,1,ROW()-1))=TRIM($B15),INDEX('Part 1'!$L$1250:$IV$1250,1,ROW()-1),"CHECK"))} -> 20 | F15: =IFERROR(D15-E15,"") -> 7 | G15: ='Part 1'!Y30 -> 96 | L15: Maruti 'F'Ring | M15: PC-8047 | N15: 0 | O15: =IF($L15="","",IF(TRIM(INDEX('Part 4'!$E$2:$AY$2,1,ROW()-1))=TRIM($L15),INDEX('Part 4'!$E$778:$AY$778,1,ROW()-1),"CHECK")) -> 0 | P15: =IFERROR(N15-O15,"") -> 0 | Q15: ='Part 4'!R20 -> 716 | T15: SD-1018IKN1.3-MC | U15: SD-1018IKN1.3-PL | V15: 0 | W15: =IFERROR('Part 7'!EU690+0,0) -> 0 | X15: =IFERROR(V15-W15,"") -> 0 | Y15: ='Part 7'!EU18 -> -1 | AA15: MARUTI 800 R134A LIQUID TUBE RD TO COIL HP | AB15: PC-113 | AC15: 0 | AD15: =IF($AB15="","",IF(TRIM(INDEX('Part 8'!$F$2:$IV$2,1,ROW()-1))=TRIM($AB15),INDEX('Part 8'!$F$244:$IV$244,1,ROW()-1),"CHECK")) -> 5 | AE15: =IFERROR(AC15-AD15,"") -> -5 | AF15: ='Part 8'!S9 -> 0
B16: BALENO-NEW | C16: PC-86803 | D16: 40 | E16: {=IF($B16="","",IF(TRIM(INDEX('Part 1'!$L$2:$IV$2,1,ROW()-1))=TRIM($B16),INDEX('Part 1'!$L$1250:$IV$1250,1,ROW()-1),"CHECK"))} -> 37 | F16: =IFERROR(D16-E16,"") -> 3 | G16: ='Part 1'!Z30 -> 175 | L16: Maruti 'O'Ring | M16: PC-8051 | N16: 0 | O16: =IF($L16="","",IF(TRIM(INDEX('Part 4'!$E$2:$AY$2,1,ROW()-1))=TRIM($L16),INDEX('Part 4'!$E$778:$AY$778,1,ROW()-1),"CHECK")) -> 0 | P16: =IFERROR(N16-O16,"") -> 0 | Q16: ='Part 4'!S20 -> 1481 | T16: SD-1020ACCD-MC/INNOVA DUAL | U16: SD-1020ACCD-PL | V16: 0 | W16: =IFERROR('Part 7'!EV690+0,0) -> 0 | X16: =IFERROR(V16-W16,"") -> 0 | Y16: ='Part 7'!EV18 -> 139 | AA16: MARUTI 800 R134A LIQUID TUBE COOLING COIL | AB16: PC-114 | AC16: 0 | AD16: =IF($AB16="","",IF(TRIM(INDEX('Part 8'!$F$2:$IV$2,1,ROW()-1))=TRIM($AB16),INDEX('Part 8'!$F$244:$IV$244,1,ROW()-1),"CHECK")) -> 0 | AE16: =IFERROR(AC16-AD16,"") -> 0 | AF16: ='Part 8'!T9 -> 0
B17: BALENO-NEW-Q5 | C17: PC-86803Q5 | D17: 0 | E17: {=IF($B17="","",IF(TRIM(INDEX('Part 1'!$L$2:$IV$2,1,ROW()-1))=TRIM($B17),INDEX('Part 1'!$L$1250:$IV$1250,1,ROW()-1),"CHECK"))} -> 0 | F17: =IFERROR(D17-E17,"") -> 0 | G17: ='Part 1'!AA30 -> 50 | L17: Matiz | M17: PC-8096 | N17: 0 | O17: =IF($L17="","",IF(TRIM(INDEX('Part 4'!$E$2:$AY$2,1,ROW()-1))=TRIM($L17),INDEX('Part 4'!$E$778:$AY$778,1,ROW()-1),"CHECK")) -> 0 | P17: =IFERROR(N17-O17,"") -> 0 | Q17: ='Part 4'!T20 -> 0 | T17: SD-1021CRV-MC | U17: SD-1021CRV-PL | V17: 0 | W17: =IFERROR('Part 7'!EW690+0,0) -> 0 | X17: =IFERROR(V17-W17,"") -> 0 | Y17: ='Part 7'!EW18 -> 260 | AA17: MARUTI 800 R134A SUCTION TUBE COOLING COIL | AB17: PC-115 | AC17: 0 | AD17: =IF($AB17="","",IF(TRIM(INDEX('Part 8'!$F$2:$IV$2,1,ROW()-1))=TRIM($AB17),INDEX('Part 8'!$F$244:$IV$244,1,ROW()-1),"CHECK")) -> 0 | AE17: =IFERROR(AC17-AD17,"") -> 0 | AF17: ='Part 8'!U9 -> 0
B18: BEAT DSL-Q5 | C18: PC-86589Q5 | D18: 25 | E18: {=IF($B18="","",IF(TRIM(INDEX('Part 1'!$L$2:$IV$2,1,ROW()-1))=TRIM($B18),INDEX('Part 1'!$L$1250:$IV$1250,1,ROW()-1),"CHECK"))} -> 5 | F18: =IFERROR(D18-E18,"") -> 20 | G18: ='Part 1'!AB30 -> 145 | L18: Opel | M18: PC-6142 | N18: 0 | O18: =IF($L18="","",IF(TRIM(INDEX('Part 4'!$E$2:$AY$2,1,ROW()-1))=TRIM($L18),INDEX('Part 4'!$E$778:$AY$778,1,ROW()-1),"CHECK")) -> 0 | P18: =IFERROR(N18-O18,"") -> 0 | Q18: ='Part 4'!U20 -> 323 | T18: ZEN DELPHI | U18: SDN-310/PL | V18: 0 | W18: =IFERROR('Part 7'!EX690+0,0) -> 0 | X18: =IFERROR(V18-W18,"") -> 0 | Y18: ='Part 7'!EX18 -> 270 | AA18: MARUTI ZEN ESTILO DISCHARGE HOSE | AB18: PC-116 | AC18: 0 | AD18: =IF($AB18="","",IF(TRIM(INDEX('Part 8'!$F$2:$IV$2,1,ROW()-1))=TRIM($AB18),INDEX('Part 8'!$F$244:$IV$244,1,ROW()-1),"CHECK")) -> 0 | AE18: =IFERROR(AC18-AD18,"") -> 0 | AF18: ='Part 8'!V9 -> 0
B19: BEAT PTL-Q5 | C19: PC-86535Q5 | D19: 20 | E19: {=IF($B19="","",IF(TRIM(INDEX('Part 1'!$L$2:$IV$2,1,ROW()-1))=TRIM($B19),INDEX('Part 1'!$L$1250:$IV$1250,1,ROW()-1),"CHECK"))} -> 15 | F19: =IFERROR(D19-E19,"") -> 5 | G19: ='Part 1'!AC30 -> 299 | L19: Optra | M19: PC-8031 | N19: 0 | O19: =IF($L19="","",IF(TRIM(INDEX('Part 4'!$E$2:$AY$2,1,ROW()-1))=TRIM($L19),INDEX('Part 4'!$E$778:$AY$778,1,ROW()-1),"CHECK")) -> 0 | P19: =IFERROR(N19-O19,"") -> 0 | Q19: ='Part 4'!V20 -> 105 | T19: SDN101/507/7PK | V19: 454 | W19: =IFERROR('Part 7'!EY690+0,0) -> 434 | X19: =IFERROR(V19-W19,"") -> 20 | Y19: ='Part 7'!EY18 -> 1232 | AA19: MARUTI ZEN ESTILO SUCTION HOSE | AB19: PC-117 | AC19: 0 | AD19: =IF($AB19="","",IF(TRIM(INDEX('Part 8'!$F$2:$IV$2,1,ROW()-1))=TRIM($AB19),INDEX('Part 8'!$F$244:$IV$244,1,ROW()-1),"CHECK")) -> 0 | AE19: =IFERROR(AC19-AD19,"") -> 0 | AF19: ='Part 8'!W9 -> 0
B20: BEAT-DSL | C20: PC-86589 | D20: 73 | E20: {=IF($B20="","",IF(TRIM(INDEX('Part 1'!$L$2:$IV$2,1,ROW()-1))=TRIM($B20),INDEX('Part 1'!$L$1250:$IV$1250,1,ROW()-1),"CHECK"))} -> 56 | F20: =IFERROR(D20-E20,"") -> 17 | G20: ='Part 1'!AD30 -> 350 | L20: PIZO (VALVO) | M20: NA | N20: 0 | O20: =IF($L20="","",IF(TRIM(INDEX('Part 4'!$E$2:$AY$2,1,ROW()-1))=TRIM($L20),INDEX('Part 4'!$E$778:$AY$778,1,ROW()-1),"CHECK")) -> 0 | P20: =IFERROR(N20-O20,"") -> 0 | Q20: ='Part 4'!W20 -> 0 | T20: SDN102/508/8PK | V20: 140 | W20: =IFERROR('Part 7'!EZ690+0,0) -> 130 | X20: =IFERROR(V20-W20,"") -> 10 | Y20: ='Part 7'!EZ18 -> 790 | AA20: MARUTI ZEN ESTILO LIQUID TUBE RD TO COIL | AB20: PC-118 | AC20: 0 | AD20: =IF($AB20="","",IF(TRIM(INDEX('Part 8'!$F$2:$IV$2,1,ROW()-1))=TRIM($AB20),INDEX('Part 8'!$F$244:$IV$244,1,ROW()-1),"CHECK")) -> 0 | AE20: =IFERROR(AC20-AD20,"") -> 0 | AF20: ='Part 8'!X9 -> 0
B21: BEAT-PTL | C21: PC-86535 | D21: 128 | E21: {=IF($B21="","",IF(TRIM(INDEX('Part 1'!$L$2:$IV$2,1,ROW()-1))=TRIM($B21),INDEX('Part 1'!$L$1250:$IV$1250,1,ROW()-1),"CHECK"))} -> 115 | F21: =IFERROR(D21-E21,"") -> 13 | G21: ='Part 1'!AE30 -> 652 | L21: Santro / Santro Zing | M21: PC-8026 | N21: 187 | O21: =IF($L21="","",IF(TRIM(INDEX('Part 4'!$E$2:$AY$2,1,ROW()-1))=TRIM($L21),INDEX('Part 4'!$E$778:$AY$778,1,ROW()-1),"CHECK")) -> 185 | P21: =IFERROR(N21-O21,"") -> 2 | Q21: ='Part 4'!X20 -> 322 | T21: I-20 (DSL) | U21: SD-313PL/I-20 DSL | V21: 15 | W21: =IFERROR('Part 7'!FA690+0,0) -> 15 | X21: =IFERROR(V21-W21,"") -> 0 | Y21: ='Part 7'!FA18 -> 387 | AA21: MARUTI SX4 DISCHARGE HOSE | AB21: PC-119 | AC21: 0 | AD21: =IF($AB21="","",IF(TRIM(INDEX('Part 8'!$F$2:$IV$2,1,ROW()-1))=TRIM($AB21),INDEX('Part 8'!$F$244:$IV$244,1,ROW()-1),"CHECK")) -> 0 | AE21: =IFERROR(AC21-AD21,"") -> 0 | AF21: ='Part 8'!Y9 -> 0
B22: BELANO | C22: PC-86242 | D22: 1 | E22: {=IF($B22="","",IF(TRIM(INDEX('Part 1'!$L$2:$IV$2,1,ROW()-1))=TRIM($B22),INDEX('Part 1'!$L$1250:$IV$1250,1,ROW()-1),"CHECK"))} -> 0 | F22: =IFERROR(D22-E22,"") -> 1 | G22: ='Part 1'!AF30 -> 118 | L22: Scorpio 3 holes | M22: PC-650138 | N22: 0 | O22: =IF($L22="","",IF(TRIM(INDEX('Part 4'!$E$2:$AY$2,1,ROW()-1))=TRIM($L22),INDEX('Part 4'!$E$778:$AY$778,1,ROW()-1),"CHECK")) -> 0 | P22: =IFERROR(N22-O22,"") -> 0 | Q22: ='Part 4'!Y20 -> 210 | T22: I-20 (PTL) | U22: SD-319PL/I-20 PTL | V22: 4 | W22: =IFERROR('Part 7'!FB690+0,0) -> 1 | X22: =IFERROR(V22-W22,"") -> 3 | Y22: ='Part 7'!FB18 -> 509 | AA22: MARUTI SX4 SUCTION HOSE | AB22: PC-120 | AC22: 0 | AD22: =IF($AB22="","",IF(TRIM(INDEX('Part 8'!$F$2:$IV$2,1,ROW()-1))=TRIM($AB22),INDEX('Part 8'!$F$244:$IV$244,1,ROW()-1),"CHECK")) -> 30 | AE22: =IFERROR(AC22-AD22,"") -> -30 | AF22: ='Part 8'!Z9 -> 0
E23: {=IF($B23="","",IF(TRIM(INDEX('Part 1'!$L$2:$IV$2,1,ROW()-1))=TRIM($B23),INDEX('Part 1'!$L$1250:$IV$1250,1,ROW()-1),"CHECK"))} | L23: Scorpio 4 holes | M23: PC-650139 | N23: 0 | O23: =IF($L23="","",IF(TRIM(INDEX('Part 4'!$E$2:$AY$2,1,ROW()-1))=TRIM($L23),INDEX('Part 4'!$E$778:$AY$778,1,ROW()-1),"CHECK")) -> 0 | P23: =IFERROR(N23-O23,"") -> 0 | Q23: ='Part 4'!Z20 -> 448 | T23: VISTA BEHR 6PK Q.JET | U23: SD316PL/V.QJET6PK | V23: 73 | W23: =IFERROR('Part 7'!FC690+0,0) -> 71 | X23: =IFERROR(V23-W23,"") -> 2 | Y23: ='Part 7'!FC18 -> 654 | AA23: MARUTI SX4 SUCTION TUBE | AB23: PC-121 | AC23: 0 | AD23: =IF($AB23="","",IF(TRIM(INDEX('Part 8'!$F$2:$IV$2,1,ROW()-1))=TRIM($AB23),INDEX('Part 8'!$F$244:$IV$244,1,ROW()-1),"CHECK")) -> 0 | AE23: =IFERROR(AC23-AD23,"") -> 0 | AF23: ='Part 8'!AA9 -> 0
B24: BMW E90 DSL SMALL | C24: PCP-C86741F | D24: 0 | E24: {=IF($B24="","",IF(TRIM(INDEX('Part 1'!$L$2:$IV$2,1,ROW()-1))=TRIM($B24),INDEX('Part 1'!$L$1250:$IV$1250,1,ROW()-1),"CHECK"))} -> 1 | F24: =IFERROR(D24-E24,"") -> -1 | G24: ='Part 1'!AH30 -> 0 | L24: Skoda | M24: PC-8053 | N24: 72 | O24: =IF($L24="","",IF(TRIM(INDEX('Part 4'!$E$2:$AY$2,1,ROW()-1))=TRIM($L24),INDEX('Part 4'!$E$778:$AY$778,1,ROW()-1),"CHECK")) -> 62 | P24: =IFERROR(N24-O24,"") -> 10 | Q24: ='Part 4'!AA20 -> 242 | T24: SCORPIO SANDEN | V24: 13 | W24: =IFERROR('Part 7'!FD690+0,0) -> 10 | X24: =IFERROR(V24-W24,"") -> 3 | Y24: ='Part 7'!FD18 -> 249 | AA24: MARUTI SX4 SUC HOSE N/M | AB24: PC-121A | AC24: 0 | AD24: =IF($AB24="","",IF(TRIM(INDEX('Part 8'!$F$2:$IV$2,1,ROW()-1))=TRIM($AB24),INDEX('Part 8'!$F$244:$IV$244,1,ROW()-1),"CHECK")) -> 0 | AE24: =IFERROR(AC24-AD24,"") -> 0 | AF24: ='Part 8'!AB9 -> 0
B25: BMW 3 SERIES E60 BIG | C25: PCP-C86749F | D25: 1 | E25: {=IF($B25="","",IF(TRIM(INDEX('Part 1'!$L$2:$IV$2,1,ROW()-1))=TRIM($B25),INDEX('Part 1'!$L$1250:$IV$1250,1,ROW()-1),"CHECK"))} -> 0 | F25: =IFERROR(D25-E25,"") -> 1 | G25: ='Part 1'!AI30 -> 28 | L25: Skoda Laura | M25: PC-8039B | N25: 5 | O25: =IF($L25="","",IF(TRIM(INDEX('Part 4'!$E$2:$AY$2,1,ROW()-1))=TRIM($L25),INDEX('Part 4'!$E$778:$AY$778,1,ROW()-1),"CHECK")) -> 5 | P25: =IFERROR(N25-O25,"") -> 0 | Q25: ='Part 4'!AB20 -> 300 | T25: SCORPIO HCC | V25: 45 | W25: =IFERROR('Part 7'!FE690+0,0) -> 48 | X25: =IFERROR(V25-W25,"") -> -3 | Y25: ='Part 7'!FE18 -> 233 | AA25: MARUTI SX4 SUCTION HOSE NEW | AB25: PC-121B | AC25: 0 | AD25: =IF($AB25="","",IF(TRIM(INDEX('Part 8'!$F$2:$IV$2,1,ROW()-1))=TRIM($AB25),INDEX('Part 8'!$F$244:$IV$244,1,ROW()-1),"CHECK")) -> 0 | AE25: =IFERROR(AC25-AD25,"") -> 0 | AF25: ='Part 8'!AC9 -> 0
B26: BMW 3 SERIES E60 PTL | C26: PCP-C86747F | D26: 0 | E26: {=IF($B26="","",IF(TRIM(INDEX('Part 1'!$L$2:$IV$2,1,ROW()-1))=TRIM($B26),INDEX('Part 1'!$L$1250:$IV$1250,1,ROW()-1),"CHECK"))} -> 0 | F26: =IFERROR(D26-E26,"") -> 0 | G26: ='Part 1'!AJ30 -> 16 | L26: Sonata | M26: PC-6066 | N26: 0 | O26: =IF($L26="","",IF(TRIM(INDEX('Part 4'!$E$2:$AY$2,1,ROW()-1))=TRIM($L26),INDEX('Part 4'!$E$778:$AY$778,1,ROW()-1),"CHECK")) -> 0 | P26: =IFERROR(N26-O26,"") -> 0 | Q26: ='Part 4'!AC20 -> 0 | T26: FEISTA DSL | U26: SD-315PL/FEISTA-DSL | V26: 9 | W26: =IFERROR('Part 7'!FF690+0,0) -> 3 | X26: =IFERROR(V26-W26,"") -> 6 | Y26: ='Part 7'!FF18 -> 325 | AA26: MARUTI SX 4 DISCHARGE HOSE NEW | AB26: PC-121C | AC26: 0 | AD26: =IF($AB26="","",IF(TRIM(INDEX('Part 8'!$F$2:$IV$2,1,ROW()-1))=TRIM($AB26),INDEX('Part 8'!$F$244:$IV$244,1,ROW()-1),"CHECK")) -> 0 | AE26: =IFERROR(AC26-AD26,"") -> 0 | AF26: ='Part 8'!AD9 -> 0
B27: BMW E60 DSL 03-07 | C27: PCP-C86748F | D27: 3 | E27: {=IF($B27="","",IF(TRIM(INDEX('Part 1'!$L$2:$IV$2,1,ROW()-1))=TRIM($B27),INDEX('Part 1'!$L$1250:$IV$1250,1,ROW()-1),"CHECK"))} -> 2 | F27: =IFERROR(D27-E27,"") -> 1 | G27: ='Part 1'!AK30 -> 15 | L27: TEMPO TRAVELLER-ORING 3/8 SIZE 70*270 | M27: PC-60002 | N27: 260 | O27: =IF($L27="","",IF(TRIM(INDEX('Part 4'!$E$2:$AY$2,1,ROW()-1))=TRIM($L27),INDEX('Part 4'!$E$778:$AY$778,1,ROW()-1),"CHECK")) -> 210 | P27: =IFERROR(N27-O27,"") -> 50 | Q27: ='Part 4'!AD20 -> 1047 | T27: SUMO VECTA DELPHI | U27: SD-321PL/SOMU V. DELPHI | V27: 0 | W27: =IFERROR('Part 7'!FG690+0,0) -> 0 | X27: =IFERROR(V27-W27,"") -> 0 | Y27: ='Part 7'!FG18 -> 546 | AA27: MARUTI SWIFT DSL DISCHARGE HOSE | AB27: PC-122 | AC27: 0 | AD27: =IF($AB27="","",IF(TRIM(INDEX('Part 8'!$F$2:$IV$2,1,ROW()-1))=TRIM($AB27),INDEX('Part 8'!$F$244:$IV$244,1,ROW()-1),"CHECK")) -> 0 | AE27: =IFERROR(AC27-AD27,"") -> 0 | AF27: ='Part 8'!AE9 -> 0
B28: BOLERO- R134A | C28: PC-86236 | D28: 42 | E28: {=IF($B28="","",IF(TRIM(INDEX('Part 1'!$L$2:$IV$2,1,ROW()-1))=TRIM($B28),INDEX('Part 1'!$L$1250:$IV$1250,1,ROW()-1),"CHECK"))} -> 42 | F28: =IFERROR(D28-E28,"") -> 0 | G28: ='Part 1'!AL30 -> 50 | L28: TEMPO TRAVELLER-SMALL (DENFOS) | M28: PC-60003 | N28: 55 | O28: =IF($L28="","",IF(TRIM(INDEX('Part 4'!$E$2:$AY$2,1,ROW()-1))=TRIM($L28),INDEX('Part 4'!$E$778:$AY$778,1,ROW()-1),"CHECK")) -> 50 | P28: =IFERROR(N28-O28,"") -> 5 | Q28: ='Part 4'!AE20 -> 115 | T28: A-STAR | U28: SD-323PL/A-STAR | V28: 282 | W28: =IFERROR('Part 7'!FH690+0,0) -> 220 | X28: =IFERROR(V28-W28,"") -> 62 | Y28: ='Part 7'!FH18 -> 1214 | AA28: MARUTI SWIFT DSL. SUCTIONON HOSE | AB28: PC-123 | AC28: 0 | AD28: =IF($AB28="","",IF(TRIM(INDEX('Part 8'!$F$2:$IV$2,1,ROW()-1))=TRIM($AB28),INDEX('Part 8'!$F$244:$IV$244,1,ROW()-1),"CHECK")) -> 0 | AE28: =IFERROR(AC28-AD28,"") -> 0 | AF28: ='Part 8'!AF9 -> 0
B29: BOLERO- R134A (NEW) | C29: PC-86395 | D29: 319 | E29: {=IF($B29="","",IF(TRIM(INDEX('Part 1'!$L$2:$IV$2,1,ROW()-1))=TRIM($B29),INDEX('Part 1'!$L$1250:$IV$1250,1,ROW()-1),"CHECK"))} -> 269 | F29: =IFERROR(D29-E29,"") -> 50 | G29: ='Part 1'!AM30 -> 728 | L29: Toyota Qualis/ SAFARI | M29: PC-8008 | N29: 420 | O29: =IF($L29="","",IF(TRIM(INDEX('Part 4'!$E$2:$AY$2,1,ROW()-1))=TRIM($L29),INDEX('Part 4'!$E$778:$AY$778,1,ROW()-1),"CHECK")) -> 310 | P29: =IFERROR(N29-O29,"") -> 110 | Q29: ='Part 4'!AF20 -> 998 | T29: I-10 KAPPA | U29: SD-317PL/I10 KAPPA | V29: 52 | W29: =IFERROR('Part 7'!FI690+0,0) -> 46 | X29: =IFERROR(V29-W29,"") -> 6 | Y29: ='Part 7'!FI18 -> 608 | AA29: MARUTI SWIFT DSL LIQUID TUBE RD TO COOLING COIL | AB29: PC-124 | AC29: 0 | AD29: =IF($AB29="","",IF(TRIM(INDEX('Part 8'!$F$2:$IV$2,1,ROW()-1))=TRIM($AB29),INDEX('Part 8'!$F$244:$IV$244,1,ROW()-1),"CHECK")) -> 0 | AE29: =IFERROR(AC29-AD29,"") -> 0 | AF29: ='Part 8'!AG9 -> 0
B30: BREEZA-Q5 | C30: PC-86811-Q5 | D30: 22 | E30: {=IF($B30="","",IF(TRIM(INDEX('Part 1'!$L$2:$IV$2,1,ROW()-1))=TRIM($B30),INDEX('Part 1'!$L$1250:$IV$1250,1,ROW()-1),"CHECK"))} -> 11 | F30: =IFERROR(D30-E30,"") -> 11 | G30: ='Part 1'!AN30 -> 127 | L30: Travera | M30: PC-8122 | N30: 10 | O30: =IF($L30="","",IF(TRIM(INDEX('Part 4'!$E$2:$AY$2,1,ROW()-1))=TRIM($L30),INDEX('Part 4'!$E$778:$AY$778,1,ROW()-1),"CHECK")) -> 10 | P30: =IFERROR(N30-O30,"") -> 0 | Q30: ='Part 4'!AG20 -> 2104 | T30: HONDA ZX/T4 | U30: SD-320PL/HT4ZXDSL | V30: 32 | W30: =IFERROR('Part 7'!FJ690+0,0) -> 32 | X30: =IFERROR(V30-W30,"") -> 0 | Y30: ='Part 7'!FJ18 -> 632 | AA30: MARUTI SWIFT DSL DISCHARGE HOSE. | AB30: PC-124A | AC30: 0 | AD30: =IF($AB30="","",IF(TRIM(INDEX('Part 8'!$F$2:$IV$2,1,ROW()-1))=TRIM($AB30),INDEX('Part 8'!$F$244:$IV$244,1,ROW()-1),"CHECK")) -> 0 | AE30: =IFERROR(AC30-AD30,"") -> 0 | AF30: ='Part 8'!AH9 -> 0
B31: BRIO | C31: PC-86581 | D31: 107 | E31: {=IF($B31="","",IF(TRIM(INDEX('Part 1'!$L$2:$IV$2,1,ROW()-1))=TRIM($B31),INDEX('Part 1'!$L$1250:$IV$1250,1,ROW()-1),"CHECK"))} -> 87 | F31: =IFERROR(D31-E31,"") -> 20 | G31: ='Part 1'!AO30 -> 517 | L31: Universal BUS- 3/8F SIZE 76*245 | M31: PC-61020 | N31: 227 | O31: =IF($L31="","",IF(TRIM(INDEX('Part 4'!$E$2:$AY$2,1,ROW()-1))=TRIM($L31),INDEX('Part 4'!$E$778:$AY$778,1,ROW()-1),"CHECK")) -> 185 | P31: =IFERROR(N31-O31,"") -> 42 | Q31: ='Part 4'!AH20 -> 1199 | T31: BOLERO | U31: SD-311PL/BLR | V31: 67 | W31: =IFERROR('Part 7'!FK690+0,0) -> 54 | X31: =IFERROR(V31-W31,"") -> 13 | Y31: ='Part 7'!FK18 -> 721 | AA31: MARUTI SWIFT DSL DISCHARGE HOSE DE'ZIRE | AB31: PC-124B | AC31: 0 | AD31: =IF($AB31="","",IF(TRIM(INDEX('Part 8'!$F$2:$IV$2,1,ROW()-1))=TRIM($AB31),INDEX('Part 8'!$F$244:$IV$244,1,ROW()-1),"CHECK")) -> 0 | AE31: =IFERROR(AC31-AD31,"") -> 0 | AF31: ='Part 8'!AI9 -> 0
B32: BRIO-Q5 | C32: PC-86581-Q5 | D32: 86 | E32: {=IF($B32="","",IF(TRIM(INDEX('Part 1'!$L$2:$IV$2,1,ROW()-1))=TRIM($B32),INDEX('Part 1'!$L$1250:$IV$1250,1,ROW()-1),"CHECK"))} -> 10 | F32: =IFERROR(D32-E32,"") -> 76 | G32: ='Part 1'!AP30 -> 195 | L32: Universal-F | M32: PC-6001 | N32: 75 | O32: =IF($L32="","",IF(TRIM(INDEX('Part 4'!$E$2:$AY$2,1,ROW()-1))=TRIM($L32),INDEX('Part 4'!$E$778:$AY$778,1,ROW()-1),"CHECK")) -> 50 | P32: =IFERROR(N32-O32,"") -> 25 | Q32: ='Part 4'!AI20 -> 1463 | T32: SX4 | U32: SD-322PL/SX4 | V32: 17 | W32: =IFERROR('Part 7'!FL690+0,0) -> 0 | X32: =IFERROR(V32-W32,"") -> 17 | Y32: ='Part 7'!FL18 -> 363 | AA32: MARUTI BALENO SUCTION HOSE | AB32: PC-125 | AC32: 0 | AD32: =IF($AB32="","",IF(TRIM(INDEX('Part 8'!$F$2:$IV$2,1,ROW()-1))=TRIM($AB32),INDEX('Part 8'!$F$244:$IV$244,1,ROW()-1),"CHECK")) -> 0 | AE32: =IFERROR(AC32-AD32,"") -> 0 | AF32: ='Part 8'!AJ9 -> 0
B33: CAIZ-Q5 | C33: PC-86812Q5 | D33: 15 | E33: {=IF($B33="","",IF(TRIM(INDEX('Part 1'!$L$2:$IV$2,1,ROW()-1))=TRIM($B33),INDEX('Part 1'!$L$1250:$IV$1250,1,ROW()-1),"CHECK"))} -> 15 | F33: =IFERROR(D33-E33,"") -> 0 | G33: ='Part 1'!AQ30 -> 100 | L33: Universal-O | M33: PC-6002 | N33: 100 | O33: =IF($L33="","",IF(TRIM(INDEX('Part 4'!$E$2:$AY$2,1,ROW()-1))=TRIM($L33),INDEX('Part 4'!$E$778:$AY$778,1,ROW()-1),"CHECK")) -> 75 | P33: =IFERROR(N33-O33,"") -> 25 | Q33: ='Part 4'!AJ20 -> 2900 | T33: ENDEAVOUR | U33: SD-318PL/END | V33: 2 | W33: =IFERROR('Part 7'!FM690+0,0) -> 2 | X33: =IFERROR(V33-W33,"") -> 0 | Y33: ='Part 7'!FM18 -> 160 | AA33: MARUTI BALENO DISCHARGE HOSE | AB33: PC-126 | AC33: 0 | AD33: =IF($AB33="","",IF(TRIM(INDEX('Part 8'!$F$2:$IV$2,1,ROW()-1))=TRIM($AB33),INDEX('Part 8'!$F$244:$IV$244,1,ROW()-1),"CHECK")) -> 0 | AE33: =IFERROR(AC33-AD33,"") -> 0 | AF33: ='Part 8'!AK9 -> 0
B34: CAMRY - 02-05 | C34: PC-86396 | D34: 0 | E34: {=IF($B34="","",IF(TRIM(INDEX('Part 1'!$L$2:$IV$2,1,ROW()-1))=TRIM($B34),INDEX('Part 1'!$L$1250:$IV$1250,1,ROW()-1),"CHECK"))} -> 0 | F34: =IFERROR(D34-E34,"") -> 0 | G34: ='Part 1'!AR30 -> 58 | L34: ADOPTER ORING 5/16 TO 3/8 FLARE | N34: 0 | O34: =IF($L34="","",IF(TRIM(INDEX('Part 4'!$E$2:$AY$2,1,ROW()-1))=TRIM($L34),INDEX('Part 4'!$E$778:$AY$778,1,ROW()-1),"CHECK")) -> 170 | P34: =IFERROR(N34-O34,"") -> -170 | Q34: ='Part 4'!AK20 -> -1535 | T34: HT3 | U34: SD312PL/HT3 | V34: 23 | W34: =IFERROR('Part 7'!FN690+0,0) -> 10 | X34: =IFERROR(V34-W34,"") -> 13 | Y34: ='Part 7'!FN18 -> 911 | AA34: MARUTI BALENO SUCTION TUBE | AB34: PC-127 | AC34: 0 | AD34: =IF($AB34="","",IF(TRIM(INDEX('Part 8'!$F$2:$IV$2,1,ROW()-1))=TRIM($AB34),INDEX('Part 8'!$F$244:$IV$244,1,ROW()-1),"CHECK")) -> 0 | AE34: =IFERROR(AC34-AD34,"") -> 0 | AF34: ='Part 8'!AL9 -> 0
B35: CAMRY - 07-09 | C35: PC-86397 | D35: 0 | E35: {=IF($B35="","",IF(TRIM(INDEX('Part 1'!$L$2:$IV$2,1,ROW()-1))=TRIM($B35),INDEX('Part 1'!$L$1250:$IV$1250,1,ROW()-1),"CHECK"))} -> 0 | F35: =IFERROR(D35-E35,"") -> 0 | G35: ='Part 1'!AS30 -> 0 | L35: Universal-O | M35: PC-6001B | N35: 0 | O35: =IF($L35="","",IF(TRIM(INDEX('Part 4'!$E$2:$AY$2,1,ROW()-1))=TRIM($L35),INDEX('Part 4'!$E$778:$AY$778,1,ROW()-1),"CHECK")) -> 0 | P35: =IFERROR(N35-O35,"") -> 0 | Q35: ='Part 4'!AL20 -> -284 | T35: SWIFT PTL | U35: SD324PL/SWT-PTL | V35: 33 | W35: =IFERROR('Part 7'!FO690+0,0) -> 33 | X35: =IFERROR(V35-W35,"") -> 0 | Y35: ='Part 7'!FO18 -> 336 | AA35: MARUTI BALENO LIQUID TUBE | AB35: PC-128 | AC35: 0 | AD35: =IF($AB35="","",IF(TRIM(INDEX('Part 8'!$F$2:$IV$2,1,ROW()-1))=TRIM($AB35),INDEX('Part 8'!$F$244:$IV$244,1,ROW()-1),"CHECK")) -> 30 | AE35: =IFERROR(AC35-AD35,"") -> -30 | AF35: ='Part 8'!AM9 -> 0
B36: CAMRY - 07-09 (Q5) | C36: PC-86397-Q5 | D36: 0 | E36: {=IF($B36="","",IF(TRIM(INDEX('Part 1'!$L$2:$IV$2,1,ROW()-1))=TRIM($B36),INDEX('Part 1'!$L$1250:$IV$1250,1,ROW()-1),"CHECK"))} -> 0 | F36: =IFERROR(D36-E36,"") -> 0 | G36: ='Part 1'!AT30 -> 35 | L36: Universal-F WITH BOLT | M36: PC-6003 | N36: 0 | O36: =IF($L36="","",IF(TRIM(INDEX('Part 4'!$E$2:$AY$2,1,ROW()-1))=TRIM($L36),INDEX('Part 4'!$E$778:$AY$778,1,ROW()-1),"CHECK")) -> 0 | P36: =IFERROR(N36-O36,"") -> 0 | Q36: ='Part 4'!AM20 -> 105 | T36: SWIFT DSL | U36: SD325PL/SWT-DSL | V36: 120 | W36: =IFERROR('Part 7'!FP690+0,0) -> 77 | X36: =IFERROR(V36-W36,"") -> 43 | Y36: ='Part 7'!FP18 -> 852 | AA36: MARUTI LIQUID TUBE BALENO | AB36: PC-129 | AC36: 0 | AD36: =IF($AB36="","",IF(TRIM(INDEX('Part 8'!$F$2:$IV$2,1,ROW()-1))=TRIM($AB36),INDEX('Part 8'!$F$244:$IV$244,1,ROW()-1),"CHECK")) -> 0 | AE36: =IFERROR(AC36-AD36,"") -> 0 | AF36: ='Part 8'!AN9 -> 0
B37: CELERO | C37: PC-86903 | D37: 95 | E37: {=IF($B37="","",IF(TRIM(INDEX('Part 1'!$L$2:$IV$2,1,ROW()-1))=TRIM($B37),INDEX('Part 1'!$L$1250:$IV$1250,1,ROW()-1),"CHECK"))} -> 89 | F37: =IFERROR(D37-E37,"") -> 6 | G37: ='Part 1'!AU30 -> 200 | L37: Skoda SUPERB | M37: PC-650140 | N37: 20 | O37: =IF($L37="","",IF(TRIM(INDEX('Part 4'!$E$2:$AY$2,1,ROW()-1))=TRIM($L37),INDEX('Part 4'!$E$778:$AY$778,1,ROW()-1),"CHECK")) -> 20 | P37: =IFERROR(N37-O37,"") -> 0 | Q37: ='Part 4'!AN20 -> 110 | T37: CRV | U37: SD301PL/CRV | V37: 0 | W37: =IFERROR('Part 7'!FQ690+0,0) -> 0 | X37: =IFERROR(V37-W37,"") -> 0 | Y37: ='Part 7'!FQ18 -> 281 | AA37: MARUTI SWIFT PTL SUCTION HOSE | AB37: PC-130 | AC37: 0 | AD37: =IF($AB37="","",IF(TRIM(INDEX('Part 8'!$F$2:$IV$2,1,ROW()-1))=TRIM($AB37),INDEX('Part 8'!$F$244:$IV$244,1,ROW()-1),"CHECK")) -> 0 | AE37: =IFERROR(AC37-AD37,"") -> 0 | AF37: ='Part 8'!AO9 -> 0
B38: CIAZ-Q5 | C38: PC-86901 | D38: 20 | E38: {=IF($B38="","",IF(TRIM(INDEX('Part 1'!$L$2:$IV$2,1,ROW()-1))=TRIM($B38),INDEX('Part 1'!$L$1250:$IV$1250,1,ROW()-1),"CHECK"))} -> 9 | F38: =IFERROR(D38-E38,"") -> 11 | G38: ='Part 1'!AV30 -> 56 | L38: Universal | M38: PC-6003 | N38: 0 | O38: =IF($L38="","",IF(TRIM(INDEX('Part 4'!$E$2:$AY$2,1,ROW()-1))=TRIM($L38),INDEX('Part 4'!$E$778:$AY$778,1,ROW()-1),"CHECK")) -> 0 | P38: =IFERROR(N38-O38,"") -> 0 | Q38: ='Part 4'!AO20 -> 0 | T38: CIVIC | U38: SD326PL/CIVIC | V38: 12 | W38: =IFERROR('Part 7'!FR690+0,0) -> 4 | X38: =IFERROR(V38-W38,"") -> 8 | Y38: ='Part 7'!FR18 -> 149 | AA38: MARUTI SWIFT DISCHARGE HOSE | AB38: PC-131 | AC38: 0 | AD38: =IF($AB38="","",IF(TRIM(INDEX('Part 8'!$F$2:$IV$2,1,ROW()-1))=TRIM($AB38),INDEX('Part 8'!$F$244:$IV$244,1,ROW()-1),"CHECK")) -> 10 | AE38: =IFERROR(AC38-AD38,"") -> -10 | AF38: ='Part 8'!AP9 -> 0
B39: COROLLA | C39: PC-86110 | D39: 16 | E39: {=IF($B39="","",IF(TRIM(INDEX('Part 1'!$L$2:$IV$2,1,ROW()-1))=TRIM($B39),INDEX('Part 1'!$L$1250:$IV$1250,1,ROW()-1),"CHECK"))} -> 14 | F39: =IFERROR(D39-E39,"") -> 2 | G39: ='Part 1'!AW30 -> 140 | L39: EYE GLASS | N39: 0 | O39: =IF($L39="","",IF(TRIM(INDEX('Part 4'!$E$2:$AY$2,1,ROW()-1))=TRIM($L39),INDEX('Part 4'!$E$778:$AY$778,1,ROW()-1),"CHECK")) -> 0 | P39: =IFERROR(N39-O39,"") -> 0 | Q39: ='Part 4'!AP20 -> -400 | T39: VARNA | U39: SD327PL/VARNA | V39: 6 | W39: =IFERROR('Part 7'!FS690+0,0) -> 4 | X39: =IFERROR(V39-W39,"") -> 2 | Y39: ='Part 7'!FS18 -> 277 | AA39: MARUTI SWIFT LIQUID TUBE RD TO COIL | AB39: PC-132 | AC39: 0 | AD39: =IF($AB39="","",IF(TRIM(INDEX('Part 8'!$F$2:$IV$2,1,ROW()-1))=TRIM($AB39),INDEX('Part 8'!$F$244:$IV$244,1,ROW()-1),"CHECK")) -> 5 | AE39: =IFERROR(AC39-AD39,"") -> -5 | AF39: ='Part 8'!AQ9 -> 0
B40: COROLLA-Q5 | C40: PC-86110A-Q5 | D40: 15 | E40: {=IF($B40="","",IF(TRIM(INDEX('Part 1'!$L$2:$IV$2,1,ROW()-1))=TRIM($B40),INDEX('Part 1'!$L$1250:$IV$1250,1,ROW()-1),"CHECK"))} -> 16 | F40: =IFERROR(D40-E40,"") -> -1 | G40: ='Part 1'!AX30 -> 200 | L40: Desiccant Drier/Filter | M40: PC-20242 | N40: 190 | O40: =IF($L40="","",IF(TRIM(INDEX('Part 4'!$E$2:$AY$2,1,ROW()-1))=TRIM($L40),INDEX('Part 4'!$E$778:$AY$778,1,ROW()-1),"CHECK")) -> 240 | P40: =IFERROR(N40-O40,"") -> -50 | Q40: ='Part 4'!AQ20 -> 8500 | T40: MHAWK | U40: SD328PL/MHWK | V40: 68 | W40: =IFERROR('Part 7'!FT690+0,0) -> 66 | X40: =IFERROR(V40-W40,"") -> 2 | Y40: ='Part 7'!FT18 -> 291 | AA40: MARUTI SWIFT PTL DISCHARGE HOSE NEW | AB40: PC-132A | AC40: 0 | AD40: =IF($AB40="","",IF(TRIM(INDEX('Part 8'!$F$2:$IV$2,1,ROW()-1))=TRIM($AB40),INDEX('Part 8'!$F$244:$IV$244,1,ROW()-1),"CHECK")) -> 0 | AE40: =IFERROR(AC40-AD40,"") -> 0 | AF40: ='Part 8'!AR9 -> 0
B41: CRETA-DSL | C41: PC-86805 | D41: 23 | E41: {=IF($B41="","",IF(TRIM(INDEX('Part 1'!$L$2:$IV$2,1,ROW()-1))=TRIM($B41),INDEX('Part 1'!$L$1250:$IV$1250,1,ROW()-1),"CHECK"))} -> 22 | F41: =IFERROR(D41-E41,"") -> 1 | G41: ='Part 1'!AY30 -> 104 | L41: Desiccant Drier/Filter | M41: PC-20243 | N41: 320 | O41: =IF($L41="","",IF(TRIM(INDEX('Part 4'!$E$2:$AY$2,1,ROW()-1))=TRIM($L41),INDEX('Part 4'!$E$778:$AY$778,1,ROW()-1),"CHECK")) -> 270 | P41: =IFERROR(N41-O41,"") -> 50 | Q41: ='Part 4'!AR20 -> 2500 | T41: TEMPO TRAVELLER | U41: SD330PL/TT | V41: 10 | W41: =IFERROR('Part 7'!FU690+0,0) -> 10 | X41: =IFERROR(V41-W41,"") -> 0 | Y41: ='Part 7'!FU18 -> 197 | AA41: MARUTI ALTO & WAGON R SUCTION HOSE | AB41: PC-133 | AC41: 0 | AD41: =IF($AB41="","",IF(TRIM(INDEX('Part 8'!$F$2:$IV$2,1,ROW()-1))=TRIM($AB41),INDEX('Part 8'!$F$244:$IV$244,1,ROW()-1),"CHECK")) -> 0 | AE41: =IFERROR(AC41-AD41,"") -> 0 | AF41: ='Part 8'!AS9 -> 0
B42: CRETA-DSL-Q5 | C42: PC-86805-Q5 | D42: 0 | E42: {=IF($B42="","",IF(TRIM(INDEX('Part 1'!$L$2:$IV$2,1,ROW()-1))=TRIM($B42),INDEX('Part 1'!$L$1250:$IV$1250,1,ROW()-1),"CHECK"))} -> 0 | F42: =IFERROR(D42-E42,"") -> 0 | G42: ='Part 1'!AZ30 -> 100 | L42: DEV'S CUSTOMER | M42: PC-80007 | N42: 0 | O42: =IF($L42="","",IF(TRIM(INDEX('Part 4'!$E$2:$AY$2,1,ROW()-1))=TRIM($L42),INDEX('Part 4'!$E$778:$AY$778,1,ROW()-1),"CHECK")) -> 0 | P42: =IFERROR(N42-O42,"") -> 0 | Q42: ='Part 4'!AS20 -> 0 | T42: IKON 1.8 DSL | U42: SD322PL/IKON DSL 1.8 | V42: 10 | W42: =IFERROR('Part 7'!FV690+0,0) -> 10 | X42: =IFERROR(V42-W42,"") -> 0 | Y42: ='Part 7'!FV18 -> -16 | AA42: MARUTI ALTO SUCTION HOSE N/M | AB42: PC-133A | AC42: 0 | AD42: =IF($AB42="","",IF(TRIM(INDEX('Part 8'!$F$2:$IV$2,1,ROW()-1))=TRIM($AB42),INDEX('Part 8'!$F$244:$IV$244,1,ROW()-1),"CHECK")) -> 0 | AE42: =IFERROR(AC42-AD42,"") -> 0 | AF42: ='Part 8'!AT9 -> 0
B43: CRETA-PTL | C43: PC-86806 | D43: 13 | E43: {=IF($B43="","",IF(TRIM(INDEX('Part 1'!$L$2:$IV$2,1,ROW()-1))=TRIM($B43),INDEX('Part 1'!$L$1250:$IV$1250,1,ROW()-1),"CHECK"))} -> 12 | F43: =IFERROR(D43-E43,"") -> 1 | G43: ='Part 1'!BA30 -> 47 | L43: DEV'S CUSTOMER | M43: PC-62130 | N43: 0 | O43: =IF($L43="","",IF(TRIM(INDEX('Part 4'!$E$2:$AY$2,1,ROW()-1))=TRIM($L43),INDEX('Part 4'!$E$778:$AY$778,1,ROW()-1),"CHECK")) -> 0 | P43: =IFERROR(N43-O43,"") -> 0 | Q43: ='Part 4'!AT20 -> 0 | T43: TAVERA | U43: SD331PL/TVR | V43: 0 | W43: =IFERROR('Part 7'!FW690+0,0) -> 0 | X43: =IFERROR(V43-W43,"") -> 0 | Y43: ='Part 7'!FW18 -> 144 | AA43: MARUTI ALTO & WAGON R DISCHARGE HOSE | AB43: PC-134 | AC43: 0 | AD43: =IF($AB43="","",IF(TRIM(INDEX('Part 8'!$F$2:$IV$2,1,ROW()-1))=TRIM($AB43),INDEX('Part 8'!$F$244:$IV$244,1,ROW()-1),"CHECK")) -> 0 | AE43: =IFERROR(AC43-AD43,"") -> 0 | AF43: ='Part 8'!AU9 -> 0
B44: CRETA-PTL-Q5 | C44: PC-86806Q5 | D44: 0 | E44: {=IF($B44="","",IF(TRIM(INDEX('Part 1'!$L$2:$IV$2,1,ROW()-1))=TRIM($B44),INDEX('Part 1'!$L$1250:$IV$1250,1,ROW()-1),"CHECK"))} -> 0 | F44: =IFERROR(D44-E44,"") -> 0 | G44: ='Part 1'!BB30 -> 50 | L44: DEV'S CUSTOMER | M44: PC-9001 | N44: 0 | O44: =IF($L44="","",IF(TRIM(INDEX('Part 4'!$E$2:$AY$2,1,ROW()-1))=TRIM($L44),INDEX('Part 4'!$E$778:$AY$778,1,ROW()-1),"CHECK")) -> 0 | P44: =IFERROR(N44-O44,"") -> 0 | Q44: ='Part 4'!AU20 -> 0 | T44: XYLO BIG | U44: SD333PL/XYLO-B | V44: 32 | W44: =IFERROR('Part 7'!FX690+0,0) -> 25 | X44: =IFERROR(V44-W44,"") -> 7 | Y44: ='Part 7'!FX18 -> 152 | AA44: MARUTI ALTO & WAGON R DISCHARGE HOSE VX | AB44: PC-135 | AC44: 0 | AD44: =IF($AB44="","",IF(TRIM(INDEX('Part 8'!$F$2:$IV$2,1,ROW()-1))=TRIM($AB44),INDEX('Part 8'!$F$244:$IV$244,1,ROW()-1),"CHECK")) -> 0 | AE44: =IFERROR(AC44-AD44,"") -> 0 | AF44: ='Part 8'!AV9 -> 0
B45: CRUZE BIG | C45: PCP-C86556 | D45: 51 | E45: {=IF($B45="","",IF(TRIM(INDEX('Part 1'!$L$2:$IV$2,1,ROW()-1))=TRIM($B45),INDEX('Part 1'!$L$1250:$IV$1250,1,ROW()-1),"CHECK"))} -> 43 | F45: =IFERROR(D45-E45,"") -> 8 | G45: ='Part 1'!BC30 -> 224 | L45: DEV'S CUSTOMER | M45: PC-9003 | N45: 0 | O45: =IF($L45="","",IF(TRIM(INDEX('Part 4'!$E$2:$AY$2,1,ROW()-1))=TRIM($L45),INDEX('Part 4'!$E$778:$AY$778,1,ROW()-1),"CHECK")) -> 0 | P45: =IFERROR(N45-O45,"") -> 0 | Q45: ='Part 4'!AV20 -> 125 | T45: JAZZ | V45: 3 | W45: =IFERROR('Part 7'!FY690+0,0) -> 0 | X45: =IFERROR(V45-W45,"") -> 3 | Y45: ='Part 7'!FY18 -> 65 | AA45: MARUTI WAGON R SUCTION HOSE | AB45: PC-136 | AC45: 0 | AD45: =IF($AB45="","",IF(TRIM(INDEX('Part 8'!$F$2:$IV$2,1,ROW()-1))=TRIM($AB45),INDEX('Part 8'!$F$244:$IV$244,1,ROW()-1),"CHECK")) -> 0 | AE45: =IFERROR(AC45-AD45,"") -> 0 | AF45: ='Part 8'!AW9 -> 0
B46: CRUZE-SMALL | C46: PC-86555 | D46: 0 | E46: {=IF($B46="","",IF(TRIM(INDEX('Part 1'!$L$2:$IV$2,1,ROW()-1))=TRIM($B46),INDEX('Part 1'!$L$1250:$IV$1250,1,ROW()-1),"CHECK"))} -> 0 | F46: =IFERROR(D46-E46,"") -> 0 | G46: ='Part 1'!BD30 -> 0 | L46: DEV'S CUSTOMER | M46: PC-62208 | N46: 0 | O46: =IF($L46="","",IF(TRIM(INDEX('Part 4'!$E$2:$AY$2,1,ROW()-1))=TRIM($L46),INDEX('Part 4'!$E$778:$AY$778,1,ROW()-1),"CHECK")) -> 0 | P46: =IFERROR(N46-O46,"") -> 0 | Q46: ='Part 4'!AW20 -> 0 | T46: XYLO D2 | U46: SD335PL/XYLO D2 | V46: 25 | W46: =IFERROR('Part 7'!FZ690+0,0) -> 23 | X46: =IFERROR(V46-W46,"") -> 2 | Y46: ='Part 7'!FZ18 -> 968 | AA46: MARUTI ALTO & WAGON R LIQUID HOSE RD TO COIL | AB46: PC-137 | AC46: 0 | AD46: =IF($AB46="","",IF(TRIM(INDEX('Part 8'!$F$2:$IV$2,1,ROW()-1))=TRIM($AB46),INDEX('Part 8'!$F$244:$IV$244,1,ROW()-1),"CHECK")) -> 0 | AE46: =IFERROR(AC46-AD46,"") -> 0 | AF46: ='Part 8'!AX9 -> 0
B47: DEV'S CUSTOMER-KAMATSU | C47: pc-86907-26MM-8MM | D47: 0 | E47: {=IF($B47="","",IF(TRIM(INDEX('Part 1'!$L$2:$IV$2,1,ROW()-1))=TRIM($B47),INDEX('Part 1'!$L$1250:$IV$1250,1,ROW()-1),"CHECK"))} -> 0 | F47: =IFERROR(D47-E47,"") -> 0 | G47: ='Part 1'!BE30 -> 110 | L47: DEV'S CUSTOMER | M47: PC-9005 | N47: 0 | O47: =IF($L47="","",IF(TRIM(INDEX('Part 4'!$E$2:$AY$2,1,ROW()-1))=TRIM($L47),INDEX('Part 4'!$E$778:$AY$778,1,ROW()-1),"CHECK")) -> 0 | P47: =IFERROR(N47-O47,"") -> 0 | Q47: ='Part 4'!AX20 -> 100 | T47: ETIOS DSL | U47: SD336PL/ETOS-DSL | V47: 165 | W47: =IFERROR('Part 7'!GA690+0,0) -> 137 | X47: =IFERROR(V47-W47,"") -> 28 | Y47: ='Part 7'!GA18 -> 1184 | AA47: MARUTI ALTO & WAGON R LIQUID TUBE RD TO COND | AB47: PC-138 | AC47: 20 | AD47: =IF($AB47="","",IF(TRIM(INDEX('Part 8'!$F$2:$IV$2,1,ROW()-1))=TRIM($AB47),INDEX('Part 8'!$F$244:$IV$244,1,ROW()-1),"CHECK")) -> 23 | AE47: =IFERROR(AC47-AD47,"") -> -3 | AF47: ='Part 8'!AY9 -> 0
B48: DEV'S CUSTOMER-VOLVO 14645543 | C48: PC-86808-Q5 | D48: 0 | E48: {=IF($B48="","",IF(TRIM(INDEX('Part 1'!$L$2:$IV$2,1,ROW()-1))=TRIM($B48),INDEX('Part 1'!$L$1250:$IV$1250,1,ROW()-1),"CHECK"))} -> 0 | F48: =IFERROR(D48-E48,"") -> 0 | G48: ='Part 1'!BF30 -> 50 | L48: DEV'S CUSTOMER | M48: PC-9006 | N48: 0 | O48: =IF($L48="","",IF(TRIM(INDEX('Part 4'!$E$2:$AY$2,1,ROW()-1))=TRIM($L48),INDEX('Part 4'!$E$778:$AY$778,1,ROW()-1),"CHECK")) -> 0 | P48: =IFERROR(N48-O48,"") -> 0 | Q48: ='Part 4'!AY20 -> 100 | T48: LOGAN DSL | U48: SD338PL/LGN DSL | V48: 58 | W48: =IFERROR('Part 7'!GB690+0,0) -> 41 | X48: =IFERROR(V48-W48,"") -> 17 | Y48: ='Part 7'!GB18 -> 128 | AA48: MARUTI ALTO SDN SUCTION HOSE | AB48: PC-139 | AC48: 0 | AD48: =IF($AB48="","",IF(TRIM(INDEX('Part 8'!$F$2:$IV$2,1,ROW()-1))=TRIM($AB48),INDEX('Part 8'!$F$244:$IV$244,1,ROW()-1),"CHECK")) -> 0 | AE48: =IFERROR(AC48-AD48,"") -> 0 | AF48: ='Part 8'!AZ9 -> 0
B49: DEV'S CUSTOMERKOMATSU 2000 | C49: PC-86814 | D49: 50 | E49: {=IF($B49="","",IF(TRIM(INDEX('Part 1'!$L$2:$IV$2,1,ROW()-1))=TRIM($B49),INDEX('Part 1'!$L$1250:$IV$1250,1,ROW()-1),"CHECK"))} -> 50 | F49: =IFERROR(D49-E49,"") -> 0 | G49: ='Part 1'!BG30 -> 50 | T49: POLO | V49: 15 | W49: =IFERROR('Part 7'!GC690+0,0) -> 10 | X49: =IFERROR(V49-W49,"") -> 5 | Y49: ='Part 7'!GC18 -> 264 | AA49: MARUTI ALTO SUCTION HESSE SDN | AB49: PC-140 | AC49: 0 | AD49: =IF($AB49="","",IF(TRIM(INDEX('Part 8'!$F$2:$IV$2,1,ROW()-1))=TRIM($AB49),INDEX('Part 8'!$F$244:$IV$244,1,ROW()-1),"CHECK")) -> 0 | AE49: =IFERROR(AC49-AD49,"") -> 0 | AF49: ='Part 8'!BA9 -> 0
B50: DUSTER / TERRANO-110CC | C50: PC-86920 | D50: 69 | E50: {=IF($B50="","",IF(TRIM(INDEX('Part 1'!$L$2:$IV$2,1,ROW()-1))=TRIM($B50),INDEX('Part 1'!$L$1250:$IV$1250,1,ROW()-1),"CHECK"))} -> 50 | F50: =IFERROR(D50-E50,"") -> 19 | G50: ='Part 1'!BH30 -> 305 | K50: COMPRESSOR | L50: 505 | N50: 0 | O50: =IF($L50="","",IF(TRIM(INDEX('Part 4'!$E$2:$IV$2,1,ROW()-1))=TRIM($L50&""),INDEX('Part 4'!$E$778:$IV$778,1,ROW()-1),"CHECK")) -> 0 | P50: =IFERROR(N50-O50,"") -> 0 | Q50: ='Part 4'!BA20 -> 24 | T50: INDICA VISTA SUBROS 7PK | U50: SD340PL/INDSUB7PK | V50: 25 | W50: =IFERROR('Part 7'!GD690+0,0) -> 25 | X50: =IFERROR(V50-W50,"") -> 0 | Y50: ='Part 7'!GD18 -> 238 | AA50: MARUTI ALTO SDN DISCHARGE HOSE | AB50: PC-141 | AC50: 0 | AD50: =IF($AB50="","",IF(TRIM(INDEX('Part 8'!$F$2:$IV$2,1,ROW()-1))=TRIM($AB50),INDEX('Part 8'!$F$244:$IV$244,1,ROW()-1),"CHECK")) -> 0 | AE50: =IFERROR(AC50-AD50,"") -> 0 | AF50: ='Part 8'!BB9 -> 0
B51: DUSTER / TERRANO-110CC-Q5 | C51: PC-86920A-Q5 | D51: 0 | E51: {=IF($B51="","",IF(TRIM(INDEX('Part 1'!$L$2:$IV$2,1,ROW()-1))=TRIM($B51),INDEX('Part 1'!$L$1250:$IV$1250,1,ROW()-1),"CHECK"))} -> 0 | F51: =IFERROR(D51-E51,"") -> 0 | G51: ='Part 1'!BI30 -> 50 | L51: 507 | N51: 31 | O51: =IF($L51="","",IF(TRIM(INDEX('Part 4'!$E$2:$IV$2,1,ROW()-1))=TRIM($L51&""),INDEX('Part 4'!$E$778:$IV$778,1,ROW()-1),"CHECK")) -> 33 | P51: =IFERROR(N51-O51,"") -> -2 | Q51: ='Part 4'!BB20 -> 528 | T51: ZEN ESTILO | V51: 3 | W51: =IFERROR('Part 7'!GE690+0,0) -> 3 | X51: =IFERROR(V51-W51,"") -> 0 | Y51: ='Part 7'!GE18 -> 243 | AA51: MARUTI ALTO SDN DISCHARGE HOSE WITH CHARGING VALVE | AB51: PC-142 | AC51: 0 | AD51: =IF($AB51="","",IF(TRIM(INDEX('Part 8'!$F$2:$IV$2,1,ROW()-1))=TRIM($AB51),INDEX('Part 8'!$F$244:$IV$244,1,ROW()-1),"CHECK")) -> 0 | AE51: =IFERROR(AC51-AD51,"") -> 0 | AF51: ='Part 8'!BC9 -> 0
B52: DUSTER / TERRANO-85CC | C52: PC-86428 | D52: 107 | E52: {=IF($B52="","",IF(TRIM(INDEX('Part 1'!$L$2:$IV$2,1,ROW()-1))=TRIM($B52),INDEX('Part 1'!$L$1250:$IV$1250,1,ROW()-1),"CHECK"))} -> 76 | F52: =IFERROR(D52-E52,"") -> 31 | G52: ='Part 1'!BJ30 -> 359 | L52: 507-MG | N52: 0 | O52: =IF($L52="","",IF(TRIM(INDEX('Part 4'!$E$2:$IV$2,1,ROW()-1))=TRIM($L52&""),INDEX('Part 4'!$E$778:$IV$778,1,ROW()-1),"CHECK")) -> 115 | P52: =IFERROR(N52-O52,"") -> -115 | Q52: ='Part 4'!BC20 -> 168 | T52: FIGO | V52: 42 | W52: =IFERROR('Part 7'!GF690+0,0) -> 28 | X52: =IFERROR(V52-W52,"") -> 14 | Y52: ='Part 7'!GF18 -> 596 | AA52: MARUTI ALTO SA,IDAN DISCHARGE HOSE | AB52: PC-143 | AC52: 0 | AD52: =IF($AB52="","",IF(TRIM(INDEX('Part 8'!$F$2:$IV$2,1,ROW()-1))=TRIM($AB52),INDEX('Part 8'!$F$244:$IV$244,1,ROW()-1),"CHECK")) -> 0 | AE52: =IFERROR(AC52-AD52,"") -> 0 | AF52: ='Part 8'!BD9 -> 0
B53: DUSTER / TERRANO-85CC-Q5 | C53: PC-86428-Q5 | D53: 2 | E53: {=IF($B53="","",IF(TRIM(INDEX('Part 1'!$L$2:$IV$2,1,ROW()-1))=TRIM($B53),INDEX('Part 1'!$L$1250:$IV$1250,1,ROW()-1),"CHECK"))} -> 2 | F53: =IFERROR(D53-E53,"") -> 0 | G53: ='Part 1'!BK30 -> 145 | L53: 508 | N53: 0 | O53: =IF($L53="","",IF(TRIM(INDEX('Part 4'!$E$2:$IV$2,1,ROW()-1))=TRIM($L53&""),INDEX('Part 4'!$E$778:$IV$778,1,ROW()-1),"CHECK")) -> 22 | P53: =IFERROR(N53-O53,"") -> -22 | Q53: ='Part 4'!BD20 -> 578 | T53: IND.MMC | V53: 8 | W53: =IFERROR('Part 7'!GG690+0,0) -> 4 | X53: =IFERROR(V53-W53,"") -> 4 | Y53: ='Part 7'!GG18 -> 201 | AA53: MARUTI ALTO SDN LIQUID HOSE RD TO COIL | AB53: PC-144 | AC53: 0 | AD53: =IF($AB53="","",IF(TRIM(INDEX('Part 8'!$F$2:$IV$2,1,ROW()-1))=TRIM($AB53),INDEX('Part 8'!$F$244:$IV$244,1,ROW()-1),"CHECK")) -> 0 | AE53: =IFERROR(AC53-AD53,"") -> 0 | AF53: ='Part 8'!BE9 -> 0
B54: ECOSPORT-DSL SMALL HOLE | C54: PC-86911B | D54: 0 | E54: {=IF($B54="","",IF(TRIM(INDEX('Part 1'!$L$2:$IV$2,1,ROW()-1))=TRIM($B54),INDEX('Part 1'!$L$1250:$IV$1250,1,ROW()-1),"CHECK"))} -> 0 | F54: =IFERROR(D54-E54,"") -> 0 | G54: ='Part 1'!BL30 -> 0 | L54: 508-MG | N54: 0 | O54: =IF($L54="","",IF(TRIM(INDEX('Part 4'!$E$2:$IV$2,1,ROW()-1))=TRIM($L54&""),INDEX('Part 4'!$E$778:$IV$778,1,ROW()-1),"CHECK")) -> 21 | P54: =IFERROR(N54-O54,"") -> -21 | Q54: ='Part 4'!BE20 -> 256 | T54: INNOVA SINGLE | U54: SD343PL/INNOVA (S) | V54: 55 | W54: =IFERROR('Part 7'!GH690+0,0) -> 51 | X54: =IFERROR(V54-W54,"") -> 4 | Y54: ='Part 7'!GH18 -> 554 | AA54: MARUTI ALTC SDN LIQUID TUBE RD TO COND | AB54: PC-145 | AC54: 0 | AD54: =IF($AB54="","",IF(TRIM(INDEX('Part 8'!$F$2:$IV$2,1,ROW()-1))=TRIM($AB54),INDEX('Part 8'!$F$244:$IV$244,1,ROW()-1),"CHECK")) -> 0 | AE54: =IFERROR(AC54-AD54,"") -> 0 | AF54: ='Part 8'!BF9 -> 0
B55: ECOSPORT-DSL-Q5 SMALL HOLE | C55: PC-86911BQ5 | D55: 0 | E55: {=IF($B55="","",IF(TRIM(INDEX('Part 1'!$L$2:$IV$2,1,ROW()-1))=TRIM($B55),INDEX('Part 1'!$L$1250:$IV$1250,1,ROW()-1),"CHECK"))} -> 0 | F55: =IFERROR(D55-E55,"") -> 0 | G55: ='Part 1'!BM30 -> 0 | L55: 510 | N55: 0 | O55: =IF($L55="","",IF(TRIM(INDEX('Part 4'!$E$2:$IV$2,1,ROW()-1))=TRIM($L55&""),INDEX('Part 4'!$E$778:$IV$778,1,ROW()-1),"CHECK")) -> 5 | P55: =IFERROR(N55-O55,"") -> -5 | Q55: ='Part 4'!BF20 -> 98 | T55: INNOVA DUAL | V55: 109 | W55: =IFERROR('Part 7'!GI690+0,0) -> 95 | X55: =IFERROR(V55-W55,"") -> 14 | Y55: ='Part 7'!GI18 -> 591 | AA55: MARUTI ESTEEM SUCTION HOSE LX R12 PTL | AB55: PC-146 | AC55: 0 | AD55: =IF($AB55="","",IF(TRIM(INDEX('Part 8'!$F$2:$IV$2,1,ROW()-1))=TRIM($AB55),INDEX('Part 8'!$F$244:$IV$244,1,ROW()-1),"CHECK")) -> 10 | AE55: =IFERROR(AC55-AD55,"") -> -10 | AF55: ='Part 8'!BG9 -> 0
B56: ECOSPORT-PTL | C56: PC-86912 | D56: 15 | E56: {=IF($B56="","",IF(TRIM(INDEX('Part 1'!$L$2:$IV$2,1,ROW()-1))=TRIM($B56),INDEX('Part 1'!$L$1250:$IV$1250,1,ROW()-1),"CHECK"))} -> 10 | F56: =IFERROR(D56-E56,"") -> 5 | G56: ='Part 1'!BN30 -> 96 | L56: INNOVA DUAL | M56: PC-4714 | N56: 9 | O56: =IF($L56="","",IF(TRIM(INDEX('Part 4'!$E$2:$IV$2,1,ROW()-1))=TRIM($L56&""),INDEX('Part 4'!$E$778:$IV$778,1,ROW()-1),"CHECK")) -> 6 | P56: =IFERROR(N56-O56,"") -> 3 | Q56: ='Part 4'!BG20 -> 71 | T56: BEAT | V56: 0 | W56: =IFERROR('Part 7'!GJ690+0,0) -> 0 | X56: =IFERROR(V56-W56,"") -> 0 | Y56: ='Part 7'!GJ18 -> 200 | AA56: MARUTI ESTEEM SUCTION HOSE VX R12 PTL | AB56: PC-147 | AC56: 0 | AD56: =IF($AB56="","",IF(TRIM(INDEX('Part 8'!$F$2:$IV$2,1,ROW()-1))=TRIM($AB56),INDEX('Part 8'!$F$244:$IV$244,1,ROW()-1),"CHECK")) -> 8 | AE56: =IFERROR(AC56-AD56,"") -> -8 | AF56: ='Part 8'!BH9 -> 0
B57: ELANTRA | C57: PC-86066 | D57: 3 | E57: {=IF($B57="","",IF(TRIM(INDEX('Part 1'!$L$2:$IV$2,1,ROW()-1))=TRIM($B57),INDEX('Part 1'!$L$1250:$IV$1250,1,ROW()-1),"CHECK"))} -> 0 | F57: =IFERROR(D57-E57,"") -> 3 | G57: ='Part 1'!BO30 -> 95 | L57: INNOVA SINGLE | N57: 0 | O57: =IF($L57="","",IF(TRIM(INDEX('Part 4'!$E$2:$IV$2,1,ROW()-1))=TRIM($L57&""),INDEX('Part 4'!$E$778:$IV$778,1,ROW()-1),"CHECK")) -> 1 | P57: =IFERROR(N57-O57,"") -> -1 | Q57: ='Part 4'!BH20 -> 39 | T57: ALTO 800 | V57: 24 | W57: =IFERROR('Part 7'!GK690+0,0) -> 24 | X57: =IFERROR(V57-W57,"") -> 0 | Y57: ='Part 7'!GK18 -> 189 | AA57: MARUTI ESTEEM DISCHARGE HOSE PTL R12 LX | AB57: PC-148 | AC57: 0 | AD57: =IF($AB57="","",IF(TRIM(INDEX('Part 8'!$F$2:$IV$2,1,ROW()-1))=TRIM($AB57),INDEX('Part 8'!$F$244:$IV$244,1,ROW()-1),"CHECK")) -> 0 | AE57: =IFERROR(AC57-AD57,"") -> 0 | AF57: ='Part 8'!BI9 -> 0
B58: ENDEAOUR | C58: PC-86277 | D58: 3 | E58: {=IF($B58="","",IF(TRIM(INDEX('Part 1'!$L$2:$IV$2,1,ROW()-1))=TRIM($B58),INDEX('Part 1'!$L$1250:$IV$1250,1,ROW()-1),"CHECK"))} -> 2 | F58: =IFERROR(D58-E58,"") -> 1 | G58: ='Part 1'!BP30 -> 13 | L58: SKODA OCTIVA | M58: PC-0202 | N58: 0 | O58: =IF($L58="","",IF(TRIM(INDEX('Part 4'!$E$2:$IV$2,1,ROW()-1))=TRIM($L58&""),INDEX('Part 4'!$E$778:$IV$778,1,ROW()-1),"CHECK")) -> 0 | P58: =IFERROR(N58-O58,"") -> 0 | Q58: ='Part 4'!BI20 -> -14 | T58: I-10 GRAND | V58: 2 | W58: =IFERROR('Part 7'!GL690+0,0) -> 2 | X58: =IFERROR(V58-W58,"") -> 0 | Y58: ='Part 7'!GL18 -> 200 | AA58: MARUTI ESTEEM DISCHARGE HOSE PTL R12 VX | AB58: PC-149 | AC58: 0 | AD58: =IF($AB58="","",IF(TRIM(INDEX('Part 8'!$F$2:$IV$2,1,ROW()-1))=TRIM($AB58),INDEX('Part 8'!$F$244:$IV$244,1,ROW()-1),"CHECK")) -> 0 | AE58: =IFERROR(AC58-AD58,"") -> 0 | AF58: ='Part 8'!BJ9 -> 0
B59: ENDEAOUR-Q5 | C59: PC-86277-Q5 | D59: 27 | E59: {=IF($B59="","",IF(TRIM(INDEX('Part 1'!$L$2:$IV$2,1,ROW()-1))=TRIM($B59),INDEX('Part 1'!$L$1250:$IV$1250,1,ROW()-1),"CHECK"))} -> 16 | F59: =IFERROR(D59-E59,"") -> 11 | G59: ='Part 1'!BQ30 -> 171 | L59: EARTH MOVING MACH COMP | M59: PC-8202 | N59: 0 | O59: =IF($L59="","",IF(TRIM(INDEX('Part 4'!$E$2:$IV$2,1,ROW()-1))=TRIM($L59&""),INDEX('Part 4'!$E$778:$IV$778,1,ROW()-1),"CHECK")) -> 0 | P59: =IFERROR(N59-O59,"") -> 0 | Q59: ='Part 4'!BJ20 -> -67 | T59: SWIFT NEW 2012 | V59: 20 | W59: =IFERROR('Part 7'!GM690+0,0) -> 20 | X59: =IFERROR(V59-W59,"") -> 0 | Y59: ='Part 7'!GM18 -> 187 | AA59: MARUTI ESTEEM LIQUID TUBE PTL R12 RD TO COND | AB59: PC-150 | AC59: 0 | AD59: =IF($AB59="","",IF(TRIM(INDEX('Part 8'!$F$2:$IV$2,1,ROW()-1))=TRIM($AB59),INDEX('Part 8'!$F$244:$IV$244,1,ROW()-1),"CHECK")) -> 0 | AE59: =IFERROR(AC59-AD59,"") -> 0 | AF59: ='Part 8'!BK9 -> 0
B60: ENJOY DSL | C60: PC-86201 | D60: 135 | E60: {=IF($B60="","",IF(TRIM(INDEX('Part 1'!$L$2:$IV$2,1,ROW()-1))=TRIM($B60),INDEX('Part 1'!$L$1250:$IV$1250,1,ROW()-1),"CHECK"))} -> 110 | F60: =IFERROR(D60-E60,"") -> 25 | G60: ='Part 1'!BR30 -> 579 | L60: SANDEN 7PISTON 508/510 | M60: PC-5036 | N60: 11 | O60: =IF($L60="","",IF(TRIM(INDEX('Part 4'!$E$2:$IV$2,1,ROW()-1))=TRIM($L60&""),INDEX('Part 4'!$E$778:$IV$778,1,ROW()-1),"CHECK")) -> 4 | P60: =IFERROR(N60-O60,"") -> 7 | Q60: ='Part 4'!BK20 -> 142 | T60: XUV 500 | U60: SD346PL/MX5 | V60: 40 | W60: =IFERROR('Part 7'!GN690+0,0) -> 30 | X60: =IFERROR(V60-W60,"") -> 10 | Y60: ='Part 7'!GN18 -> 670 | AA60: MARUTI ESTEEM R12 PTL LIQUID TUBE RD TO JOINT | AB60: PC-151 | AC60: 0 | AD60: =IF($AB60="","",IF(TRIM(INDEX('Part 8'!$F$2:$IV$2,1,ROW()-1))=TRIM($AB60),INDEX('Part 8'!$F$244:$IV$244,1,ROW()-1),"CHECK")) -> 0 | AE60: =IFERROR(AC60-AD60,"") -> 0 | AF60: ='Part 8'!BL9 -> 0
B61: ENJOY DSL-Q5 | C61: PC-86201-Q5 | D61: 12 | E61: {=IF($B61="","",IF(TRIM(INDEX('Part 1'!$L$2:$IV$2,1,ROW()-1))=TRIM($B61),INDEX('Part 1'!$L$1250:$IV$1250,1,ROW()-1),"CHECK"))} -> 12 | F61: =IFERROR(D61-E61,"") -> 0 | G61: ='Part 1'!BS30 -> 39 | L61: BOLERO SANDEN | M61: PC-5302 | N61: 13 | O61: =IF($L61="","",IF(TRIM(INDEX('Part 4'!$E$2:$IV$2,1,ROW()-1))=TRIM($L61&""),INDEX('Part 4'!$E$778:$IV$778,1,ROW()-1),"CHECK")) -> 12 | P61: =IFERROR(N61-O61,"") -> 1 | Q61: ='Part 4'!BL20 -> 64 | T61: VISTA SUBROS-5PK | U61: SD347PL/V.S 5PK | V61: 37 | W61: =IFERROR('Part 7'!GO690+0,0) -> 34 | X61: =IFERROR(V61-W61,"") -> 3 | Y61: ='Part 7'!GO18 -> 250 | AA61: MARUTI ESTEEM R12 PTL LIQUID TUBE JOINT TO C. COIL | AB61: PC-152 | AC61: 0 | AD61: =IF($AB61="","",IF(TRIM(INDEX('Part 8'!$F$2:$IV$2,1,ROW()-1))=TRIM($AB61),INDEX('Part 8'!$F$244:$IV$244,1,ROW()-1),"CHECK")) -> 0 | AE61: =IFERROR(AC61-AD61,"") -> 0 | AF61: ='Part 8'!BM9 -> 0
B62: ENJOY PTL | C62: PC-86202 | D62: 20 | E62: {=IF($B62="","",IF(TRIM(INDEX('Part 1'!$L$2:$IV$2,1,ROW()-1))=TRIM($B62),INDEX('Part 1'!$L$1250:$IV$1250,1,ROW()-1),"CHECK"))} -> 18 | F62: =IFERROR(D62-E62,"") -> 2 | G62: ='Part 1'!BT30 -> 220 | L62: ETIOS | M62: PC-5008 | N62: 0 | O62: =IF($L62="","",IF(TRIM(INDEX('Part 4'!$E$2:$IV$2,1,ROW()-1))=TRIM($L62&""),INDEX('Part 4'!$E$778:$IV$778,1,ROW()-1),"CHECK")) -> 0 | P62: =IFERROR(N62-O62,"") -> 0 | Q62: ='Part 4'!BM20 -> 2 | T62: SANDEN 4745 | U62: SDN/351PL/S-1 | V62: 0 | W62: =IFERROR('Part 7'!GP690+0,0) -> 0 | X62: =IFERROR(V62-W62,"") -> 0 | Y62: ='Part 7'!GP18 -> 0 | AA62: MARUTI ESTEEM R12 PTL SUCTION TUBE C COIL | AB62: PC-153 | AC62: 0 | AD62: =IF($AB62="","",IF(TRIM(INDEX('Part 8'!$F$2:$IV$2,1,ROW()-1))=TRIM($AB62),INDEX('Part 8'!$F$244:$IV$244,1,ROW()-1),"CHECK")) -> 0 | AE62: =IFERROR(AC62-AD62,"") -> 0 | AF62: ='Part 8'!BN9 -> 0
B63: ENJOY PTL-Q5 | C63: PC-86202Q5 | D63: 0 | E63: {=IF($B63="","",IF(TRIM(INDEX('Part 1'!$L$2:$IV$2,1,ROW()-1))=TRIM($B63),INDEX('Part 1'!$L$1250:$IV$1250,1,ROW()-1),"CHECK"))} -> 0 | F63: =IFERROR(D63-E63,"") -> 0 | G63: ='Part 1'!BU30 -> 25 | L63: I-10 KAPPA | M63: PC-6008 | N63: 71 | O63: =IF($L63="","",IF(TRIM(INDEX('Part 4'!$E$2:$IV$2,1,ROW()-1))=TRIM($L63&""),INDEX('Part 4'!$E$778:$IV$778,1,ROW()-1),"CHECK")) -> 34 | P63: =IFERROR(N63-O63,"") -> 37 | Q63: ='Part 4'!BN20 -> 126 | T63: CRUZE | U63: SD350PL/CRZ | V63: 36 | W63: =IFERROR('Part 7'!GQ690+0,0) -> 36 | X63: =IFERROR(V63-W63,"") -> 0 | Y63: ='Part 7'!GQ18 -> 95 | AA63: MARUTI ESTEEM DSL R12 SUCTION HOSE | AB63: PC-154 | AC63: 0 | AD63: =IF($AB63="","",IF(TRIM(INDEX('Part 8'!$F$2:$IV$2,1,ROW()-1))=TRIM($AB63),INDEX('Part 8'!$F$244:$IV$244,1,ROW()-1),"CHECK")) -> 0 | AE63: =IFERROR(AC63-AD63,"") -> 0 | AF63: ='Part 8'!BO9 -> 0
B64: EON | C64: PC-86617 | D64: 110 | E64: {=IF($B64="","",IF(TRIM(INDEX('Part 1'!$L$2:$IV$2,1,ROW()-1))=TRIM($B64),INDEX('Part 1'!$L$1250:$IV$1250,1,ROW()-1),"CHECK"))} -> 105 | F64: =IFERROR(D64-E64,"") -> 5 | G64: ='Part 1'!BV30 -> 511 | L64: 3600 | M64: PC-3600 | N64: 26 | O64: =IF($L64="","",IF(TRIM(INDEX('Part 4'!$E$2:$IV$2,1,ROW()-1))=TRIM($L64&""),INDEX('Part 4'!$E$778:$IV$778,1,ROW()-1),"CHECK")) -> 11 | P64: =IFERROR(N64-O64,"") -> 15 | Q64: ='Part 4'!BO20 -> 140 | V64: 0 | AA64: MARUTI ESTEEM DSL R12 DISCHARGE HOSE | AB64: PC-155 | AC64: 0 | AD64: =IF($AB64="","",IF(TRIM(INDEX('Part 8'!$F$2:$IV$2,1,ROW()-1))=TRIM($AB64),INDEX('Part 8'!$F$244:$IV$244,1,ROW()-1),"CHECK")) -> 0 | AE64: =IFERROR(AC64-AD64,"") -> 0 | AF64: ='Part 8'!BP9 -> 0
B65: Esteem-134a / Esteem PAD | C65: PC-86090 | D65: 7 | E65: {=IF($B65="","",IF(TRIM(INDEX('Part 1'!$L$2:$IV$2,1,ROW()-1))=TRIM($B65),INDEX('Part 1'!$L$1250:$IV$1250,1,ROW()-1),"CHECK"))} -> 4 | F65: =IFERROR(D65-E65,"") -> 3 | G65: ='Part 1'!BW30 -> 98 | L65: DEV'S CUSTOMER | M65: PC-2827 | N65: 0 | O65: =IF($L65="","",IF(TRIM(INDEX('Part 4'!$E$2:$IV$2,1,ROW()-1))=TRIM($L65&""),INDEX('Part 4'!$E$778:$IV$778,1,ROW()-1),"CHECK")) -> 0 | P65: =IFERROR(N65-O65,"") -> 0 | Q65: ='Part 4'!BP20 -> 56 | V65: 0 | AA65: MARUTI ESTEEM DSL R12 LIQUID TUBE RD TO COND | AB65: PC-156 | AC65: 0 | AD65: =IF($AB65="","",IF(TRIM(INDEX('Part 8'!$F$2:$IV$2,1,ROW()-1))=TRIM($AB65),INDEX('Part 8'!$F$244:$IV$244,1,ROW()-1),"CHECK")) -> 0 | AE65: =IFERROR(AC65-AD65,"") -> 0 | AF65: ='Part 8'!BQ9 -> 0
B66: ESTEEM-R12 | C66: PC-86040 | D66: 0 | E66: {=IF($B66="","",IF(TRIM(INDEX('Part 1'!$L$2:$IV$2,1,ROW()-1))=TRIM($B66),INDEX('Part 1'!$L$1250:$IV$1250,1,ROW()-1),"CHECK"))} -> 0 | F66: =IFERROR(D66-E66,"") -> 0 | G66: ='Part 1'!BX30 -> 22 | L66: DEV'S CUSTOMER | M66: PC-1923 | N66: 0 | O66: =IF($L66="","",IF(TRIM(INDEX('Part 4'!$E$2:$IV$2,1,ROW()-1))=TRIM($L66&""),INDEX('Part 4'!$E$778:$IV$778,1,ROW()-1),"CHECK")) -> 0 | P66: =IFERROR(N66-O66,"") -> 0 | Q66: ='Part 4'!BQ20 -> 60 | V66: 0 | AA66: MARUTI ESTEEM DSL R12 LIQUID TUBE RD TO JOINT | AB66: PC-157 | AC66: 0 | AD66: =IF($AB66="","",IF(TRIM(INDEX('Part 8'!$F$2:$IV$2,1,ROW()-1))=TRIM($AB66),INDEX('Part 8'!$F$244:$IV$244,1,ROW()-1),"CHECK")) -> 0 | AE66: =IFERROR(AC66-AD66,"") -> 0 | AF66: ='Part 8'!BR9 -> 0
B67: ETIOS (DSL) | C67: PC-86580 | D67: 253 | E67: {=IF($B67="","",IF(TRIM(INDEX('Part 1'!$L$2:$IV$2,1,ROW()-1))=TRIM($B67),INDEX('Part 1'!$L$1250:$IV$1250,1,ROW()-1),"CHECK"))} -> 210 | F67: =IFERROR(D67-E67,"") -> 43 | G67: ='Part 1'!BY30 -> 880 | L67: DEV'S CUSTOMER | M67: PC-1113 | N67: 0 | O67: =IF($L67="","",IF(TRIM(INDEX('Part 4'!$E$2:$IV$2,1,ROW()-1))=TRIM($L67&""),INDEX('Part 4'!$E$778:$IV$778,1,ROW()-1),"CHECK")) -> 0 | P67: =IFERROR(N67-O67,"") -> 0 | Q67: ='Part 4'!BR20 -> 64 | S67: PART 7 – CLUTCH SETS | T67: CLUTCH SET WITH BEARING | V67: 0 | W67: =IFERROR('Part 7'!GU690+0,0) -> 0 | X67: =IFERROR(V67-W67,"") -> 0 | Y67: ='Part 7'!GU18 -> 0 | AA67: MARUTI ESTEEM DSL R12 LIQUID TUBE JOINT TO C. COIL | AB67: PC-158 | AC67: 0 | AD67: =IF($AB67="","",IF(TRIM(INDEX('Part 8'!$F$2:$IV$2,1,ROW()-1))=TRIM($AB67),INDEX('Part 8'!$F$244:$IV$244,1,ROW()-1),"CHECK")) -> 0 | AE67: =IFERROR(AC67-AD67,"") -> 0 | AF67: ='Part 8'!BS9 -> 0
B68: ETIOS (PTL) | C68: PC-86656 | D68: 76 | E68: {=IF($B68="","",IF(TRIM(INDEX('Part 1'!$L$2:$IV$2,1,ROW()-1))=TRIM($B68),INDEX('Part 1'!$L$1250:$IV$1250,1,ROW()-1),"CHECK"))} -> 75 | F68: =IFERROR(D68-E68,"") -> 1 | G68: ='Part 1'!BZ30 -> 259 | L68: DEV'S CUSTOMER | M68: PC-4340 | N68: 0 | O68: =IF($L68="","",IF(TRIM(INDEX('Part 4'!$E$2:$IV$2,1,ROW()-1))=TRIM($L68&""),INDEX('Part 4'!$E$778:$IV$778,1,ROW()-1),"CHECK")) -> 0 | P68: =IFERROR(N68-O68,"") -> 0 | Q68: ='Part 4'!BS20 -> 0 | T68: A-STAR / WR-K10 | U68: SDN-003/ASTAR | V68: 0 | W68: =IFERROR('Part 7'!GV690+0,0) -> 0 | X68: =IFERROR(V68-W68,"") -> 0 | Y68: ='Part 7'!GV18 -> -94 | AA68: MARUTI ESTEEM DSL R12 SUCTION TUBE C. COIL | AB68: PC-159 | AC68: 0 | AD68: =IF($AB68="","",IF(TRIM(INDEX('Part 8'!$F$2:$IV$2,1,ROW()-1))=TRIM($AB68),INDEX('Part 8'!$F$244:$IV$244,1,ROW()-1),"CHECK")) -> 0 | AE68: =IFERROR(AC68-AD68,"") -> 0 | AF68: ='Part 8'!BT9 -> 0
B69: ETIOS (PTL)-Q5 | C69: PC-86656Q5 | D69: 10 | E69: {=IF($B69="","",IF(TRIM(INDEX('Part 1'!$L$2:$IV$2,1,ROW()-1))=TRIM($B69),INDEX('Part 1'!$L$1250:$IV$1250,1,ROW()-1),"CHECK"))} -> 10 | F69: =IFERROR(D69-E69,"") -> 0 | G69: ='Part 1'!CA30 -> 45 | L69: DEV'S CUSTOMER | M69: PC-4745 | N69: 0 | O69: =IF($L69="","",IF(TRIM(INDEX('Part 4'!$E$2:$IV$2,1,ROW()-1))=TRIM($L69&""),INDEX('Part 4'!$E$778:$IV$778,1,ROW()-1),"CHECK")) -> 0 | P69: =IFERROR(N69-O69,"") -> 0 | Q69: ='Part 4'!BT20 -> 59 | T69: ACCENT | U69: SDN-010/ACCENT-CRDi | V69: 0 | W69: =IFERROR('Part 7'!GW690+0,0) -> 0 | X69: =IFERROR(V69-W69,"") -> 0 | Y69: ='Part 7'!GW18 -> 120 | AA69: MARUTI ESTEEM PTL R134A SUCTION HOSE LX | AB69: PC-160 | AC69: 0 | AD69: =IF($AB69="","",IF(TRIM(INDEX('Part 8'!$F$2:$IV$2,1,ROW()-1))=TRIM($AB69),INDEX('Part 8'!$F$244:$IV$244,1,ROW()-1),"CHECK")) -> 5 | AE69: =IFERROR(AC69-AD69,"") -> -5 | AF69: ='Part 8'!BU9 -> 0
B70: FIESTA | C70: PC-86272 | D70: 0 | E70: {=IF($B70="","",IF(TRIM(INDEX('Part 1'!$L$2:$IV$2,1,ROW()-1))=TRIM($B70),INDEX('Part 1'!$L$1250:$IV$1250,1,ROW()-1),"CHECK"))} -> 0 | F70: =IFERROR(D70-E70,"") -> 0 | G70: ='Part 1'!CB30 -> 132 | L70: DEV'S CUSTOMER | M70: ST750363 | N70: 0 | O70: =IF($L70="","",IF(TRIM(INDEX('Part 4'!$E$2:$IV$2,1,ROW()-1))=TRIM($L70&""),INDEX('Part 4'!$E$778:$IV$778,1,ROW()-1),"CHECK")) -> 0 | P70: =IFERROR(N70-O70,"") -> 0 | Q70: ='Part 4'!BU20 -> 1 | T70: BOLERO-12V | U70: SDN-002/BLR | V70: 0 | W70: =IFERROR('Part 7'!GX690+0,0) -> 0 | X70: =IFERROR(V70-W70,"") -> 0 | Y70: ='Part 7'!GX18 -> 38 | AA70: MARUTI ESTEEM PTL 134A SUCTION HOSE VX | AB70: PC-161 | AC70: 0 | AD70: =IF($AB70="","",IF(TRIM(INDEX('Part 8'!$F$2:$IV$2,1,ROW()-1))=TRIM($AB70),INDEX('Part 8'!$F$244:$IV$244,1,ROW()-1),"CHECK")) -> 15 | AE70: =IFERROR(AC70-AD70,"") -> -15 | AF70: ='Part 8'!BV9 -> 0
B71: FIGO | C71: PC-86590 | D71: 116 | E71: {=IF($B71="","",IF(TRIM(INDEX('Part 1'!$L$2:$IV$2,1,ROW()-1))=TRIM($B71),INDEX('Part 1'!$L$1250:$IV$1250,1,ROW()-1),"CHECK"))} -> 100 | F71: =IFERROR(D71-E71,"") -> 16 | G71: ='Part 1'!CC30 -> 479 | L71: DEV'S CUSTOMER | M71: PC-1920 | N71: 0 | O71: =IF($L71="","",IF(TRIM(INDEX('Part 4'!$E$2:$IV$2,1,ROW()-1))=TRIM($L71&""),INDEX('Part 4'!$E$778:$IV$778,1,ROW()-1),"CHECK")) -> 0 | P71: =IFERROR(N71-O71,"") -> 0 | Q71: ='Part 4'!BV20 -> 59 | T71: CIVIC | U71: SDN-016/CIVIC | V71: 0 | W71: =IFERROR('Part 7'!GY690+0,0) -> 0 | X71: =IFERROR(V71-W71,"") -> 0 | Y71: ='Part 7'!GY18 -> -31 | AA71: MARUTI ESTEEM PTL 134A DISCHARGE HOSE LX | AB71: PC-162 | AC71: 0 | AD71: =IF($AB71="","",IF(TRIM(INDEX('Part 8'!$F$2:$IV$2,1,ROW()-1))=TRIM($AB71),INDEX('Part 8'!$F$244:$IV$244,1,ROW()-1),"CHECK")) -> 0 | AE71: =IFERROR(AC71-AD71,"") -> 0 | AF71: ='Part 8'!BW9 -> 0
B72: FLUENCE-Q5 | C72: PC-86769-Q5 | D72: 11 | E72: {=IF($B72="","",IF(TRIM(INDEX('Part 1'!$L$2:$IV$2,1,ROW()-1))=TRIM($B72),INDEX('Part 1'!$L$1250:$IV$1250,1,ROW()-1),"CHECK"))} -> 4 | F72: =IFERROR(D72-E72,"") -> 7 | G72: ='Part 1'!CD30 -> 35 | L72: DEV'S CUSTOMER | M72: PC-1712 | N72: 0 | O72: =IF($L72="","",IF(TRIM(INDEX('Part 4'!$E$2:$IV$2,1,ROW()-1))=TRIM($L72&""),INDEX('Part 4'!$E$778:$IV$778,1,ROW()-1),"CHECK")) -> 0 | P72: =IFERROR(N72-O72,"") -> 0 | Q72: ='Part 4'!BW20 -> -1 | T72: CRV | U72: SDN-017/CRV | V72: 0 | W72: =IFERROR('Part 7'!GZ690+0,0) -> 0 | X72: =IFERROR(V72-W72,"") -> 0 | Y72: ='Part 7'!GZ18 -> 120 | AA72: MARUTI ESTEEM PTL 134A DISCHARE HOSE VX | AB72: PC-163 | AC72: 0 | AD72: =IF($AB72="","",IF(TRIM(INDEX('Part 8'!$F$2:$IV$2,1,ROW()-1))=TRIM($AB72),INDEX('Part 8'!$F$244:$IV$244,1,ROW()-1),"CHECK")) -> 5 | AE72: =IFERROR(AC72-AD72,"") -> -5 | AF72: ='Part 8'!BX9 -> 0
B73: FORCE SUV-DSL | C73: PC-86904 | D73: 15 | E73: {=IF($B73="","",IF(TRIM(INDEX('Part 1'!$L$2:$IV$2,1,ROW()-1))=TRIM($B73),INDEX('Part 1'!$L$1250:$IV$1250,1,ROW()-1),"CHECK"))} -> 15 | F73: =IFERROR(D73-E73,"") -> 0 | G73: ='Part 1'!CE30 -> 49 | L73: DEV'S CUSTOMER | M73: PC-1925 | N73: 0 | O73: =IF($L73="","",IF(TRIM(INDEX('Part 4'!$E$2:$IV$2,1,ROW()-1))=TRIM($L73&""),INDEX('Part 4'!$E$778:$IV$778,1,ROW()-1),"CHECK")) -> 0 | P73: =IFERROR(N73-O73,"") -> 0 | Q73: ='Part 4'!BX20 -> 60 | T73: ESTEEM ND | U73: SDN-013/ND | V73: 0 | W73: =IFERROR('Part 7'!HA690+0,0) -> 0 | X73: =IFERROR(V73-W73,"") -> 0 | Y73: ='Part 7'!HA18 -> 190 | AA73: MARUTI ESTEEM PTL 134A LIQUID RD TO COND. PAD + NUT | AB73: PC-164 | AC73: 0 | AD73: =IF($AB73="","",IF(TRIM(INDEX('Part 8'!$F$2:$IV$2,1,ROW()-1))=TRIM($AB73),INDEX('Part 8'!$F$244:$IV$244,1,ROW()-1),"CHECK")) -> 0 | AE73: =IFERROR(AC73-AD73,"") -> 0 | AF73: ='Part 8'!BY9 -> 0
B74: Ford Ikon | C74: PC-86034 | D74: 15 | E74: {=IF($B74="","",IF(TRIM(INDEX('Part 1'!$L$2:$IV$2,1,ROW()-1))=TRIM($B74),INDEX('Part 1'!$L$1250:$IV$1250,1,ROW()-1),"CHECK"))} -> 9 | F74: =IFERROR(D74-E74,"") -> 6 | G74: ='Part 1'!CF30 -> 66 | L74: DEV'S CUSTOMER | M74: PC-1926 | N74: 1 | O74: =IF($L74="","",IF(TRIM(INDEX('Part 4'!$E$2:$IV$2,1,ROW()-1))=TRIM($L74&""),INDEX('Part 4'!$E$778:$IV$778,1,ROW()-1),"CHECK")) -> 0 | P74: =IFERROR(N74-O74,"") -> 1 | Q74: ='Part 4'!BY20 -> 60 | T74: HONDA T3 | U74: SDN-008/H.T3 | V74: 0 | W74: =IFERROR('Part 7'!HB690+0,0) -> 0 | X74: =IFERROR(V74-W74,"") -> 0 | Y74: ='Part 7'!HB18 -> -50 | AA74: MARUTI ESTEEM PTL 134A LUID RD TO COND. BOTH PAD | AB74: PC-165 | AC74: 0 | AD74: =IF($AB74="","",IF(TRIM(INDEX('Part 8'!$F$2:$IV$2,1,ROW()-1))=TRIM($AB74),INDEX('Part 8'!$F$244:$IV$244,1,ROW()-1),"CHECK")) -> 0 | AE74: =IFERROR(AC74-AD74,"") -> 0 | AF74: ='Part 8'!BZ9 -> 0
B75: FURTUNER (DSL)-Q5 | C75: PC-86604 | D75: 3 | E75: {=IF($B75="","",IF(TRIM(INDEX('Part 1'!$L$2:$IV$2,1,ROW()-1))=TRIM($B75),INDEX('Part 1'!$L$1250:$IV$1250,1,ROW()-1),"CHECK"))} -> 8 | F75: =IFERROR(D75-E75,"") -> -5 | G75: ='Part 1'!CG30 -> 63 | O75: =IF($L75="","",IF(TRIM(INDEX('Part 4'!$E$2:$IV$2,1,ROW()-1))=TRIM($L75&""),INDEX('Part 4'!$E$778:$IV$778,1,ROW()-1),"CHECK")) | T75: WR | U75: SDN-011/WR | V75: 0 | W75: =IFERROR('Part 7'!HC690+0,0) -> 0 | X75: =IFERROR(V75-W75,"") -> 0 | Y75: ='Part 7'!HC18 -> -53 | AA75: MARUTI ESTEEM PTL 134A DISCHARGE TUBE | AB75: PC-166 | AC75: 0 | AD75: =IF($AB75="","",IF(TRIM(INDEX('Part 8'!$F$2:$IV$2,1,ROW()-1))=TRIM($AB75),INDEX('Part 8'!$F$244:$IV$244,1,ROW()-1),"CHECK")) -> 0 | AE75: =IFERROR(AC75-AD75,"") -> 0 | AF75: ='Part 8'!CA9 -> 0
B76: FUSION | C76: PC-86271 | D76: 2 | E76: {=IF($B76="","",IF(TRIM(INDEX('Part 1'!$L$2:$IV$2,1,ROW()-1))=TRIM($B76),INDEX('Part 1'!$L$1250:$IV$1250,1,ROW()-1),"CHECK"))} -> 2 | F76: =IFERROR(D76-E76,"") -> 0 | G76: ='Part 1'!CH30 -> 166 | O76: =IF($L76="","",IF(TRIM(INDEX('Part 4'!$E$2:$IV$2,1,ROW()-1))=TRIM($L76&""),INDEX('Part 4'!$E$778:$IV$778,1,ROW()-1),"CHECK")) | T76: HONDA T4 | U76: SDN-001/H.T4DSL | V76: 0 | W76: =IFERROR('Part 7'!HD690+0,0) -> 0 | X76: =IFERROR(V76-W76,"") -> 0 | Y76: ='Part 7'!HD18 -> -60 | AA76: MARUTI ESTEEM PTL 134A LIQ. TUBE RD TO JOINT | AB76: PC-167 | AC76: 0 | AD76: =IF($AB76="","",IF(TRIM(INDEX('Part 8'!$F$2:$IV$2,1,ROW()-1))=TRIM($AB76),INDEX('Part 8'!$F$244:$IV$244,1,ROW()-1),"CHECK")) -> 0 | AE76: =IFERROR(AC76-AD76,"") -> 0 | AF76: ='Part 8'!CB9 -> 0
B77: GETZ | C77: PC-86027B | D77: 0 | E77: {=IF($B77="","",IF(TRIM(INDEX('Part 1'!$L$2:$IV$2,1,ROW()-1))=TRIM($B77),INDEX('Part 1'!$L$1250:$IV$1250,1,ROW()-1),"CHECK"))} -> 0 | F77: =IFERROR(D77-E77,"") -> 0 | G77: ='Part 1'!CI30 -> 48 | L77: COMP. SAMPLES | N77: 0 | O77: =IF($L77="","",IF(TRIM(INDEX('Part 4'!$E$2:$IV$2,1,ROW()-1))=TRIM($L77&""),INDEX('Part 4'!$E$778:$IV$778,1,ROW()-1),"CHECK")) -> 0 | P77: =IFERROR(N77-O77,"") -> 0 | Q77: ='Part 4'!CB20 -> 1 | T77: INNOVA DUAL | U77: SDN-009/INNOVA | V77: 0 | W77: =IFERROR('Part 7'!HE690+0,0) -> 0 | X77: =IFERROR(V77-W77,"") -> 0 | Y77: ='Part 7'!HE18 -> -203 | AA77: MARUTI ESTEEM PTL R134A LIQUID TUBE JOINT TO COIL | AB77: PC-168 | AC77: 0 | AD77: =IF($AB77="","",IF(TRIM(INDEX('Part 8'!$F$2:$IV$2,1,ROW()-1))=TRIM($AB77),INDEX('Part 8'!$F$244:$IV$244,1,ROW()-1),"CHECK")) -> 0 | AE77: =IFERROR(AC77-AD77,"") -> 0 | AF77: ='Part 8'!CC9 -> 0
B78: HONDA CIVIC | C78: PC-86251 | D78: 57 | E78: {=IF($B78="","",IF(TRIM(INDEX('Part 1'!$L$2:$IV$2,1,ROW()-1))=TRIM($B78),INDEX('Part 1'!$L$1250:$IV$1250,1,ROW()-1),"CHECK"))} -> 54 | F78: =IFERROR(D78-E78,"") -> 3 | G78: ='Part 1'!CJ30 -> 190 | T78: INNOVA SINGLE | U78: SDN-018/INNOVA SINGLE | V78: 0 | W78: =IFERROR('Part 7'!HF690+0,0) -> 0 | X78: =IFERROR(V78-W78,"") -> 0 | Y78: ='Part 7'!HF18 -> -22 | AA78: MARUTI ESTEEM PTL R134A SUCTION TUBE C COIL | AB78: PC-169 | AC78: 0 | AD78: =IF($AB78="","",IF(TRIM(INDEX('Part 8'!$F$2:$IV$2,1,ROW()-1))=TRIM($AB78),INDEX('Part 8'!$F$244:$IV$244,1,ROW()-1),"CHECK")) -> 0 | AE78: =IFERROR(AC78-AD78,"") -> 0 | AF78: ='Part 8'!CD9 -> 0
B79: HONDA CIVIC-Q5 | C79: PC-86251Q5 | D79: 66 | E79: {=IF($B79="","",IF(TRIM(INDEX('Part 1'!$L$2:$IV$2,1,ROW()-1))=TRIM($B79),INDEX('Part 1'!$L$1250:$IV$1250,1,ROW()-1),"CHECK"))} -> 47 | F79: =IFERROR(D79-E79,"") -> 19 | G79: ='Part 1'!CK30 -> 68 | T79: QUALIS | U79: SDN-020/QUALIS | V79: 0 | W79: =IFERROR('Part 7'!HG690+0,0) -> 0 | X79: =IFERROR(V79-W79,"") -> 0 | Y79: ='Part 7'!HG18 -> -31 | AA79: MARUTI ESTEEM DSL R134A SUCTION HOSE | AB79: PC-170 | AC79: 0 | AD79: =IF($AB79="","",IF(TRIM(INDEX('Part 8'!$F$2:$IV$2,1,ROW()-1))=TRIM($AB79),INDEX('Part 8'!$F$244:$IV$244,1,ROW()-1),"CHECK")) -> 0 | AE79: =IFERROR(AC79-AD79,"") -> 0 | AF79: ='Part 8'!CE9 -> 0
B80: HONDA ACCORD Q5 | C80: PC-86006 | D80: 8 | E80: {=IF($B80="","",IF(TRIM(INDEX('Part 1'!$L$2:$IV$2,1,ROW()-1))=TRIM($B80),INDEX('Part 1'!$L$1250:$IV$1250,1,ROW()-1),"CHECK"))} -> 5 | F80: =IFERROR(D80-E80,"") -> 3 | G80: ='Part 1'!CL30 -> 51 | K80: MOTOR | L80: ZEN | M80: TD-6034 | N80: 0 | O80: =IF($L80="","",IF(TRIM(INDEX('Part 4'!$E$2:$IV$2,1,ROW()-1))=TRIM($L80&""),INDEX('Part 4'!$E$778:$IV$778,1,ROW()-1),"CHECK")) -> 0 | P80: =IFERROR(N80-O80,"") -> 0 | Q80: ='Part 4'!CE20 -> 427 | T80: SANTRO XING | U80: SDN-012/XING | V80: 0 | W80: =IFERROR('Part 7'!HH690+0,0) -> 0 | X80: =IFERROR(V80-W80,"") -> 0 | Y80: ='Part 7'!HH18 -> -191 | AA80: MARUTI ESTEEM DSL R134A DISCHARGE HOSE | AB80: PC-171 | AC80: 0 | AD80: =IF($AB80="","",IF(TRIM(INDEX('Part 8'!$F$2:$IV$2,1,ROW()-1))=TRIM($AB80),INDEX('Part 8'!$F$244:$IV$244,1,ROW()-1),"CHECK")) -> 0 | AE80: =IFERROR(AC80-AD80,"") -> 0 | AF80: ='Part 8'!CF9 -> 0
B81: HONDA ACCORD T4 | C81: PCP-86532 Q5 | D81: 7 | E81: {=IF($B81="","",IF(TRIM(INDEX('Part 1'!$L$2:$IV$2,1,ROW()-1))=TRIM($B81),INDEX('Part 1'!$L$1250:$IV$1250,1,ROW()-1),"CHECK"))} -> 5 | F81: =IFERROR(D81-E81,"") -> 2 | G81: ='Part 1'!CM30 -> 32 | L81: ESTEEM | M81: TD-6035 | N81: 0 | O81: =IF($L81="","",IF(TRIM(INDEX('Part 4'!$E$2:$IV$2,1,ROW()-1))=TRIM($L81&""),INDEX('Part 4'!$E$778:$IV$778,1,ROW()-1),"CHECK")) -> 0 | P81: =IFERROR(N81-O81,"") -> 0 | Q81: ='Part 4'!CF20 -> 401 | T81: SCORPIO HALLA (wrong model) | U81: SDN-021/SCR | V81: 0 | W81: =IFERROR('Part 7'!HI690+0,0) -> 0 | X81: =IFERROR(V81-W81,"") -> 0 | Y81: ='Part 7'!HI18 -> 42 | AA81: MARUTI ESTEEM DSL R134A DISCHARGE TUBE | AB81: PC-172 | AC81: 0 | AD81: =IF($AB81="","",IF(TRIM(INDEX('Part 8'!$F$2:$IV$2,1,ROW()-1))=TRIM($AB81),INDEX('Part 8'!$F$244:$IV$244,1,ROW()-1),"CHECK")) -> 0 | AE81: =IFERROR(AC81-AD81,"") -> 0 | AF81: ='Part 8'!CG9 -> 0
B82: HONDA AMAZE DSL | C82: PC-86902 | D82: 263 | E82: {=IF($B82="","",IF(TRIM(INDEX('Part 1'!$L$2:$IV$2,1,ROW()-1))=TRIM($B82),INDEX('Part 1'!$L$1250:$IV$1250,1,ROW()-1),"CHECK"))} -> 230 | F82: =IFERROR(D82-E82,"") -> 33 | G82: ='Part 1'!CN30 -> 893 | L82: CONCORD MOTOR | N82: 33 | O82: =IF($L82="","",IF(TRIM(INDEX('Part 4'!$E$2:$IV$2,1,ROW()-1))=TRIM($L82&""),INDEX('Part 4'!$E$778:$IV$778,1,ROW()-1),"CHECK")) -> 20 | P82: =IFERROR(N82-O82,"") -> 13 | Q82: ='Part 4'!CG20 -> 694 | T82: SKODA | U82: SDN-015/SKD | V82: 0 | W82: =IFERROR('Part 7'!HJ690+0,0) -> 0 | X82: =IFERROR(V82-W82,"") -> 0 | Y82: ='Part 7'!HJ18 -> 183 | AA82: MARUTI ESTEEM DSL R134A LIQUID TUBE RD TO COND | AB82: PC-173 | AC82: 0 | AD82: =IF($AB82="","",IF(TRIM(INDEX('Part 8'!$F$2:$IV$2,1,ROW()-1))=TRIM($AB82),INDEX('Part 8'!$F$244:$IV$244,1,ROW()-1),"CHECK")) -> 0 | AE82: =IFERROR(AC82-AD82,"") -> 0 | AF82: ='Part 8'!CH9 -> 0
B83: HONDA AMAZE DSL-Q5 | C83: PC-86902Q5 | D83: 5 | E83: {=IF($B83="","",IF(TRIM(INDEX('Part 1'!$L$2:$IV$2,1,ROW()-1))=TRIM($B83),INDEX('Part 1'!$L$1250:$IV$1250,1,ROW()-1),"CHECK"))} -> 5 | F83: =IFERROR(D83-E83,"") -> 0 | G83: ='Part 1'!CO30 -> 232 | L83: MICRO-BUS 12V | N83: 0 | O83: =IF($L83="","",IF(TRIM(INDEX('Part 4'!$E$2:$IV$2,1,ROW()-1))=TRIM($L83&""),INDEX('Part 4'!$E$778:$IV$778,1,ROW()-1),"CHECK")) -> 0 | P83: =IFERROR(N83-O83,"") -> 0 | Q83: ='Part 4'!CH20 -> 34 | T83: SUMO VECTA | U83: SDN-004/SUMO V.DELPHI | V83: 0 | W83: =IFERROR('Part 7'!HK690+0,0) -> 0 | X83: =IFERROR(V83-W83,"") -> 0 | Y83: ='Part 7'!HK18 -> -7 | AA83: MARUTI ESTEEM DSL R134A LIQUID TUBE RD TO JOINT | AB83: PC-174 | AC83: 0 | AD83: =IF($AB83="","",IF(TRIM(INDEX('Part 8'!$F$2:$IV$2,1,ROW()-1))=TRIM($AB83),INDEX('Part 8'!$F$244:$IV$244,1,ROW()-1),"CHECK")) -> 0 | AE83: =IFERROR(AC83-AD83,"") -> 0 | AF83: ='Part 8'!CI9 -> 0
B84: Honda City-TYPE-1&2 | C84: PC-86091 | D84: 11 | E84: {=IF($B84="","",IF(TRIM(INDEX('Part 1'!$L$2:$IV$2,1,ROW()-1))=TRIM($B84),INDEX('Part 1'!$L$1250:$IV$1250,1,ROW()-1),"CHECK"))} -> 1 | F84: =IFERROR(D84-E84,"") -> 10 | G84: ='Part 1'!CP30 -> 66 | L84: SK MOTOR-12V | M84: TD-7800 | N84: 0 | O84: =IF($L84="","",IF(TRIM(INDEX('Part 4'!$E$2:$IV$2,1,ROW()-1))=TRIM($L84&""),INDEX('Part 4'!$E$778:$IV$778,1,ROW()-1),"CHECK")) -> 30 | P84: =IFERROR(N84-O84,"") -> -30 | Q84: ='Part 4'!CI20 -> 613 | T84: SWIFT DSL | U84: SDN-014/SWIFT DSL | V84: 0 | W84: =IFERROR('Part 7'!HL690+0,0) -> 0 | X84: =IFERROR(V84-W84,"") -> 0 | Y84: ='Part 7'!HL18 -> 24 | AA84: MARUTI ESTEEM DSL R134A LIQUID TUBE JOINT TO C COIL | AB84: PC-175 | AC84: 0 | AD84: =IF($AB84="","",IF(TRIM(INDEX('Part 8'!$F$2:$IV$2,1,ROW()-1))=TRIM($AB84),INDEX('Part 8'!$F$244:$IV$244,1,ROW()-1),"CHECK")) -> 0 | AE84: =IFERROR(AC84-AD84,"") -> 0 | AF84: ='Part 8'!CJ9 -> 0
B85: Honda City-TYPE-3 | C85: PC-86240 | D85: 103 | E85: {=IF($B85="","",IF(TRIM(INDEX('Part 1'!$L$2:$IV$2,1,ROW()-1))=TRIM($B85),INDEX('Part 1'!$L$1250:$IV$1250,1,ROW()-1),"CHECK"))} -> 81 | F85: =IFERROR(D85-E85,"") -> 22 | G85: ='Part 1'!CQ30 -> 588 | L85: MICRO-BUS 24V | N85: 40 | O85: =IF($L85="","",IF(TRIM(INDEX('Part 4'!$E$2:$IV$2,1,ROW()-1))=TRIM($L85&""),INDEX('Part 4'!$E$778:$IV$778,1,ROW()-1),"CHECK")) -> 40 | P85: =IFERROR(N85-O85,"") -> 0 | Q85: ='Part 4'!CJ20 -> 325 | T85: SWIFT PTL | U85: SDN-019/SWIFT PTL | V85: 0 | W85: =IFERROR('Part 7'!HM690+0,0) -> 0 | X85: =IFERROR(V85-W85,"") -> 0 | Y85: ='Part 7'!HM18 -> -67 | AA85: MARUTI ESTEEM DSL SUCTION TUBE C COIL R134A | AB85: PC-176 | AC85: 0 | AD85: =IF($AB85="","",IF(TRIM(INDEX('Part 8'!$F$2:$IV$2,1,ROW()-1))=TRIM($AB85),INDEX('Part 8'!$F$244:$IV$244,1,ROW()-1),"CHECK")) -> 0 | AE85: =IFERROR(AC85-AD85,"") -> 0 | AF85: ='Part 8'!CK9 -> 0
B86: Honda City-TYPE-3-Q5 | C86: PC-86240AQ5 | D86: 3 | E86: {=IF($B86="","",IF(TRIM(INDEX('Part 1'!$L$2:$IV$2,1,ROW()-1))=TRIM($B86),INDEX('Part 1'!$L$1250:$IV$1250,1,ROW()-1),"CHECK"))} -> 0 | F86: =IFERROR(D86-E86,"") -> 3 | G86: ='Part 1'!CR30 -> 120 | K86: COMP. PARTS | L86: COMP. BACK PLATE-505/507 (FLARE) | N86: 0 | O86: =IF($L86="","",IF(TRIM(INDEX('Part 4'!$E$2:$IV$2,1,ROW()-1))=TRIM($L86&""),INDEX('Part 4'!$E$778:$IV$778,1,ROW()-1),"CHECK")) -> 0 | P86: =IFERROR(N86-O86,"") -> 0 | Q86: ='Part 4'!CK20 -> 1070 | T86: SX-4 | U86: SDN-006/SX4 | V86: 0 | W86: =IFERROR('Part 7'!HN690+0,0) -> 0 | X86: =IFERROR(V86-W86,"") -> 0 | Y86: ='Part 7'!HN18 -> -5 | AA86: MARUTI ZEN PTL SUCTION HOSE LX R12 | AB86: PC-177 | AC86: 0 | AD86: =IF($AB86="","",IF(TRIM(INDEX('Part 8'!$F$2:$IV$2,1,ROW()-1))=TRIM($AB86),INDEX('Part 8'!$F$244:$IV$244,1,ROW()-1),"CHECK")) -> 0 | AE86: =IFERROR(AC86-AD86,"") -> 0 | AF86: ='Part 8'!CL9 -> 0
B87: HONDA CRV | C87: PC-86101 | D87: 0 | E87: {=IF($B87="","",IF(TRIM(INDEX('Part 1'!$L$2:$IV$2,1,ROW()-1))=TRIM($B87),INDEX('Part 1'!$L$1250:$IV$1250,1,ROW()-1),"CHECK"))} -> 0 | F87: =IFERROR(D87-E87,"") -> 0 | G87: ='Part 1'!CS30 -> 5 | L87: COMP. BACK PLATE-508/510 (FLARE) | N87: 0 | O87: =IF($L87="","",IF(TRIM(INDEX('Part 4'!$E$2:$IV$2,1,ROW()-1))=TRIM($L87&""),INDEX('Part 4'!$E$778:$IV$778,1,ROW()-1),"CHECK")) -> 0 | P87: =IFERROR(N87-O87,"") -> 0 | Q87: ='Part 4'!CL20 -> 185 | T87: VARNA | U87: SDN-005/VERNA | V87: 0 | W87: =IFERROR('Part 7'!HO690+0,0) -> 0 | X87: =IFERROR(V87-W87,"") -> 0 | Y87: ='Part 7'!HO18 -> 58 | AA87: MARUTI ZEN PTL SUCTION HOSE R12 VX | AB87: PC-178 | AC87: 0 | AD87: =IF($AB87="","",IF(TRIM(INDEX('Part 8'!$F$2:$IV$2,1,ROW()-1))=TRIM($AB87),INDEX('Part 8'!$F$244:$IV$244,1,ROW()-1),"CHECK")) -> 0 | AE87: =IFERROR(AC87-AD87,"") -> 0 | AF87: ='Part 8'!CM9 -> 0
B88: HONDA CRV (NEW)-Q5 | C88: PC-86398-Q5 | D88: 12 | E88: {=IF($B88="","",IF(TRIM(INDEX('Part 1'!$L$2:$IV$2,1,ROW()-1))=TRIM($B88),INDEX('Part 1'!$L$1250:$IV$1250,1,ROW()-1),"CHECK"))} -> 12 | F88: =IFERROR(D88-E88,"") -> 0 | G88: ='Part 1'!CT30 -> 22 | L88: COMP. BACK PLATE-505/507 (O RING) | N88: 0 | O88: =IF($L88="","",IF(TRIM(INDEX('Part 4'!$E$2:$IV$2,1,ROW()-1))=TRIM($L88&""),INDEX('Part 4'!$E$778:$IV$778,1,ROW()-1),"CHECK")) -> 0 | P88: =IFERROR(N88-O88,"") -> 0 | Q88: ='Part 4'!CM20 -> 360 | T88: VISTA-SUBROS-5PK | U88: SDN-007/I.V.SUBROS | V88: 0 | W88: =IFERROR('Part 7'!HP690+0,0) -> 0 | X88: =IFERROR(V88-W88,"") -> 0 | Y88: ='Part 7'!HP18 -> -7 | AA88: MARUTI ZEN PTL R12 DISCHARGE HOSE | AB88: PC-179 | AC88: 0 | AD88: =IF($AB88="","",IF(TRIM(INDEX('Part 8'!$F$2:$IV$2,1,ROW()-1))=TRIM($AB88),INDEX('Part 8'!$F$244:$IV$244,1,ROW()-1),"CHECK")) -> 3 | AE88: =IFERROR(AC88-AD88,"") -> -3 | AF88: ='Part 8'!CN9 -> 0
B89: HONDA CRV-Q5 | C89: PC-86101 Q5 | D89: 12 | E89: {=IF($B89="","",IF(TRIM(INDEX('Part 1'!$L$2:$IV$2,1,ROW()-1))=TRIM($B89),INDEX('Part 1'!$L$1250:$IV$1250,1,ROW()-1),"CHECK"))} -> 11 | F89: =IFERROR(D89-E89,"") -> 1 | G89: ='Part 1'!CU30 -> 27 | L89: COMP. BACK PLATE-508/510 (O RING) | N89: 0 | O89: =IF($L89="","",IF(TRIM(INDEX('Part 4'!$E$2:$IV$2,1,ROW()-1))=TRIM($L89&""),INDEX('Part 4'!$E$778:$IV$778,1,ROW()-1),"CHECK")) -> 0 | P89: =IFERROR(N89-O89,"") -> 0 | Q89: ='Part 4'!CN20 -> 25 | T89: VOLVO BIG PULLEY SDN/061/S-3 VOLVO | V89: 0 | W89: =IFERROR('Part 7'!HQ690+0,0) -> 0 | X89: =IFERROR(V89-W89,"") -> 0 | Y89: ='Part 7'!HQ18 -> 10 | AA89: MARUTI ZEN PTL R12 SUCTION TUBE HOCKEY TYPE | AB89: PC-180 | AC89: 0 | AD89: =IF($AB89="","",IF(TRIM(INDEX('Part 8'!$F$2:$IV$2,1,ROW()-1))=TRIM($AB89),INDEX('Part 8'!$F$244:$IV$244,1,ROW()-1),"CHECK")) -> 0 | AE89: =IFERROR(AC89-AD89,"") -> 0 | AF89: ='Part 8'!CO9 -> 0
B90: HONDA I.D.TEC (DSL)-Q5 | C90: PC-86807-Q5 | D90: 75 | E90: {=IF($B90="","",IF(TRIM(INDEX('Part 1'!$L$2:$IV$2,1,ROW()-1))=TRIM($B90),INDEX('Part 1'!$L$1250:$IV$1250,1,ROW()-1),"CHECK"))} -> 68 | F90: =IFERROR(D90-E90,"") -> 7 | G90: ='Part 1'!CV30 -> 311 | L90: VALVE PIN R12 | N90: 18000 | O90: =IF($L90="","",IF(TRIM(INDEX('Part 4'!$E$2:$IV$2,1,ROW()-1))=TRIM($L90&""),INDEX('Part 4'!$E$778:$IV$778,1,ROW()-1),"CHECK")) -> 14500 | P90: =IFERROR(N90-O90,"") -> 3500 | Q90: ='Part 4'!CO20 -> 239200 | T90: 10PK SDN/062/10PK | V90: 0 | W90: =IFERROR('Part 7'!HR690+0,0) -> 0 | X90: =IFERROR(V90-W90,"") -> 0 | Y90: ='Part 7'!HR18 -> 10 | AA90: MARUTI ZEN PTL LIQUID TUBE R12 RD TCC COND | AB90: PC-181 | AC90: 0 | AD90: =IF($AB90="","",IF(TRIM(INDEX('Part 8'!$F$2:$IV$2,1,ROW()-1))=TRIM($AB90),INDEX('Part 8'!$F$244:$IV$244,1,ROW()-1),"CHECK")) -> 0 | AE90: =IFERROR(AC90-AD90,"") -> 0 | AF90: ='Part 8'!CP9 -> 0
B91: HONDA I.D.TEC (PTL) | C91: PC-86827 | D91: 46 | E91: {=IF($B91="","",IF(TRIM(INDEX('Part 1'!$L$2:$IV$2,1,ROW()-1))=TRIM($B91),INDEX('Part 1'!$L$1250:$IV$1250,1,ROW()-1),"CHECK"))} -> 36 | F91: =IFERROR(D91-E91,"") -> 10 | G91: ='Part 1'!CW30 -> 76 | L91: VALVE PIN R134 | N91: 18000 | O91: =IF($L91="","",IF(TRIM(INDEX('Part 4'!$E$2:$IV$2,1,ROW()-1))=TRIM($L91&""),INDEX('Part 4'!$E$778:$IV$778,1,ROW()-1),"CHECK")) -> 13250 | P91: =IFERROR(N91-O91,"") -> 4750 | Q91: ='Part 4'!CP20 -> 230240 | T91: HONDA TYPE 5 | U91: SDN-064/HT5 | V91: 0 | W91: =IFERROR('Part 7'!HS690+0,0) -> 0 | X91: =IFERROR(V91-W91,"") -> 0 | Y91: ='Part 7'!HS18 -> 100 | AA91: MARUTI ZEN PTL R12 LIQUID TUBE RD TO COIL | AB91: PC-182 | AC91: 0 | AD91: =IF($AB91="","",IF(TRIM(INDEX('Part 8'!$F$2:$IV$2,1,ROW()-1))=TRIM($AB91),INDEX('Part 8'!$F$244:$IV$244,1,ROW()-1),"CHECK")) -> 0 | AE91: =IFERROR(AC91-AD91,"") -> 0 | AF91: ='Part 8'!CQ9 -> 0
B92: HONDA I.D.TEC (PTL)-Q5 | C92: PC-86827Q5 | D92: 13 | E92: {=IF($B92="","",IF(TRIM(INDEX('Part 1'!$L$2:$IV$2,1,ROW()-1))=TRIM($B92),INDEX('Part 1'!$L$1250:$IV$1250,1,ROW()-1),"CHECK"))} -> 13 | F92: =IFERROR(D92-E92,"") -> 0 | G92: ='Part 1'!CX30 -> 230 | T92: SUBROS 3600 | U92: SDN-065/S3600 | V92: 0 | W92: =IFERROR('Part 7'!HT690+0,0) -> 0 | X92: =IFERROR(V92-W92,"") -> 0 | Y92: ='Part 7'!HT18 -> 100 | AA92: MARUTI ZEN PTL R12 LIQUID TUBE COOLING COIL | AB92: PC-183 | AC92: 0 | AD92: =IF($AB92="","",IF(TRIM(INDEX('Part 8'!$F$2:$IV$2,1,ROW()-1))=TRIM($AB92),INDEX('Part 8'!$F$244:$IV$244,1,ROW()-1),"CHECK")) -> 0 | AE92: =IFERROR(AC92-AD92,"") -> 0 | AF92: ='Part 8'!CR9 -> 0
B93: HONDA JAZZ | C93: PC-86900 | D93: 12 | E93: {=IF($B93="","",IF(TRIM(INDEX('Part 1'!$L$2:$IV$2,1,ROW()-1))=TRIM($B93),INDEX('Part 1'!$L$1250:$IV$1250,1,ROW()-1),"CHECK"))} -> 12 | F93: =IFERROR(D93-E93,"") -> 0 | G93: ='Part 1'!CY30 -> 25 | T93: BEAT PETROL | U93: SDN-066/BEAT PTRL | V93: 0 | W93: =IFERROR('Part 7'!HU690+0,0) -> 0 | X93: =IFERROR(V93-W93,"") -> 0 | Y93: ='Part 7'!HU18 -> 100 | AA93: MARUTI ZEN PTL SUCTION TUBE R12 | AB93: PC-184 | AC93: 0 | AD93: =IF($AB93="","",IF(TRIM(INDEX('Part 8'!$F$2:$IV$2,1,ROW()-1))=TRIM($AB93),INDEX('Part 8'!$F$244:$IV$244,1,ROW()-1),"CHECK")) -> 0 | AE93: =IFERROR(AC93-AD93,"") -> 0 | AF93: ='Part 8'!CS9 -> 0
B94: HONDA MOBILIO (DSL) | C94: PC-86828 | D94: 60 | E94: {=IF($B94="","",IF(TRIM(INDEX('Part 1'!$L$2:$IV$2,1,ROW()-1))=TRIM($B94),INDEX('Part 1'!$L$1250:$IV$1250,1,ROW()-1),"CHECK"))} -> 43 | F94: =IFERROR(D94-E94,"") -> 17 | G94: ='Part 1'!CZ30 -> 90 | K94: EXP.VALVE | L94: TRAVERA / XING/ ACCENT | M94: FK-C906 | N94: 100 | O94: =IF($L94="","",IF(TRIM(INDEX('Part 4'!$E$2:$IV$2,1,ROW()-1))=TRIM($L94&""),INDEX('Part 4'!$E$778:$IV$778,1,ROW()-1),"CHECK")) -> 80 | P94: =IFERROR(N94-O94,"") -> 20 | Q94: ='Part 4'!CS20 -> 935 | T94: ECOSPORT | U94: SDN-067/ECOSPORT | V94: 0 | W94: =IFERROR('Part 7'!HV690+0,0) -> 0 | X94: =IFERROR(V94-W94,"") -> 0 | Y94: ='Part 7'!HV18 -> 100 | AA94: MARUTI ZEN PTL R12 LIQUID TUBE COOLING COIL OUTLET | AB94: PC-185 | AC94: 0 | AD94: =IF($AB94="","",IF(TRIM(INDEX('Part 8'!$F$2:$IV$2,1,ROW()-1))=TRIM($AB94),INDEX('Part 8'!$F$244:$IV$244,1,ROW()-1),"CHECK")) -> 0 | AE94: =IFERROR(AC94-AD94,"") -> 0 | AF94: ='Part 8'!CT9 -> 0
B95: HONDA MOBILIO (DSL)-Q5 | C95: PC-86828Q5 | D95: 0 | E95: {=IF($B95="","",IF(TRIM(INDEX('Part 1'!$L$2:$IV$2,1,ROW()-1))=TRIM($B95),INDEX('Part 1'!$L$1250:$IV$1250,1,ROW()-1),"CHECK"))} -> 0 | F95: =IFERROR(D95-E95,"") -> 0 | G95: ='Part 1'!DA30 -> 74 | L95: AVEO | M95: PC-1209 | N95: 10 | O95: =IF($L95="","",IF(TRIM(INDEX('Part 4'!$E$2:$IV$2,1,ROW()-1))=TRIM($L95&""),INDEX('Part 4'!$E$778:$IV$778,1,ROW()-1),"CHECK")) -> 0 | P95: =IFERROR(N95-O95,"") -> 10 | Q95: ='Part 4'!CT20 -> 98 | T95: MICRA | U95: SDN-068/MICRA | V95: 0 | W95: =IFERROR('Part 7'!HW690+0,0) -> 0 | X95: =IFERROR(V95-W95,"") -> 0 | Y95: ='Part 7'!HW18 -> 100 | AA95: MARUTI ZEN DELPHI SUCTION IJ7,SE R12 | AB95: PC-186 | AC95: 0 | AD95: =IF($AB95="","",IF(TRIM(INDEX('Part 8'!$F$2:$IV$2,1,ROW()-1))=TRIM($AB95),INDEX('Part 8'!$F$244:$IV$244,1,ROW()-1),"CHECK")) -> 0 | AE95: =IFERROR(AC95-AD95,"") -> 0 | AF95: ='Part 8'!CU9 -> 0
B96: HONDA MOBILIO (PTL) | C96: PC-86829 | D96: 17 | E96: {=IF($B96="","",IF(TRIM(INDEX('Part 1'!$L$2:$IV$2,1,ROW()-1))=TRIM($B96),INDEX('Part 1'!$L$1250:$IV$1250,1,ROW()-1),"CHECK"))} -> 15 | F96: =IFERROR(D96-E96,"") -> 2 | G96: ='Part 1'!DB30 -> 128 | L96: SKODA | M96: FK-1080 | N96: 22 | O96: =IF($L96="","",IF(TRIM(INDEX('Part 4'!$E$2:$IV$2,1,ROW()-1))=TRIM($L96&""),INDEX('Part 4'!$E$778:$IV$778,1,ROW()-1),"CHECK")) -> 20 | P96: =IFERROR(N96-O96,"") -> 2 | Q96: ='Part 4'!CU20 -> 405 | T96: VOLVO BIG PULLEY SDN/061/S-3 VOLVO | V96: 10 | W96: =IFERROR('Part 7'!HX690+0,0) -> 10 | X96: =IFERROR(V96-W96,"") -> 0 | Y96: ='Part 7'!HX18 -> 60 | AA96: MARUTI ZEN DELPHI R12 DISCHARGE HOSE | AB96: PC-187 | AC96: 0 | AD96: =IF($AB96="","",IF(TRIM(INDEX('Part 8'!$F$2:$IV$2,1,ROW()-1))=TRIM($AB96),INDEX('Part 8'!$F$244:$IV$244,1,ROW()-1),"CHECK")) -> 0 | AE96: =IFERROR(AC96-AD96,"") -> 0 | AF96: ='Part 8'!CV9 -> 0
B97: HONDA MOBILIO (PTL)-Q5 | C97: PC-86829-Q5 | D97: 0 | E97: {=IF($B97="","",IF(TRIM(INDEX('Part 1'!$L$2:$IV$2,1,ROW()-1))=TRIM($B97),INDEX('Part 1'!$L$1250:$IV$1250,1,ROW()-1),"CHECK"))} -> 0 | F97: =IFERROR(D97-E97,"") -> 0 | G97: ='Part 1'!DC30 -> 185 | L97: WR/ALTO | M97: FK-1089D | N97: 354 | O97: =IF($L97="","",IF(TRIM(INDEX('Part 4'!$E$2:$IV$2,1,ROW()-1))=TRIM($L97&""),INDEX('Part 4'!$E$778:$IV$778,1,ROW()-1),"CHECK")) -> 311 | P97: =IFERROR(N97-O97,"") -> 43 | Q97: ='Part 4'!CV20 -> 906 | T97: 10PK SDN/062/10PK | V97: 10 | W97: =IFERROR('Part 7'!HY690+0,0) -> 10 | X97: =IFERROR(V97-W97,"") -> 0 | Y97: ='Part 7'!HY18 -> 60 | AA97: MARUTI ZEN DELPHI SUCTION TUBE HOCKEY TYPE | AB97: PC-188 | AC97: 0 | AD97: =IF($AB97="","",IF(TRIM(INDEX('Part 8'!$F$2:$IV$2,1,ROW()-1))=TRIM($AB97),INDEX('Part 8'!$F$244:$IV$244,1,ROW()-1),"CHECK")) -> 0 | AE97: =IFERROR(AC97-AD97,"") -> 0 | AF97: ='Part 8'!CW9 -> 0
B98: HONDA T-5 | C98: PC-86278 | D98: 63 | E98: {=IF($B98="","",IF(TRIM(INDEX('Part 1'!$L$2:$IV$2,1,ROW()-1))=TRIM($B98),INDEX('Part 1'!$L$1250:$IV$1250,1,ROW()-1),"CHECK"))} -> 52 | F98: =IFERROR(D98-E98,"") -> 11 | G98: ='Part 1'!DD30 -> 316 | L98: OPEL/INDICA BEHR/SCORPIO | M98: FK-1181B | N98: 52 | O98: =IF($L98="","",IF(TRIM(INDEX('Part 4'!$E$2:$IV$2,1,ROW()-1))=TRIM($L98&""),INDEX('Part 4'!$E$778:$IV$778,1,ROW()-1),"CHECK")) -> 50 | P98: =IFERROR(N98-O98,"") -> 2 | Q98: ='Part 4'!CW20 -> 787 | S98: BEARING | T98: Sanden 505,507 | U98: 35BD219DU | V98: 780 | W98: =IFERROR('Part 7'!HZ690+0,0) -> 780 | X98: =IFERROR(V98-W98,"") -> 0 | Y98: ='Part 7'!HZ18 -> 13390 | AA98: MARUTI ZEN DELPHI R12 LIQUID TUBE RD TO COND | AB98: PC-189 | AC98: 0 | AD98: =IF($AB98="","",IF(TRIM(INDEX('Part 8'!$F$2:$IV$2,1,ROW()-1))=TRIM($AB98),INDEX('Part 8'!$F$244:$IV$244,1,ROW()-1),"CHECK")) -> 0 | AE98: =IFERROR(AC98-AD98,"") -> 0 | AF98: ='Part 8'!CX9 -> 0
B99: HONDA T-5-Q5 | C99: PC-86278-Q5 | D99: 0 | E99: {=IF($B99="","",IF(TRIM(INDEX('Part 1'!$L$2:$IV$2,1,ROW()-1))=TRIM($B99),INDEX('Part 1'!$L$1250:$IV$1250,1,ROW()-1),"CHECK"))} -> 0 | F99: =IFERROR(D99-E99,"") -> 0 | G99: ='Part 1'!DE30 -> 25 | L99: HONDA CITY (TYPE-1) | M99: FK-1034 | N99: 5 | O99: =IF($L99="","",IF(TRIM(INDEX('Part 4'!$E$2:$IV$2,1,ROW()-1))=TRIM($L99&""),INDEX('Part 4'!$E$778:$IV$778,1,ROW()-1),"CHECK")) -> 0 | P99: =IFERROR(N99-O99,"") -> 5 | Q99: ='Part 4'!CX20 -> 334 | AA99: MARUTI ZEN DELPHI R12 LIQUID TUBE RD TO COIL | AB99: PC-190 | AC99: 0 | AD99: =IF($AB99="","",IF(TRIM(INDEX('Part 8'!$F$2:$IV$2,1,ROW()-1))=TRIM($AB99),INDEX('Part 8'!$F$244:$IV$244,1,ROW()-1),"CHECK")) -> 0 | AE99: =IFERROR(AC99-AD99,"") -> 0 | AF99: ='Part 8'!CY9 -> 0
B100: I-10 | C100: PC-86266 | D100: 231 | E100: {=IF($B100="","",IF(TRIM(INDEX('Part 1'!$L$2:$IV$2,1,ROW()-1))=TRIM($B100),INDEX('Part 1'!$L$1250:$IV$1250,1,ROW()-1),"CHECK"))} -> 230 | F100: =IFERROR(D100-E100,"") -> 1 | G100: ='Part 1'!DF30 -> 447 | L100: LANCER MMC | M100: FK-1031B | N100: 6 | O100: =IF($L100="","",IF(TRIM(INDEX('Part 4'!$E$2:$IV$2,1,ROW()-1))=TRIM($L100&""),INDEX('Part 4'!$E$778:$IV$778,1,ROW()-1),"CHECK")) -> 6 | P100: =IFERROR(N100-O100,"") -> 0 | Q100: ='Part 4'!CY20 -> 256 | U100: COIL | X100: =IFERROR(V100-W100,"") -> 0 | AA100: MARUTI ZEN DELPHI R12 SUCTION TUBE COOLING COIL | AB100: PC-191 | AC100: 0 | AD100: =IF($AB100="","",IF(TRIM(INDEX('Part 8'!$F$2:$IV$2,1,ROW()-1))=TRIM($AB100),INDEX('Part 8'!$F$244:$IV$244,1,ROW()-1),"CHECK")) -> 0 | AE100: =IFERROR(AC100-AD100,"") -> 0 | AF100: ='Part 8'!CZ9 -> 0
...

Sheet Part Summary
A1: PART SUMMARY 2019 — Challan book GST-Challan 2019-0001 to 2019-0490 (01.01.19 – 13.05.19). Total Qty = D × E, else Qty column. Cancelled = CANCEL mark in the challan block. Values from Pivot Data; checks live.
A3: Part Name | B3: Part Number | C3: Total Qty | D3: Cancelled Qty | E3: Net Qty (excl. Cancelled)
A4: 10 PK | B4: SDN/062/10PK | C4: 10 | D4: 0 | E4: 10
A5: 10"X10 B- (Straight Blade) | B5: TST-8801 | C5: 10 | D5: 10 | E5: 0
A6: 10"X6 B- ('S' Type Blade) | B6: TS-8805 | C6: 82 | D6: 32 | E6: 50
A7: 11mm flare iron nut | C7: 782 | D7: 0 | E7: 782
A8: 12"X10 B- Straight Blade | B8: TST-8801-A | C8: 10 | D8: 0 | E8: 10
A9: 12"X10 B- Straight Blade) | B9: TST-8801-A | C9: 56 | D9: 16 | E9: 40
A10: 12"X10 Blade- ('S' Type Blade) | B10: TS-8805-B | C10: 502 | D10: 72 | E10: 430
A11: 14"X10 B-(Straight Blade) | B11: TST-8801-B | C11: 42 | D11: 22 | E11: 20
A12: 14X25X20MM flare | C12: 200 | D12: 0 | E12: 200
A13: 14X28X20MM flare | C13: 60 | D13: 5 | E13: 55
A14: 14X30X20MM flare | C14: 30 | D14: 0 | E14: 30
A15: 14x15x18mm ORING - CUT TYPE | C15: 2 | D15: 0 | E15: 2
A16: 14x15x18mm flare - CUT TYPE | C16: 102 | D16: 20 | E16: 82
A17: 14x18x20mm flare | C17: 90 | D17: 0 | E17: 90
A18: 14x21x20mm flare | C18: 50 | D18: 0 | E18: 50
A19: 14x21x22mm flare | C19: 84 | D19: 14 | E19: 70
A20: 14x23x16mm flare | C20: 60 | D20: 0 | E20: 60
A21: 14x23x20mm flare | C21: 40 | D21: 10 | E21: 30
A22: 14x23x22mm flare | C22: 10 | D22: 0 | E22: 10
A23: 14x25x26mm flare | B23: 142526 | C23: 10 | D23: 0 | E23: 10
A24: 15mm flare iron nut | C24: 55 | D24: 0 | E24: 55
A25: 1PC SAMPLE SEND BY COURIER | C25: 2 | D25: 1 | E25: 1
A26: 2 PCS 86125 SCHEME OF 86541Q5 WAS NOT SUPPLIED IN 2019-0250, | C26: 2 | D26: 0 | E26: 2
A27: 25x28x20 | C27: 78 | D27: 2 | E27: 76
A28: 25x28x26 | C28: 20 | D28: 0 | E28: 20
A29: 3 Speed A/C Santro Switch | B29: PC-1001 | C29: 220 | D29: 20 | E29: 200
A30: 4 PCS 507 IN MULTIGROOVE | B30: 5H11-507MG | C30: 134 | D30: 4 | E30: 130
A31: 4 PCS 507-V GROVE PULLEY | B31: 5H11 | C31: 12 | D31: 0 | E31: 12
A32: 4 PCS 508 IN MULTIGROOVE | B32: 5H14-508MG | C32: 22 | D32: 8 | E32: 14
A33: 4 PCS 508-V GROVE PULLEY | B33: 5H14 | C33: 4 | D33: 0 | E33: 4
A34: 4 Speed A/C Xing Switch | C34: 145 | D34: 0 | E34: 145
A35: 404 BAZEL | B35: SEA-NAIR | C35: 40 | D35: 8 | E35: 32
A36: 505-V GROVE PULLEY | B36: COMPANY-A | C36: 3 | D36: 3 | E36: 0
A37: 507 IN MULTIGROOVE | B37: 5H11-507MG | C37: 36 | D37: 5 | E37: 31
A38: 507 IN MULTIGROOVE FREE WITH COOLING COIL | B38: 5H11-507MG | C38: 1 | D38: 0 | E38: 1
A39: 507 Small Single | B39: PC-7201 | C39: 25 | D39: 0 | E39: 25
A40: 507 V-GROVE FREE WITH CC | B40: 5H11 | C40: 1 | D40: 0 | E40: 1
A41: 507-7PK (WITHOUT BEARING) | B41: SDN-101/507/7PK | C41: 454 | D41: 0 | E41: 454
A42: 507-V GROVE PULLEY | B42: 5H11 | C42: 28 | D42: 2 | E42: 26
A43: 507-V GROVE PULLEY FREE WITH CC | B43: 5H11 | C43: 2 | D43: 0 | E43: 2
A44: 507-V GROVE PULLEY FREE WITH CC SCHEME | B44: 5H11 | C44: 1 | D44: 0 | E44: 1
A45: 507-V GROVE PULLEY FREE WITH COOLING COIL | B45: 5H11 | C45: 1 | D45: 0 | E45: 1
A46: 507/508 single seal | B46: PC-7053A PC-7200 | C46: 200 | D46: 0 | E46: 200
... A52: 510-V GROVE PULLEY | B52: COMPANY-A | C52: 19 | D52: 8 | E52: 11
A53: 6 PCS AL.PIPE WITH CONNECTOR FITTING SAMPLE FOR Contact-181 | C53: 0 | D53: 0 | E53: 0
A54: 7+1PCS i10 grand cc FREE TILL 31.03.19 | B54: PCP-E07638 | C54: 1 | D54: 0 | E54: 1
A55: 747 THERMOAMPLIFIER (NEW) (BOLERO, AMBASDOR) | B55: TK-66001 | C55: 145 | D55: 10 | E55: 135
A56: 8mm oring iron nut | C56: 135 | D56: 0 | E56: 135
A57: A-STAR | B57: PC-86274 | C57: 8 | D57: 5 | E57: 3
A58: A-STAR | B58: PCP-E10681R | C58: 1 | D58: 0 | E58: 1
A59: A-STAR | B59: SD-136MC/A-STAR | C59: 65 | D59: 30 | E59: 35
A60: A-STAR | B60: SDN-003/ASTAR | C60: 177 | D60: 7 | E60: 170
A61: A6 | B61: PC-8026 | C61: 4 | D61: 2 | E61: 2
A62: AC HOSE | B62: BS-15MM | C62: 100 | D62: 100 | E62: 0
A63: ACCENT | B63: 30BD40DU 305523 | C63: 7.5 | D63: 0 | E63: 7.5
A64: ACCENT | B64: PC-0213 | C64: 10 | D64: 0 | E64: 10
A65: ACCENT | B65: PC-2126 | C65: 50 | D65: 0 | E65: 50
A66: ACCENT | B66: PCP-E82420 | C66: 199 | D66: 0 | E66: 199
A67: ACCENT (BLOCK TYPE) | B67: FK-C906 | C67: 16 | D67: 1 | E67: 15
A68: ACCENT BIG DEISAL / SCORPIO PETROL / SONATA / TRAVERA | B68: SD-1002-MC // SDN-1007/MC/ACCENT CRDI // SD-138MC/MHWK // SD-100MC/SCR | C68: 70 | D68: 0 | E68: 70
... A73: ACCENT-PETROL | B73: PC-86248 | C73: 5 | D73: 5 | E73: 0
A74: ADOPTER 6002 | C74: 20 | D74: 0 | E74: 20
A75: ADOPTER OF R/D6002 F TO O | C75: 500 | D75: 0 | E75: 500
A76: PC3600 COMPRESSOR FREE | C76: 1 | D76: 0 | E76: 1
A77: COMPANY-A 3600 (SUBROS) | B77: PC-3600 | C77: 15 | D77: 1 | E77: 14
A78: COMPANY-A CONDENSER | C78: 0 | D78: 0 | E78: 0
A79: COMPANY-A COOLING COIL | C79: 2 | D79: 1 | E79: 1
A80: ALTIS -DSL | B80: PC-86083 | C80: 29 | D80: 0 | E80: 29
A81: ALTIS -DSL- Q5 | B81: PC-86083-Q5 | C81: 39 | D81: 0 | E81: 39
A82: ALTIS -PTL | B82: PC-86032 | C82: 4 | D82: 0 | E82: 4
A83: ALTIS-(DENSO TYPE) | B83: PCP-E10209 | C83: 6 | D83: 4 | E83: 2
A84: ALTO | B84: 30BGS32-DST 30BD5220DU 305220 | C84: 250 | D84: 0 | E84: 250
A85: ALTO | B85: FK-1089D | C85: 202 | D85: 11 | E85: 191
A86: ALTO 800 | B86: PC-86634 | C86: 19 | D86: 8 | E86: 11
A87: ALTO 800 | B87: SD-226CP/A-STAR, SD-224CP/SX4 SD238CP/ETOS-DSL, SD-208CP/XYLO D2, SD244CP/ALTO 800 | C87: 3 | D87: 0 | E87: 3
A88: ALTO 800 | B88: SD150MC/ALTO 800 | C88: 40 | D88: 32 | E88: 8
A89: ALTO 800 | B89: SD345PL/ALTO 800 | C89: 3 | D89: 0 | E89: 3
A90: ALTO 800 | B90: SDN056/ALTO 800 | C90: 21 | D90: 0 | E90: 21
A91: ALTO K-10 | B91: PC-0701 | C91: 5 | D91: 0 | E91: 5
... A96: ANY COMP OF HCC | B96: PC-7034A | C96: 75 | D96: 10 | E96: 65
A97: AS PER Contact, 5 PCS BOLOERO MEG SD102MC/BLR. WAS NOT FOUND IN CLUTCH SET OF BOLERO, IT IS NOT POSSIBLE BUT AS A SPECIAL CASE WE ACCEPT HIS REQUEST | C97: 5 | D97: 0 | E97: 5
A98: ASHOK LEYLAND STILE | B98: PCP-E12109 | C98: 6 | D98: 0 | E98: 6
A99: ASPIRE FORD | B99: PCP-E10091 | C99: 6 | D99: 6 | E99: 0
A100: ASSORTED MODEL 1 HOSE FITTING WITH CATORI | C100: 50 | D100: 0 | E100: 50
A101: ASSORTED MODEL 2 HOSE FITTING WITH CATORI | C101: 50 | D101: 0 | E101: 50
A102: ASSORTED MODEL 3 HOSE FITTING WITH CATORI | C102: 50 | D102: 0 | E102: 50
A103: AUDI | B103: PC-037 | C103: 25 | D103: 25 | E103: 0
A104: AUDI (ORIGINAL MADE IN GERMANY) | B104: PC-9191B | C104: 17 | D104: 0 | E104: 17
A105: AUDI A3 PREMIUM Q5 | B105: PCP-C86283Q5 | C105: 4 | D105: 0 | E105: 4
A106: AUDI A4 | B106: PCP-E03149 | C106: 4 | D106: 4 | E106: 0
A107: AUDI A4 NEW (DENSO TYPE) | B107: PCP-E10094 | C107: 4 | D107: 0 | E107: 4
A108: AUDI A6 PREMIUM Q5 | B108: PCP-C86082 | C108: 5 | D108: 0 | E108: 5
A109: AUDI Q3 PREMIUM Q5 | B109: PCP-C86020 | C109: 23 | D109: 0 | E109: 23
A110: AUDI Q7 (REAR) | B110: PCP-E10065 | C110: 24 | D110: 4 | E110: 20
A111: AUDI Q7 PREMIUM Q5 | B111: PCP-C86832 | C111: 3 | D111: 0 | E111: 3
A112: AVEO | B112: PC-017 | C112: 50 | D112: 50 | E112: 0
A113: AVEO | B113: PC-1209 | C113: 11 | D113: 1 | E113: 10
A114: AVEO | B114: PC-86177 | C114: 27 | D114: 0 | E114: 27
...

Sheet Pivot Summary
A1: PIVOT SUMMARY 2019 — PivotTable over Pivot Data (challan book)
A2: Cancelled filter "-" = active challans only. Double-click any total to list its lines. Grand total must equal Part Summary Net Qty.
A5: Cancelled | B5: (Multiple Items)
A7: Part Name | B7: Part Number | C7: Sum of Total Qty
A8: 10 PK | B8: SDN/062/10PK | C8: 10
A9: 10"X6 B- ('S' Type Blade) | B9: TS-8805 | C9: 50
A10: 11mm flare iron nut | C10: 782
A11: 12"X10 B- Straight Blade | B11: TST-8801-A | C11: 10
A12: 12"X10 B- Straight Blade) | B12: TST-8801-A | C12: 40
A13: 12"X10 Blade- ('S' Type Blade) | B13: TS-8805-B | C13: 430
A14: 14"X10 B-(Straight Blade) | B14: TST-8801-B | C14: 20
A15: 14x15x18mm flare - CUT TYPE | C15: 82
A16: 14x15x18mm ORING - CUT TYPE | C16: 2
A17: 14x18x20mm flare | C17: 90
A18: 14x21x20mm flare | C18: 50
A19: 14x21x22mm flare | C19: 70
A20: 14x23x16mm flare | C20: 60
A21: 14x23x20mm flare | C21: 30
A22: 14x23x22mm flare | C22: 10
A23: 14X25X20MM flare | C23: 200
A24: 14x25x26mm flare | B24: 142526 | C24: 10
A25: 14X28X20MM flare | C25: 55
A26: 14X30X20MM flare | C26: 30
A27: 15mm flare iron nut | C27: 55
A28: 1PC SAMPLE SEND BY COURIER | C28: 1
A29: 2 PCS 86125 SCHEME OF 86541Q5 WAS NOT SUPPLIED IN 2019-0250, | C29: 2
A30: 25x28x20 | C30: 76
A31: 25x28x26 | C31: 20
A32: 3 Speed A/C Santro Switch | B32: PC-1001 | C32: 200
A33: 4 PCS 507 IN MULTIGROOVE | B33: 5H11-507MG | C33: 130
A34: 4 PCS 507-V GROVE PULLEY | B34: 5H11 | C34: 12
A35: 4 PCS 508 IN MULTIGROOVE | B35: 5H14-508MG | C35: 14
A36: 4 PCS 508-V GROVE PULLEY | B36: 5H14 | C36: 4
A37: 4 Speed A/C Xing Switch | C37: 145
A38: 404 BAZEL | B38: SEA-NAIR | C38: 32
A39: 507 IN MULTIGROOVE | B39: 5H11-507MG | C39: 31
A40: 507 IN MULTIGROOVE FREE WITH COOLING COIL | B40: 5H11-507MG | C40: 1
A41: 507 Small Single | B41: PC-7201 | C41: 25
A42: 507 V-GROVE FREE WITH CC | B42: 5H11 | C42: 1
A43: 507/508 single seal | B43: PC-7053A PC-7200 | C43: 200
A44: 507-7PK (WITHOUT BEARING) | B44: SDN-101/507/7PK | C44: 454
A45: 507-V GROVE PULLEY | B45: 5H11 | C45: 26
A46: 507-V GROVE PULLEY FREE WITH CC | B46: 5H11 | C46: 2
A47: 507-V GROVE PULLEY FREE WITH CC SCHEME | B47: 5H11 | C47: 1
A48: 507-V GROVE PULLEY FREE WITH COOLING COIL | B48: 5H11 | C48: 1
A49: 508 (SD7H15) IN MULTIGROOVE | B49: 5H14-508MG | C49: 10
... A54: 510-V GROVE PULLEY | B54: COMPANY-A | C54: 11
A55: 6 PCS AL.PIPE WITH CONNECTOR FITTING SAMPLE FOR Contact-181 | C55: 0
A56: 7+1PCS i10 grand cc FREE TILL 31.03.19 | B56: PCP-E07638 | C56: 1
A57: 747 THERMOAMPLIFIER (NEW) (BOLERO, AMBASDOR) | B57: TK-66001 | C57: 135
A58: 8mm oring iron nut | C58: 135
A59: A6 | B59: PC-8026 | C59: 2
A60: ACCENT | B60: 30BD40DU 305523 | C60: 7.5
A61: ACCENT | B61: PC-0213 | C61: 10
A62: ACCENT | B62: PC-2126 | C62: 50
A63: ACCENT | B63: PCP-E82420 | C63: 199
A64: ACCENT (BLOCK TYPE) | B64: FK-C906 | C64: 15
A65: ACCENT BIG DEISAL / SCORPIO PETROL / SONATA / TRAVERA | B65: SD-1002-MC // SDN-1007/MC/ACCENT CRDI // SD-138MC/MHWK // SD-100MC/SCR | C65: 70
A66: ACCENT BIG DEISAL / SCORPIO PETROL / SONATA / TRAVERA | B66: SD-100MC/SCR | C66: 40
A67: ACCENT CRD-I | B67: PC-86064B | C67: 17
A68: ACCENT HUB / TRAVERA | B68: SD-1011ACRDI-MC // SD-206CP/SCR | C68: 3
A69: ACCENT-PETROL | B69: PC-86064B | C69: 5
A70: ADOPTER 6002 | C70: 20
A71: ADOPTER OF R/D6002 F TO O | C71: 500
A72: PC3600 COMPRESSOR FREE | C72: 1
A73: COMPANY-A 3600 (SUBROS) | B73: PC-3600 | C73: 14
A74: COMPANY-A CONDENSER | C74: 0
A75: COMPANY-A COOLING COIL | C75: 1
A76: ALTIS -DSL | B76: PC-86083 | C76: 29
A77: ALTIS -DSL- Q5 | B77: PC-86083-Q5 | C77: 39
A78: ALTIS -PTL | B78: PC-86032 | C78: 4
A79: ALTIS-(DENSO TYPE) | B79: PCP-E10209 | C79: 2
A80: ALTO | B80: 30BGS32-DST 30BD5220DU 305220 | C80: 250
A81: ALTO | B81: FK-1089D | C81: 191
A82: ALTO 800 | B82: PC-86634 | C82: 11
A83: ALTO 800 | B83: SD150MC/ALTO 800 | C83: 8
A84: ALTO 800 | B84: SD-226CP/A-STAR, SD-224CP/SX4 SD238CP/ETOS-DSL, SD-208CP/XYLO D2, SD244CP/ALTO 800 | C84: 3
A85: ALTO 800 | B85: SD345PL/ALTO 800 | C85: 3
A86: ALTO 800 | B86: SDN056/ALTO 800 | C86: 21
A87: ALTO K-10 | B87: PC-0701 | C87: 5
... A93: ANY COMP OF HCC | B93: PC-7034A | C93: 65
A94: AS PER Contact, 5 PCS BOLOERO MEG SD102MC/BLR. WAS NOT FOUND IN CLUTCH SET OF BOLERO, IT IS NOT POSSIBLE BUT AS A SPECIAL CASE WE ACCEPT HIS REQUEST | C94: 5
A95: ASHOK LEYLAND STILE | B95: PCP-E12109 | C95: 6
A96: ASSORTED MODEL 1 HOSE FITTING WITH CATORI | C96: 50
A97: ASSORTED MODEL 2 HOSE FITTING WITH CATORI | C97: 50
A98: ASSORTED MODEL 3 HOSE FITTING WITH CATORI | C98: 50
A99: A-STAR | B99: PC-86274 | C99: 3
A100: A-STAR | B100: PCP-E10681R | C100: 1
A101: A-STAR | B101: SD-136MC/A-STAR | C101: 35
A102: A-STAR | B102: SDN-003/ASTAR | C102: 170
A103: AUDI (ORIGINAL MADE IN GERMANY) | B103: PC-9191B | C103: 17
A104: AUDI A3 PREMIUM Q5 | B104: PCP-C86283Q5 | C104: 4
A105: AUDI A4 NEW (DENSO TYPE) | B105: PCP-E10094 | C105: 4
A106: AUDI A6 PREMIUM Q5 | B106: PCP-C86082 | C106: 5
A107: AUDI Q3 PREMIUM Q5 | B107: PCP-C86020 | C107: 23
A108: AUDI Q7 (REAR) | B108: PCP-E10065 | C108: 20
A109: AUDI Q7 PREMIUM Q5 | B109: PCP-C86832 | C109: 3
A110: AVEO | B110: PC-1209 | C110: 10
... A130: BMW E90 (X1)-DENSO TYPE | B130: PCP-E10090 | C130: 8
A131: BMW E90DSL- SMALL | C131: 1
...

Sheet Condenser Audit
A1: CONDENSER (Part 1) — AUDIT 2019
A2: 221 Recon condenser rows: Challan recounted from active challan lines (Pivot Data, 01.01–13.05.19); every Part 1 ledger sale traced to its challan. Stock = Part 1 TOTAL SOLD.
B4: AT A GLANCE | C4: Rows | D4: Gap (pcs)
B5: Rows reviewed | C5: 221
B6: Tie (no gap) before audit | C6: 93
B7: Fixed — Recon formula missed challan lines | C7: 4 | D7: 18
B8: Explained — gap fully traced to ledger postings (noted on Recon, green) | C8: 69 | D8: 699
B10: CONFLICTS FOR DECISION | C10: Rows | D10: Gap (pcs)
B11: One code used for several car models | C11: 14 | D11: 712
B12: Ledger qty differs from challan line | C12: 12 | D12: 255
B13: Ledger sale, no challan line under this code | C13: 15 | D13: 234
B14: Ledger postings not fully traced | C14: 14 | D14: 150
B15: Total | C15: =SUM(C11:C14) -> 55 | D15: =SUM(D11:D14) -> 1351
A17: CONFLICT REGISTER
A18: # | B18: Conflict | C18: Recon row | D18: Part | E18: Code | F18: Recon Challan | G18: Challan lines | H18: Ledger sold | I18: Gap / detail
A19: 1 | B19: One code used for several car models | C19: 192 | D19: VERNA (FLUDIC)-Q5 | E19: PC-86541-Q5 | F19: 0 | G19: 240 | H19: 231 | I19: -231 — Lines under PC-86541-Q5 (240 pcs) carry: I-20 (DSL OLD)-Q5 / VARNA FLUDIC-DSL-Q5 / VARNA FLUDIC-DSL-Q5 WITH SCHEME; ledger books 231.
A20: 2 | B20: One code used for several car models | C20: 104 | D20: I-10 GRAND (PTL) | E20: PC-86448B | F20: 0 | G20: 205 | H20: 197 | I20: -197 — Lines under PC-86448B (205 pcs) carry: I-20 NEW PAD TYPE / I-10 GRAND (PTL) / I-20 (ELITE); ledger books 197.
A21: 3 | B21: One code used for several car models | C21: 197 | D21: WAGON R / ALTO (NEW) | E21: PC-86393 | F21: 498 | G21: 498 | H21: 452 | I21: 46 — Lines under PC-86393 (498 pcs) carry: WAGON R / ALTO (NEW)-K10 / ZEN ESTILO -T2; ledger books 452.
A22: 4 | B22: One code used for several car models | C22: 193 | D22: VERSA | E22: PC-86365 | F22: 129 | G22: 128 | H22: 84 | I22: 45 — Lines under PC-86365 (128 pcs) carry: EECO / VERSA; ledger books 84.
A23: 5 | B23: One code used for several car models | C23: 161 | D23: SAIL DSL | E23: PC-86910 | F23: 143 | G23: 143 | H23: 103 | I23: 40 — Lines under PC-86910 (143 pcs) carry: SAIL-DSL / TATA ARIA-DSL; ledger books 103.
A24: 6 | B24: One code used for several car models | C24: 178 | D24: SWIFT-NEW | E24: PC-86539 | F24: 335 | G24: 335 | H24: 297 | I24: 38 — Lines under PC-86539 (335 pcs) carry: SWIFT (NEW) / ERTIGA / SX 4 (NEW); ledger books 297.
A25: 7 | B25: One code used for several car models | C25: 179 | D25: SWIFT-NEW-Q5 | E25: PC-86539-Q5 | F25: 0 | G25: 58 | H25: 33 | I25: -33 — Lines under PC-86539-Q5 (58 pcs) carry: SWIFT (NEW)-Q5 / SX 4 (NEW)-Q5 / ERTIGA-Q5; ledger books 33.
A26: 8 | B26: One code used for several car models | C26: 123 | D26: INNOVA-T4-Q5 | E26: PC-86536-Q5 | F26: 81 | G26: 81 | H26: 60 | I26: 21 — Lines under PC-86536-Q5 (81 pcs) carry: INNOVA - T4 (Q5) / INNOVA - T4 (Q5) FREE 1 PCS PC CC I-10 GRAND ON 7 PCS 86536Q5; ledger books 60.
A27: 9 | B27: One code used for several car models | C27: 200 | D27: XYLO-Q5 SUBROS (BIG) | E27: PC-86449 | F27: 89 | G27: 88 | H27: 68 | I27: 21 — Lines under PC-86449 (88 pcs) carry: TEMPO TRAVELLER-NEW / XYLO SUBROS 3680 -BIG; ledger books 68.
A28: 10 | B28: One code used for several car models | C28: 50 | D28: DUSTER / TERRANO-110CC | E28: PC-86920 | F28: 69 | G28: 69 | H28: 50 | I28: 19 — Lines under PC-86920 (69 pcs) carry: DUSTER DSL 110CC / TERRANO; ledger books 50.
A29: 11 | B29: One code used for several car models | C29: 13 | D29: AUDI Q3 | E29: PCP-C86020 | F29: 28 | G29: 28 | H29: 20 | I29: 8 — Lines under PCP-C86020 (28 pcs) carry: AUDI Q3 PREMIUM Q5 / SKODA SUPERB (NEW) PREMIUM Q5; ledger books 20.
A30: 12 | B30: One code used for several car models | C30: 102 | D30: I-10 GRAND (DSL) | E30: PC-86655 | F30: 107 | G30: 107 | H30: 102 | I30: 5 — Lines under PC-86655 (107 pcs) carry: I-10 GRAND (DSL) / XCENT (DSL) / VARNA FLUDIC-PTL; ledger books 102.
... A73: 55 | B73: Ledger postings not fully traced | C73: 157 | D73: RITZ PETROL-Q5 | E73: PC-86370AQ5 | F73: 34 | G73: 34 | H73: 33 | I73: 1 — not posted: 2019-0349:1, 2019-0387:1, 2019-0442:1

Sheet CHALLAN
W1: ChallanNo | X1: Cancelled | Y1: CleanCode | Z1: Qty | AB1: CancelledChallans
W2: =IF(LEFT($H2&"",5)="2019-",$H2,"") | X2: =IF($W2="",0,IF(COUNTIF($AB$2:$AB$80,$W2)>0,1,0)) | Y2: =IF($C2="","",UPPER(TRIM(IFERROR(LEFT($C2&"",FIND("/",$C2&"")-1),$C2&"")))) | Z2: =IFERROR(IF(ISNUMBER($G2),$G2,0),0) | AB2: 2019-0001
A3: To, | G3: Dated.: | H3: 01.01.19 | W3: =IF(LEFT($H3&"",5)="2019-",$H3,W2) | X3: =IF($W3="",0,IF(COUNTIF($AB$2:$AB$80,$W3)>0,1,0)) | Y3: =IF($C3="","",UPPER(TRIM(IFERROR(LEFT($C3&"",FIND("/",$C3&"")-1),$C3&"")))) | Z3: =IFERROR(IF(ISNUMBER($G3),$G3,0),0) | AB3: 2019-0003
A4: Dealer-150 | F4: GST-Challan # | H4: 2019-0001 | W4: =IF(LEFT($H4&"",5)="2019-",$H4,W3) | X4: =IF($W4="",0,IF(COUNTIF($AB$2:$AB$80,$W4)>0,1,0)) | Y4: =IF($C4="","",UPPER(TRIM(IFERROR(LEFT($C4&"",FIND("/",$C4&"")-1),$C4&"")))) | Z4: =IFERROR(IF(ISNUMBER($G4),$G4,0),0) | AB4: 2019-0004
A5: Dealer-159 | W5: =IF(LEFT($H5&"",5)="2019-",$H5,W4) | X5: =IF($W5="",0,IF(COUNTIF($AB$2:$AB$80,$W5)>0,1,0)) | Y5: =IF($C5="","",UPPER(TRIM(IFERROR(LEFT($C5&"",FIND("/",$C5&"")-1),$C5&"")))) | Z5: =IFERROR(IF(ISNUMBER($G5),$G5,0),0) | AB5: 2019-0007
A6: Address line (redacted) | W6: =IF(LEFT($H6&"",5)="2019-",$H6,W5) | X6: =IF($W6="",0,IF(COUNTIF($AB$2:$AB$80,$W6)>0,1,0)) | Y6: =IF($C6="","",UPPER(TRIM(IFERROR(LEFT($C6&"",FIND("/",$C6&"")-1),$C6&"")))) | Z6: =IFERROR(IF(ISNUMBER($G6),$G6,0),0) | AB6: 2019-0010
A7: Address line (redacted) | W7: =IF(LEFT($H7&"",5)="2019-",$H7,W6) | X7: =IF($W7="",0,IF(COUNTIF($AB$2:$AB$80,$W7)>0,1,0)) | Y7: =IF($C7="","",UPPER(TRIM(IFERROR(LEFT($C7&"",FIND("/",$C7&"")-1),$C7&"")))) | Z7: =IFERROR(IF(ISNUMBER($G7),$G7,0),0) | AB7: 2019-0018
A8: GSTIN: | B8: GSTIN-MASKED | W8: =IF(LEFT($H8&"",5)="2019-",$H8,W7) | X8: =IF($W8="",0,IF(COUNTIF($AB$2:$AB$80,$W8)>0,1,0)) | Y8: =IF($C8="","",UPPER(TRIM(IFERROR(LEFT($C8&"",FIND("/",$C8&"")-1),$C8&"")))) | Z8: =IFERROR(IF(ISNUMBER($G8),$G8,0),0) | AB8: 2019-0040
W9: =IF(LEFT($H9&"",5)="2019-",$H9,W8) | X9: =IF($W9="",0,IF(COUNTIF($AB$2:$AB$80,$W9)>0,1,0)) | Y9: =IF($C9="","",UPPER(TRIM(IFERROR(LEFT($C9&"",FIND("/",$C9&"")-1),$C9&"")))) | Z9: =IFERROR(IF(ISNUMBER($G9),$G9,0),0) | AB9: 2019-0042
A10: Through : | W10: =IF(LEFT($H10&"",5)="2019-",$H10,W9) | X10: =IF($W10="",0,IF(COUNTIF($AB$2:$AB$80,$W10)>0,1,0)) | Y10: =IF($C10="","",UPPER(TRIM(IFERROR(LEFT($C10&"",FIND("/",$C10&"")-1),$C10&"")))) | Z10: =IFERROR(IF(ISNUMBER($G10),$G10,0),0) | AB10: 2019-0060
A11: Address line (redacted) | W11: =IF(LEFT($H11&"",5)="2019-",$H11,W10) | X11: =IF($W11="",0,IF(COUNTIF($AB$2:$AB$80,$W11)>0,1,0)) | Y11: =IF($C11="","",UPPER(TRIM(IFERROR(LEFT($C11&"",FIND("/",$C11&"")-1),$C11&"")))) | Z11: =IFERROR(IF(ISNUMBER($G11),$G11,0),0) | AB11: 2019-0064
W12: =IF(LEFT($H12&"",5)="2019-",$H12,W11) | X12: =IF($W12="",0,IF(COUNTIF($AB$2:$AB$80,$W12)>0,1,0)) | Y12: =IF($C12="","",UPPER(TRIM(IFERROR(LEFT($C12&"",FIND("/",$C12&"")-1),$C12&"")))) | Z12: =IFERROR(IF(ISNUMBER($G12),$G12,0),0) | AB12: 2019-0065
A13: Dear Sir, | W13: =IF(LEFT($H13&"",5)="2019-",$H13,W12) | X13: =IF($W13="",0,IF(COUNTIF($AB$2:$AB$80,$W13)>0,1,0)) | Y13: =IF($C13="","",UPPER(TRIM(IFERROR(LEFT($C13&"",FIND("/",$C13&"")-1),$C13&"")))) | Z13: =IFERROR(IF(ISNUMBER($G13),$G13,0),0) | AB13: 2019-0069
A14: According to instructions we are sending followng goods. Please acknowledge the same and after your | W14: =IF(LEFT($H14&"",5)="2019-",$H14,W13) | X14: =IF($W14="",0,IF(COUNTIF($AB$2:$AB$80,$W14)>0,1,0)) | Y14: =IF($C14="","",UPPER(TRIM(IFERROR(LEFT($C14&"",FIND("/",$C14&"")-1),$C14&"")))) | Z14: =IFERROR(IF(ISNUMBER($G14),$G14,0),0) | AB14: 2019-0076
A15: acknowledgement we will issue you sales invoice. | W15: =IF(LEFT($H15&"",5)="2019-",$H15,W14) | X15: =IF($W15="",0,IF(COUNTIF($AB$2:$AB$80,$W15)>0,1,0)) | Y15: =IF($C15="","",UPPER(TRIM(IFERROR(LEFT($C15&"",FIND("/",$C15&"")-1),$C15&"")))) | Z15: =IFERROR(IF(ISNUMBER($G15),$G15,0),0) | AB15: 2019-0078
A16: S.No. | B16: Description | C16: PART NO. | D16: CTN | E16: PCS CTN | F16: QTY | G16: TOTAL QTY | H16: PRICE | I16: AMOUNT | W16: =IF(LEFT($H16&"",5)="2019-",$H16,W15) | X16: =IF($W16="",0,IF(COUNTIF($AB$2:$AB$80,$W16)>0,1,0)) | Y16: =IF($C16="","",UPPER(TRIM(IFERROR(LEFT($C16&"",FIND("/",$C16&"")-1),$C16&"")))) | Z16: =IFERROR(IF(ISNUMBER($G16),$G16,0),0) | AB16: 2019-0105
B17: COMPANY-A CONDENSER | W17: =IF(LEFT($H17&"",5)="2019-",$H17,W16) | X17: =IF($W17="",0,IF(COUNTIF($AB$2:$AB$80,$W17)>0,1,0)) | Y17: =IF($C17="","",UPPER(TRIM(IFERROR(LEFT($C17&"",FIND("/",$C17&"")-1),$C17&"")))) | Z17: =IFERROR(IF(ISNUMBER($G17),$G17,0),0) | AB17: 2019-0106
B18: BEAT (PTL) | C18: PC-86535 | F18: 1 | G18: =+F18 | H18: 1 | I18: =+H18*G18 | W18: =IF(LEFT($H18&"",5)="2019-",$H18,W17) | X18: =IF($W18="",0,IF(COUNTIF($AB$2:$AB$80,$W18)>0,1,0)) | Y18: =IF($C18="","",UPPER(TRIM(IFERROR(LEFT($C18&"",FIND("/",$C18&"")-1),$C18&"")))) | Z18: =IFERROR(IF(ISNUMBER($G18),$G18,0),0) | AB18: 2019-0110
B19: DUSTER NEW DSL 2016 (BEHR-Q5) | C19: PC-86909Q5 | D19: 1 | F19: 2 | G19: =+F19 | H19: 1 | I19: =+H19*G19 | W19: =IF(LEFT($H19&"",5)="2019-",$H19,W18) | X19: =IF($W19="",0,IF(COUNTIF($AB$2:$AB$80,$W19)>0,1,0)) | Y19: =IF($C19="","",UPPER(TRIM(IFERROR(LEFT($C19&"",FIND("/",$C19&"")-1),$C19&"")))) | Z19: =IFERROR(IF(ISNUMBER($G19),$G19,0),0) | AB19: 2019-0120
B20: ENJOY-DSL | C20: PC-86201 | D20: 1 | F20: 2 | G20: =+F20 | H20: 1 | I20: =+H20*G20 | W20: =IF(LEFT($H20&"",5)="2019-",$H20,W19) | X20: =IF($W20="",0,IF(COUNTIF($AB$2:$AB$80,$W20)>0,1,0)) | Y20: =IF($C20="","",UPPER(TRIM(IFERROR(LEFT($C20&"",FIND("/",$C20&"")-1),$C20&"")))) | Z20: =IFERROR(IF(ISNUMBER($G20),$G20,0),0) | AB20: 2019-0121
B21: FLUENCE RENAULT -Q5 | C21: PC-86769BAQ5 | D21: 1 | F21: 2 | G21: =+F21 | H21: 1 | I21: =+H21*G21 | W21: =IF(LEFT($H21&"",5)="2019-",$H21,W20) | X21: =IF($W21="",0,IF(COUNTIF($AB$2:$AB$80,$W21)>0,1,0)) | Y21: =IF($C21="","",UPPER(TRIM(IFERROR(LEFT($C21&"",FIND("/",$C21&"")-1),$C21&"")))) | Z21: =IFERROR(IF(ISNUMBER($G21),$G21,0),0) | AB21: 2019-0124
B22: HONDA AMAZE -DSL-Q5 | C22: PC-86902Q5 | F22: 2 | G22: =+F22 | H22: 1 | I22: =+H22*G22 | W22: =IF(LEFT($H22&"",5)="2019-",$H22,W21) | X22: =IF($W22="",0,IF(COUNTIF($AB$2:$AB$80,$W22)>0,1,0)) | Y22: =IF($C22="","",UPPER(TRIM(IFERROR(LEFT($C22&"",FIND("/",$C22&"")-1),$C22&"")))) | Z22: =IFERROR(IF(ISNUMBER($G22),$G22,0),0) | AB22: 2019-0130
B23: HONDA CITY 2016 I.D.TEC DSL-Q5 | C23: PC-86807-Q5 | F23: 2 | G23: =+F23 | H23: 1 | I23: =+H23*G23 | W23: =IF(LEFT($H23&"",5)="2019-",$H23,W22) | X23: =IF($W23="",0,IF(COUNTIF($AB$2:$AB$80,$W23)>0,1,0)) | Y23: =IF($C23="","",UPPER(TRIM(IFERROR(LEFT($C23&"",FIND("/",$C23&"")-1),$C23&"")))) | Z23: =IFERROR(IF(ISNUMBER($G23),$G23,0),0) | AB23: 2019-0135
B24: I-20 (ELITE)-Q5 | C24: PC-86448-BAQ5 | F24: 3 | G24: =+F24 | H24: 1 | I24: =+H24*G24 | W24: =IF(LEFT($H24&"",5)="2019-",$H24,W23) | X24: =IF($W24="",0,IF(COUNTIF($AB$2:$AB$80,$W24)>0,1,0)) | Y24: =IF($C24="","",UPPER(TRIM(IFERROR(LEFT($C24&"",FIND("/",$C24&"")-1),$C24&"")))) | Z24: =IFERROR(IF(ISNUMBER($G24),$G24,0),0) | AB24: 2019-0140
B25: HPLP | W25: =IF(LEFT($H25&"",5)="2019-",$H25,W24) | X25: =IF($W25="",0,IF(COUNTIF($AB$2:$AB$80,$W25)>0,1,0)) | Y25: =IF($C25="","",UPPER(TRIM(IFERROR(LEFT($C25&"",FIND("/",$C25&"")-1),$C25&"")))) | Z25: =IFERROR(IF(ISNUMBER($G25),$G25,0),0) | AB25: 2019-0143
B26: TRAVERA-4 PIN | C26: PC-2126 | E26: 25 | F26: =+E26 | G26: =+F26 | H26: 1 | I26: =+H26*G26 | W26: =IF(LEFT($H26&"",5)="2019-",$H26,W25) | X26: =IF($W26="",0,IF(COUNTIF($AB$2:$AB$80,$W26)>0,1,0)) | Y26: =IF($C26="","",UPPER(TRIM(IFERROR(LEFT($C26&"",FIND("/",$C26&"")-1),$C26&"")))) | Z26: =IFERROR(IF(ISNUMBER($G26),$G26,0),0) | AB26: 2019-0160
B27: COMPANY-A COOLING COIL | W27: =IF(LEFT($H27&"",5)="2019-",$H27,W26) | X27: =IF($W27="",0,IF(COUNTIF($AB$2:$AB$80,$W27)>0,1,0)) | Y27: =IF($C27="","",UPPER(TRIM(IFERROR(LEFT($C27&"",FIND("/",$C27&"")-1),$C27&"")))) | Z27: =IFERROR(IF(ISNUMBER($G27),$G27,0),0) | AB27: 2019-0163
B28: TATA VENTURE-FRONT | C28: PC-531R | F28: 1 | G28: =+F28 | H28: 1 | I28: =+H28*G28 | W28: =IF(LEFT($H28&"",5)="2019-",$H28,W27) | X28: =IF($W28="",0,IF(COUNTIF($AB$2:$AB$80,$W28)>0,1,0)) | Y28: =IF($C28="","",UPPER(TRIM(IFERROR(LEFT($C28&"",FIND("/",$C28&"")-1),$C28&"")))) | Z28: =IFERROR(IF(ISNUMBER($G28),$G28,0),0) | AB28: 2019-0164
B29: TOKODEN BLOWER MOTOR | W29: =IF(LEFT($H29&"",5)="2019-",$H29,W28) | X29: =IF($W29="",0,IF(COUNTIF($AB$2:$AB$80,$W29)>0,1,0)) | Y29: =IF($C29="","",UPPER(TRIM(IFERROR(LEFT($C29&"",FIND("/",$C29&"")-1),$C29&"")))) | Z29: =IFERROR(IF(ISNUMBER($G29),$G29,0),0) | AB29: 2019-0173
B30: SKODA LAURA WITH RESISTANCE | C30: TS-3308B | D30: 1 | F30: 2 | G30: =+F30 | H30: 1 | I30: =+H30*G30 | W30: =IF(LEFT($H30&"",5)="2019-",$H30,W29) | X30: =IF($W30="",0,IF(COUNTIF($AB$2:$AB$80,$W30)>0,1,0)) | Y30: =IF($C30="","",UPPER(TRIM(IFERROR(LEFT($C30&"",FIND("/",$C30&"")-1),$C30&"")))) | Z30: =IFERROR(IF(ISNUMBER($G30),$G30,0),0) | AB30: 2019-0181
W31: =IF(LEFT($H31&"",5)="2019-",$H31,W30) | X31: =IF($W31="",0,IF(COUNTIF($AB$2:$AB$80,$W31)>0,1,0)) | Y31: =IF($C31="","",UPPER(TRIM(IFERROR(LEFT($C31&"",FIND("/",$C31&"")-1),$C31&"")))) | Z31: =IFERROR(IF(ISNUMBER($G31),$G31,0),0) | AB31: 2019-0190
W32: =IF(LEFT($H32&"",5)="2019-",$H32,W31) | X32: =IF($W32="",0,IF(COUNTIF($AB$2:$AB$80,$W32)>0,1,0)) | Y32: =IF($C32="","",UPPER(TRIM(IFERROR(LEFT($C32&"",FIND("/",$C32&"")-1),$C32&"")))) | Z32: =IFERROR(IF(ISNUMBER($G32),$G32,0),0) | AB32: 2019-0192
W33: =IF(LEFT($H33&"",5)="2019-",$H33,W32) | X33: =IF($W33="",0,IF(COUNTIF($AB$2:$AB$80,$W33)>0,1,0)) | Y33: =IF($C33="","",UPPER(TRIM(IFERROR(LEFT($C33&"",FIND("/",$C33&"")-1),$C33&"")))) | Z33: =IFERROR(IF(ISNUMBER($G33),$G33,0),0) | AB33: 2019-0228
I34: =SUM(I17:I33) | W34: =IF(LEFT($H34&"",5)="2019-",$H34,W33) | X34: =IF($W34="",0,IF(COUNTIF($AB$2:$AB$80,$W34)>0,1,0)) | Y34: =IF($C34="","",UPPER(TRIM(IFERROR(LEFT($C34&"",FIND("/",$C34&"")-1),$C34&"")))) | Z34: =IFERROR(IF(ISNUMBER($G34),$G34,0),0) | AB34: 2019-0260
W35: =IF(LEFT($H35&"",5)="2019-",$H35,W34) | X35: =IF($W35="",0,IF(COUNTIF($AB$2:$AB$80,$W35)>0,1,0)) | Y35: =IF($C35="","",UPPER(TRIM(IFERROR(LEFT($C35&"",FIND("/",$C35&"")-1),$C35&"")))) | Z35: =IFERROR(IF(ISNUMBER($G35),$G35,0),0) | AB35: 2019-0264
B36: cancel shifted to 2018-1151/31.12.18 | W36: =IF(LEFT($H36&"",5)="2019-",$H36,W35) | X36: =IF($W36="",0,IF(COUNTIF($AB$2:$AB$80,$W36)>0,1,0)) | Y36: =IF($C36="","",UPPER(TRIM(IFERROR(LEFT($C36&"",FIND("/",$C36&"")-1),$C36&"")))) | Z36: =IFERROR(IF(ISNUMBER($G36),$G36,0),0) | AB36: 2019-0265
W37: =IF(LEFT($H37&"",5)="2019-",$H37,W36) | X37: =IF($W37="",0,IF(COUNTIF($AB$2:$AB$80,$W37)>0,1,0)) | Y37: =IF($C37="","",UPPER(TRIM(IFERROR(LEFT($C37&"",FIND("/",$C37&"")-1),$C37&"")))) | Z37: =IFERROR(IF(ISNUMBER($G37),$G37,0),0) | AB37: 2019-0268
B38: NOTE: ONCE GOODS SOLD WILL NOT BE TAKEN BACK | W38: =IF(LEFT($H38&"",5)="2019-",$H38,W37) | X38: =IF($W38="",0,IF(COUNTIF($AB$2:$AB$80,$W38)>0,1,0)) | Y38: =IF($C38="","",UPPER(TRIM(IFERROR(LEFT($C38&"",FIND("/",$C38&"")-1),$C38&"")))) | Z38: =IFERROR(IF(ISNUMBER($G38),$G38,0),0) | AB38: 2019-0286
B39: VALIDITY: 7DAYS FROM THE DATE | C39: G.TOTAL | D39: =SUM(D17:D38) | E39: =IF(H39=I39,"OK","NO") | F39: =SUM(F17:F38) | G39: =SUM(G17:G38) | H39: =SUMPRODUCT(F14:F37,H14:H37) | I39: =+I34-I35 | N39: =+I39+72000+80000 | W39: =IF(LEFT($H39&"",5)="2019-",$H39,W38) | X39: =IF($W39="",0,IF(COUNTIF($AB$2:$AB$80,$W39)>0,1,0)) | Y39: =IF($C39="","",UPPER(TRIM(IFERROR(LEFT($C39&"",FIND("/",$C39&"")-1),$C39&"")))) | Z39: =IFERROR(IF(ISNUMBER($G39),$G39,0),0) | AB39: 2019-0300
B40: OF ISSUED | W40: =IF(LEFT($H40&"",5)="2019-",$H40,W39) | X40: =IF($W40="",0,IF(COUNTIF($AB$2:$AB$80,$W40)>0,1,0)) | Y40: =IF($C40="","",UPPER(TRIM(IFERROR(LEFT($C40&"",FIND("/",$C40&"")-1),$C40&"")))) | Z40: =IFERROR(IF(ISNUMBER($G40),$G40,0),0) | AB40: 2019-0306
A41: PAYMENT TERMS: 100% ADVANCE | W41: =IF(LEFT($H41&"",5)="2019-",$H41,W40) | X41: =IF($W41="",0,IF(COUNTIF($AB$2:$AB$80,$W41)>0,1,0)) | Y41: =IF($C41="","",UPPER(TRIM(IFERROR(LEFT($C41&"",FIND("/",$C41&"")-1),$C41&"")))) | Z41: =IFERROR(IF(ISNUMBER($G41),$G41,0),0) | AB41: 2019-0308
W42: =IF(LEFT($H42&"",5)="2019-",$H42,W41) | X42: =IF($W42="",0,IF(COUNTIF($AB$2:$AB$80,$W42)>0,1,0)) | Y42: =IF($C42="","",UPPER(TRIM(IFERROR(LEFT($C42&"",FIND("/",$C42&"")-1),$C42&"")))) | Z42: =IFERROR(IF(ISNUMBER($G42),$G42,0),0) | AB42: 2019-0325
W43: =IF(LEFT($H43&"",5)="2019-",$H43,W42) | X43: =IF($W43="",0,IF(COUNTIF($AB$2:$AB$80,$W43)>0,1,0)) | Y43: =IF($C43="","",UPPER(TRIM(IFERROR(LEFT($C43&"",FIND("/",$C43&"")-1),$C43&"")))) | Z43: =IFERROR(IF(ISNUMBER($G43),$G43,0),0) | AB43: 2019-0334
W44: =IF(LEFT($H44&"",5)="2019-",$H44,W43) | X44: =IF($W44="",0,IF(COUNTIF($AB$2:$AB$80,$W44)>0,1,0)) | Y44: =IF($C44="","",UPPER(TRIM(IFERROR(LEFT($C44&"",FIND("/",$C44&"")-1),$C44&"")))) | Z44: =IFERROR(IF(ISNUMBER($G44),$G44,0),0) | AB44: 2019-0341
W45: =IF(LEFT($H45&"",5)="2019-",$H45,W44) | X45: =IF($W45="",0,IF(COUNTIF($AB$2:$AB$80,$W45)>0,1,0)) | Y45: =IF($C45="","",UPPER(TRIM(IFERROR(LEFT($C45&"",FIND("/",$C45&"")-1),$C45&"")))) | Z45: =IFERROR(IF(ISNUMBER($G45),$G45,0),0) | AB45: 2019-0342
W46: =IF(LEFT($H46&"",5)="2019-",$H46,W45) | X46: =IF($W46="",0,IF(COUNTIF($AB$2:$AB$80,$W46)>0,1,0)) | Y46: =IF($C46="","",UPPER(TRIM(IFERROR(LEFT($C46&"",FIND("/",$C46&"")-1),$C46&"")))) | Z46: =IFERROR(IF(ISNUMBER($G46),$G46,0),0) | AB46: 2019-0344
W47: =IF(LEFT($H47&"",5)="2019-",$H47,W46) | X47: =IF($W47="",0,IF(COUNTIF($AB$2:$AB$80,$W47)>0,1,0)) | Y47: =IF($C47="","",UPPER(TRIM(IFERROR(LEFT($C47&"",FIND("/",$C47&"")-1),$C47&"")))) | Z47: =IFERROR(IF(ISNUMBER($G47),$G47,0),0) | AB47: 2019-0346
W48: =IF(LEFT($H48&"",5)="2019-",$H48,W47) | X48: =IF($W48="",0,IF(COUNTIF($AB$2:$AB$80,$W48)>0,1,0)) | Y48: =IF($C48="","",UPPER(TRIM(IFERROR(LEFT($C48&"",FIND("/",$C48&"")-1),$C48&"")))) | Z48: =IFERROR(IF(ISNUMBER($G48),$G48,0),0) | AB48: 2019-0347
W49: =IF(LEFT($H49&"",5)="2019-",$H49,W48) | X49: =IF($W49="",0,IF(COUNTIF($AB$2:$AB$80,$W49)>0,1,0)) | Y49: =IF($C49="","",UPPER(TRIM(IFERROR(LEFT($C49&"",FIND("/",$C49&"")-1),$C49&"")))) | Z49: =IFERROR(IF(ISNUMBER($G49),$G49,0),0) | AB49: 2019-0356
W50: =IF(LEFT($H50&"",5)="2019-",$H50,W49) | X50: =IF($W50="",0,IF(COUNTIF($AB$2:$AB$80,$W50)>0,1,0)) | Y50: =IF($C50="","",UPPER(TRIM(IFERROR(LEFT($C50&"",FIND("/",$C50&"")-1),$C50&"")))) | Z50: =IFERROR(IF(ISNUMBER($G50),$G50,0),0) | AB50: 2019-0358
W51: =IF(LEFT($H51&"",5)="2019-",$H51,W50) | X51: =IF($W51="",0,IF(COUNTIF($AB$2:$AB$80,$W51)>0,1,0)) | Y51: =IF($C51="","",UPPER(TRIM(IFERROR(LEFT($C51&"",FIND("/",$C51&"")-1),$C51&"")))) | Z51: =IFERROR(IF(ISNUMBER($G51),$G51,0),0) | AB51: 2019-0386
W52: =IF(LEFT($H52&"",5)="2019-",$H52,W51) | X52: =IF($W52="",0,IF(COUNTIF($AB$2:$AB$80,$W52)>0,1,0)) | Y52: =IF($C52="","",UPPER(TRIM(IFERROR(LEFT($C52&"",FIND("/",$C52&"")-1),$C52&"")))) | Z52: =IFERROR(IF(ISNUMBER($G52),$G52,0),0) | AB52: 2019-0394
A53: PROFORMA / DELIVERY CHALLAN | W53: =IF(LEFT($H53&"",5)="2019-",$H53,W52) | X53: =IF($W53="",0,IF(COUNTIF($AB$2:$AB$80,$W53)>0,1,0)) | Y53: =IF($C53="","",UPPER(TRIM(IFERROR(LEFT($C53&"",FIND("/",$C53&"")-1),$C53&"")))) | Z53: =IFERROR(IF(ISNUMBER($G53),$G53,0),0) | AB53: 2019-0395
W54: =IF(LEFT($H54&"",5)="2019-",$H54,W53) | X54: =IF($W54="",0,IF(COUNTIF($AB$2:$AB$80,$W54)>0,1,0)) | Y54: =IF($C54="","",UPPER(TRIM(IFERROR(LEFT($C54&"",FIND("/",$C54&"")-1),$C54&"")))) | Z54: =IFERROR(IF(ISNUMBER($G54),$G54,0),0) | AB54: 2019-0397
A55: To, | G55: Dated.: | H55: 01.01.19 | W55: =IF(LEFT($H55&"",5)="2019-",$H55,W54) | X55: =IF($W55="",0,IF(COUNTIF($AB$2:$AB$80,$W55)>0,1,0)) | Y55: =IF($C55="","",UPPER(TRIM(IFERROR(LEFT($C55&"",FIND("/",$C55&"")-1),$C55&"")))) | Z55: =IFERROR(IF(ISNUMBER($G55),$G55,0),0) | AB55: 2019-0408
A56: ATTN: Contact-005 | F56: GST-Challan # | H56: 2019-0002 | W56: =IF(LEFT($H56&"",5)="2019-",$H56,W55) | X56: =IF($W56="",0,IF(COUNTIF($AB$2:$AB$80,$W56)>0,1,0)) | Y56: =IF($C56="","",UPPER(TRIM(IFERROR(LEFT($C56&"",FIND("/",$C56&"")-1),$C56&"")))) | Z56: =IFERROR(IF(ISNUMBER($G56),$G56,0),0) | AB56: 2019-0412
A57: Dealer-112 | W57: =IF(LEFT($H57&"",5)="2019-",$H57,W56) | X57: =IF($W57="",0,IF(COUNTIF($AB$2:$AB$80,$W57)>0,1,0)) | Y57: =IF($C57="","",UPPER(TRIM(IFERROR(LEFT($C57&"",FIND("/",$C57&"")-1),$C57&"")))) | Z57: =IFERROR(IF(ISNUMBER($G57),$G57,0),0) | AB57: 2019-0419
A58: Address line (redacted) | W58: =IF(LEFT($H58&"",5)="2019-",$H58,W57) | X58: =IF($W58="",0,IF(COUNTIF($AB$2:$AB$80,$W58)>0,1,0)) | Y58: =IF($C58="","",UPPER(TRIM(IFERROR(LEFT($C58&"",FIND("/",$C58&"")-1),$C58&"")))) | Z58: =IFERROR(IF(ISNUMBER($G58),$G58,0),0) | AB58: 2019-0420
A59: Address line (redacted) | W59: =IF(LEFT($H59&"",5)="2019-",$H59,W58) | X59: =IF($W59="",0,IF(COUNTIF($AB$2:$AB$80,$W59)>0,1,0)) | Y59: =IF($C59="","",UPPER(TRIM(IFERROR(LEFT($C59&"",FIND("/",$C59&"")-1),$C59&"")))) | Z59: =IFERROR(IF(ISNUMBER($G59),$G59,0),0) | AB59: 2019-0421
A60: GSTIN: | B60: GSTIN-MASKED | W60: =IF(LEFT($H60&"",5)="2019-",$H60,W59) | X60: =IF($W60="",0,IF(COUNTIF($AB$2:$AB$80,$W60)>0,1,0)) | Y60: =IF($C60="","",UPPER(TRIM(IFERROR(LEFT($C60&"",FIND("/",$C60&"")-1),$C60&"")))) | Z60: =IFERROR(IF(ISNUMBER($G60),$G60,0),0) | AB60: 2019-0428
A61: Dear Sir, | W61: =IF(LEFT($H61&"",5)="2019-",$H61,W60) | X61: =IF($W61="",0,IF(COUNTIF($AB$2:$AB$80,$W61)>0,1,0)) | Y61: =IF($C61="","",UPPER(TRIM(IFERROR(LEFT($C61&"",FIND("/",$C61&"")-1),$C61&"")))) | Z61: =IFERROR(IF(ISNUMBER($G61),$G61,0),0) | AB61: 2019-0447
A62: According to instructions we are sending followng goods. Please acknowledge the same and after your | W62: =IF(LEFT($H62&"",5)="2019-",$H62,W61) | X62: =IF($W62="",0,IF(COUNTIF($AB$2:$AB$80,$W62)>0,1,0)) | Y62: =IF($C62="","",UPPER(TRIM(IFERROR(LEFT($C62&"",FIND("/",$C62&"")-1),$C62&"")))) | Z62: =IFERROR(IF(ISNUMBER($G62),$G62,0),0) | AB62: 2019-0451
A63: acknowledgement we will issue you sales invoice. | W63: =IF(LEFT($H63&"",5)="2019-",$H63,W62) | X63: =IF($W63="",0,IF(COUNTIF($AB$2:$AB$80,$W63)>0,1,0)) | Y63: =IF($C63="","",UPPER(TRIM(IFERROR(LEFT($C63&"",FIND("/",$C63&"")-1),$C63&"")))) | Z63: =IFERROR(IF(ISNUMBER($G63),$G63,0),0) | AB63: 2019-0452
A64: S.No. | B64: Description | C64: PART NO. | D64: CTN | E64: PCS CTN | F64: QTY | G64: TOTAL QTY | H64: PRICE | I64: AMOUNT | W64: =IF(LEFT($H64&"",5)="2019-",$H64,W63) | X64: =IF($W64="",0,IF(COUNTIF($AB$2:$AB$80,$W64)>0,1,0)) | Y64: =IF($C64="","",UPPER(TRIM(IFERROR(LEFT($C64&"",FIND("/",$C64&"")-1),$C64&"")))) | Z64: =IFERROR(IF(ISNUMBER($G64),$G64,0),0) | AB64: 2019-0464
B65: COMPANY-A CONDENSER | W65: =IF(LEFT($H65&"",5)="2019-",$H65,W64) | X65: =IF($W65="",0,IF(COUNTIF($AB$2:$AB$80,$W65)>0,1,0)) | Y65: =IF($C65="","",UPPER(TRIM(IFERROR(LEFT($C65&"",FIND("/",$C65&"")-1),$C65&"")))) | Z65: =IFERROR(IF(ISNUMBER($G65),$G65,0),0) | AB65: 2019-0483
A66: 1 | B66: BOLERO- R134A (NEW) WITH DRIER | C66: PC-86395 | D66: 3 | E66: 5 | F66: =+E66*D66 | G66: =+E66*D66 | H66: 1 | I66: =+H66*G66 | W66: =IF(LEFT($H66&"",5)="2019-",$H66,W65) | X66: =IF($W66="",0,IF(COUNTIF($AB$2:$AB$80,$W66)>0,1,0)) | Y66: =IF($C66="","",UPPER(TRIM(IFERROR(LEFT($C66&"",FIND("/",$C66&"")-1),$C66&"")))) | Z66: =IFERROR(IF(ISNUMBER($G66),$G66,0),0)
A67: 2 | B67: INDICA BEHR (EV2) | C67: PC-86639 | D67: 1 | E67: 5 | F67: =+E67*D67 | G67: =+E67*D67 | H67: 1 | I67: =+H67*G67 | W67: =IF(LEFT($H67&"",5)="2019-",$H67,W66) | X67: =IF($W67="",0,IF(COUNTIF($AB$2:$AB$80,$W67)>0,1,0)) | Y67: =IF($C67="","",UPPER(TRIM(IFERROR(LEFT($C67&"",FIND("/",$C67&"")-1),$C67&"")))) | Z67: =IFERROR(IF(ISNUMBER($G67),$G67,0),0)
W68: =IF(LEFT($H68&"",5)="2019-",$H68,W67) | X68: =IF($W68="",0,IF(COUNTIF($AB$2:$AB$80,$W68)>0,1,0)) | Y68: =IF($C68="","",UPPER(TRIM(IFERROR(LEFT($C68&"",FIND("/",$C68&"")-1),$C68&"")))) | Z68: =IFERROR(IF(ISNUMBER($G68),$G68,0),0)
A69: 4 | B69: M-HAWK | C69: PC-86371 | D69: 1 | E69: 5 | F69: =+E69*D69 | G69: =+E69*D69 | H69: 1 | I69: =+H69*G69 | W69: =IF(LEFT($H69&"",5)="2019-",$H69,W68) | X69: =IF($W69="",0,IF(COUNTIF($AB$2:$AB$80,$W69)>0,1,0)) | Y69: =IF($C69="","",UPPER(TRIM(IFERROR(LEFT($C69&"",FIND("/",$C69&"")-1),$C69&"")))) | Z69: =IFERROR(IF(ISNUMBER($G69),$G69,0),0)
A70: 5 | B70: SAFARI DICOR | C70: PC-86238 | D70: 1 | E70: 5 | F70: =+E70*D70 | G70: =+E70*D70 | H70: 1 | I70: =+H70*G70 | W70: =IF(LEFT($H70&"",5)="2019-",$H70,W69) | X70: =IF($W70="",0,IF(COUNTIF($AB$2:$AB$80,$W70)>0,1,0)) | Y70: =IF($C70="","",UPPER(TRIM(IFERROR(LEFT($C70&"",FIND("/",$C70&"")-1),$C70&"")))) | Z70: =IFERROR(IF(ISNUMBER($G70),$G70,0),0)
A71: 6 | B71: SCORPIO WITH BRACKET | C71: PC-86093B | D71: 1 | E71: 5 | F71: =+E71*D71 | G71: =+E71*D71 | H71: 1 | I71: =+H71*G71 | W71: =IF(LEFT($H71&"",5)="2019-",$H71,W70) | X71: =IF($W71="",0,IF(COUNTIF($AB$2:$AB$80,$W71)>0,1,0)) | Y71: =IF($C71="","",UPPER(TRIM(IFERROR(LEFT($C71&"",FIND("/",$C71&"")-1),$C71&"")))) | Z71: =IFERROR(IF(ISNUMBER($G71),$G71,0),0)
B72: SCORPIO WITH BRACKET | C72: PC-86093B | D72: 2 | E72: 1 | F72: =+E72*D72 | G72: =+E72*D72 | H72: 1 | I72: =+H72*G72 | W72: =IF(LEFT($H72&"",5)="2019-",$H72,W71) | X72: =IF($W72="",0,IF(COUNTIF($AB$2:$AB$80,$W72)>0,1,0)) | Y72: =IF($C72="","",UPPER(TRIM(IFERROR(LEFT($C72&"",FIND("/",$C72&"")-1),$C72&"")))) | Z72: =IFERROR(IF(ISNUMBER($G72),$G72,0),0)
B73: COMPANY-A COOLING COIL | W73: =IF(LEFT($H73&"",5)="2019-",$H73,W72) | X73: =IF($W73="",0,IF(COUNTIF($AB$2:$AB$80,$W73)>0,1,0)) | Y73: =IF($C73="","",UPPER(TRIM(IFERROR(LEFT($C73&"",FIND("/",$C73&"")-1),$C73&"")))) | Z73: =IFERROR(IF(ISNUMBER($G73),$G73,0),0)
A74: 7 | B74: BEAT- T2 (MMF) | C74: PCP-E10067 | D74: 1 | E74: 4 | F74: =+E74*D74 | G74: =+E74*D74 | H74: 1 | I74: =+H74*G74 | W74: =IF(LEFT($H74&"",5)="2019-",$H74,W73) | X74: =IF($W74="",0,IF(COUNTIF($AB$2:$AB$80,$W74)>0,1,0)) | Y74: =IF($C74="","",UPPER(TRIM(IFERROR(LEFT($C74&"",FIND("/",$C74&"")-1),$C74&"")))) | Z74: =IFERROR(IF(ISNUMBER($G74),$G74,0),0)
A75: 8 | B75: BEAT-MMF | C75: PCP-E10723R | D75: 1 | E75: 3 | F75: =+E75*D75 | G75: =+E75*D75 | H75: 1 | I75: =+H75*G75 | W75: =IF(LEFT($H75&"",5)="2019-",$H75,W74) | X75: =IF($W75="",0,IF(COUNTIF($AB$2:$AB$80,$W75)>0,1,0)) | Y75: =IF($C75="","",UPPER(TRIM(IFERROR(LEFT($C75&"",FIND("/",$C75&"")-1),$C75&"")))) | Z75: =IFERROR(IF(ISNUMBER($G75),$G75,0),0)
A76: 9 | B76: BOLERO | C76: PCP-E08095R | D76: 3 | E76: 4 | F76: =+E76*D76 | G76: =+E76*D76 | H76: 1 | I76: =+H76*G76 | W76: =IF(LEFT($H76&"",5)="2019-",$H76,W75) | X76: =IF($W76="",0,IF(COUNTIF($AB$2:$AB$80,$W76)>0,1,0)) | Y76: =IF($C76="","",UPPER(TRIM(IFERROR(LEFT($C76&"",FIND("/",$C76&"")-1),$C76&"")))) | Z76: =IFERROR(IF(ISNUMBER($G76),$G76,0),0)
A77: 10 | B77: FIGO | C77: PCP-E10705 | D77: 1 | E77: 4 | F77: =+E77*D77 | G77: =+E77*D77 | H77: 1 | I77: =+H77*G77 | W77: =IF(LEFT($H77&"",5)="2019-",$H77,W76) | X77: =IF($W77="",0,IF(COUNTIF($AB$2:$AB$80,$W77)>0,1,0)) | Y77: =IF($C77="","",UPPER(TRIM(IFERROR(LEFT($C77&"",FIND("/",$C77&"")-1),$C77&"")))) | Z77: =IFERROR(IF(ISNUMBER($G77),$G77,0),0)
A78: 11 | B78: TRAVERA | C78: PCP-EUN036 | D78: 1 | E78: 4 | F78: =+E78*D78 | G78: =+E78*D78 | H78: 1 | I78: =+H78*G78 | W78: =IF(LEFT($H78&"",5)="2019-",$H78,W77) | X78: =IF($W78="",0,IF(COUNTIF($AB$2:$AB$80,$W78)>0,1,0)) | Y78: =IF($C78="","",UPPER(TRIM(IFERROR(LEFT($C78&"",FIND("/",$C78&"")-1),$C78&"")))) | Z78: =IFERROR(IF(ISNUMBER($G78),$G78,0),0)
A79: 12 | B79: XUV 500- FRONT | C79: PCP-E03122 | D79: 1 | E79: 4 | F79: =+E79*D79 | G79: =+E79*D79 | H79: 1 | I79: =+H79*G79 | W79: =IF(LEFT($H79&"",5)="2019-",$H79,W78) | X79: =IF($W79="",0,IF(COUNTIF($AB$2:$AB$80,$W79)>0,1,0)) | Y79: =IF($C79="","",UPPER(TRIM(IFERROR(LEFT($C79&"",FIND("/",$C79&"")-1),$C79&"")))) | Z79: =IFERROR(IF(ISNUMBER($G79),$G79,0),0)
B80: MISC | W80: =IF(LEFT($H80&"",5)="2019-",$H80,W79) | X80: =IF($W80="",0,IF(COUNTIF($AB$2:$AB$80,$W80)>0,1,0)) | Y80: =IF($C80="","",UPPER(TRIM(IFERROR(LEFT($C80&"",FIND("/",$C80&"")-1),$C80&"")))) | Z80: =IFERROR(IF(ISNUMBER($G80),$G80,0),0)
B81: SUPERKING | C81: UNICLA | D81: 1 | E81: 2 | F81: =+E81*D81 | G81: =+E81*D81 | H81: 1 | I81: =+H81*G81 | W81: =IF(LEFT($H81&"",5)="2019-",$H81,W80) | X81: =IF($W81="",0,IF(COUNTIF($AB$2:$AB$80,$W81)>0,1,0)) | Y81: =IF($C81="","",UPPER(TRIM(IFERROR(LEFT($C81&"",FIND("/",$C81&"")-1),$C81&"")))) | Z81: =IFERROR(IF(ISNUMBER($G81),$G81,0),0)
W82: =IF(LEFT($H82&"",5)="2019-",$H82,W81) | X82: =IF($W82="",0,IF(COUNTIF($AB$2:$AB$80,$W82)>0,1,0)) | Y82: =IF($C82="","",UPPER(TRIM(IFERROR(LEFT($C82&"",FIND("/",$C82&"")-1),$C82&"")))) | Z82: =IFERROR(IF(ISNUMBER($G82),$G82,0),0)
W83: =IF(LEFT($H83&"",5)="2019-",$H83,W82) | X83: =IF($W83="",0,IF(COUNTIF($AB$2:$AB$80,$W83)>0,1,0)) | Y83: =IF($C83="","",UPPER(TRIM(IFERROR(LEFT($C83&"",FIND("/",$C83&"")-1),$C83&"")))) | Z83: =IFERROR(IF(ISNUMBER($G83),$G83,0),0)
W84: =IF(LEFT($H84&"",5)="2019-",$H84,W83) | X84: =IF($W84="",0,IF(COUNTIF($AB$2:$AB$80,$W84)>0,1,0)) | Y84: =IF($C84="","",UPPER(TRIM(IFERROR(LEFT($C84&"",FIND("/",$C84&"")-1),$C84&"")))) | Z84: =IFERROR(IF(ISNUMBER($G84),$G84,0),0)
W85: =IF(LEFT($H85&"",5)="2019-",$H85,W84) | X85: =IF($W85="",0,IF(COUNTIF($AB$2:$AB$80,$W85)>0,1,0)) | Y85: =IF($C85="","",UPPER(TRIM(IFERROR(LEFT($C85&"",FIND("/",$C85&"")-1),$C85&"")))) | Z85: =IFERROR(IF(ISNUMBER($G85),$G85,0),0)
W86: =IF(LEFT($H86&"",5)="2019-",$H86,W85) | X86: =IF($W86="",0,IF(COUNTIF($AB$2:$AB$80,$W86)>0,1,0)) | Y86: =IF($C86="","",UPPER(TRIM(IFERROR(LEFT($C86&"",FIND("/",$C86&"")-1),$C86&"")))) | Z86: =IFERROR(IF(ISNUMBER($G86),$G86,0),0)
B87: NOTE: ONCE GOODS SOLD WILL NOT BE TAKEN BACK | W87: =IF(LEFT($H87&"",5)="2019-",$H87,W86) | X87: =IF($W87="",0,IF(COUNTIF($AB$2:$AB$80,$W87)>0,1,0)) | Y87: =IF($C87="","",UPPER(TRIM(IFERROR(LEFT($C87&"",FIND("/",$C87&"")-1),$C87&"")))) | Z87: =IFERROR(IF(ISNUMBER($G87),$G87,0),0)
C88: G.TOTAL | D88: =SUM(D65:D87) | E88: =IF(H88=I88,"OK","NO") | F88: =SUM(F65:F87) | G88: =SUM(G65:G87) | H88: =SUMPRODUCT(H65:H87,G65:G87) | I88: =SUM(I65:I87) | W88: =IF(LEFT($H88&"",5)="2019-",$H88,W87) | X88: =IF($W88="",0,IF(COUNTIF($AB$2:$AB$80,$W88)>0,1,0)) | Y88: =IF($C88="","",UPPER(TRIM(IFERROR(LEFT($C88&"",FIND("/",$C88&"")-1),$C88&"")))) | Z88: =IFERROR(IF(ISNUMBER($G88),$G88,0),0)
W89: =IF(LEFT($H89&"",5)="2019-",$H89,W88) | X89: =IF($W89="",0,IF(COUNTIF($AB$2:$AB$80,$W89)>0,1,0)) | Y89: =IF($C89="","",UPPER(TRIM(IFERROR(LEFT($C89&"",FIND("/",$C89&"")-1),$C89&"")))) | Z89: =IFERROR(IF(ISNUMBER($G89),$G89,0),0)
A90: PAYMENT TERMS: WITHIN 15 DAYS. | W90: =IF(LEFT($H90&"",5)="2019-",$H90,W89) | X90: =IF($W90="",0,IF(COUNTIF($AB$2:$AB$80,$W90)>0,1,0)) | Y90: =IF($C90="","",UPPER(TRIM(IFERROR(LEFT($C90&"",FIND("/",$C90&"")-1),$C90&"")))) | Z90: =IFERROR(IF(ISNUMBER($G90),$G90,0),0)
W91: =IF(LEFT($H91&"",5)="2019-",$H91,W90) | X91: =IF($W91="",0,IF(COUNTIF($AB$2:$AB$80,$W91)>0,1,0)) | Y91: =IF($C91="","",UPPER(TRIM(IFERROR(LEFT($C91&"",FIND("/",$C91&"")-1),$C91&"")))) | Z91: =IFERROR(IF(ISNUMBER($G91),$G91,0),0)
W92: =IF(LEFT($H92&"",5)="2019-",$H92,W91) | X92: =IF($W92="",0,IF(COUNTIF($AB$2:$AB$80,$W92)>0,1,0)) | Y92: =IF($C92="","",UPPER(TRIM(IFERROR(LEFT($C92&"",FIND("/",$C92&"")-1),$C92&"")))) | Z92: =IFERROR(IF(ISNUMBER($G92),$G92,0),0)
A93: PROFORMA / DELIVERY CHALLAN | W93: =IF(LEFT($H93&"",5)="2019-",$H93,W92) | X93: =IF($W93="",0,IF(COUNTIF($AB$2:$AB$80,$W93)>0,1,0)) | Y93: =IF($C93="","",UPPER(TRIM(IFERROR(LEFT($C93&"",FIND("/",$C93&"")-1),$C93&"")))) | Z93: =IFERROR(IF(ISNUMBER($G93),$G93,0),0)
W94: =IF(LEFT($H94&"",5)="2019-",$H94,W93) | X94: =IF($W94="",0,IF(COUNTIF($AB$2:$AB$80,$W94)>0,1,0)) | Y94: =IF($C94="","",UPPER(TRIM(IFERROR(LEFT($C94&"",FIND("/",$C94&"")-1),$C94&"")))) | Z94: =IFERROR(IF(ISNUMBER($G94),$G94,0),0)
A95: To, | G95: Dated.: | H95: 01.01.19 | W95: =IF(LEFT($H95&"",5)="2019-",$H95,W94) | X95: =IF($W95="",0,IF(COUNTIF($AB$2:$AB$80,$W95)>0,1,0)) | Y95: =IF($C95="","",UPPER(TRIM(IFERROR(LEFT($C95&"",FIND("/",$C95&"")-1),$C95&"")))) | Z95: =IFERROR(IF(ISNUMBER($G95),$G95,0),0)
A96: Dealer-051 | F96: GST-Challan # | H96: 2019-0003 | W96: =IF(LEFT($H96&"",5)="2019-",$H96,W95) | X96: =IF($W96="",0,IF(COUNTIF($AB$2:$AB$80,$W96)>0,1,0)) | Y96: =IF($C96="","",UPPER(TRIM(IFERROR(LEFT($C96&"",FIND("/",$C96&"")-1),$C96&"")))) | Z96: =IFERROR(IF(ISNUMBER($G96),$G96,0),0)
A97: Dealer-187 | W97: =IF(LEFT($H97&"",5)="2019-",$H97,W96) | X97: =IF($W97="",0,IF(COUNTIF($AB$2:$AB$80,$W97)>0,1,0)) | Y97: =IF($C97="","",UPPER(TRIM(IFERROR(LEFT($C97&"",FIND("/",$C97&"")-1),$C97&"")))) | Z97: =IFERROR(IF(ISNUMBER($G97),$G97,0),0)
A98: Address line (redacted) | W98: =IF(LEFT($H98&"",5)="2019-",$H98,W97) | X98: =IF($W98="",0,IF(COUNTIF($AB$2:$AB$80,$W98)>0,1,0)) | Y98: =IF($C98="","",UPPER(TRIM(IFERROR(LEFT($C98&"",FIND("/",$C98&"")-1),$C98&"")))) | Z98: =IFERROR(IF(ISNUMBER($G98),$G98,0),0)
A99: Tin no.: | W99: =IF(LEFT($H99&"",5)="2019-",$H99,W98) | X99: =IF($W99="",0,IF(COUNTIF($AB$2:$AB$80,$W99)>0,1,0)) | Y99: =IF($C99="","",UPPER(TRIM(IFERROR(LEFT($C99&"",FIND("/",$C99&"")-1),$C99&"")))) | Z99: =IFERROR(IF(ISNUMBER($G99),$G99,0),0)
W100: =IF(LEFT($H100&"",5)="2019-",$H100,W99) | X100: =IF($W100="",0,IF(COUNTIF($AB$2:$AB$80,$W100)>0,1,0)) | Y100: =IF($C100="","",UPPER(TRIM(IFERROR(LEFT($C100&"",FIND("/",$C100&"")-1),$C100&"")))) | Z100: =IFERROR(IF(ISNUMBER($G100),$G100,0),0)
...

Sheet Formula Check
A1: FORMULA CHECK - type a part code in B3
A3: Part code to test | B3: PC-107
A5: RAW SEARCH (what Ctrl+F would find) | D5: Live challans carrying this code | E5: Qty | F5: Row in CHALLAN
A6: Cells in CHALLAN col C containing this text | B6: =COUNTIF(CHALLAN!$C$2:$C$22278,"*"&TRIM($B$3)&"*") -> 0 | D6: {=IFERROR(_xlfn._xlws.FILTER(CHALLAN!$W$2:$W$22278,(CHALLAN!$Y$2:$Y$22278=TRIM($B$3))*(CHALLAN!$X$2:$X$22278=0)),"none")} -> none | E6: {=IFERROR(_xlfn._xlws.FILTER(CHALLAN!$Z$2:$Z$22278,(CHALLAN!$Y$2:$Y$22278=TRIM($B$3))*(CHALLAN!$X$2:$X$22278=0)),"")} | F6: {=IFERROR(_xlfn._xlws.FILTER(ROW(CHALLAN!$Y$2:$Y$22278),(CHALLAN!$Y$2:$Y$22278=TRIM($B$3))*(CHALLAN!$X$2:$X$22278=0)),"")}
A7: Cells in CHALLAN col C exactly equal to this | B7: =COUNTIF(CHALLAN!$C$2:$C$22278,TRIM($B$3)) -> 0
A8: Sum of TOTAL QTY on those exact cells (incl. cancelled) | B8: =SUMIF(CHALLAN!$C$2:$C$22278,TRIM($B$3),CHALLAN!$G$2:$G$22278) -> 0
A10: WHAT THE SHEET1 FORMULA COUNTS
A11: Live lines (cancelled excluded) | B11: =COUNTIFS(CHALLAN!$Y$2:$Y$22278,TRIM($B$3),CHALLAN!$X$2:$X$22278,0) -> 0
A12: Live quantity <-- should equal Sheet1 col D | B12: =SUMIFS(CHALLAN!$Z$2:$Z$22278,CHALLAN!$Y$2:$Y$22278,TRIM($B$3),CHALLAN!$X$2:$X$22278,0) -> 0
A13: Cancelled lines | B13: =COUNTIFS(CHALLAN!$Y$2:$Y$22278,TRIM($B$3),CHALLAN!$X$2:$X$22278,1) -> 0
A14: Cancelled quantity | B14: =SUMIFS(CHALLAN!$Z$2:$Z$22278,CHALLAN!$Y$2:$Y$22278,TRIM($B$3),CHALLAN!$X$2:$X$22278,1) -> 0
A15: Total lines (live + cancelled) | B15: =COUNTIF(CHALLAN!$Y$2:$Y$22278,TRIM($B$3)) -> 0
A17: CROSS-CHECK AGAINST SHEET1
A18: Sheet1 row holding this code | B18: =IFERROR(MATCH(TRIM($B$3),Recon!$C$2:$C$223,0)+1,"not on list") -> not on list
A19: Sheet1 item name | B19: =IFERROR(INDEX(Recon!$B$2:$B$223,MATCH(TRIM($B$3),Recon!$C$2:$C$223,0)),"-") -> -
A20: Sheet1 Challan (col D) | B20: =IFERROR(INDEX(Recon!$D$2:$D$223,MATCH(TRIM($B$3),Recon!$C$2:$C$223,0)),"-") -> -
A21: Difference (panel live qty - Sheet1 D) | B21: =IF(ISNUMBER($B$20),$B$12-$B$20,"-") -> -

Sheet Part 2
H1: 107 | I1: 108 | J1: 109 | K1: 110 | L1: 111 | M1: 112 | N1: 113 | O1: 114 | P1: 115 | Q1: 116 | R1: 117 | S1: 118 | T1: 119 | W1: 122 | X1: 123 | Y1: 124 | Z1: 125 | AA1: 126 | AB1: 127 | AC1: 128 | AD1: 129 | AE1: 130 | AF1: 131 | AG1: 132 | AH1: 133 | AI1: 134
A2: S.NO | B2: CHALLAN/ BE NO | C2: DATE | D2: BUYER/ SUPPLIER | H2: 14x15x22mm oring | I2: 14x15x22mm flare | J2: 14x15x26mm flare | K2: 14x18x22mm flare | L2: 14x18x26mm flare | M2: 14x21x22mm flare | N2: 14x21x26mm flare | O2: 14x23x22mm flare | P2: 14x23x26mm flare | Q2: 14x23x44mm flare | R2: 14x25x26mm flare | S2: 14x25x44mm flare | T2: 14x28x44mm flare | U2: 141518-ADOPTER | W2: 141518-F (NEW) | X2: 141518-O (NEW) | Y2: 14x18x16mm flare | Z2: 14x18x20mm flare | AA2: 14x21x16mm flare | AB2: 14x21x20mm flare | AC2: 14x23x16mm flare | AD2: 14x23x20mm flare | AE2: 25x28x20mm | AF2: 25x28x26mm | AG2: 14x28x20mm flare | AH2: 14x30x20mm flare | AI2: 14x25x20mm flare | AJ2: TOTAL | AK2: KG | AL2: T-SHARTS
K3: entry of new qty | N3: entry of new qty | T3: entry of new qty | AA3: no mistk
A4: QTY/CTN | H4: 10 | I4: 10 | J4: 10 | K4: 10 | L4: 10 | M4: 10 | N4: 10 | O4: 10 | P4: 10 | Q4: 5 | R4: 10 | S4: 5 | T4: 5 | Y4: 10 | Z4: 10 | AA4: 10 | AB4: 10 | AC4: 10 | AD4: 10
A6: OPENING | B6: STOCK | C6: 01.04.2019 | H6: 0 | I6: 0 | J6: 0 | K6: 10 | L6: 10 | M6: 364 | N6: -40 | O6: 192 | P6: 17 | Q6: 94 | R6: 37 | S6: 117 | T6: 126 | W6: 275 | X6: 57 | Y6: 20 | Z6: 101 | AA6: 30 | AB6: 63 | AC6: 60 | AD6: -15 | AE6: 273 | AF6: 50 | AG6: 50 | AH6: 75 | AI6: 178 | AJ6: 0 | AK6: 0 | AL6: 326
A9: PUR
B12: 2414903 | C12: 14.03.2019 | D12: OUYADI THR. HSS FROM SS IMPORTS TO DD IMPORTS (HUF) | AE12: 80
A14: 3447368 | B14: 30.05.19 | C14: OYADI PLUS KALIDA THROUGH SS IMPORTS | D14: N.A | E14: OYDY190504 | F14: 589 | Y14: 150 | Z14: 990 | AB14: 150 | AD14: 200 | AG14: 350 | AH14: 150 | AI14: 150
A15: 3916709 | B15: 03.07.19 | C15: OUNUO AUTOMOTIVE THROUGH SS IMPORTS (HOSE+CONDENSER+LEILA+STAL+OYD) | F15: 817 | U15: 350
A16: 7579687 | B16: 10.08.18 | C16: OUYADI THROUGH OVERSEAS IMPORT, | F16: 488
A17: 3631723 | B17: 13.06.19 | C17: OUYADI THROUGH OVERSEAS IMPORT, | F17: 417 | Y17: 200
A24: TOTAL | B24: PUR | F24: =SUM(F6:F23) -> 2311 | G24: =SUM(G6:G23) -> 0 | H24: =SUM(H6:H23) -> 0 | I24: =SUM(I6:I23) -> 0 | J24: =SUM(J6:J23) -> 0 | K24: =SUM(K6:K23) -> 10 | L24: =SUM(L6:L23) -> 10 | M24: =SUM(M6:M23) -> 364 | ... BJ24: =SUM(BJ6:BJ23) -> 0
A26: SALE
A30: 2019-0011 | B30: 08.01.19 | C30: Transporter-005 | Z30: 10
A32: 2019-0013 | B32: 08.01.19 | C32: Dealer-292-PUNJAB | AL32: 30
A33: 2019-0014 | B33: 08.01.19 | C33: HEM | Z33: 30
A36: 2019-0025 | B36: 15.01.19 | C36: Dealer-292-PUNJAB | Z36: 20
A37: 2019-0026 | B37: 15.01.19 | C37: Contact-004 | Z37: 20
A38: 2019-0029 | B38: 16.01.19 | C38: MAXCOOL | W38: 2
A41: 2019-0043 | B41: 29.01.19 | C41: Contact-004 | AE41: 10
A43: 2019-0052 | B43: 01.02.19 | C43: PRIYA ZIGMA | W43: 5 | X43: 2 | AB43: 20 | AD43: 10
A44: 2019-0053 | B44: 01.02.19 | C44: SALIM-NANDED | AL44: 20
A46: 2019-0058 | B46: 02.02.19 | C46: ADVANCE AIR CONDITIONING SYS | AI46: 30
A49: 2019-0066 | B49: 06.02.19 | C49: Dealer-055 | W49: 10 | AB49: 10 | AE49: 5
A52: 2019-0071 | B52: 05.02.19 | C52: Dealer-011 | M52: 30
A53: 2019-0091 | B53: 13.02.19 | C53: Dealer-108 | AD53: 20
A56: 2019-0117 | B56: 20.02.19 | C56: Transporter-005 | AL56: 30
A57: 2019-0118 | B57: 20.02.19 | C57: Dealer-292 | AL57: 20
A58: 2019-0125 | B58: 23.02.19 | C58: SHYAMA KOLKATA | AH58: 20 | AI58: 20
A61: 2019-0131 | B61: 26.02.19 | C61: DALIP | AG61: 15
A64: 2019-0139 | B64: 27.02.19 | C64: ARIHANT AUTO- Dealer-319 | AC64: 10 | AG64: 5
A65: 2019-0148 | B65: 03.03.19 | C65: Dealer-140 | AL65: 5
A66: 2019-0153 | B66: 05.03.19 | C66: Dealer-272 | AL66: 5
A67: 2019-0156 | B67: 05.03.19 | C67: SALIM NANDED | AL67: 10
A71: 2019-0162 | B71: 06.03.19 | C71: ADVANCE AIR CONDITIONING SYS | AI71: 30
A72: 2019-0167 | B72: 07.03.19 | C72: PRIYA ZIGMA | AB72: 10 | AG72: 5
A73: 2018-0183 | B73: 11.03.19 | C73: DALIP | AG73: 5
A74: 2019-196 | B74: 16.03.19 | C74: Dealer-329 | AE74: 2
A76: 2019-0230 | B76: 25.03.19 | C76: SALIM NANDED | AL76: 5
A77: 2019-0232 | B77: 26.03.19 | C77: DALIP | AF77: 10
A78: 2019-0235 | C78: S K AUTOMOBILE | AC78: 10 | AE78: 5 | AL78: 10
A79: 2019-0236 | B79: 27.03.19 | C79: Dealer-139 EMX NOIDA
A81: 2019-0243 | B81: 27.03.19 | C81: AMIT TRADING | AL81: 10
A82: 2019-0245 | B82: 06.03.19 | C82: ADVANCE AIR CONDITIONING SYS | AI82: 80
A83: 2019-0246 | B83: 27.03.19 | C83: Dealer-329 | AL83: 10
A84: 2019-0248 | B84: 29.03.19 | C84: Dealer-139 EMX NOIDA | AE84: 5
A85: 2019-0256 | B85: 31.03.19 | C85: Transporter-005 | AE85: 5
A88: 2019-0270 | B88: 02.04.19 | C88: Dealer-316-CHANDIGHAR | AL88: 5
A89: 2019-0271 | B89: 02.04.19 | C89: DALIP | AG89: 10
A91: 2019-0274 | B91: 02.04.19 | C91: PRAMOD-JODHPUR | AL91: 10
A94: 2019-0277 | B94: 02.04.19 | C94: Contact-004 | AL94: 30
A95: 2019-0288 | B95: 05.04.19 | C95: DALIP | AC95: 10 | AG95: 5
A97: 2019-0293 | B97: 06.04.19 | C97: Transporter-005 | AE97: 4
A100: 2019-0302 | B100: 08.04.19 | C100: Transporter-005 | R100: 10
A101: 2019-0309 | B101: 09.04.19 | C101: Dealer-329-AGRA | M101: 10
A103: 2019-0316 | B103: 12.04.19 | C103: DALIP | AF103: 10
A106: 2019-0324 | B106: 12.04.19 | C106: EMX-Dealer-139 NOIDA | W106: 20
A109: 2019-0339 | B109: 16.04.19 | C109: Dealer-132 | M109: 10
A113: 2019-0365 | B113: 20.04.19 | C113: Transporter-005 | AE113: 10
A117: 2019-0404 | B117: 29.04.19 | C117: Transporter-005 | AE117: 10
A120: 2019-0461 | B120: 07.05.19 | C120: Transporter-005 | AE120: 10
A123: 2019-0475 | B123: 10.05.19 | C123: JAIN-ROHINI | AL123: 10
A127: 2019-0459 | B127: 07.05.19 | C127: Dealer-055-KERALA | W127: 10 | AE127: 10 | AH127: 10
A245: TOTAL | B245: FEB | C245: SALE
A374: TOTAL | B374: MARCH | C374: SALE
A510: TOTAL | B510: APRIL | C510: SALE
A657: TOTAL | B657: MAY | C657: SALE
A796: TOTAL | B796: JUNE
A902: TOTAL | B902: JULY
A992: TOTAL | B992: AUG
A1071: TOTAL | B1071: SEPT
A1155: TOTAL | B1155: OCT
A1177: TOTAL | B1177: NOV
A1190: TOTAL | B1190: DEC
A1196: TOTAL | B1196: SOLD | F1196: =SUM(F27:F1195) -> 0 | G1196: =SUM(G27:G1195) -> 0 | H1196: =SUM(H28:H1195) -> 0 | I1196: =SUM(I28:I1195) -> 0 | J1196: =SUM(J28:J1195) -> 0 | K1196: =SUM(K28:K1195) -> 0 | L1196: =SUM(L28:L1195) -> 0 | M1196: =SUM(M28:M1195) -> 50 | N1196: =SUM(N28:N1195) -> 0 | O1196: =SUM(O28:O1195) -> 0 | ... AR1196: =SUM(AR28:AR1195) -> 0
A1198: BAL | B1198: QTY | F1198: =+F24-F1196 -> 2311 | G1198: =+G24-G1196 -> 0 | H1198: =+H24-H1196 -> 0 | I1198: =+I24-I1196 -> 0 | J1198: =+J24-J1196 -> 0 | K1198: =+K24-K1196 -> 10 | L1198: =+L24-L1196 -> 10 | M1198: =+M24-M1196 -> 314 | ... AR1198: =+AR24-AR1196 -> 0
B1202: NEW ORDER PLACED
D1214: TOTAL | F1214: =SUM(F1198:F1213) -> 2311 | G1214: =SUM(G1198:G1213) -> 0 | H1214: =SUM(H1198:H1213) -> 0 | I1214: =SUM(I1198:I1213) -> 0 | J1214: =SUM(J1198:J1213) -> 0 | K1214: =SUM(K1198:K1213) -> 10 | L1214: =SUM(L1198:L1213) -> 10 | M1214: =SUM(M1198:M1213) -> 314 | ... AL1214: =SUM(AL1198:AL1213) -> 116

Sheet Part 3
H1: 107 | I1: 108 | J1: 109 | K1: 110 | L1: 111 | M1: 112 | N1: 113 | O1: 114 | P1: 115 | Q1: 116 | R1: 117 | S1: 118 | T1: 119 | W1: 122 | X1: 123 | Y1: 124 | Z1: 125 | AA1: 126 | AB1: 127 | AC1: 128 | AD1: 129 | AE1: 130 | AF1: 131 | AG1: 132 | AH1: 133 | AI1: 134
A2: S.NO | B2: CHALLAN/ BE NO | C2: DATE | D2: BUYER/ SUPPLIER | H2: 14x15x22mm oring | I2: 14x15x22mm flare | J2: 14x15x26mm flare | K2: 14x18x22mm flare | L2: 14x18x26mm flare | M2: 14x21x22mm flare | N2: 14x21x26mm flare | O2: 14x23x22mm flare | P2: 14x23x26mm flare | Q2: 14x23x44mm flare | R2: 14x25x26mm flare | S2: 14x25x44mm flare | T2: 14x28x44mm flare | U2: 141518-ADOPTER | W2: 141518-F (NEW) | X2: 141518-O (NEW) | Y2: 14x18x16mm flare | Z2: 14x18x20mm flare | AA2: 14x21x16mm flare | AB2: 14x21x20mm flare | AC2: 14x23x16mm flare | AD2: 14x23x20mm flare | AE2: 25x28x20mm | AF2: 25x28x26mm | AG2: 14x28x20mm flare | AH2: 14x30x20mm flare | AI2: 14x25x20mm flare | AJ2: TOTAL | AK2: KG | AL2: T-SHARTS
K3: entry of new qty | N3: entry of new qty | T3: entry of new qty | AA3: no mistk
A4: QTY/CTN | H4: 10 | I4: 10 | J4: 10 | K4: 10 | L4: 10 | M4: 10 | N4: 10 | O4: 10 | P4: 10 | Q4: 5 | R4: 10 | S4: 5 | T4: 5 | Y4: 10 | Z4: 10 | AA4: 10 | AB4: 10 | AC4: 10 | AD4: 10
A6: OPENING | B6: STOCK | C6: 01.04.2019 | H6: 0 | I6: 0 | J6: 0 | K6: 10 | L6: 10 | M6: 364 | N6: -40 | O6: 192 | P6: 17 | Q6: 94 | R6: 37 | S6: 117 | T6: 126 | W6: 275 | X6: 57 | Y6: 20 | Z6: 101 | AA6: 30 | AB6: 63 | AC6: 60 | AD6: -15 | AE6: 273 | AF6: 50 | AG6: 50 | AH6: 75 | AI6: 178 | AJ6: 0 | AK6: 0 | AL6: 326
A9: PUR
B12: 2414903 | C12: 14.03.2019 | D12: OUYADI THR. HSS FROM SS IMPORTS TO DD IMPORTS (HUF) | AE12: 80
A14: 3447368 | B14: 30.05.19 | C14: OYADI PLUS KALIDA THROUGH SS IMPORTS | D14: N.A | E14: OYDY190504 | F14: 589 | Y14: 150 | Z14: 990 | AB14: 150 | AD14: 200 | AG14: 350 | AH14: 150 | AI14: 150
A15: 3916709 | B15: 03.07.19 | C15: OUNUO AUTOMOTIVE THROUGH SS IMPORTS (HOSE+CONDENSER+LEILA+STAL+OYD) | F15: 817 | U15: 350
A16: 7579687 | B16: 10.08.18 | C16: OUYADI THROUGH OVERSEAS IMPORT, | F16: 488
A17: 3631723 | B17: 13.06.19 | C17: OUYADI THROUGH OVERSEAS IMPORT, | F17: 417 | Y17: 200
A24: TOTAL | B24: PUR | F24: =SUM(F6:F23) -> 2311 | G24: =SUM(G6:G23) -> 0 | H24: =SUM(H6:H23) -> 0 | I24: =SUM(I6:I23) -> 0 | J24: =SUM(J6:J23) -> 0 | K24: =SUM(K6:K23) -> 10 | L24: =SUM(L6:L23) -> 10 | M24: =SUM(M6:M23) -> 364 | ... BJ24: =SUM(BJ6:BJ23) -> 0
A26: SALE
A30: 2019-0011 | B30: 08.01.19 | C30: Transporter-005 | Z30: 10
A32: 2019-0013 | B32: 08.01.19 | C32: Dealer-292-PUNJAB | AL32: 30
A33: 2019-0014 | B33: 08.01.19 | C33: HEM | Z33: 30
A36: 2019-0025 | B36: 15.01.19 | C36: Dealer-292-PUNJAB | Z36: 20
A37: 2019-0026 | B37: 15.01.19 | C37: Contact-004 | Z37: 20
A38: 2019-0029 | B38: 16.01.19 | C38: MAXCOOL | W38: 2
A41: 2019-0043 | B41: 29.01.19 | C41: Contact-004 | AE41: 10
A43: 2019-0052 | B43: 01.02.19 | C43: PRIYA ZIGMA | W43: 5 | X43: 2 | AB43: 20 | AD43: 10
A44: 2019-0053 | B44: 01.02.19 | C44: SALIM-NANDED | AL44: 20
A46: 2019-0058 | B46: 02.02.19 | C46: ADVANCE AIR CONDITIONING SYS | AI46: 30
A49: 2019-0066 | B49: 06.02.19 | C49: Dealer-055 | W49: 10 | AB49: 10 | AE49: 5
A52: 2019-0071 | B52: 05.02.19 | C52: Dealer-011 | M52: 30
A53: 2019-0091 | B53: 13.02.19 | C53: Dealer-108 | AD53: 20
A56: 2019-0117 | B56: 20.02.19 | C56: Transporter-005 | AL56: 30
A57: 2019-0118 | B57: 20.02.19 | C57: Dealer-292 | AL57: 20
A58: 2019-0125 | B58: 23.02.19 | C58: SHYAMA KOLKATA | AH58: 20 | AI58: 20
A61: 2019-0131 | B61: 26.02.19 | C61: DALIP | AG61: 15
A64: 2019-0139 | B64: 27.02.19 | C64: ARIHANT AUTO- Dealer-319 | AC64: 10 | AG64: 5
A65: 2019-0148 | B65: 03.03.19 | C65: Dealer-140 | AL65: 5
A66: 2019-0153 | B66: 05.03.19 | C66: Dealer-272 | AL66: 5
A67: 2019-0156 | B67: 05.03.19 | C67: SALIM NANDED | AL67: 10
A71: 2019-0162 | B71: 06.03.19 | C71: ADVANCE AIR CONDITIONING SYS | AI71: 30
A72: 2019-0167 | B72: 07.03.19 | C72: PRIYA ZIGMA | AB72: 10 | AG72: 5
A73: 2018-0183 | B73: 11.03.19 | C73: DALIP | AG73: 5
A74: 2019-196 | B74: 16.03.19 | C74: Dealer-329 | AE74: 2
A76: 2019-0230 | B76: 25.03.19 | C76: SALIM NANDED | AL76: 5
A77: 2019-0232 | B77: 26.03.19 | C77: DALIP | AF77: 10
A78: 2019-0235 | C78: S K AUTOMOBILE | AC78: 10 | AE78: 5 | AL78: 10
A79: 2019-0236 | B79: 27.03.19 | C79: Dealer-139 EMX NOIDA
A81: 2019-0243 | B81: 27.03.19 | C81: AMIT TRADING | AL81: 10
A82: 2019-0245 | B82: 06.03.19 | C82: ADVANCE AIR CONDITIONING SYS | AI82: 80
A83: 2019-0246 | B83: 27.03.19 | C83: Dealer-329 | AL83: 10
A84: 2019-0248 | B84: 29.03.19 | C84: Dealer-139 EMX NOIDA | AE84: 5
A85: 2019-0256 | B85: 31.03.19 | C85: Transporter-005 | AE85: 5
A88: 2019-0270 | B88: 02.04.19 | C88: Dealer-316-CHANDIGHAR | AL88: 5
A89: 2019-0271 | B89: 02.04.19 | C89: DALIP | AG89: 10
A91: 2019-0274 | B91: 02.04.19 | C91: PRAMOD-JODHPUR | AL91: 10
A94: 2019-0277 | B94: 02.04.19 | C94: Contact-004 | AL94: 30
A95: 2019-0288 | B95: 05.04.19 | C95: DALIP | AC95: 10 | AG95: 5
A97: 2019-0293 | B97: 06.04.19 | C97: Transporter-005 | AE97: 4
A100: 2019-0302 | B100: 08.04.19 | C100: Transporter-005 | R100: 10
A101: 2019-0309 | B101: 09.04.19 | C101: Dealer-329-AGRA | M101: 10
A103: 2019-0316 | B103: 12.04.19 | C103: DALIP | AF103: 10
A106: 2019-0324 | B106: 12.04.19 | C106: EMX-Dealer-139 NOIDA | W106: 20
A109: 2019-0339 | B109: 16.04.19 | C109: Dealer-132 | M109: 10
A113: 2019-0365 | B113: 20.04.19 | C113: Transporter-005 | AE113: 10
A117: 2019-0404 | B117: 29.04.19 | C117: Transporter-005 | AE117: 10
A120: 2019-0461 | B120: 07.05.19 | C120: Transporter-005 | AE120: 10
A123: 2019-0475 | B123: 10.05.19 | C123: JAIN-ROHINI | AL123: 10
A127: 2019-0459 | B127: 07.05.19 | C127: Dealer-055-KERALA | W127: 10 | AE127: 10 | AH127: 10
A245: TOTAL | B245: FEB | C245: SALE
A374: TOTAL | B374: MARCH | C374: SALE
A510: TOTAL | B510: APRIL | C510: SALE
A657: TOTAL | B657: MAY | C657: SALE
A796: TOTAL | B796: JUNE
A902: TOTAL | B902: JULY
A992: TOTAL | B992: AUG
A1071: TOTAL | B1071: SEPT
A1155: TOTAL | B1155: OCT
A1177: TOTAL | B1177: NOV
A1190: TOTAL | B1190: DEC
A1196: TOTAL | B1196: SOLD | F1196: =SUM(F27:F1195) -> 0 | G1196: =SUM(G27:G1195) -> 0 | H1196: =SUM(H28:H1195) -> 0 | I1196: =SUM(I28:I1195) -> 0 | J1196: =SUM(J28:J1195) -> 0 | K1196: =SUM(K28:K1195) -> 0 | L1196: =SUM(L28:L1195) -> 0 | M1196: =SUM(M28:M1195) -> 50 | N1196: =SUM(N28:N1195) -> 0 | O1196: =SUM(O28:O1195) -> 0 | ... AR1196: =SUM(AR28:AR1195) -> 0
A1198: BAL | B1198: QTY | F1198: =+F24-F1196 -> 2311 | G1198: =+G24-G1196 -> 0 | H1198: =+H24-H1196 -> 0 | I1198: =+I24-I1196 -> 0 | J1198: =+J24-J1196 -> 0 | K1198: =+K24-K1196 -> 10 | L1198: =+L24-L1196 -> 10 | M1198: =+M24-M1196 -> 314 | ... AR1198: =+AR24-AR1196 -> 0
B1202: NEW ORDER PLACED
D1214: TOTAL | F1214: =SUM(F1198:F1213) -> 2311 | G1214: =SUM(G1198:G1213) -> 0 | H1214: =SUM(H1198:H1213) -> 0 | I1214: =SUM(I1198:I1213) -> 0 | J1214: =SUM(J1198:J1213) -> 0 | K1214: =SUM(K1198:K1213) -> 10 | L1214: =SUM(L1198:L1213) -> 10 | M1214: =SUM(M1198:M1213) -> 314 | ... AL1214: =SUM(AL1198:AL1213) -> 116

Sheet Part 1
E1: WITHOUT GST AMT | I1: CONDENSER | L1: 1 | M1: 2 | N1: 3 | O1: 4 | P1: 5 | Q1: 6 | R1: 7 | S1: 8 | T1: 9 | U1: 10 | V1: 11 | W1: 12 | X1: 13 | Y1: 14 | Z1: 15 | AA1: 16 | AB1: 17 | AC1: 18 | AD1: 19 | AE1: 20 | AF1: 21 | AI1: 23 | AJ1: 24 | AK1: 25 | AL1: 26 | AM1: 27 | AN1: 28 | AO1: 29 | AP1: 30 | AQ1: 31 | AR1: 32 | AS1: 33 | AT1: 34 | AU1: 35 | AV1: 36 | AW1: 37 | AX1: 38 | AY1: 39 | AZ1: 40 | BA1: 41 | BB1: 42 | BC1: 43 | BD1: 44 | BE1: 45 | BF1: 46 | BH1: 47 | BI1: 48 | BJ1: 49 | BK1: 50 | BL1: 51 | BM1: 52 | BN1: 53 | BO1: 54 | BP1: 55 | BQ1: 56 | BR1: 57 | BS1: 58 | BT1: 59 | BU1: 60 | BV1: 61 | BW1: 62 | BX1: 63 | BY1: 64 | BZ1: 65 | CA1: 66 | CB1: 67 | CC1: 68 | CD1: 69 | CE1: 70 | CF1: 71 | CG1: 72 | CH1: 73 | CI1: 74 | CJ1: 75 | CK1: 76 | CL1: 77 | CM1: 78 | CN1: 79 | CO1: 80 | CP1: 81 | CQ1: 82 | CR1: 83 | CS1: 84 | CT1: 85 | CU1: 86 | CV1: 87 | CW1: 88 | CX1: 89 | CY1: 90 | CZ1: 91 | DA1: 92 | DB1: 93 | DC1: 94 | DD1: 95 | DE1: 96 | DF1: 97 | DG1: 98 | DH1: 99 | DI1: 100 | DJ1: 101 | DK1: 102 | DL1: 103 | DM1: 104 | DN1: 105 | DO1: 106 | DP1: 107 | DQ1: 108 | DR1: 109 | DS1: 110 | DT1: 111 | DU1: 112 | DV1: 113 | DW1: 114 | DX1: 115 | DY1: 116 | DZ1: 117 | EA1: 118 | EB1: 119 | EC1: 120 | ED1: 121 | EE1: 122 | EF1: 123 | EG1: 124 | EH1: 125 | EI1: 126 | EJ1: 127 | EK1: 128 | EL1: 129 | EM1: 130 | EN1: 131 | EO1: 132 | EP1: 133 | EQ1: 134 | ER1: 135 | ES1: 136 | ET1: 137 | EU1: 138 | EV1: 139 | EW1: 140 | EX1: 141 | EY1: 142 | EZ1: 143 | FA1: 144 | FB1: 145 | FC1: 146 | FD1: 147 | FE1: 148 | FF1: 149 | FG1: 150 | FH1: 151 | FI1: 152 | FJ1: 153 | FK1: 154 | FL1: 155 | FM1: 156 | FN1: 157 | FO1: 158 | FP1: 159 | FQ1: 160 | FR1: 161 | FS1: 162 | FT1: 163 | FU1: 164 | FV1: 165 | FW1: 166 | FX1: 167 | FY1: 168 | FZ1: 169 | GA1: 170 | GB1: 171 | GC1: 172 | GD1: 173 | GE1: 174 | GF1: 175 | GG1: 176 | GH1: 177 | GI1: 178 | GJ1: 179 | GK1: 180 | GL1: 181 | GM1: 182 | GN1: 183 | GO1: 184 | GP1: 185 | GQ1: 186 | GR1: 187 | GS1: 188 | GT1: 189 | GU1: 190 | GV1: 191 | GW1: 192 | GX1: 193 | GY1: 194 | GZ1: 195 | HA1: 196 | HB1: 197 | HC1: 198 | HD1: 199 | HE1: 200 | HF1: 201 | HG1: 202 | HH1: 203 | HI1: 204 | HJ1: 205 | HK1: 206 | HL1: 207 | HM1: 208 | HN1: 209 | HO1: 210 | HP1: 211 | HQ1: 212 | HR1: 213 | HS1: 214 | HT1: 215 | HU1: 216 | HV1: 217 | HW1: 218 | HX1: 219 | HY1: 220
A2: S.NO | B2: CHALLAN/ BE NO | C2: DATE | D2: BUYER/ SUPPLIER | E2: BE SUBMISSION | F2: D.O. ARRIVAL | G2: PAYMENT BY BANK | H2: INV NO. & DT. | I2: AMT IN USD | J2: CTNS | L2: ACCENT CRD-I | M2: ACCENT-PETROL | N2: ALTIS | O2: ALTIS-CORRECTED | P2: ALTIS-Q5 | Q2: ALTO 800 NEW | R2: AMBASDOR | S2: A-STAR | T2: AUDI A3 | U2: AUDI A4 | V2: AUDI A6 | W2: AUDI Q3 | X2: AUDI Q7 | Y2: AVEO | Z2: BALENO-NEW | AA2: BALENO-NEW-Q5 | AB2: BEAT DSL-Q5 | AC2: BEAT PTL-Q5 | AD2: BEAT-DSL | AE2: BEAT-PTL | AF2: BELANO | AH2: BMW E90 DSL SMALL | AI2: BMW 3 SERIES E60 BIG | AJ2: BMW 3 SERIES E60 PTL | AK2: BMW E60 DSL 03-07 | AL2: BOLERO- R134A | AM2: BOLERO- R134A (NEW) | AN2: BREEZA-Q5 | AO2: BRIO | AP2: BRIO-Q5 | AQ2: CAIZ-Q5 | AR2: CAMRY - 02-05 | AS2: CAMRY - 07-09 | AT2: CAMRY - 07-09 (Q5) | AU2: CELERO | AV2: CIAZ-Q5 | AW2: COROLLA | AX2: COROLLA-Q5 | AY2: CRETA-DSL | AZ2: CRETA-DSL-Q5 | BA2: CRETA-PTL | BB2: CRETA-PTL-Q5 | BC2: CRUZE BIG | BD2: CRUZE-SMALL | BE2: DEV'S CUSTOMER-KAMATSU | BF2: DEV'S CUSTOMER-VOLVO 14645543 | BG2: DEV'S CUSTOMERKOMATSU 2000 | BH2: DUSTER / TERRANO-110CC | BI2: DUSTER / TERRANO-110CC-Q5 | BJ2: DUSTER / TERRANO-85CC | BK2: DUSTER / TERRANO-85CC-Q5 | BL2: ECOSPORT-DSL SMALL HOLE | BM2: ECOSPORT-DSL-Q5 SMALL HOLE | BN2: ECOSPORT-PTL | BO2: ELANTRA | BP2: ENDEAOUR | BQ2: ENDEAOUR-Q5 | BR2: ENJOY DSL | BS2: ENJOY DSL-Q5 | BT2: ENJOY PTL | BU2: ENJOY PTL-Q5 | BV2: EON | BW2: Esteem-134a / Esteem PAD | BX2: ESTEEM-R12 | BY2: ETIOS (DSL) | BZ2: ETIOS (PTL) | CA2: ETIOS (PTL)-Q5 | CB2: FIESTA | CC2: FIGO | CD2: FLUENCE-Q5 | CE2: FORCE SUV-DSL | CF2: Ford Ikon | CG2: FURTUNER (DSL)-Q5 | CH2: FUSION | CI2: GETZ | CJ2: HONDA CIVIC | CK2: HONDA CIVIC-Q5 | CL2: HONDA ACCORD Q5 | CM2: HONDA ACCORD T4 | CN2: HONDA AMAZE DSL | CO2: HONDA AMAZE DSL-Q5 | CP2: Honda City-TYPE-1&2 | CQ2: Honda City-TYPE-3 | CR2: Honda City-TYPE-3-Q5 | CS2: HONDA CRV | CT2: HONDA CRV (NEW)-Q5 | CU2: HONDA CRV-Q5 | CV2: HONDA I.D.TEC (DSL)-Q5 | CW2: HONDA I.D.TEC (PTL) | CX2: HONDA I.D.TEC (PTL)-Q5 | CY2: HONDA JAZZ | CZ2: HONDA MOBILIO (DSL) | DA2: HONDA MOBILIO (DSL)-Q5 | DB2: HONDA MOBILIO (PTL) | DC2: HONDA MOBILIO (PTL)-Q5 | DD2: HONDA T-5 | DE2: HONDA T-5-Q5 | DF2: I-10 | DG2: I-10-Q5 | DH2: I-10 GRAND (DSL) | DI2: I-10 GRAND (DSL)-Q5 | DJ2: I-10 GRAND (PTL) | DK2: I-10 GRAND (PTL)-Q5 | DL2: I-20 | DM2: I-20-Q5 | DN2: I-20-DSL | DO2: I-20-DSL=T2 | DP2: I-20-DSL=T2-Q5 | DQ2: INDICA BEHR-R134A (WITH BRACKET) | DR2: INDICA SUBROS NEW | DS2: INDICA VISTA BEHR- Q-JET | DT2: INDICA VISTA -BEHR EV2 | DU2: INDICA VISTA SUBROS 4540 EV2 STEP-4 | DV2: INDICA VISTA SUBROS-T1 | DW2: INDICA VISTA SUBROS-T2 | DX2: INDICA VISTA-TDI | DY2: INDIGO (WITH BRACKET) | DZ2: INNOVA | EA2: INNOVA-Q5 | EB2: INNOVA-T4 | EC2: INNOVA-T4-Q5 | ED2: KWID-DSL | EE2: LANCER | EF2: LINEA | EG2: LOGAN PAD-DSL | EH2: MAGNUM | EI2: Maruti Car-800 MPFI | EJ2: MATIZ | EK2: MERC BENZ W204 | EL2: MERC BENZ W210 | EM2: MERC BENZ W211 (MD) | EN2: MERX BENZ-DW203-Q5 | EO2: M-HWK | EP2: M-HWK-Q5 | EQ2: MICRA | ER2: NANO | ES2: OPEL ASTRA | ET2: OPEL CORSA | EU2: OPTRA (WITH DRIER) | EV2: PAJERO SPORT WITH R/D-Q5 | EW2: PALIO | EX2: PALIO STILE | EY2: PASSAT | EZ2: PASSAT-Q5 | FA2: POLO | FB2: POLO-Q5 | FC2: PUNTO KALE (DSL) | FD2: PUNTO KALE (DSL)-AQ5 | FE2: QUALIS FLARE | FF2: Qualis O Ring | FG2: Qualis PAD | FH2: RITZ DEISAL | FI2: RITZ DEISAL-Q5 | FJ2: RITZ PETROL | FK2: RITZ PETROL-Q5 | FL2: SAFARI / DICOR | FM2: SAFARI STROME (SUBROS) | FN2: SAFARI STROME (SUBROS)-Q5 | FO2: SAIL DSL | FP2: SAIL DSL-Q5 | FQ2: SAIL PTL | FR2: SANTRO | FS2: Santro XING | FT2: SCORPIO | FU2: SKODA FABIA | FV2: SKODA LAURA | FW2: SKODA LAURA-Q5 | FX2: SKODA -Q5 | FY2: SKODA WITH DRIER | FZ2: SONATA | GA2: SPARK (WITH BRACKET) | GB2: SUMO DELPHI | GC2: SUMO GOLD DELPHI BS4 | GD2: SUMO VECTA | GE2: SWIFT / SWIFT DZIRE | GF2: SWIFT-NEW | GG2: SWIFT-NEW-Q5 | GH2: SX4 | GI2: SX4Q5 | GJ2: SX4 SUBROS-4140 DSL | GK2: SX4 -Q5 SUBROS-4140 DSL | GL2: TEMPO TRAVELLER-SUBROS | GM2: TERRANO - BEHR 2016-Q5 | GN2: TERRANO - BEHR 2016 | GO2: TRAVERA | GP2: TUV-300-Q5 | GQ2: VARNA PETROL | GR2: VERNA (D) | GS2: VERNA (FLUDIC) | GT2: VERNA (FLUDIC)-Q5 | GU2: VERSA | GV2: VERSA NEW WITH DRIER | GW2: VOLVO | GX2: WAGON R / ALTO | GY2: WAGON R / ALTO (NEW) | GZ2: XUV 500- | HA2: XUV 500-Q5 | HB2: XYLO-Q5 SUBROS (BIG) | HC2: XYLO- SUBROS (BIG) | HD2: XYLO SUBROS SMALL TYPE | HE2: ZEN DELPHI R12 | HF2: ZEN DELPHI R134 | HG2: ZEN ESTILO- T1 | HH2: ZEN-DIESEL | HI2: ZEN-R12 SUBROS | HJ2: ZEN-R134A | HK2: INNOVA CRYSTA | HL2: KUV 100 | HM2: M-HAWK S2 | HN2: M-HAWK S2 IN 15 SERIES | HO2: DEV SONY | HP2: DEV SONY | HQ2: SUMO VECTA BS 305 | HR2: DATSUN GO | HS2: BOLERO 2018 | HT2: BOLERO 2018 | HU2: SWIFT 2017 | HV2: BREEZA | HW2: TUV 100 | HX2: ECOSPORT-DSL BIG HOLE | HY2: ECOSPORT-DSL-Q5 BIG HOLE
E3: SALE AMT | L3: PC-86064B | M3: PC-86248 | N3: PC-86032 | O3: PC-86083 | P3: PC-86083-Q5 | Q3: PC-86634 | R3: PC-86041 | S3: PC-86274 | T3: PCP-C86283Q5 | U3: PCP-C86001 | V3: PCP-C86082 | W3: PCP-C86020 | X3: PCP-C86832 | Y3: PC-86177 | Z3: PC-86803 | AA3: PC-86803Q5 | AB3: PC-86589Q5 | AC3: PC-86535Q5 | AD3: PC-86589 | AE3: PC-86535 | AF3: PC-86242 | AH3: PCP-C86741F | AI3: PCP-C86749F | AJ3: PCP-C86747F | AK3: PCP-C86748F | AL3: PC-86236 | AM3: PC-86395 | AN3: PC-86811-Q5 | AO3: PC-86581 | AP3: PC-86581-Q5 | AQ3: PC-86812Q5 | AR3: PC-86396 | AS3: PC-86397 | AT3: PC-86397-Q5 | AU3: PC-86903 | AV3: PC-86901 | AW3: PC-86110 | AX3: PC-86110A-Q5 | AY3: PC-86805 | AZ3: PC-86805-Q5 | BA3: PC-86806 | BB3: PC-86806Q5 | BC3: PCP-C86556 | BD3: PC-86555 | BE3: pc-86907-26MM-8MM | BF3: PC-86808-Q5 | BG3: PC-86814 | BH3: PC-86920 | BI3: PC-86920A-Q5 | BJ3: PC-86428 | BK3: PC-86428-Q5 | BL3: PC-86911B | BM3: PC-86911BQ5 | BN3: PC-86912 | BO3: PC-86066 | BP3: PC-86277 | BQ3: PC-86277-Q5 | BR3: PC-86201 | BS3: PC-86201-Q5 | BT3: PC-86202 | BU3: PC-86202Q5 | BV3: PC-86617 | BW3: PC-86090 | BX3: PC-86040 | BY3: PC-86580 | BZ3: PC-86656 | CA3: PC-86656Q5 | CB3: PC-86272 | CC3: PC-86590 | CD3: PC-86769-Q5 | CE3: PC-86904 | CF3: PC-86034 | CG3: PC-86604 | CH3: PC-86271 | CI3: PC-86027B | CJ3: PC-86251 | CK3: PC-86251Q5 | CL3: PC-86006 | CM3: PCP-86532 Q5 | CN3: PC-86902 | CO3: PC-86902Q5 | CP3: PC-86091 | CQ3: PC-86240 | CR3: PC-86240AQ5 | CS3: PC-86101 | CT3: PC-86398-Q5 | CU3: PC-86101 Q5 | CV3: PC-86807Q5 | CW3: PC-86827 | CX3: PC-86827Q5 | CY3: PC-86900 | CZ3: PC-86828 | DA3: PC-86828Q5 | DB3: PC-86829 | DC3: PC-86829-Q5 | DD3: PC-86278 | DE3: PC-86278-Q5 | DF3: PC-86266 | DG3: PC-86266Q5 | DH3: PC-86655 | DI3: PC-86655-Q5 | DJ3: PC-86448B | DK3: PC-86448B-Q5 | DL3: PC-86268 | DM3: PC-86268Q5 | DN3: PC-86540 | DO3: PC-86804 | DP3: PC-86804-Q5 | DQ3: PC-86233 | DR3: PC-86204 | DS3: PC-86276 | DT3: PC-86639 | DU3: PC-86925 | DV3: PC-86366 | DW3: PC-86369 | DX3: PC-86273 | DY3: PC-86237 | DZ3: PC-86046B | EA3: PC-86046B-Q5 | EB3: PC-86536 | EC3: PC-86536-Q5 | ED3: PC-86915 | EE3: PC-86246B | EF3: PC-86537 | EG3: PC-86087 | EH3: PC-86605 | EI3: PC-86092 | EJ3: PC-86042 | EK3: PCP-C86950 | EL3: COMING SOON | EM3: PCP-C86703 | EN3: PC-86437Q5 | EO3: PC-86371 | EP3: PC-86371-Q5 | EQ3: PC-86800 | ER3: PC-86538 | ES3: PC-86243 | ET3: PC-86038 | EU3: PC-86186 | EV3: PC-86758Q5 | EW3: PC-86039 | EX3: PC-86269 | EY3: PC-86801 | EZ3: PC-86801-Q5 | FA3: PC-86457 (86843) | FB3: PC-86457Q5 (86843) | FC3: PC-86534 | FD3: PC-86534AQ5 | FE3: PC-86234 | FF3: PC-86244 | FG3: PC-86235 | FH3: PC-86367 | FI3: PC-86367-Q5 | FJ3: PC-86370 | FK3: PC-86370-Q5 | FL3: PC-86238 | FM3: PC-86810 | FN3: PC-86810-Q5 | FO3: PC-86910 | FP3: PC-86910Q5 | FQ3: PC-86914 | FR3: PC-86125 | FS3: PC-86239 | FT3: PC-86093B | FU3: PC-86134 | FV3: PC-86026B | FW3: PC-86026B-Q5 | FX3: PC-86004-Q5 | FY3: PC-86004 | FZ3: COMING SOON | GA3: PC-86015 | GB3: PC-86368 | GC3: PC-86906 | GD3: PC-86241 | GE3: PC-86207 | GF3: PC-86539 | GG3: PC-86539-Q5 | GH3: PC-86025 | GI3: PC-86025Q5 | GJ3: PC-86802 | GK3: PC-86802Q5 | GL3: PC-86203 | GM3: PC-86909Q5 | GN3: PC-86909 | GO3: PC-86247 | GP3: PC-86809A-Q5 | GQ3: PC-86027 | GR3: PC-86450 | GS3: PC-86541 | GT3: PC-86541-Q5 | GU3: PC-86365 | GV3: PC-86905 | GW3: PC-86255B | GX3: PC-86037 | GY3: PC-86393 | GZ3: PC-86657-R | HA3: PC-86657-Q5 | HB3: PC-86449 | HC3: PC-86449Q5 | HD3: PC-86372 | HE3: PC-86270-R12 | HF3: PC-86270R-134A | HG3: PC-86275 | HH3: PC-86279 | HI3: PC-86043 | HJ3: PC-86245 | HK3: PC-86819-Q5 | HL3: PC-86818 | HM3: PC-86823 | HN3: PC-86824-Q5 | HO3: PC-86825 | HP3: PC-86826 | HQ3: PC-86821-Q5 | HR3: PC-86822 | HS3: PC-86817A-Q5 | HT3: PC-86817 | HU3: PC-86815 | HV3: PC-86811 | HW3: PC-86809 | HX3: PC-86911B (PC-86718) | HY3: PC-86911BQ5 (86718)
A4: QTY/CTN | L4: 5 | M4: 5 | N4: 5 | Q4: 5 | R4: 5 | S4: 5 | W4: 5 | Y4: 5 | AB4: 5 | AC4: 5 | AD4: 5 | AF4: 5 | AI4: 5 | AJ4: 5 | AK4: 5 | AN4: 5 | AR4: 5 | AS4: 5 | AV4: 5 | BB4: 5 | BC4: 5 | BD4: 5 | BF4: 5 | BI4: 5 | BK4: 5 | BL4: 5 | BM4: 5 | BN4: 5 | BO4: 5 | BQ4: 5 | BT4: 5 | BU4: 10 | BV4: 5 | BY4: 5 | CB4: 5 | CC4: 5 | CE4: 5 | CF4: 5 | CG4: 5 | CH4: 5 | CI4: 5 | CK4: 5 | CL4: 5 | CN4: 5 | CQ4: 5 | CS4: 5 | CT4: 5 | CV4: 5 | DC4: 5 | DJ4: 5 | DM4: 5 | DO4: 5 | DP4: 5 | DU4: 5 | DV4: 5 | DW4: 5 | DY4: 5 | EA4: 5 | EB4: 5 | EC4: 5 | ED4: 5 | EE4: 5 | EG4: 5 | EH4: 5 | EN4: 5 | EQ4: 5 | ER4: 5 | ES4: 5 | ET4: 5 | EU4: 5 | EV4: 5 | EW4: 5 | EX4: 5 | EZ4: 5 | FA4: 5 | FB4: 5 | FD4: 5 | FE4: 5 | FF4: 5 | FK4: 5 | FQ4: 5 | FR4: 5 | FS4: 5 | FT4: 5 | FU4: 5 | FX4: 5 | FZ4: 5 | GB4: 5 | GC4: 5 | GD4: 5 | GE4: 5 | GG4: 5 | GH4: 5 | GJ4: 5 | GK4: 5 | GM4: 5 | GP4: 5 | GR4: 5 | GT4: 5 | GU4: 5 | GV4: 5 | GW4: 5 | HD4: 5 | HE4: 5 | HF4: 5 | HH4: 10 | HI4: 5
A6: OPENING | B6: STOCK | C6: 01.04.2019 | L6: -5 | M6: 20 | N6: -6 | O6: 57 | P6: 172 | Q6: 18 | R6: 63 | S6: 8 | T6: 46 | U6: 37 | V6: 39 | W6: 65 | X6: 20 | Y6: 46 | Z6: 75 | AA6: 0 | AB6: 45 | AC6: 284 | AD6: 154 | AE6: 352 | AF6: 118 | AI6: 28 | AJ6: 16 | AK6: 15 | AL6: 50 | AM6: 383 | AN6: 77 | AO6: 267 | AP6: 95 | AQ6: 0 | AR6: 58 | AS6: 0 | AT6: 10 | AU6: 0 | AV6: 56 | AW6: 140 | AX6: 150 | AY6: 54 | AZ6: 100 | BA6: 47 | BB6: 0 | BC6: 78 | BD6: 0 | BE6: 0 | BF6: 0 | BH6: 130 | BI6: 0 | BJ6: 259 | BK6: 5 | BL6: 0 | BM6: 0 | BN6: 46 | BO6: 95 | BP6: 13 | BQ6: 171 | BR6: 244 | BS6: 39 | BT6: 220 | BU6: 25 | BV6: 96 | BW6: 98 | BX6: 22 | BY6: 880 | BZ6: 209 | CA6: 45 | CB6: 7 | CC6: 129 | CD6: 35 | CE6: 49 | CF6: 16 | CG6: 63 | CH6: 166 | CI6: -2 | CJ6: 40 | CK6: 68 | CL6: 51 | CM6: 32 | CN6: 293 | CO6: 87 | CP6: 66 | CQ6: 58 | CR6: 75 | CS6: 5 | CT6: 22 | CU6: 27 | CV6: 146 | CW6: 76 | CX6: 105 | CY6: 25 | CZ6: 90 | DA6: 74 | DB6: 28 | DC6: 145 | DD6: 166 | DE6: 25 | DF6: 247 | DG6: 45 | DH6: 182 | DI6: 50 | DJ6: 212 | DK6: 94 | DL6: 251 | DM6: 95 | DN6: 96 | DO6: 169 | DP6: 120 | DQ6: 7 | DR6: 132 | DS6: 23 | DT6: 212 | DU6: 10 | DV6: 207 | DW6: 292 | DX6: -8 | DY6: 16 | DZ6: 242 | EA6: 138 | EB6: 13 | EC6: 310 | ED6: 58 | EE6: 17 | EF6: 73 | EG6: 29 | EH6: 35 | EI6: 361 | EJ6: 26 | EK6: 17 | EL6: 0 | EM6: 23 | EN6: 42 | EO6: 177 | EP6: 127 | EQ6: 212 | ER6: 106 | ES6: 11 | ET6: 205 | EU6: 55 | EV6: 30 | EW6: 141 | EX6: 23 | EY6: 9 | EZ6: 27 | FA6: 103 | FB6: 20 | FC6: 97 | FD6: 20 | FE6: 10 | FF6: 25 | FG6: 19 | FH6: 67 | FI6: 40 | FJ6: 52 | FK6: 50 | FL6: 115 | FM6: 75 | FN6: 25 | FO6: 195 | FQ6: 20 | FR6: 374 | FS6: 324 | FT6: 389 | FU6: 38 | FV6: 10 | FW6: 38 | FX6: -14 | FY6: -15 | FZ6: 0 | GA6: 124 | GB6: 58 | GC6: -6 | GD6: -2 | GE6: 235 | GF6: 398 | GG6: 165 | GH6: 76 | GI6: 18 | GJ6: 110 | GL6: 478 | GM6: 53 | GO6: 72 | GP6: 104 | GQ6: -3 | GR6: 205 | GS6: -4 | GT6: 238 | GU6: 210 | GV6: 342 | GW6: -8 | GX6: 566 | GY6: 246 | GZ6: 79 | HA6: 103 | HB6: 102 | HC6: 9 | HD6: 454 | HE6: 15 | HF6: 194 | HG6: 178 | HH6: 5 | HI6: 22 | HJ6: 78 | HX6: 48 | HY6: 123
A9: PUR
B11: FBT1819/B2B02537 | C11: 07.01.19 | D11: JMF SYN.INDIA PVT LTD (METALOC) | E11: THESE TWO PUR ENTERED IN 2018-STK
B12: FBT1819/B2B02544 | C12: 08.01.19 | D12: JMF SYN.INDIA PVT LTD (METALOC)
B14: 9914260 | C14: 43500 | D14: OUNUO (+KAILIDA+ QIRUITE HOSE + SALLY BLOWER MOTOR) THR. HSS FROM SS IMPORTS TO DD IMPORTS (HUF) | E14: N.A | F14: 12.02.19 | G14: NOT TILL 31/3/19 | H14: 2019-1 13/01/2019 | I14: 19596.22 | J14: 1022 | AQ14: 100 | AU14: 100 | BG14: 50 | BV14: =15+55 -> 70 | CC14: 60 | CQ14: 150 | CR14: 45 | DU14: 150 | FH14: 75 | FT14: 3 | GM14: 50 | GY14: 410
B15: 2414903 | C15: 14.03.2019 | D15: OUYADI THR. HSS FROM SS IMPORTS TO DD IMPORTS (HUF) | E15: N.A | F15: 23.03.19 | G15: NOT TILL 31/3/19 | H15: OYD-190221 21/02/2019 | I15: 11211.1 | J15: 355 | AP15: 100 | AX15: 50 | CX15: 75 | DI15: 75 | EA15: 95 | EB15: 100 | EC15: 455 | EO15: 175 | EP15: 150 | FL15: 50 | FU15: 75 | FW15: 75 | GH15: 75
B16: 2776110 | C16: 09.04.19 | D16: JUNBO THR. HSS FROM OVERSEAS IMPORTS TO DD IMPORTS (HUF) (JUNBO+KAILIDA+BLUE+LEILA) | E16: N.A | F16: 17.04.19 | G16: NOT TILL 30/4/19 | H16: JB-GR021 DT.05.03.19 | I16: 27730.07 | J16: 1009 | AD16: 45 | AE16: 100 | AM16: 200 | BB16: 50 | BR16: 135 | BV16: 195 | CC16: 40 | CO16: 35 | CQ16: 230 | CV16: 165 | DK16: 5 | GC16: 50 | GG16: 30 | GK16: 125 | GR16: 75 | GY16: 535
B17: 3058693 | C17: 01.05.19 | D17: HBS YOU2 THR. HSS FROM OVERSEAS IMPORTS TO DD IMPORTS (HUF) (HBS+BRYAN-GZ) | E17: N.A | F17: 08.05.19 | G17: NOT TILL 31/5/19 | H17: HBS19M0321AG 21/03/2019 | I17: 14749.2 | J17: 1180
B18: 3174223 | C18: 10.05.19 | D18: KALIDA THR. HSS FROM OVERSEAS IMPORTS TO DD IMPORTS (HUF) (KAILIDA+TRACY BLOWER) | E18: N.A | F18: 16.05.19 | G18: NOT TILL 31/5/19 | H18: KLD20190412 12/04/2019 | I18: 11141.28 | J18: 555 | AB18: 100 | AC18: 15 | AD18: 1 | AE18: 200 | BI18: 50 | BK18: =45+45 -> 90 | BN18: 50 | CO18: 110 | DJ18: 5 | DK18: =90+4 -> 94 | DL18: =300+3 -> 303 | DM18: 50 | DU18: =1+60 -> 61 | ER18: =95+5 -> 100 | FO18: =45+3 -> 48 | FP18: 50 | FQ18: 50 | FT18: =70+2 -> 72 | GF18: 4 | GG18: 200 | GM18: 150 | GR18: 50 | GT18: =190+4 -> 194 | GY18: 500 | HC18: 90
B19: 3447368 | C19: 30.05.19 | D19: OYADI PLUS KALIDA THROUGH SS IMPORTS | E19: N.A | H19: OYDY190504 | J19: 589 | L19: 100 | Q19: 200 | AD19: 50 | BV19: 100 | CJ19: 150 | CN19: 150 | DD19: 50 | DJ19: 295 | GF19: 200 | GZ19: 55 | HA19: 50 | HJ19: 150 | HX19: 75
B20: 3916709 | C20: 03.07.19 | D20: OUNUO AUTOMOTIVE THROUGH SS IMPORTS (HOSE+CONDENSER+LEILA+STAL+OYD) | J20: 817 | AA20: 50 | AM20: 45 | BR20: 50 | CC20: 160 | DF20: 200 | DO20: 75 | EO20: 150 | EP20: 45 | FJ20: 150 | HK20: 50 | HL20: 100 | HM20: 150 | HN20: 50 | HO20: 50 | HP20: 50
A21: this BOE of 2018 stock wrongly entered in 2019 stock | B21: 7579687 | C21: 10.08.18 | D21: OUYADI THROUGH OVERSEAS IMPORT, | H21: OYD-180630 | J21: 488
B22: 3631723 | C22: 13.06.19 | D22: OUYADI THROUGH OVERSEAS IMPORT, | H22: OYD-190511 | J22: 417 | M22: 100 | S22: 100 | Y22: 50 | AO22: 250 | AT22: 25 | CB22: 125 | CF22: 50 | CI22: 50 | CX22: 50 | DB22: 100 | DC22: 40 | DD22: 100 | DN22: 5 | DX22: 25 | DY22: 50 | EB22: 45 | EE22: 50 | EI22: 155 | FV22: 75 | FW22: 75 | GB22: 100 | GD22: 20 | GH22: 150 | GW22: 25 | GZ22: 95 | HI22: 50
B23: 4233982 | C23: 26.07.19 | D23: HBS YOU2 FROM OVERSEAS IMPORTS 963 CTN | J23: 963 | T23: 50 | BC23: =145+1 -> 146
B24: 4522428 | C24: 16.08.19 | D24: OUNUO AUTOMOTIVE THROUGH SS IMPORTS (CONDENSER+TRACCY+KALIDA+OYD+CHUNGLI+STAL) | J24: 711 | AM24: 100 | BE24: 110 | BF24: 50 | BH24: 100 | BJ24: 50 | CN24: 135 | DH24: 15 | DJ24: 300 | DU24: 80 | ED24: 100 | ER24: 50 | FH24: 25 | GP24: 50 | HP24: 30 | HQ24: 40 | HR24: 200
