Workbook

Sheet Recon
B1: Condensers | I1: Cooling Coil | P1: Blowers
B2: Part | D2: Challan (pcs) | E2: Stock Sold | F2: Gap | G2: Total Available | I2: Part | K2: Challan (pcs) | L2: Stock Sold | M2: Gap | N2: Total Available | P2: Part | R2: Challan (pcs) | S2: Stock Sold | T2: Gap | U2: Total Available
B3: INNOVA | C3: PC-86046 | D3: 340 | E3: =IF(AND(B3="",C3=""),"",IF(C3<>"",IF(COUNTIFS(Stock!$D$4:$IP$4,B3,Stock!$D$5:$IP$5,C3)>0,SUMIFS(Stock!$D$340:$IP$340,Stock!$D$4:$IP$4,B3,Stock!$D$5:$IP$5,C3),IF(COUNTIF(Stock!$D$5:$IP$5,C3)>0,SUMIF(Stock!$D$5:$IP$5,C3,Stock!$D$340:$IP$340),SUMIF(Stock!$D$4:$IP$4,B3,Stock!$D$340:$IP$340))),SUMIF(Stock!$D$4:$IP$4,B3,Stock!$D$340:$IP$340))) -> 265 | F3: =D3-E3 -> 75 | G3: =IF(AND(B3="",C3=""),"",IF(C3<>"",IF(COUNTIFS(Stock!$D$4:$IP$4,B3,Stock!$D$5:$IP$5,C3)>0,SUMIFS(Stock!$D$32:$IP$32,Stock!$D$4:$IP$4,B3,Stock!$D$5:$IP$5,C3),IF(COUNTIF(Stock!$D$5:$IP$5,C3)>0,SUMIF(Stock!$D$5:$IP$5,C3,Stock!$D$32:$IP$32),SUMIF(Stock!$D$4:$IP$4,B3,Stock!$D$32:$IP$32))),SUMIF(Stock!$D$4:$IP$4,B3,Stock!$D$32:$IP$32))) -> 360 | I3: A6 | J3: PC-A6 | K3: 602 | L3: =IF(AND(I3="",J3=""),"",IF(J3<>"",IF(COUNTIFS(Stock!$D$4:$IP$4,I3,Stock!$D$5:$IP$5,J3)>0,SUMIFS(Stock!$D$340:$IP$340,Stock!$D$4:$IP$4,I3,Stock!$D$5:$IP$5,J3),IF(COUNTIF(Stock!$D$5:$IP$5,J3)>0,SUMIF(Stock!$D$5:$IP$5,J3,Stock!$D$340:$IP$340),SUMIF(Stock!$D$4:$IP$4,I3,Stock!$D$340:$IP$340))),SUMIF(Stock!$D$4:$IP$4,I3,Stock!$D$340:$IP$340))) -> 250 | M3: =K3-L3 -> 352 | N3: =IF(AND(I3="",J3=""),"",IF(J3<>"",IF(COUNTIFS(Stock!$D$4:$IP$4,I3,Stock!$D$5:$IP$5,J3)>0,SUMIFS(Stock!$D$32:$IP$32,Stock!$D$4:$IP$4,I3,Stock!$D$5:$IP$5,J3),IF(COUNTIF(Stock!$D$5:$IP$5,J3)>0,SUMIF(Stock!$D$5:$IP$5,J3,Stock!$D$32:$IP$32),SUMIF(Stock!$D$4:$IP$4,I3,Stock!$D$32:$IP$32))),SUMIF(Stock!$D$4:$IP$4,I3,Stock!$D$32:$IP$32))) -> 650 | P3: MICROBUS-Tubefin | Q3: MICROBUS | R3: 62 | S3: =IF(AND(P3="",Q3=""),"",IF(Q3<>"",IF(COUNTIFS(Stock!$D$4:$IP$4,P3,Stock!$D$5:$IP$5,Q3)>0,SUMIFS(Stock!$D$340:$IP$340,Stock!$D$4:$IP$4,P3,Stock!$D$5:$IP$5,Q3),IF(COUNTIF(Stock!$D$5:$IP$5,Q3)>0,SUMIF(Stock!$D$5:$IP$5,Q3,Stock!$D$340:$IP$340),SUMIF(Stock!$D$4:$IP$4,P3,Stock!$D$340:$IP$340))),SUMIF(Stock!$D$4:$IP$4,P3,Stock!$D$340:$IP$340))) -> 42 | T3: =R3-S3 -> 20 | U3: =IF(AND(P3="",Q3=""),"",IF(Q3<>"",IF(COUNTIFS(Stock!$D$4:$IP$4,P3,Stock!$D$5:$IP$5,Q3)>0,SUMIFS(Stock!$D$32:$IP$32,Stock!$D$4:$IP$4,P3,Stock!$D$5:$IP$5,Q3),IF(COUNTIF(Stock!$D$5:$IP$5,Q3)>0,SUMIF(Stock!$D$5:$IP$5,Q3,Stock!$D$32:$IP$32),SUMIF(Stock!$D$4:$IP$4,P3,Stock!$D$32:$IP$32))),SUMIF(Stock!$D$4:$IP$4,P3,Stock!$D$32:$IP$32))) -> 62
B4: SKODA | C4: PC-86004 | D4: 85 | E4: =IF(AND(B4="",C4=""),"",IF(C4<>"",IF(COUNTIFS(Stock!$D$4:$IP$4,B4,Stock!$D$5:$IP$5,C4)>0,SUMIFS(Stock!$D$340:$IP$340,Stock!$D$4:$IP$4,B4,Stock!$D$5:$IP$5,C4),IF(COUNTIF(Stock!$D$5:$IP$5,C4)>0,SUMIF(Stock!$D$5:$IP$5,C4,Stock!$D$340:$IP$340),SUMIF(Stock!$D$4:$IP$4,B4,Stock!$D$340:$IP$340))),SUMIF(Stock!$D$4:$IP$4,B4,Stock!$D$340:$IP$340))) -> 45 | F4: =D4-E4 -> 40 | G4: =IF(AND(B4="",C4=""),"",IF(C4<>"",IF(COUNTIFS(Stock!$D$4:$IP$4,B4,Stock!$D$5:$IP$5,C4)>0,SUMIFS(Stock!$D$32:$IP$32,Stock!$D$4:$IP$4,B4,Stock!$D$5:$IP$5,C4),IF(COUNTIF(Stock!$D$5:$IP$5,C4)>0,SUMIF(Stock!$D$5:$IP$5,C4,Stock!$D$32:$IP$32),SUMIF(Stock!$D$4:$IP$4,B4,Stock!$D$32:$IP$32))),SUMIF(Stock!$D$4:$IP$4,B4,Stock!$D$32:$IP$32))) -> 94 | I4: Accent | J4: PC-055R | K4: 50 | L4: =IF(AND(I4="",J4=""),"",IF(J4<>"",IF(COUNTIFS(Stock!$D$4:$IP$4,I4,Stock!$D$5:$IP$5,J4)>0,SUMIFS(Stock!$D$340:$IP$340,Stock!$D$4:$IP$4,I4,Stock!$D$5:$IP$5,J4),IF(COUNTIF(Stock!$D$5:$IP$5,J4)>0,SUMIF(Stock!$D$5:$IP$5,J4,Stock!$D$340:$IP$340),SUMIF(Stock!$D$4:$IP$4,I4,Stock!$D$340:$IP$340))),SUMIF(Stock!$D$4:$IP$4,I4,Stock!$D$340:$IP$340))) -> 50 | M4: =K4-L4 -> 0 | N4: =IF(AND(I4="",J4=""),"",IF(J4<>"",IF(COUNTIFS(Stock!$D$4:$IP$4,I4,Stock!$D$5:$IP$5,J4)>0,SUMIFS(Stock!$D$32:$IP$32,Stock!$D$4:$IP$4,I4,Stock!$D$5:$IP$5,J4),IF(COUNTIF(Stock!$D$5:$IP$5,J4)>0,SUMIF(Stock!$D$5:$IP$5,J4,Stock!$D$32:$IP$32),SUMIF(Stock!$D$4:$IP$4,I4,Stock!$D$32:$IP$32))),SUMIF(Stock!$D$4:$IP$4,I4,Stock!$D$32:$IP$32))) -> 50 | P4: MICROBUS-PF | Q4: PFMICROBUS;PARALLFLOWMICROBUS;MULTIFLOWMICROBUS;848L | R4: 300 | S4: =IF(AND(P4="",Q4=""),"",IF(Q4<>"",IF(COUNTIFS(Stock!$D$4:$IP$4,P4,Stock!$D$5:$IP$5,Q4)>0,SUMIFS(Stock!$D$340:$IP$340,Stock!$D$4:$IP$4,P4,Stock!$D$5:$IP$5,Q4),IF(COUNTIF(Stock!$D$5:$IP$5,Q4)>0,SUMIF(Stock!$D$5:$IP$5,Q4,Stock!$D$340:$IP$340),SUMIF(Stock!$D$4:$IP$4,P4,Stock!$D$340:$IP$340))),SUMIF(Stock!$D$4:$IP$4,P4,Stock!$D$340:$IP$340))) -> 202 | T4: =R4-S4 -> 98 | U4: =IF(AND(P4="",Q4=""),"",IF(Q4<>"",IF(COUNTIFS(Stock!$D$4:$IP$4,P4,Stock!$D$5:$IP$5,Q4)>0,SUMIFS(Stock!$D$32:$IP$32,Stock!$D$4:$IP$4,P4,Stock!$D$5:$IP$5,Q4),IF(COUNTIF(Stock!$D$5:$IP$5,Q4)>0,SUMIF(Stock!$D$5:$IP$5,Q4,Stock!$D$32:$IP$32),SUMIF(Stock!$D$4:$IP$4,P4,Stock!$D$32:$IP$32))),SUMIF(Stock!$D$4:$IP$4,P4,Stock!$D$32:$IP$32))) -> 300
B5: INDICA/BEHR-R134A | C5: PC-86233 | D5: 785 | E5: =IF(AND(B5="",C5=""),"",IF(C5<>"",IF(COUNTIFS(Stock!$D$4:$IP$4,B5,Stock!$D$5:$IP$5,C5)>0,SUMIFS(Stock!$D$340:$IP$340,Stock!$D$4:$IP$4,B5,Stock!$D$5:$IP$5,C5),IF(COUNTIF(Stock!$D$5:$IP$5,C5)>0,SUMIF(Stock!$D$5:$IP$5,C5,Stock!$D$340:$IP$340),SUMIF(Stock!$D$4:$IP$4,B5,Stock!$D$340:$IP$340))),SUMIF(Stock!$D$4:$IP$4,B5,Stock!$D$340:$IP$340))) -> 585 | F5: =D5-E5 -> 200 | G5: =IF(AND(B5="",C5=""),"",IF(C5<>"",IF(COUNTIFS(Stock!$D$4:$IP$4,B5,Stock!$D$5:$IP$5,C5)>0,SUMIFS(Stock!$D$32:$IP$32,Stock!$D$4:$IP$4,B5,Stock!$D$5:$IP$5,C5),IF(COUNTIF(Stock!$D$5:$IP$5,C5)>0,SUMIF(Stock!$D$5:$IP$5,C5,Stock!$D$32:$IP$32),SUMIF(Stock!$D$4:$IP$4,B5,Stock!$D$32:$IP$32))),SUMIF(Stock!$D$4:$IP$4,B5,Stock!$D$32:$IP$32))) -> 785 | I5: ACCORD | J5: PC-510 | K5: 0 | L5: =IF(AND(I5="",J5=""),"",IF(J5<>"",IF(COUNTIFS(Stock!$D$4:$IP$4,I5,Stock!$D$5:$IP$5,J5)>0,SUMIFS(Stock!$D$340:$IP$340,Stock!$D$4:$IP$4,I5,Stock!$D$5:$IP$5,J5),IF(COUNTIF(Stock!$D$5:$IP$5,J5)>0,SUMIF(Stock!$D$5:$IP$5,J5,Stock!$D$340:$IP$340),SUMIF(Stock!$D$4:$IP$4,I5,Stock!$D$340:$IP$340))),SUMIF(Stock!$D$4:$IP$4,I5,Stock!$D$340:$IP$340))) -> 0 | M5: =K5-L5 -> 0 | N5: =IF(AND(I5="",J5=""),"",IF(J5<>"",IF(COUNTIFS(Stock!$D$4:$IP$4,I5,Stock!$D$5:$IP$5,J5)>0,SUMIFS(Stock!$D$32:$IP$32,Stock!$D$4:$IP$4,I5,Stock!$D$5:$IP$5,J5),IF(COUNTIF(Stock!$D$5:$IP$5,J5)>0,SUMIF(Stock!$D$5:$IP$5,J5,Stock!$D$32:$IP$32),SUMIF(Stock!$D$4:$IP$4,I5,Stock!$D$32:$IP$32))),SUMIF(Stock!$D$4:$IP$4,I5,Stock!$D$32:$IP$32))) -> 0 | P5: MiniBus | Q5: MINIBUS | R5: 14 | S5: =IF(AND(P5="",Q5=""),"",IF(Q5<>"",IF(COUNTIFS(Stock!$D$4:$IP$4,P5,Stock!$D$5:$IP$5,Q5)>0,SUMIFS(Stock!$D$340:$IP$340,Stock!$D$4:$IP$4,P5,Stock!$D$5:$IP$5,Q5),IF(COUNTIF(Stock!$D$5:$IP$5,Q5)>0,SUMIF(Stock!$D$5:$IP$5,Q5,Stock!$D$340:$IP$340),SUMIF(Stock!$D$4:$IP$4,P5,Stock!$D$340:$IP$340))),SUMIF(Stock!$D$4:$IP$4,P5,Stock!$D$340:$IP$340))) -> 4 | T5: =R5-S5 -> 10 | U5: =IF(AND(P5="",Q5=""),"",IF(Q5<>"",IF(COUNTIFS(Stock!$D$4:$IP$4,P5,Stock!$D$5:$IP$5,Q5)>0,SUMIFS(Stock!$D$32:$IP$32,Stock!$D$4:$IP$4,P5,Stock!$D$5:$IP$5,Q5),IF(COUNTIF(Stock!$D$5:$IP$5,Q5)>0,SUMIF(Stock!$D$5:$IP$5,Q5,Stock!$D$32:$IP$32),SUMIF(Stock!$D$4:$IP$4,P5,Stock!$D$32:$IP$32))),SUMIF(Stock!$D$4:$IP$4,P5,Stock!$D$32:$IP$32))) -> 80
B6: QUALIS-FLARE | C6: PC-86234 | D6: 95 | E6: =IF(AND(B6="",C6=""),"",IF(C6<>"",IF(COUNTIFS(Stock!$D$4:$IP$4,B6,Stock!$D$5:$IP$5,C6)>0,SUMIFS(Stock!$D$340:$IP$340,Stock!$D$4:$IP$4,B6,Stock!$D$5:$IP$5,C6),IF(COUNTIF(Stock!$D$5:$IP$5,C6)>0,SUMIF(Stock!$D$5:$IP$5,C6,Stock!$D$340:$IP$340),SUMIF(Stock!$D$4:$IP$4,B6,Stock!$D$340:$IP$340))),SUMIF(Stock!$D$4:$IP$4,B6,Stock!$D$340:$IP$340))) -> 50 | F6: =D6-E6 -> 45 | G6: =IF(AND(B6="",C6=""),"",IF(C6<>"",IF(COUNTIFS(Stock!$D$4:$IP$4,B6,Stock!$D$5:$IP$5,C6)>0,SUMIFS(Stock!$D$32:$IP$32,Stock!$D$4:$IP$4,B6,Stock!$D$5:$IP$5,C6),IF(COUNTIF(Stock!$D$5:$IP$5,C6)>0,SUMIF(Stock!$D$5:$IP$5,C6,Stock!$D$32:$IP$32),SUMIF(Stock!$D$4:$IP$4,B6,Stock!$D$32:$IP$32))),SUMIF(Stock!$D$4:$IP$4,B6,Stock!$D$32:$IP$32))) -> 100 | I6: AVEO | J6: PC-614 | K6: 51 | L6: =IF(AND(I6="",J6=""),"",IF(J6<>"",IF(COUNTIFS(Stock!$D$4:$IP$4,I6,Stock!$D$5:$IP$5,J6)>0,SUMIFS(Stock!$D$340:$IP$340,Stock!$D$4:$IP$4,I6,Stock!$D$5:$IP$5,J6),IF(COUNTIF(Stock!$D$5:$IP$5,J6)>0,SUMIF(Stock!$D$5:$IP$5,J6,Stock!$D$340:$IP$340),SUMIF(Stock!$D$4:$IP$4,I6,Stock!$D$340:$IP$340))),SUMIF(Stock!$D$4:$IP$4,I6,Stock!$D$340:$IP$340))) -> 0 | M6: =K6-L6 -> 51 | N6: =IF(AND(I6="",J6=""),"",IF(J6<>"",IF(COUNTIFS(Stock!$D$4:$IP$4,I6,Stock!$D$5:$IP$5,J6)>0,SUMIFS(Stock!$D$32:$IP$32,Stock!$D$4:$IP$4,I6,Stock!$D$5:$IP$5,J6),IF(COUNTIF(Stock!$D$5:$IP$5,J6)>0,SUMIF(Stock!$D$5:$IP$5,J6,Stock!$D$32:$IP$32),SUMIF(Stock!$D$4:$IP$4,I6,Stock!$D$32:$IP$32))),SUMIF(Stock!$D$4:$IP$4,I6,Stock!$D$32:$IP$32))) -> 0 | P6: SK | Q6: SK;SKBLOWER;UNICLASK;UNICLASKBLOWER | R6: 312 | S6: =IF(AND(P6="",Q6=""),"",IF(Q6<>"",IF(COUNTIFS(Stock!$D$4:$IP$4,P6,Stock!$D$5:$IP$5,Q6)>0,SUMIFS(Stock!$D$340:$IP$340,Stock!$D$4:$IP$4,P6,Stock!$D$5:$IP$5,Q6),IF(COUNTIF(Stock!$D$5:$IP$5,Q6)>0,SUMIF(Stock!$D$5:$IP$5,Q6,Stock!$D$340:$IP$340),SUMIF(Stock!$D$4:$IP$4,P6,Stock!$D$340:$IP$340))),SUMIF(Stock!$D$4:$IP$4,P6,Stock!$D$340:$IP$340))) -> 350 | T6: =R6-S6 -> -38 | U6: =IF(AND(P6="",Q6=""),"",IF(Q6<>"",IF(COUNTIFS(Stock!$D$4:$IP$4,P6,Stock!$D$5:$IP$5,Q6)>0,SUMIFS(Stock!$D$32:$IP$32,Stock!$D$4:$IP$4,P6,Stock!$D$5:$IP$5,Q6),IF(COUNTIF(Stock!$D$5:$IP$5,Q6)>0,SUMIF(Stock!$D$5:$IP$5,Q6,Stock!$D$32:$IP$32),SUMIF(Stock!$D$4:$IP$4,P6,Stock!$D$32:$IP$32))),SUMIF(Stock!$D$4:$IP$4,P6,Stock!$D$32:$IP$32))) -> 350
B7: Qualis-PAD | C7: PC-86235 | D7: 205 | E7: =IF(AND(B7="",C7=""),"",IF(C7<>"",IF(COUNTIFS(Stock!$D$4:$IP$4,B7,Stock!$D$5:$IP$5,C7)>0,SUMIFS(Stock!$D$340:$IP$340,Stock!$D$4:$IP$4,B7,Stock!$D$5:$IP$5,C7),IF(COUNTIF(Stock!$D$5:$IP$5,C7)>0,SUMIF(Stock!$D$5:$IP$5,C7,Stock!$D$340:$IP$340),SUMIF(Stock!$D$4:$IP$4,B7,Stock!$D$340:$IP$340))),SUMIF(Stock!$D$4:$IP$4,B7,Stock!$D$340:$IP$340))) -> 155 | F7: =D7-E7 -> 50 | G7: =IF(AND(B7="",C7=""),"",IF(C7<>"",IF(COUNTIFS(Stock!$D$4:$IP$4,B7,Stock!$D$5:$IP$5,C7)>0,SUMIFS(Stock!$D$32:$IP$32,Stock!$D$4:$IP$4,B7,Stock!$D$5:$IP$5,C7),IF(COUNTIF(Stock!$D$5:$IP$5,C7)>0,SUMIF(Stock!$D$5:$IP$5,C7,Stock!$D$32:$IP$32),SUMIF(Stock!$D$4:$IP$4,B7,Stock!$D$32:$IP$32))),SUMIF(Stock!$D$4:$IP$4,B7,Stock!$D$32:$IP$32))) -> 205 | I7: Baleno | J7: PC-142R | K7: 126 | L7: =IF(AND(I7="",J7=""),"",IF(J7<>"",IF(COUNTIFS(Stock!$D$4:$IP$4,I7,Stock!$D$5:$IP$5,J7)>0,SUMIFS(Stock!$D$340:$IP$340,Stock!$D$4:$IP$4,I7,Stock!$D$5:$IP$5,J7),IF(COUNTIF(Stock!$D$5:$IP$5,J7)>0,SUMIF(Stock!$D$5:$IP$5,J7,Stock!$D$340:$IP$340),SUMIF(Stock!$D$4:$IP$4,I7,Stock!$D$340:$IP$340))),SUMIF(Stock!$D$4:$IP$4,I7,Stock!$D$340:$IP$340))) -> 126 | M7: =K7-L7 -> 0 | N7: =IF(AND(I7="",J7=""),"",IF(J7<>"",IF(COUNTIFS(Stock!$D$4:$IP$4,I7,Stock!$D$5:$IP$5,J7)>0,SUMIFS(Stock!$D$32:$IP$32,Stock!$D$4:$IP$4,I7,Stock!$D$5:$IP$5,J7),IF(COUNTIF(Stock!$D$5:$IP$5,J7)>0,SUMIF(Stock!$D$5:$IP$5,J7,Stock!$D$32:$IP$32),SUMIF(Stock!$D$4:$IP$4,I7,Stock!$D$32:$IP$32))),SUMIF(Stock!$D$4:$IP$4,I7,Stock!$D$32:$IP$32))) -> 129 | P7: Concord-Elec, | Q7: CONCORD;UNICLACONCORD;UNICALCONCORD;CONCORDSUPERIOR;CONCORDBEIGE | R7: 597 | S7: =IF(AND(P7="",Q7=""),"",IF(Q7<>"",IF(COUNTIFS(Stock!$D$4:$IP$4,P7,Stock!$D$5:$IP$5,Q7)>0,SUMIFS(Stock!$D$340:$IP$340,Stock!$D$4:$IP$4,P7,Stock!$D$5:$IP$5,Q7),IF(COUNTIF(Stock!$D$5:$IP$5,Q7)>0,SUMIF(Stock!$D$5:$IP$5,Q7,Stock!$D$340:$IP$340),SUMIF(Stock!$D$4:$IP$4,P7,Stock!$D$340:$IP$340))),SUMIF(Stock!$D$4:$IP$4,P7,Stock!$D$340:$IP$340))) -> 577 | T7: =R7-S7 -> 20 | U7: =IF(AND(P7="",Q7=""),"",IF(Q7<>"",IF(COUNTIFS(Stock!$D$4:$IP$4,P7,Stock!$D$5:$IP$5,Q7)>0,SUMIFS(Stock!$D$32:$IP$32,Stock!$D$4:$IP$4,P7,Stock!$D$5:$IP$5,Q7),IF(COUNTIF(Stock!$D$5:$IP$5,Q7)>0,SUMIF(Stock!$D$5:$IP$5,Q7,Stock!$D$32:$IP$32),SUMIF(Stock!$D$4:$IP$4,P7,Stock!$D$32:$IP$32))),SUMIF(Stock!$D$4:$IP$4,P7,Stock!$D$32:$IP$32))) -> 579
B8: Qualis-O Ring | C8: PC-86244 | D8: 100 | E8: =IF(AND(B8="",C8=""),"",IF(C8<>"",IF(COUNTIFS(Stock!$D$4:$IP$4,B8,Stock!$D$5:$IP$5,C8)>0,SUMIFS(Stock!$D$340:$IP$340,Stock!$D$4:$IP$4,B8,Stock!$D$5:$IP$5,C8),IF(COUNTIF(Stock!$D$5:$IP$5,C8)>0,SUMIF(Stock!$D$5:$IP$5,C8,Stock!$D$340:$IP$340),SUMIF(Stock!$D$4:$IP$4,B8,Stock!$D$340:$IP$340))),SUMIF(Stock!$D$4:$IP$4,B8,Stock!$D$340:$IP$340))) -> 100 | F8: =D8-E8 -> 0 | G8: =IF(AND(B8="",C8=""),"",IF(C8<>"",IF(COUNTIFS(Stock!$D$4:$IP$4,B8,Stock!$D$5:$IP$5,C8)>0,SUMIFS(Stock!$D$32:$IP$32,Stock!$D$4:$IP$4,B8,Stock!$D$5:$IP$5,C8),IF(COUNTIF(Stock!$D$5:$IP$5,C8)>0,SUMIF(Stock!$D$5:$IP$5,C8,Stock!$D$32:$IP$32),SUMIF(Stock!$D$4:$IP$4,B8,Stock!$D$32:$IP$32))),SUMIF(Stock!$D$4:$IP$4,B8,Stock!$D$32:$IP$32))) -> 100 | I8: BOlero R134a | J8: PC-8095 | K8: 72 | L8: =IF(AND(I8="",J8=""),"",IF(J8<>"",IF(COUNTIFS(Stock!$D$4:$IP$4,I8,Stock!$D$5:$IP$5,J8)>0,SUMIFS(Stock!$D$340:$IP$340,Stock!$D$4:$IP$4,I8,Stock!$D$5:$IP$5,J8),IF(COUNTIF(Stock!$D$5:$IP$5,J8)>0,SUMIF(Stock!$D$5:$IP$5,J8,Stock!$D$340:$IP$340),SUMIF(Stock!$D$4:$IP$4,I8,Stock!$D$340:$IP$340))),SUMIF(Stock!$D$4:$IP$4,I8,Stock!$D$340:$IP$340))) -> 54 | M8: =K8-L8 -> 18 | N8: =IF(AND(I8="",J8=""),"",IF(J8<>"",IF(COUNTIFS(Stock!$D$4:$IP$4,I8,Stock!$D$5:$IP$5,J8)>0,SUMIFS(Stock!$D$32:$IP$32,Stock!$D$4:$IP$4,I8,Stock!$D$5:$IP$5,J8),IF(COUNTIF(Stock!$D$5:$IP$5,J8)>0,SUMIF(Stock!$D$5:$IP$5,J8,Stock!$D$32:$IP$32),SUMIF(Stock!$D$4:$IP$4,I8,Stock!$D$32:$IP$32))),SUMIF(Stock!$D$4:$IP$4,I8,Stock!$D$32:$IP$32))) -> 84 | P8: Concord-Normal | S8: =IF(AND(P8="",Q8=""),"",IF(Q8<>"",IF(COUNTIFS(Stock!$D$4:$IP$4,P8,Stock!$D$5:$IP$5,Q8)>0,SUMIFS(Stock!$D$340:$IP$340,Stock!$D$4:$IP$4,P8,Stock!$D$5:$IP$5,Q8),IF(COUNTIF(Stock!$D$5:$IP$5,Q8)>0,SUMIF(Stock!$D$5:$IP$5,Q8,Stock!$D$340:$IP$340),SUMIF(Stock!$D$4:$IP$4,P8,Stock!$D$340:$IP$340))),SUMIF(Stock!$D$4:$IP$4,P8,Stock!$D$340:$IP$340))) -> 0 | T8: =R8-S8 -> 0 | U8: =IF(AND(P8="",Q8=""),"",IF(Q8<>"",IF(COUNTIFS(Stock!$D$4:$IP$4,P8,Stock!$D$5:$IP$5,Q8)>0,SUMIFS(Stock!$D$32:$IP$32,Stock!$D$4:$IP$4,P8,Stock!$D$5:$IP$5,Q8),IF(COUNTIF(Stock!$D$5:$IP$5,Q8)>0,SUMIF(Stock!$D$5:$IP$5,Q8,Stock!$D$32:$IP$32),SUMIF(Stock!$D$4:$IP$4,P8,Stock!$D$32:$IP$32))),SUMIF(Stock!$D$4:$IP$4,P8,Stock!$D$32:$IP$32))) -> 0
B9: Ford Ikon | C9: PC-86034 | D9: 125 | E9: =IF(AND(B9="",C9=""),"",IF(C9<>"",IF(COUNTIFS(Stock!$D$4:$IP$4,B9,Stock!$D$5:$IP$5,C9)>0,SUMIFS(Stock!$D$340:$IP$340,Stock!$D$4:$IP$4,B9,Stock!$D$5:$IP$5,C9),IF(COUNTIF(Stock!$D$5:$IP$5,C9)>0,SUMIF(Stock!$D$5:$IP$5,C9,Stock!$D$340:$IP$340),SUMIF(Stock!$D$4:$IP$4,B9,Stock!$D$340:$IP$340))),SUMIF(Stock!$D$4:$IP$4,B9,Stock!$D$340:$IP$340))) -> 85 | F9: =D9-E9 -> 40 | G9: =IF(AND(B9="",C9=""),"",IF(C9<>"",IF(COUNTIFS(Stock!$D$4:$IP$4,B9,Stock!$D$5:$IP$5,C9)>0,SUMIFS(Stock!$D$32:$IP$32,Stock!$D$4:$IP$4,B9,Stock!$D$5:$IP$5,C9),IF(COUNTIF(Stock!$D$5:$IP$5,C9)>0,SUMIF(Stock!$D$5:$IP$5,C9,Stock!$D$32:$IP$32),SUMIF(Stock!$D$4:$IP$4,B9,Stock!$D$32:$IP$32))),SUMIF(Stock!$D$4:$IP$4,B9,Stock!$D$32:$IP$32))) -> 135 | I9: CAMERY | J9: PC-533 | L9: =IF(AND(I9="",J9=""),"",IF(J9<>"",IF(COUNTIFS(Stock!$D$4:$IP$4,I9,Stock!$D$5:$IP$5,J9)>0,SUMIFS(Stock!$D$340:$IP$340,Stock!$D$4:$IP$4,I9,Stock!$D$5:$IP$5,J9),IF(COUNTIF(Stock!$D$5:$IP$5,J9)>0,SUMIF(Stock!$D$5:$IP$5,J9,Stock!$D$340:$IP$340),SUMIF(Stock!$D$4:$IP$4,I9,Stock!$D$340:$IP$340))),SUMIF(Stock!$D$4:$IP$4,I9,Stock!$D$340:$IP$340))) -> 0 | M9: =K9-L9 -> 0 | N9: =IF(AND(I9="",J9=""),"",IF(J9<>"",IF(COUNTIFS(Stock!$D$4:$IP$4,I9,Stock!$D$5:$IP$5,J9)>0,SUMIFS(Stock!$D$32:$IP$32,Stock!$D$4:$IP$4,I9,Stock!$D$5:$IP$5,J9),IF(COUNTIF(Stock!$D$5:$IP$5,J9)>0,SUMIF(Stock!$D$5:$IP$5,J9,Stock!$D$32:$IP$32),SUMIF(Stock!$D$4:$IP$4,I9,Stock!$D$32:$IP$32))),SUMIF(Stock!$D$4:$IP$4,I9,Stock!$D$32:$IP$32))) -> 0 | P9: 405 | Q9: 405;405SUPERKING;SUPERKING;SK405;FSK405;405BLOWER;F405SUPERKINGBLOWER;BLOWERSUPERKING;FORMULA405SUPERKINGBLOWER;FSUPERKING405 | R9: 10 | S9: =IF(AND(P9="",Q9=""),"",IF(Q9<>"",IF(COUNTIFS(Stock!$D$4:$IP$4,P9,Stock!$D$5:$IP$5,Q9)>0,SUMIFS(Stock!$D$340:$IP$340,Stock!$D$4:$IP$4,P9,Stock!$D$5:$IP$5,Q9),IF(COUNTIF(Stock!$D$5:$IP$5,Q9)>0,SUMIF(Stock!$D$5:$IP$5,Q9,Stock!$D$340:$IP$340),SUMIF(Stock!$D$4:$IP$4,P9,Stock!$D$340:$IP$340))),SUMIF(Stock!$D$4:$IP$4,P9,Stock!$D$340:$IP$340))) -> 151 | T9: =R9-S9 -> -141 | U9: =IF(AND(P9="",Q9=""),"",IF(Q9<>"",IF(COUNTIFS(Stock!$D$4:$IP$4,P9,Stock!$D$5:$IP$5,Q9)>0,SUMIFS(Stock!$D$32:$IP$32,Stock!$D$4:$IP$4,P9,Stock!$D$5:$IP$5,Q9),IF(COUNTIF(Stock!$D$5:$IP$5,Q9)>0,SUMIF(Stock!$D$5:$IP$5,Q9,Stock!$D$32:$IP$32),SUMIF(Stock!$D$4:$IP$4,P9,Stock!$D$32:$IP$32))),SUMIF(Stock!$D$4:$IP$4,P9,Stock!$D$32:$IP$32))) -> 151
B10: BOLERO- R134A | C10: PC-86236 | D10: 95 | E10: =IF(AND(B10="",C10=""),"",IF(C10<>"",IF(COUNTIFS(Stock!$D$4:$IP$4,B10,Stock!$D$5:$IP$5,C10)>0,SUMIFS(Stock!$D$340:$IP$340,Stock!$D$4:$IP$4,B10,Stock!$D$5:$IP$5,C10),IF(COUNTIF(Stock!$D$5:$IP$5,C10)>0,SUMIF(Stock!$D$5:$IP$5,C10,Stock!$D$340:$IP$340),SUMIF(Stock!$D$4:$IP$4,B10,Stock!$D$340:$IP$340))),SUMIF(Stock!$D$4:$IP$4,B10,Stock!$D$340:$IP$340))) -> 80 | F10: =D10-E10 -> 15 | G10: =IF(AND(B10="",C10=""),"",IF(C10<>"",IF(COUNTIFS(Stock!$D$4:$IP$4,B10,Stock!$D$5:$IP$5,C10)>0,SUMIFS(Stock!$D$32:$IP$32,Stock!$D$4:$IP$4,B10,Stock!$D$5:$IP$5,C10),IF(COUNTIF(Stock!$D$5:$IP$5,C10)>0,SUMIF(Stock!$D$5:$IP$5,C10,Stock!$D$32:$IP$32),SUMIF(Stock!$D$4:$IP$4,B10,Stock!$D$32:$IP$32))),SUMIF(Stock!$D$4:$IP$4,B10,Stock!$D$32:$IP$32))) -> 80 | I10: Cielo | J10: PC-043R | K10: 25 | L10: =IF(AND(I10="",J10=""),"",IF(J10<>"",IF(COUNTIFS(Stock!$D$4:$IP$4,I10,Stock!$D$5:$IP$5,J10)>0,SUMIFS(Stock!$D$340:$IP$340,Stock!$D$4:$IP$4,I10,Stock!$D$5:$IP$5,J10),IF(COUNTIF(Stock!$D$5:$IP$5,J10)>0,SUMIF(Stock!$D$5:$IP$5,J10,Stock!$D$340:$IP$340),SUMIF(Stock!$D$4:$IP$4,I10,Stock!$D$340:$IP$340))),SUMIF(Stock!$D$4:$IP$4,I10,Stock!$D$340:$IP$340))) -> 25 | M10: =K10-L10 -> 0 | N10: =IF(AND(I10="",J10=""),"",IF(J10<>"",IF(COUNTIFS(Stock!$D$4:$IP$4,I10,Stock!$D$5:$IP$5,J10)>0,SUMIFS(Stock!$D$32:$IP$32,Stock!$D$4:$IP$4,I10,Stock!$D$5:$IP$5,J10),IF(COUNTIF(Stock!$D$5:$IP$5,J10)>0,SUMIF(Stock!$D$5:$IP$5,J10,Stock!$D$32:$IP$32),SUMIF(Stock!$D$4:$IP$4,I10,Stock!$D$32:$IP$32))),SUMIF(Stock!$D$4:$IP$4,I10,Stock!$D$32:$IP$32))) -> 25 | P10: 404 | Q10: 404;404BLOWER;BAZEL404;F404BAZEL;F404BAZELBLOWER;BAZELBLOWER404 | R10: 285 | S10: =IF(AND(P10="",Q10=""),"",IF(Q10<>"",IF(COUNTIFS(Stock!$D$4:$IP$4,P10,Stock!$D$5:$IP$5,Q10)>0,SUMIFS(Stock!$D$340:$IP$340,Stock!$D$4:$IP$4,P10,Stock!$D$5:$IP$5,Q10),IF(COUNTIF(Stock!$D$5:$IP$5,Q10)>0,SUMIF(Stock!$D$5:$IP$5,Q10,Stock!$D$340:$IP$340),SUMIF(Stock!$D$4:$IP$4,P10,Stock!$D$340:$IP$340))),SUMIF(Stock!$D$4:$IP$4,P10,Stock!$D$340:$IP$340))) -> 150 | T10: =R10-S10 -> 135 | U10: =IF(AND(P10="",Q10=""),"",IF(Q10<>"",IF(COUNTIFS(Stock!$D$4:$IP$4,P10,Stock!$D$5:$IP$5,Q10)>0,SUMIFS(Stock!$D$32:$IP$32,Stock!$D$4:$IP$4,P10,Stock!$D$5:$IP$5,Q10),IF(COUNTIF(Stock!$D$5:$IP$5,Q10)>0,SUMIF(Stock!$D$5:$IP$5,Q10,Stock!$D$32:$IP$32),SUMIF(Stock!$D$4:$IP$4,P10,Stock!$D$32:$IP$32))),SUMIF(Stock!$D$4:$IP$4,P10,Stock!$D$32:$IP$32))) -> 609
B11: Indigo | C11: PC-86237 | D11: 200 | E11: =IF(AND(B11="",C11=""),"",IF(C11<>"",IF(COUNTIFS(Stock!$D$4:$IP$4,B11,Stock!$D$5:$IP$5,C11)>0,SUMIFS(Stock!$D$340:$IP$340,Stock!$D$4:$IP$4,B11,Stock!$D$5:$IP$5,C11),IF(COUNTIF(Stock!$D$5:$IP$5,C11)>0,SUMIF(Stock!$D$5:$IP$5,C11,Stock!$D$340:$IP$340),SUMIF(Stock!$D$4:$IP$4,B11,Stock!$D$340:$IP$340))),SUMIF(Stock!$D$4:$IP$4,B11,Stock!$D$340:$IP$340))) -> 100 | F11: =D11-E11 -> 100 | G11: =IF(AND(B11="",C11=""),"",IF(C11<>"",IF(COUNTIFS(Stock!$D$4:$IP$4,B11,Stock!$D$5:$IP$5,C11)>0,SUMIFS(Stock!$D$32:$IP$32,Stock!$D$4:$IP$4,B11,Stock!$D$5:$IP$5,C11),IF(COUNTIF(Stock!$D$5:$IP$5,C11)>0,SUMIF(Stock!$D$5:$IP$5,C11,Stock!$D$32:$IP$32),SUMIF(Stock!$D$4:$IP$4,B11,Stock!$D$32:$IP$32))),SUMIF(Stock!$D$4:$IP$4,B11,Stock!$D$32:$IP$32))) -> 200 | I11: CIVIC | J11: PC-523 | L11: =IF(AND(I11="",J11=""),"",IF(J11<>"",IF(COUNTIFS(Stock!$D$4:$IP$4,I11,Stock!$D$5:$IP$5,J11)>0,SUMIFS(Stock!$D$340:$IP$340,Stock!$D$4:$IP$4,I11,Stock!$D$5:$IP$5,J11),IF(COUNTIF(Stock!$D$5:$IP$5,J11)>0,SUMIF(Stock!$D$5:$IP$5,J11,Stock!$D$340:$IP$340),SUMIF(Stock!$D$4:$IP$4,I11,Stock!$D$340:$IP$340))),SUMIF(Stock!$D$4:$IP$4,I11,Stock!$D$340:$IP$340))) -> 0 | M11: =K11-L11 -> 0 | N11: =IF(AND(I11="",J11=""),"",IF(J11<>"",IF(COUNTIFS(Stock!$D$4:$IP$4,I11,Stock!$D$5:$IP$5,J11)>0,SUMIFS(Stock!$D$32:$IP$32,Stock!$D$4:$IP$4,I11,Stock!$D$5:$IP$5,J11),IF(COUNTIF(Stock!$D$5:$IP$5,J11)>0,SUMIF(Stock!$D$5:$IP$5,J11,Stock!$D$32:$IP$32),SUMIF(Stock!$D$4:$IP$4,I11,Stock!$D$32:$IP$32))),SUMIF(Stock!$D$4:$IP$4,I11,Stock!$D$32:$IP$32))) -> 0 | P11: CONCORD WHEEL | Q11: CONCORDWHEEL | R11: 99 | S11: =IF(AND(P11="",Q11=""),"",IF(Q11<>"",IF(COUNTIFS(Stock!$D$4:$IP$4,P11,Stock!$D$5:$IP$5,Q11)>0,SUMIFS(Stock!$D$340:$IP$340,Stock!$D$4:$IP$4,P11,Stock!$D$5:$IP$5,Q11),IF(COUNTIF(Stock!$D$5:$IP$5,Q11)>0,SUMIF(Stock!$D$5:$IP$5,Q11,Stock!$D$340:$IP$340),SUMIF(Stock!$D$4:$IP$4,P11,Stock!$D$340:$IP$340))),SUMIF(Stock!$D$4:$IP$4,P11,Stock!$D$340:$IP$340))) -> 0 | T11: =R11-S11 -> 99 | U11: =IF(AND(P11="",Q11=""),"",IF(Q11<>"",IF(COUNTIFS(Stock!$D$4:$IP$4,P11,Stock!$D$5:$IP$5,Q11)>0,SUMIFS(Stock!$D$32:$IP$32,Stock!$D$4:$IP$4,P11,Stock!$D$5:$IP$5,Q11),IF(COUNTIF(Stock!$D$5:$IP$5,Q11)>0,SUMIF(Stock!$D$5:$IP$5,Q11,Stock!$D$32:$IP$32),SUMIF(Stock!$D$4:$IP$4,P11,Stock!$D$32:$IP$32))),SUMIF(Stock!$D$4:$IP$4,P11,Stock!$D$32:$IP$32))) -> 100
B12: SAFARI | C12: PC-86238 | D12: 100 | E12: =IF(AND(B12="",C12=""),"",IF(C12<>"",IF(COUNTIFS(Stock!$D$4:$IP$4,B12,Stock!$D$5:$IP$5,C12)>0,SUMIFS(Stock!$D$340:$IP$340,Stock!$D$4:$IP$4,B12,Stock!$D$5:$IP$5,C12),IF(COUNTIF(Stock!$D$5:$IP$5,C12)>0,SUMIF(Stock!$D$5:$IP$5,C12,Stock!$D$340:$IP$340),SUMIF(Stock!$D$4:$IP$4,B12,Stock!$D$340:$IP$340))),SUMIF(Stock!$D$4:$IP$4,B12,Stock!$D$340:$IP$340))) -> 100 | F12: =D12-E12 -> 0 | G12: =IF(AND(B12="",C12=""),"",IF(C12<>"",IF(COUNTIFS(Stock!$D$4:$IP$4,B12,Stock!$D$5:$IP$5,C12)>0,SUMIFS(Stock!$D$32:$IP$32,Stock!$D$4:$IP$4,B12,Stock!$D$5:$IP$5,C12),IF(COUNTIF(Stock!$D$5:$IP$5,C12)>0,SUMIF(Stock!$D$5:$IP$5,C12,Stock!$D$32:$IP$32),SUMIF(Stock!$D$4:$IP$4,B12,Stock!$D$32:$IP$32))),SUMIF(Stock!$D$4:$IP$4,B12,Stock!$D$32:$IP$32))) -> 100 | I12: CITY | L12: =IF(AND(I12="",J12=""),"",IF(J12<>"",IF(COUNTIFS(Stock!$D$4:$IP$4,I12,Stock!$D$5:$IP$5,J12)>0,SUMIFS(Stock!$D$340:$IP$340,Stock!$D$4:$IP$4,I12,Stock!$D$5:$IP$5,J12),IF(COUNTIF(Stock!$D$5:$IP$5,J12)>0,SUMIF(Stock!$D$5:$IP$5,J12,Stock!$D$340:$IP$340),SUMIF(Stock!$D$4:$IP$4,I12,Stock!$D$340:$IP$340))),SUMIF(Stock!$D$4:$IP$4,I12,Stock!$D$340:$IP$340))) -> 0 | M12: =K12-L12 -> 0 | N12: =IF(AND(I12="",J12=""),"",IF(J12<>"",IF(COUNTIFS(Stock!$D$4:$IP$4,I12,Stock!$D$5:$IP$5,J12)>0,SUMIFS(Stock!$D$32:$IP$32,Stock!$D$4:$IP$4,I12,Stock!$D$5:$IP$5,J12),IF(COUNTIF(Stock!$D$5:$IP$5,J12)>0,SUMIF(Stock!$D$5:$IP$5,J12,Stock!$D$32:$IP$32),SUMIF(Stock!$D$4:$IP$4,I12,Stock!$D$32:$IP$32))),SUMIF(Stock!$D$4:$IP$4,I12,Stock!$D$32:$IP$32))) -> 0 | P12: CONCORD MOTOR | Q12: CONCORDMOTOR | R12: 35 | S12: =IF(AND(P12="",Q12=""),"",IF(Q12<>"",IF(COUNTIFS(Stock!$D$4:$IP$4,P12,Stock!$D$5:$IP$5,Q12)>0,SUMIFS(Stock!$D$340:$IP$340,Stock!$D$4:$IP$4,P12,Stock!$D$5:$IP$5,Q12),IF(COUNTIF(Stock!$D$5:$IP$5,Q12)>0,SUMIF(Stock!$D$5:$IP$5,Q12,Stock!$D$340:$IP$340),SUMIF(Stock!$D$4:$IP$4,P12,Stock!$D$340:$IP$340))),SUMIF(Stock!$D$4:$IP$4,P12,Stock!$D$340:$IP$340))) -> 0 | T12: =R12-S12 -> 35 | U12: =IF(AND(P12="",Q12=""),"",IF(Q12<>"",IF(COUNTIFS(Stock!$D$4:$IP$4,P12,Stock!$D$5:$IP$5,Q12)>0,SUMIFS(Stock!$D$32:$IP$32,Stock!$D$4:$IP$4,P12,Stock!$D$5:$IP$5,Q12),IF(COUNTIF(Stock!$D$5:$IP$5,Q12)>0,SUMIF(Stock!$D$5:$IP$5,Q12,Stock!$D$32:$IP$32),SUMIF(Stock!$D$4:$IP$4,P12,Stock!$D$32:$IP$32))),SUMIF(Stock!$D$4:$IP$4,P12,Stock!$D$32:$IP$32))) -> 50
B13: Santro-ZING | C13: PC-86239 | D13: 185 | E13: =IF(AND(B13="",C13=""),"",IF(C13<>"",IF(COUNTIFS(Stock!$D$4:$IP$4,B13,Stock!$D$5:$IP$5,C13)>0,SUMIFS(Stock!$D$340:$IP$340,Stock!$D$4:$IP$4,B13,Stock!$D$5:$IP$5,C13),IF(COUNTIF(Stock!$D$5:$IP$5,C13)>0,SUMIF(Stock!$D$5:$IP$5,C13,Stock!$D$340:$IP$340),SUMIF(Stock!$D$4:$IP$4,B13,Stock!$D$340:$IP$340))),SUMIF(Stock!$D$4:$IP$4,B13,Stock!$D$340:$IP$340))) -> 200 | F13: =D13-E13 -> -15 | G13: =IF(AND(B13="",C13=""),"",IF(C13<>"",IF(COUNTIFS(Stock!$D$4:$IP$4,B13,Stock!$D$5:$IP$5,C13)>0,SUMIFS(Stock!$D$32:$IP$32,Stock!$D$4:$IP$4,B13,Stock!$D$5:$IP$5,C13),IF(COUNTIF(Stock!$D$5:$IP$5,C13)>0,SUMIF(Stock!$D$5:$IP$5,C13,Stock!$D$32:$IP$32),SUMIF(Stock!$D$4:$IP$4,B13,Stock!$D$32:$IP$32))),SUMIF(Stock!$D$4:$IP$4,B13,Stock!$D$32:$IP$32))) -> 200 | I13: Corrolla | J13: PC-114R | K13: 44 | L13: =IF(AND(I13="",J13=""),"",IF(J13<>"",IF(COUNTIFS(Stock!$D$4:$IP$4,I13,Stock!$D$5:$IP$5,J13)>0,SUMIFS(Stock!$D$340:$IP$340,Stock!$D$4:$IP$4,I13,Stock!$D$5:$IP$5,J13),IF(COUNTIF(Stock!$D$5:$IP$5,J13)>0,SUMIF(Stock!$D$5:$IP$5,J13,Stock!$D$340:$IP$340),SUMIF(Stock!$D$4:$IP$4,I13,Stock!$D$340:$IP$340))),SUMIF(Stock!$D$4:$IP$4,I13,Stock!$D$340:$IP$340))) -> 48 | M13: =K13-L13 -> -4 | N13: =IF(AND(I13="",J13=""),"",IF(J13<>"",IF(COUNTIFS(Stock!$D$4:$IP$4,I13,Stock!$D$5:$IP$5,J13)>0,SUMIFS(Stock!$D$32:$IP$32,Stock!$D$4:$IP$4,I13,Stock!$D$5:$IP$5,J13),IF(COUNTIF(Stock!$D$5:$IP$5,J13)>0,SUMIF(Stock!$D$5:$IP$5,J13,Stock!$D$32:$IP$32),SUMIF(Stock!$D$4:$IP$4,I13,Stock!$D$32:$IP$32))),SUMIF(Stock!$D$4:$IP$4,I13,Stock!$D$32:$IP$32))) -> 50 | P13: Switches | R13: Challan (pcs) <=283 | S13: =IF(AND(P13="",Q13=""),"",IF(Q13<>"",IF(COUNTIFS(Stock!$D$4:$IP$4,P13,Stock!$D$5:$IP$5,Q13)>0,SUMIFS(Stock!$D$340:$IP$340,Stock!$D$4:$IP$4,P13,Stock!$D$5:$IP$5,Q13),IF(COUNTIF(Stock!$D$5:$IP$5,Q13)>0,SUMIF(Stock!$D$5:$IP$5,Q13,Stock!$D$340:$IP$340),SUMIF(Stock!$D$4:$IP$4,P13,Stock!$D$340:$IP$340))),SUMIF(Stock!$D$4:$IP$4,P13,Stock!$D$340:$IP$340))) -> 0 | T13: Gap | U13: =IF(AND(P13="",Q13=""),"",IF(Q13<>"",IF(COUNTIFS(Stock!$D$4:$IP$4,P13,Stock!$D$5:$IP$5,Q13)>0,SUMIFS(Stock!$D$32:$IP$32,Stock!$D$4:$IP$4,P13,Stock!$D$5:$IP$5,Q13),IF(COUNTIF(Stock!$D$5:$IP$5,Q13)>0,SUMIF(Stock!$D$5:$IP$5,Q13,Stock!$D$32:$IP$32),SUMIF(Stock!$D$4:$IP$4,P13,Stock!$D$32:$IP$32))),SUMIF(Stock!$D$4:$IP$4,P13,Stock!$D$32:$IP$32))) -> 0 | V13: Match Key(s) | W13: Stock col idx | X13: Guard
B14: Maruti Car-800 MPFI | C14: PC-86092 | D14: 400 | E14: =IF(AND(B14="",C14=""),"",IF(C14<>"",IF(COUNTIFS(Stock!$D$4:$IP$4,B14,Stock!$D$5:$IP$5,C14)>0,SUMIFS(Stock!$D$340:$IP$340,Stock!$D$4:$IP$4,B14,Stock!$D$5:$IP$5,C14),IF(COUNTIF(Stock!$D$5:$IP$5,C14)>0,SUMIF(Stock!$D$5:$IP$5,C14,Stock!$D$340:$IP$340),SUMIF(Stock!$D$4:$IP$4,B14,Stock!$D$340:$IP$340))),SUMIF(Stock!$D$4:$IP$4,B14,Stock!$D$340:$IP$340))) -> 405 | F14: =D14-E14 -> -5 | G14: =IF(AND(B14="",C14=""),"",IF(C14<>"",IF(COUNTIFS(Stock!$D$4:$IP$4,B14,Stock!$D$5:$IP$5,C14)>0,SUMIFS(Stock!$D$32:$IP$32,Stock!$D$4:$IP$4,B14,Stock!$D$5:$IP$5,C14),IF(COUNTIF(Stock!$D$5:$IP$5,C14)>0,SUMIF(Stock!$D$5:$IP$5,C14,Stock!$D$32:$IP$32),SUMIF(Stock!$D$4:$IP$4,B14,Stock!$D$32:$IP$32))),SUMIF(Stock!$D$4:$IP$4,B14,Stock!$D$32:$IP$32))) -> 405 | I14: Esteem R-12 | J14: PC-036R12 | K14: 232 | L14: =IF(AND(I14="",J14=""),"",IF(J14<>"",IF(COUNTIFS(Stock!$D$4:$IP$4,I14,Stock!$D$5:$IP$5,J14)>0,SUMIFS(Stock!$D$340:$IP$340,Stock!$D$4:$IP$4,I14,Stock!$D$5:$IP$5,J14),IF(COUNTIF(Stock!$D$5:$IP$5,J14)>0,SUMIF(Stock!$D$5:$IP$5,J14,Stock!$D$340:$IP$340),SUMIF(Stock!$D$4:$IP$4,I14,Stock!$D$340:$IP$340))),SUMIF(Stock!$D$4:$IP$4,I14,Stock!$D$340:$IP$340))) -> 100 | M14: =K14-L14 -> 132 | N14: =IF(AND(I14="",J14=""),"",IF(J14<>"",IF(COUNTIFS(Stock!$D$4:$IP$4,I14,Stock!$D$5:$IP$5,J14)>0,SUMIFS(Stock!$D$32:$IP$32,Stock!$D$4:$IP$4,I14,Stock!$D$5:$IP$5,J14),IF(COUNTIF(Stock!$D$5:$IP$5,J14)>0,SUMIF(Stock!$D$5:$IP$5,J14,Stock!$D$32:$IP$32),SUMIF(Stock!$D$4:$IP$4,I14,Stock!$D$32:$IP$32))),SUMIF(Stock!$D$4:$IP$4,I14,Stock!$D$32:$IP$32))) -> 304 | P14: Santro-3 Speed | R14: 500 | S14: =IF(AND(P14="",Q14=""),"",IF(Q14<>"",IF(COUNTIFS(Stock!$D$4:$IP$4,P14,Stock!$D$5:$IP$5,Q14)>0,SUMIFS(Stock!$D$340:$IP$340,Stock!$D$4:$IP$4,P14,Stock!$D$5:$IP$5,Q14),IF(COUNTIF(Stock!$D$5:$IP$5,Q14)>0,SUMIF(Stock!$D$5:$IP$5,Q14,Stock!$D$340:$IP$340),SUMIF(Stock!$D$4:$IP$4,P14,Stock!$D$340:$IP$340))),SUMIF(Stock!$D$4:$IP$4,P14,Stock!$D$340:$IP$340))) -> 300 | T14: =R14-S14 -> 200 | U14: =IF(AND(P14="",Q14=""),"",IF(Q14<>"",IF(COUNTIFS(Stock!$D$4:$IP$4,P14,Stock!$D$5:$IP$5,Q14)>0,SUMIFS(Stock!$D$32:$IP$32,Stock!$D$4:$IP$4,P14,Stock!$D$5:$IP$5,Q14),IF(COUNTIF(Stock!$D$5:$IP$5,Q14)>0,SUMIF(Stock!$D$5:$IP$5,Q14,Stock!$D$32:$IP$32),SUMIF(Stock!$D$4:$IP$4,P14,Stock!$D$32:$IP$32))),SUMIF(Stock!$D$4:$IP$4,P14,Stock!$D$32:$IP$32))) -> 1799 | V14: 3SPEEDACSANTROSWITCH;SANTROACSWITCH | X14: {=IF(NOT(ISNUMBER($W14)),"CHECK",IF(OR(AND(TRIM($Q14&"")<>"",INDEX(Stock!$EW$5:$FU$5,$W14)=$Q14),INDEX(Stock!$EW$4:$FU$4,$W14)=$P14),"OK","CHECK"))} -> CHECK
B15: SANTRO | C15: PC-86125 | D15: 375 | E15: =IF(AND(B15="",C15=""),"",IF(C15<>"",IF(COUNTIFS(Stock!$D$4:$IP$4,B15,Stock!$D$5:$IP$5,C15)>0,SUMIFS(Stock!$D$340:$IP$340,Stock!$D$4:$IP$4,B15,Stock!$D$5:$IP$5,C15),IF(COUNTIF(Stock!$D$5:$IP$5,C15)>0,SUMIF(Stock!$D$5:$IP$5,C15,Stock!$D$340:$IP$340),SUMIF(Stock!$D$4:$IP$4,B15,Stock!$D$340:$IP$340))),SUMIF(Stock!$D$4:$IP$4,B15,Stock!$D$340:$IP$340))) -> 175 | F15: =D15-E15 -> 200 | G15: =IF(AND(B15="",C15=""),"",IF(C15<>"",IF(COUNTIFS(Stock!$D$4:$IP$4,B15,Stock!$D$5:$IP$5,C15)>0,SUMIFS(Stock!$D$32:$IP$32,Stock!$D$4:$IP$4,B15,Stock!$D$5:$IP$5,C15),IF(COUNTIF(Stock!$D$5:$IP$5,C15)>0,SUMIF(Stock!$D$5:$IP$5,C15,Stock!$D$32:$IP$32),SUMIF(Stock!$D$4:$IP$4,B15,Stock!$D$32:$IP$32))),SUMIF(Stock!$D$4:$IP$4,B15,Stock!$D$32:$IP$32))) -> 375 | I15: Esteem R-134a | J15: PC-036R-134 | K15: 131 | L15: =IF(AND(I15="",J15=""),"",IF(J15<>"",IF(COUNTIFS(Stock!$D$4:$IP$4,I15,Stock!$D$5:$IP$5,J15)>0,SUMIFS(Stock!$D$340:$IP$340,Stock!$D$4:$IP$4,I15,Stock!$D$5:$IP$5,J15),IF(COUNTIF(Stock!$D$5:$IP$5,J15)>0,SUMIF(Stock!$D$5:$IP$5,J15,Stock!$D$340:$IP$340),SUMIF(Stock!$D$4:$IP$4,I15,Stock!$D$340:$IP$340))),SUMIF(Stock!$D$4:$IP$4,I15,Stock!$D$340:$IP$340))) -> 104 | M15: =K15-L15 -> 27 | N15: =IF(AND(I15="",J15=""),"",IF(J15<>"",IF(COUNTIFS(Stock!$D$4:$IP$4,I15,Stock!$D$5:$IP$5,J15)>0,SUMIFS(Stock!$D$32:$IP$32,Stock!$D$4:$IP$4,I15,Stock!$D$5:$IP$5,J15),IF(COUNTIF(Stock!$D$5:$IP$5,J15)>0,SUMIF(Stock!$D$5:$IP$5,J15,Stock!$D$32:$IP$32),SUMIF(Stock!$D$4:$IP$4,I15,Stock!$D$32:$IP$32))),SUMIF(Stock!$D$4:$IP$4,I15,Stock!$D$32:$IP$32))) -> 206 | P15: Santro-4 Speed | R15: 500 | S15: =IF(AND(P15="",Q15=""),"",IF(Q15<>"",IF(COUNTIFS(Stock!$D$4:$IP$4,P15,Stock!$D$5:$IP$5,Q15)>0,SUMIFS(Stock!$D$340:$IP$340,Stock!$D$4:$IP$4,P15,Stock!$D$5:$IP$5,Q15),IF(COUNTIF(Stock!$D$5:$IP$5,Q15)>0,SUMIF(Stock!$D$5:$IP$5,Q15,Stock!$D$340:$IP$340),SUMIF(Stock!$D$4:$IP$4,P15,Stock!$D$340:$IP$340))),SUMIF(Stock!$D$4:$IP$4,P15,Stock!$D$340:$IP$340))) -> 400 | T15: =R15-S15 -> 100 | U15: =IF(AND(P15="",Q15=""),"",IF(Q15<>"",IF(COUNTIFS(Stock!$D$4:$IP$4,P15,Stock!$D$5:$IP$5,Q15)>0,SUMIFS(Stock!$D$32:$IP$32,Stock!$D$4:$IP$4,P15,Stock!$D$5:$IP$5,Q15),IF(COUNTIF(Stock!$D$5:$IP$5,Q15)>0,SUMIF(Stock!$D$5:$IP$5,Q15,Stock!$D$32:$IP$32),SUMIF(Stock!$D$4:$IP$4,P15,Stock!$D$32:$IP$32))),SUMIF(Stock!$D$4:$IP$4,P15,Stock!$D$32:$IP$32))) -> 2149 | V15: TOKAISANTROXINGACSWITCH;SANTROXINGACSWITCH;SANTROXING | X15: {=IF(NOT(ISNUMBER($W15)),"CHECK",IF(OR(AND(TRIM($Q15&"")<>"",INDEX(Stock!$EW$5:$FU$5,$W15)=$Q15),INDEX(Stock!$EW$4:$FU$4,$W15)=$P15),"OK","CHECK"))} -> CHECK
B16: Honda City-TYPE-3 | C16: PC-86240 | D16: 134 | E16: =IF(AND(B16="",C16=""),"",IF(C16<>"",IF(COUNTIFS(Stock!$D$4:$IP$4,B16,Stock!$D$5:$IP$5,C16)>0,SUMIFS(Stock!$D$340:$IP$340,Stock!$D$4:$IP$4,B16,Stock!$D$5:$IP$5,C16),IF(COUNTIF(Stock!$D$5:$IP$5,C16)>0,SUMIF(Stock!$D$5:$IP$5,C16,Stock!$D$340:$IP$340),SUMIF(Stock!$D$4:$IP$4,B16,Stock!$D$340:$IP$340))),SUMIF(Stock!$D$4:$IP$4,B16,Stock!$D$340:$IP$340))) -> 107 | F16: =D16-E16 -> 27 | G16: =IF(AND(B16="",C16=""),"",IF(C16<>"",IF(COUNTIFS(Stock!$D$4:$IP$4,B16,Stock!$D$5:$IP$5,C16)>0,SUMIFS(Stock!$D$32:$IP$32,Stock!$D$4:$IP$4,B16,Stock!$D$5:$IP$5,C16),IF(COUNTIF(Stock!$D$5:$IP$5,C16)>0,SUMIF(Stock!$D$5:$IP$5,C16,Stock!$D$32:$IP$32),SUMIF(Stock!$D$4:$IP$4,B16,Stock!$D$32:$IP$32))),SUMIF(Stock!$D$4:$IP$4,B16,Stock!$D$32:$IP$32))) -> 132 | I16: ESTILO | J16: PC-408 | K16: 1 | L16: =IF(AND(I16="",J16=""),"",IF(J16<>"",IF(COUNTIFS(Stock!$D$4:$IP$4,I16,Stock!$D$5:$IP$5,J16)>0,SUMIFS(Stock!$D$340:$IP$340,Stock!$D$4:$IP$4,I16,Stock!$D$5:$IP$5,J16),IF(COUNTIF(Stock!$D$5:$IP$5,J16)>0,SUMIF(Stock!$D$5:$IP$5,J16,Stock!$D$340:$IP$340),SUMIF(Stock!$D$4:$IP$4,I16,Stock!$D$340:$IP$340))),SUMIF(Stock!$D$4:$IP$4,I16,Stock!$D$340:$IP$340))) -> 0 | M16: =K16-L16 -> 1 | N16: =IF(AND(I16="",J16=""),"",IF(J16<>"",IF(COUNTIFS(Stock!$D$4:$IP$4,I16,Stock!$D$5:$IP$5,J16)>0,SUMIFS(Stock!$D$32:$IP$32,Stock!$D$4:$IP$4,I16,Stock!$D$5:$IP$5,J16),IF(COUNTIF(Stock!$D$5:$IP$5,J16)>0,SUMIF(Stock!$D$5:$IP$5,J16,Stock!$D$32:$IP$32),SUMIF(Stock!$D$4:$IP$4,I16,Stock!$D$32:$IP$32))),SUMIF(Stock!$D$4:$IP$4,I16,Stock!$D$32:$IP$32))) -> 0 | P16: Innova | R16: 664 | S16: =IF(AND(P16="",Q16=""),"",IF(Q16<>"",IF(COUNTIFS(Stock!$D$4:$IP$4,P16,Stock!$D$5:$IP$5,Q16)>0,SUMIFS(Stock!$D$340:$IP$340,Stock!$D$4:$IP$4,P16,Stock!$D$5:$IP$5,Q16),IF(COUNTIF(Stock!$D$5:$IP$5,Q16)>0,SUMIF(Stock!$D$5:$IP$5,Q16,Stock!$D$340:$IP$340),SUMIF(Stock!$D$4:$IP$4,P16,Stock!$D$340:$IP$340))),SUMIF(Stock!$D$4:$IP$4,P16,Stock!$D$340:$IP$340))) -> 741 | T16: =R16-S16 -> -77 | U16: =IF(AND(P16="",Q16=""),"",IF(Q16<>"",IF(COUNTIFS(Stock!$D$4:$IP$4,P16,Stock!$D$5:$IP$5,Q16)>0,SUMIFS(Stock!$D$32:$IP$32,Stock!$D$4:$IP$4,P16,Stock!$D$5:$IP$5,Q16),IF(COUNTIF(Stock!$D$5:$IP$5,Q16)>0,SUMIF(Stock!$D$5:$IP$5,Q16,Stock!$D$32:$IP$32),SUMIF(Stock!$D$4:$IP$4,P16,Stock!$D$32:$IP$32))),SUMIF(Stock!$D$4:$IP$4,P16,Stock!$D$32:$IP$32))) -> 1507 | V16: INNOVA;INNOVAACSWITCH;INNOVAACSWTICH;TOKAIINNOVAACSWITCH | X16: {=IF(NOT(ISNUMBER($W16)),"CHECK",IF(OR(AND(TRIM($Q16&"")<>"",INDEX(Stock!$EW$5:$FU$5,$W16)=$Q16),INDEX(Stock!$EW$4:$FU$4,$W16)=$P16),"OK","CHECK"))} -> CHECK
B17: Sumo VECTA | C17: PC-86241 | D17: 100 | E17: =IF(AND(B17="",C17=""),"",IF(C17<>"",IF(COUNTIFS(Stock!$D$4:$IP$4,B17,Stock!$D$5:$IP$5,C17)>0,SUMIFS(Stock!$D$340:$IP$340,Stock!$D$4:$IP$4,B17,Stock!$D$5:$IP$5,C17),IF(COUNTIF(Stock!$D$5:$IP$5,C17)>0,SUMIF(Stock!$D$5:$IP$5,C17,Stock!$D$340:$IP$340),SUMIF(Stock!$D$4:$IP$4,B17,Stock!$D$340:$IP$340))),SUMIF(Stock!$D$4:$IP$4,B17,Stock!$D$340:$IP$340))) -> 55 | F17: =D17-E17 -> 45 | G17: =IF(AND(B17="",C17=""),"",IF(C17<>"",IF(COUNTIFS(Stock!$D$4:$IP$4,B17,Stock!$D$5:$IP$5,C17)>0,SUMIFS(Stock!$D$32:$IP$32,Stock!$D$4:$IP$4,B17,Stock!$D$5:$IP$5,C17),IF(COUNTIF(Stock!$D$5:$IP$5,C17)>0,SUMIF(Stock!$D$5:$IP$5,C17,Stock!$D$32:$IP$32),SUMIF(Stock!$D$4:$IP$4,B17,Stock!$D$32:$IP$32))),SUMIF(Stock!$D$4:$IP$4,B17,Stock!$D$32:$IP$32))) -> 100 | I17: FORD IKON | J17: PC-053 | K17: 348 | L17: =IF(AND(I17="",J17=""),"",IF(J17<>"",IF(COUNTIFS(Stock!$D$4:$IP$4,I17,Stock!$D$5:$IP$5,J17)>0,SUMIFS(Stock!$D$340:$IP$340,Stock!$D$4:$IP$4,I17,Stock!$D$5:$IP$5,J17),IF(COUNTIF(Stock!$D$5:$IP$5,J17)>0,SUMIF(Stock!$D$5:$IP$5,J17,Stock!$D$340:$IP$340),SUMIF(Stock!$D$4:$IP$4,I17,Stock!$D$340:$IP$340))),SUMIF(Stock!$D$4:$IP$4,I17,Stock!$D$340:$IP$340))) -> 202 | M17: =K17-L17 -> 146 | N17: =IF(AND(I17="",J17=""),"",IF(J17<>"",IF(COUNTIFS(Stock!$D$4:$IP$4,I17,Stock!$D$5:$IP$5,J17)>0,SUMIFS(Stock!$D$32:$IP$32,Stock!$D$4:$IP$4,I17,Stock!$D$5:$IP$5,J17),IF(COUNTIF(Stock!$D$5:$IP$5,J17)>0,SUMIF(Stock!$D$5:$IP$5,J17,Stock!$D$32:$IP$32),SUMIF(Stock!$D$4:$IP$4,I17,Stock!$D$32:$IP$32))),SUMIF(Stock!$D$4:$IP$4,I17,Stock!$D$32:$IP$32))) -> 346 | P17: SANTRO | Q17: PC-1054B | R17: 100 | S17: =IF(AND(P17="",Q17=""),"",IF(Q17<>"",IF(COUNTIFS(Stock!$D$4:$IP$4,P17,Stock!$D$5:$IP$5,Q17)>0,SUMIFS(Stock!$D$340:$IP$340,Stock!$D$4:$IP$4,P17,Stock!$D$5:$IP$5,Q17),IF(COUNTIF(Stock!$D$5:$IP$5,Q17)>0,SUMIF(Stock!$D$5:$IP$5,Q17,Stock!$D$340:$IP$340),SUMIF(Stock!$D$4:$IP$4,P17,Stock!$D$340:$IP$340))),SUMIF(Stock!$D$4:$IP$4,P17,Stock!$D$340:$IP$340))) -> 100 | T17: =R17-S17 -> 0 | U17: =IF(AND(P17="",Q17=""),"",IF(Q17<>"",IF(COUNTIFS(Stock!$D$4:$IP$4,P17,Stock!$D$5:$IP$5,Q17)>0,SUMIFS(Stock!$D$32:$IP$32,Stock!$D$4:$IP$4,P17,Stock!$D$5:$IP$5,Q17),IF(COUNTIF(Stock!$D$5:$IP$5,Q17)>0,SUMIF(Stock!$D$5:$IP$5,Q17,Stock!$D$32:$IP$32),SUMIF(Stock!$D$4:$IP$4,P17,Stock!$D$32:$IP$32))),SUMIF(Stock!$D$4:$IP$4,P17,Stock!$D$32:$IP$32))) -> 848 | V17: PC1054B | X17: {=IF(NOT(ISNUMBER($W17)),"CHECK",IF(OR(AND(TRIM($Q17&"")<>"",INDEX(Stock!$EW$5:$FU$5,$W17)=$Q17),INDEX(Stock!$EW$4:$FU$4,$W17)=$P17),"OK","CHECK"))} -> CHECK
B18: BELANO | C18: PC-86242 | D18: 60 | E18: =IF(AND(B18="",C18=""),"",IF(C18<>"",IF(COUNTIFS(Stock!$D$4:$IP$4,B18,Stock!$D$5:$IP$5,C18)>0,SUMIFS(Stock!$D$340:$IP$340,Stock!$D$4:$IP$4,B18,Stock!$D$5:$IP$5,C18),IF(COUNTIF(Stock!$D$5:$IP$5,C18)>0,SUMIF(Stock!$D$5:$IP$5,C18,Stock!$D$340:$IP$340),SUMIF(Stock!$D$4:$IP$4,B18,Stock!$D$340:$IP$340))),SUMIF(Stock!$D$4:$IP$4,B18,Stock!$D$340:$IP$340))) -> 30 | F18: =D18-E18 -> 30 | G18: =IF(AND(B18="",C18=""),"",IF(C18<>"",IF(COUNTIFS(Stock!$D$4:$IP$4,B18,Stock!$D$5:$IP$5,C18)>0,SUMIFS(Stock!$D$32:$IP$32,Stock!$D$4:$IP$4,B18,Stock!$D$5:$IP$5,C18),IF(COUNTIF(Stock!$D$5:$IP$5,C18)>0,SUMIF(Stock!$D$5:$IP$5,C18,Stock!$D$32:$IP$32),SUMIF(Stock!$D$4:$IP$4,B18,Stock!$D$32:$IP$32))),SUMIF(Stock!$D$4:$IP$4,B18,Stock!$D$32:$IP$32))) -> 100 | I18: FIESTA | J18: PC-205 | K18: 92 | L18: =IF(AND(I18="",J18=""),"",IF(J18<>"",IF(COUNTIFS(Stock!$D$4:$IP$4,I18,Stock!$D$5:$IP$5,J18)>0,SUMIFS(Stock!$D$340:$IP$340,Stock!$D$4:$IP$4,I18,Stock!$D$5:$IP$5,J18),IF(COUNTIF(Stock!$D$5:$IP$5,J18)>0,SUMIF(Stock!$D$5:$IP$5,J18,Stock!$D$340:$IP$340),SUMIF(Stock!$D$4:$IP$4,I18,Stock!$D$340:$IP$340))),SUMIF(Stock!$D$4:$IP$4,I18,Stock!$D$340:$IP$340))) -> 104 | M18: =K18-L18 -> -12 | N18: =IF(AND(I18="",J18=""),"",IF(J18<>"",IF(COUNTIFS(Stock!$D$4:$IP$4,I18,Stock!$D$5:$IP$5,J18)>0,SUMIFS(Stock!$D$32:$IP$32,Stock!$D$4:$IP$4,I18,Stock!$D$5:$IP$5,J18),IF(COUNTIF(Stock!$D$5:$IP$5,J18)>0,SUMIF(Stock!$D$5:$IP$5,J18,Stock!$D$32:$IP$32),SUMIF(Stock!$D$4:$IP$4,I18,Stock!$D$32:$IP$32))),SUMIF(Stock!$D$4:$IP$4,I18,Stock!$D$32:$IP$32))) -> 104 | P18: OPEL-BIG | Q18: PC-1091 | S18: =IF(AND(P18="",Q18=""),"",IF(Q18<>"",IF(COUNTIFS(Stock!$D$4:$IP$4,P18,Stock!$D$5:$IP$5,Q18)>0,SUMIFS(Stock!$D$340:$IP$340,Stock!$D$4:$IP$4,P18,Stock!$D$5:$IP$5,Q18),IF(COUNTIF(Stock!$D$5:$IP$5,Q18)>0,SUMIF(Stock!$D$5:$IP$5,Q18,Stock!$D$340:$IP$340),SUMIF(Stock!$D$4:$IP$4,P18,Stock!$D$340:$IP$340))),SUMIF(Stock!$D$4:$IP$4,P18,Stock!$D$340:$IP$340))) -> 0 | T18: =R18-S18 -> 0 | U18: =IF(AND(P18="",Q18=""),"",IF(Q18<>"",IF(COUNTIFS(Stock!$D$4:$IP$4,P18,Stock!$D$5:$IP$5,Q18)>0,SUMIFS(Stock!$D$32:$IP$32,Stock!$D$4:$IP$4,P18,Stock!$D$5:$IP$5,Q18),IF(COUNTIF(Stock!$D$5:$IP$5,Q18)>0,SUMIF(Stock!$D$5:$IP$5,Q18,Stock!$D$32:$IP$32),SUMIF(Stock!$D$4:$IP$4,P18,Stock!$D$32:$IP$32))),SUMIF(Stock!$D$4:$IP$4,P18,Stock!$D$32:$IP$32))) -> 199 | V18: PC1091 | X18: {=IF(NOT(ISNUMBER($W18)),"CHECK",IF(OR(AND(TRIM($Q18&"")<>"",INDEX(Stock!$EW$5:$FU$5,$W18)=$Q18),INDEX(Stock!$EW$4:$FU$4,$W18)=$P18),"OK","CHECK"))} -> CHECK
B19: ESTEEM-R12 | C19: PC-86040 | D19: 110 | E19: =IF(AND(B19="",C19=""),"",IF(C19<>"",IF(COUNTIFS(Stock!$D$4:$IP$4,B19,Stock!$D$5:$IP$5,C19)>0,SUMIFS(Stock!$D$340:$IP$340,Stock!$D$4:$IP$4,B19,Stock!$D$5:$IP$5,C19),IF(COUNTIF(Stock!$D$5:$IP$5,C19)>0,SUMIF(Stock!$D$5:$IP$5,C19,Stock!$D$340:$IP$340),SUMIF(Stock!$D$4:$IP$4,B19,Stock!$D$340:$IP$340))),SUMIF(Stock!$D$4:$IP$4,B19,Stock!$D$340:$IP$340))) -> 0 | F19: =D19-E19 -> 110 | G19: =IF(AND(B19="",C19=""),"",IF(C19<>"",IF(COUNTIFS(Stock!$D$4:$IP$4,B19,Stock!$D$5:$IP$5,C19)>0,SUMIFS(Stock!$D$32:$IP$32,Stock!$D$4:$IP$4,B19,Stock!$D$5:$IP$5,C19),IF(COUNTIF(Stock!$D$5:$IP$5,C19)>0,SUMIF(Stock!$D$5:$IP$5,C19,Stock!$D$32:$IP$32),SUMIF(Stock!$D$4:$IP$4,B19,Stock!$D$32:$IP$32))),SUMIF(Stock!$D$4:$IP$4,B19,Stock!$D$32:$IP$32))) -> 200 | I19: Getz | J19: PC-024R (origin PC-207) | K19: 45 | L19: =IF(AND(I19="",J19=""),"",IF(J19<>"",IF(COUNTIFS(Stock!$D$4:$IP$4,I19,Stock!$D$5:$IP$5,J19)>0,SUMIFS(Stock!$D$340:$IP$340,Stock!$D$4:$IP$4,I19,Stock!$D$5:$IP$5,J19),IF(COUNTIF(Stock!$D$5:$IP$5,J19)>0,SUMIF(Stock!$D$5:$IP$5,J19,Stock!$D$340:$IP$340),SUMIF(Stock!$D$4:$IP$4,I19,Stock!$D$340:$IP$340))),SUMIF(Stock!$D$4:$IP$4,I19,Stock!$D$340:$IP$340))) -> 75 | M19: =K19-L19 -> -30 | N19: =IF(AND(I19="",J19=""),"",IF(J19<>"",IF(COUNTIFS(Stock!$D$4:$IP$4,I19,Stock!$D$5:$IP$5,J19)>0,SUMIFS(Stock!$D$32:$IP$32,Stock!$D$4:$IP$4,I19,Stock!$D$5:$IP$5,J19),IF(COUNTIF(Stock!$D$5:$IP$5,J19)>0,SUMIF(Stock!$D$5:$IP$5,J19,Stock!$D$32:$IP$32),SUMIF(Stock!$D$4:$IP$4,I19,Stock!$D$32:$IP$32))),SUMIF(Stock!$D$4:$IP$4,I19,Stock!$D$32:$IP$32))) -> 75 | P19: ESTEEM-R12 / Accent | Q19: PC-1046 | R19: 500 | S19: =IF(AND(P19="",Q19=""),"",IF(Q19<>"",IF(COUNTIFS(Stock!$D$4:$IP$4,P19,Stock!$D$5:$IP$5,Q19)>0,SUMIFS(Stock!$D$340:$IP$340,Stock!$D$4:$IP$4,P19,Stock!$D$5:$IP$5,Q19),IF(COUNTIF(Stock!$D$5:$IP$5,Q19)>0,SUMIF(Stock!$D$5:$IP$5,Q19,Stock!$D$340:$IP$340),SUMIF(Stock!$D$4:$IP$4,P19,Stock!$D$340:$IP$340))),SUMIF(Stock!$D$4:$IP$4,P19,Stock!$D$340:$IP$340))) -> 500 | T19: =R19-S19 -> 0 | U19: =IF(AND(P19="",Q19=""),"",IF(Q19<>"",IF(COUNTIFS(Stock!$D$4:$IP$4,P19,Stock!$D$5:$IP$5,Q19)>0,SUMIFS(Stock!$D$32:$IP$32,Stock!$D$4:$IP$4,P19,Stock!$D$5:$IP$5,Q19),IF(COUNTIF(Stock!$D$5:$IP$5,Q19)>0,SUMIF(Stock!$D$5:$IP$5,Q19,Stock!$D$32:$IP$32),SUMIF(Stock!$D$4:$IP$4,P19,Stock!$D$32:$IP$32))),SUMIF(Stock!$D$4:$IP$4,P19,Stock!$D$32:$IP$32))) -> 750 | V19: PC1046 | X19: {=IF(NOT(ISNUMBER($W19)),"CHECK",IF(OR(AND(TRIM($Q19&"")<>"",INDEX(Stock!$EW$5:$FU$5,$W19)=$Q19),INDEX(Stock!$EW$4:$FU$4,$W19)=$P19),"OK","CHECK"))} -> CHECK
B20: Esteem-134a | C20: PC-86090 | D20: 221 | E20: =IF(AND(B20="",C20=""),"",IF(C20<>"",IF(COUNTIFS(Stock!$D$4:$IP$4,B20,Stock!$D$5:$IP$5,C20)>0,SUMIFS(Stock!$D$340:$IP$340,Stock!$D$4:$IP$4,B20,Stock!$D$5:$IP$5,C20),IF(COUNTIF(Stock!$D$5:$IP$5,C20)>0,SUMIF(Stock!$D$5:$IP$5,C20,Stock!$D$340:$IP$340),SUMIF(Stock!$D$4:$IP$4,B20,Stock!$D$340:$IP$340))),SUMIF(Stock!$D$4:$IP$4,B20,Stock!$D$340:$IP$340))) -> 171 | F20: =D20-E20 -> 50 | G20: =IF(AND(B20="",C20=""),"",IF(C20<>"",IF(COUNTIFS(Stock!$D$4:$IP$4,B20,Stock!$D$5:$IP$5,C20)>0,SUMIFS(Stock!$D$32:$IP$32,Stock!$D$4:$IP$4,B20,Stock!$D$5:$IP$5,C20),IF(COUNTIF(Stock!$D$5:$IP$5,C20)>0,SUMIF(Stock!$D$5:$IP$5,C20,Stock!$D$32:$IP$32),SUMIF(Stock!$D$4:$IP$4,B20,Stock!$D$32:$IP$32))),SUMIF(Stock!$D$4:$IP$4,B20,Stock!$D$32:$IP$32))) -> 221 | I20: ELANTRA | J20: PC-135R | K20: 66 | L20: =IF(AND(I20="",J20=""),"",IF(J20<>"",IF(COUNTIFS(Stock!$D$4:$IP$4,I20,Stock!$D$5:$IP$5,J20)>0,SUMIFS(Stock!$D$340:$IP$340,Stock!$D$4:$IP$4,I20,Stock!$D$5:$IP$5,J20),IF(COUNTIF(Stock!$D$5:$IP$5,J20)>0,SUMIF(Stock!$D$5:$IP$5,J20,Stock!$D$340:$IP$340),SUMIF(Stock!$D$4:$IP$4,I20,Stock!$D$340:$IP$340))),SUMIF(Stock!$D$4:$IP$4,I20,Stock!$D$340:$IP$340))) -> 42 | M20: =K20-L20 -> 24 | N20: =IF(AND(I20="",J20=""),"",IF(J20<>"",IF(COUNTIFS(Stock!$D$4:$IP$4,I20,Stock!$D$5:$IP$5,J20)>0,SUMIFS(Stock!$D$32:$IP$32,Stock!$D$4:$IP$4,I20,Stock!$D$5:$IP$5,J20),IF(COUNTIF(Stock!$D$5:$IP$5,J20)>0,SUMIF(Stock!$D$5:$IP$5,J20,Stock!$D$32:$IP$32),SUMIF(Stock!$D$4:$IP$4,I20,Stock!$D$32:$IP$32))),SUMIF(Stock!$D$4:$IP$4,I20,Stock!$D$32:$IP$32))) -> 80 | P20: SONATA | Q20: PC-2126 | R20: 49 | S20: =IF(AND(P20="",Q20=""),"",IF(Q20<>"",IF(COUNTIFS(Stock!$D$4:$IP$4,P20,Stock!$D$5:$IP$5,Q20)>0,SUMIFS(Stock!$D$340:$IP$340,Stock!$D$4:$IP$4,P20,Stock!$D$5:$IP$5,Q20),IF(COUNTIF(Stock!$D$5:$IP$5,Q20)>0,SUMIF(Stock!$D$5:$IP$5,Q20,Stock!$D$340:$IP$340),SUMIF(Stock!$D$4:$IP$4,P20,Stock!$D$340:$IP$340))),SUMIF(Stock!$D$4:$IP$4,P20,Stock!$D$340:$IP$340))) -> 100 | T20: =R20-S20 -> -51 | U20: =IF(AND(P20="",Q20=""),"",IF(Q20<>"",IF(COUNTIFS(Stock!$D$4:$IP$4,P20,Stock!$D$5:$IP$5,Q20)>0,SUMIFS(Stock!$D$32:$IP$32,Stock!$D$4:$IP$4,P20,Stock!$D$5:$IP$5,Q20),IF(COUNTIF(Stock!$D$5:$IP$5,Q20)>0,SUMIF(Stock!$D$5:$IP$5,Q20,Stock!$D$32:$IP$32),SUMIF(Stock!$D$4:$IP$4,P20,Stock!$D$32:$IP$32))),SUMIF(Stock!$D$4:$IP$4,P20,Stock!$D$32:$IP$32))) -> 200 | V20: PC2126 | X20: {=IF(NOT(ISNUMBER($W20)),"CHECK",IF(OR(AND(TRIM($Q20&"")<>"",INDEX(Stock!$EW$5:$FU$5,$W20)=$Q20),INDEX(Stock!$EW$4:$FU$4,$W20)=$P20),"OK","CHECK"))} -> CHECK
B21: ACCENT CRD-I | C21: PC-86064B | D21: 100 | E21: =IF(AND(B21="",C21=""),"",IF(C21<>"",IF(COUNTIFS(Stock!$D$4:$IP$4,B21,Stock!$D$5:$IP$5,C21)>0,SUMIFS(Stock!$D$340:$IP$340,Stock!$D$4:$IP$4,B21,Stock!$D$5:$IP$5,C21),IF(COUNTIF(Stock!$D$5:$IP$5,C21)>0,SUMIF(Stock!$D$5:$IP$5,C21,Stock!$D$340:$IP$340),SUMIF(Stock!$D$4:$IP$4,B21,Stock!$D$340:$IP$340))),SUMIF(Stock!$D$4:$IP$4,B21,Stock!$D$340:$IP$340))) -> 75 | F21: =D21-E21 -> 25 | G21: =IF(AND(B21="",C21=""),"",IF(C21<>"",IF(COUNTIFS(Stock!$D$4:$IP$4,B21,Stock!$D$5:$IP$5,C21)>0,SUMIFS(Stock!$D$32:$IP$32,Stock!$D$4:$IP$4,B21,Stock!$D$5:$IP$5,C21),IF(COUNTIF(Stock!$D$5:$IP$5,C21)>0,SUMIF(Stock!$D$5:$IP$5,C21,Stock!$D$32:$IP$32),SUMIF(Stock!$D$4:$IP$4,B21,Stock!$D$32:$IP$32))),SUMIF(Stock!$D$4:$IP$4,B21,Stock!$D$32:$IP$32))) -> 100 | I21: SENTRO | J21: PC-144R | K21: 104 | L21: =IF(AND(I21="",J21=""),"",IF(J21<>"",IF(COUNTIFS(Stock!$D$4:$IP$4,I21,Stock!$D$5:$IP$5,J21)>0,SUMIFS(Stock!$D$340:$IP$340,Stock!$D$4:$IP$4,I21,Stock!$D$5:$IP$5,J21),IF(COUNTIF(Stock!$D$5:$IP$5,J21)>0,SUMIF(Stock!$D$5:$IP$5,J21,Stock!$D$340:$IP$340),SUMIF(Stock!$D$4:$IP$4,I21,Stock!$D$340:$IP$340))),SUMIF(Stock!$D$4:$IP$4,I21,Stock!$D$340:$IP$340))) -> 110 | M21: =K21-L21 -> -6 | N21: =IF(AND(I21="",J21=""),"",IF(J21<>"",IF(COUNTIFS(Stock!$D$4:$IP$4,I21,Stock!$D$5:$IP$5,J21)>0,SUMIFS(Stock!$D$32:$IP$32,Stock!$D$4:$IP$4,I21,Stock!$D$5:$IP$5,J21),IF(COUNTIF(Stock!$D$5:$IP$5,J21)>0,SUMIF(Stock!$D$5:$IP$5,J21,Stock!$D$32:$IP$32),SUMIF(Stock!$D$4:$IP$4,I21,Stock!$D$32:$IP$32))),SUMIF(Stock!$D$4:$IP$4,I21,Stock!$D$32:$IP$32))) -> 110 | P21: ESTEEM-R134/Lancer | Q21: PC-1042A | S21: =IF(AND(P21="",Q21=""),"",IF(Q21<>"",IF(COUNTIFS(Stock!$D$4:$IP$4,P21,Stock!$D$5:$IP$5,Q21)>0,SUMIFS(Stock!$D$340:$IP$340,Stock!$D$4:$IP$4,P21,Stock!$D$5:$IP$5,Q21),IF(COUNTIF(Stock!$D$5:$IP$5,Q21)>0,SUMIF(Stock!$D$5:$IP$5,Q21,Stock!$D$340:$IP$340),SUMIF(Stock!$D$4:$IP$4,P21,Stock!$D$340:$IP$340))),SUMIF(Stock!$D$4:$IP$4,P21,Stock!$D$340:$IP$340))) -> 0 | T21: =R21-S21 -> 0 | U21: =IF(AND(P21="",Q21=""),"",IF(Q21<>"",IF(COUNTIFS(Stock!$D$4:$IP$4,P21,Stock!$D$5:$IP$5,Q21)>0,SUMIFS(Stock!$D$32:$IP$32,Stock!$D$4:$IP$4,P21,Stock!$D$5:$IP$5,Q21),IF(COUNTIF(Stock!$D$5:$IP$5,Q21)>0,SUMIF(Stock!$D$5:$IP$5,Q21,Stock!$D$32:$IP$32),SUMIF(Stock!$D$4:$IP$4,P21,Stock!$D$32:$IP$32))),SUMIF(Stock!$D$4:$IP$4,P21,Stock!$D$32:$IP$32))) -> 200 | V21: PC1042A | X21: {=IF(NOT(ISNUMBER($W21)),"CHECK",IF(OR(AND(TRIM($Q21&"")<>"",INDEX(Stock!$EW$5:$FU$5,$W21)=$Q21),INDEX(Stock!$EW$4:$FU$4,$W21)=$P21),"OK","CHECK"))} -> CHECK
B22: OPEL-ASTRA | C22: PC-86243 | D22: 5 | E22: =IF(AND(B22="",C22=""),"",IF(C22<>"",IF(COUNTIFS(Stock!$D$4:$IP$4,B22,Stock!$D$5:$IP$5,C22)>0,SUMIFS(Stock!$D$340:$IP$340,Stock!$D$4:$IP$4,B22,Stock!$D$5:$IP$5,C22),IF(COUNTIF(Stock!$D$5:$IP$5,C22)>0,SUMIF(Stock!$D$5:$IP$5,C22,Stock!$D$340:$IP$340),SUMIF(Stock!$D$4:$IP$4,B22,Stock!$D$340:$IP$340))),SUMIF(Stock!$D$4:$IP$4,B22,Stock!$D$340:$IP$340))) -> 5 | F22: =D22-E22 -> 0 | G22: =IF(AND(B22="",C22=""),"",IF(C22<>"",IF(COUNTIFS(Stock!$D$4:$IP$4,B22,Stock!$D$5:$IP$5,C22)>0,SUMIFS(Stock!$D$32:$IP$32,Stock!$D$4:$IP$4,B22,Stock!$D$5:$IP$5,C22),IF(COUNTIF(Stock!$D$5:$IP$5,C22)>0,SUMIF(Stock!$D$5:$IP$5,C22,Stock!$D$32:$IP$32),SUMIF(Stock!$D$4:$IP$4,B22,Stock!$D$32:$IP$32))),SUMIF(Stock!$D$4:$IP$4,B22,Stock!$D$32:$IP$32))) -> 10 | I22: Indigo | J22: PC-7157 | K22: 322 | L22: =IF(AND(I22="",J22=""),"",IF(J22<>"",IF(COUNTIFS(Stock!$D$4:$IP$4,I22,Stock!$D$5:$IP$5,J22)>0,SUMIFS(Stock!$D$340:$IP$340,Stock!$D$4:$IP$4,I22,Stock!$D$5:$IP$5,J22),IF(COUNTIF(Stock!$D$5:$IP$5,J22)>0,SUMIF(Stock!$D$5:$IP$5,J22,Stock!$D$340:$IP$340),SUMIF(Stock!$D$4:$IP$4,I22,Stock!$D$340:$IP$340))),SUMIF(Stock!$D$4:$IP$4,I22,Stock!$D$340:$IP$340))) -> 150 | M22: =K22-L22 -> 172 | N22: =IF(AND(I22="",J22=""),"",IF(J22<>"",IF(COUNTIFS(Stock!$D$4:$IP$4,I22,Stock!$D$5:$IP$5,J22)>0,SUMIFS(Stock!$D$32:$IP$32,Stock!$D$4:$IP$4,I22,Stock!$D$5:$IP$5,J22),IF(COUNTIF(Stock!$D$5:$IP$5,J22)>0,SUMIF(Stock!$D$5:$IP$5,J22,Stock!$D$32:$IP$32),SUMIF(Stock!$D$4:$IP$4,I22,Stock!$D$32:$IP$32))),SUMIF(Stock!$D$4:$IP$4,I22,Stock!$D$32:$IP$32))) -> 300 | P22: OPEL-SMALL-2pin | Q22: PC-1087 | S22: =IF(AND(P22="",Q22=""),"",IF(Q22<>"",IF(COUNTIFS(Stock!$D$4:$IP$4,P22,Stock!$D$5:$IP$5,Q22)>0,SUMIFS(Stock!$D$340:$IP$340,Stock!$D$4:$IP$4,P22,Stock!$D$5:$IP$5,Q22),IF(COUNTIF(Stock!$D$5:$IP$5,Q22)>0,SUMIF(Stock!$D$5:$IP$5,Q22,Stock!$D$340:$IP$340),SUMIF(Stock!$D$4:$IP$4,P22,Stock!$D$340:$IP$340))),SUMIF(Stock!$D$4:$IP$4,P22,Stock!$D$340:$IP$340))) -> 0 | T22: =R22-S22 -> 0 | U22: =IF(AND(P22="",Q22=""),"",IF(Q22<>"",IF(COUNTIFS(Stock!$D$4:$IP$4,P22,Stock!$D$5:$IP$5,Q22)>0,SUMIFS(Stock!$D$32:$IP$32,Stock!$D$4:$IP$4,P22,Stock!$D$5:$IP$5,Q22),IF(COUNTIF(Stock!$D$5:$IP$5,Q22)>0,SUMIF(Stock!$D$5:$IP$5,Q22,Stock!$D$32:$IP$32),SUMIF(Stock!$D$4:$IP$4,P22,Stock!$D$32:$IP$32))),SUMIF(Stock!$D$4:$IP$4,P22,Stock!$D$32:$IP$32))) -> 224 | V22: PC1087 | X22: {=IF(NOT(ISNUMBER($W22)),"CHECK",IF(OR(AND(TRIM($Q22&"")<>"",INDEX(Stock!$EW$5:$FU$5,$W22)=$Q22),INDEX(Stock!$EW$4:$FU$4,$W22)=$P22),"OK","CHECK"))} -> CHECK
B23: ZEN-R134A | C23: PC-86245 | D23: 330 | E23: =IF(AND(B23="",C23=""),"",IF(C23<>"",IF(COUNTIFS(Stock!$D$4:$IP$4,B23,Stock!$D$5:$IP$5,C23)>0,SUMIFS(Stock!$D$340:$IP$340,Stock!$D$4:$IP$4,B23,Stock!$D$5:$IP$5,C23),IF(COUNTIF(Stock!$D$5:$IP$5,C23)>0,SUMIF(Stock!$D$5:$IP$5,C23,Stock!$D$340:$IP$340),SUMIF(Stock!$D$4:$IP$4,B23,Stock!$D$340:$IP$340))),SUMIF(Stock!$D$4:$IP$4,B23,Stock!$D$340:$IP$340))) -> 230 | F23: =D23-E23 -> 100 | G23: =IF(AND(B23="",C23=""),"",IF(C23<>"",IF(COUNTIFS(Stock!$D$4:$IP$4,B23,Stock!$D$5:$IP$5,C23)>0,SUMIFS(Stock!$D$32:$IP$32,Stock!$D$4:$IP$4,B23,Stock!$D$5:$IP$5,C23),IF(COUNTIF(Stock!$D$5:$IP$5,C23)>0,SUMIF(Stock!$D$5:$IP$5,C23,Stock!$D$32:$IP$32),SUMIF(Stock!$D$4:$IP$4,B23,Stock!$D$32:$IP$32))),SUMIF(Stock!$D$4:$IP$4,B23,Stock!$D$32:$IP$32))) -> 330 | I23: Innova | J23: PC-209 | K23: 100 | L23: =IF(AND(I23="",J23=""),"",IF(J23<>"",IF(COUNTIFS(Stock!$D$4:$IP$4,I23,Stock!$D$5:$IP$5,J23)>0,SUMIFS(Stock!$D$340:$IP$340,Stock!$D$4:$IP$4,I23,Stock!$D$5:$IP$5,J23),IF(COUNTIF(Stock!$D$5:$IP$5,J23)>0,SUMIF(Stock!$D$5:$IP$5,J23,Stock!$D$340:$IP$340),SUMIF(Stock!$D$4:$IP$4,I23,Stock!$D$340:$IP$340))),SUMIF(Stock!$D$4:$IP$4,I23,Stock!$D$340:$IP$340))) -> 100 | M23: =K23-L23 -> 0 | N23: =IF(AND(I23="",J23=""),"",IF(J23<>"",IF(COUNTIFS(Stock!$D$4:$IP$4,I23,Stock!$D$5:$IP$5,J23)>0,SUMIFS(Stock!$D$32:$IP$32,Stock!$D$4:$IP$4,I23,Stock!$D$5:$IP$5,J23),IF(COUNTIF(Stock!$D$5:$IP$5,J23)>0,SUMIF(Stock!$D$5:$IP$5,J23,Stock!$D$32:$IP$32),SUMIF(Stock!$D$4:$IP$4,I23,Stock!$D$32:$IP$32))),SUMIF(Stock!$D$4:$IP$4,I23,Stock!$D$32:$IP$32))) -> 100 | P23: HONDA CITY | Q23: PC-1045B | R23: 200 | S23: =IF(AND(P23="",Q23=""),"",IF(Q23<>"",IF(COUNTIFS(Stock!$D$4:$IP$4,P23,Stock!$D$5:$IP$5,Q23)>0,SUMIFS(Stock!$D$340:$IP$340,Stock!$D$4:$IP$4,P23,Stock!$D$5:$IP$5,Q23),IF(COUNTIF(Stock!$D$5:$IP$5,Q23)>0,SUMIF(Stock!$D$5:$IP$5,Q23,Stock!$D$340:$IP$340),SUMIF(Stock!$D$4:$IP$4,P23,Stock!$D$340:$IP$340))),SUMIF(Stock!$D$4:$IP$4,P23,Stock!$D$340:$IP$340))) -> 300 | T23: =R23-S23 -> -100 | U23: =IF(AND(P23="",Q23=""),"",IF(Q23<>"",IF(COUNTIFS(Stock!$D$4:$IP$4,P23,Stock!$D$5:$IP$5,Q23)>0,SUMIFS(Stock!$D$32:$IP$32,Stock!$D$4:$IP$4,P23,Stock!$D$5:$IP$5,Q23),IF(COUNTIF(Stock!$D$5:$IP$5,Q23)>0,SUMIF(Stock!$D$5:$IP$5,Q23,Stock!$D$32:$IP$32),SUMIF(Stock!$D$4:$IP$4,P23,Stock!$D$32:$IP$32))),SUMIF(Stock!$D$4:$IP$4,P23,Stock!$D$32:$IP$32))) -> 400 | V23: PC1045B | X23: {=IF(NOT(ISNUMBER($W23)),"CHECK",IF(OR(AND(TRIM($Q23&"")<>"",INDEX(Stock!$EW$5:$FU$5,$W23)=$Q23),INDEX(Stock!$EW$4:$FU$4,$W23)=$P23),"OK","CHECK"))} -> CHECK
B24: ZEN-R12 | C24: PC-86043 | D24: 400 | E24: =IF(AND(B24="",C24=""),"",IF(C24<>"",IF(COUNTIFS(Stock!$D$4:$IP$4,B24,Stock!$D$5:$IP$5,C24)>0,SUMIFS(Stock!$D$340:$IP$340,Stock!$D$4:$IP$4,B24,Stock!$D$5:$IP$5,C24),IF(COUNTIF(Stock!$D$5:$IP$5,C24)>0,SUMIF(Stock!$D$5:$IP$5,C24,Stock!$D$340:$IP$340),SUMIF(Stock!$D$4:$IP$4,B24,Stock!$D$340:$IP$340))),SUMIF(Stock!$D$4:$IP$4,B24,Stock!$D$340:$IP$340))) -> 0 | F24: =D24-E24 -> 400 | G24: =IF(AND(B24="",C24=""),"",IF(C24<>"",IF(COUNTIFS(Stock!$D$4:$IP$4,B24,Stock!$D$5:$IP$5,C24)>0,SUMIFS(Stock!$D$32:$IP$32,Stock!$D$4:$IP$4,B24,Stock!$D$5:$IP$5,C24),IF(COUNTIF(Stock!$D$5:$IP$5,C24)>0,SUMIF(Stock!$D$5:$IP$5,C24,Stock!$D$32:$IP$32),SUMIF(Stock!$D$4:$IP$4,B24,Stock!$D$32:$IP$32))),SUMIF(Stock!$D$4:$IP$4,B24,Stock!$D$32:$IP$32))) -> 400 | I24: Lancer HCC | J24: PC-206 | K24: 71 | L24: =IF(AND(I24="",J24=""),"",IF(J24<>"",IF(COUNTIFS(Stock!$D$4:$IP$4,I24,Stock!$D$5:$IP$5,J24)>0,SUMIFS(Stock!$D$340:$IP$340,Stock!$D$4:$IP$4,I24,Stock!$D$5:$IP$5,J24),IF(COUNTIF(Stock!$D$5:$IP$5,J24)>0,SUMIF(Stock!$D$5:$IP$5,J24,Stock!$D$340:$IP$340),SUMIF(Stock!$D$4:$IP$4,I24,Stock!$D$340:$IP$340))),SUMIF(Stock!$D$4:$IP$4,I24,Stock!$D$340:$IP$340))) -> 77 | M24: =K24-L24 -> -6 | N24: =IF(AND(I24="",J24=""),"",IF(J24<>"",IF(COUNTIFS(Stock!$D$4:$IP$4,I24,Stock!$D$5:$IP$5,J24)>0,SUMIFS(Stock!$D$32:$IP$32,Stock!$D$4:$IP$4,I24,Stock!$D$5:$IP$5,J24),IF(COUNTIF(Stock!$D$5:$IP$5,J24)>0,SUMIF(Stock!$D$5:$IP$5,J24,Stock!$D$32:$IP$32),SUMIF(Stock!$D$4:$IP$4,I24,Stock!$D$32:$IP$32))),SUMIF(Stock!$D$4:$IP$4,I24,Stock!$D$32:$IP$32))) -> 76 | P24: SWIFT | Q24: PC-1525 | R24: 154 | S24: =IF(AND(P24="",Q24=""),"",IF(Q24<>"",IF(COUNTIFS(Stock!$D$4:$IP$4,P24,Stock!$D$5:$IP$5,Q24)>0,SUMIFS(Stock!$D$340:$IP$340,Stock!$D$4:$IP$4,P24,Stock!$D$5:$IP$5,Q24),IF(COUNTIF(Stock!$D$5:$IP$5,Q24)>0,SUMIF(Stock!$D$5:$IP$5,Q24,Stock!$D$340:$IP$340),SUMIF(Stock!$D$4:$IP$4,P24,Stock!$D$340:$IP$340))),SUMIF(Stock!$D$4:$IP$4,P24,Stock!$D$340:$IP$340))) -> 0 | T24: =R24-S24 -> 154 | U24: =IF(AND(P24="",Q24=""),"",IF(Q24<>"",IF(COUNTIFS(Stock!$D$4:$IP$4,P24,Stock!$D$5:$IP$5,Q24)>0,SUMIFS(Stock!$D$32:$IP$32,Stock!$D$4:$IP$4,P24,Stock!$D$5:$IP$5,Q24),IF(COUNTIF(Stock!$D$5:$IP$5,Q24)>0,SUMIF(Stock!$D$5:$IP$5,Q24,Stock!$D$32:$IP$32),SUMIF(Stock!$D$4:$IP$4,P24,Stock!$D$32:$IP$32))),SUMIF(Stock!$D$4:$IP$4,P24,Stock!$D$32:$IP$32))) -> 222 | V24: PC1525 | X24: {=IF(NOT(ISNUMBER($W24)),"CHECK",IF(OR(AND(TRIM($Q24&"")<>"",INDEX(Stock!$EW$5:$FU$5,$W24)=$Q24),INDEX(Stock!$EW$4:$FU$4,$W24)=$P24),"OK","CHECK"))} -> CHECK
B25: ZEN DEISAL | C25: PC-86279 | D25: 100 | E25: =IF(AND(B25="",C25=""),"",IF(C25<>"",IF(COUNTIFS(Stock!$D$4:$IP$4,B25,Stock!$D$5:$IP$5,C25)>0,SUMIFS(Stock!$D$340:$IP$340,Stock!$D$4:$IP$4,B25,Stock!$D$5:$IP$5,C25),IF(COUNTIF(Stock!$D$5:$IP$5,C25)>0,SUMIF(Stock!$D$5:$IP$5,C25,Stock!$D$340:$IP$340),SUMIF(Stock!$D$4:$IP$4,B25,Stock!$D$340:$IP$340))),SUMIF(Stock!$D$4:$IP$4,B25,Stock!$D$340:$IP$340))) -> 15 | F25: =D25-E25 -> 85 | G25: =IF(AND(B25="",C25=""),"",IF(C25<>"",IF(COUNTIFS(Stock!$D$4:$IP$4,B25,Stock!$D$5:$IP$5,C25)>0,SUMIFS(Stock!$D$32:$IP$32,Stock!$D$4:$IP$4,B25,Stock!$D$5:$IP$5,C25),IF(COUNTIF(Stock!$D$5:$IP$5,C25)>0,SUMIF(Stock!$D$5:$IP$5,C25,Stock!$D$32:$IP$32),SUMIF(Stock!$D$4:$IP$4,B25,Stock!$D$32:$IP$32))),SUMIF(Stock!$D$4:$IP$4,B25,Stock!$D$32:$IP$32))) -> 100 | I25: Lancer MMC-2000 | J25: PC-051R | K25: 241 | L25: =IF(AND(I25="",J25=""),"",IF(J25<>"",IF(COUNTIFS(Stock!$D$4:$IP$4,I25,Stock!$D$5:$IP$5,J25)>0,SUMIFS(Stock!$D$340:$IP$340,Stock!$D$4:$IP$4,I25,Stock!$D$5:$IP$5,J25),IF(COUNTIF(Stock!$D$5:$IP$5,J25)>0,SUMIF(Stock!$D$5:$IP$5,J25,Stock!$D$340:$IP$340),SUMIF(Stock!$D$4:$IP$4,I25,Stock!$D$340:$IP$340))),SUMIF(Stock!$D$4:$IP$4,I25,Stock!$D$340:$IP$340))) -> 177 | M25: =K25-L25 -> 64 | N25: =IF(AND(I25="",J25=""),"",IF(J25<>"",IF(COUNTIFS(Stock!$D$4:$IP$4,I25,Stock!$D$5:$IP$5,J25)>0,SUMIFS(Stock!$D$32:$IP$32,Stock!$D$4:$IP$4,I25,Stock!$D$5:$IP$5,J25),IF(COUNTIF(Stock!$D$5:$IP$5,J25)>0,SUMIF(Stock!$D$5:$IP$5,J25,Stock!$D$32:$IP$32),SUMIF(Stock!$D$4:$IP$4,I25,Stock!$D$32:$IP$32))),SUMIF(Stock!$D$4:$IP$4,I25,Stock!$D$32:$IP$32))) -> 237 | P25: LENCER | Q25: PC-1044A | S25: =IF(AND(P25="",Q25=""),"",IF(Q25<>"",IF(COUNTIFS(Stock!$D$4:$IP$4,P25,Stock!$D$5:$IP$5,Q25)>0,SUMIFS(Stock!$D$340:$IP$340,Stock!$D$4:$IP$4,P25,Stock!$D$5:$IP$5,Q25),IF(COUNTIF(Stock!$D$5:$IP$5,Q25)>0,SUMIF(Stock!$D$5:$IP$5,Q25,Stock!$D$340:$IP$340),SUMIF(Stock!$D$4:$IP$4,P25,Stock!$D$340:$IP$340))),SUMIF(Stock!$D$4:$IP$4,P25,Stock!$D$340:$IP$340))) -> 100 | T25: =R25-S25 -> -100 | U25: =IF(AND(P25="",Q25=""),"",IF(Q25<>"",IF(COUNTIFS(Stock!$D$4:$IP$4,P25,Stock!$D$5:$IP$5,Q25)>0,SUMIFS(Stock!$D$32:$IP$32,Stock!$D$4:$IP$4,P25,Stock!$D$5:$IP$5,Q25),IF(COUNTIF(Stock!$D$5:$IP$5,Q25)>0,SUMIF(Stock!$D$5:$IP$5,Q25,Stock!$D$32:$IP$32),SUMIF(Stock!$D$4:$IP$4,P25,Stock!$D$32:$IP$32))),SUMIF(Stock!$D$4:$IP$4,P25,Stock!$D$32:$IP$32))) -> 200 | V25: PC1044A | X25: {=IF(NOT(ISNUMBER($W25)),"CHECK",IF(OR(AND(TRIM($Q25&"")<>"",INDEX(Stock!$EW$5:$FU$5,$W25)=$Q25),INDEX(Stock!$EW$4:$FU$4,$W25)=$P25),"OK","CHECK"))} -> CHECK
B26: ZEN DELPHI R12 | C26: PC-86270 R12 | D26: 97 | E26: =IF(AND(B26="",C26=""),"",IF(C26<>"",IF(COUNTIFS(Stock!$D$4:$IP$4,B26,Stock!$D$5:$IP$5,C26)>0,SUMIFS(Stock!$D$340:$IP$340,Stock!$D$4:$IP$4,B26,Stock!$D$5:$IP$5,C26),IF(COUNTIF(Stock!$D$5:$IP$5,C26)>0,SUMIF(Stock!$D$5:$IP$5,C26,Stock!$D$340:$IP$340),SUMIF(Stock!$D$4:$IP$4,B26,Stock!$D$340:$IP$340))),SUMIF(Stock!$D$4:$IP$4,B26,Stock!$D$340:$IP$340))) -> 0 | F26: =D26-E26 -> 97 | G26: =IF(AND(B26="",C26=""),"",IF(C26<>"",IF(COUNTIFS(Stock!$D$4:$IP$4,B26,Stock!$D$5:$IP$5,C26)>0,SUMIFS(Stock!$D$32:$IP$32,Stock!$D$4:$IP$4,B26,Stock!$D$5:$IP$5,C26),IF(COUNTIF(Stock!$D$5:$IP$5,C26)>0,SUMIF(Stock!$D$5:$IP$5,C26,Stock!$D$32:$IP$32),SUMIF(Stock!$D$4:$IP$4,B26,Stock!$D$32:$IP$32))),SUMIF(Stock!$D$4:$IP$4,B26,Stock!$D$32:$IP$32))) -> 150 | I26: Logan | J26: PC-407R | K26: 84 | L26: =IF(AND(I26="",J26=""),"",IF(J26<>"",IF(COUNTIFS(Stock!$D$4:$IP$4,I26,Stock!$D$5:$IP$5,J26)>0,SUMIFS(Stock!$D$340:$IP$340,Stock!$D$4:$IP$4,I26,Stock!$D$5:$IP$5,J26),IF(COUNTIF(Stock!$D$5:$IP$5,J26)>0,SUMIF(Stock!$D$5:$IP$5,J26,Stock!$D$340:$IP$340),SUMIF(Stock!$D$4:$IP$4,I26,Stock!$D$340:$IP$340))),SUMIF(Stock!$D$4:$IP$4,I26,Stock!$D$340:$IP$340))) -> 0 | M26: =K26-L26 -> 84 | N26: =IF(AND(I26="",J26=""),"",IF(J26<>"",IF(COUNTIFS(Stock!$D$4:$IP$4,I26,Stock!$D$5:$IP$5,J26)>0,SUMIFS(Stock!$D$32:$IP$32,Stock!$D$4:$IP$4,I26,Stock!$D$5:$IP$5,J26),IF(COUNTIF(Stock!$D$5:$IP$5,J26)>0,SUMIF(Stock!$D$5:$IP$5,J26,Stock!$D$32:$IP$32),SUMIF(Stock!$D$4:$IP$4,I26,Stock!$D$32:$IP$32))),SUMIF(Stock!$D$4:$IP$4,I26,Stock!$D$32:$IP$32))) -> 84 | P26: TOYOTA QUALIS | Q26: PC-1065 | R26: 100 | S26: =IF(AND(P26="",Q26=""),"",IF(Q26<>"",IF(COUNTIFS(Stock!$D$4:$IP$4,P26,Stock!$D$5:$IP$5,Q26)>0,SUMIFS(Stock!$D$340:$IP$340,Stock!$D$4:$IP$4,P26,Stock!$D$5:$IP$5,Q26),IF(COUNTIF(Stock!$D$5:$IP$5,Q26)>0,SUMIF(Stock!$D$5:$IP$5,Q26,Stock!$D$340:$IP$340),SUMIF(Stock!$D$4:$IP$4,P26,Stock!$D$340:$IP$340))),SUMIF(Stock!$D$4:$IP$4,P26,Stock!$D$340:$IP$340))) -> 100 | T26: =R26-S26 -> 0 | U26: =IF(AND(P26="",Q26=""),"",IF(Q26<>"",IF(COUNTIFS(Stock!$D$4:$IP$4,P26,Stock!$D$5:$IP$5,Q26)>0,SUMIFS(Stock!$D$32:$IP$32,Stock!$D$4:$IP$4,P26,Stock!$D$5:$IP$5,Q26),IF(COUNTIF(Stock!$D$5:$IP$5,Q26)>0,SUMIF(Stock!$D$5:$IP$5,Q26,Stock!$D$32:$IP$32),SUMIF(Stock!$D$4:$IP$4,P26,Stock!$D$32:$IP$32))),SUMIF(Stock!$D$4:$IP$4,P26,Stock!$D$32:$IP$32))) -> 300 | V26: PC1065 | X26: {=IF(NOT(ISNUMBER($W26)),"CHECK",IF(OR(AND(TRIM($Q26&"")<>"",INDEX(Stock!$EW$5:$FU$5,$W26)=$Q26),INDEX(Stock!$EW$4:$FU$4,$W26)=$P26),"OK","CHECK"))} -> CHECK
B27: ZEN DELPHI R134A | C27: PC-86270 R134 | D27: 126 | E27: =IF(AND(B27="",C27=""),"",IF(C27<>"",IF(COUNTIFS(Stock!$D$4:$IP$4,B27,Stock!$D$5:$IP$5,C27)>0,SUMIFS(Stock!$D$340:$IP$340,Stock!$D$4:$IP$4,B27,Stock!$D$5:$IP$5,C27),IF(COUNTIF(Stock!$D$5:$IP$5,C27)>0,SUMIF(Stock!$D$5:$IP$5,C27,Stock!$D$340:$IP$340),SUMIF(Stock!$D$4:$IP$4,B27,Stock!$D$340:$IP$340))),SUMIF(Stock!$D$4:$IP$4,B27,Stock!$D$340:$IP$340))) -> 1 | F27: =D27-E27 -> 125 | G27: =IF(AND(B27="",C27=""),"",IF(C27<>"",IF(COUNTIFS(Stock!$D$4:$IP$4,B27,Stock!$D$5:$IP$5,C27)>0,SUMIFS(Stock!$D$32:$IP$32,Stock!$D$4:$IP$4,B27,Stock!$D$5:$IP$5,C27),IF(COUNTIF(Stock!$D$5:$IP$5,C27)>0,SUMIF(Stock!$D$5:$IP$5,C27,Stock!$D$32:$IP$32),SUMIF(Stock!$D$4:$IP$4,B27,Stock!$D$32:$IP$32))),SUMIF(Stock!$D$4:$IP$4,B27,Stock!$D$32:$IP$32))) -> 151 | I27: MATIZ | J27: PC-8084 | K27: 32 | L27: =IF(AND(I27="",J27=""),"",IF(J27<>"",IF(COUNTIFS(Stock!$D$4:$IP$4,I27,Stock!$D$5:$IP$5,J27)>0,SUMIFS(Stock!$D$340:$IP$340,Stock!$D$4:$IP$4,I27,Stock!$D$5:$IP$5,J27),IF(COUNTIF(Stock!$D$5:$IP$5,J27)>0,SUMIF(Stock!$D$5:$IP$5,J27,Stock!$D$340:$IP$340),SUMIF(Stock!$D$4:$IP$4,I27,Stock!$D$340:$IP$340))),SUMIF(Stock!$D$4:$IP$4,I27,Stock!$D$340:$IP$340))) -> 22 | M27: =K27-L27 -> 10 | N27: =IF(AND(I27="",J27=""),"",IF(J27<>"",IF(COUNTIFS(Stock!$D$4:$IP$4,I27,Stock!$D$5:$IP$5,J27)>0,SUMIFS(Stock!$D$32:$IP$32,Stock!$D$4:$IP$4,I27,Stock!$D$5:$IP$5,J27),IF(COUNTIF(Stock!$D$5:$IP$5,J27)>0,SUMIF(Stock!$D$5:$IP$5,J27,Stock!$D$32:$IP$32),SUMIF(Stock!$D$4:$IP$4,I27,Stock!$D$32:$IP$32))),SUMIF(Stock!$D$4:$IP$4,I27,Stock!$D$32:$IP$32))) -> 42 | P27: INDICA R-134A-4 pin | Q27: PC-1066 | R27: 100 | S27: =IF(AND(P27="",Q27=""),"",IF(Q27<>"",IF(COUNTIFS(Stock!$D$4:$IP$4,P27,Stock!$D$5:$IP$5,Q27)>0,SUMIFS(Stock!$D$340:$IP$340,Stock!$D$4:$IP$4,P27,Stock!$D$5:$IP$5,Q27),IF(COUNTIF(Stock!$D$5:$IP$5,Q27)>0,SUMIF(Stock!$D$5:$IP$5,Q27,Stock!$D$340:$IP$340),SUMIF(Stock!$D$4:$IP$4,P27,Stock!$D$340:$IP$340))),SUMIF(Stock!$D$4:$IP$4,P27,Stock!$D$340:$IP$340))) -> 100 | T27: =R27-S27 -> 0 | U27: =IF(AND(P27="",Q27=""),"",IF(Q27<>"",IF(COUNTIFS(Stock!$D$4:$IP$4,P27,Stock!$D$5:$IP$5,Q27)>0,SUMIFS(Stock!$D$32:$IP$32,Stock!$D$4:$IP$4,P27,Stock!$D$5:$IP$5,Q27),IF(COUNTIF(Stock!$D$5:$IP$5,Q27)>0,SUMIF(Stock!$D$5:$IP$5,Q27,Stock!$D$32:$IP$32),SUMIF(Stock!$D$4:$IP$4,P27,Stock!$D$32:$IP$32))),SUMIF(Stock!$D$4:$IP$4,P27,Stock!$D$32:$IP$32))) -> 300 | V27: PC1066 | X27: {=IF(NOT(ISNUMBER($W27)),"CHECK",IF(OR(AND(TRIM($Q27&"")<>"",INDEX(Stock!$EW$5:$FU$5,$W27)=$Q27),INDEX(Stock!$EW$4:$FU$4,$W27)=$P27),"OK","CHECK"))} -> CHECK
B28: SCORPIO | C28: PC-86093 | D28: 165 | E28: =IF(AND(B28="",C28=""),"",IF(C28<>"",IF(COUNTIFS(Stock!$D$4:$IP$4,B28,Stock!$D$5:$IP$5,C28)>0,SUMIFS(Stock!$D$340:$IP$340,Stock!$D$4:$IP$4,B28,Stock!$D$5:$IP$5,C28),IF(COUNTIF(Stock!$D$5:$IP$5,C28)>0,SUMIF(Stock!$D$5:$IP$5,C28,Stock!$D$340:$IP$340),SUMIF(Stock!$D$4:$IP$4,B28,Stock!$D$340:$IP$340))),SUMIF(Stock!$D$4:$IP$4,B28,Stock!$D$340:$IP$340))) -> 150 | F28: =D28-E28 -> 15 | G28: =IF(AND(B28="",C28=""),"",IF(C28<>"",IF(COUNTIFS(Stock!$D$4:$IP$4,B28,Stock!$D$5:$IP$5,C28)>0,SUMIFS(Stock!$D$32:$IP$32,Stock!$D$4:$IP$4,B28,Stock!$D$5:$IP$5,C28),IF(COUNTIF(Stock!$D$5:$IP$5,C28)>0,SUMIF(Stock!$D$5:$IP$5,C28,Stock!$D$32:$IP$32),SUMIF(Stock!$D$4:$IP$4,B28,Stock!$D$32:$IP$32))),SUMIF(Stock!$D$4:$IP$4,B28,Stock!$D$32:$IP$32))) -> 175 | I28: Opel | J28: PC-052R | K28: 25 | L28: =IF(AND(I28="",J28=""),"",IF(J28<>"",IF(COUNTIFS(Stock!$D$4:$IP$4,I28,Stock!$D$5:$IP$5,J28)>0,SUMIFS(Stock!$D$340:$IP$340,Stock!$D$4:$IP$4,I28,Stock!$D$5:$IP$5,J28),IF(COUNTIF(Stock!$D$5:$IP$5,J28)>0,SUMIF(Stock!$D$5:$IP$5,J28,Stock!$D$340:$IP$340),SUMIF(Stock!$D$4:$IP$4,I28,Stock!$D$340:$IP$340))),SUMIF(Stock!$D$4:$IP$4,I28,Stock!$D$340:$IP$340))) -> 25 | M28: =K28-L28 -> 0 | N28: =IF(AND(I28="",J28=""),"",IF(J28<>"",IF(COUNTIFS(Stock!$D$4:$IP$4,I28,Stock!$D$5:$IP$5,J28)>0,SUMIFS(Stock!$D$32:$IP$32,Stock!$D$4:$IP$4,I28,Stock!$D$5:$IP$5,J28),IF(COUNTIF(Stock!$D$5:$IP$5,J28)>0,SUMIF(Stock!$D$5:$IP$5,J28,Stock!$D$32:$IP$32),SUMIF(Stock!$D$4:$IP$4,I28,Stock!$D$32:$IP$32))),SUMIF(Stock!$D$4:$IP$4,I28,Stock!$D$32:$IP$32))) -> 25 | P28: skoda-3PIN | Q28: PC-1191 | S28: =IF(AND(P28="",Q28=""),"",IF(Q28<>"",IF(COUNTIFS(Stock!$D$4:$IP$4,P28,Stock!$D$5:$IP$5,Q28)>0,SUMIFS(Stock!$D$340:$IP$340,Stock!$D$4:$IP$4,P28,Stock!$D$5:$IP$5,Q28),IF(COUNTIF(Stock!$D$5:$IP$5,Q28)>0,SUMIF(Stock!$D$5:$IP$5,Q28,Stock!$D$340:$IP$340),SUMIF(Stock!$D$4:$IP$4,P28,Stock!$D$340:$IP$340))),SUMIF(Stock!$D$4:$IP$4,P28,Stock!$D$340:$IP$340))) -> 0 | T28: =R28-S28 -> 0 | U28: =IF(AND(P28="",Q28=""),"",IF(Q28<>"",IF(COUNTIFS(Stock!$D$4:$IP$4,P28,Stock!$D$5:$IP$5,Q28)>0,SUMIFS(Stock!$D$32:$IP$32,Stock!$D$4:$IP$4,P28,Stock!$D$5:$IP$5,Q28),IF(COUNTIF(Stock!$D$5:$IP$5,Q28)>0,SUMIF(Stock!$D$5:$IP$5,Q28,Stock!$D$32:$IP$32),SUMIF(Stock!$D$4:$IP$4,P28,Stock!$D$32:$IP$32))),SUMIF(Stock!$D$4:$IP$4,P28,Stock!$D$32:$IP$32))) -> 150 | V28: PC1191 | X28: {=IF(NOT(ISNUMBER($W28)),"CHECK",IF(OR(AND(TRIM($Q28&"")<>"",INDEX(Stock!$EW$5:$FU$5,$W28)=$Q28),INDEX(Stock!$EW$4:$FU$4,$W28)=$P28),"OK","CHECK"))} -> CHECK
B29: LANCER | C29: PC-86246B | D29: 100 | E29: =IF(AND(B29="",C29=""),"",IF(C29<>"",IF(COUNTIFS(Stock!$D$4:$IP$4,B29,Stock!$D$5:$IP$5,C29)>0,SUMIFS(Stock!$D$340:$IP$340,Stock!$D$4:$IP$4,B29,Stock!$D$5:$IP$5,C29),IF(COUNTIF(Stock!$D$5:$IP$5,C29)>0,SUMIF(Stock!$D$5:$IP$5,C29,Stock!$D$340:$IP$340),SUMIF(Stock!$D$4:$IP$4,B29,Stock!$D$340:$IP$340))),SUMIF(Stock!$D$4:$IP$4,B29,Stock!$D$340:$IP$340))) -> 100 | F29: =D29-E29 -> 0 | G29: =IF(AND(B29="",C29=""),"",IF(C29<>"",IF(COUNTIFS(Stock!$D$4:$IP$4,B29,Stock!$D$5:$IP$5,C29)>0,SUMIFS(Stock!$D$32:$IP$32,Stock!$D$4:$IP$4,B29,Stock!$D$5:$IP$5,C29),IF(COUNTIF(Stock!$D$5:$IP$5,C29)>0,SUMIF(Stock!$D$5:$IP$5,C29,Stock!$D$32:$IP$32),SUMIF(Stock!$D$4:$IP$4,B29,Stock!$D$32:$IP$32))),SUMIF(Stock!$D$4:$IP$4,B29,Stock!$D$32:$IP$32))) -> 100 | I29: Opel Corsa | J29: PC-8096 | K29: 100 | L29: =IF(AND(I29="",J29=""),"",IF(J29<>"",IF(COUNTIFS(Stock!$D$4:$IP$4,I29,Stock!$D$5:$IP$5,J29)>0,SUMIFS(Stock!$D$340:$IP$340,Stock!$D$4:$IP$4,I29,Stock!$D$5:$IP$5,J29),IF(COUNTIF(Stock!$D$5:$IP$5,J29)>0,SUMIF(Stock!$D$5:$IP$5,J29,Stock!$D$340:$IP$340),SUMIF(Stock!$D$4:$IP$4,I29,Stock!$D$340:$IP$340))),SUMIF(Stock!$D$4:$IP$4,I29,Stock!$D$340:$IP$340))) -> 52 | M29: =K29-L29 -> 48 | N29: =IF(AND(I29="",J29=""),"",IF(J29<>"",IF(COUNTIFS(Stock!$D$4:$IP$4,I29,Stock!$D$5:$IP$5,J29)>0,SUMIFS(Stock!$D$32:$IP$32,Stock!$D$4:$IP$4,I29,Stock!$D$5:$IP$5,J29),IF(COUNTIF(Stock!$D$5:$IP$5,J29)>0,SUMIF(Stock!$D$5:$IP$5,J29,Stock!$D$32:$IP$32),SUMIF(Stock!$D$4:$IP$4,I29,Stock!$D$32:$IP$32))),SUMIF(Stock!$D$4:$IP$4,I29,Stock!$D$32:$IP$32))) -> 100 | P29: esteem r12 ordanary | Q29: PC-1052 | S29: =IF(AND(P29="",Q29=""),"",IF(Q29<>"",IF(COUNTIFS(Stock!$D$4:$IP$4,P29,Stock!$D$5:$IP$5,Q29)>0,SUMIFS(Stock!$D$340:$IP$340,Stock!$D$4:$IP$4,P29,Stock!$D$5:$IP$5,Q29),IF(COUNTIF(Stock!$D$5:$IP$5,Q29)>0,SUMIF(Stock!$D$5:$IP$5,Q29,Stock!$D$340:$IP$340),SUMIF(Stock!$D$4:$IP$4,P29,Stock!$D$340:$IP$340))),SUMIF(Stock!$D$4:$IP$4,P29,Stock!$D$340:$IP$340))) -> 0 | T29: =R29-S29 -> 0 | U29: =IF(AND(P29="",Q29=""),"",IF(Q29<>"",IF(COUNTIFS(Stock!$D$4:$IP$4,P29,Stock!$D$5:$IP$5,Q29)>0,SUMIFS(Stock!$D$32:$IP$32,Stock!$D$4:$IP$4,P29,Stock!$D$5:$IP$5,Q29),IF(COUNTIF(Stock!$D$5:$IP$5,Q29)>0,SUMIF(Stock!$D$5:$IP$5,Q29,Stock!$D$32:$IP$32),SUMIF(Stock!$D$4:$IP$4,P29,Stock!$D$32:$IP$32))),SUMIF(Stock!$D$4:$IP$4,P29,Stock!$D$32:$IP$32))) -> 200 | V29: PC1052 | X29: {=IF(NOT(ISNUMBER($W29)),"CHECK",IF(OR(AND(TRIM($Q29&"")<>"",INDEX(Stock!$EW$5:$FU$5,$W29)=$Q29),INDEX(Stock!$EW$4:$FU$4,$W29)=$P29),"OK","CHECK"))} -> CHECK
B30: TRAVERA | C30: PC-86247 | D30: 325 | E30: =IF(AND(B30="",C30=""),"",IF(C30<>"",IF(COUNTIFS(Stock!$D$4:$IP$4,B30,Stock!$D$5:$IP$5,C30)>0,SUMIFS(Stock!$D$340:$IP$340,Stock!$D$4:$IP$4,B30,Stock!$D$5:$IP$5,C30),IF(COUNTIF(Stock!$D$5:$IP$5,C30)>0,SUMIF(Stock!$D$5:$IP$5,C30,Stock!$D$340:$IP$340),SUMIF(Stock!$D$4:$IP$4,B30,Stock!$D$340:$IP$340))),SUMIF(Stock!$D$4:$IP$4,B30,Stock!$D$340:$IP$340))) -> 300 | F30: =D30-E30 -> 25 | G30: =IF(AND(B30="",C30=""),"",IF(C30<>"",IF(COUNTIFS(Stock!$D$4:$IP$4,B30,Stock!$D$5:$IP$5,C30)>0,SUMIFS(Stock!$D$32:$IP$32,Stock!$D$4:$IP$4,B30,Stock!$D$5:$IP$5,C30),IF(COUNTIF(Stock!$D$5:$IP$5,C30)>0,SUMIF(Stock!$D$5:$IP$5,C30,Stock!$D$32:$IP$32),SUMIF(Stock!$D$4:$IP$4,B30,Stock!$D$32:$IP$32))),SUMIF(Stock!$D$4:$IP$4,B30,Stock!$D$32:$IP$32))) -> 350 | I30: Optra | J30: PC-210 | K30: 75 | L30: =IF(AND(I30="",J30=""),"",IF(J30<>"",IF(COUNTIFS(Stock!$D$4:$IP$4,I30,Stock!$D$5:$IP$5,J30)>0,SUMIFS(Stock!$D$340:$IP$340,Stock!$D$4:$IP$4,I30,Stock!$D$5:$IP$5,J30),IF(COUNTIF(Stock!$D$5:$IP$5,J30)>0,SUMIF(Stock!$D$5:$IP$5,J30,Stock!$D$340:$IP$340),SUMIF(Stock!$D$4:$IP$4,I30,Stock!$D$340:$IP$340))),SUMIF(Stock!$D$4:$IP$4,I30,Stock!$D$340:$IP$340))) -> 75 | M30: =K30-L30 -> 0 | N30: =IF(AND(I30="",J30=""),"",IF(J30<>"",IF(COUNTIFS(Stock!$D$4:$IP$4,I30,Stock!$D$5:$IP$5,J30)>0,SUMIFS(Stock!$D$32:$IP$32,Stock!$D$4:$IP$4,I30,Stock!$D$5:$IP$5,J30),IF(COUNTIF(Stock!$D$5:$IP$5,J30)>0,SUMIF(Stock!$D$5:$IP$5,J30,Stock!$D$32:$IP$32),SUMIF(Stock!$D$4:$IP$4,I30,Stock!$D$32:$IP$32))),SUMIF(Stock!$D$4:$IP$4,I30,Stock!$D$32:$IP$32))) -> 75 | P30: SONATA D | Q30: PC-1802B | S30: =IF(AND(P30="",Q30=""),"",IF(Q30<>"",IF(COUNTIFS(Stock!$D$4:$IP$4,P30,Stock!$D$5:$IP$5,Q30)>0,SUMIFS(Stock!$D$340:$IP$340,Stock!$D$4:$IP$4,P30,Stock!$D$5:$IP$5,Q30),IF(COUNTIF(Stock!$D$5:$IP$5,Q30)>0,SUMIF(Stock!$D$5:$IP$5,Q30,Stock!$D$340:$IP$340),SUMIF(Stock!$D$4:$IP$4,P30,Stock!$D$340:$IP$340))),SUMIF(Stock!$D$4:$IP$4,P30,Stock!$D$340:$IP$340))) -> 0 | T30: =R30-S30 -> 0 | U30: =IF(AND(P30="",Q30=""),"",IF(Q30<>"",IF(COUNTIFS(Stock!$D$4:$IP$4,P30,Stock!$D$5:$IP$5,Q30)>0,SUMIFS(Stock!$D$32:$IP$32,Stock!$D$4:$IP$4,P30,Stock!$D$5:$IP$5,Q30),IF(COUNTIF(Stock!$D$5:$IP$5,Q30)>0,SUMIF(Stock!$D$5:$IP$5,Q30,Stock!$D$32:$IP$32),SUMIF(Stock!$D$4:$IP$4,P30,Stock!$D$32:$IP$32))),SUMIF(Stock!$D$4:$IP$4,P30,Stock!$D$32:$IP$32))) -> 200 | V30: PC1802B | X30: {=IF(NOT(ISNUMBER($W30)),"CHECK",IF(OR(AND(TRIM($Q30&"")<>"",INDEX(Stock!$EW$5:$FU$5,$W30)=$Q30),INDEX(Stock!$EW$4:$FU$4,$W30)=$P30),"OK","CHECK"))} -> CHECK
B31: ACCENT-PETROL | C31: PC-86248 | D31: 100 | E31: =IF(AND(B31="",C31=""),"",IF(C31<>"",IF(COUNTIFS(Stock!$D$4:$IP$4,B31,Stock!$D$5:$IP$5,C31)>0,SUMIFS(Stock!$D$340:$IP$340,Stock!$D$4:$IP$4,B31,Stock!$D$5:$IP$5,C31),IF(COUNTIF(Stock!$D$5:$IP$5,C31)>0,SUMIF(Stock!$D$5:$IP$5,C31,Stock!$D$340:$IP$340),SUMIF(Stock!$D$4:$IP$4,B31,Stock!$D$340:$IP$340))),SUMIF(Stock!$D$4:$IP$4,B31,Stock!$D$340:$IP$340))) -> 85 | F31: =D31-E31 -> 15 | G31: =IF(AND(B31="",C31=""),"",IF(C31<>"",IF(COUNTIFS(Stock!$D$4:$IP$4,B31,Stock!$D$5:$IP$5,C31)>0,SUMIFS(Stock!$D$32:$IP$32,Stock!$D$4:$IP$4,B31,Stock!$D$5:$IP$5,C31),IF(COUNTIF(Stock!$D$5:$IP$5,C31)>0,SUMIF(Stock!$D$5:$IP$5,C31,Stock!$D$32:$IP$32),SUMIF(Stock!$D$4:$IP$4,B31,Stock!$D$32:$IP$32))),SUMIF(Stock!$D$4:$IP$4,B31,Stock!$D$32:$IP$32))) -> 100 | I31: Santro Xing | J31: PC-250R | K31: 69 | L31: =IF(AND(I31="",J31=""),"",IF(J31<>"",IF(COUNTIFS(Stock!$D$4:$IP$4,I31,Stock!$D$5:$IP$5,J31)>0,SUMIFS(Stock!$D$340:$IP$340,Stock!$D$4:$IP$4,I31,Stock!$D$5:$IP$5,J31),IF(COUNTIF(Stock!$D$5:$IP$5,J31)>0,SUMIF(Stock!$D$5:$IP$5,J31,Stock!$D$340:$IP$340),SUMIF(Stock!$D$4:$IP$4,I31,Stock!$D$340:$IP$340))),SUMIF(Stock!$D$4:$IP$4,I31,Stock!$D$340:$IP$340))) -> 75 | M31: =K31-L31 -> -6 | N31: =IF(AND(I31="",J31=""),"",IF(J31<>"",IF(COUNTIFS(Stock!$D$4:$IP$4,I31,Stock!$D$5:$IP$5,J31)>0,SUMIFS(Stock!$D$32:$IP$32,Stock!$D$4:$IP$4,I31,Stock!$D$5:$IP$5,J31),IF(COUNTIF(Stock!$D$5:$IP$5,J31)>0,SUMIF(Stock!$D$5:$IP$5,J31,Stock!$D$32:$IP$32),SUMIF(Stock!$D$4:$IP$4,I31,Stock!$D$32:$IP$32))),SUMIF(Stock!$D$4:$IP$4,I31,Stock!$D$32:$IP$32))) -> 75 | P31: PALIO | Q31: PC-1100 | R31: 295 | S31: =IF(AND(P31="",Q31=""),"",IF(Q31<>"",IF(COUNTIFS(Stock!$D$4:$IP$4,P31,Stock!$D$5:$IP$5,Q31)>0,SUMIFS(Stock!$D$340:$IP$340,Stock!$D$4:$IP$4,P31,Stock!$D$5:$IP$5,Q31),IF(COUNTIF(Stock!$D$5:$IP$5,Q31)>0,SUMIF(Stock!$D$5:$IP$5,Q31,Stock!$D$340:$IP$340),SUMIF(Stock!$D$4:$IP$4,P31,Stock!$D$340:$IP$340))),SUMIF(Stock!$D$4:$IP$4,P31,Stock!$D$340:$IP$340))) -> 0 | T31: =R31-S31 -> 295 | U31: =IF(AND(P31="",Q31=""),"",IF(Q31<>"",IF(COUNTIFS(Stock!$D$4:$IP$4,P31,Stock!$D$5:$IP$5,Q31)>0,SUMIFS(Stock!$D$32:$IP$32,Stock!$D$4:$IP$4,P31,Stock!$D$5:$IP$5,Q31),IF(COUNTIF(Stock!$D$5:$IP$5,Q31)>0,SUMIF(Stock!$D$5:$IP$5,Q31,Stock!$D$32:$IP$32),SUMIF(Stock!$D$4:$IP$4,P31,Stock!$D$32:$IP$32))),SUMIF(Stock!$D$4:$IP$4,P31,Stock!$D$32:$IP$32))) -> 300 | V31: PC1100 | X31: {=IF(NOT(ISNUMBER($W31)),"CHECK",IF(OR(AND(TRIM($Q31&"")<>"",INDEX(Stock!$EW$5:$FU$5,$W31)=$Q31),INDEX(Stock!$EW$4:$FU$4,$W31)=$P31),"OK","CHECK"))} -> CHECK
B32: SX4 | C32: PC-86025 | D32: 55 | E32: =IF(AND(B32="",C32=""),"",IF(C32<>"",IF(COUNTIFS(Stock!$D$4:$IP$4,B32,Stock!$D$5:$IP$5,C32)>0,SUMIFS(Stock!$D$340:$IP$340,Stock!$D$4:$IP$4,B32,Stock!$D$5:$IP$5,C32),IF(COUNTIF(Stock!$D$5:$IP$5,C32)>0,SUMIF(Stock!$D$5:$IP$5,C32,Stock!$D$340:$IP$340),SUMIF(Stock!$D$4:$IP$4,B32,Stock!$D$340:$IP$340))),SUMIF(Stock!$D$4:$IP$4,B32,Stock!$D$340:$IP$340))) -> 20 | F32: =D32-E32 -> 35 | G32: =IF(AND(B32="",C32=""),"",IF(C32<>"",IF(COUNTIFS(Stock!$D$4:$IP$4,B32,Stock!$D$5:$IP$5,C32)>0,SUMIFS(Stock!$D$32:$IP$32,Stock!$D$4:$IP$4,B32,Stock!$D$5:$IP$5,C32),IF(COUNTIF(Stock!$D$5:$IP$5,C32)>0,SUMIF(Stock!$D$5:$IP$5,C32,Stock!$D$32:$IP$32),SUMIF(Stock!$D$4:$IP$4,B32,Stock!$D$32:$IP$32))),SUMIF(Stock!$D$4:$IP$4,B32,Stock!$D$32:$IP$32))) -> 100 | I32: Scorpio | J32: PC-7159 | K32: 230 | L32: =IF(AND(I32="",J32=""),"",IF(J32<>"",IF(COUNTIFS(Stock!$D$4:$IP$4,I32,Stock!$D$5:$IP$5,J32)>0,SUMIFS(Stock!$D$340:$IP$340,Stock!$D$4:$IP$4,I32,Stock!$D$5:$IP$5,J32),IF(COUNTIF(Stock!$D$5:$IP$5,J32)>0,SUMIF(Stock!$D$5:$IP$5,J32,Stock!$D$340:$IP$340),SUMIF(Stock!$D$4:$IP$4,I32,Stock!$D$340:$IP$340))),SUMIF(Stock!$D$4:$IP$4,I32,Stock!$D$340:$IP$340))) -> 128 | M32: =K32-L32 -> 102 | N32: =IF(AND(I32="",J32=""),"",IF(J32<>"",IF(COUNTIFS(Stock!$D$4:$IP$4,I32,Stock!$D$5:$IP$5,J32)>0,SUMIFS(Stock!$D$32:$IP$32,Stock!$D$4:$IP$4,I32,Stock!$D$5:$IP$5,J32),IF(COUNTIF(Stock!$D$5:$IP$5,J32)>0,SUMIF(Stock!$D$5:$IP$5,J32,Stock!$D$32:$IP$32),SUMIF(Stock!$D$4:$IP$4,I32,Stock!$D$32:$IP$32))),SUMIF(Stock!$D$4:$IP$4,I32,Stock!$D$32:$IP$32))) -> 220 | P32: THERMO-STAT | Q32: PC-1229A | R32: 4900 | S32: =IF(AND(P32="",Q32=""),"",IF(Q32<>"",IF(COUNTIFS(Stock!$D$4:$IP$4,P32,Stock!$D$5:$IP$5,Q32)>0,SUMIFS(Stock!$D$340:$IP$340,Stock!$D$4:$IP$4,P32,Stock!$D$5:$IP$5,Q32),IF(COUNTIF(Stock!$D$5:$IP$5,Q32)>0,SUMIF(Stock!$D$5:$IP$5,Q32,Stock!$D$340:$IP$340),SUMIF(Stock!$D$4:$IP$4,P32,Stock!$D$340:$IP$340))),SUMIF(Stock!$D$4:$IP$4,P32,Stock!$D$340:$IP$340))) -> 4000 | T32: =R32-S32 -> 900 | U32: =IF(AND(P32="",Q32=""),"",IF(Q32<>"",IF(COUNTIFS(Stock!$D$4:$IP$4,P32,Stock!$D$5:$IP$5,Q32)>0,SUMIFS(Stock!$D$32:$IP$32,Stock!$D$4:$IP$4,P32,Stock!$D$5:$IP$5,Q32),IF(COUNTIF(Stock!$D$5:$IP$5,Q32)>0,SUMIF(Stock!$D$5:$IP$5,Q32,Stock!$D$32:$IP$32),SUMIF(Stock!$D$4:$IP$4,P32,Stock!$D$32:$IP$32))),SUMIF(Stock!$D$4:$IP$4,P32,Stock!$D$32:$IP$32))) -> 6000 | V32: PC1229A;THERMOSTATE | X32: {=IF(NOT(ISNUMBER($W32)),"CHECK",IF(OR(AND(TRIM($Q32&"")<>"",INDEX(Stock!$EW$5:$FU$5,$W32)=$Q32),INDEX(Stock!$EW$4:$FU$4,$W32)=$P32),"OK","CHECK"))} -> CHECK
B33: I-10 | D33: 0 | E33: =IF(AND(B33="",C33=""),"",IF(C33<>"",IF(COUNTIFS(Stock!$D$4:$IP$4,B33,Stock!$D$5:$IP$5,C33)>0,SUMIFS(Stock!$D$340:$IP$340,Stock!$D$4:$IP$4,B33,Stock!$D$5:$IP$5,C33),IF(COUNTIF(Stock!$D$5:$IP$5,C33)>0,SUMIF(Stock!$D$5:$IP$5,C33,Stock!$D$340:$IP$340),SUMIF(Stock!$D$4:$IP$4,B33,Stock!$D$340:$IP$340))),SUMIF(Stock!$D$4:$IP$4,B33,Stock!$D$340:$IP$340))) -> 0 | F33: =D33-E33 -> 0 | G33: =IF(AND(B33="",C33=""),"",IF(C33<>"",IF(COUNTIFS(Stock!$D$4:$IP$4,B33,Stock!$D$5:$IP$5,C33)>0,SUMIFS(Stock!$D$32:$IP$32,Stock!$D$4:$IP$4,B33,Stock!$D$5:$IP$5,C33),IF(COUNTIF(Stock!$D$5:$IP$5,C33)>0,SUMIF(Stock!$D$5:$IP$5,C33,Stock!$D$32:$IP$32),SUMIF(Stock!$D$4:$IP$4,B33,Stock!$D$32:$IP$32))),SUMIF(Stock!$D$4:$IP$4,B33,Stock!$D$32:$IP$32))) -> 0 | I33: Palio | J33: PC-054 | K33: 348 | L33: =IF(AND(I33="",J33=""),"",IF(J33<>"",IF(COUNTIFS(Stock!$D$4:$IP$4,I33,Stock!$D$5:$IP$5,J33)>0,SUMIFS(Stock!$D$340:$IP$340,Stock!$D$4:$IP$4,I33,Stock!$D$5:$IP$5,J33),IF(COUNTIF(Stock!$D$5:$IP$5,J33)>0,SUMIF(Stock!$D$5:$IP$5,J33,Stock!$D$340:$IP$340),SUMIF(Stock!$D$4:$IP$4,I33,Stock!$D$340:$IP$340))),SUMIF(Stock!$D$4:$IP$4,I33,Stock!$D$340:$IP$340))) -> 202 | M33: =K33-L33 -> 146 | N33: =IF(AND(I33="",J33=""),"",IF(J33<>"",IF(COUNTIFS(Stock!$D$4:$IP$4,I33,Stock!$D$5:$IP$5,J33)>0,SUMIFS(Stock!$D$32:$IP$32,Stock!$D$4:$IP$4,I33,Stock!$D$5:$IP$5,J33),IF(COUNTIF(Stock!$D$5:$IP$5,J33)>0,SUMIF(Stock!$D$5:$IP$5,J33,Stock!$D$32:$IP$32),SUMIF(Stock!$D$4:$IP$4,I33,Stock!$D$32:$IP$32))),SUMIF(Stock!$D$4:$IP$4,I33,Stock!$D$32:$IP$32))) -> 412 | P33: Pancil Thermostat White | Q33: PC-8002 | S33: =IF(AND(P33="",Q33=""),"",IF(Q33<>"",IF(COUNTIFS(Stock!$D$4:$IP$4,P33,Stock!$D$5:$IP$5,Q33)>0,SUMIFS(Stock!$D$340:$IP$340,Stock!$D$4:$IP$4,P33,Stock!$D$5:$IP$5,Q33),IF(COUNTIF(Stock!$D$5:$IP$5,Q33)>0,SUMIF(Stock!$D$5:$IP$5,Q33,Stock!$D$340:$IP$340),SUMIF(Stock!$D$4:$IP$4,P33,Stock!$D$340:$IP$340))),SUMIF(Stock!$D$4:$IP$4,P33,Stock!$D$340:$IP$340))) -> 0 | T33: =R33-S33 -> 0 | U33: =IF(AND(P33="",Q33=""),"",IF(Q33<>"",IF(COUNTIFS(Stock!$D$4:$IP$4,P33,Stock!$D$5:$IP$5,Q33)>0,SUMIFS(Stock!$D$32:$IP$32,Stock!$D$4:$IP$4,P33,Stock!$D$5:$IP$5,Q33),IF(COUNTIF(Stock!$D$5:$IP$5,Q33)>0,SUMIF(Stock!$D$5:$IP$5,Q33,Stock!$D$32:$IP$32),SUMIF(Stock!$D$4:$IP$4,P33,Stock!$D$32:$IP$32))),SUMIF(Stock!$D$4:$IP$4,P33,Stock!$D$32:$IP$32))) -> 250 | V33: PC8002 | X33: {=IF(NOT(ISNUMBER($W33)),"CHECK",IF(OR(AND(TRIM($Q33&"")<>"",INDEX(Stock!$EW$5:$FU$5,$W33)=$Q33),INDEX(Stock!$EW$4:$FU$4,$W33)=$P33),"OK","CHECK"))} -> CHECK
B34: SWIFT | C34: PC-86207 | D34: 100 | E34: =IF(AND(B34="",C34=""),"",IF(C34<>"",IF(COUNTIFS(Stock!$D$4:$IP$4,B34,Stock!$D$5:$IP$5,C34)>0,SUMIFS(Stock!$D$340:$IP$340,Stock!$D$4:$IP$4,B34,Stock!$D$5:$IP$5,C34),IF(COUNTIF(Stock!$D$5:$IP$5,C34)>0,SUMIF(Stock!$D$5:$IP$5,C34,Stock!$D$340:$IP$340),SUMIF(Stock!$D$4:$IP$4,B34,Stock!$D$340:$IP$340))),SUMIF(Stock!$D$4:$IP$4,B34,Stock!$D$340:$IP$340))) -> 100 | F34: =D34-E34 -> 0 | G34: =IF(AND(B34="",C34=""),"",IF(C34<>"",IF(COUNTIFS(Stock!$D$4:$IP$4,B34,Stock!$D$5:$IP$5,C34)>0,SUMIFS(Stock!$D$32:$IP$32,Stock!$D$4:$IP$4,B34,Stock!$D$5:$IP$5,C34),IF(COUNTIF(Stock!$D$5:$IP$5,C34)>0,SUMIF(Stock!$D$5:$IP$5,C34,Stock!$D$32:$IP$32),SUMIF(Stock!$D$4:$IP$4,B34,Stock!$D$32:$IP$32))),SUMIF(Stock!$D$4:$IP$4,B34,Stock!$D$32:$IP$32))) -> 100 | I34: Skoda | J34: PC-143R | K34: 320 | L34: =IF(AND(I34="",J34=""),"",IF(J34<>"",IF(COUNTIFS(Stock!$D$4:$IP$4,I34,Stock!$D$5:$IP$5,J34)>0,SUMIFS(Stock!$D$340:$IP$340,Stock!$D$4:$IP$4,I34,Stock!$D$5:$IP$5,J34),IF(COUNTIF(Stock!$D$5:$IP$5,J34)>0,SUMIF(Stock!$D$5:$IP$5,J34,Stock!$D$340:$IP$340),SUMIF(Stock!$D$4:$IP$4,I34,Stock!$D$340:$IP$340))),SUMIF(Stock!$D$4:$IP$4,I34,Stock!$D$340:$IP$340))) -> 109 | M34: =K34-L34 -> 211 | N34: =IF(AND(I34="",J34=""),"",IF(J34<>"",IF(COUNTIFS(Stock!$D$4:$IP$4,I34,Stock!$D$5:$IP$5,J34)>0,SUMIFS(Stock!$D$32:$IP$32,Stock!$D$4:$IP$4,I34,Stock!$D$5:$IP$5,J34),IF(COUNTIF(Stock!$D$5:$IP$5,J34)>0,SUMIF(Stock!$D$5:$IP$5,J34,Stock!$D$32:$IP$32),SUMIF(Stock!$D$4:$IP$4,I34,Stock!$D$32:$IP$32))),SUMIF(Stock!$D$4:$IP$4,I34,Stock!$D$32:$IP$32))) -> 367 | P34: Pancil Thermostat Oringe | Q34: PC-8006 | R34: 3074 | S34: =IF(AND(P34="",Q34=""),"",IF(Q34<>"",IF(COUNTIFS(Stock!$D$4:$IP$4,P34,Stock!$D$5:$IP$5,Q34)>0,SUMIFS(Stock!$D$340:$IP$340,Stock!$D$4:$IP$4,P34,Stock!$D$5:$IP$5,Q34),IF(COUNTIF(Stock!$D$5:$IP$5,Q34)>0,SUMIF(Stock!$D$5:$IP$5,Q34,Stock!$D$340:$IP$340),SUMIF(Stock!$D$4:$IP$4,P34,Stock!$D$340:$IP$340))),SUMIF(Stock!$D$4:$IP$4,P34,Stock!$D$340:$IP$340))) -> 0 | T34: =R34-S34 -> 3074 | U34: =IF(AND(P34="",Q34=""),"",IF(Q34<>"",IF(COUNTIFS(Stock!$D$4:$IP$4,P34,Stock!$D$5:$IP$5,Q34)>0,SUMIFS(Stock!$D$32:$IP$32,Stock!$D$4:$IP$4,P34,Stock!$D$5:$IP$5,Q34),IF(COUNTIF(Stock!$D$5:$IP$5,Q34)>0,SUMIF(Stock!$D$5:$IP$5,Q34,Stock!$D$32:$IP$32),SUMIF(Stock!$D$4:$IP$4,P34,Stock!$D$32:$IP$32))),SUMIF(Stock!$D$4:$IP$4,P34,Stock!$D$32:$IP$32))) -> 250 | V34: PC8006 | X34: {=IF(NOT(ISNUMBER($W34)),"CHECK",IF(OR(AND(TRIM($Q34&"")<>"",INDEX(Stock!$EW$5:$FU$5,$W34)=$Q34),INDEX(Stock!$EW$4:$FU$4,$W34)=$P34),"OK","CHECK"))} -> CHECK
B35: INDICA-134A-SUBROS | C35: PC-86036 | D35: 600 | E35: =IF(AND(B35="",C35=""),"",IF(C35<>"",IF(COUNTIFS(Stock!$D$4:$IP$4,B35,Stock!$D$5:$IP$5,C35)>0,SUMIFS(Stock!$D$340:$IP$340,Stock!$D$4:$IP$4,B35,Stock!$D$5:$IP$5,C35),IF(COUNTIF(Stock!$D$5:$IP$5,C35)>0,SUMIF(Stock!$D$5:$IP$5,C35,Stock!$D$340:$IP$340),SUMIF(Stock!$D$4:$IP$4,B35,Stock!$D$340:$IP$340))),SUMIF(Stock!$D$4:$IP$4,B35,Stock!$D$340:$IP$340))) -> 275 | F35: =D35-E35 -> 325 | G35: =IF(AND(B35="",C35=""),"",IF(C35<>"",IF(COUNTIFS(Stock!$D$4:$IP$4,B35,Stock!$D$5:$IP$5,C35)>0,SUMIFS(Stock!$D$32:$IP$32,Stock!$D$4:$IP$4,B35,Stock!$D$5:$IP$5,C35),IF(COUNTIF(Stock!$D$5:$IP$5,C35)>0,SUMIF(Stock!$D$5:$IP$5,C35,Stock!$D$32:$IP$32),SUMIF(Stock!$D$4:$IP$4,B35,Stock!$D$32:$IP$32))),SUMIF(Stock!$D$4:$IP$4,B35,Stock!$D$32:$IP$32))) -> 600 | I35: SONATA | J35: PC-079R | K35: 49 | L35: =IF(AND(I35="",J35=""),"",IF(J35<>"",IF(COUNTIFS(Stock!$D$4:$IP$4,I35,Stock!$D$5:$IP$5,J35)>0,SUMIFS(Stock!$D$340:$IP$340,Stock!$D$4:$IP$4,I35,Stock!$D$5:$IP$5,J35),IF(COUNTIF(Stock!$D$5:$IP$5,J35)>0,SUMIF(Stock!$D$5:$IP$5,J35,Stock!$D$340:$IP$340),SUMIF(Stock!$D$4:$IP$4,I35,Stock!$D$340:$IP$340))),SUMIF(Stock!$D$4:$IP$4,I35,Stock!$D$340:$IP$340))) -> 0 | M35: =K35-L35 -> 49 | N35: =IF(AND(I35="",J35=""),"",IF(J35<>"",IF(COUNTIFS(Stock!$D$4:$IP$4,I35,Stock!$D$5:$IP$5,J35)>0,SUMIFS(Stock!$D$32:$IP$32,Stock!$D$4:$IP$4,I35,Stock!$D$5:$IP$5,J35),IF(COUNTIF(Stock!$D$5:$IP$5,J35)>0,SUMIF(Stock!$D$5:$IP$5,J35,Stock!$D$32:$IP$32),SUMIF(Stock!$D$4:$IP$4,I35,Stock!$D$32:$IP$32))),SUMIF(Stock!$D$4:$IP$4,I35,Stock!$D$32:$IP$32))) -> 0 | P35: WAGON-R HPLP-2PIN | Q35: PC-1047B / 1801-A | R35: 400 | S35: =IF(AND(P35="",Q35=""),"",IF(Q35<>"",IF(COUNTIFS(Stock!$D$4:$IP$4,P35,Stock!$D$5:$IP$5,Q35)>0,SUMIFS(Stock!$D$340:$IP$340,Stock!$D$4:$IP$4,P35,Stock!$D$5:$IP$5,Q35),IF(COUNTIF(Stock!$D$5:$IP$5,Q35)>0,SUMIF(Stock!$D$5:$IP$5,Q35,Stock!$D$340:$IP$340),SUMIF(Stock!$D$4:$IP$4,P35,Stock!$D$340:$IP$340))),SUMIF(Stock!$D$4:$IP$4,P35,Stock!$D$340:$IP$340))) -> 700 | T35: =R35-S35 -> -300 | U35: =IF(AND(P35="",Q35=""),"",IF(Q35<>"",IF(COUNTIFS(Stock!$D$4:$IP$4,P35,Stock!$D$5:$IP$5,Q35)>0,SUMIFS(Stock!$D$32:$IP$32,Stock!$D$4:$IP$4,P35,Stock!$D$5:$IP$5,Q35),IF(COUNTIF(Stock!$D$5:$IP$5,Q35)>0,SUMIF(Stock!$D$5:$IP$5,Q35,Stock!$D$32:$IP$32),SUMIF(Stock!$D$4:$IP$4,P35,Stock!$D$32:$IP$32))),SUMIF(Stock!$D$4:$IP$4,P35,Stock!$D$32:$IP$32))) -> 1000 | V35: PC1047B;PC1801A | X35: {=IF(NOT(ISNUMBER($W35)),"CHECK",IF(OR(AND(TRIM($Q35&"")<>"",INDEX(Stock!$EW$5:$FU$5,$W35)=$Q35),INDEX(Stock!$EW$4:$FU$4,$W35)=$P35),"OK","CHECK"))} -> CHECK
B36: WAGON-R / ALTO | C36: PC-86037 | D36: 470 | E36: =IF(AND(B36="",C36=""),"",IF(C36<>"",IF(COUNTIFS(Stock!$D$4:$IP$4,B36,Stock!$D$5:$IP$5,C36)>0,SUMIFS(Stock!$D$340:$IP$340,Stock!$D$4:$IP$4,B36,Stock!$D$5:$IP$5,C36),IF(COUNTIF(Stock!$D$5:$IP$5,C36)>0,SUMIF(Stock!$D$5:$IP$5,C36,Stock!$D$340:$IP$340),SUMIF(Stock!$D$4:$IP$4,B36,Stock!$D$340:$IP$340))),SUMIF(Stock!$D$4:$IP$4,B36,Stock!$D$340:$IP$340))) -> 199 | F36: =D36-E36 -> 271 | G36: =IF(AND(B36="",C36=""),"",IF(C36<>"",IF(COUNTIFS(Stock!$D$4:$IP$4,B36,Stock!$D$5:$IP$5,C36)>0,SUMIFS(Stock!$D$32:$IP$32,Stock!$D$4:$IP$4,B36,Stock!$D$5:$IP$5,C36),IF(COUNTIF(Stock!$D$5:$IP$5,C36)>0,SUMIF(Stock!$D$5:$IP$5,C36,Stock!$D$32:$IP$32),SUMIF(Stock!$D$4:$IP$4,B36,Stock!$D$32:$IP$32))),SUMIF(Stock!$D$4:$IP$4,B36,Stock!$D$32:$IP$32))) -> 500 | I36: Spark | J36: PC-249R | K36: 94 | L36: =IF(AND(I36="",J36=""),"",IF(J36<>"",IF(COUNTIFS(Stock!$D$4:$IP$4,I36,Stock!$D$5:$IP$5,J36)>0,SUMIFS(Stock!$D$340:$IP$340,Stock!$D$4:$IP$4,I36,Stock!$D$5:$IP$5,J36),IF(COUNTIF(Stock!$D$5:$IP$5,J36)>0,SUMIF(Stock!$D$5:$IP$5,J36,Stock!$D$340:$IP$340),SUMIF(Stock!$D$4:$IP$4,I36,Stock!$D$340:$IP$340))),SUMIF(Stock!$D$4:$IP$4,I36,Stock!$D$340:$IP$340))) -> 100 | M36: =K36-L36 -> -6 | N36: =IF(AND(I36="",J36=""),"",IF(J36<>"",IF(COUNTIFS(Stock!$D$4:$IP$4,I36,Stock!$D$5:$IP$5,J36)>0,SUMIFS(Stock!$D$32:$IP$32,Stock!$D$4:$IP$4,I36,Stock!$D$5:$IP$5,J36),IF(COUNTIF(Stock!$D$5:$IP$5,J36)>0,SUMIF(Stock!$D$5:$IP$5,J36,Stock!$D$32:$IP$32),SUMIF(Stock!$D$4:$IP$4,I36,Stock!$D$32:$IP$32))),SUMIF(Stock!$D$4:$IP$4,I36,Stock!$D$32:$IP$32))) -> 100 | P36: LANCER BLOWER SWITCH | Q36: PC-926 | R36: 950 | S36: =IF(AND(P36="",Q36=""),"",IF(Q36<>"",IF(COUNTIFS(Stock!$D$4:$IP$4,P36,Stock!$D$5:$IP$5,Q36)>0,SUMIFS(Stock!$D$340:$IP$340,Stock!$D$4:$IP$4,P36,Stock!$D$5:$IP$5,Q36),IF(COUNTIF(Stock!$D$5:$IP$5,Q36)>0,SUMIF(Stock!$D$5:$IP$5,Q36,Stock!$D$340:$IP$340),SUMIF(Stock!$D$4:$IP$4,P36,Stock!$D$340:$IP$340))),SUMIF(Stock!$D$4:$IP$4,P36,Stock!$D$340:$IP$340))) -> 1100 | T36: =R36-S36 -> -150 | U36: =IF(AND(P36="",Q36=""),"",IF(Q36<>"",IF(COUNTIFS(Stock!$D$4:$IP$4,P36,Stock!$D$5:$IP$5,Q36)>0,SUMIFS(Stock!$D$32:$IP$32,Stock!$D$4:$IP$4,P36,Stock!$D$5:$IP$5,Q36),IF(COUNTIF(Stock!$D$5:$IP$5,Q36)>0,SUMIF(Stock!$D$5:$IP$5,Q36,Stock!$D$32:$IP$32),SUMIF(Stock!$D$4:$IP$4,P36,Stock!$D$32:$IP$32))),SUMIF(Stock!$D$4:$IP$4,P36,Stock!$D$32:$IP$32))) -> 1600 | V36: PC926;LANCERBLOWERSWITCH | X36: {=IF(NOT(ISNUMBER($W36)),"CHECK",IF(OR(AND(TRIM($Q36&"")<>"",INDEX(Stock!$EW$5:$FU$5,$W36)=$Q36),INDEX(Stock!$EW$4:$FU$4,$W36)=$P36),"OK","CHECK"))} -> CHECK
B37: COROLLA | C37: PC-86110 | D37: 120 | E37: =IF(AND(B37="",C37=""),"",IF(C37<>"",IF(COUNTIFS(Stock!$D$4:$IP$4,B37,Stock!$D$5:$IP$5,C37)>0,SUMIFS(Stock!$D$340:$IP$340,Stock!$D$4:$IP$4,B37,Stock!$D$5:$IP$5,C37),IF(COUNTIF(Stock!$D$5:$IP$5,C37)>0,SUMIF(Stock!$D$5:$IP$5,C37,Stock!$D$340:$IP$340),SUMIF(Stock!$D$4:$IP$4,B37,Stock!$D$340:$IP$340))),SUMIF(Stock!$D$4:$IP$4,B37,Stock!$D$340:$IP$340))) -> 55 | F37: =D37-E37 -> 65 | G37: =IF(AND(B37="",C37=""),"",IF(C37<>"",IF(COUNTIFS(Stock!$D$4:$IP$4,B37,Stock!$D$5:$IP$5,C37)>0,SUMIFS(Stock!$D$32:$IP$32,Stock!$D$4:$IP$4,B37,Stock!$D$5:$IP$5,C37),IF(COUNTIF(Stock!$D$5:$IP$5,C37)>0,SUMIF(Stock!$D$5:$IP$5,C37,Stock!$D$32:$IP$32),SUMIF(Stock!$D$4:$IP$4,B37,Stock!$D$32:$IP$32))),SUMIF(Stock!$D$4:$IP$4,B37,Stock!$D$32:$IP$32))) -> 100 | I37: Sk-Coil | J37: PC-7029 | K37: 72 | L37: =IF(AND(I37="",J37=""),"",IF(J37<>"",IF(COUNTIFS(Stock!$D$4:$IP$4,I37,Stock!$D$5:$IP$5,J37)>0,SUMIFS(Stock!$D$340:$IP$340,Stock!$D$4:$IP$4,I37,Stock!$D$5:$IP$5,J37),IF(COUNTIF(Stock!$D$5:$IP$5,J37)>0,SUMIF(Stock!$D$5:$IP$5,J37,Stock!$D$340:$IP$340),SUMIF(Stock!$D$4:$IP$4,I37,Stock!$D$340:$IP$340))),SUMIF(Stock!$D$4:$IP$4,I37,Stock!$D$340:$IP$340))) -> 281 | M37: =K37-L37 -> -209 | N37: =IF(AND(I37="",J37=""),"",IF(J37<>"",IF(COUNTIFS(Stock!$D$4:$IP$4,I37,Stock!$D$5:$IP$5,J37)>0,SUMIFS(Stock!$D$32:$IP$32,Stock!$D$4:$IP$4,I37,Stock!$D$5:$IP$5,J37),IF(COUNTIF(Stock!$D$5:$IP$5,J37)>0,SUMIF(Stock!$D$5:$IP$5,J37,Stock!$D$32:$IP$32),SUMIF(Stock!$D$4:$IP$4,I37,Stock!$D$32:$IP$32))),SUMIF(Stock!$D$4:$IP$4,I37,Stock!$D$32:$IP$32))) -> 281 | P37: CONCORD A/C SWITCH | S37: =IF(AND(P37="",Q37=""),"",IF(Q37<>"",IF(COUNTIFS(Stock!$D$4:$IP$4,P37,Stock!$D$5:$IP$5,Q37)>0,SUMIFS(Stock!$D$340:$IP$340,Stock!$D$4:$IP$4,P37,Stock!$D$5:$IP$5,Q37),IF(COUNTIF(Stock!$D$5:$IP$5,Q37)>0,SUMIF(Stock!$D$5:$IP$5,Q37,Stock!$D$340:$IP$340),SUMIF(Stock!$D$4:$IP$4,P37,Stock!$D$340:$IP$340))),SUMIF(Stock!$D$4:$IP$4,P37,Stock!$D$340:$IP$340))) -> 0 | T37: =R37-S37 -> 0 | U37: =IF(AND(P37="",Q37=""),"",IF(Q37<>"",IF(COUNTIFS(Stock!$D$4:$IP$4,P37,Stock!$D$5:$IP$5,Q37)>0,SUMIFS(Stock!$D$32:$IP$32,Stock!$D$4:$IP$4,P37,Stock!$D$5:$IP$5,Q37),IF(COUNTIF(Stock!$D$5:$IP$5,Q37)>0,SUMIF(Stock!$D$5:$IP$5,Q37,Stock!$D$32:$IP$32),SUMIF(Stock!$D$4:$IP$4,P37,Stock!$D$32:$IP$32))),SUMIF(Stock!$D$4:$IP$4,P37,Stock!$D$32:$IP$32))) -> 100 | V37: CONCORDDIGITALSWITCHWITHOUTRESISTANCEWIRE | X37: {=IF(NOT(ISNUMBER($W37)),"CHECK",IF(OR(AND(TRIM($Q37&"")<>"",INDEX(Stock!$EW$5:$FU$5,$W37)=$Q37),INDEX(Stock!$EW$4:$FU$4,$W37)=$P37),"OK","CHECK"))} -> CHECK
B38: OPEL CORSA | C38: PC-86038 | D38: 40 | E38: =IF(AND(B38="",C38=""),"",IF(C38<>"",IF(COUNTIFS(Stock!$D$4:$IP$4,B38,Stock!$D$5:$IP$5,C38)>0,SUMIFS(Stock!$D$340:$IP$340,Stock!$D$4:$IP$4,B38,Stock!$D$5:$IP$5,C38),IF(COUNTIF(Stock!$D$5:$IP$5,C38)>0,SUMIF(Stock!$D$5:$IP$5,C38,Stock!$D$340:$IP$340),SUMIF(Stock!$D$4:$IP$4,B38,Stock!$D$340:$IP$340))),SUMIF(Stock!$D$4:$IP$4,B38,Stock!$D$340:$IP$340))) -> 20 | F38: =D38-E38 -> 20 | G38: =IF(AND(B38="",C38=""),"",IF(C38<>"",IF(COUNTIFS(Stock!$D$4:$IP$4,B38,Stock!$D$5:$IP$5,C38)>0,SUMIFS(Stock!$D$32:$IP$32,Stock!$D$4:$IP$4,B38,Stock!$D$5:$IP$5,C38),IF(COUNTIF(Stock!$D$5:$IP$5,C38)>0,SUMIF(Stock!$D$5:$IP$5,C38,Stock!$D$32:$IP$32),SUMIF(Stock!$D$4:$IP$4,B38,Stock!$D$32:$IP$32))),SUMIF(Stock!$D$4:$IP$4,B38,Stock!$D$32:$IP$32))) -> 100 | I38: Honda City-III | J38: NA | L38: =IF(AND(I38="",J38=""),"",IF(J38<>"",IF(COUNTIFS(Stock!$D$4:$IP$4,I38,Stock!$D$5:$IP$5,J38)>0,SUMIFS(Stock!$D$340:$IP$340,Stock!$D$4:$IP$4,I38,Stock!$D$5:$IP$5,J38),IF(COUNTIF(Stock!$D$5:$IP$5,J38)>0,SUMIF(Stock!$D$5:$IP$5,J38,Stock!$D$340:$IP$340),SUMIF(Stock!$D$4:$IP$4,I38,Stock!$D$340:$IP$340))),SUMIF(Stock!$D$4:$IP$4,I38,Stock!$D$340:$IP$340))) -> 0 | M38: =K38-L38 -> 0 | N38: =IF(AND(I38="",J38=""),"",IF(J38<>"",IF(COUNTIFS(Stock!$D$4:$IP$4,I38,Stock!$D$5:$IP$5,J38)>0,SUMIFS(Stock!$D$32:$IP$32,Stock!$D$4:$IP$4,I38,Stock!$D$5:$IP$5,J38),IF(COUNTIF(Stock!$D$5:$IP$5,J38)>0,SUMIF(Stock!$D$5:$IP$5,J38,Stock!$D$32:$IP$32),SUMIF(Stock!$D$4:$IP$4,I38,Stock!$D$32:$IP$32))),SUMIF(Stock!$D$4:$IP$4,I38,Stock!$D$32:$IP$32))) -> 0 | P38: CONCORD RESISTANCE | R38: 100 | S38: =IF(AND(P38="",Q38=""),"",IF(Q38<>"",IF(COUNTIFS(Stock!$D$4:$IP$4,P38,Stock!$D$5:$IP$5,Q38)>0,SUMIFS(Stock!$D$340:$IP$340,Stock!$D$4:$IP$4,P38,Stock!$D$5:$IP$5,Q38),IF(COUNTIF(Stock!$D$5:$IP$5,Q38)>0,SUMIF(Stock!$D$5:$IP$5,Q38,Stock!$D$340:$IP$340),SUMIF(Stock!$D$4:$IP$4,P38,Stock!$D$340:$IP$340))),SUMIF(Stock!$D$4:$IP$4,P38,Stock!$D$340:$IP$340))) -> 0 | T38: =R38-S38 -> 100 | U38: =IF(AND(P38="",Q38=""),"",IF(Q38<>"",IF(COUNTIFS(Stock!$D$4:$IP$4,P38,Stock!$D$5:$IP$5,Q38)>0,SUMIFS(Stock!$D$32:$IP$32,Stock!$D$4:$IP$4,P38,Stock!$D$5:$IP$5,Q38),IF(COUNTIF(Stock!$D$5:$IP$5,Q38)>0,SUMIF(Stock!$D$5:$IP$5,Q38,Stock!$D$32:$IP$32),SUMIF(Stock!$D$4:$IP$4,P38,Stock!$D$32:$IP$32))),SUMIF(Stock!$D$4:$IP$4,P38,Stock!$D$32:$IP$32))) -> 0 | V38: CONCORDRESISTANCE | X38: {=IF(NOT(ISNUMBER($W38)),"CHECK",IF(OR(AND(TRIM($Q38&"")<>"",INDEX(Stock!$EW$5:$FU$5,$W38)=$Q38),INDEX(Stock!$EW$4:$FU$4,$W38)=$P38),"OK","CHECK"))} -> CHECK
B39: PALIO | C39: PC-86039 | D39: 20 | E39: =IF(AND(B39="",C39=""),"",IF(C39<>"",IF(COUNTIFS(Stock!$D$4:$IP$4,B39,Stock!$D$5:$IP$5,C39)>0,SUMIFS(Stock!$D$340:$IP$340,Stock!$D$4:$IP$4,B39,Stock!$D$5:$IP$5,C39),IF(COUNTIF(Stock!$D$5:$IP$5,C39)>0,SUMIF(Stock!$D$5:$IP$5,C39,Stock!$D$340:$IP$340),SUMIF(Stock!$D$4:$IP$4,B39,Stock!$D$340:$IP$340))),SUMIF(Stock!$D$4:$IP$4,B39,Stock!$D$340:$IP$340))) -> 15 | F39: =D39-E39 -> 5 | G39: =IF(AND(B39="",C39=""),"",IF(C39<>"",IF(COUNTIFS(Stock!$D$4:$IP$4,B39,Stock!$D$5:$IP$5,C39)>0,SUMIFS(Stock!$D$32:$IP$32,Stock!$D$4:$IP$4,B39,Stock!$D$5:$IP$5,C39),IF(COUNTIF(Stock!$D$5:$IP$5,C39)>0,SUMIF(Stock!$D$5:$IP$5,C39,Stock!$D$32:$IP$32),SUMIF(Stock!$D$4:$IP$4,B39,Stock!$D$32:$IP$32))),SUMIF(Stock!$D$4:$IP$4,B39,Stock!$D$32:$IP$32))) -> 200 | I39: Honda CRV | J39: PC-113R | K39: 43 | L39: =IF(AND(I39="",J39=""),"",IF(J39<>"",IF(COUNTIFS(Stock!$D$4:$IP$4,I39,Stock!$D$5:$IP$5,J39)>0,SUMIFS(Stock!$D$340:$IP$340,Stock!$D$4:$IP$4,I39,Stock!$D$5:$IP$5,J39),IF(COUNTIF(Stock!$D$5:$IP$5,J39)>0,SUMIF(Stock!$D$5:$IP$5,J39,Stock!$D$340:$IP$340),SUMIF(Stock!$D$4:$IP$4,I39,Stock!$D$340:$IP$340))),SUMIF(Stock!$D$4:$IP$4,I39,Stock!$D$340:$IP$340))) -> 25 | M39: =K39-L39 -> 18 | N39: =IF(AND(I39="",J39=""),"",IF(J39<>"",IF(COUNTIFS(Stock!$D$4:$IP$4,I39,Stock!$D$5:$IP$5,J39)>0,SUMIFS(Stock!$D$32:$IP$32,Stock!$D$4:$IP$4,I39,Stock!$D$5:$IP$5,J39),IF(COUNTIF(Stock!$D$5:$IP$5,J39)>0,SUMIF(Stock!$D$5:$IP$5,J39,Stock!$D$32:$IP$32),SUMIF(Stock!$D$4:$IP$4,I39,Stock!$D$32:$IP$32))),SUMIF(Stock!$D$4:$IP$4,I39,Stock!$D$32:$IP$32))) -> 79
B40: CIELO | D40: 24 | E40: =IF(AND(B40="",C40=""),"",IF(C40<>"",IF(COUNTIFS(Stock!$D$4:$IP$4,B40,Stock!$D$5:$IP$5,C40)>0,SUMIFS(Stock!$D$340:$IP$340,Stock!$D$4:$IP$4,B40,Stock!$D$5:$IP$5,C40),IF(COUNTIF(Stock!$D$5:$IP$5,C40)>0,SUMIF(Stock!$D$5:$IP$5,C40,Stock!$D$340:$IP$340),SUMIF(Stock!$D$4:$IP$4,B40,Stock!$D$340:$IP$340))),SUMIF(Stock!$D$4:$IP$4,B40,Stock!$D$340:$IP$340))) -> 25 | F40: =D40-E40 -> -1 | G40: =IF(AND(B40="",C40=""),"",IF(C40<>"",IF(COUNTIFS(Stock!$D$4:$IP$4,B40,Stock!$D$5:$IP$5,C40)>0,SUMIFS(Stock!$D$32:$IP$32,Stock!$D$4:$IP$4,B40,Stock!$D$5:$IP$5,C40),IF(COUNTIF(Stock!$D$5:$IP$5,C40)>0,SUMIF(Stock!$D$5:$IP$5,C40,Stock!$D$32:$IP$32),SUMIF(Stock!$D$4:$IP$4,B40,Stock!$D$32:$IP$32))),SUMIF(Stock!$D$4:$IP$4,B40,Stock!$D$32:$IP$32))) -> 25 | I40: Swift | J40: PC-211 | K40: 4 | L40: =IF(AND(I40="",J40=""),"",IF(J40<>"",IF(COUNTIFS(Stock!$D$4:$IP$4,I40,Stock!$D$5:$IP$5,J40)>0,SUMIFS(Stock!$D$340:$IP$340,Stock!$D$4:$IP$4,I40,Stock!$D$5:$IP$5,J40),IF(COUNTIF(Stock!$D$5:$IP$5,J40)>0,SUMIF(Stock!$D$5:$IP$5,J40,Stock!$D$340:$IP$340),SUMIF(Stock!$D$4:$IP$4,I40,Stock!$D$340:$IP$340))),SUMIF(Stock!$D$4:$IP$4,I40,Stock!$D$340:$IP$340))) -> 4 | M40: =K40-L40 -> 0 | N40: =IF(AND(I40="",J40=""),"",IF(J40<>"",IF(COUNTIFS(Stock!$D$4:$IP$4,I40,Stock!$D$5:$IP$5,J40)>0,SUMIFS(Stock!$D$32:$IP$32,Stock!$D$4:$IP$4,I40,Stock!$D$5:$IP$5,J40),IF(COUNTIF(Stock!$D$5:$IP$5,J40)>0,SUMIF(Stock!$D$5:$IP$5,J40,Stock!$D$32:$IP$32),SUMIF(Stock!$D$4:$IP$4,I40,Stock!$D$32:$IP$32))),SUMIF(Stock!$D$4:$IP$4,I40,Stock!$D$32:$IP$32))) -> 4
B41: OPTRA | C41: PC-86186 | D41: 75 | E41: =IF(AND(B41="",C41=""),"",IF(C41<>"",IF(COUNTIFS(Stock!$D$4:$IP$4,B41,Stock!$D$5:$IP$5,C41)>0,SUMIFS(Stock!$D$340:$IP$340,Stock!$D$4:$IP$4,B41,Stock!$D$5:$IP$5,C41),IF(COUNTIF(Stock!$D$5:$IP$5,C41)>0,SUMIF(Stock!$D$5:$IP$5,C41,Stock!$D$340:$IP$340),SUMIF(Stock!$D$4:$IP$4,B41,Stock!$D$340:$IP$340))),SUMIF(Stock!$D$4:$IP$4,B41,Stock!$D$340:$IP$340))) -> 30 | F41: =D41-E41 -> 45 | G41: =IF(AND(B41="",C41=""),"",IF(C41<>"",IF(COUNTIFS(Stock!$D$4:$IP$4,B41,Stock!$D$5:$IP$5,C41)>0,SUMIFS(Stock!$D$32:$IP$32,Stock!$D$4:$IP$4,B41,Stock!$D$5:$IP$5,C41),IF(COUNTIF(Stock!$D$5:$IP$5,C41)>0,SUMIF(Stock!$D$5:$IP$5,C41,Stock!$D$32:$IP$32),SUMIF(Stock!$D$4:$IP$4,B41,Stock!$D$32:$IP$32))),SUMIF(Stock!$D$4:$IP$4,B41,Stock!$D$32:$IP$32))) -> 75 | I41: INDICA | L41: =IF(AND(I41="",J41=""),"",IF(J41<>"",IF(COUNTIFS(Stock!$D$4:$IP$4,I41,Stock!$D$5:$IP$5,J41)>0,SUMIFS(Stock!$D$340:$IP$340,Stock!$D$4:$IP$4,I41,Stock!$D$5:$IP$5,J41),IF(COUNTIF(Stock!$D$5:$IP$5,J41)>0,SUMIF(Stock!$D$5:$IP$5,J41,Stock!$D$340:$IP$340),SUMIF(Stock!$D$4:$IP$4,I41,Stock!$D$340:$IP$340))),SUMIF(Stock!$D$4:$IP$4,I41,Stock!$D$340:$IP$340))) -> 0 | M41: =K41-L41 -> 0 | N41: =IF(AND(I41="",J41=""),"",IF(J41<>"",IF(COUNTIFS(Stock!$D$4:$IP$4,I41,Stock!$D$5:$IP$5,J41)>0,SUMIFS(Stock!$D$32:$IP$32,Stock!$D$4:$IP$4,I41,Stock!$D$5:$IP$5,J41),IF(COUNTIF(Stock!$D$5:$IP$5,J41)>0,SUMIF(Stock!$D$5:$IP$5,J41,Stock!$D$32:$IP$32),SUMIF(Stock!$D$4:$IP$4,I41,Stock!$D$32:$IP$32))),SUMIF(Stock!$D$4:$IP$4,I41,Stock!$D$32:$IP$32))) -> 0 | P41: Drier | R41: Challan (pcs) <=283 | S41: Stock Sold (<=283) | T41: Gap | V41: Match Key(s) | W41: Stock col / guard
B42: GETZ | C42: PC-86027B | D42: 95 | E42: =IF(AND(B42="",C42=""),"",IF(C42<>"",IF(COUNTIFS(Stock!$D$4:$IP$4,B42,Stock!$D$5:$IP$5,C42)>0,SUMIFS(Stock!$D$340:$IP$340,Stock!$D$4:$IP$4,B42,Stock!$D$5:$IP$5,C42),IF(COUNTIF(Stock!$D$5:$IP$5,C42)>0,SUMIF(Stock!$D$5:$IP$5,C42,Stock!$D$340:$IP$340),SUMIF(Stock!$D$4:$IP$4,B42,Stock!$D$340:$IP$340))),SUMIF(Stock!$D$4:$IP$4,B42,Stock!$D$340:$IP$340))) -> 55 | F42: =D42-E42 -> 40 | G42: =IF(AND(B42="",C42=""),"",IF(C42<>"",IF(COUNTIFS(Stock!$D$4:$IP$4,B42,Stock!$D$5:$IP$5,C42)>0,SUMIFS(Stock!$D$32:$IP$32,Stock!$D$4:$IP$4,B42,Stock!$D$5:$IP$5,C42),IF(COUNTIF(Stock!$D$5:$IP$5,C42)>0,SUMIF(Stock!$D$5:$IP$5,C42,Stock!$D$32:$IP$32),SUMIF(Stock!$D$4:$IP$4,B42,Stock!$D$32:$IP$32))),SUMIF(Stock!$D$4:$IP$4,B42,Stock!$D$32:$IP$32))) -> 100 | I42: Indica Behr | K42: 250 | L42: =IF(AND(I42="",J42=""),"",IF(J42<>"",IF(COUNTIFS(Stock!$D$4:$IP$4,I42,Stock!$D$5:$IP$5,J42)>0,SUMIFS(Stock!$D$340:$IP$340,Stock!$D$4:$IP$4,I42,Stock!$D$5:$IP$5,J42),IF(COUNTIF(Stock!$D$5:$IP$5,J42)>0,SUMIF(Stock!$D$5:$IP$5,J42,Stock!$D$340:$IP$340),SUMIF(Stock!$D$4:$IP$4,I42,Stock!$D$340:$IP$340))),SUMIF(Stock!$D$4:$IP$4,I42,Stock!$D$340:$IP$340))) -> 150 | M42: =K42-L42 -> 100 | N42: =IF(AND(I42="",J42=""),"",IF(J42<>"",IF(COUNTIFS(Stock!$D$4:$IP$4,I42,Stock!$D$5:$IP$5,J42)>0,SUMIFS(Stock!$D$32:$IP$32,Stock!$D$4:$IP$4,I42,Stock!$D$5:$IP$5,J42),IF(COUNTIF(Stock!$D$5:$IP$5,J42)>0,SUMIF(Stock!$D$5:$IP$5,J42,Stock!$D$32:$IP$32),SUMIF(Stock!$D$4:$IP$4,I42,Stock!$D$32:$IP$32))),SUMIF(Stock!$D$4:$IP$4,I42,Stock!$D$32:$IP$32))) -> 624 | P42: Indica Behr | Q42: PC-8115 | R42: 250 | S42: =IF(AND(P42="",Q42=""),"",IF(Q42<>"",IF(COUNTIFS(Stock!$D$4:$IP$4,P42,Stock!$D$5:$IP$5,Q42)>0,SUMIFS(Stock!$D$340:$IP$340,Stock!$D$4:$IP$4,P42,Stock!$D$5:$IP$5,Q42),IF(COUNTIF(Stock!$D$5:$IP$5,Q42)>0,SUMIF(Stock!$D$5:$IP$5,Q42,Stock!$D$340:$IP$340),SUMIF(Stock!$D$4:$IP$4,P42,Stock!$D$340:$IP$340))),SUMIF(Stock!$D$4:$IP$4,P42,Stock!$D$340:$IP$340))) -> 150 | T42: =R42-S42 -> 100 | U42: =IF(AND(P42="",Q42=""),"",IF(Q42<>"",IF(COUNTIFS(Stock!$D$4:$IP$4,P42,Stock!$D$5:$IP$5,Q42)>0,SUMIFS(Stock!$D$32:$IP$32,Stock!$D$4:$IP$4,P42,Stock!$D$5:$IP$5,Q42),IF(COUNTIF(Stock!$D$5:$IP$5,Q42)>0,SUMIF(Stock!$D$5:$IP$5,Q42,Stock!$D$32:$IP$32),SUMIF(Stock!$D$4:$IP$4,P42,Stock!$D$32:$IP$32))),SUMIF(Stock!$D$4:$IP$4,P42,Stock!$D$32:$IP$32))) -> 624 | V42: PC8115
B43: HONDA CRV | C43: PC-86101 | D43: 100 | E43: =IF(AND(B43="",C43=""),"",IF(C43<>"",IF(COUNTIFS(Stock!$D$4:$IP$4,B43,Stock!$D$5:$IP$5,C43)>0,SUMIFS(Stock!$D$340:$IP$340,Stock!$D$4:$IP$4,B43,Stock!$D$5:$IP$5,C43),IF(COUNTIF(Stock!$D$5:$IP$5,C43)>0,SUMIF(Stock!$D$5:$IP$5,C43,Stock!$D$340:$IP$340),SUMIF(Stock!$D$4:$IP$4,B43,Stock!$D$340:$IP$340))),SUMIF(Stock!$D$4:$IP$4,B43,Stock!$D$340:$IP$340))) -> 50 | F43: =D43-E43 -> 50 | G43: =IF(AND(B43="",C43=""),"",IF(C43<>"",IF(COUNTIFS(Stock!$D$4:$IP$4,B43,Stock!$D$5:$IP$5,C43)>0,SUMIFS(Stock!$D$32:$IP$32,Stock!$D$4:$IP$4,B43,Stock!$D$5:$IP$5,C43),IF(COUNTIF(Stock!$D$5:$IP$5,C43)>0,SUMIF(Stock!$D$5:$IP$5,C43,Stock!$D$32:$IP$32),SUMIF(Stock!$D$4:$IP$4,B43,Stock!$D$32:$IP$32))),SUMIF(Stock!$D$4:$IP$4,B43,Stock!$D$32:$IP$32))) -> 100 | I43: QUALIS | J43: PC-8904R | K43: 48 | L43: =IF(AND(I43="",J43=""),"",IF(J43<>"",IF(COUNTIFS(Stock!$D$4:$IP$4,I43,Stock!$D$5:$IP$5,J43)>0,SUMIFS(Stock!$D$340:$IP$340,Stock!$D$4:$IP$4,I43,Stock!$D$5:$IP$5,J43),IF(COUNTIF(Stock!$D$5:$IP$5,J43)>0,SUMIF(Stock!$D$5:$IP$5,J43,Stock!$D$340:$IP$340),SUMIF(Stock!$D$4:$IP$4,I43,Stock!$D$340:$IP$340))),SUMIF(Stock!$D$4:$IP$4,I43,Stock!$D$340:$IP$340))) -> 0 | M43: =K43-L43 -> 48 | N43: =IF(AND(I43="",J43=""),"",IF(J43<>"",IF(COUNTIFS(Stock!$D$4:$IP$4,I43,Stock!$D$5:$IP$5,J43)>0,SUMIFS(Stock!$D$32:$IP$32,Stock!$D$4:$IP$4,I43,Stock!$D$5:$IP$5,J43),IF(COUNTIF(Stock!$D$5:$IP$5,J43)>0,SUMIF(Stock!$D$5:$IP$5,J43,Stock!$D$32:$IP$32),SUMIF(Stock!$D$4:$IP$4,I43,Stock!$D$32:$IP$32))),SUMIF(Stock!$D$4:$IP$4,I43,Stock!$D$32:$IP$32))) -> 102 | P43: AVEO | Q43: PC-8797 | R43: 50 | S43: =IF(AND(P43="",Q43=""),"",IF(Q43<>"",IF(COUNTIFS(Stock!$D$4:$IP$4,P43,Stock!$D$5:$IP$5,Q43)>0,SUMIFS(Stock!$D$340:$IP$340,Stock!$D$4:$IP$4,P43,Stock!$D$5:$IP$5,Q43),IF(COUNTIF(Stock!$D$5:$IP$5,Q43)>0,SUMIF(Stock!$D$5:$IP$5,Q43,Stock!$D$340:$IP$340),SUMIF(Stock!$D$4:$IP$4,P43,Stock!$D$340:$IP$340))),SUMIF(Stock!$D$4:$IP$4,P43,Stock!$D$340:$IP$340))) -> 0 | T43: =R43-S43 -> 50 | U43: =IF(AND(P43="",Q43=""),"",IF(Q43<>"",IF(COUNTIFS(Stock!$D$4:$IP$4,P43,Stock!$D$5:$IP$5,Q43)>0,SUMIFS(Stock!$D$32:$IP$32,Stock!$D$4:$IP$4,P43,Stock!$D$5:$IP$5,Q43),IF(COUNTIF(Stock!$D$5:$IP$5,Q43)>0,SUMIF(Stock!$D$5:$IP$5,Q43,Stock!$D$32:$IP$32),SUMIF(Stock!$D$4:$IP$4,P43,Stock!$D$32:$IP$32))),SUMIF(Stock!$D$4:$IP$4,P43,Stock!$D$32:$IP$32))) -> 50 | V43: PC8797
B44: VARNA-PETROL | C44: PC-86027 | D44: 20 | E44: =IF(AND(B44="",C44=""),"",IF(C44<>"",IF(COUNTIFS(Stock!$D$4:$IP$4,B44,Stock!$D$5:$IP$5,C44)>0,SUMIFS(Stock!$D$340:$IP$340,Stock!$D$4:$IP$4,B44,Stock!$D$5:$IP$5,C44),IF(COUNTIF(Stock!$D$5:$IP$5,C44)>0,SUMIF(Stock!$D$5:$IP$5,C44,Stock!$D$340:$IP$340),SUMIF(Stock!$D$4:$IP$4,B44,Stock!$D$340:$IP$340))),SUMIF(Stock!$D$4:$IP$4,B44,Stock!$D$340:$IP$340))) -> 15 | F44: =D44-E44 -> 5 | G44: =IF(AND(B44="",C44=""),"",IF(C44<>"",IF(COUNTIFS(Stock!$D$4:$IP$4,B44,Stock!$D$5:$IP$5,C44)>0,SUMIFS(Stock!$D$32:$IP$32,Stock!$D$4:$IP$4,B44,Stock!$D$5:$IP$5,C44),IF(COUNTIF(Stock!$D$5:$IP$5,C44)>0,SUMIF(Stock!$D$5:$IP$5,C44,Stock!$D$32:$IP$32),SUMIF(Stock!$D$4:$IP$4,B44,Stock!$D$32:$IP$32))),SUMIF(Stock!$D$4:$IP$4,B44,Stock!$D$32:$IP$32))) -> 100 | I44: Safari | J44: PC-8083 | K44: 108 | L44: =IF(AND(I44="",J44=""),"",IF(J44<>"",IF(COUNTIFS(Stock!$D$4:$IP$4,I44,Stock!$D$5:$IP$5,J44)>0,SUMIFS(Stock!$D$340:$IP$340,Stock!$D$4:$IP$4,I44,Stock!$D$5:$IP$5,J44),IF(COUNTIF(Stock!$D$5:$IP$5,J44)>0,SUMIF(Stock!$D$5:$IP$5,J44,Stock!$D$340:$IP$340),SUMIF(Stock!$D$4:$IP$4,I44,Stock!$D$340:$IP$340))),SUMIF(Stock!$D$4:$IP$4,I44,Stock!$D$340:$IP$340))) -> 54 | M44: =K44-L44 -> 54 | N44: =IF(AND(I44="",J44=""),"",IF(J44<>"",IF(COUNTIFS(Stock!$D$4:$IP$4,I44,Stock!$D$5:$IP$5,J44)>0,SUMIFS(Stock!$D$32:$IP$32,Stock!$D$4:$IP$4,I44,Stock!$D$5:$IP$5,J44),IF(COUNTIF(Stock!$D$5:$IP$5,J44)>0,SUMIF(Stock!$D$5:$IP$5,J44,Stock!$D$32:$IP$32),SUMIF(Stock!$D$4:$IP$4,I44,Stock!$D$32:$IP$32))),SUMIF(Stock!$D$4:$IP$4,I44,Stock!$D$32:$IP$32))) -> 108 | P44: Matiz | Q44: PC-8096 | R44: 343 | S44: =IF(AND(P44="",Q44=""),"",IF(Q44<>"",IF(COUNTIFS(Stock!$D$4:$IP$4,P44,Stock!$D$5:$IP$5,Q44)>0,SUMIFS(Stock!$D$340:$IP$340,Stock!$D$4:$IP$4,P44,Stock!$D$5:$IP$5,Q44),IF(COUNTIF(Stock!$D$5:$IP$5,Q44)>0,SUMIF(Stock!$D$5:$IP$5,Q44,Stock!$D$340:$IP$340),SUMIF(Stock!$D$4:$IP$4,P44,Stock!$D$340:$IP$340))),SUMIF(Stock!$D$4:$IP$4,P44,Stock!$D$340:$IP$340))) -> 25 | T44: =R44-S44 -> 318 | U44: =IF(AND(P44="",Q44=""),"",IF(Q44<>"",IF(COUNTIFS(Stock!$D$4:$IP$4,P44,Stock!$D$5:$IP$5,Q44)>0,SUMIFS(Stock!$D$32:$IP$32,Stock!$D$4:$IP$4,P44,Stock!$D$5:$IP$5,Q44),IF(COUNTIF(Stock!$D$5:$IP$5,Q44)>0,SUMIF(Stock!$D$5:$IP$5,Q44,Stock!$D$32:$IP$32),SUMIF(Stock!$D$4:$IP$4,P44,Stock!$D$32:$IP$32))),SUMIF(Stock!$D$4:$IP$4,P44,Stock!$D$32:$IP$32))) -> 243 | V44: PC8096OLD
B45: ELANTRA | C45: PC-86066 | D45: 55 | E45: =IF(AND(B45="",C45=""),"",IF(C45<>"",IF(COUNTIFS(Stock!$D$4:$IP$4,B45,Stock!$D$5:$IP$5,C45)>0,SUMIFS(Stock!$D$340:$IP$340,Stock!$D$4:$IP$4,B45,Stock!$D$5:$IP$5,C45),IF(COUNTIF(Stock!$D$5:$IP$5,C45)>0,SUMIF(Stock!$D$5:$IP$5,C45,Stock!$D$340:$IP$340),SUMIF(Stock!$D$4:$IP$4,B45,Stock!$D$340:$IP$340))),SUMIF(Stock!$D$4:$IP$4,B45,Stock!$D$340:$IP$340))) -> 50 | F45: =D45-E45 -> 5 | G45: =IF(AND(B45="",C45=""),"",IF(C45<>"",IF(COUNTIFS(Stock!$D$4:$IP$4,B45,Stock!$D$5:$IP$5,C45)>0,SUMIFS(Stock!$D$32:$IP$32,Stock!$D$4:$IP$4,B45,Stock!$D$5:$IP$5,C45),IF(COUNTIF(Stock!$D$5:$IP$5,C45)>0,SUMIF(Stock!$D$5:$IP$5,C45,Stock!$D$32:$IP$32),SUMIF(Stock!$D$4:$IP$4,B45,Stock!$D$32:$IP$32))),SUMIF(Stock!$D$4:$IP$4,B45,Stock!$D$32:$IP$32))) -> 100 | I45: SUMO VECTA | J45: PC-8905 | K45: 144 | L45: =IF(AND(I45="",J45=""),"",IF(J45<>"",IF(COUNTIFS(Stock!$D$4:$IP$4,I45,Stock!$D$5:$IP$5,J45)>0,SUMIFS(Stock!$D$340:$IP$340,Stock!$D$4:$IP$4,I45,Stock!$D$5:$IP$5,J45),IF(COUNTIF(Stock!$D$5:$IP$5,J45)>0,SUMIF(Stock!$D$5:$IP$5,J45,Stock!$D$340:$IP$340),SUMIF(Stock!$D$4:$IP$4,I45,Stock!$D$340:$IP$340))),SUMIF(Stock!$D$4:$IP$4,I45,Stock!$D$340:$IP$340))) -> 0 | M45: =K45-L45 -> 144 | N45: =IF(AND(I45="",J45=""),"",IF(J45<>"",IF(COUNTIFS(Stock!$D$4:$IP$4,I45,Stock!$D$5:$IP$5,J45)>0,SUMIFS(Stock!$D$32:$IP$32,Stock!$D$4:$IP$4,I45,Stock!$D$5:$IP$5,J45),IF(COUNTIF(Stock!$D$5:$IP$5,J45)>0,SUMIF(Stock!$D$5:$IP$5,J45,Stock!$D$32:$IP$32),SUMIF(Stock!$D$4:$IP$4,I45,Stock!$D$32:$IP$32))),SUMIF(Stock!$D$4:$IP$4,I45,Stock!$D$32:$IP$32))) -> 54 | P45: Matiz-NEW | Q45: PC-8096 | S45: =IF(AND(P45="",Q45=""),"",IF(Q45<>"",IF(COUNTIFS(Stock!$D$4:$IP$4,P45,Stock!$D$5:$IP$5,Q45)>0,SUMIFS(Stock!$D$340:$IP$340,Stock!$D$4:$IP$4,P45,Stock!$D$5:$IP$5,Q45),IF(COUNTIF(Stock!$D$5:$IP$5,Q45)>0,SUMIF(Stock!$D$5:$IP$5,Q45,Stock!$D$340:$IP$340),SUMIF(Stock!$D$4:$IP$4,P45,Stock!$D$340:$IP$340))),SUMIF(Stock!$D$4:$IP$4,P45,Stock!$D$340:$IP$340))) -> 318 | T45: =R45-S45 -> -318 | U45: =IF(AND(P45="",Q45=""),"",IF(Q45<>"",IF(COUNTIFS(Stock!$D$4:$IP$4,P45,Stock!$D$5:$IP$5,Q45)>0,SUMIFS(Stock!$D$32:$IP$32,Stock!$D$4:$IP$4,P45,Stock!$D$5:$IP$5,Q45),IF(COUNTIF(Stock!$D$5:$IP$5,Q45)>0,SUMIF(Stock!$D$5:$IP$5,Q45,Stock!$D$32:$IP$32),SUMIF(Stock!$D$4:$IP$4,P45,Stock!$D$32:$IP$32))),SUMIF(Stock!$D$4:$IP$4,P45,Stock!$D$32:$IP$32))) -> 100 | V45: PC8096NEW
B46: AMBASDOR | C46: PC-86041 | D46: 170 | E46: =IF(AND(B46="",C46=""),"",IF(C46<>"",IF(COUNTIFS(Stock!$D$4:$IP$4,B46,Stock!$D$5:$IP$5,C46)>0,SUMIFS(Stock!$D$340:$IP$340,Stock!$D$4:$IP$4,B46,Stock!$D$5:$IP$5,C46),IF(COUNTIF(Stock!$D$5:$IP$5,C46)>0,SUMIF(Stock!$D$5:$IP$5,C46,Stock!$D$340:$IP$340),SUMIF(Stock!$D$4:$IP$4,B46,Stock!$D$340:$IP$340))),SUMIF(Stock!$D$4:$IP$4,B46,Stock!$D$340:$IP$340))) -> 200 | F46: =D46-E46 -> -30 | G46: =IF(AND(B46="",C46=""),"",IF(C46<>"",IF(COUNTIFS(Stock!$D$4:$IP$4,B46,Stock!$D$5:$IP$5,C46)>0,SUMIFS(Stock!$D$32:$IP$32,Stock!$D$4:$IP$4,B46,Stock!$D$5:$IP$5,C46),IF(COUNTIF(Stock!$D$5:$IP$5,C46)>0,SUMIF(Stock!$D$5:$IP$5,C46,Stock!$D$32:$IP$32),SUMIF(Stock!$D$4:$IP$4,B46,Stock!$D$32:$IP$32))),SUMIF(Stock!$D$4:$IP$4,B46,Stock!$D$32:$IP$32))) -> 200 | I46: Tavera | J46: PC-012 | K46: 213 | L46: =IF(AND(I46="",J46=""),"",IF(J46<>"",IF(COUNTIFS(Stock!$D$4:$IP$4,I46,Stock!$D$5:$IP$5,J46)>0,SUMIFS(Stock!$D$340:$IP$340,Stock!$D$4:$IP$4,I46,Stock!$D$5:$IP$5,J46),IF(COUNTIF(Stock!$D$5:$IP$5,J46)>0,SUMIF(Stock!$D$5:$IP$5,J46,Stock!$D$340:$IP$340),SUMIF(Stock!$D$4:$IP$4,I46,Stock!$D$340:$IP$340))),SUMIF(Stock!$D$4:$IP$4,I46,Stock!$D$340:$IP$340))) -> 106 | M46: =K46-L46 -> 107 | N46: =IF(AND(I46="",J46=""),"",IF(J46<>"",IF(COUNTIFS(Stock!$D$4:$IP$4,I46,Stock!$D$5:$IP$5,J46)>0,SUMIFS(Stock!$D$32:$IP$32,Stock!$D$4:$IP$4,I46,Stock!$D$5:$IP$5,J46),IF(COUNTIF(Stock!$D$5:$IP$5,J46)>0,SUMIF(Stock!$D$5:$IP$5,J46,Stock!$D$32:$IP$32),SUMIF(Stock!$D$4:$IP$4,I46,Stock!$D$32:$IP$32))),SUMIF(Stock!$D$4:$IP$4,I46,Stock!$D$32:$IP$32))) -> 214 | P46: Honda City | Q46: PC-8020 | R46: 450 | S46: =IF(AND(P46="",Q46=""),"",IF(Q46<>"",IF(COUNTIFS(Stock!$D$4:$IP$4,P46,Stock!$D$5:$IP$5,Q46)>0,SUMIFS(Stock!$D$340:$IP$340,Stock!$D$4:$IP$4,P46,Stock!$D$5:$IP$5,Q46),IF(COUNTIF(Stock!$D$5:$IP$5,Q46)>0,SUMIF(Stock!$D$5:$IP$5,Q46,Stock!$D$340:$IP$340),SUMIF(Stock!$D$4:$IP$4,P46,Stock!$D$340:$IP$340))),SUMIF(Stock!$D$4:$IP$4,P46,Stock!$D$340:$IP$340))) -> 475 | T46: =R46-S46 -> -25 | U46: =IF(AND(P46="",Q46=""),"",IF(Q46<>"",IF(COUNTIFS(Stock!$D$4:$IP$4,P46,Stock!$D$5:$IP$5,Q46)>0,SUMIFS(Stock!$D$32:$IP$32,Stock!$D$4:$IP$4,P46,Stock!$D$5:$IP$5,Q46),IF(COUNTIF(Stock!$D$5:$IP$5,Q46)>0,SUMIF(Stock!$D$5:$IP$5,Q46,Stock!$D$32:$IP$32),SUMIF(Stock!$D$4:$IP$4,P46,Stock!$D$32:$IP$32))),SUMIF(Stock!$D$4:$IP$4,P46,Stock!$D$32:$IP$32))) -> 475 | V46: PC8020;HONDACITY
B47: MATIZ | C47: PC-86042 | D47: 45 | E47: =IF(AND(B47="",C47=""),"",IF(C47<>"",IF(COUNTIFS(Stock!$D$4:$IP$4,B47,Stock!$D$5:$IP$5,C47)>0,SUMIFS(Stock!$D$340:$IP$340,Stock!$D$4:$IP$4,B47,Stock!$D$5:$IP$5,C47),IF(COUNTIF(Stock!$D$5:$IP$5,C47)>0,SUMIF(Stock!$D$5:$IP$5,C47,Stock!$D$340:$IP$340),SUMIF(Stock!$D$4:$IP$4,B47,Stock!$D$340:$IP$340))),SUMIF(Stock!$D$4:$IP$4,B47,Stock!$D$340:$IP$340))) -> 20 | F47: =D47-E47 -> 25 | G47: =IF(AND(B47="",C47=""),"",IF(C47<>"",IF(COUNTIFS(Stock!$D$4:$IP$4,B47,Stock!$D$5:$IP$5,C47)>0,SUMIFS(Stock!$D$32:$IP$32,Stock!$D$4:$IP$4,B47,Stock!$D$5:$IP$5,C47),IF(COUNTIF(Stock!$D$5:$IP$5,C47)>0,SUMIF(Stock!$D$5:$IP$5,C47,Stock!$D$32:$IP$32),SUMIF(Stock!$D$4:$IP$4,B47,Stock!$D$32:$IP$32))),SUMIF(Stock!$D$4:$IP$4,B47,Stock!$D$32:$IP$32))) -> 50 | I47: Varna | J47: PC-207 (ORIGIN PC-203) | K47: 11 | L47: =IF(AND(I47="",J47=""),"",IF(J47<>"",IF(COUNTIFS(Stock!$D$4:$IP$4,I47,Stock!$D$5:$IP$5,J47)>0,SUMIFS(Stock!$D$340:$IP$340,Stock!$D$4:$IP$4,I47,Stock!$D$5:$IP$5,J47),IF(COUNTIF(Stock!$D$5:$IP$5,J47)>0,SUMIF(Stock!$D$5:$IP$5,J47,Stock!$D$340:$IP$340),SUMIF(Stock!$D$4:$IP$4,I47,Stock!$D$340:$IP$340))),SUMIF(Stock!$D$4:$IP$4,I47,Stock!$D$340:$IP$340))) -> 11 | M47: =K47-L47 -> 0 | N47: =IF(AND(I47="",J47=""),"",IF(J47<>"",IF(COUNTIFS(Stock!$D$4:$IP$4,I47,Stock!$D$5:$IP$5,J47)>0,SUMIFS(Stock!$D$32:$IP$32,Stock!$D$4:$IP$4,I47,Stock!$D$5:$IP$5,J47),IF(COUNTIF(Stock!$D$5:$IP$5,J47)>0,SUMIF(Stock!$D$5:$IP$5,J47,Stock!$D$32:$IP$32),SUMIF(Stock!$D$4:$IP$4,I47,Stock!$D$32:$IP$32))),SUMIF(Stock!$D$4:$IP$4,I47,Stock!$D$32:$IP$32))) -> 11 | P47: Esteem-R12 | Q47: PC-8005 | R47: 4500 | S47: =IF(AND(P47="",Q47=""),"",IF(Q47<>"",IF(COUNTIFS(Stock!$D$4:$IP$4,P47,Stock!$D$5:$IP$5,Q47)>0,SUMIFS(Stock!$D$340:$IP$340,Stock!$D$4:$IP$4,P47,Stock!$D$5:$IP$5,Q47),IF(COUNTIF(Stock!$D$5:$IP$5,Q47)>0,SUMIF(Stock!$D$5:$IP$5,Q47,Stock!$D$340:$IP$340),SUMIF(Stock!$D$4:$IP$4,P47,Stock!$D$340:$IP$340))),SUMIF(Stock!$D$4:$IP$4,P47,Stock!$D$340:$IP$340))) -> 1500 | T47: =R47-S47 -> 3000 | U47: =IF(AND(P47="",Q47=""),"",IF(Q47<>"",IF(COUNTIFS(Stock!$D$4:$IP$4,P47,Stock!$D$5:$IP$5,Q47)>0,SUMIFS(Stock!$D$32:$IP$32,Stock!$D$4:$IP$4,P47,Stock!$D$5:$IP$5,Q47),IF(COUNTIF(Stock!$D$5:$IP$5,Q47)>0,SUMIF(Stock!$D$5:$IP$5,Q47,Stock!$D$32:$IP$32),SUMIF(Stock!$D$4:$IP$4,P47,Stock!$D$32:$IP$32))),SUMIF(Stock!$D$4:$IP$4,P47,Stock!$D$32:$IP$32))) -> 4450 | V47: PC8005
B48: LOGAN | C48: PC-86087 | D48: 25 | E48: =IF(AND(B48="",C48=""),"",IF(C48<>"",IF(COUNTIFS(Stock!$D$4:$IP$4,B48,Stock!$D$5:$IP$5,C48)>0,SUMIFS(Stock!$D$340:$IP$340,Stock!$D$4:$IP$4,B48,Stock!$D$5:$IP$5,C48),IF(COUNTIF(Stock!$D$5:$IP$5,C48)>0,SUMIF(Stock!$D$5:$IP$5,C48,Stock!$D$340:$IP$340),SUMIF(Stock!$D$4:$IP$4,B48,Stock!$D$340:$IP$340))),SUMIF(Stock!$D$4:$IP$4,B48,Stock!$D$340:$IP$340))) -> 15 | F48: =D48-E48 -> 10 | G48: =IF(AND(B48="",C48=""),"",IF(C48<>"",IF(COUNTIFS(Stock!$D$4:$IP$4,B48,Stock!$D$5:$IP$5,C48)>0,SUMIFS(Stock!$D$32:$IP$32,Stock!$D$4:$IP$4,B48,Stock!$D$5:$IP$5,C48),IF(COUNTIF(Stock!$D$5:$IP$5,C48)>0,SUMIF(Stock!$D$5:$IP$5,C48,Stock!$D$32:$IP$32),SUMIF(Stock!$D$4:$IP$4,B48,Stock!$D$32:$IP$32))),SUMIF(Stock!$D$4:$IP$4,B48,Stock!$D$32:$IP$32))) -> 25 | I48: MITSUBISHI PAJERO | L48: =IF(AND(I48="",J48=""),"",IF(J48<>"",IF(COUNTIFS(Stock!$D$4:$IP$4,I48,Stock!$D$5:$IP$5,J48)>0,SUMIFS(Stock!$D$340:$IP$340,Stock!$D$4:$IP$4,I48,Stock!$D$5:$IP$5,J48),IF(COUNTIF(Stock!$D$5:$IP$5,J48)>0,SUMIF(Stock!$D$5:$IP$5,J48,Stock!$D$340:$IP$340),SUMIF(Stock!$D$4:$IP$4,I48,Stock!$D$340:$IP$340))),SUMIF(Stock!$D$4:$IP$4,I48,Stock!$D$340:$IP$340))) -> 0 | M48: =K48-L48 -> 0 | N48: =IF(AND(I48="",J48=""),"",IF(J48<>"",IF(COUNTIFS(Stock!$D$4:$IP$4,I48,Stock!$D$5:$IP$5,J48)>0,SUMIFS(Stock!$D$32:$IP$32,Stock!$D$4:$IP$4,I48,Stock!$D$5:$IP$5,J48),IF(COUNTIF(Stock!$D$5:$IP$5,J48)>0,SUMIF(Stock!$D$5:$IP$5,J48,Stock!$D$32:$IP$32),SUMIF(Stock!$D$4:$IP$4,I48,Stock!$D$32:$IP$32))),SUMIF(Stock!$D$4:$IP$4,I48,Stock!$D$32:$IP$32))) -> 0 | P48: Esteem-R134A | Q48: PC-8006 | R48: 3074 | S48: =IF(AND(P48="",Q48=""),"",IF(Q48<>"",IF(COUNTIFS(Stock!$D$4:$IP$4,P48,Stock!$D$5:$IP$5,Q48)>0,SUMIFS(Stock!$D$340:$IP$340,Stock!$D$4:$IP$4,P48,Stock!$D$5:$IP$5,Q48),IF(COUNTIF(Stock!$D$5:$IP$5,Q48)>0,SUMIF(Stock!$D$5:$IP$5,Q48,Stock!$D$340:$IP$340),SUMIF(Stock!$D$4:$IP$4,P48,Stock!$D$340:$IP$340))),SUMIF(Stock!$D$4:$IP$4,P48,Stock!$D$340:$IP$340))) -> 2196 | T48: =R48-S48 -> 878 | U48: =IF(AND(P48="",Q48=""),"",IF(Q48<>"",IF(COUNTIFS(Stock!$D$4:$IP$4,P48,Stock!$D$5:$IP$5,Q48)>0,SUMIFS(Stock!$D$32:$IP$32,Stock!$D$4:$IP$4,P48,Stock!$D$5:$IP$5,Q48),IF(COUNTIF(Stock!$D$5:$IP$5,Q48)>0,SUMIF(Stock!$D$5:$IP$5,Q48,Stock!$D$32:$IP$32),SUMIF(Stock!$D$4:$IP$4,P48,Stock!$D$32:$IP$32))),SUMIF(Stock!$D$4:$IP$4,P48,Stock!$D$32:$IP$32))) -> 3247 | V48: PC8006;ESTEEMR134A
B49: VOLVO | C49: PC-86255B | D49: 25 | E49: =IF(AND(B49="",C49=""),"",IF(C49<>"",IF(COUNTIFS(Stock!$D$4:$IP$4,B49,Stock!$D$5:$IP$5,C49)>0,SUMIFS(Stock!$D$340:$IP$340,Stock!$D$4:$IP$4,B49,Stock!$D$5:$IP$5,C49),IF(COUNTIF(Stock!$D$5:$IP$5,C49)>0,SUMIF(Stock!$D$5:$IP$5,C49,Stock!$D$340:$IP$340),SUMIF(Stock!$D$4:$IP$4,B49,Stock!$D$340:$IP$340))),SUMIF(Stock!$D$4:$IP$4,B49,Stock!$D$340:$IP$340))) -> 25 | F49: =D49-E49 -> 0 | G49: =IF(AND(B49="",C49=""),"",IF(C49<>"",IF(COUNTIFS(Stock!$D$4:$IP$4,B49,Stock!$D$5:$IP$5,C49)>0,SUMIFS(Stock!$D$32:$IP$32,Stock!$D$4:$IP$4,B49,Stock!$D$5:$IP$5,C49),IF(COUNTIF(Stock!$D$5:$IP$5,C49)>0,SUMIF(Stock!$D$5:$IP$5,C49,Stock!$D$32:$IP$32),SUMIF(Stock!$D$4:$IP$4,B49,Stock!$D$32:$IP$32))),SUMIF(Stock!$D$4:$IP$4,B49,Stock!$D$32:$IP$32))) -> 25 | I49: Wagan R / Alto | J49: PC-208 | K49: 388 | L49: =IF(AND(I49="",J49=""),"",IF(J49<>"",IF(COUNTIFS(Stock!$D$4:$IP$4,I49,Stock!$D$5:$IP$5,J49)>0,SUMIFS(Stock!$D$340:$IP$340,Stock!$D$4:$IP$4,I49,Stock!$D$5:$IP$5,J49),IF(COUNTIF(Stock!$D$5:$IP$5,J49)>0,SUMIF(Stock!$D$5:$IP$5,J49,Stock!$D$340:$IP$340),SUMIF(Stock!$D$4:$IP$4,I49,Stock!$D$340:$IP$340))),SUMIF(Stock!$D$4:$IP$4,I49,Stock!$D$340:$IP$340))) -> 100 | M49: =K49-L49 -> 288 | N49: =IF(AND(I49="",J49=""),"",IF(J49<>"",IF(COUNTIFS(Stock!$D$4:$IP$4,I49,Stock!$D$5:$IP$5,J49)>0,SUMIFS(Stock!$D$32:$IP$32,Stock!$D$4:$IP$4,I49,Stock!$D$5:$IP$5,J49),IF(COUNTIF(Stock!$D$5:$IP$5,J49)>0,SUMIF(Stock!$D$5:$IP$5,J49,Stock!$D$32:$IP$32),SUMIF(Stock!$D$4:$IP$4,I49,Stock!$D$32:$IP$32))),SUMIF(Stock!$D$4:$IP$4,I49,Stock!$D$32:$IP$32))) -> 400 | P49: Universal | Q49: PC-6001 | R49: 14098 | S49: =IF(AND(P49="",Q49=""),"",IF(Q49<>"",IF(COUNTIFS(Stock!$D$4:$IP$4,P49,Stock!$D$5:$IP$5,Q49)>0,SUMIFS(Stock!$D$340:$IP$340,Stock!$D$4:$IP$4,P49,Stock!$D$5:$IP$5,Q49),IF(COUNTIF(Stock!$D$5:$IP$5,Q49)>0,SUMIF(Stock!$D$5:$IP$5,Q49,Stock!$D$340:$IP$340),SUMIF(Stock!$D$4:$IP$4,P49,Stock!$D$340:$IP$340))),SUMIF(Stock!$D$4:$IP$4,P49,Stock!$D$340:$IP$340))) -> 8200 | T49: =R49-S49 -> 5898 | U49: =IF(AND(P49="",Q49=""),"",IF(Q49<>"",IF(COUNTIFS(Stock!$D$4:$IP$4,P49,Stock!$D$5:$IP$5,Q49)>0,SUMIFS(Stock!$D$32:$IP$32,Stock!$D$4:$IP$4,P49,Stock!$D$5:$IP$5,Q49),IF(COUNTIF(Stock!$D$5:$IP$5,Q49)>0,SUMIF(Stock!$D$5:$IP$5,Q49,Stock!$D$32:$IP$32),SUMIF(Stock!$D$4:$IP$4,P49,Stock!$D$32:$IP$32))),SUMIF(Stock!$D$4:$IP$4,P49,Stock!$D$32:$IP$32))) -> 14200 | V49: PC6001
B50: VISTA | C50: PC-86276 | D50: 1 | E50: =IF(AND(B50="",C50=""),"",IF(C50<>"",IF(COUNTIFS(Stock!$D$4:$IP$4,B50,Stock!$D$5:$IP$5,C50)>0,SUMIFS(Stock!$D$340:$IP$340,Stock!$D$4:$IP$4,B50,Stock!$D$5:$IP$5,C50),IF(COUNTIF(Stock!$D$5:$IP$5,C50)>0,SUMIF(Stock!$D$5:$IP$5,C50,Stock!$D$340:$IP$340),SUMIF(Stock!$D$4:$IP$4,B50,Stock!$D$340:$IP$340))),SUMIF(Stock!$D$4:$IP$4,B50,Stock!$D$340:$IP$340))) -> 1 | F50: =D50-E50 -> 0 | G50: =IF(AND(B50="",C50=""),"",IF(C50<>"",IF(COUNTIFS(Stock!$D$4:$IP$4,B50,Stock!$D$5:$IP$5,C50)>0,SUMIFS(Stock!$D$32:$IP$32,Stock!$D$4:$IP$4,B50,Stock!$D$5:$IP$5,C50),IF(COUNTIF(Stock!$D$5:$IP$5,C50)>0,SUMIF(Stock!$D$5:$IP$5,C50,Stock!$D$32:$IP$32),SUMIF(Stock!$D$4:$IP$4,B50,Stock!$D$32:$IP$32))),SUMIF(Stock!$D$4:$IP$4,B50,Stock!$D$32:$IP$32))) -> 0 | I50: Zen Delphi R-12 | J50: PC-050R | K50: 84 | L50: =IF(AND(I50="",J50=""),"",IF(J50<>"",IF(COUNTIFS(Stock!$D$4:$IP$4,I50,Stock!$D$5:$IP$5,J50)>0,SUMIFS(Stock!$D$340:$IP$340,Stock!$D$4:$IP$4,I50,Stock!$D$5:$IP$5,J50),IF(COUNTIF(Stock!$D$5:$IP$5,J50)>0,SUMIF(Stock!$D$5:$IP$5,J50,Stock!$D$340:$IP$340),SUMIF(Stock!$D$4:$IP$4,I50,Stock!$D$340:$IP$340))),SUMIF(Stock!$D$4:$IP$4,I50,Stock!$D$340:$IP$340))) -> 73 | M50: =K50-L50 -> 11 | N50: =IF(AND(I50="",J50=""),"",IF(J50<>"",IF(COUNTIFS(Stock!$D$4:$IP$4,I50,Stock!$D$5:$IP$5,J50)>0,SUMIFS(Stock!$D$32:$IP$32,Stock!$D$4:$IP$4,I50,Stock!$D$5:$IP$5,J50),IF(COUNTIF(Stock!$D$5:$IP$5,J50)>0,SUMIF(Stock!$D$5:$IP$5,J50,Stock!$D$32:$IP$32),SUMIF(Stock!$D$4:$IP$4,I50,Stock!$D$32:$IP$32))),SUMIF(Stock!$D$4:$IP$4,I50,Stock!$D$32:$IP$32))) -> 107 | P50: Universal | Q50: PC-6002 | R50: 500 | S50: =IF(AND(P50="",Q50=""),"",IF(Q50<>"",IF(COUNTIFS(Stock!$D$4:$IP$4,P50,Stock!$D$5:$IP$5,Q50)>0,SUMIFS(Stock!$D$340:$IP$340,Stock!$D$4:$IP$4,P50,Stock!$D$5:$IP$5,Q50),IF(COUNTIF(Stock!$D$5:$IP$5,Q50)>0,SUMIF(Stock!$D$5:$IP$5,Q50,Stock!$D$340:$IP$340),SUMIF(Stock!$D$4:$IP$4,P50,Stock!$D$340:$IP$340))),SUMIF(Stock!$D$4:$IP$4,P50,Stock!$D$340:$IP$340))) -> 0 | T50: =R50-S50 -> 500 | U50: =IF(AND(P50="",Q50=""),"",IF(Q50<>"",IF(COUNTIFS(Stock!$D$4:$IP$4,P50,Stock!$D$5:$IP$5,Q50)>0,SUMIFS(Stock!$D$32:$IP$32,Stock!$D$4:$IP$4,P50,Stock!$D$5:$IP$5,Q50),IF(COUNTIF(Stock!$D$5:$IP$5,Q50)>0,SUMIF(Stock!$D$5:$IP$5,Q50,Stock!$D$32:$IP$32),SUMIF(Stock!$D$4:$IP$4,P50,Stock!$D$32:$IP$32))),SUMIF(Stock!$D$4:$IP$4,P50,Stock!$D$32:$IP$32))) -> 500 | V50: PC6002
B51: INDICA DICOR | E51: =IF(AND(B51="",C51=""),"",IF(C51<>"",IF(COUNTIFS(Stock!$D$4:$IP$4,B51,Stock!$D$5:$IP$5,C51)>0,SUMIFS(Stock!$D$340:$IP$340,Stock!$D$4:$IP$4,B51,Stock!$D$5:$IP$5,C51),IF(COUNTIF(Stock!$D$5:$IP$5,C51)>0,SUMIF(Stock!$D$5:$IP$5,C51,Stock!$D$340:$IP$340),SUMIF(Stock!$D$4:$IP$4,B51,Stock!$D$340:$IP$340))),SUMIF(Stock!$D$4:$IP$4,B51,Stock!$D$340:$IP$340))) -> 1 | F51: =D51-E51 -> -1 | G51: =IF(AND(B51="",C51=""),"",IF(C51<>"",IF(COUNTIFS(Stock!$D$4:$IP$4,B51,Stock!$D$5:$IP$5,C51)>0,SUMIFS(Stock!$D$32:$IP$32,Stock!$D$4:$IP$4,B51,Stock!$D$5:$IP$5,C51),IF(COUNTIF(Stock!$D$5:$IP$5,C51)>0,SUMIF(Stock!$D$5:$IP$5,C51,Stock!$D$32:$IP$32),SUMIF(Stock!$D$4:$IP$4,B51,Stock!$D$32:$IP$32))),SUMIF(Stock!$D$4:$IP$4,B51,Stock!$D$32:$IP$32))) -> 0 | I51: Zen Delphi R-134a | J51: PC-204 | K51: 94 | L51: =IF(AND(I51="",J51=""),"",IF(J51<>"",IF(COUNTIFS(Stock!$D$4:$IP$4,I51,Stock!$D$5:$IP$5,J51)>0,SUMIFS(Stock!$D$340:$IP$340,Stock!$D$4:$IP$4,I51,Stock!$D$5:$IP$5,J51),IF(COUNTIF(Stock!$D$5:$IP$5,J51)>0,SUMIF(Stock!$D$5:$IP$5,J51,Stock!$D$340:$IP$340),SUMIF(Stock!$D$4:$IP$4,I51,Stock!$D$340:$IP$340))),SUMIF(Stock!$D$4:$IP$4,I51,Stock!$D$340:$IP$340))) -> 85 | M51: =K51-L51 -> 9 | N51: =IF(AND(I51="",J51=""),"",IF(J51<>"",IF(COUNTIFS(Stock!$D$4:$IP$4,I51,Stock!$D$5:$IP$5,J51)>0,SUMIFS(Stock!$D$32:$IP$32,Stock!$D$4:$IP$4,I51,Stock!$D$5:$IP$5,J51),IF(COUNTIF(Stock!$D$5:$IP$5,J51)>0,SUMIF(Stock!$D$5:$IP$5,J51,Stock!$D$32:$IP$32),SUMIF(Stock!$D$4:$IP$4,I51,Stock!$D$32:$IP$32))),SUMIF(Stock!$D$4:$IP$4,I51,Stock!$D$32:$IP$32))) -> 125 | P51: BUS-UNI | Q51: PC-61020 | R51: 200 | S51: =IF(AND(P51="",Q51=""),"",IF(Q51<>"",IF(COUNTIFS(Stock!$D$4:$IP$4,P51,Stock!$D$5:$IP$5,Q51)>0,SUMIFS(Stock!$D$340:$IP$340,Stock!$D$4:$IP$4,P51,Stock!$D$5:$IP$5,Q51),IF(COUNTIF(Stock!$D$5:$IP$5,Q51)>0,SUMIF(Stock!$D$5:$IP$5,Q51,Stock!$D$340:$IP$340),SUMIF(Stock!$D$4:$IP$4,P51,Stock!$D$340:$IP$340))),SUMIF(Stock!$D$4:$IP$4,P51,Stock!$D$340:$IP$340))) -> 0 | T51: =R51-S51 -> 200 | U51: =IF(AND(P51="",Q51=""),"",IF(Q51<>"",IF(COUNTIFS(Stock!$D$4:$IP$4,P51,Stock!$D$5:$IP$5,Q51)>0,SUMIFS(Stock!$D$32:$IP$32,Stock!$D$4:$IP$4,P51,Stock!$D$5:$IP$5,Q51),IF(COUNTIF(Stock!$D$5:$IP$5,Q51)>0,SUMIF(Stock!$D$5:$IP$5,Q51,Stock!$D$32:$IP$32),SUMIF(Stock!$D$4:$IP$4,P51,Stock!$D$32:$IP$32))),SUMIF(Stock!$D$4:$IP$4,P51,Stock!$D$32:$IP$32))) -> 200 | V51: PC61020
B52: ENDEAVOUR | C52: PC-86277 | D52: 2 | E52: =IF(AND(B52="",C52=""),"",IF(C52<>"",IF(COUNTIFS(Stock!$D$4:$IP$4,B52,Stock!$D$5:$IP$5,C52)>0,SUMIFS(Stock!$D$340:$IP$340,Stock!$D$4:$IP$4,B52,Stock!$D$5:$IP$5,C52),IF(COUNTIF(Stock!$D$5:$IP$5,C52)>0,SUMIF(Stock!$D$5:$IP$5,C52,Stock!$D$340:$IP$340),SUMIF(Stock!$D$4:$IP$4,B52,Stock!$D$340:$IP$340))),SUMIF(Stock!$D$4:$IP$4,B52,Stock!$D$340:$IP$340))) -> 1 | F52: =D52-E52 -> 1 | G52: =IF(AND(B52="",C52=""),"",IF(C52<>"",IF(COUNTIFS(Stock!$D$4:$IP$4,B52,Stock!$D$5:$IP$5,C52)>0,SUMIFS(Stock!$D$32:$IP$32,Stock!$D$4:$IP$4,B52,Stock!$D$5:$IP$5,C52),IF(COUNTIF(Stock!$D$5:$IP$5,C52)>0,SUMIF(Stock!$D$5:$IP$5,C52,Stock!$D$32:$IP$32),SUMIF(Stock!$D$4:$IP$4,B52,Stock!$D$32:$IP$32))),SUMIF(Stock!$D$4:$IP$4,B52,Stock!$D$32:$IP$32))) -> 0 | I52: Zen R-134-SUBROS | J52: PC-8082 | K52: 101 | L52: =IF(AND(I52="",J52=""),"",IF(J52<>"",IF(COUNTIFS(Stock!$D$4:$IP$4,I52,Stock!$D$5:$IP$5,J52)>0,SUMIFS(Stock!$D$340:$IP$340,Stock!$D$4:$IP$4,I52,Stock!$D$5:$IP$5,J52),IF(COUNTIF(Stock!$D$5:$IP$5,J52)>0,SUMIF(Stock!$D$5:$IP$5,J52,Stock!$D$340:$IP$340),SUMIF(Stock!$D$4:$IP$4,I52,Stock!$D$340:$IP$340))),SUMIF(Stock!$D$4:$IP$4,I52,Stock!$D$340:$IP$340))) -> 81 | M52: =K52-L52 -> 20 | N52: =IF(AND(I52="",J52=""),"",IF(J52<>"",IF(COUNTIFS(Stock!$D$4:$IP$4,I52,Stock!$D$5:$IP$5,J52)>0,SUMIFS(Stock!$D$32:$IP$32,Stock!$D$4:$IP$4,I52,Stock!$D$5:$IP$5,J52),IF(COUNTIF(Stock!$D$5:$IP$5,J52)>0,SUMIF(Stock!$D$5:$IP$5,J52,Stock!$D$32:$IP$32),SUMIF(Stock!$D$4:$IP$4,I52,Stock!$D$32:$IP$32))),SUMIF(Stock!$D$4:$IP$4,I52,Stock!$D$32:$IP$32))) -> 105 | P52: Toyota Qualis | Q52: PC-8008 | R52: 525 | S52: =IF(AND(P52="",Q52=""),"",IF(Q52<>"",IF(COUNTIFS(Stock!$D$4:$IP$4,P52,Stock!$D$5:$IP$5,Q52)>0,SUMIFS(Stock!$D$340:$IP$340,Stock!$D$4:$IP$4,P52,Stock!$D$5:$IP$5,Q52),IF(COUNTIF(Stock!$D$5:$IP$5,Q52)>0,SUMIF(Stock!$D$5:$IP$5,Q52,Stock!$D$340:$IP$340),SUMIF(Stock!$D$4:$IP$4,P52,Stock!$D$340:$IP$340))),SUMIF(Stock!$D$4:$IP$4,P52,Stock!$D$340:$IP$340))) -> 524 | T52: =R52-S52 -> 1 | U52: =IF(AND(P52="",Q52=""),"",IF(Q52<>"",IF(COUNTIFS(Stock!$D$4:$IP$4,P52,Stock!$D$5:$IP$5,Q52)>0,SUMIFS(Stock!$D$32:$IP$32,Stock!$D$4:$IP$4,P52,Stock!$D$5:$IP$5,Q52),IF(COUNTIF(Stock!$D$5:$IP$5,Q52)>0,SUMIF(Stock!$D$5:$IP$5,Q52,Stock!$D$32:$IP$32),SUMIF(Stock!$D$4:$IP$4,P52,Stock!$D$32:$IP$32))),SUMIF(Stock!$D$4:$IP$4,P52,Stock!$D$32:$IP$32))) -> 525 | V52: PC8008
B53: FEISTA | C53: PC-86272 | D53: 1 | E53: =IF(AND(B53="",C53=""),"",IF(C53<>"",IF(COUNTIFS(Stock!$D$4:$IP$4,B53,Stock!$D$5:$IP$5,C53)>0,SUMIFS(Stock!$D$340:$IP$340,Stock!$D$4:$IP$4,B53,Stock!$D$5:$IP$5,C53),IF(COUNTIF(Stock!$D$5:$IP$5,C53)>0,SUMIF(Stock!$D$5:$IP$5,C53,Stock!$D$340:$IP$340),SUMIF(Stock!$D$4:$IP$4,B53,Stock!$D$340:$IP$340))),SUMIF(Stock!$D$4:$IP$4,B53,Stock!$D$340:$IP$340))) -> 1 | F53: =D53-E53 -> 0 | G53: =IF(AND(B53="",C53=""),"",IF(C53<>"",IF(COUNTIFS(Stock!$D$4:$IP$4,B53,Stock!$D$5:$IP$5,C53)>0,SUMIFS(Stock!$D$32:$IP$32,Stock!$D$4:$IP$4,B53,Stock!$D$5:$IP$5,C53),IF(COUNTIF(Stock!$D$5:$IP$5,C53)>0,SUMIF(Stock!$D$5:$IP$5,C53,Stock!$D$32:$IP$32),SUMIF(Stock!$D$4:$IP$4,B53,Stock!$D$32:$IP$32))),SUMIF(Stock!$D$4:$IP$4,B53,Stock!$D$32:$IP$32))) -> 0 | I53: 848L MICROBUS COIL | K53: 5 | L53: =IF(AND(I53="",J53=""),"",IF(J53<>"",IF(COUNTIFS(Stock!$D$4:$IP$4,I53,Stock!$D$5:$IP$5,J53)>0,SUMIFS(Stock!$D$340:$IP$340,Stock!$D$4:$IP$4,I53,Stock!$D$5:$IP$5,J53),IF(COUNTIF(Stock!$D$5:$IP$5,J53)>0,SUMIF(Stock!$D$5:$IP$5,J53,Stock!$D$340:$IP$340),SUMIF(Stock!$D$4:$IP$4,I53,Stock!$D$340:$IP$340))),SUMIF(Stock!$D$4:$IP$4,I53,Stock!$D$340:$IP$340))) -> 5 | M53: =K53-L53 -> 0 | N53: =IF(AND(I53="",J53=""),"",IF(J53<>"",IF(COUNTIFS(Stock!$D$4:$IP$4,I53,Stock!$D$5:$IP$5,J53)>0,SUMIFS(Stock!$D$32:$IP$32,Stock!$D$4:$IP$4,I53,Stock!$D$5:$IP$5,J53),IF(COUNTIF(Stock!$D$5:$IP$5,J53)>0,SUMIF(Stock!$D$5:$IP$5,J53,Stock!$D$32:$IP$32),SUMIF(Stock!$D$4:$IP$4,I53,Stock!$D$32:$IP$32))),SUMIF(Stock!$D$4:$IP$4,I53,Stock!$D$32:$IP$32))) -> 5 | P53: Daewoo Cielo | Q53: PC-8263 | S53: =IF(AND(P53="",Q53=""),"",IF(Q53<>"",IF(COUNTIFS(Stock!$D$4:$IP$4,P53,Stock!$D$5:$IP$5,Q53)>0,SUMIFS(Stock!$D$340:$IP$340,Stock!$D$4:$IP$4,P53,Stock!$D$5:$IP$5,Q53),IF(COUNTIF(Stock!$D$5:$IP$5,Q53)>0,SUMIF(Stock!$D$5:$IP$5,Q53,Stock!$D$340:$IP$340),SUMIF(Stock!$D$4:$IP$4,P53,Stock!$D$340:$IP$340))),SUMIF(Stock!$D$4:$IP$4,P53,Stock!$D$340:$IP$340))) -> 0 | T53: =R53-S53 -> 0 | U53: =IF(AND(P53="",Q53=""),"",IF(Q53<>"",IF(COUNTIFS(Stock!$D$4:$IP$4,P53,Stock!$D$5:$IP$5,Q53)>0,SUMIFS(Stock!$D$32:$IP$32,Stock!$D$4:$IP$4,P53,Stock!$D$5:$IP$5,Q53),IF(COUNTIF(Stock!$D$5:$IP$5,Q53)>0,SUMIF(Stock!$D$5:$IP$5,Q53,Stock!$D$32:$IP$32),SUMIF(Stock!$D$4:$IP$4,P53,Stock!$D$32:$IP$32))),SUMIF(Stock!$D$4:$IP$4,P53,Stock!$D$32:$IP$32))) -> 80 | V53: PC8263
B54: H.CITY-T-5 | C54: PC-86278 | D54: 1 | E54: =IF(AND(B54="",C54=""),"",IF(C54<>"",IF(COUNTIFS(Stock!$D$4:$IP$4,B54,Stock!$D$5:$IP$5,C54)>0,SUMIFS(Stock!$D$340:$IP$340,Stock!$D$4:$IP$4,B54,Stock!$D$5:$IP$5,C54),IF(COUNTIF(Stock!$D$5:$IP$5,C54)>0,SUMIF(Stock!$D$5:$IP$5,C54,Stock!$D$340:$IP$340),SUMIF(Stock!$D$4:$IP$4,B54,Stock!$D$340:$IP$340))),SUMIF(Stock!$D$4:$IP$4,B54,Stock!$D$340:$IP$340))) -> 1 | F54: =D54-E54 -> 0 | G54: =IF(AND(B54="",C54=""),"",IF(C54<>"",IF(COUNTIFS(Stock!$D$4:$IP$4,B54,Stock!$D$5:$IP$5,C54)>0,SUMIFS(Stock!$D$32:$IP$32,Stock!$D$4:$IP$4,B54,Stock!$D$5:$IP$5,C54),IF(COUNTIF(Stock!$D$5:$IP$5,C54)>0,SUMIF(Stock!$D$5:$IP$5,C54,Stock!$D$32:$IP$32),SUMIF(Stock!$D$4:$IP$4,B54,Stock!$D$32:$IP$32))),SUMIF(Stock!$D$4:$IP$4,B54,Stock!$D$32:$IP$32))) -> 0 | L54: =IF(AND(I54="",J54=""),"",IF(J54<>"",IF(COUNTIFS(Stock!$D$4:$IP$4,I54,Stock!$D$5:$IP$5,J54)>0,SUMIFS(Stock!$D$340:$IP$340,Stock!$D$4:$IP$4,I54,Stock!$D$5:$IP$5,J54),IF(COUNTIF(Stock!$D$5:$IP$5,J54)>0,SUMIF(Stock!$D$5:$IP$5,J54,Stock!$D$340:$IP$340),SUMIF(Stock!$D$4:$IP$4,I54,Stock!$D$340:$IP$340))),SUMIF(Stock!$D$4:$IP$4,I54,Stock!$D$340:$IP$340))) | N54: =IF(AND(I54="",J54=""),"",IF(J54<>"",IF(COUNTIFS(Stock!$D$4:$IP$4,I54,Stock!$D$5:$IP$5,J54)>0,SUMIFS(Stock!$D$32:$IP$32,Stock!$D$4:$IP$4,I54,Stock!$D$5:$IP$5,J54),IF(COUNTIF(Stock!$D$5:$IP$5,J54)>0,SUMIF(Stock!$D$5:$IP$5,J54,Stock!$D$32:$IP$32),SUMIF(Stock!$D$4:$IP$4,I54,Stock!$D$32:$IP$32))),SUMIF(Stock!$D$4:$IP$4,I54,Stock!$D$32:$IP$32))) | P54: Ford | Q54: PC-8321 | R54: 170 | S54: =IF(AND(P54="",Q54=""),"",IF(Q54<>"",IF(COUNTIFS(Stock!$D$4:$IP$4,P54,Stock!$D$5:$IP$5,Q54)>0,SUMIFS(Stock!$D$340:$IP$340,Stock!$D$4:$IP$4,P54,Stock!$D$5:$IP$5,Q54),IF(COUNTIF(Stock!$D$5:$IP$5,Q54)>0,SUMIF(Stock!$D$5:$IP$5,Q54,Stock!$D$340:$IP$340),SUMIF(Stock!$D$4:$IP$4,P54,Stock!$D$340:$IP$340))),SUMIF(Stock!$D$4:$IP$4,P54,Stock!$D$340:$IP$340))) -> 130 | T54: =R54-S54 -> 40 | U54: =IF(AND(P54="",Q54=""),"",IF(Q54<>"",IF(COUNTIFS(Stock!$D$4:$IP$4,P54,Stock!$D$5:$IP$5,Q54)>0,SUMIFS(Stock!$D$32:$IP$32,Stock!$D$4:$IP$4,P54,Stock!$D$5:$IP$5,Q54),IF(COUNTIF(Stock!$D$5:$IP$5,Q54)>0,SUMIF(Stock!$D$5:$IP$5,Q54,Stock!$D$32:$IP$32),SUMIF(Stock!$D$4:$IP$4,P54,Stock!$D$32:$IP$32))),SUMIF(Stock!$D$4:$IP$4,P54,Stock!$D$32:$IP$32))) -> 260 | V54: PC8321
B55: FUSION | C55: PC-86271 | D55: 1 | E55: =IF(AND(B55="",C55=""),"",IF(C55<>"",IF(COUNTIFS(Stock!$D$4:$IP$4,B55,Stock!$D$5:$IP$5,C55)>0,SUMIFS(Stock!$D$340:$IP$340,Stock!$D$4:$IP$4,B55,Stock!$D$5:$IP$5,C55),IF(COUNTIF(Stock!$D$5:$IP$5,C55)>0,SUMIF(Stock!$D$5:$IP$5,C55,Stock!$D$340:$IP$340),SUMIF(Stock!$D$4:$IP$4,B55,Stock!$D$340:$IP$340))),SUMIF(Stock!$D$4:$IP$4,B55,Stock!$D$340:$IP$340))) -> 1 | F55: =D55-E55 -> 0 | G55: =IF(AND(B55="",C55=""),"",IF(C55<>"",IF(COUNTIFS(Stock!$D$4:$IP$4,B55,Stock!$D$5:$IP$5,C55)>0,SUMIFS(Stock!$D$32:$IP$32,Stock!$D$4:$IP$4,B55,Stock!$D$5:$IP$5,C55),IF(COUNTIF(Stock!$D$5:$IP$5,C55)>0,SUMIF(Stock!$D$5:$IP$5,C55,Stock!$D$32:$IP$32),SUMIF(Stock!$D$4:$IP$4,B55,Stock!$D$32:$IP$32))),SUMIF(Stock!$D$4:$IP$4,B55,Stock!$D$32:$IP$32))) -> 0 | M55: =K55-L55 -> 0 | O55: Gap | P55: Opel | Q55: PC-6142 | R55: 25 | S55: =IF(AND(P55="",Q55=""),"",IF(Q55<>"",IF(COUNTIFS(Stock!$D$4:$IP$4,P55,Stock!$D$5:$IP$5,Q55)>0,SUMIFS(Stock!$D$340:$IP$340,Stock!$D$4:$IP$4,P55,Stock!$D$5:$IP$5,Q55),IF(COUNTIF(Stock!$D$5:$IP$5,Q55)>0,SUMIF(Stock!$D$5:$IP$5,Q55,Stock!$D$340:$IP$340),SUMIF(Stock!$D$4:$IP$4,P55,Stock!$D$340:$IP$340))),SUMIF(Stock!$D$4:$IP$4,P55,Stock!$D$340:$IP$340))) -> 0 | T55: =R55-S55 -> 25 | U55: =IF(AND(P55="",Q55=""),"",IF(Q55<>"",IF(COUNTIFS(Stock!$D$4:$IP$4,P55,Stock!$D$5:$IP$5,Q55)>0,SUMIFS(Stock!$D$32:$IP$32,Stock!$D$4:$IP$4,P55,Stock!$D$5:$IP$5,Q55),IF(COUNTIF(Stock!$D$5:$IP$5,Q55)>0,SUMIF(Stock!$D$5:$IP$5,Q55,Stock!$D$32:$IP$32),SUMIF(Stock!$D$4:$IP$4,P55,Stock!$D$32:$IP$32))),SUMIF(Stock!$D$4:$IP$4,P55,Stock!$D$32:$IP$32))) -> 110 | V55: PC6142
B56: PALIO STILE | C56: PC-86269 | D56: 1 | E56: =IF(AND(B56="",C56=""),"",IF(C56<>"",IF(COUNTIFS(Stock!$D$4:$IP$4,B56,Stock!$D$5:$IP$5,C56)>0,SUMIFS(Stock!$D$340:$IP$340,Stock!$D$4:$IP$4,B56,Stock!$D$5:$IP$5,C56),IF(COUNTIF(Stock!$D$5:$IP$5,C56)>0,SUMIF(Stock!$D$5:$IP$5,C56,Stock!$D$340:$IP$340),SUMIF(Stock!$D$4:$IP$4,B56,Stock!$D$340:$IP$340))),SUMIF(Stock!$D$4:$IP$4,B56,Stock!$D$340:$IP$340))) -> 1 | F56: =D56-E56 -> 0 | G56: =IF(AND(B56="",C56=""),"",IF(C56<>"",IF(COUNTIFS(Stock!$D$4:$IP$4,B56,Stock!$D$5:$IP$5,C56)>0,SUMIFS(Stock!$D$32:$IP$32,Stock!$D$4:$IP$4,B56,Stock!$D$5:$IP$5,C56),IF(COUNTIF(Stock!$D$5:$IP$5,C56)>0,SUMIF(Stock!$D$5:$IP$5,C56,Stock!$D$32:$IP$32),SUMIF(Stock!$D$4:$IP$4,B56,Stock!$D$32:$IP$32))),SUMIF(Stock!$D$4:$IP$4,B56,Stock!$D$32:$IP$32))) -> 0 | H56: FAN | I56: 10" Straight -80w | J56: TST-8801 | K56: 1150 | L56: =IF(AND(I56="",J56=""),"",IF(J56<>"",IF(COUNTIFS(Stock!$D$4:$IP$4,I56,Stock!$D$5:$IP$5,J56)>0,SUMIFS(Stock!$D$340:$IP$340,Stock!$D$4:$IP$4,I56,Stock!$D$5:$IP$5,J56),IF(COUNTIF(Stock!$D$5:$IP$5,J56)>0,SUMIF(Stock!$D$5:$IP$5,J56,Stock!$D$340:$IP$340),SUMIF(Stock!$D$4:$IP$4,I56,Stock!$D$340:$IP$340))),SUMIF(Stock!$D$4:$IP$4,I56,Stock!$D$340:$IP$340))) -> 995 | M56: =K56-L56 -> 155 | N56: =IF(AND(I56="",J56=""),"",IF(J56<>"",IF(COUNTIFS(Stock!$D$4:$IP$4,I56,Stock!$D$5:$IP$5,J56)>0,SUMIFS(Stock!$D$32:$IP$32,Stock!$D$4:$IP$4,I56,Stock!$D$5:$IP$5,J56),IF(COUNTIF(Stock!$D$5:$IP$5,J56)>0,SUMIF(Stock!$D$5:$IP$5,J56,Stock!$D$32:$IP$32),SUMIF(Stock!$D$4:$IP$4,I56,Stock!$D$32:$IP$32))),SUMIF(Stock!$D$4:$IP$4,I56,Stock!$D$32:$IP$32))) -> 1000 | P56: OPTRA | Q56: PC-8031 | R56: 150 | S56: =IF(AND(P56="",Q56=""),"",IF(Q56<>"",IF(COUNTIFS(Stock!$D$4:$IP$4,P56,Stock!$D$5:$IP$5,Q56)>0,SUMIFS(Stock!$D$340:$IP$340,Stock!$D$4:$IP$4,P56,Stock!$D$5:$IP$5,Q56),IF(COUNTIF(Stock!$D$5:$IP$5,Q56)>0,SUMIF(Stock!$D$5:$IP$5,Q56,Stock!$D$340:$IP$340),SUMIF(Stock!$D$4:$IP$4,P56,Stock!$D$340:$IP$340))),SUMIF(Stock!$D$4:$IP$4,P56,Stock!$D$340:$IP$340))) -> 0 | T56: =R56-S56 -> 150 | U56: =IF(AND(P56="",Q56=""),"",IF(Q56<>"",IF(COUNTIFS(Stock!$D$4:$IP$4,P56,Stock!$D$5:$IP$5,Q56)>0,SUMIFS(Stock!$D$32:$IP$32,Stock!$D$4:$IP$4,P56,Stock!$D$5:$IP$5,Q56),IF(COUNTIF(Stock!$D$5:$IP$5,Q56)>0,SUMIF(Stock!$D$5:$IP$5,Q56,Stock!$D$32:$IP$32),SUMIF(Stock!$D$4:$IP$4,P56,Stock!$D$32:$IP$32))),SUMIF(Stock!$D$4:$IP$4,P56,Stock!$D$32:$IP$32))) -> 200 | V56: PC8031
B57: ZEN ESTILO | C57: PC-86275 | D57: 1 | E57: =IF(AND(B57="",C57=""),"",IF(C57<>"",IF(COUNTIFS(Stock!$D$4:$IP$4,B57,Stock!$D$5:$IP$5,C57)>0,SUMIFS(Stock!$D$340:$IP$340,Stock!$D$4:$IP$4,B57,Stock!$D$5:$IP$5,C57),IF(COUNTIF(Stock!$D$5:$IP$5,C57)>0,SUMIF(Stock!$D$5:$IP$5,C57,Stock!$D$340:$IP$340),SUMIF(Stock!$D$4:$IP$4,B57,Stock!$D$340:$IP$340))),SUMIF(Stock!$D$4:$IP$4,B57,Stock!$D$340:$IP$340))) -> 1 | F57: =D57-E57 -> 0 | G57: =IF(AND(B57="",C57=""),"",IF(C57<>"",IF(COUNTIFS(Stock!$D$4:$IP$4,B57,Stock!$D$5:$IP$5,C57)>0,SUMIFS(Stock!$D$32:$IP$32,Stock!$D$4:$IP$4,B57,Stock!$D$5:$IP$5,C57),IF(COUNTIF(Stock!$D$5:$IP$5,C57)>0,SUMIF(Stock!$D$5:$IP$5,C57,Stock!$D$32:$IP$32),SUMIF(Stock!$D$4:$IP$4,B57,Stock!$D$32:$IP$32))),SUMIF(Stock!$D$4:$IP$4,B57,Stock!$D$32:$IP$32))) -> 0 | I57: 10" 'S' 80w | J57: TS-8805 | K57: 1050 | L57: =IF(AND(I57="",J57=""),"",IF(J57<>"",IF(COUNTIFS(Stock!$D$4:$IP$4,I57,Stock!$D$5:$IP$5,J57)>0,SUMIFS(Stock!$D$340:$IP$340,Stock!$D$4:$IP$4,I57,Stock!$D$5:$IP$5,J57),IF(COUNTIF(Stock!$D$5:$IP$5,J57)>0,SUMIF(Stock!$D$5:$IP$5,J57,Stock!$D$340:$IP$340),SUMIF(Stock!$D$4:$IP$4,I57,Stock!$D$340:$IP$340))),SUMIF(Stock!$D$4:$IP$4,I57,Stock!$D$340:$IP$340))) -> 1015 | M57: =K57-L57 -> 35 | N57: =IF(AND(I57="",J57=""),"",IF(J57<>"",IF(COUNTIFS(Stock!$D$4:$IP$4,I57,Stock!$D$5:$IP$5,J57)>0,SUMIFS(Stock!$D$32:$IP$32,Stock!$D$4:$IP$4,I57,Stock!$D$5:$IP$5,J57),IF(COUNTIF(Stock!$D$5:$IP$5,J57)>0,SUMIF(Stock!$D$5:$IP$5,J57,Stock!$D$32:$IP$32),SUMIF(Stock!$D$4:$IP$4,I57,Stock!$D$32:$IP$32))),SUMIF(Stock!$D$4:$IP$4,I57,Stock!$D$32:$IP$32))) -> 1000 | P57: Maruti 'O'Ring | Q57: PC-8051 | R57: 649 | S57: =IF(AND(P57="",Q57=""),"",IF(Q57<>"",IF(COUNTIFS(Stock!$D$4:$IP$4,P57,Stock!$D$5:$IP$5,Q57)>0,SUMIFS(Stock!$D$340:$IP$340,Stock!$D$4:$IP$4,P57,Stock!$D$5:$IP$5,Q57),IF(COUNTIF(Stock!$D$5:$IP$5,Q57)>0,SUMIF(Stock!$D$5:$IP$5,Q57,Stock!$D$340:$IP$340),SUMIF(Stock!$D$4:$IP$4,P57,Stock!$D$340:$IP$340))),SUMIF(Stock!$D$4:$IP$4,P57,Stock!$D$340:$IP$340))) -> 799 | T57: =R57-S57 -> -150 | U57: =IF(AND(P57="",Q57=""),"",IF(Q57<>"",IF(COUNTIFS(Stock!$D$4:$IP$4,P57,Stock!$D$5:$IP$5,Q57)>0,SUMIFS(Stock!$D$32:$IP$32,Stock!$D$4:$IP$4,P57,Stock!$D$5:$IP$5,Q57),IF(COUNTIF(Stock!$D$5:$IP$5,Q57)>0,SUMIF(Stock!$D$5:$IP$5,Q57,Stock!$D$32:$IP$32),SUMIF(Stock!$D$4:$IP$4,P57,Stock!$D$32:$IP$32))),SUMIF(Stock!$D$4:$IP$4,P57,Stock!$D$32:$IP$32))) -> 750 | V57: PC8051;MARUTIO
B58: A-STAR | C58: PC-86274 | D58: 1 | E58: =IF(AND(B58="",C58=""),"",IF(C58<>"",IF(COUNTIFS(Stock!$D$4:$IP$4,B58,Stock!$D$5:$IP$5,C58)>0,SUMIFS(Stock!$D$340:$IP$340,Stock!$D$4:$IP$4,B58,Stock!$D$5:$IP$5,C58),IF(COUNTIF(Stock!$D$5:$IP$5,C58)>0,SUMIF(Stock!$D$5:$IP$5,C58,Stock!$D$340:$IP$340),SUMIF(Stock!$D$4:$IP$4,B58,Stock!$D$340:$IP$340))),SUMIF(Stock!$D$4:$IP$4,B58,Stock!$D$340:$IP$340))) -> 1 | F58: =D58-E58 -> 0 | G58: =IF(AND(B58="",C58=""),"",IF(C58<>"",IF(COUNTIFS(Stock!$D$4:$IP$4,B58,Stock!$D$5:$IP$5,C58)>0,SUMIFS(Stock!$D$32:$IP$32,Stock!$D$4:$IP$4,B58,Stock!$D$5:$IP$5,C58),IF(COUNTIF(Stock!$D$5:$IP$5,C58)>0,SUMIF(Stock!$D$5:$IP$5,C58,Stock!$D$32:$IP$32),SUMIF(Stock!$D$4:$IP$4,B58,Stock!$D$32:$IP$32))),SUMIF(Stock!$D$4:$IP$4,B58,Stock!$D$32:$IP$32))) -> 0 | I58: 12" Straight -80w | J58: TST-8801-A | K58: 658 | L58: =IF(AND(I58="",J58=""),"",IF(J58<>"",IF(COUNTIFS(Stock!$D$4:$IP$4,I58,Stock!$D$5:$IP$5,J58)>0,SUMIFS(Stock!$D$340:$IP$340,Stock!$D$4:$IP$4,I58,Stock!$D$5:$IP$5,J58),IF(COUNTIF(Stock!$D$5:$IP$5,J58)>0,SUMIF(Stock!$D$5:$IP$5,J58,Stock!$D$340:$IP$340),SUMIF(Stock!$D$4:$IP$4,I58,Stock!$D$340:$IP$340))),SUMIF(Stock!$D$4:$IP$4,I58,Stock!$D$340:$IP$340))) -> 1188 | M58: =K58-L58 -> -530 | N58: =IF(AND(I58="",J58=""),"",IF(J58<>"",IF(COUNTIFS(Stock!$D$4:$IP$4,I58,Stock!$D$5:$IP$5,J58)>0,SUMIFS(Stock!$D$32:$IP$32,Stock!$D$4:$IP$4,I58,Stock!$D$5:$IP$5,J58),IF(COUNTIF(Stock!$D$5:$IP$5,J58)>0,SUMIF(Stock!$D$5:$IP$5,J58,Stock!$D$32:$IP$32),SUMIF(Stock!$D$4:$IP$4,I58,Stock!$D$32:$IP$32))),SUMIF(Stock!$D$4:$IP$4,I58,Stock!$D$32:$IP$32))) -> 1199 | P58: Maruti 'F'Ring | Q58: PC-8047 | R58: 774 | S58: =IF(AND(P58="",Q58=""),"",IF(Q58<>"",IF(COUNTIFS(Stock!$D$4:$IP$4,P58,Stock!$D$5:$IP$5,Q58)>0,SUMIFS(Stock!$D$340:$IP$340,Stock!$D$4:$IP$4,P58,Stock!$D$5:$IP$5,Q58),IF(COUNTIF(Stock!$D$5:$IP$5,Q58)>0,SUMIF(Stock!$D$5:$IP$5,Q58,Stock!$D$340:$IP$340),SUMIF(Stock!$D$4:$IP$4,P58,Stock!$D$340:$IP$340))),SUMIF(Stock!$D$4:$IP$4,P58,Stock!$D$340:$IP$340))) -> 874 | T58: =R58-S58 -> -100 | U58: =IF(AND(P58="",Q58=""),"",IF(Q58<>"",IF(COUNTIFS(Stock!$D$4:$IP$4,P58,Stock!$D$5:$IP$5,Q58)>0,SUMIFS(Stock!$D$32:$IP$32,Stock!$D$4:$IP$4,P58,Stock!$D$5:$IP$5,Q58),IF(COUNTIF(Stock!$D$5:$IP$5,Q58)>0,SUMIF(Stock!$D$5:$IP$5,Q58,Stock!$D$32:$IP$32),SUMIF(Stock!$D$4:$IP$4,P58,Stock!$D$32:$IP$32))),SUMIF(Stock!$D$4:$IP$4,P58,Stock!$D$32:$IP$32))) -> 850 | V58: PC8047
B59: I-20 | C59: PC-86268 | D59: 1 | E59: =IF(AND(B59="",C59=""),"",IF(C59<>"",IF(COUNTIFS(Stock!$D$4:$IP$4,B59,Stock!$D$5:$IP$5,C59)>0,SUMIFS(Stock!$D$340:$IP$340,Stock!$D$4:$IP$4,B59,Stock!$D$5:$IP$5,C59),IF(COUNTIF(Stock!$D$5:$IP$5,C59)>0,SUMIF(Stock!$D$5:$IP$5,C59,Stock!$D$340:$IP$340),SUMIF(Stock!$D$4:$IP$4,B59,Stock!$D$340:$IP$340))),SUMIF(Stock!$D$4:$IP$4,B59,Stock!$D$340:$IP$340))) -> 1 | F59: =D59-E59 -> 0 | G59: =IF(AND(B59="",C59=""),"",IF(C59<>"",IF(COUNTIFS(Stock!$D$4:$IP$4,B59,Stock!$D$5:$IP$5,C59)>0,SUMIFS(Stock!$D$32:$IP$32,Stock!$D$4:$IP$4,B59,Stock!$D$5:$IP$5,C59),IF(COUNTIF(Stock!$D$5:$IP$5,C59)>0,SUMIF(Stock!$D$5:$IP$5,C59,Stock!$D$32:$IP$32),SUMIF(Stock!$D$4:$IP$4,B59,Stock!$D$32:$IP$32))),SUMIF(Stock!$D$4:$IP$4,B59,Stock!$D$32:$IP$32))) -> 0 | I59: 12" 'S' 80w | J59: TS-8805-B | K59: 489 | L59: =IF(AND(I59="",J59=""),"",IF(J59<>"",IF(COUNTIFS(Stock!$D$4:$IP$4,I59,Stock!$D$5:$IP$5,J59)>0,SUMIFS(Stock!$D$340:$IP$340,Stock!$D$4:$IP$4,I59,Stock!$D$5:$IP$5,J59),IF(COUNTIF(Stock!$D$5:$IP$5,J59)>0,SUMIF(Stock!$D$5:$IP$5,J59,Stock!$D$340:$IP$340),SUMIF(Stock!$D$4:$IP$4,I59,Stock!$D$340:$IP$340))),SUMIF(Stock!$D$4:$IP$4,I59,Stock!$D$340:$IP$340))) -> 579 | M59: =K59-L59 -> -90 | N59: =IF(AND(I59="",J59=""),"",IF(J59<>"",IF(COUNTIFS(Stock!$D$4:$IP$4,I59,Stock!$D$5:$IP$5,J59)>0,SUMIFS(Stock!$D$32:$IP$32,Stock!$D$4:$IP$4,I59,Stock!$D$5:$IP$5,J59),IF(COUNTIF(Stock!$D$5:$IP$5,J59)>0,SUMIF(Stock!$D$5:$IP$5,J59,Stock!$D$32:$IP$32),SUMIF(Stock!$D$4:$IP$4,I59,Stock!$D$32:$IP$32))),SUMIF(Stock!$D$4:$IP$4,I59,Stock!$D$32:$IP$32))) -> 589 | P59: Lancer | Q59: PC-8017 | R59: 225 | S59: =IF(AND(P59="",Q59=""),"",IF(Q59<>"",IF(COUNTIFS(Stock!$D$4:$IP$4,P59,Stock!$D$5:$IP$5,Q59)>0,SUMIFS(Stock!$D$340:$IP$340,Stock!$D$4:$IP$4,P59,Stock!$D$5:$IP$5,Q59),IF(COUNTIF(Stock!$D$5:$IP$5,Q59)>0,SUMIF(Stock!$D$5:$IP$5,Q59,Stock!$D$340:$IP$340),SUMIF(Stock!$D$4:$IP$4,P59,Stock!$D$340:$IP$340))),SUMIF(Stock!$D$4:$IP$4,P59,Stock!$D$340:$IP$340))) -> 225 | T59: =R59-S59 -> 0 | U59: =IF(AND(P59="",Q59=""),"",IF(Q59<>"",IF(COUNTIFS(Stock!$D$4:$IP$4,P59,Stock!$D$5:$IP$5,Q59)>0,SUMIFS(Stock!$D$32:$IP$32,Stock!$D$4:$IP$4,P59,Stock!$D$5:$IP$5,Q59),IF(COUNTIF(Stock!$D$5:$IP$5,Q59)>0,SUMIF(Stock!$D$5:$IP$5,Q59,Stock!$D$32:$IP$32),SUMIF(Stock!$D$4:$IP$4,P59,Stock!$D$32:$IP$32))),SUMIF(Stock!$D$4:$IP$4,P59,Stock!$D$32:$IP$32))) -> 300 | V59: PC8017
B60: SPARK | C60: PC-86013 | D60: 101 | E60: =IF(AND(B60="",C60=""),"",IF(C60<>"",IF(COUNTIFS(Stock!$D$4:$IP$4,B60,Stock!$D$5:$IP$5,C60)>0,SUMIFS(Stock!$D$340:$IP$340,Stock!$D$4:$IP$4,B60,Stock!$D$5:$IP$5,C60),IF(COUNTIF(Stock!$D$5:$IP$5,C60)>0,SUMIF(Stock!$D$5:$IP$5,C60,Stock!$D$340:$IP$340),SUMIF(Stock!$D$4:$IP$4,B60,Stock!$D$340:$IP$340))),SUMIF(Stock!$D$4:$IP$4,B60,Stock!$D$340:$IP$340))) -> 1 | F60: =D60-E60 -> 100 | G60: =IF(AND(B60="",C60=""),"",IF(C60<>"",IF(COUNTIFS(Stock!$D$4:$IP$4,B60,Stock!$D$5:$IP$5,C60)>0,SUMIFS(Stock!$D$32:$IP$32,Stock!$D$4:$IP$4,B60,Stock!$D$5:$IP$5,C60),IF(COUNTIF(Stock!$D$5:$IP$5,C60)>0,SUMIF(Stock!$D$5:$IP$5,C60,Stock!$D$32:$IP$32),SUMIF(Stock!$D$4:$IP$4,B60,Stock!$D$32:$IP$32))),SUMIF(Stock!$D$4:$IP$4,B60,Stock!$D$32:$IP$32))) -> 0 | I60: 12" 'S' 100w BEHR | J60: TS-8805-CB | K60: 10 | L60: =IF(AND(I60="",J60=""),"",IF(J60<>"",IF(COUNTIFS(Stock!$D$4:$IP$4,I60,Stock!$D$5:$IP$5,J60)>0,SUMIFS(Stock!$D$340:$IP$340,Stock!$D$4:$IP$4,I60,Stock!$D$5:$IP$5,J60),IF(COUNTIF(Stock!$D$5:$IP$5,J60)>0,SUMIF(Stock!$D$5:$IP$5,J60,Stock!$D$340:$IP$340),SUMIF(Stock!$D$4:$IP$4,I60,Stock!$D$340:$IP$340))),SUMIF(Stock!$D$4:$IP$4,I60,Stock!$D$340:$IP$340))) -> 200 | M60: =K60-L60 -> -190 | N60: =IF(AND(I60="",J60=""),"",IF(J60<>"",IF(COUNTIFS(Stock!$D$4:$IP$4,I60,Stock!$D$5:$IP$5,J60)>0,SUMIFS(Stock!$D$32:$IP$32,Stock!$D$4:$IP$4,I60,Stock!$D$5:$IP$5,J60),IF(COUNTIF(Stock!$D$5:$IP$5,J60)>0,SUMIF(Stock!$D$5:$IP$5,J60,Stock!$D$32:$IP$32),SUMIF(Stock!$D$4:$IP$4,I60,Stock!$D$32:$IP$32))),SUMIF(Stock!$D$4:$IP$4,I60,Stock!$D$32:$IP$32))) -> 200 | P60: Santro/santro xing | Q60: PC-8026 | R60: 3900 | S60: =IF(AND(P60="",Q60=""),"",IF(Q60<>"",IF(COUNTIFS(Stock!$D$4:$IP$4,P60,Stock!$D$5:$IP$5,Q60)>0,SUMIFS(Stock!$D$340:$IP$340,Stock!$D$4:$IP$4,P60,Stock!$D$5:$IP$5,Q60),IF(COUNTIF(Stock!$D$5:$IP$5,Q60)>0,SUMIF(Stock!$D$5:$IP$5,Q60,Stock!$D$340:$IP$340),SUMIF(Stock!$D$4:$IP$4,P60,Stock!$D$340:$IP$340))),SUMIF(Stock!$D$4:$IP$4,P60,Stock!$D$340:$IP$340))) -> 1900 | T60: =R60-S60 -> 2000 | U60: =IF(AND(P60="",Q60=""),"",IF(Q60<>"",IF(COUNTIFS(Stock!$D$4:$IP$4,P60,Stock!$D$5:$IP$5,Q60)>0,SUMIFS(Stock!$D$32:$IP$32,Stock!$D$4:$IP$4,P60,Stock!$D$5:$IP$5,Q60),IF(COUNTIF(Stock!$D$5:$IP$5,Q60)>0,SUMIF(Stock!$D$5:$IP$5,Q60,Stock!$D$32:$IP$32),SUMIF(Stock!$D$4:$IP$4,P60,Stock!$D$32:$IP$32))),SUMIF(Stock!$D$4:$IP$4,P60,Stock!$D$32:$IP$32))) -> 3900 | V60: PC8026
B61: ACCORD | D61: 0 | E61: =IF(AND(B61="",C61=""),"",IF(C61<>"",IF(COUNTIFS(Stock!$D$4:$IP$4,B61,Stock!$D$5:$IP$5,C61)>0,SUMIFS(Stock!$D$340:$IP$340,Stock!$D$4:$IP$4,B61,Stock!$D$5:$IP$5,C61),IF(COUNTIF(Stock!$D$5:$IP$5,C61)>0,SUMIF(Stock!$D$5:$IP$5,C61,Stock!$D$340:$IP$340),SUMIF(Stock!$D$4:$IP$4,B61,Stock!$D$340:$IP$340))),SUMIF(Stock!$D$4:$IP$4,B61,Stock!$D$340:$IP$340))) -> 0 | F61: =D61-E61 -> 0 | G61: =IF(AND(B61="",C61=""),"",IF(C61<>"",IF(COUNTIFS(Stock!$D$4:$IP$4,B61,Stock!$D$5:$IP$5,C61)>0,SUMIFS(Stock!$D$32:$IP$32,Stock!$D$4:$IP$4,B61,Stock!$D$5:$IP$5,C61),IF(COUNTIF(Stock!$D$5:$IP$5,C61)>0,SUMIF(Stock!$D$5:$IP$5,C61,Stock!$D$32:$IP$32),SUMIF(Stock!$D$4:$IP$4,B61,Stock!$D$32:$IP$32))),SUMIF(Stock!$D$4:$IP$4,B61,Stock!$D$32:$IP$32))) -> 0 | I61: 14" Straight -80w | J61: TST-8801-B | K61: 390 | L61: =IF(AND(I61="",J61=""),"",IF(J61<>"",IF(COUNTIFS(Stock!$D$4:$IP$4,I61,Stock!$D$5:$IP$5,J61)>0,SUMIFS(Stock!$D$340:$IP$340,Stock!$D$4:$IP$4,I61,Stock!$D$5:$IP$5,J61),IF(COUNTIF(Stock!$D$5:$IP$5,J61)>0,SUMIF(Stock!$D$5:$IP$5,J61,Stock!$D$340:$IP$340),SUMIF(Stock!$D$4:$IP$4,I61,Stock!$D$340:$IP$340))),SUMIF(Stock!$D$4:$IP$4,I61,Stock!$D$340:$IP$340))) -> 350 | M61: =K61-L61 -> 40 | N61: =IF(AND(I61="",J61=""),"",IF(J61<>"",IF(COUNTIFS(Stock!$D$4:$IP$4,I61,Stock!$D$5:$IP$5,J61)>0,SUMIFS(Stock!$D$32:$IP$32,Stock!$D$4:$IP$4,I61,Stock!$D$5:$IP$5,J61),IF(COUNTIF(Stock!$D$5:$IP$5,J61)>0,SUMIF(Stock!$D$5:$IP$5,J61,Stock!$D$32:$IP$32),SUMIF(Stock!$D$4:$IP$4,I61,Stock!$D$32:$IP$32))),SUMIF(Stock!$D$4:$IP$4,I61,Stock!$D$32:$IP$32))) -> 350 | P61: Ambasdor/ Balero | Q61: PC-8120 | R61: 671 | S61: =IF(AND(P61="",Q61=""),"",IF(Q61<>"",IF(COUNTIFS(Stock!$D$4:$IP$4,P61,Stock!$D$5:$IP$5,Q61)>0,SUMIFS(Stock!$D$340:$IP$340,Stock!$D$4:$IP$4,P61,Stock!$D$5:$IP$5,Q61),IF(COUNTIF(Stock!$D$5:$IP$5,Q61)>0,SUMIF(Stock!$D$5:$IP$5,Q61,Stock!$D$340:$IP$340),SUMIF(Stock!$D$4:$IP$4,P61,Stock!$D$340:$IP$340))),SUMIF(Stock!$D$4:$IP$4,P61,Stock!$D$340:$IP$340))) -> 671 | T61: =R61-S61 -> 0 | U61: =IF(AND(P61="",Q61=""),"",IF(Q61<>"",IF(COUNTIFS(Stock!$D$4:$IP$4,P61,Stock!$D$5:$IP$5,Q61)>0,SUMIFS(Stock!$D$32:$IP$32,Stock!$D$4:$IP$4,P61,Stock!$D$5:$IP$5,Q61),IF(COUNTIF(Stock!$D$5:$IP$5,Q61)>0,SUMIF(Stock!$D$5:$IP$5,Q61,Stock!$D$32:$IP$32),SUMIF(Stock!$D$4:$IP$4,P61,Stock!$D$32:$IP$32))),SUMIF(Stock!$D$4:$IP$4,P61,Stock!$D$32:$IP$32))) -> 649 | V61: PC8120
B62: I-10 | D62: 0 | E62: =IF(AND(B62="",C62=""),"",IF(C62<>"",IF(COUNTIFS(Stock!$D$4:$IP$4,B62,Stock!$D$5:$IP$5,C62)>0,SUMIFS(Stock!$D$340:$IP$340,Stock!$D$4:$IP$4,B62,Stock!$D$5:$IP$5,C62),IF(COUNTIF(Stock!$D$5:$IP$5,C62)>0,SUMIF(Stock!$D$5:$IP$5,C62,Stock!$D$340:$IP$340),SUMIF(Stock!$D$4:$IP$4,B62,Stock!$D$340:$IP$340))),SUMIF(Stock!$D$4:$IP$4,B62,Stock!$D$340:$IP$340))) -> 0 | F62: =D62-E62 -> 0 | G62: =IF(AND(B62="",C62=""),"",IF(C62<>"",IF(COUNTIFS(Stock!$D$4:$IP$4,B62,Stock!$D$5:$IP$5,C62)>0,SUMIFS(Stock!$D$32:$IP$32,Stock!$D$4:$IP$4,B62,Stock!$D$5:$IP$5,C62),IF(COUNTIF(Stock!$D$5:$IP$5,C62)>0,SUMIF(Stock!$D$5:$IP$5,C62,Stock!$D$32:$IP$32),SUMIF(Stock!$D$4:$IP$4,B62,Stock!$D$32:$IP$32))),SUMIF(Stock!$D$4:$IP$4,B62,Stock!$D$32:$IP$32))) -> 0 | I62: 14" 'S' 100w JPI | J62: TS-8805-A | K62: 255 | L62: =IF(AND(I62="",J62=""),"",IF(J62<>"",IF(COUNTIFS(Stock!$D$4:$IP$4,I62,Stock!$D$5:$IP$5,J62)>0,SUMIFS(Stock!$D$340:$IP$340,Stock!$D$4:$IP$4,I62,Stock!$D$5:$IP$5,J62),IF(COUNTIF(Stock!$D$5:$IP$5,J62)>0,SUMIF(Stock!$D$5:$IP$5,J62,Stock!$D$340:$IP$340),SUMIF(Stock!$D$4:$IP$4,I62,Stock!$D$340:$IP$340))),SUMIF(Stock!$D$4:$IP$4,I62,Stock!$D$340:$IP$340))) -> 215 | M62: =K62-L62 -> 40 | N62: =IF(AND(I62="",J62=""),"",IF(J62<>"",IF(COUNTIFS(Stock!$D$4:$IP$4,I62,Stock!$D$5:$IP$5,J62)>0,SUMIFS(Stock!$D$32:$IP$32,Stock!$D$4:$IP$4,I62,Stock!$D$5:$IP$5,J62),IF(COUNTIF(Stock!$D$5:$IP$5,J62)>0,SUMIF(Stock!$D$5:$IP$5,J62,Stock!$D$32:$IP$32),SUMIF(Stock!$D$4:$IP$4,I62,Stock!$D$32:$IP$32))),SUMIF(Stock!$D$4:$IP$4,I62,Stock!$D$32:$IP$32))) -> 506 | P62: Balero | Q62: PC-8121 | S62: =IF(AND(P62="",Q62=""),"",IF(Q62<>"",IF(COUNTIFS(Stock!$D$4:$IP$4,P62,Stock!$D$5:$IP$5,Q62)>0,SUMIFS(Stock!$D$340:$IP$340,Stock!$D$4:$IP$4,P62,Stock!$D$5:$IP$5,Q62),IF(COUNTIF(Stock!$D$5:$IP$5,Q62)>0,SUMIF(Stock!$D$5:$IP$5,Q62,Stock!$D$340:$IP$340),SUMIF(Stock!$D$4:$IP$4,P62,Stock!$D$340:$IP$340))),SUMIF(Stock!$D$4:$IP$4,P62,Stock!$D$340:$IP$340))) -> 0 | T62: =R62-S62 -> 0 | U62: =IF(AND(P62="",Q62=""),"",IF(Q62<>"",IF(COUNTIFS(Stock!$D$4:$IP$4,P62,Stock!$D$5:$IP$5,Q62)>0,SUMIFS(Stock!$D$32:$IP$32,Stock!$D$4:$IP$4,P62,Stock!$D$5:$IP$5,Q62),IF(COUNTIF(Stock!$D$5:$IP$5,Q62)>0,SUMIF(Stock!$D$5:$IP$5,Q62,Stock!$D$32:$IP$32),SUMIF(Stock!$D$4:$IP$4,P62,Stock!$D$32:$IP$32))),SUMIF(Stock!$D$4:$IP$4,P62,Stock!$D$32:$IP$32))) -> 0 | V62: PC8121
B63: FABIA | E63: =IF(AND(B63="",C63=""),"",IF(C63<>"",IF(COUNTIFS(Stock!$D$4:$IP$4,B63,Stock!$D$5:$IP$5,C63)>0,SUMIFS(Stock!$D$340:$IP$340,Stock!$D$4:$IP$4,B63,Stock!$D$5:$IP$5,C63),IF(COUNTIF(Stock!$D$5:$IP$5,C63)>0,SUMIF(Stock!$D$5:$IP$5,C63,Stock!$D$340:$IP$340),SUMIF(Stock!$D$4:$IP$4,B63,Stock!$D$340:$IP$340))),SUMIF(Stock!$D$4:$IP$4,B63,Stock!$D$340:$IP$340))) -> 0 | F63: =D63-E63 -> 0 | G63: =IF(AND(B63="",C63=""),"",IF(C63<>"",IF(COUNTIFS(Stock!$D$4:$IP$4,B63,Stock!$D$5:$IP$5,C63)>0,SUMIFS(Stock!$D$32:$IP$32,Stock!$D$4:$IP$4,B63,Stock!$D$5:$IP$5,C63),IF(COUNTIF(Stock!$D$5:$IP$5,C63)>0,SUMIF(Stock!$D$5:$IP$5,C63,Stock!$D$32:$IP$32),SUMIF(Stock!$D$4:$IP$4,B63,Stock!$D$32:$IP$32))),SUMIF(Stock!$D$4:$IP$4,B63,Stock!$D$32:$IP$32))) -> 0 | I63: 15" 'S' Scorpio | K63: 320 | L63: =IF(AND(I63="",J63=""),"",IF(J63<>"",IF(COUNTIFS(Stock!$D$4:$IP$4,I63,Stock!$D$5:$IP$5,J63)>0,SUMIFS(Stock!$D$340:$IP$340,Stock!$D$4:$IP$4,I63,Stock!$D$5:$IP$5,J63),IF(COUNTIF(Stock!$D$5:$IP$5,J63)>0,SUMIF(Stock!$D$5:$IP$5,J63,Stock!$D$340:$IP$340),SUMIF(Stock!$D$4:$IP$4,I63,Stock!$D$340:$IP$340))),SUMIF(Stock!$D$4:$IP$4,I63,Stock!$D$340:$IP$340))) -> 255 | M63: =K63-L63 -> 65 | N63: =IF(AND(I63="",J63=""),"",IF(J63<>"",IF(COUNTIFS(Stock!$D$4:$IP$4,I63,Stock!$D$5:$IP$5,J63)>0,SUMIFS(Stock!$D$32:$IP$32,Stock!$D$4:$IP$4,I63,Stock!$D$5:$IP$5,J63),IF(COUNTIF(Stock!$D$5:$IP$5,J63)>0,SUMIF(Stock!$D$5:$IP$5,J63,Stock!$D$32:$IP$32),SUMIF(Stock!$D$4:$IP$4,I63,Stock!$D$32:$IP$32))),SUMIF(Stock!$D$4:$IP$4,I63,Stock!$D$32:$IP$32))) -> 500 | P63: Scorpio-3hole | Q63: PC-8115A | R63: 100 | S63: =IF(AND(P63="",Q63=""),"",IF(Q63<>"",IF(COUNTIFS(Stock!$D$4:$IP$4,P63,Stock!$D$5:$IP$5,Q63)>0,SUMIFS(Stock!$D$340:$IP$340,Stock!$D$4:$IP$4,P63,Stock!$D$5:$IP$5,Q63),IF(COUNTIF(Stock!$D$5:$IP$5,Q63)>0,SUMIF(Stock!$D$5:$IP$5,Q63,Stock!$D$340:$IP$340),SUMIF(Stock!$D$4:$IP$4,P63,Stock!$D$340:$IP$340))),SUMIF(Stock!$D$4:$IP$4,P63,Stock!$D$340:$IP$340))) -> 125 | T63: =R63-S63 -> -25 | U63: =IF(AND(P63="",Q63=""),"",IF(Q63<>"",IF(COUNTIFS(Stock!$D$4:$IP$4,P63,Stock!$D$5:$IP$5,Q63)>0,SUMIFS(Stock!$D$32:$IP$32,Stock!$D$4:$IP$4,P63,Stock!$D$5:$IP$5,Q63),IF(COUNTIF(Stock!$D$5:$IP$5,Q63)>0,SUMIF(Stock!$D$5:$IP$5,Q63,Stock!$D$32:$IP$32),SUMIF(Stock!$D$4:$IP$4,P63,Stock!$D$32:$IP$32))),SUMIF(Stock!$D$4:$IP$4,P63,Stock!$D$32:$IP$32))) -> 474 | V63: PC8115A
B64: LAURA | D64: 0 | E64: =IF(AND(B64="",C64=""),"",IF(C64<>"",IF(COUNTIFS(Stock!$D$4:$IP$4,B64,Stock!$D$5:$IP$5,C64)>0,SUMIFS(Stock!$D$340:$IP$340,Stock!$D$4:$IP$4,B64,Stock!$D$5:$IP$5,C64),IF(COUNTIF(Stock!$D$5:$IP$5,C64)>0,SUMIF(Stock!$D$5:$IP$5,C64,Stock!$D$340:$IP$340),SUMIF(Stock!$D$4:$IP$4,B64,Stock!$D$340:$IP$340))),SUMIF(Stock!$D$4:$IP$4,B64,Stock!$D$340:$IP$340))) -> 0 | F64: =D64-E64 -> 0 | G64: =IF(AND(B64="",C64=""),"",IF(C64<>"",IF(COUNTIFS(Stock!$D$4:$IP$4,B64,Stock!$D$5:$IP$5,C64)>0,SUMIFS(Stock!$D$32:$IP$32,Stock!$D$4:$IP$4,B64,Stock!$D$5:$IP$5,C64),IF(COUNTIF(Stock!$D$5:$IP$5,C64)>0,SUMIF(Stock!$D$5:$IP$5,C64,Stock!$D$32:$IP$32),SUMIF(Stock!$D$4:$IP$4,B64,Stock!$D$32:$IP$32))),SUMIF(Stock!$D$4:$IP$4,B64,Stock!$D$32:$IP$32))) -> 0 | I64: 16" 'S' Scorpio | K64: 30 | L64: =IF(AND(I64="",J64=""),"",IF(J64<>"",IF(COUNTIFS(Stock!$D$4:$IP$4,I64,Stock!$D$5:$IP$5,J64)>0,SUMIFS(Stock!$D$340:$IP$340,Stock!$D$4:$IP$4,I64,Stock!$D$5:$IP$5,J64),IF(COUNTIF(Stock!$D$5:$IP$5,J64)>0,SUMIF(Stock!$D$5:$IP$5,J64,Stock!$D$340:$IP$340),SUMIF(Stock!$D$4:$IP$4,I64,Stock!$D$340:$IP$340))),SUMIF(Stock!$D$4:$IP$4,I64,Stock!$D$340:$IP$340))) -> 30 | M64: =K64-L64 -> 0 | N64: =IF(AND(I64="",J64=""),"",IF(J64<>"",IF(COUNTIFS(Stock!$D$4:$IP$4,I64,Stock!$D$5:$IP$5,J64)>0,SUMIFS(Stock!$D$32:$IP$32,Stock!$D$4:$IP$4,I64,Stock!$D$5:$IP$5,J64),IF(COUNTIF(Stock!$D$5:$IP$5,J64)>0,SUMIF(Stock!$D$5:$IP$5,J64,Stock!$D$32:$IP$32),SUMIF(Stock!$D$4:$IP$4,I64,Stock!$D$32:$IP$32))),SUMIF(Stock!$D$4:$IP$4,I64,Stock!$D$32:$IP$32))) -> 200 | P64: Scorpio-4hole | Q64: PC-8115B | R64: 150 | S64: =IF(AND(P64="",Q64=""),"",IF(Q64<>"",IF(COUNTIFS(Stock!$D$4:$IP$4,P64,Stock!$D$5:$IP$5,Q64)>0,SUMIFS(Stock!$D$340:$IP$340,Stock!$D$4:$IP$4,P64,Stock!$D$5:$IP$5,Q64),IF(COUNTIF(Stock!$D$5:$IP$5,Q64)>0,SUMIF(Stock!$D$5:$IP$5,Q64,Stock!$D$340:$IP$340),SUMIF(Stock!$D$4:$IP$4,P64,Stock!$D$340:$IP$340))),SUMIF(Stock!$D$4:$IP$4,P64,Stock!$D$340:$IP$340))) -> 125 | T64: =R64-S64 -> 25 | U64: =IF(AND(P64="",Q64=""),"",IF(Q64<>"",IF(COUNTIFS(Stock!$D$4:$IP$4,P64,Stock!$D$5:$IP$5,Q64)>0,SUMIFS(Stock!$D$32:$IP$32,Stock!$D$4:$IP$4,P64,Stock!$D$5:$IP$5,Q64),IF(COUNTIF(Stock!$D$5:$IP$5,Q64)>0,SUMIF(Stock!$D$5:$IP$5,Q64,Stock!$D$32:$IP$32),SUMIF(Stock!$D$4:$IP$4,P64,Stock!$D$32:$IP$32))),SUMIF(Stock!$D$4:$IP$4,P64,Stock!$D$32:$IP$32))) -> 474 | V64: PC8115B
E65: =IF(AND(B65="",C65=""),"",IF(C65<>"",IF(COUNTIFS(Stock!$D$4:$IP$4,B65,Stock!$D$5:$IP$5,C65)>0,SUMIFS(Stock!$D$340:$IP$340,Stock!$D$4:$IP$4,B65,Stock!$D$5:$IP$5,C65),IF(COUNTIF(Stock!$D$5:$IP$5,C65)>0,SUMIF(Stock!$D$5:$IP$5,C65,Stock!$D$340:$IP$340),SUMIF(Stock!$D$4:$IP$4,B65,Stock!$D$340:$IP$340))),SUMIF(Stock!$D$4:$IP$4,B65,Stock!$D$340:$IP$340))) | F65: =D65-E65 -> #VALUE! | G65: =IF(AND(B65="",C65=""),"",IF(C65<>"",IF(COUNTIFS(Stock!$D$4:$IP$4,B65,Stock!$D$5:$IP$5,C65)>0,SUMIFS(Stock!$D$32:$IP$32,Stock!$D$4:$IP$4,B65,Stock!$D$5:$IP$5,C65),IF(COUNTIF(Stock!$D$5:$IP$5,C65)>0,SUMIF(Stock!$D$5:$IP$5,C65,Stock!$D$32:$IP$32),SUMIF(Stock!$D$4:$IP$4,B65,Stock!$D$32:$IP$32))),SUMIF(Stock!$D$4:$IP$4,B65,Stock!$D$32:$IP$32))) | H65: OIL | I65: 1 LITR | J65: CTNS | K65: 6672 | L65: =IF(AND(I65="",J65=""),"",IF(J65<>"",IF(COUNTIFS(Stock!$D$4:$IP$4,I65,Stock!$D$5:$IP$5,J65)>0,SUMIFS(Stock!$D$340:$IP$340,Stock!$D$4:$IP$4,I65,Stock!$D$5:$IP$5,J65),IF(COUNTIF(Stock!$D$5:$IP$5,J65)>0,SUMIF(Stock!$D$5:$IP$5,J65,Stock!$D$340:$IP$340),SUMIF(Stock!$D$4:$IP$4,I65,Stock!$D$340:$IP$340))),SUMIF(Stock!$D$4:$IP$4,I65,Stock!$D$340:$IP$340))) -> 5924 | M65: =K65-L65 -> 748 | N65: =IF(AND(I65="",J65=""),"",IF(J65<>"",IF(COUNTIFS(Stock!$D$4:$IP$4,I65,Stock!$D$5:$IP$5,J65)>0,SUMIFS(Stock!$D$32:$IP$32,Stock!$D$4:$IP$4,I65,Stock!$D$5:$IP$5,J65),IF(COUNTIF(Stock!$D$5:$IP$5,J65)>0,SUMIF(Stock!$D$5:$IP$5,J65,Stock!$D$32:$IP$32),SUMIF(Stock!$D$4:$IP$4,I65,Stock!$D$32:$IP$32))),SUMIF(Stock!$D$4:$IP$4,I65,Stock!$D$32:$IP$32))) -> 2641 | P65: Travera | Q65: PC-8122 | R65: 499 | S65: =IF(AND(P65="",Q65=""),"",IF(Q65<>"",IF(COUNTIFS(Stock!$D$4:$IP$4,P65,Stock!$D$5:$IP$5,Q65)>0,SUMIFS(Stock!$D$340:$IP$340,Stock!$D$4:$IP$4,P65,Stock!$D$5:$IP$5,Q65),IF(COUNTIF(Stock!$D$5:$IP$5,Q65)>0,SUMIF(Stock!$D$5:$IP$5,Q65,Stock!$D$340:$IP$340),SUMIF(Stock!$D$4:$IP$4,P65,Stock!$D$340:$IP$340))),SUMIF(Stock!$D$4:$IP$4,P65,Stock!$D$340:$IP$340))) -> 500 | T65: =R65-S65 -> -1 | U65: =IF(AND(P65="",Q65=""),"",IF(Q65<>"",IF(COUNTIFS(Stock!$D$4:$IP$4,P65,Stock!$D$5:$IP$5,Q65)>0,SUMIFS(Stock!$D$32:$IP$32,Stock!$D$4:$IP$4,P65,Stock!$D$5:$IP$5,Q65),IF(COUNTIF(Stock!$D$5:$IP$5,Q65)>0,SUMIF(Stock!$D$5:$IP$5,Q65,Stock!$D$32:$IP$32),SUMIF(Stock!$D$4:$IP$4,P65,Stock!$D$32:$IP$32))),SUMIF(Stock!$D$4:$IP$4,P65,Stock!$D$32:$IP$32))) -> 500 | V65: PC8122
B66: PF/UNI 25X28X26MM | C66: PC-086101 | D66: 342 | E66: =IF(AND(B66="",C66=""),"",IF(C66<>"",IF(COUNTIFS(Stock!$D$4:$IP$4,B66,Stock!$D$5:$IP$5,C66)>0,SUMIFS(Stock!$D$340:$IP$340,Stock!$D$4:$IP$4,B66,Stock!$D$5:$IP$5,C66),IF(COUNTIF(Stock!$D$5:$IP$5,C66)>0,SUMIF(Stock!$D$5:$IP$5,C66,Stock!$D$340:$IP$340),SUMIF(Stock!$D$4:$IP$4,B66,Stock!$D$340:$IP$340))),SUMIF(Stock!$D$4:$IP$4,B66,Stock!$D$340:$IP$340))) -> 150 | F66: =D66-E66 -> 192 | G66: =IF(AND(B66="",C66=""),"",IF(C66<>"",IF(COUNTIFS(Stock!$D$4:$IP$4,B66,Stock!$D$5:$IP$5,C66)>0,SUMIFS(Stock!$D$32:$IP$32,Stock!$D$4:$IP$4,B66,Stock!$D$5:$IP$5,C66),IF(COUNTIF(Stock!$D$5:$IP$5,C66)>0,SUMIF(Stock!$D$5:$IP$5,C66,Stock!$D$32:$IP$32),SUMIF(Stock!$D$4:$IP$4,B66,Stock!$D$32:$IP$32))),SUMIF(Stock!$D$4:$IP$4,B66,Stock!$D$32:$IP$32))) -> 342 | I66: 250G | J66: CTNS | K66: 9144 | L66: =IF(AND(I66="",J66=""),"",IF(J66<>"",IF(COUNTIFS(Stock!$D$4:$IP$4,I66,Stock!$D$5:$IP$5,J66)>0,SUMIFS(Stock!$D$340:$IP$340,Stock!$D$4:$IP$4,I66,Stock!$D$5:$IP$5,J66),IF(COUNTIF(Stock!$D$5:$IP$5,J66)>0,SUMIF(Stock!$D$5:$IP$5,J66,Stock!$D$340:$IP$340),SUMIF(Stock!$D$4:$IP$4,I66,Stock!$D$340:$IP$340))),SUMIF(Stock!$D$4:$IP$4,I66,Stock!$D$340:$IP$340))) -> 2029 | M66: =K66-L66 -> 7115 | N66: =IF(AND(I66="",J66=""),"",IF(J66<>"",IF(COUNTIFS(Stock!$D$4:$IP$4,I66,Stock!$D$5:$IP$5,J66)>0,SUMIFS(Stock!$D$32:$IP$32,Stock!$D$4:$IP$4,I66,Stock!$D$5:$IP$5,J66),IF(COUNTIF(Stock!$D$5:$IP$5,J66)>0,SUMIF(Stock!$D$5:$IP$5,J66,Stock!$D$32:$IP$32),SUMIF(Stock!$D$4:$IP$4,I66,Stock!$D$32:$IP$32))),SUMIF(Stock!$D$4:$IP$4,I66,Stock!$D$32:$IP$32))) -> 500 | P66: Sonata | Q66: PC-6066 | R66: 50 | S66: =IF(AND(P66="",Q66=""),"",IF(Q66<>"",IF(COUNTIFS(Stock!$D$4:$IP$4,P66,Stock!$D$5:$IP$5,Q66)>0,SUMIFS(Stock!$D$340:$IP$340,Stock!$D$4:$IP$4,P66,Stock!$D$5:$IP$5,Q66),IF(COUNTIF(Stock!$D$5:$IP$5,Q66)>0,SUMIF(Stock!$D$5:$IP$5,Q66,Stock!$D$340:$IP$340),SUMIF(Stock!$D$4:$IP$4,P66,Stock!$D$340:$IP$340))),SUMIF(Stock!$D$4:$IP$4,P66,Stock!$D$340:$IP$340))) -> 75 | T66: =R66-S66 -> -25 | U66: =IF(AND(P66="",Q66=""),"",IF(Q66<>"",IF(COUNTIFS(Stock!$D$4:$IP$4,P66,Stock!$D$5:$IP$5,Q66)>0,SUMIFS(Stock!$D$32:$IP$32,Stock!$D$4:$IP$4,P66,Stock!$D$5:$IP$5,Q66),IF(COUNTIF(Stock!$D$5:$IP$5,Q66)>0,SUMIF(Stock!$D$5:$IP$5,Q66,Stock!$D$32:$IP$32),SUMIF(Stock!$D$4:$IP$4,P66,Stock!$D$32:$IP$32))),SUMIF(Stock!$D$4:$IP$4,P66,Stock!$D$32:$IP$32))) -> 75 | V66: PC6066;SONATA
B67: PF/UNI 25X28X20MM | C67: PC-086102 | D67: 365 | E67: =IF(AND(B67="",C67=""),"",IF(C67<>"",IF(COUNTIFS(Stock!$D$4:$IP$4,B67,Stock!$D$5:$IP$5,C67)>0,SUMIFS(Stock!$D$340:$IP$340,Stock!$D$4:$IP$4,B67,Stock!$D$5:$IP$5,C67),IF(COUNTIF(Stock!$D$5:$IP$5,C67)>0,SUMIF(Stock!$D$5:$IP$5,C67,Stock!$D$340:$IP$340),SUMIF(Stock!$D$4:$IP$4,B67,Stock!$D$340:$IP$340))),SUMIF(Stock!$D$4:$IP$4,B67,Stock!$D$340:$IP$340))) -> 315 | F67: =D67-E67 -> 50 | G67: =IF(AND(B67="",C67=""),"",IF(C67<>"",IF(COUNTIFS(Stock!$D$4:$IP$4,B67,Stock!$D$5:$IP$5,C67)>0,SUMIFS(Stock!$D$32:$IP$32,Stock!$D$4:$IP$4,B67,Stock!$D$5:$IP$5,C67),IF(COUNTIF(Stock!$D$5:$IP$5,C67)>0,SUMIF(Stock!$D$5:$IP$5,C67,Stock!$D$32:$IP$32),SUMIF(Stock!$D$4:$IP$4,B67,Stock!$D$32:$IP$32))),SUMIF(Stock!$D$4:$IP$4,B67,Stock!$D$32:$IP$32))) -> 365 | I67: 4 LTR | K67: 120 | L67: =IF(AND(I67="",J67=""),"",IF(J67<>"",IF(COUNTIFS(Stock!$D$4:$IP$4,I67,Stock!$D$5:$IP$5,J67)>0,SUMIFS(Stock!$D$340:$IP$340,Stock!$D$4:$IP$4,I67,Stock!$D$5:$IP$5,J67),IF(COUNTIF(Stock!$D$5:$IP$5,J67)>0,SUMIF(Stock!$D$5:$IP$5,J67,Stock!$D$340:$IP$340),SUMIF(Stock!$D$4:$IP$4,I67,Stock!$D$340:$IP$340))),SUMIF(Stock!$D$4:$IP$4,I67,Stock!$D$340:$IP$340))) -> 0 | M67: =K67-L67 -> 120 | N67: =IF(AND(I67="",J67=""),"",IF(J67<>"",IF(COUNTIFS(Stock!$D$4:$IP$4,I67,Stock!$D$5:$IP$5,J67)>0,SUMIFS(Stock!$D$32:$IP$32,Stock!$D$4:$IP$4,I67,Stock!$D$5:$IP$5,J67),IF(COUNTIF(Stock!$D$5:$IP$5,J67)>0,SUMIF(Stock!$D$5:$IP$5,J67,Stock!$D$32:$IP$32),SUMIF(Stock!$D$4:$IP$4,I67,Stock!$D$32:$IP$32))),SUMIF(Stock!$D$4:$IP$4,I67,Stock!$D$32:$IP$32))) -> 120 | P67: Skoda | Q67: PC-8053 | R67: 100 | S67: =IF(AND(P67="",Q67=""),"",IF(Q67<>"",IF(COUNTIFS(Stock!$D$4:$IP$4,P67,Stock!$D$5:$IP$5,Q67)>0,SUMIFS(Stock!$D$340:$IP$340,Stock!$D$4:$IP$4,P67,Stock!$D$5:$IP$5,Q67),IF(COUNTIF(Stock!$D$5:$IP$5,Q67)>0,SUMIF(Stock!$D$5:$IP$5,Q67,Stock!$D$340:$IP$340),SUMIF(Stock!$D$4:$IP$4,P67,Stock!$D$340:$IP$340))),SUMIF(Stock!$D$4:$IP$4,P67,Stock!$D$340:$IP$340))) -> 100 | T67: =R67-S67 -> 0 | U67: =IF(AND(P67="",Q67=""),"",IF(Q67<>"",IF(COUNTIFS(Stock!$D$4:$IP$4,P67,Stock!$D$5:$IP$5,Q67)>0,SUMIFS(Stock!$D$32:$IP$32,Stock!$D$4:$IP$4,P67,Stock!$D$5:$IP$5,Q67),IF(COUNTIF(Stock!$D$5:$IP$5,Q67)>0,SUMIF(Stock!$D$5:$IP$5,Q67,Stock!$D$32:$IP$32),SUMIF(Stock!$D$4:$IP$4,P67,Stock!$D$32:$IP$32))),SUMIF(Stock!$D$4:$IP$4,P67,Stock!$D$32:$IP$32))) -> 100 | V67: PC8053
B68: PF/UNI 14X15X20MM | C68: "F" | D68: 479 | E68: =IF(AND(B68="",C68=""),"",IF(C68<>"",IF(COUNTIFS(Stock!$D$4:$IP$4,B68,Stock!$D$5:$IP$5,C68)>0,SUMIFS(Stock!$D$340:$IP$340,Stock!$D$4:$IP$4,B68,Stock!$D$5:$IP$5,C68),IF(COUNTIF(Stock!$D$5:$IP$5,C68)>0,SUMIF(Stock!$D$5:$IP$5,C68,Stock!$D$340:$IP$340),SUMIF(Stock!$D$4:$IP$4,B68,Stock!$D$340:$IP$340))),SUMIF(Stock!$D$4:$IP$4,B68,Stock!$D$340:$IP$340))) -> 605 | F68: =D68-E68 -> -126 | G68: =IF(AND(B68="",C68=""),"",IF(C68<>"",IF(COUNTIFS(Stock!$D$4:$IP$4,B68,Stock!$D$5:$IP$5,C68)>0,SUMIFS(Stock!$D$32:$IP$32,Stock!$D$4:$IP$4,B68,Stock!$D$5:$IP$5,C68),IF(COUNTIF(Stock!$D$5:$IP$5,C68)>0,SUMIF(Stock!$D$5:$IP$5,C68,Stock!$D$32:$IP$32),SUMIF(Stock!$D$4:$IP$4,B68,Stock!$D$32:$IP$32))),SUMIF(Stock!$D$4:$IP$4,B68,Stock!$D$32:$IP$32))) -> 605 | H68: compressor | I68: compressor | J68: SM-5 | K68: 141 | L68: =IF(AND(I68="",J68=""),"",IF(J68<>"",IF(COUNTIFS(Stock!$D$4:$IP$4,I68,Stock!$D$5:$IP$5,J68)>0,SUMIFS(Stock!$D$340:$IP$340,Stock!$D$4:$IP$4,I68,Stock!$D$5:$IP$5,J68),IF(COUNTIF(Stock!$D$5:$IP$5,J68)>0,SUMIF(Stock!$D$5:$IP$5,J68,Stock!$D$340:$IP$340),SUMIF(Stock!$D$4:$IP$4,I68,Stock!$D$340:$IP$340))),SUMIF(Stock!$D$4:$IP$4,I68,Stock!$D$340:$IP$340))) -> 140 | M68: =K68-L68 -> 1 | N68: =IF(AND(I68="",J68=""),"",IF(J68<>"",IF(COUNTIFS(Stock!$D$4:$IP$4,I68,Stock!$D$5:$IP$5,J68)>0,SUMIFS(Stock!$D$32:$IP$32,Stock!$D$4:$IP$4,I68,Stock!$D$5:$IP$5,J68),IF(COUNTIF(Stock!$D$5:$IP$5,J68)>0,SUMIF(Stock!$D$5:$IP$5,J68,Stock!$D$32:$IP$32),SUMIF(Stock!$D$4:$IP$4,I68,Stock!$D$32:$IP$32))),SUMIF(Stock!$D$4:$IP$4,I68,Stock!$D$32:$IP$32))) -> 140 | P68: JIVAN'S | Q68: F.DRIER | V68: UNIVERSALO;UNIVERSALORING
B69: PF/UNI 14X15X20MM | C69: "O" | D69: 170 | E69: =IF(AND(B69="",C69=""),"",IF(C69<>"",IF(COUNTIFS(Stock!$D$4:$IP$4,B69,Stock!$D$5:$IP$5,C69)>0,SUMIFS(Stock!$D$340:$IP$340,Stock!$D$4:$IP$4,B69,Stock!$D$5:$IP$5,C69),IF(COUNTIF(Stock!$D$5:$IP$5,C69)>0,SUMIF(Stock!$D$5:$IP$5,C69,Stock!$D$340:$IP$340),SUMIF(Stock!$D$4:$IP$4,B69,Stock!$D$340:$IP$340))),SUMIF(Stock!$D$4:$IP$4,B69,Stock!$D$340:$IP$340))) -> 355 | F69: =D69-E69 -> -185 | G69: =IF(AND(B69="",C69=""),"",IF(C69<>"",IF(COUNTIFS(Stock!$D$4:$IP$4,B69,Stock!$D$5:$IP$5,C69)>0,SUMIFS(Stock!$D$32:$IP$32,Stock!$D$4:$IP$4,B69,Stock!$D$5:$IP$5,C69),IF(COUNTIF(Stock!$D$5:$IP$5,C69)>0,SUMIF(Stock!$D$5:$IP$5,C69,Stock!$D$32:$IP$32),SUMIF(Stock!$D$4:$IP$4,B69,Stock!$D$32:$IP$32))),SUMIF(Stock!$D$4:$IP$4,B69,Stock!$D$32:$IP$32))) -> 355 | J69: SM-7 | L69: =IF(AND(I69="",J69=""),"",IF(J69<>"",IF(COUNTIFS(Stock!$D$4:$IP$4,I69,Stock!$D$5:$IP$5,J69)>0,SUMIFS(Stock!$D$340:$IP$340,Stock!$D$4:$IP$4,I69,Stock!$D$5:$IP$5,J69),IF(COUNTIF(Stock!$D$5:$IP$5,J69)>0,SUMIF(Stock!$D$5:$IP$5,J69,Stock!$D$340:$IP$340),SUMIF(Stock!$D$4:$IP$4,I69,Stock!$D$340:$IP$340))),SUMIF(Stock!$D$4:$IP$4,I69,Stock!$D$340:$IP$340))) -> 804 | M69: =K69-L69 -> -804 | N69: =IF(AND(I69="",J69=""),"",IF(J69<>"",IF(COUNTIFS(Stock!$D$4:$IP$4,I69,Stock!$D$5:$IP$5,J69)>0,SUMIFS(Stock!$D$32:$IP$32,Stock!$D$4:$IP$4,I69,Stock!$D$5:$IP$5,J69),IF(COUNTIF(Stock!$D$5:$IP$5,J69)>0,SUMIF(Stock!$D$5:$IP$5,J69,Stock!$D$32:$IP$32),SUMIF(Stock!$D$4:$IP$4,I69,Stock!$D$32:$IP$32))),SUMIF(Stock!$D$4:$IP$4,I69,Stock!$D$32:$IP$32))) -> 840 | P69: Seal | R69: Challan (pcs) <=283 | S69: Stock Sold (<=283) | T69: Gap | V69: Match Key(s) | W69: Stock col / guard
B70: PF/UNI 14X14X20MM | C70: "F" | D70: 120 | E70: =IF(AND(B70="",C70=""),"",IF(C70<>"",IF(COUNTIFS(Stock!$D$4:$IP$4,B70,Stock!$D$5:$IP$5,C70)>0,SUMIFS(Stock!$D$340:$IP$340,Stock!$D$4:$IP$4,B70,Stock!$D$5:$IP$5,C70),IF(COUNTIF(Stock!$D$5:$IP$5,C70)>0,SUMIF(Stock!$D$5:$IP$5,C70,Stock!$D$340:$IP$340),SUMIF(Stock!$D$4:$IP$4,B70,Stock!$D$340:$IP$340))),SUMIF(Stock!$D$4:$IP$4,B70,Stock!$D$340:$IP$340))) -> 0 | F70: =D70-E70 -> 120 | G70: =IF(AND(B70="",C70=""),"",IF(C70<>"",IF(COUNTIFS(Stock!$D$4:$IP$4,B70,Stock!$D$5:$IP$5,C70)>0,SUMIFS(Stock!$D$32:$IP$32,Stock!$D$4:$IP$4,B70,Stock!$D$5:$IP$5,C70),IF(COUNTIF(Stock!$D$5:$IP$5,C70)>0,SUMIF(Stock!$D$5:$IP$5,C70,Stock!$D$32:$IP$32),SUMIF(Stock!$D$4:$IP$4,B70,Stock!$D$32:$IP$32))),SUMIF(Stock!$D$4:$IP$4,B70,Stock!$D$32:$IP$32))) -> 0 | J70: SM-8 | L70: =IF(AND(I70="",J70=""),"",IF(J70<>"",IF(COUNTIFS(Stock!$D$4:$IP$4,I70,Stock!$D$5:$IP$5,J70)>0,SUMIFS(Stock!$D$340:$IP$340,Stock!$D$4:$IP$4,I70,Stock!$D$5:$IP$5,J70),IF(COUNTIF(Stock!$D$5:$IP$5,J70)>0,SUMIF(Stock!$D$5:$IP$5,J70,Stock!$D$340:$IP$340),SUMIF(Stock!$D$4:$IP$4,I70,Stock!$D$340:$IP$340))),SUMIF(Stock!$D$4:$IP$4,I70,Stock!$D$340:$IP$340))) -> 312 | M70: =K70-L70 -> -312 | N70: =IF(AND(I70="",J70=""),"",IF(J70<>"",IF(COUNTIFS(Stock!$D$4:$IP$4,I70,Stock!$D$5:$IP$5,J70)>0,SUMIFS(Stock!$D$32:$IP$32,Stock!$D$4:$IP$4,I70,Stock!$D$5:$IP$5,J70),IF(COUNTIF(Stock!$D$5:$IP$5,J70)>0,SUMIF(Stock!$D$5:$IP$5,J70,Stock!$D$32:$IP$32),SUMIF(Stock!$D$4:$IP$4,I70,Stock!$D$32:$IP$32))),SUMIF(Stock!$D$4:$IP$4,I70,Stock!$D$32:$IP$32))) -> 280 | P70: WR | Q70: PC-7038A | R70: 1009 | S70: =IF(AND(P70="",Q70=""),"",IF(Q70<>"",IF(COUNTIFS(Stock!$D$4:$IP$4,P70,Stock!$D$5:$IP$5,Q70)>0,SUMIFS(Stock!$D$340:$IP$340,Stock!$D$4:$IP$4,P70,Stock!$D$5:$IP$5,Q70),IF(COUNTIF(Stock!$D$5:$IP$5,Q70)>0,SUMIF(Stock!$D$5:$IP$5,Q70,Stock!$D$340:$IP$340),SUMIF(Stock!$D$4:$IP$4,P70,Stock!$D$340:$IP$340))),SUMIF(Stock!$D$4:$IP$4,P70,Stock!$D$340:$IP$340))) -> 200 | T70: =R70-S70 -> 809 | U70: =IF(AND(P70="",Q70=""),"",IF(Q70<>"",IF(COUNTIFS(Stock!$D$4:$IP$4,P70,Stock!$D$5:$IP$5,Q70)>0,SUMIFS(Stock!$D$32:$IP$32,Stock!$D$4:$IP$4,P70,Stock!$D$5:$IP$5,Q70),IF(COUNTIF(Stock!$D$5:$IP$5,Q70)>0,SUMIF(Stock!$D$5:$IP$5,Q70,Stock!$D$32:$IP$32),SUMIF(Stock!$D$4:$IP$4,P70,Stock!$D$32:$IP$32))),SUMIF(Stock!$D$4:$IP$4,P70,Stock!$D$32:$IP$32))) -> 500 | V70: PC7038A;PC7038D;SEALWRALTO;WRSEAL
B71: PF/UNI 14X14X20MM | C71: "O" | D71: 60 | E71: =IF(AND(B71="",C71=""),"",IF(C71<>"",IF(COUNTIFS(Stock!$D$4:$IP$4,B71,Stock!$D$5:$IP$5,C71)>0,SUMIFS(Stock!$D$340:$IP$340,Stock!$D$4:$IP$4,B71,Stock!$D$5:$IP$5,C71),IF(COUNTIF(Stock!$D$5:$IP$5,C71)>0,SUMIF(Stock!$D$5:$IP$5,C71,Stock!$D$340:$IP$340),SUMIF(Stock!$D$4:$IP$4,B71,Stock!$D$340:$IP$340))),SUMIF(Stock!$D$4:$IP$4,B71,Stock!$D$340:$IP$340))) -> 0 | F71: =D71-E71 -> 60 | G71: =IF(AND(B71="",C71=""),"",IF(C71<>"",IF(COUNTIFS(Stock!$D$4:$IP$4,B71,Stock!$D$5:$IP$5,C71)>0,SUMIFS(Stock!$D$32:$IP$32,Stock!$D$4:$IP$4,B71,Stock!$D$5:$IP$5,C71),IF(COUNTIF(Stock!$D$5:$IP$5,C71)>0,SUMIF(Stock!$D$5:$IP$5,C71,Stock!$D$32:$IP$32),SUMIF(Stock!$D$4:$IP$4,B71,Stock!$D$32:$IP$32))),SUMIF(Stock!$D$4:$IP$4,B71,Stock!$D$32:$IP$32))) -> 0 | J71: SM-10 | L71: =IF(AND(I71="",J71=""),"",IF(J71<>"",IF(COUNTIFS(Stock!$D$4:$IP$4,I71,Stock!$D$5:$IP$5,J71)>0,SUMIFS(Stock!$D$340:$IP$340,Stock!$D$4:$IP$4,I71,Stock!$D$5:$IP$5,J71),IF(COUNTIF(Stock!$D$5:$IP$5,J71)>0,SUMIF(Stock!$D$5:$IP$5,J71,Stock!$D$340:$IP$340),SUMIF(Stock!$D$4:$IP$4,I71,Stock!$D$340:$IP$340))),SUMIF(Stock!$D$4:$IP$4,I71,Stock!$D$340:$IP$340))) -> 81 | M71: =K71-L71 -> -81 | N71: =IF(AND(I71="",J71=""),"",IF(J71<>"",IF(COUNTIFS(Stock!$D$4:$IP$4,I71,Stock!$D$5:$IP$5,J71)>0,SUMIFS(Stock!$D$32:$IP$32,Stock!$D$4:$IP$4,I71,Stock!$D$5:$IP$5,J71),IF(COUNTIF(Stock!$D$5:$IP$5,J71)>0,SUMIF(Stock!$D$5:$IP$5,J71,Stock!$D$32:$IP$32),SUMIF(Stock!$D$4:$IP$4,I71,Stock!$D$32:$IP$32))),SUMIF(Stock!$D$4:$IP$4,I71,Stock!$D$32:$IP$32))) -> 140 | P71: 507 single seal | Q71: PC-7053A | R71: 2350 | S71: =IF(AND(P71="",Q71=""),"",IF(Q71<>"",IF(COUNTIFS(Stock!$D$4:$IP$4,P71,Stock!$D$5:$IP$5,Q71)>0,SUMIFS(Stock!$D$340:$IP$340,Stock!$D$4:$IP$4,P71,Stock!$D$5:$IP$5,Q71),IF(COUNTIF(Stock!$D$5:$IP$5,Q71)>0,SUMIF(Stock!$D$5:$IP$5,Q71,Stock!$D$340:$IP$340),SUMIF(Stock!$D$4:$IP$4,P71,Stock!$D$340:$IP$340))),SUMIF(Stock!$D$4:$IP$4,P71,Stock!$D$340:$IP$340))) -> 573 | T71: =R71-S71 -> 1777 | U71: =IF(AND(P71="",Q71=""),"",IF(Q71<>"",IF(COUNTIFS(Stock!$D$4:$IP$4,P71,Stock!$D$5:$IP$5,Q71)>0,SUMIFS(Stock!$D$32:$IP$32,Stock!$D$4:$IP$4,P71,Stock!$D$5:$IP$5,Q71),IF(COUNTIF(Stock!$D$5:$IP$5,Q71)>0,SUMIF(Stock!$D$5:$IP$5,Q71,Stock!$D$32:$IP$32),SUMIF(Stock!$D$4:$IP$4,P71,Stock!$D$32:$IP$32))),SUMIF(Stock!$D$4:$IP$4,P71,Stock!$D$32:$IP$32))) -> 3048 | V71: PC7053A;SEAL507SINGLE
B72: PF/UNI 14X18X16MM | D72: 100 | E72: =IF(AND(B72="",C72=""),"",IF(C72<>"",IF(COUNTIFS(Stock!$D$4:$IP$4,B72,Stock!$D$5:$IP$5,C72)>0,SUMIFS(Stock!$D$340:$IP$340,Stock!$D$4:$IP$4,B72,Stock!$D$5:$IP$5,C72),IF(COUNTIF(Stock!$D$5:$IP$5,C72)>0,SUMIF(Stock!$D$5:$IP$5,C72,Stock!$D$340:$IP$340),SUMIF(Stock!$D$4:$IP$4,B72,Stock!$D$340:$IP$340))),SUMIF(Stock!$D$4:$IP$4,B72,Stock!$D$340:$IP$340))) -> 100 | F72: =D72-E72 -> 0 | G72: =IF(AND(B72="",C72=""),"",IF(C72<>"",IF(COUNTIFS(Stock!$D$4:$IP$4,B72,Stock!$D$5:$IP$5,C72)>0,SUMIFS(Stock!$D$32:$IP$32,Stock!$D$4:$IP$4,B72,Stock!$D$5:$IP$5,C72),IF(COUNTIF(Stock!$D$5:$IP$5,C72)>0,SUMIF(Stock!$D$5:$IP$5,C72,Stock!$D$32:$IP$32),SUMIF(Stock!$D$4:$IP$4,B72,Stock!$D$32:$IP$32))),SUMIF(Stock!$D$4:$IP$4,B72,Stock!$D$32:$IP$32))) -> 100 | I72: COMP BACK PLATE | J72: 505/507 | K72: 150 | L72: =IF(AND(I72="",J72=""),"",IF(J72<>"",IF(COUNTIFS(Stock!$D$4:$IP$4,I72,Stock!$D$5:$IP$5,J72)>0,SUMIFS(Stock!$D$340:$IP$340,Stock!$D$4:$IP$4,I72,Stock!$D$5:$IP$5,J72),IF(COUNTIF(Stock!$D$5:$IP$5,J72)>0,SUMIF(Stock!$D$5:$IP$5,J72,Stock!$D$340:$IP$340),SUMIF(Stock!$D$4:$IP$4,I72,Stock!$D$340:$IP$340))),SUMIF(Stock!$D$4:$IP$4,I72,Stock!$D$340:$IP$340))) -> 0 | M72: =K72-L72 -> 150 | N72: =IF(AND(I72="",J72=""),"",IF(J72<>"",IF(COUNTIFS(Stock!$D$4:$IP$4,I72,Stock!$D$5:$IP$5,J72)>0,SUMIFS(Stock!$D$32:$IP$32,Stock!$D$4:$IP$4,I72,Stock!$D$5:$IP$5,J72),IF(COUNTIF(Stock!$D$5:$IP$5,J72)>0,SUMIF(Stock!$D$5:$IP$5,J72,Stock!$D$32:$IP$32),SUMIF(Stock!$D$4:$IP$4,I72,Stock!$D$32:$IP$32))),SUMIF(Stock!$D$4:$IP$4,I72,Stock!$D$32:$IP$32))) -> 200 | P72: Santro Large-matiz | Q72: PC-7058A | R72: 350 | S72: =IF(AND(P72="",Q72=""),"",IF(Q72<>"",IF(COUNTIFS(Stock!$D$4:$IP$4,P72,Stock!$D$5:$IP$5,Q72)>0,SUMIFS(Stock!$D$340:$IP$340,Stock!$D$4:$IP$4,P72,Stock!$D$5:$IP$5,Q72),IF(COUNTIF(Stock!$D$5:$IP$5,Q72)>0,SUMIF(Stock!$D$5:$IP$5,Q72,Stock!$D$340:$IP$340),SUMIF(Stock!$D$4:$IP$4,P72,Stock!$D$340:$IP$340))),SUMIF(Stock!$D$4:$IP$4,P72,Stock!$D$340:$IP$340))) -> 300 | T72: =R72-S72 -> 50 | U72: =IF(AND(P72="",Q72=""),"",IF(Q72<>"",IF(COUNTIFS(Stock!$D$4:$IP$4,P72,Stock!$D$5:$IP$5,Q72)>0,SUMIFS(Stock!$D$32:$IP$32,Stock!$D$4:$IP$4,P72,Stock!$D$5:$IP$5,Q72),IF(COUNTIF(Stock!$D$5:$IP$5,Q72)>0,SUMIF(Stock!$D$5:$IP$5,Q72,Stock!$D$32:$IP$32),SUMIF(Stock!$D$4:$IP$4,P72,Stock!$D$32:$IP$32))),SUMIF(Stock!$D$4:$IP$4,P72,Stock!$D$32:$IP$32))) -> 2300 | V72: PC7058A
B73: PF/UNI 14X18X20MM | D73: 200 | E73: =IF(AND(B73="",C73=""),"",IF(C73<>"",IF(COUNTIFS(Stock!$D$4:$IP$4,B73,Stock!$D$5:$IP$5,C73)>0,SUMIFS(Stock!$D$340:$IP$340,Stock!$D$4:$IP$4,B73,Stock!$D$5:$IP$5,C73),IF(COUNTIF(Stock!$D$5:$IP$5,C73)>0,SUMIF(Stock!$D$5:$IP$5,C73,Stock!$D$340:$IP$340),SUMIF(Stock!$D$4:$IP$4,B73,Stock!$D$340:$IP$340))),SUMIF(Stock!$D$4:$IP$4,B73,Stock!$D$340:$IP$340))) -> 200 | F73: =D73-E73 -> 0 | G73: =IF(AND(B73="",C73=""),"",IF(C73<>"",IF(COUNTIFS(Stock!$D$4:$IP$4,B73,Stock!$D$5:$IP$5,C73)>0,SUMIFS(Stock!$D$32:$IP$32,Stock!$D$4:$IP$4,B73,Stock!$D$5:$IP$5,C73),IF(COUNTIF(Stock!$D$5:$IP$5,C73)>0,SUMIF(Stock!$D$5:$IP$5,C73,Stock!$D$32:$IP$32),SUMIF(Stock!$D$4:$IP$4,B73,Stock!$D$32:$IP$32))),SUMIF(Stock!$D$4:$IP$4,B73,Stock!$D$32:$IP$32))) -> 200 | J73: 508/510 | L73: =IF(AND(I73="",J73=""),"",IF(J73<>"",IF(COUNTIFS(Stock!$D$4:$IP$4,I73,Stock!$D$5:$IP$5,J73)>0,SUMIFS(Stock!$D$340:$IP$340,Stock!$D$4:$IP$4,I73,Stock!$D$5:$IP$5,J73),IF(COUNTIF(Stock!$D$5:$IP$5,J73)>0,SUMIF(Stock!$D$5:$IP$5,J73,Stock!$D$340:$IP$340),SUMIF(Stock!$D$4:$IP$4,I73,Stock!$D$340:$IP$340))),SUMIF(Stock!$D$4:$IP$4,I73,Stock!$D$340:$IP$340))) -> 0 | M73: =K73-L73 -> 0 | N73: =IF(AND(I73="",J73=""),"",IF(J73<>"",IF(COUNTIFS(Stock!$D$4:$IP$4,I73,Stock!$D$5:$IP$5,J73)>0,SUMIFS(Stock!$D$32:$IP$32,Stock!$D$4:$IP$4,I73,Stock!$D$5:$IP$5,J73),IF(COUNTIF(Stock!$D$5:$IP$5,J73)>0,SUMIF(Stock!$D$5:$IP$5,J73,Stock!$D$32:$IP$32),SUMIF(Stock!$D$4:$IP$4,I73,Stock!$D$32:$IP$32))),SUMIF(Stock!$D$4:$IP$4,I73,Stock!$D$32:$IP$32))) -> 100 | P73: TM-16 | Q73: PC-7046A | S73: =IF(AND(P73="",Q73=""),"",IF(Q73<>"",IF(COUNTIFS(Stock!$D$4:$IP$4,P73,Stock!$D$5:$IP$5,Q73)>0,SUMIFS(Stock!$D$340:$IP$340,Stock!$D$4:$IP$4,P73,Stock!$D$5:$IP$5,Q73),IF(COUNTIF(Stock!$D$5:$IP$5,Q73)>0,SUMIF(Stock!$D$5:$IP$5,Q73,Stock!$D$340:$IP$340),SUMIF(Stock!$D$4:$IP$4,P73,Stock!$D$340:$IP$340))),SUMIF(Stock!$D$4:$IP$4,P73,Stock!$D$340:$IP$340))) -> 0 | T73: =R73-S73 -> 0 | U73: =IF(AND(P73="",Q73=""),"",IF(Q73<>"",IF(COUNTIFS(Stock!$D$4:$IP$4,P73,Stock!$D$5:$IP$5,Q73)>0,SUMIFS(Stock!$D$32:$IP$32,Stock!$D$4:$IP$4,P73,Stock!$D$5:$IP$5,Q73),IF(COUNTIF(Stock!$D$5:$IP$5,Q73)>0,SUMIF(Stock!$D$5:$IP$5,Q73,Stock!$D$32:$IP$32),SUMIF(Stock!$D$4:$IP$4,P73,Stock!$D$32:$IP$32))),SUMIF(Stock!$D$4:$IP$4,P73,Stock!$D$32:$IP$32))) -> 325 | V73: PC7046A
B74: PF/UNI 14X21X16MM | D74: 100 | E74: =IF(AND(B74="",C74=""),"",IF(C74<>"",IF(COUNTIFS(Stock!$D$4:$IP$4,B74,Stock!$D$5:$IP$5,C74)>0,SUMIFS(Stock!$D$340:$IP$340,Stock!$D$4:$IP$4,B74,Stock!$D$5:$IP$5,C74),IF(COUNTIF(Stock!$D$5:$IP$5,C74)>0,SUMIF(Stock!$D$5:$IP$5,C74,Stock!$D$340:$IP$340),SUMIF(Stock!$D$4:$IP$4,B74,Stock!$D$340:$IP$340))),SUMIF(Stock!$D$4:$IP$4,B74,Stock!$D$340:$IP$340))) -> 150 | F74: =D74-E74 -> -50 | G74: =IF(AND(B74="",C74=""),"",IF(C74<>"",IF(COUNTIFS(Stock!$D$4:$IP$4,B74,Stock!$D$5:$IP$5,C74)>0,SUMIFS(Stock!$D$32:$IP$32,Stock!$D$4:$IP$4,B74,Stock!$D$5:$IP$5,C74),IF(COUNTIF(Stock!$D$5:$IP$5,C74)>0,SUMIF(Stock!$D$5:$IP$5,C74,Stock!$D$32:$IP$32),SUMIF(Stock!$D$4:$IP$4,B74,Stock!$D$32:$IP$32))),SUMIF(Stock!$D$4:$IP$4,B74,Stock!$D$32:$IP$32))) -> 100 | I74: HCC | J74: SANTRO | K74: 200 | L74: =IF(AND(I74="",J74=""),"",IF(J74<>"",IF(COUNTIFS(Stock!$D$4:$IP$4,I74,Stock!$D$5:$IP$5,J74)>0,SUMIFS(Stock!$D$340:$IP$340,Stock!$D$4:$IP$4,I74,Stock!$D$5:$IP$5,J74),IF(COUNTIF(Stock!$D$5:$IP$5,J74)>0,SUMIF(Stock!$D$5:$IP$5,J74,Stock!$D$340:$IP$340),SUMIF(Stock!$D$4:$IP$4,I74,Stock!$D$340:$IP$340))),SUMIF(Stock!$D$4:$IP$4,I74,Stock!$D$340:$IP$340))) -> 200 | M74: =K74-L74 -> 0 | N74: =IF(AND(I74="",J74=""),"",IF(J74<>"",IF(COUNTIFS(Stock!$D$4:$IP$4,I74,Stock!$D$5:$IP$5,J74)>0,SUMIFS(Stock!$D$32:$IP$32,Stock!$D$4:$IP$4,I74,Stock!$D$5:$IP$5,J74),IF(COUNTIF(Stock!$D$5:$IP$5,J74)>0,SUMIF(Stock!$D$5:$IP$5,J74,Stock!$D$32:$IP$32),SUMIF(Stock!$D$4:$IP$4,I74,Stock!$D$32:$IP$32))),SUMIF(Stock!$D$4:$IP$4,I74,Stock!$D$32:$IP$32))) -> 200 | P74: Clelo | Q74: PC-7059A | R74: 30 | S74: =IF(AND(P74="",Q74=""),"",IF(Q74<>"",IF(COUNTIFS(Stock!$D$4:$IP$4,P74,Stock!$D$5:$IP$5,Q74)>0,SUMIFS(Stock!$D$340:$IP$340,Stock!$D$4:$IP$4,P74,Stock!$D$5:$IP$5,Q74),IF(COUNTIF(Stock!$D$5:$IP$5,Q74)>0,SUMIF(Stock!$D$5:$IP$5,Q74,Stock!$D$340:$IP$340),SUMIF(Stock!$D$4:$IP$4,P74,Stock!$D$340:$IP$340))),SUMIF(Stock!$D$4:$IP$4,P74,Stock!$D$340:$IP$340))) -> 0 | T74: =R74-S74 -> 30 | U74: =IF(AND(P74="",Q74=""),"",IF(Q74<>"",IF(COUNTIFS(Stock!$D$4:$IP$4,P74,Stock!$D$5:$IP$5,Q74)>0,SUMIFS(Stock!$D$32:$IP$32,Stock!$D$4:$IP$4,P74,Stock!$D$5:$IP$5,Q74),IF(COUNTIF(Stock!$D$5:$IP$5,Q74)>0,SUMIF(Stock!$D$5:$IP$5,Q74,Stock!$D$32:$IP$32),SUMIF(Stock!$D$4:$IP$4,P74,Stock!$D$32:$IP$32))),SUMIF(Stock!$D$4:$IP$4,P74,Stock!$D$32:$IP$32))) -> 50 | V74: PC7059A
B75: PF/UNI 14X21X20MM | D75: 150 | E75: =IF(AND(B75="",C75=""),"",IF(C75<>"",IF(COUNTIFS(Stock!$D$4:$IP$4,B75,Stock!$D$5:$IP$5,C75)>0,SUMIFS(Stock!$D$340:$IP$340,Stock!$D$4:$IP$4,B75,Stock!$D$5:$IP$5,C75),IF(COUNTIF(Stock!$D$5:$IP$5,C75)>0,SUMIF(Stock!$D$5:$IP$5,C75,Stock!$D$340:$IP$340),SUMIF(Stock!$D$4:$IP$4,B75,Stock!$D$340:$IP$340))),SUMIF(Stock!$D$4:$IP$4,B75,Stock!$D$340:$IP$340))) -> 150 | F75: =D75-E75 -> 0 | G75: =IF(AND(B75="",C75=""),"",IF(C75<>"",IF(COUNTIFS(Stock!$D$4:$IP$4,B75,Stock!$D$5:$IP$5,C75)>0,SUMIFS(Stock!$D$32:$IP$32,Stock!$D$4:$IP$4,B75,Stock!$D$5:$IP$5,C75),IF(COUNTIF(Stock!$D$5:$IP$5,C75)>0,SUMIF(Stock!$D$5:$IP$5,C75,Stock!$D$32:$IP$32),SUMIF(Stock!$D$4:$IP$4,B75,Stock!$D$32:$IP$32))),SUMIF(Stock!$D$4:$IP$4,B75,Stock!$D$32:$IP$32))) -> 250 | I75: HCC | J75: SONATA | K75: 10 | L75: =IF(AND(I75="",J75=""),"",IF(J75<>"",IF(COUNTIFS(Stock!$D$4:$IP$4,I75,Stock!$D$5:$IP$5,J75)>0,SUMIFS(Stock!$D$340:$IP$340,Stock!$D$4:$IP$4,I75,Stock!$D$5:$IP$5,J75),IF(COUNTIF(Stock!$D$5:$IP$5,J75)>0,SUMIF(Stock!$D$5:$IP$5,J75,Stock!$D$340:$IP$340),SUMIF(Stock!$D$4:$IP$4,I75,Stock!$D$340:$IP$340))),SUMIF(Stock!$D$4:$IP$4,I75,Stock!$D$340:$IP$340))) -> 30 | M75: =K75-L75 -> -20 | N75: =IF(AND(I75="",J75=""),"",IF(J75<>"",IF(COUNTIFS(Stock!$D$4:$IP$4,I75,Stock!$D$5:$IP$5,J75)>0,SUMIFS(Stock!$D$32:$IP$32,Stock!$D$4:$IP$4,I75,Stock!$D$5:$IP$5,J75),IF(COUNTIF(Stock!$D$5:$IP$5,J75)>0,SUMIF(Stock!$D$5:$IP$5,J75,Stock!$D$32:$IP$32),SUMIF(Stock!$D$4:$IP$4,I75,Stock!$D$32:$IP$32))),SUMIF(Stock!$D$4:$IP$4,I75,Stock!$D$32:$IP$32))) -> 30 | P75: TQ | Q75: PC-7032A | R75: 251 | S75: =IF(AND(P75="",Q75=""),"",IF(Q75<>"",IF(COUNTIFS(Stock!$D$4:$IP$4,P75,Stock!$D$5:$IP$5,Q75)>0,SUMIFS(Stock!$D$340:$IP$340,Stock!$D$4:$IP$4,P75,Stock!$D$5:$IP$5,Q75),IF(COUNTIF(Stock!$D$5:$IP$5,Q75)>0,SUMIF(Stock!$D$5:$IP$5,Q75,Stock!$D$340:$IP$340),SUMIF(Stock!$D$4:$IP$4,P75,Stock!$D$340:$IP$340))),SUMIF(Stock!$D$4:$IP$4,P75,Stock!$D$340:$IP$340))) -> 292 | T75: =R75-S75 -> -41 | U75: =IF(AND(P75="",Q75=""),"",IF(Q75<>"",IF(COUNTIFS(Stock!$D$4:$IP$4,P75,Stock!$D$5:$IP$5,Q75)>0,SUMIFS(Stock!$D$32:$IP$32,Stock!$D$4:$IP$4,P75,Stock!$D$5:$IP$5,Q75),IF(COUNTIF(Stock!$D$5:$IP$5,Q75)>0,SUMIF(Stock!$D$5:$IP$5,Q75,Stock!$D$32:$IP$32),SUMIF(Stock!$D$4:$IP$4,P75,Stock!$D$32:$IP$32))),SUMIF(Stock!$D$4:$IP$4,P75,Stock!$D$32:$IP$32))) -> 792 | V75: PC7032A
B76: PF/UNI 14X23X16MM | D76: 50 | E76: =IF(AND(B76="",C76=""),"",IF(C76<>"",IF(COUNTIFS(Stock!$D$4:$IP$4,B76,Stock!$D$5:$IP$5,C76)>0,SUMIFS(Stock!$D$340:$IP$340,Stock!$D$4:$IP$4,B76,Stock!$D$5:$IP$5,C76),IF(COUNTIF(Stock!$D$5:$IP$5,C76)>0,SUMIF(Stock!$D$5:$IP$5,C76,Stock!$D$340:$IP$340),SUMIF(Stock!$D$4:$IP$4,B76,Stock!$D$340:$IP$340))),SUMIF(Stock!$D$4:$IP$4,B76,Stock!$D$340:$IP$340))) -> 50 | F76: =D76-E76 -> 0 | G76: =IF(AND(B76="",C76=""),"",IF(C76<>"",IF(COUNTIFS(Stock!$D$4:$IP$4,B76,Stock!$D$5:$IP$5,C76)>0,SUMIFS(Stock!$D$32:$IP$32,Stock!$D$4:$IP$4,B76,Stock!$D$5:$IP$5,C76),IF(COUNTIF(Stock!$D$5:$IP$5,C76)>0,SUMIF(Stock!$D$5:$IP$5,C76,Stock!$D$32:$IP$32),SUMIF(Stock!$D$4:$IP$4,B76,Stock!$D$32:$IP$32))),SUMIF(Stock!$D$4:$IP$4,B76,Stock!$D$32:$IP$32))) -> 100 | I76: HCC | J76: ELANTRA-2006 | K76: 5 | L76: =IF(AND(I76="",J76=""),"",IF(J76<>"",IF(COUNTIFS(Stock!$D$4:$IP$4,I76,Stock!$D$5:$IP$5,J76)>0,SUMIFS(Stock!$D$340:$IP$340,Stock!$D$4:$IP$4,I76,Stock!$D$5:$IP$5,J76),IF(COUNTIF(Stock!$D$5:$IP$5,J76)>0,SUMIF(Stock!$D$5:$IP$5,J76,Stock!$D$340:$IP$340),SUMIF(Stock!$D$4:$IP$4,I76,Stock!$D$340:$IP$340))),SUMIF(Stock!$D$4:$IP$4,I76,Stock!$D$340:$IP$340))) -> 5 | M76: =K76-L76 -> 0 | N76: =IF(AND(I76="",J76=""),"",IF(J76<>"",IF(COUNTIFS(Stock!$D$4:$IP$4,I76,Stock!$D$5:$IP$5,J76)>0,SUMIFS(Stock!$D$32:$IP$32,Stock!$D$4:$IP$4,I76,Stock!$D$5:$IP$5,J76),IF(COUNTIF(Stock!$D$5:$IP$5,J76)>0,SUMIF(Stock!$D$5:$IP$5,J76,Stock!$D$32:$IP$32),SUMIF(Stock!$D$4:$IP$4,I76,Stock!$D$32:$IP$32))),SUMIF(Stock!$D$4:$IP$4,I76,Stock!$D$32:$IP$32))) -> 5 | P76: ND | Q76: PC-7031A | R76: 1305 | S76: =IF(AND(P76="",Q76=""),"",IF(Q76<>"",IF(COUNTIFS(Stock!$D$4:$IP$4,P76,Stock!$D$5:$IP$5,Q76)>0,SUMIFS(Stock!$D$340:$IP$340,Stock!$D$4:$IP$4,P76,Stock!$D$5:$IP$5,Q76),IF(COUNTIF(Stock!$D$5:$IP$5,Q76)>0,SUMIF(Stock!$D$5:$IP$5,Q76,Stock!$D$340:$IP$340),SUMIF(Stock!$D$4:$IP$4,P76,Stock!$D$340:$IP$340))),SUMIF(Stock!$D$4:$IP$4,P76,Stock!$D$340:$IP$340))) -> 300 | T76: =R76-S76 -> 1005 | U76: =IF(AND(P76="",Q76=""),"",IF(Q76<>"",IF(COUNTIFS(Stock!$D$4:$IP$4,P76,Stock!$D$5:$IP$5,Q76)>0,SUMIFS(Stock!$D$32:$IP$32,Stock!$D$4:$IP$4,P76,Stock!$D$5:$IP$5,Q76),IF(COUNTIF(Stock!$D$5:$IP$5,Q76)>0,SUMIF(Stock!$D$5:$IP$5,Q76,Stock!$D$32:$IP$32),SUMIF(Stock!$D$4:$IP$4,P76,Stock!$D$32:$IP$32))),SUMIF(Stock!$D$4:$IP$4,P76,Stock!$D$32:$IP$32))) -> 2688 | V76: PC7031A;NDSUBROS;SEALND
B77: PF/UNI 14X23X20MM | D77: 200 | E77: =IF(AND(B77="",C77=""),"",IF(C77<>"",IF(COUNTIFS(Stock!$D$4:$IP$4,B77,Stock!$D$5:$IP$5,C77)>0,SUMIFS(Stock!$D$340:$IP$340,Stock!$D$4:$IP$4,B77,Stock!$D$5:$IP$5,C77),IF(COUNTIF(Stock!$D$5:$IP$5,C77)>0,SUMIF(Stock!$D$5:$IP$5,C77,Stock!$D$340:$IP$340),SUMIF(Stock!$D$4:$IP$4,B77,Stock!$D$340:$IP$340))),SUMIF(Stock!$D$4:$IP$4,B77,Stock!$D$340:$IP$340))) -> 150 | F77: =D77-E77 -> 50 | G77: =IF(AND(B77="",C77=""),"",IF(C77<>"",IF(COUNTIFS(Stock!$D$4:$IP$4,B77,Stock!$D$5:$IP$5,C77)>0,SUMIFS(Stock!$D$32:$IP$32,Stock!$D$4:$IP$4,B77,Stock!$D$5:$IP$5,C77),IF(COUNTIF(Stock!$D$5:$IP$5,C77)>0,SUMIF(Stock!$D$5:$IP$5,C77,Stock!$D$32:$IP$32),SUMIF(Stock!$D$4:$IP$4,B77,Stock!$D$32:$IP$32))),SUMIF(Stock!$D$4:$IP$4,B77,Stock!$D$32:$IP$32))) -> 200 | I77: HCC | J77: ELANTRA-2000 | K77: 5 | L77: =IF(AND(I77="",J77=""),"",IF(J77<>"",IF(COUNTIFS(Stock!$D$4:$IP$4,I77,Stock!$D$5:$IP$5,J77)>0,SUMIFS(Stock!$D$340:$IP$340,Stock!$D$4:$IP$4,I77,Stock!$D$5:$IP$5,J77),IF(COUNTIF(Stock!$D$5:$IP$5,J77)>0,SUMIF(Stock!$D$5:$IP$5,J77,Stock!$D$340:$IP$340),SUMIF(Stock!$D$4:$IP$4,I77,Stock!$D$340:$IP$340))),SUMIF(Stock!$D$4:$IP$4,I77,Stock!$D$340:$IP$340))) -> 5 | M77: =K77-L77 -> 0 | N77: =IF(AND(I77="",J77=""),"",IF(J77<>"",IF(COUNTIFS(Stock!$D$4:$IP$4,I77,Stock!$D$5:$IP$5,J77)>0,SUMIFS(Stock!$D$32:$IP$32,Stock!$D$4:$IP$4,I77,Stock!$D$5:$IP$5,J77),IF(COUNTIF(Stock!$D$5:$IP$5,J77)>0,SUMIF(Stock!$D$5:$IP$5,J77,Stock!$D$32:$IP$32),SUMIF(Stock!$D$4:$IP$4,I77,Stock!$D$32:$IP$32))),SUMIF(Stock!$D$4:$IP$4,I77,Stock!$D$32:$IP$32))) -> 5 | P77: Santro small-SWIFT | Q77: PC-7034A | R77: 50 | S77: =IF(AND(P77="",Q77=""),"",IF(Q77<>"",IF(COUNTIFS(Stock!$D$4:$IP$4,P77,Stock!$D$5:$IP$5,Q77)>0,SUMIFS(Stock!$D$340:$IP$340,Stock!$D$4:$IP$4,P77,Stock!$D$5:$IP$5,Q77),IF(COUNTIF(Stock!$D$5:$IP$5,Q77)>0,SUMIF(Stock!$D$5:$IP$5,Q77,Stock!$D$340:$IP$340),SUMIF(Stock!$D$4:$IP$4,P77,Stock!$D$340:$IP$340))),SUMIF(Stock!$D$4:$IP$4,P77,Stock!$D$340:$IP$340))) -> 150 | T77: =R77-S77 -> -100 | U77: =IF(AND(P77="",Q77=""),"",IF(Q77<>"",IF(COUNTIFS(Stock!$D$4:$IP$4,P77,Stock!$D$5:$IP$5,Q77)>0,SUMIFS(Stock!$D$32:$IP$32,Stock!$D$4:$IP$4,P77,Stock!$D$5:$IP$5,Q77),IF(COUNTIF(Stock!$D$5:$IP$5,Q77)>0,SUMIF(Stock!$D$5:$IP$5,Q77,Stock!$D$32:$IP$32),SUMIF(Stock!$D$4:$IP$4,P77,Stock!$D$32:$IP$32))),SUMIF(Stock!$D$4:$IP$4,P77,Stock!$D$32:$IP$32))) -> 872 | V77: PC7034A
B78: SP/UNI 14X15X22MM (O) | D78: 580 | E78: =IF(AND(B78="",C78=""),"",IF(C78<>"",IF(COUNTIFS(Stock!$D$4:$IP$4,B78,Stock!$D$5:$IP$5,C78)>0,SUMIFS(Stock!$D$340:$IP$340,Stock!$D$4:$IP$4,B78,Stock!$D$5:$IP$5,C78),IF(COUNTIF(Stock!$D$5:$IP$5,C78)>0,SUMIF(Stock!$D$5:$IP$5,C78,Stock!$D$340:$IP$340),SUMIF(Stock!$D$4:$IP$4,B78,Stock!$D$340:$IP$340))),SUMIF(Stock!$D$4:$IP$4,B78,Stock!$D$340:$IP$340))) -> 500 | F78: =D78-E78 -> 80 | G78: =IF(AND(B78="",C78=""),"",IF(C78<>"",IF(COUNTIFS(Stock!$D$4:$IP$4,B78,Stock!$D$5:$IP$5,C78)>0,SUMIFS(Stock!$D$32:$IP$32,Stock!$D$4:$IP$4,B78,Stock!$D$5:$IP$5,C78),IF(COUNTIF(Stock!$D$5:$IP$5,C78)>0,SUMIF(Stock!$D$5:$IP$5,C78,Stock!$D$32:$IP$32),SUMIF(Stock!$D$4:$IP$4,B78,Stock!$D$32:$IP$32))),SUMIF(Stock!$D$4:$IP$4,B78,Stock!$D$32:$IP$32))) -> 500 | I78: HOSE | J78: 8MM-LID | K78: 40 | L78: =IF(AND(I78="",J78=""),"",IF(J78<>"",IF(COUNTIFS(Stock!$D$4:$IP$4,I78,Stock!$D$5:$IP$5,J78)>0,SUMIFS(Stock!$D$340:$IP$340,Stock!$D$4:$IP$4,I78,Stock!$D$5:$IP$5,J78),IF(COUNTIF(Stock!$D$5:$IP$5,J78)>0,SUMIF(Stock!$D$5:$IP$5,J78,Stock!$D$340:$IP$340),SUMIF(Stock!$D$4:$IP$4,I78,Stock!$D$340:$IP$340))),SUMIF(Stock!$D$4:$IP$4,I78,Stock!$D$340:$IP$340))) -> 40 | M78: =K78-L78 -> 0 | N78: =IF(AND(I78="",J78=""),"",IF(J78<>"",IF(COUNTIFS(Stock!$D$4:$IP$4,I78,Stock!$D$5:$IP$5,J78)>0,SUMIFS(Stock!$D$32:$IP$32,Stock!$D$4:$IP$4,I78,Stock!$D$5:$IP$5,J78),IF(COUNTIF(Stock!$D$5:$IP$5,J78)>0,SUMIF(Stock!$D$5:$IP$5,J78,Stock!$D$32:$IP$32),SUMIF(Stock!$D$4:$IP$4,I78,Stock!$D$32:$IP$32))),SUMIF(Stock!$D$4:$IP$4,I78,Stock!$D$32:$IP$32))) -> 40 | P78: H.CITY | Q78: PC-7061A | R78: 99 | S78: =IF(AND(P78="",Q78=""),"",IF(Q78<>"",IF(COUNTIFS(Stock!$D$4:$IP$4,P78,Stock!$D$5:$IP$5,Q78)>0,SUMIFS(Stock!$D$340:$IP$340,Stock!$D$4:$IP$4,P78,Stock!$D$5:$IP$5,Q78),IF(COUNTIF(Stock!$D$5:$IP$5,Q78)>0,SUMIF(Stock!$D$5:$IP$5,Q78,Stock!$D$340:$IP$340),SUMIF(Stock!$D$4:$IP$4,P78,Stock!$D$340:$IP$340))),SUMIF(Stock!$D$4:$IP$4,P78,Stock!$D$340:$IP$340))) -> 0 | T78: =R78-S78 -> 99 | U78: =IF(AND(P78="",Q78=""),"",IF(Q78<>"",IF(COUNTIFS(Stock!$D$4:$IP$4,P78,Stock!$D$5:$IP$5,Q78)>0,SUMIFS(Stock!$D$32:$IP$32,Stock!$D$4:$IP$4,P78,Stock!$D$5:$IP$5,Q78),IF(COUNTIF(Stock!$D$5:$IP$5,Q78)>0,SUMIF(Stock!$D$5:$IP$5,Q78,Stock!$D$32:$IP$32),SUMIF(Stock!$D$4:$IP$4,P78,Stock!$D$32:$IP$32))),SUMIF(Stock!$D$4:$IP$4,P78,Stock!$D$32:$IP$32))) -> 1200 | V78: PC7061A
B79: SP/UNI 14X15X22MM (F) | D79: 720 | E79: =IF(AND(B79="",C79=""),"",IF(C79<>"",IF(COUNTIFS(Stock!$D$4:$IP$4,B79,Stock!$D$5:$IP$5,C79)>0,SUMIFS(Stock!$D$340:$IP$340,Stock!$D$4:$IP$4,B79,Stock!$D$5:$IP$5,C79),IF(COUNTIF(Stock!$D$5:$IP$5,C79)>0,SUMIF(Stock!$D$5:$IP$5,C79,Stock!$D$340:$IP$340),SUMIF(Stock!$D$4:$IP$4,B79,Stock!$D$340:$IP$340))),SUMIF(Stock!$D$4:$IP$4,B79,Stock!$D$340:$IP$340))) -> 950 | F79: =D79-E79 -> -230 | G79: =IF(AND(B79="",C79=""),"",IF(C79<>"",IF(COUNTIFS(Stock!$D$4:$IP$4,B79,Stock!$D$5:$IP$5,C79)>0,SUMIFS(Stock!$D$32:$IP$32,Stock!$D$4:$IP$4,B79,Stock!$D$5:$IP$5,C79),IF(COUNTIF(Stock!$D$5:$IP$5,C79)>0,SUMIF(Stock!$D$5:$IP$5,C79,Stock!$D$32:$IP$32),SUMIF(Stock!$D$4:$IP$4,B79,Stock!$D$32:$IP$32))),SUMIF(Stock!$D$4:$IP$4,B79,Stock!$D$32:$IP$32))) -> 950 | J79: 11MM-DIS | K79: 116 | L79: =IF(AND(I79="",J79=""),"",IF(J79<>"",IF(COUNTIFS(Stock!$D$4:$IP$4,I79,Stock!$D$5:$IP$5,J79)>0,SUMIFS(Stock!$D$340:$IP$340,Stock!$D$4:$IP$4,I79,Stock!$D$5:$IP$5,J79),IF(COUNTIF(Stock!$D$5:$IP$5,J79)>0,SUMIF(Stock!$D$5:$IP$5,J79,Stock!$D$340:$IP$340),SUMIF(Stock!$D$4:$IP$4,I79,Stock!$D$340:$IP$340))),SUMIF(Stock!$D$4:$IP$4,I79,Stock!$D$340:$IP$340))) -> 216 | M79: =K79-L79 -> -100 | N79: =IF(AND(I79="",J79=""),"",IF(J79<>"",IF(COUNTIFS(Stock!$D$4:$IP$4,I79,Stock!$D$5:$IP$5,J79)>0,SUMIFS(Stock!$D$32:$IP$32,Stock!$D$4:$IP$4,I79,Stock!$D$5:$IP$5,J79),IF(COUNTIF(Stock!$D$5:$IP$5,J79)>0,SUMIF(Stock!$D$5:$IP$5,J79,Stock!$D$32:$IP$32),SUMIF(Stock!$D$4:$IP$4,I79,Stock!$D$32:$IP$32))),SUMIF(Stock!$D$4:$IP$4,I79,Stock!$D$32:$IP$32))) -> 216 | P79: 507-AA | Q79: PC-7001A-AA | R79: 3643 | S79: =IF(AND(P79="",Q79=""),"",IF(Q79<>"",IF(COUNTIFS(Stock!$D$4:$IP$4,P79,Stock!$D$5:$IP$5,Q79)>0,SUMIFS(Stock!$D$340:$IP$340,Stock!$D$4:$IP$4,P79,Stock!$D$5:$IP$5,Q79),IF(COUNTIF(Stock!$D$5:$IP$5,Q79)>0,SUMIF(Stock!$D$5:$IP$5,Q79,Stock!$D$340:$IP$340),SUMIF(Stock!$D$4:$IP$4,P79,Stock!$D$340:$IP$340))),SUMIF(Stock!$D$4:$IP$4,P79,Stock!$D$340:$IP$340))) -> 1250 | T79: =R79-S79 -> 2393 | U79: =IF(AND(P79="",Q79=""),"",IF(Q79<>"",IF(COUNTIFS(Stock!$D$4:$IP$4,P79,Stock!$D$5:$IP$5,Q79)>0,SUMIFS(Stock!$D$32:$IP$32,Stock!$D$4:$IP$4,P79,Stock!$D$5:$IP$5,Q79),IF(COUNTIF(Stock!$D$5:$IP$5,Q79)>0,SUMIF(Stock!$D$5:$IP$5,Q79,Stock!$D$32:$IP$32),SUMIF(Stock!$D$4:$IP$4,P79,Stock!$D$32:$IP$32))),SUMIF(Stock!$D$4:$IP$4,P79,Stock!$D$32:$IP$32))) -> 4250 | V79: 507;AA507;SEAL507;SEALAA507;AA507SEAL
B80: SP/UNI 14X15X26MM (F) | D80: 100 | E80: =IF(AND(B80="",C80=""),"",IF(C80<>"",IF(COUNTIFS(Stock!$D$4:$IP$4,B80,Stock!$D$5:$IP$5,C80)>0,SUMIFS(Stock!$D$340:$IP$340,Stock!$D$4:$IP$4,B80,Stock!$D$5:$IP$5,C80),IF(COUNTIF(Stock!$D$5:$IP$5,C80)>0,SUMIF(Stock!$D$5:$IP$5,C80,Stock!$D$340:$IP$340),SUMIF(Stock!$D$4:$IP$4,B80,Stock!$D$340:$IP$340))),SUMIF(Stock!$D$4:$IP$4,B80,Stock!$D$340:$IP$340))) -> 50 | F80: =D80-E80 -> 50 | G80: =IF(AND(B80="",C80=""),"",IF(C80<>"",IF(COUNTIFS(Stock!$D$4:$IP$4,B80,Stock!$D$5:$IP$5,C80)>0,SUMIFS(Stock!$D$32:$IP$32,Stock!$D$4:$IP$4,B80,Stock!$D$5:$IP$5,C80),IF(COUNTIF(Stock!$D$5:$IP$5,C80)>0,SUMIF(Stock!$D$5:$IP$5,C80,Stock!$D$32:$IP$32),SUMIF(Stock!$D$4:$IP$4,B80,Stock!$D$32:$IP$32))),SUMIF(Stock!$D$4:$IP$4,B80,Stock!$D$32:$IP$32))) -> 100 | J80: 15MM-SUC | K80: 94 | L80: =IF(AND(I80="",J80=""),"",IF(J80<>"",IF(COUNTIFS(Stock!$D$4:$IP$4,I80,Stock!$D$5:$IP$5,J80)>0,SUMIFS(Stock!$D$340:$IP$340,Stock!$D$4:$IP$4,I80,Stock!$D$5:$IP$5,J80),IF(COUNTIF(Stock!$D$5:$IP$5,J80)>0,SUMIF(Stock!$D$5:$IP$5,J80,Stock!$D$340:$IP$340),SUMIF(Stock!$D$4:$IP$4,I80,Stock!$D$340:$IP$340))),SUMIF(Stock!$D$4:$IP$4,I80,Stock!$D$340:$IP$340))) -> 120 | M80: =K80-L80 -> -26 | N80: =IF(AND(I80="",J80=""),"",IF(J80<>"",IF(COUNTIFS(Stock!$D$4:$IP$4,I80,Stock!$D$5:$IP$5,J80)>0,SUMIFS(Stock!$D$32:$IP$32,Stock!$D$4:$IP$4,I80,Stock!$D$5:$IP$5,J80),IF(COUNTIF(Stock!$D$5:$IP$5,J80)>0,SUMIF(Stock!$D$5:$IP$5,J80,Stock!$D$32:$IP$32),SUMIF(Stock!$D$4:$IP$4,I80,Stock!$D$32:$IP$32))),SUMIF(Stock!$D$4:$IP$4,I80,Stock!$D$32:$IP$32))) -> 120 | P80: 508-AA | Q80: PC-7004A-AA | R80: 279 | S80: =IF(AND(P80="",Q80=""),"",IF(Q80<>"",IF(COUNTIFS(Stock!$D$4:$IP$4,P80,Stock!$D$5:$IP$5,Q80)>0,SUMIFS(Stock!$D$340:$IP$340,Stock!$D$4:$IP$4,P80,Stock!$D$5:$IP$5,Q80),IF(COUNTIF(Stock!$D$5:$IP$5,Q80)>0,SUMIF(Stock!$D$5:$IP$5,Q80,Stock!$D$340:$IP$340),SUMIF(Stock!$D$4:$IP$4,P80,Stock!$D$340:$IP$340))),SUMIF(Stock!$D$4:$IP$4,P80,Stock!$D$340:$IP$340))) -> 600 | T80: =R80-S80 -> -321 | U80: =IF(AND(P80="",Q80=""),"",IF(Q80<>"",IF(COUNTIFS(Stock!$D$4:$IP$4,P80,Stock!$D$5:$IP$5,Q80)>0,SUMIFS(Stock!$D$32:$IP$32,Stock!$D$4:$IP$4,P80,Stock!$D$5:$IP$5,Q80),IF(COUNTIF(Stock!$D$5:$IP$5,Q80)>0,SUMIF(Stock!$D$5:$IP$5,Q80,Stock!$D$32:$IP$32),SUMIF(Stock!$D$4:$IP$4,P80,Stock!$D$32:$IP$32))),SUMIF(Stock!$D$4:$IP$4,P80,Stock!$D$32:$IP$32))) -> 1827 | V80: 508;AA508;SEAL508;SEALAA508;AA508SEAL
B81: SP/UNI 14X18X22MM (F) | D81: 496 | E81: =IF(AND(B81="",C81=""),"",IF(C81<>"",IF(COUNTIFS(Stock!$D$4:$IP$4,B81,Stock!$D$5:$IP$5,C81)>0,SUMIFS(Stock!$D$340:$IP$340,Stock!$D$4:$IP$4,B81,Stock!$D$5:$IP$5,C81),IF(COUNTIF(Stock!$D$5:$IP$5,C81)>0,SUMIF(Stock!$D$5:$IP$5,C81,Stock!$D$340:$IP$340),SUMIF(Stock!$D$4:$IP$4,B81,Stock!$D$340:$IP$340))),SUMIF(Stock!$D$4:$IP$4,B81,Stock!$D$340:$IP$340))) -> 200 | F81: =D81-E81 -> 296 | G81: =IF(AND(B81="",C81=""),"",IF(C81<>"",IF(COUNTIFS(Stock!$D$4:$IP$4,B81,Stock!$D$5:$IP$5,C81)>0,SUMIFS(Stock!$D$32:$IP$32,Stock!$D$4:$IP$4,B81,Stock!$D$5:$IP$5,C81),IF(COUNTIF(Stock!$D$5:$IP$5,C81)>0,SUMIF(Stock!$D$5:$IP$5,C81,Stock!$D$32:$IP$32),SUMIF(Stock!$D$4:$IP$4,B81,Stock!$D$32:$IP$32))),SUMIF(Stock!$D$4:$IP$4,B81,Stock!$D$32:$IP$32))) -> 500 | H81: BUTANE | I81: BUTANE | J81: CTNS | K81: 908 | L81: =IF(AND(I81="",J81=""),"",IF(J81<>"",IF(COUNTIFS(Stock!$D$4:$IP$4,I81,Stock!$D$5:$IP$5,J81)>0,SUMIFS(Stock!$D$340:$IP$340,Stock!$D$4:$IP$4,I81,Stock!$D$5:$IP$5,J81),IF(COUNTIF(Stock!$D$5:$IP$5,J81)>0,SUMIF(Stock!$D$5:$IP$5,J81,Stock!$D$340:$IP$340),SUMIF(Stock!$D$4:$IP$4,I81,Stock!$D$340:$IP$340))),SUMIF(Stock!$D$4:$IP$4,I81,Stock!$D$340:$IP$340))) -> 908 | M81: =K81-L81 -> 0 | N81: =IF(AND(I81="",J81=""),"",IF(J81<>"",IF(COUNTIFS(Stock!$D$4:$IP$4,I81,Stock!$D$5:$IP$5,J81)>0,SUMIFS(Stock!$D$32:$IP$32,Stock!$D$4:$IP$4,I81,Stock!$D$5:$IP$5,J81),IF(COUNTIF(Stock!$D$5:$IP$5,J81)>0,SUMIF(Stock!$D$5:$IP$5,J81,Stock!$D$32:$IP$32),SUMIF(Stock!$D$4:$IP$4,I81,Stock!$D$32:$IP$32))),SUMIF(Stock!$D$4:$IP$4,I81,Stock!$D$32:$IP$32))) -> 908 | P81: 507 | Q81: PC-7001A-507-AA (507) | S81: =IF(AND(P81="",Q81=""),"",IF(Q81<>"",IF(COUNTIFS(Stock!$D$4:$IP$4,P81,Stock!$D$5:$IP$5,Q81)>0,SUMIFS(Stock!$D$340:$IP$340,Stock!$D$4:$IP$4,P81,Stock!$D$5:$IP$5,Q81),IF(COUNTIF(Stock!$D$5:$IP$5,Q81)>0,SUMIF(Stock!$D$5:$IP$5,Q81,Stock!$D$340:$IP$340),SUMIF(Stock!$D$4:$IP$4,P81,Stock!$D$340:$IP$340))),SUMIF(Stock!$D$4:$IP$4,P81,Stock!$D$340:$IP$340))) -> 0 | T81: =R81-S81 -> 0 | U81: =IF(AND(P81="",Q81=""),"",IF(Q81<>"",IF(COUNTIFS(Stock!$D$4:$IP$4,P81,Stock!$D$5:$IP$5,Q81)>0,SUMIFS(Stock!$D$32:$IP$32,Stock!$D$4:$IP$4,P81,Stock!$D$5:$IP$5,Q81),IF(COUNTIF(Stock!$D$5:$IP$5,Q81)>0,SUMIF(Stock!$D$5:$IP$5,Q81,Stock!$D$32:$IP$32),SUMIF(Stock!$D$4:$IP$4,P81,Stock!$D$32:$IP$32))),SUMIF(Stock!$D$4:$IP$4,P81,Stock!$D$32:$IP$32))) -> 0
B82: SP/UNI 14X18X26MM (F) | D82: 200 | E82: =IF(AND(B82="",C82=""),"",IF(C82<>"",IF(COUNTIFS(Stock!$D$4:$IP$4,B82,Stock!$D$5:$IP$5,C82)>0,SUMIFS(Stock!$D$340:$IP$340,Stock!$D$4:$IP$4,B82,Stock!$D$5:$IP$5,C82),IF(COUNTIF(Stock!$D$5:$IP$5,C82)>0,SUMIF(Stock!$D$5:$IP$5,C82,Stock!$D$340:$IP$340),SUMIF(Stock!$D$4:$IP$4,B82,Stock!$D$340:$IP$340))),SUMIF(Stock!$D$4:$IP$4,B82,Stock!$D$340:$IP$340))) -> 20 | F82: =D82-E82 -> 180 | G82: =IF(AND(B82="",C82=""),"",IF(C82<>"",IF(COUNTIFS(Stock!$D$4:$IP$4,B82,Stock!$D$5:$IP$5,C82)>0,SUMIFS(Stock!$D$32:$IP$32,Stock!$D$4:$IP$4,B82,Stock!$D$5:$IP$5,C82),IF(COUNTIF(Stock!$D$5:$IP$5,C82)>0,SUMIF(Stock!$D$5:$IP$5,C82,Stock!$D$32:$IP$32),SUMIF(Stock!$D$4:$IP$4,B82,Stock!$D$32:$IP$32))),SUMIF(Stock!$D$4:$IP$4,B82,Stock!$D$32:$IP$32))) -> 200 | H82: WICK | I82: WICK | J82: PCS | K82: 8400 | L82: =IF(AND(I82="",J82=""),"",IF(J82<>"",IF(COUNTIFS(Stock!$D$4:$IP$4,I82,Stock!$D$5:$IP$5,J82)>0,SUMIFS(Stock!$D$340:$IP$340,Stock!$D$4:$IP$4,I82,Stock!$D$5:$IP$5,J82),IF(COUNTIF(Stock!$D$5:$IP$5,J82)>0,SUMIF(Stock!$D$5:$IP$5,J82,Stock!$D$340:$IP$340),SUMIF(Stock!$D$4:$IP$4,I82,Stock!$D$340:$IP$340))),SUMIF(Stock!$D$4:$IP$4,I82,Stock!$D$340:$IP$340))) -> 8400 | M82: =K82-L82 -> 0 | N82: =IF(AND(I82="",J82=""),"",IF(J82<>"",IF(COUNTIFS(Stock!$D$4:$IP$4,I82,Stock!$D$5:$IP$5,J82)>0,SUMIFS(Stock!$D$32:$IP$32,Stock!$D$4:$IP$4,I82,Stock!$D$5:$IP$5,J82),IF(COUNTIF(Stock!$D$5:$IP$5,J82)>0,SUMIF(Stock!$D$5:$IP$5,J82,Stock!$D$32:$IP$32),SUMIF(Stock!$D$4:$IP$4,I82,Stock!$D$32:$IP$32))),SUMIF(Stock!$D$4:$IP$4,I82,Stock!$D$32:$IP$32))) -> 8400 | P82: 508 | Q82: PC-7004A-508 PART NO./508 | S82: =IF(AND(P82="",Q82=""),"",IF(Q82<>"",IF(COUNTIFS(Stock!$D$4:$IP$4,P82,Stock!$D$5:$IP$5,Q82)>0,SUMIFS(Stock!$D$340:$IP$340,Stock!$D$4:$IP$4,P82,Stock!$D$5:$IP$5,Q82),IF(COUNTIF(Stock!$D$5:$IP$5,Q82)>0,SUMIF(Stock!$D$5:$IP$5,Q82,Stock!$D$340:$IP$340),SUMIF(Stock!$D$4:$IP$4,P82,Stock!$D$340:$IP$340))),SUMIF(Stock!$D$4:$IP$4,P82,Stock!$D$340:$IP$340))) -> 0 | T82: =R82-S82 -> 0 | U82: =IF(AND(P82="",Q82=""),"",IF(Q82<>"",IF(COUNTIFS(Stock!$D$4:$IP$4,P82,Stock!$D$5:$IP$5,Q82)>0,SUMIFS(Stock!$D$32:$IP$32,Stock!$D$4:$IP$4,P82,Stock!$D$5:$IP$5,Q82),IF(COUNTIF(Stock!$D$5:$IP$5,Q82)>0,SUMIF(Stock!$D$5:$IP$5,Q82,Stock!$D$32:$IP$32),SUMIF(Stock!$D$4:$IP$4,P82,Stock!$D$32:$IP$32))),SUMIF(Stock!$D$4:$IP$4,P82,Stock!$D$32:$IP$32))) -> 44
B83: SP/UNI 14X21X22MM (F) | D83: 200 | E83: =IF(AND(B83="",C83=""),"",IF(C83<>"",IF(COUNTIFS(Stock!$D$4:$IP$4,B83,Stock!$D$5:$IP$5,C83)>0,SUMIFS(Stock!$D$340:$IP$340,Stock!$D$4:$IP$4,B83,Stock!$D$5:$IP$5,C83),IF(COUNTIF(Stock!$D$5:$IP$5,C83)>0,SUMIF(Stock!$D$5:$IP$5,C83,Stock!$D$340:$IP$340),SUMIF(Stock!$D$4:$IP$4,B83,Stock!$D$340:$IP$340))),SUMIF(Stock!$D$4:$IP$4,B83,Stock!$D$340:$IP$340))) -> 200 | F83: =D83-E83 -> 0 | G83: =IF(AND(B83="",C83=""),"",IF(C83<>"",IF(COUNTIFS(Stock!$D$4:$IP$4,B83,Stock!$D$5:$IP$5,C83)>0,SUMIFS(Stock!$D$32:$IP$32,Stock!$D$4:$IP$4,B83,Stock!$D$5:$IP$5,C83),IF(COUNTIF(Stock!$D$5:$IP$5,C83)>0,SUMIF(Stock!$D$5:$IP$5,C83,Stock!$D$32:$IP$32),SUMIF(Stock!$D$4:$IP$4,B83,Stock!$D$32:$IP$32))),SUMIF(Stock!$D$4:$IP$4,B83,Stock!$D$32:$IP$32))) -> 200 | H83: INSULATION TAPE | I83: INSULATION TAPE | J83: PCS | K83: 720 | L83: =IF(AND(I83="",J83=""),"",IF(J83<>"",IF(COUNTIFS(Stock!$D$4:$IP$4,I83,Stock!$D$5:$IP$5,J83)>0,SUMIFS(Stock!$D$340:$IP$340,Stock!$D$4:$IP$4,I83,Stock!$D$5:$IP$5,J83),IF(COUNTIF(Stock!$D$5:$IP$5,J83)>0,SUMIF(Stock!$D$5:$IP$5,J83,Stock!$D$340:$IP$340),SUMIF(Stock!$D$4:$IP$4,I83,Stock!$D$340:$IP$340))),SUMIF(Stock!$D$4:$IP$4,I83,Stock!$D$340:$IP$340))) -> 0 | M83: =K83-L83 -> 720 | N83: =IF(AND(I83="",J83=""),"",IF(J83<>"",IF(COUNTIFS(Stock!$D$4:$IP$4,I83,Stock!$D$5:$IP$5,J83)>0,SUMIFS(Stock!$D$32:$IP$32,Stock!$D$4:$IP$4,I83,Stock!$D$5:$IP$5,J83),IF(COUNTIF(Stock!$D$5:$IP$5,J83)>0,SUMIF(Stock!$D$5:$IP$5,J83,Stock!$D$32:$IP$32),SUMIF(Stock!$D$4:$IP$4,I83,Stock!$D$32:$IP$32))),SUMIF(Stock!$D$4:$IP$4,I83,Stock!$D$32:$IP$32))) -> 1000 | P83: SANTRO SMALL | Q83: PC-7217 | R83: 1800 | S83: =IF(AND(P83="",Q83=""),"",IF(Q83<>"",IF(COUNTIFS(Stock!$D$4:$IP$4,P83,Stock!$D$5:$IP$5,Q83)>0,SUMIFS(Stock!$D$340:$IP$340,Stock!$D$4:$IP$4,P83,Stock!$D$5:$IP$5,Q83),IF(COUNTIF(Stock!$D$5:$IP$5,Q83)>0,SUMIF(Stock!$D$5:$IP$5,Q83,Stock!$D$340:$IP$340),SUMIF(Stock!$D$4:$IP$4,P83,Stock!$D$340:$IP$340))),SUMIF(Stock!$D$4:$IP$4,P83,Stock!$D$340:$IP$340))) -> 0 | T83: =R83-S83 -> 1800 | U83: =IF(AND(P83="",Q83=""),"",IF(Q83<>"",IF(COUNTIFS(Stock!$D$4:$IP$4,P83,Stock!$D$5:$IP$5,Q83)>0,SUMIFS(Stock!$D$32:$IP$32,Stock!$D$4:$IP$4,P83,Stock!$D$5:$IP$5,Q83),IF(COUNTIF(Stock!$D$5:$IP$5,Q83)>0,SUMIF(Stock!$D$5:$IP$5,Q83,Stock!$D$32:$IP$32),SUMIF(Stock!$D$4:$IP$4,P83,Stock!$D$32:$IP$32))),SUMIF(Stock!$D$4:$IP$4,P83,Stock!$D$32:$IP$32))) -> 2000 | V83: PC7217
B84: SP/UNI 14X21X26MM (F) | D84: 200 | E84: =IF(AND(B84="",C84=""),"",IF(C84<>"",IF(COUNTIFS(Stock!$D$4:$IP$4,B84,Stock!$D$5:$IP$5,C84)>0,SUMIFS(Stock!$D$340:$IP$340,Stock!$D$4:$IP$4,B84,Stock!$D$5:$IP$5,C84),IF(COUNTIF(Stock!$D$5:$IP$5,C84)>0,SUMIF(Stock!$D$5:$IP$5,C84,Stock!$D$340:$IP$340),SUMIF(Stock!$D$4:$IP$4,B84,Stock!$D$340:$IP$340))),SUMIF(Stock!$D$4:$IP$4,B84,Stock!$D$340:$IP$340))) -> 80 | F84: =D84-E84 -> 120 | G84: =IF(AND(B84="",C84=""),"",IF(C84<>"",IF(COUNTIFS(Stock!$D$4:$IP$4,B84,Stock!$D$5:$IP$5,C84)>0,SUMIFS(Stock!$D$32:$IP$32,Stock!$D$4:$IP$4,B84,Stock!$D$5:$IP$5,C84),IF(COUNTIF(Stock!$D$5:$IP$5,C84)>0,SUMIF(Stock!$D$5:$IP$5,C84,Stock!$D$32:$IP$32),SUMIF(Stock!$D$4:$IP$4,B84,Stock!$D$32:$IP$32))),SUMIF(Stock!$D$4:$IP$4,B84,Stock!$D$32:$IP$32))) -> 200 | M84: =K84-L84 -> 0 | P84: BOLERO | Q84: PC-7237 | R84: 25 | S84: =IF(AND(P84="",Q84=""),"",IF(Q84<>"",IF(COUNTIFS(Stock!$D$4:$IP$4,P84,Stock!$D$5:$IP$5,Q84)>0,SUMIFS(Stock!$D$340:$IP$340,Stock!$D$4:$IP$4,P84,Stock!$D$5:$IP$5,Q84),IF(COUNTIF(Stock!$D$5:$IP$5,Q84)>0,SUMIF(Stock!$D$5:$IP$5,Q84,Stock!$D$340:$IP$340),SUMIF(Stock!$D$4:$IP$4,P84,Stock!$D$340:$IP$340))),SUMIF(Stock!$D$4:$IP$4,P84,Stock!$D$340:$IP$340))) -> 0 | T84: =R84-S84 -> 25 | U84: =IF(AND(P84="",Q84=""),"",IF(Q84<>"",IF(COUNTIFS(Stock!$D$4:$IP$4,P84,Stock!$D$5:$IP$5,Q84)>0,SUMIFS(Stock!$D$32:$IP$32,Stock!$D$4:$IP$4,P84,Stock!$D$5:$IP$5,Q84),IF(COUNTIF(Stock!$D$5:$IP$5,Q84)>0,SUMIF(Stock!$D$5:$IP$5,Q84,Stock!$D$32:$IP$32),SUMIF(Stock!$D$4:$IP$4,P84,Stock!$D$32:$IP$32))),SUMIF(Stock!$D$4:$IP$4,P84,Stock!$D$32:$IP$32))) -> 100 | V84: PC7237
B85: SP/UNI 14X23X22MM (F) | D85: 100 | E85: =IF(AND(B85="",C85=""),"",IF(C85<>"",IF(COUNTIFS(Stock!$D$4:$IP$4,B85,Stock!$D$5:$IP$5,C85)>0,SUMIFS(Stock!$D$340:$IP$340,Stock!$D$4:$IP$4,B85,Stock!$D$5:$IP$5,C85),IF(COUNTIF(Stock!$D$5:$IP$5,C85)>0,SUMIF(Stock!$D$5:$IP$5,C85,Stock!$D$340:$IP$340),SUMIF(Stock!$D$4:$IP$4,B85,Stock!$D$340:$IP$340))),SUMIF(Stock!$D$4:$IP$4,B85,Stock!$D$340:$IP$340))) -> 100 | F85: =D85-E85 -> 0 | G85: =IF(AND(B85="",C85=""),"",IF(C85<>"",IF(COUNTIFS(Stock!$D$4:$IP$4,B85,Stock!$D$5:$IP$5,C85)>0,SUMIFS(Stock!$D$32:$IP$32,Stock!$D$4:$IP$4,B85,Stock!$D$5:$IP$5,C85),IF(COUNTIF(Stock!$D$5:$IP$5,C85)>0,SUMIF(Stock!$D$5:$IP$5,C85,Stock!$D$32:$IP$32),SUMIF(Stock!$D$4:$IP$4,B85,Stock!$D$32:$IP$32))),SUMIF(Stock!$D$4:$IP$4,B85,Stock!$D$32:$IP$32))) -> 100 | M85: =K85-L85 -> 0 | P85: OPEL ASTRA | Q85: PC-7210 | R85: 5 | S85: =IF(AND(P85="",Q85=""),"",IF(Q85<>"",IF(COUNTIFS(Stock!$D$4:$IP$4,P85,Stock!$D$5:$IP$5,Q85)>0,SUMIFS(Stock!$D$340:$IP$340,Stock!$D$4:$IP$4,P85,Stock!$D$5:$IP$5,Q85),IF(COUNTIF(Stock!$D$5:$IP$5,Q85)>0,SUMIF(Stock!$D$5:$IP$5,Q85,Stock!$D$340:$IP$340),SUMIF(Stock!$D$4:$IP$4,P85,Stock!$D$340:$IP$340))),SUMIF(Stock!$D$4:$IP$4,P85,Stock!$D$340:$IP$340))) -> 0 | T85: =R85-S85 -> 5 | U85: =IF(AND(P85="",Q85=""),"",IF(Q85<>"",IF(COUNTIFS(Stock!$D$4:$IP$4,P85,Stock!$D$5:$IP$5,Q85)>0,SUMIFS(Stock!$D$32:$IP$32,Stock!$D$4:$IP$4,P85,Stock!$D$5:$IP$5,Q85),IF(COUNTIF(Stock!$D$5:$IP$5,Q85)>0,SUMIF(Stock!$D$5:$IP$5,Q85,Stock!$D$32:$IP$32),SUMIF(Stock!$D$4:$IP$4,P85,Stock!$D$32:$IP$32))),SUMIF(Stock!$D$4:$IP$4,P85,Stock!$D$32:$IP$32))) -> 100 | V85: PC7210
B86: SP/UNI 14X23X26MM (F) | D86: 100 | E86: =IF(AND(B86="",C86=""),"",IF(C86<>"",IF(COUNTIFS(Stock!$D$4:$IP$4,B86,Stock!$D$5:$IP$5,C86)>0,SUMIFS(Stock!$D$340:$IP$340,Stock!$D$4:$IP$4,B86,Stock!$D$5:$IP$5,C86),IF(COUNTIF(Stock!$D$5:$IP$5,C86)>0,SUMIF(Stock!$D$5:$IP$5,C86,Stock!$D$340:$IP$340),SUMIF(Stock!$D$4:$IP$4,B86,Stock!$D$340:$IP$340))),SUMIF(Stock!$D$4:$IP$4,B86,Stock!$D$340:$IP$340))) -> 100 | F86: =D86-E86 -> 0 | G86: =IF(AND(B86="",C86=""),"",IF(C86<>"",IF(COUNTIFS(Stock!$D$4:$IP$4,B86,Stock!$D$5:$IP$5,C86)>0,SUMIFS(Stock!$D$32:$IP$32,Stock!$D$4:$IP$4,B86,Stock!$D$5:$IP$5,C86),IF(COUNTIF(Stock!$D$5:$IP$5,C86)>0,SUMIF(Stock!$D$5:$IP$5,C86,Stock!$D$32:$IP$32),SUMIF(Stock!$D$4:$IP$4,B86,Stock!$D$32:$IP$32))),SUMIF(Stock!$D$4:$IP$4,B86,Stock!$D$32:$IP$32))) -> 100 | M86: =K86-L86 -> 0 | P86: GASKET 505/507 | S86: =IF(AND(P86="",Q86=""),"",IF(Q86<>"",IF(COUNTIFS(Stock!$D$4:$IP$4,P86,Stock!$D$5:$IP$5,Q86)>0,SUMIFS(Stock!$D$340:$IP$340,Stock!$D$4:$IP$4,P86,Stock!$D$5:$IP$5,Q86),IF(COUNTIF(Stock!$D$5:$IP$5,Q86)>0,SUMIF(Stock!$D$5:$IP$5,Q86,Stock!$D$340:$IP$340),SUMIF(Stock!$D$4:$IP$4,P86,Stock!$D$340:$IP$340))),SUMIF(Stock!$D$4:$IP$4,P86,Stock!$D$340:$IP$340))) -> 0 | T86: =R86-S86 -> 0 | U86: =IF(AND(P86="",Q86=""),"",IF(Q86<>"",IF(COUNTIFS(Stock!$D$4:$IP$4,P86,Stock!$D$5:$IP$5,Q86)>0,SUMIFS(Stock!$D$32:$IP$32,Stock!$D$4:$IP$4,P86,Stock!$D$5:$IP$5,Q86),IF(COUNTIF(Stock!$D$5:$IP$5,Q86)>0,SUMIF(Stock!$D$5:$IP$5,Q86,Stock!$D$32:$IP$32),SUMIF(Stock!$D$4:$IP$4,P86,Stock!$D$32:$IP$32))),SUMIF(Stock!$D$4:$IP$4,P86,Stock!$D$32:$IP$32))) -> 0
B87: SP/UNI 14X23X44MM (F) | D87: 200 | E87: =IF(AND(B87="",C87=""),"",IF(C87<>"",IF(COUNTIFS(Stock!$D$4:$IP$4,B87,Stock!$D$5:$IP$5,C87)>0,SUMIFS(Stock!$D$340:$IP$340,Stock!$D$4:$IP$4,B87,Stock!$D$5:$IP$5,C87),IF(COUNTIF(Stock!$D$5:$IP$5,C87)>0,SUMIF(Stock!$D$5:$IP$5,C87,Stock!$D$340:$IP$340),SUMIF(Stock!$D$4:$IP$4,B87,Stock!$D$340:$IP$340))),SUMIF(Stock!$D$4:$IP$4,B87,Stock!$D$340:$IP$340))) -> 150 | F87: =D87-E87 -> 50 | G87: =IF(AND(B87="",C87=""),"",IF(C87<>"",IF(COUNTIFS(Stock!$D$4:$IP$4,B87,Stock!$D$5:$IP$5,C87)>0,SUMIFS(Stock!$D$32:$IP$32,Stock!$D$4:$IP$4,B87,Stock!$D$5:$IP$5,C87),IF(COUNTIF(Stock!$D$5:$IP$5,C87)>0,SUMIF(Stock!$D$5:$IP$5,C87,Stock!$D$32:$IP$32),SUMIF(Stock!$D$4:$IP$4,B87,Stock!$D$32:$IP$32))),SUMIF(Stock!$D$4:$IP$4,B87,Stock!$D$32:$IP$32))) -> 200 | M87: =K87-L87 -> 0 | P87: O-RINGS | Q87: PC-7085A | R87: 2400 | S87: =IF(AND(P87="",Q87=""),"",IF(Q87<>"",IF(COUNTIFS(Stock!$D$4:$IP$4,P87,Stock!$D$5:$IP$5,Q87)>0,SUMIFS(Stock!$D$340:$IP$340,Stock!$D$4:$IP$4,P87,Stock!$D$5:$IP$5,Q87),IF(COUNTIF(Stock!$D$5:$IP$5,Q87)>0,SUMIF(Stock!$D$5:$IP$5,Q87,Stock!$D$340:$IP$340),SUMIF(Stock!$D$4:$IP$4,P87,Stock!$D$340:$IP$340))),SUMIF(Stock!$D$4:$IP$4,P87,Stock!$D$340:$IP$340))) -> 1998 | T87: =R87-S87 -> 402 | U87: =IF(AND(P87="",Q87=""),"",IF(Q87<>"",IF(COUNTIFS(Stock!$D$4:$IP$4,P87,Stock!$D$5:$IP$5,Q87)>0,SUMIFS(Stock!$D$32:$IP$32,Stock!$D$4:$IP$4,P87,Stock!$D$5:$IP$5,Q87),IF(COUNTIF(Stock!$D$5:$IP$5,Q87)>0,SUMIF(Stock!$D$5:$IP$5,Q87,Stock!$D$32:$IP$32),SUMIF(Stock!$D$4:$IP$4,P87,Stock!$D$32:$IP$32))),SUMIF(Stock!$D$4:$IP$4,P87,Stock!$D$32:$IP$32))) -> 4000 | V87: ORING;COMPANYAORING
B88: SP/UNI 14X25X26MM (F) | D88: 0 | E88: =IF(AND(B88="",C88=""),"",IF(C88<>"",IF(COUNTIFS(Stock!$D$4:$IP$4,B88,Stock!$D$5:$IP$5,C88)>0,SUMIFS(Stock!$D$340:$IP$340,Stock!$D$4:$IP$4,B88,Stock!$D$5:$IP$5,C88),IF(COUNTIF(Stock!$D$5:$IP$5,C88)>0,SUMIF(Stock!$D$5:$IP$5,C88,Stock!$D$340:$IP$340),SUMIF(Stock!$D$4:$IP$4,B88,Stock!$D$340:$IP$340))),SUMIF(Stock!$D$4:$IP$4,B88,Stock!$D$340:$IP$340))) -> 0 | F88: =D88-E88 -> 0 | G88: =IF(AND(B88="",C88=""),"",IF(C88<>"",IF(COUNTIFS(Stock!$D$4:$IP$4,B88,Stock!$D$5:$IP$5,C88)>0,SUMIFS(Stock!$D$32:$IP$32,Stock!$D$4:$IP$4,B88,Stock!$D$5:$IP$5,C88),IF(COUNTIF(Stock!$D$5:$IP$5,C88)>0,SUMIF(Stock!$D$5:$IP$5,C88,Stock!$D$32:$IP$32),SUMIF(Stock!$D$4:$IP$4,B88,Stock!$D$32:$IP$32))),SUMIF(Stock!$D$4:$IP$4,B88,Stock!$D$32:$IP$32))) -> 100 | M88: =K88-L88 -> 0
B89: SP/UNI 14X25X44MM (F) | D89: 135 | E89: =IF(AND(B89="",C89=""),"",IF(C89<>"",IF(COUNTIFS(Stock!$D$4:$IP$4,B89,Stock!$D$5:$IP$5,C89)>0,SUMIFS(Stock!$D$340:$IP$340,Stock!$D$4:$IP$4,B89,Stock!$D$5:$IP$5,C89),IF(COUNTIF(Stock!$D$5:$IP$5,C89)>0,SUMIF(Stock!$D$5:$IP$5,C89,Stock!$D$340:$IP$340),SUMIF(Stock!$D$4:$IP$4,B89,Stock!$D$340:$IP$340))),SUMIF(Stock!$D$4:$IP$4,B89,Stock!$D$340:$IP$340))) -> 100 | F89: =D89-E89 -> 35 | G89: =IF(AND(B89="",C89=""),"",IF(C89<>"",IF(COUNTIFS(Stock!$D$4:$IP$4,B89,Stock!$D$5:$IP$5,C89)>0,SUMIFS(Stock!$D$32:$IP$32,Stock!$D$4:$IP$4,B89,Stock!$D$5:$IP$5,C89),IF(COUNTIF(Stock!$D$5:$IP$5,C89)>0,SUMIF(Stock!$D$5:$IP$5,C89,Stock!$D$32:$IP$32),SUMIF(Stock!$D$4:$IP$4,B89,Stock!$D$32:$IP$32))),SUMIF(Stock!$D$4:$IP$4,B89,Stock!$D$32:$IP$32))) -> 200 | M89: =K89-L89 -> 0
