Workbook

Sheet CHALLAN
A1: G & G ENTERPRISES
A2: (Importer & Exporter)
G3: Address line (redacted)
G4: New Delhi-XXXXXX
G5: M-XXXXXXXXXX
A7: DELIVERY CHALLAN
F9: Dated.: | G9: 03.04.10
A10: To, | F10: Challan # : | G10: GG/001/10-11
A11: Dealer-004
A12: Address line (redacted)
A13: Address line (redacted)
A15: Dear Sir,
A17: According to instructions we are sending followng goods. Please acknowledge the same and after your
A18: acknowledgement we will issue you sales invoice.
A20: S.No. | B20: Description | D20: Nos of ctn | E20: Nos of PCs/ctn | F20: Qty in PCs | G20: Price | H20: Amount
B22: COMPANY-A CONDENSER
A24: 1- | B24: ZEN DELHI-R12 | C24: PC-86270R12 | D24: 3 | E24: 5 | F24: =+E24*D24 | G24: 1 | H24: =+G24*F24
A26: 2- | B26: ZEN DELHI-R134A | C26: PC-86270R134A | D26: 3 | E26: 5 | F26: =+E26*D26 | G26: 1 | H26: =+G26*F26
B28: COMPANY-A HPLP
A29: 3- | B29: PALIO | C29: PC-1100 | D29: 1 | E29: 1*25 | F29: 25 | G29: 1 | H29: =+G29*F29
C34: TOTAL | D34: =SUM(D24:D33) | F34: =SUM(F24:F33) | H34: =SUM(H24:H33)
D37: for | E37: G & G Enterprises
E40: Auth. Sign
A58: DELIVERY CHALLAN
A61: To, | F61: Dated.: | G61: 03.04.10
A62: Dealer-009 | C62: ATTN: Contact-001 | F62: Challan # : | G62: GG/002/10-11
A63: Address line (redacted)
A64: Address line (redacted)
A66: Dear Sir,
A68: According to instructions we are sending followng goods. Please acknowledge the same and after your
A69: acknowledgement we will issue you sales invoice.
A71: S.No. | B71: Description | D71: Nos of ctn | E71: Nos of PCs/ctn | F71: Qty in PCs | G71: Price | H71: Amount
B73: COMP OIL
A74: 1- | B74: ND-8 | C74: 250ML | D74: 29 | E74: 24 | F74: =+E74*D74 | G74: 1 | H74: =+G74*F74
C79: TOTAL | D79: =SUM(D73:D78) | H79: =SUM(H73:H78)
A81: PAYMENT TERMS: WITHIN 15 DAYS.
D82: for | E82: G & G Enterprises
E85: Auth. Sign
A104: DELIVERY CHALLAN
A106: To, | F106: Dated.: | G106: 06.04.10
A107: Dealer-002 | F107: Challan # : | G107: GG/003/10-11
A108: Address line (redacted) | C108: Address line (redacted)
A109: Address line (redacted)
A111: Dear Sir
A113: According to instructions we are sending followng goods. Please acknowledge the same and after your
A114: acknowledgement we will issue you sales invoice.
A115: S.No. | B115: Description | D115: Nos of ctn | E115: Nos of PCs/ctn | F115: Qty in PCs | G115: Price | H115: Amount
B117: COMPANY-A PF CONDENSER SAMPLES
A118: 1 | B118: CIVIC | C118: PC-86251 | D118: 1 | E118: 1 | F118: =+E118*D118 | G118: 1 | H118: =+G118*F118
A119: 2 | B119: I-10 | C119: PC-86266 | D119: 1 | E119: 1 | F119: =+E119*D119 | G119: 1 | H119: =+G119*F119
A120: 3 | B120: FABIA | C120: PC-86134 | D120: 1 | E120: 1 | F120: =+E120*D120 | G120: 1 | H120: =+G120*F120
A121: 4 | B121: LAURA | C121: PC-86026B | D121: 1 | E121: 1 | F121: =+E121*D121 | G121: 1 | H121: =+G121*F121
C124: TOTAL | D124: =SUM(D118:D123) | F124: =SUM(F118:F123) | H124: =SUM(H118:H123)
D126: for | E126: G & G Enterprises
D128: PHONE-MASKED
D129: PARIK | E129: Auth. Sign
A149: DELIVERY CHALLAN
A151: To, | F151: Dated.: | G151: 07.04.10
A152: Dealer-002 | F152: Challan # : | G152: GG/004/10-11
A153: Address line (redacted) | C153: Address line (redacted)
A154: Address line (redacted)
A156: Dear Sir
A158: According to instructions we are sending followng goods. Please acknowledge the same and after your
A159: acknowledgement we will issue you sales invoice.
A160: S.No. | B160: Description | D160: Nos of ctn | E160: Nos of PCs/ctn | F160: Qty in PCs | G160: Price | H160: Amount
B162: 747 A/C SWITCH
B163: Address line (redacted)
A164: 1 | B164: 747 A/C SWITCH 3 COUPLER | D164: 1 | E164: 1 | F164: 1 | G164: AGAINST SAMPLE
A165: 2 | B165: 747 A/C SWITCH 1 COUPLER | D165: 1 | E165: 1 | F165: 1 | G165: AGAINST SAMPLE
C169: TOTAL | D169: =SUM(D163:D168) | F169: =SUM(F163:F168) | H169: =SUM(H163:H168)
D171: for | E171: G & G Enterprises
E174: Auth. Sign
A194: DELIVERY CHALLAN
A196: To, | F196: Dated.: | G196: 07.04.10
A197: Dealer-002 | F197: Challan # : | G197: GG/005/10-11
A198: Address line (redacted)
A199: Address line (redacted)
A201: Dear Sir
A203: According to instructions we are sending followng goods. Please acknowledge the same and after your
A204: acknowledgement we will issue you sales invoice.
A205: S.No. | B205: Description | D205: Nos of ctn | E205: Nos of PCs/ctn | F205: Qty in PCs | G205: Price | H205: Amount
B207: BS.HOSE
A208: 1 | B208: 8MM | D208: 2 | E208: 100 | F208: =+E208*D208 | G208: 1 | H208: =+G208*F208
A209: 2 | B209: 11MM | D209: 12 | E209: 100 | F209: =+E209*D209 | G209: 1 | H209: =+G209*F209
A210: 3 | B210: 15MM | D210: 6 | E210: 100 | F210: =+E210*D210 | G210: 1 | H210: =+G210*F210
C214: TOTAL | D214: =SUM(D208:D213) | F214: =SUM(F208:F213) | H214: =SUM(H208:H213)
D216: for | E216: G & G Enterprises
E219: Auth. Sign
A239: DELIVERY CHALLAN
A241: To, | F241: Dated.: | G241: 07.04.10
A242: Dealer-003 | F242: Challan # : | G242: GG/006/10-11
A243: Address line (redacted)
A244: Address line (redacted)
A246: Dear Sir
A248: According to instructions we are sending followng goods. Please acknowledge the same and after your
A249: acknowledgement we will issue you sales invoice.
A250: S.No. | B250: Description | D250: Nos of ctn | E250: Nos of PCs/ctn | F250: Qty in PCs | G250: Price | H250: Amount
B252: BS.HOSE
A253: 1 | B253: 8MM | D253: 3 | E253: 100 | F253: =+E253*D253 | G253: 1 | H253: =+G253*F253
A254: 2 | B254: 11MM | D254: 18 | E254: 100 | F254: =+E254*D254 | G254: 1 | H254: =+G254*F254
...

Sheet Recon
C1: Challan (pcs) | D1: Stock (Sold) | E1: Gap | F1: Total Available | J1: Coooling Coil | L1: Challan (pcs) | M1: Stock (Sold) | N1: Gap | O1: Total Available | Q1: R.Drier | S1: Challan (pcs) | T1: Stock (Sold) | U1: Gap | V1: Total Available | X1: Switches | Z1: Challan (pcs) | AA1: Stock (Sold) | AB1: Gap | AC1: Total Available | AE1: Blowers | AG1: Challan (pcs) | AH1: Stock (Sold) | AI1: Gap | AJ1: Total Available | AK1: Match key | AM1: SEAL | AO1: Challan (pcs) | AP1: Stock (Sold) | AQ1: Gap | AR1: Total Available | AT1: TOKODEN FAN | AV1: Challan (pcs) | AW1: Stock (Sold) | AX1: Gap | AY1: Total Available | AZ1: Match key | BB1: EXPENSION VALVE | BD1: Challan (pcs) | BE1: Stock (Sold) | BF1: Gap | BG1: Total Available | BH1: Match key | BJ1: COOLING COIL (PREMIUM) | BL1: Challan (pcs) | BM1: Stock (Sold) | BN1: Gap | BO1: Total Available | BP1: Match key | BR1: COMPRESSOR / HOSE / TAPE / GAS | BT1: Challan (pcs) | BU1: Stock (Sold) | BV1: Gap | BW1: Total Available | BY1: SDN COMPRESSOR CLUTCH PARTS | CA1: Challan (pcs) | CB1: Stock (Sold) | CC1: Gap | CD1: Total Available | CF1: OIL & AGRICULTURAL HOSE (Part 3) | CG1: Stock unit | CH1: Challan (pcs) | CI1: Stock (Sold) | CJ1: Gap | CK1: Total Available | CL1: Stock header (guard)
A2: ACCENT CRD-I | B2: PC-86064 | C2: 88 | D2: {=IF($A2="","",IF(TRIM(INDEX('Part 1'!$F$3:$CZ$3,1,ROW()-1))=TRIM($A2),INDEX('Part 1'!$F$386:$CZ$386,1,ROW()-1),"CHECK"))} -> 100 | E2: =IF(OR($A2="",$D2="CHECK",$D2=""),"",$C2-$D2) -> -12 | F2: {=IF($A2="","",IF(TRIM(INDEX('Part 1'!$F$3:$CZ$3,1,ROW()-1))=TRIM($A2),INDEX('Part 1'!$F$38:$CZ$38,1,ROW()-1),"CHECK"))} -> 100 | J2: A6 | K2: PC-A6 | L2: 715 | M2: {=IF($J2="","",IF(TRIM(INDEX('Part 1'!$CS$3:$EQ$3,1,ROW()-1))=TRIM($J2),INDEX('Part 1'!$CS$386:$EQ$386,1,ROW()-1),"CHECK"))} -> 702 | N2: =IF(OR($J2="",$M2="CHECK",$M2=""),"",$L2-$M2) -> 13 | O2: {=IF($J2="","",IF(TRIM(INDEX('Part 1'!$CS$3:$EQ$3,1,ROW()-1))=TRIM($J2),INDEX('Part 1'!$CS$38:$EQ$38,1,ROW()-1),"CHECK"))} -> 1008 | Q2: Ambasdor/ BOlero | R2: PC-8120 | S2: 325 | T2: {=IF($Q2="","",IF(TRIM(INDEX('Part 1'!$GD$3:$HB$3,1,ROW()-1))=TRIM($Q2),INDEX('Part 1'!$GD$386:$HB$386,1,ROW()-1),"CHECK"))} -> 325 | U2: =IF(OR($Q2="",$T2="CHECK",$T2=""),"",$S2-$T2) -> 0 | V2: {=IF($Q2="","",IF(TRIM(INDEX('Part 1'!$GD$3:$HB$3,1,ROW()-1))=TRIM($Q2),INDEX('Part 1'!$GD$38:$HB$38,1,ROW()-1),"CHECK"))} -> 750 | X2: CONCORD A/C SWITCH | Z2: 2 | AA2: {=IF($X2="","",IF(TRIM(INDEX('Part 1'!$FG$3:$GC$3,1,ROW()-1))=TRIM($X2),INDEX('Part 1'!$FG$386:$GC$386,1,ROW()-1),"CHECK"))} -> 2 | AB2: =IF(OR($X2="",$AA2="CHECK",$AA2=""),"",$Z2-$AA2) -> 0 | AC2: {=IF($X2="","",IF(TRIM(INDEX('Part 1'!$FG$3:$GC$3,1,ROW()-1))=TRIM($X2),INDEX('Part 1'!$FG$38:$GC$38,1,ROW()-1),"CHECK"))} -> 0 | AE2: MICROBUS-Tubefin | AG2: 155 | AH2: {=IF($AE2="","",IF(TRIM(INDEX('Part 1'!$ER$3:$FF$3,1,ROW()-1))=TRIM($AE2),INDEX('Part 1'!$ER$386:$FF$386,1,ROW()-1),"CHECK"))} -> 155 | AI2: =IF(OR($AE2="",$AH2="CHECK",$AH2=""),"",ROUND($AG2-$AH2,2)) -> 0 | AJ2: {=IF($AE2="","",IF(TRIM(INDEX('Part 1'!$ER$3:$FF$3,1,ROW()-1))=TRIM($AE2),INDEX('Part 1'!$ER$38:$FF$38,1,ROW()-1),"CHECK"))} -> 155 | AK2: MICROBUS BLOWER | AM2: 507 | AN2: PC-7001A | AO2: 0 | AP2: {=IF($AM2="","",IF(TRIM(INDEX('Part 1'!$HC$3:$HT$3,1,ROW()-1))=TRIM($AM2),INDEX('Part 1'!$HC$386:$HT$386,1,ROW()-1),"CHECK"))} -> 0 | AQ2: =IF(OR($AM2="",$AP2="CHECK",$AP2=""),"",ROUND($AO2-$AP2,2)) -> 0 | AR2: {=IF($AM2="","",IF(TRIM(INDEX('Part 1'!$HC$3:$HT$3,1,ROW()-1))=TRIM($AM2),INDEX('Part 1'!$HC$38:$HT$38,1,ROW()-1),"CHECK"))} -> 0 | AT2: 10" Staight -80w | AU2: TST-8801 | AV2: 1020 | AW2: {=IF($AT2="","",IF(TRIM(INDEX('Part 1'!$HU$3:$IC$3,1,ROW()-1))=TRIM($AT2),INDEX('Part 1'!$HU$386:$IC$386,1,ROW()-1),"CHECK"))} -> 1030 | AX2: =IF(OR($AT2="",$AW2="CHECK",$AW2=""),"",ROUND($AV2-$AW2,2)) -> -10 | AY2: {=IF($AT2="","",IF(TRIM(INDEX('Part 1'!$HU$3:$IC$3,1,ROW()-1))=TRIM($AT2),INDEX('Part 1'!$HU$38:$IC$38,1,ROW()-1),"CHECK"))} -> 2000 | AZ2: 10" Staight -80w | BB2: TRAVERA / ACCENT | BC2: FK-C906 | BD2: 50 | BE2: {=IF($BB2="","",IF(TRIM(INDEX('Part 1'!$ID$3:$IP$3,1,ROW()-1))=TRIM($BB2),INDEX('Part 1'!$ID$386:$IP$386,1,ROW()-1),"CHECK"))} -> 50 | BF2: =IF(OR($BB2="",$BE2="CHECK",$BE2=""),"",ROUND($BD2-$BE2,2)) -> 0 | BG2: {=IF($BB2="","",IF(TRIM(INDEX('Part 1'!$ID$3:$IP$3,1,ROW()-1))=TRIM($BB2),INDEX('Part 1'!$ID$38:$IP$38,1,ROW()-1),"CHECK"))} -> 200 | BH2: TRAVERA / ACCENT | BJ2: ACCENT | BK2: PC-E420 | BL2: 70 | BM2: {=IF($BJ2="","",IF(TRIM(INDEX('Part 2'!$F$3:$AS$3,1,ROW()-1))=TRIM($BJ2),INDEX('Part 2'!$F$243:$AS$243,1,ROW()-1),"CHECK"))} -> 70 | BN2: =IF(OR($BJ2="",$BM2="CHECK",$BM2=""),"",ROUND($BL2-$BM2,2)) -> 0 | BO2: {=IF($BJ2="","",IF(TRIM(INDEX('Part 2'!$F$3:$AS$3,1,ROW()-1))=TRIM($BJ2),INDEX('Part 2'!$F$33:$AS$33,1,ROW()-1),"CHECK"))} -> 70 | BP2: ACCENT | BR2: compressor SM-5 | BS2: AT | BT2: 100 | BU2: =IF(TRIM('Part 2'!$AT$3&" "&'Part 2'!$AT$4)=TRIM($BR2),'Part 2'!$AT$243,"CHECK") -> 100 | BV2: =IF(OR($BR2="",$BU2="CHECK"),"",ROUND($BT2-$BU2,2)) -> 0 | BW2: =IF(TRIM('Part 2'!$AT$3&" "&'Part 2'!$AT$4)=TRIM($BR2),'Part 2'!$AT$33,"CHECK") -> 100 | BY2: PLATE HONDA | BZ2: SD-1001 | CA2: 60 | CB2: {=IF($BY2="","",IF(TRIM(INDEX('Part 2'!$BJ$3:$CZ$3,1,ROW()-1))=TRIM($BZ2),INDEX('Part 2'!$BJ$243:$CZ$243,1,ROW()-1),"CHECK"))} -> 60 | CC2: =IF(OR($BY2="",$CB2="CHECK"),"",ROUND($CA2-$CB2,2)) -> 0 | CD2: {=IF($BY2="","",IF(TRIM(INDEX('Part 2'!$BJ$3:$CZ$3,1,ROW()-1))=TRIM($BZ2),INDEX('Part 2'!$BJ$33:$CZ$33,1,ROW()-1),"CHECK"))} -> 60 | CF2: 1 LITR | CG2: PCS | CH2: 7464 | CI2: =IF(TRIM('Part 3'!$F$3&" "&'Part 3'!$F$4)=TRIM($CL2),'Part 3'!$F$57,"CHECK") -> 7464 | CJ2: =IF(OR($CH2="",$CI2="CHECK"),"",ROUND($CH2-$CI2,2)) -> 0 | CK2: =IF(TRIM('Part 3'!$F$3&" "&'Part 3'!$F$4)=TRIM($CL2),'Part 3'!$F$16,"CHECK") -> 12696 | CL2: 1 LITR PCS
A3: ACCENT-PETROL | B3: PC-86248 | C3: 101 | D3: {=IF($A3="","",IF(TRIM(INDEX('Part 1'!$F$3:$CZ$3,1,ROW()-1))=TRIM($A3),INDEX('Part 1'!$F$386:$CZ$386,1,ROW()-1),"CHECK"))} -> 101 | E3: =IF(OR($A3="",$D3="CHECK",$D3=""),"",$C3-$D3) -> 0 | F3: {=IF($A3="","",IF(TRIM(INDEX('Part 1'!$F$3:$CZ$3,1,ROW()-1))=TRIM($A3),INDEX('Part 1'!$F$38:$CZ$38,1,ROW()-1),"CHECK"))} -> 100 | J3: 848L MICROBUS COIL | L3: 0 | M3: {=IF($J3="","",IF(TRIM(INDEX('Part 1'!$CS$3:$EQ$3,1,ROW()-1))=TRIM($J3),INDEX('Part 1'!$CS$386:$EQ$386,1,ROW()-1),"CHECK"))} -> 0 | N3: =IF(OR($J3="",$M3="CHECK",$M3=""),"",$L3-$M3) -> 0 | O3: {=IF($J3="","",IF(TRIM(INDEX('Part 1'!$CS$3:$EQ$3,1,ROW()-1))=TRIM($J3),INDEX('Part 1'!$CS$38:$EQ$38,1,ROW()-1),"CHECK"))} -> 0 | Q3: AVEO | R3: PC-8797 | S3: 50 | T3: {=IF($Q3="","",IF(TRIM(INDEX('Part 1'!$GD$3:$HB$3,1,ROW()-1))=TRIM($Q3),INDEX('Part 1'!$GD$386:$HB$386,1,ROW()-1),"CHECK"))} -> 50 | U3: =IF(OR($Q3="",$T3="CHECK",$T3=""),"",$S3-$T3) -> 0 | V3: {=IF($Q3="","",IF(TRIM(INDEX('Part 1'!$GD$3:$HB$3,1,ROW()-1))=TRIM($Q3),INDEX('Part 1'!$GD$38:$HB$38,1,ROW()-1),"CHECK"))} -> 50 | X3: CONCORD RESISTANCE | Z3: 0 | AA3: {=IF($X3="","",IF(TRIM(INDEX('Part 1'!$FG$3:$GC$3,1,ROW()-1))=TRIM($X3),INDEX('Part 1'!$FG$386:$GC$386,1,ROW()-1),"CHECK"))} -> 0 | AB3: =IF(OR($X3="",$AA3="CHECK",$AA3=""),"",$Z3-$AA3) -> 0 | AC3: {=IF($X3="","",IF(TRIM(INDEX('Part 1'!$FG$3:$GC$3,1,ROW()-1))=TRIM($X3),INDEX('Part 1'!$FG$38:$GC$38,1,ROW()-1),"CHECK"))} -> 0 | AE3: MICROBUS-PF | AG3: 0 | AH3: {=IF($AE3="","",IF(TRIM(INDEX('Part 1'!$ER$3:$FF$3,1,ROW()-1))=TRIM($AE3),INDEX('Part 1'!$ER$386:$FF$386,1,ROW()-1),"CHECK"))} -> 0 | AI3: =IF(OR($AE3="",$AH3="CHECK",$AH3=""),"",ROUND($AG3-$AH3,2)) -> 0 | AJ3: {=IF($AE3="","",IF(TRIM(INDEX('Part 1'!$ER$3:$FF$3,1,ROW()-1))=TRIM($AE3),INDEX('Part 1'!$ER$38:$FF$38,1,ROW()-1),"CHECK"))} -> 0 | AM3: 508 | AN3: PC-7004A | AO3: 0 | AP3: {=IF($AM3="","",IF(TRIM(INDEX('Part 1'!$HC$3:$HT$3,1,ROW()-1))=TRIM($AM3),INDEX('Part 1'!$HC$386:$HT$386,1,ROW()-1),"CHECK"))} -> 0 | AQ3: =IF(OR($AM3="",$AP3="CHECK",$AP3=""),"",ROUND($AO3-$AP3,2)) -> 0 | AR3: {=IF($AM3="","",IF(TRIM(INDEX('Part 1'!$HC$3:$HT$3,1,ROW()-1))=TRIM($AM3),INDEX('Part 1'!$HC$38:$HT$38,1,ROW()-1),"CHECK"))} -> 0 | AT3: 10" 'S' 80w | AU3: TS-8805 | AV3: 751 | AW3: {=IF($AT3="","",IF(TRIM(INDEX('Part 1'!$HU$3:$IC$3,1,ROW()-1))=TRIM($AT3),INDEX('Part 1'!$HU$386:$IC$386,1,ROW()-1),"CHECK"))} -> 751 | AX3: =IF(OR($AT3="",$AW3="CHECK",$AW3=""),"",ROUND($AV3-$AW3,2)) -> 0 | AY3: {=IF($AT3="","",IF(TRIM(INDEX('Part 1'!$HU$3:$IC$3,1,ROW()-1))=TRIM($AT3),INDEX('Part 1'!$HU$38:$IC$38,1,ROW()-1),"CHECK"))} -> 2000 | AZ3: 10" 'S' 80w | BB3: SKODA | BC3: FK-1080 | BD3: 150 | BE3: {=IF($BB3="","",IF(TRIM(INDEX('Part 1'!$ID$3:$IP$3,1,ROW()-1))=TRIM($BB3),INDEX('Part 1'!$ID$386:$IP$386,1,ROW()-1),"CHECK"))} -> 150 | BF3: =IF(OR($BB3="",$BE3="CHECK",$BE3=""),"",ROUND($BD3-$BE3,2)) -> 0 | BG3: {=IF($BB3="","",IF(TRIM(INDEX('Part 1'!$ID$3:$IP$3,1,ROW()-1))=TRIM($BB3),INDEX('Part 1'!$ID$38:$IP$38,1,ROW()-1),"CHECK"))} -> 200 | BH3: SKODA | BJ3: AVEO | BK3: PC-E614 | BL3: 32 | BM3: {=IF($BJ3="","",IF(TRIM(INDEX('Part 2'!$F$3:$AS$3,1,ROW()-1))=TRIM($BJ3),INDEX('Part 2'!$F$243:$AS$243,1,ROW()-1),"CHECK"))} -> 32 | BN3: =IF(OR($BJ3="",$BM3="CHECK",$BM3=""),"",ROUND($BL3-$BM3,2)) -> 0 | BO3: {=IF($BJ3="","",IF(TRIM(INDEX('Part 2'!$F$3:$AS$3,1,ROW()-1))=TRIM($BJ3),INDEX('Part 2'!$F$33:$AS$33,1,ROW()-1),"CHECK"))} -> 79 | BP3: AVEO | BR3: SM-7 | BS3: AU | BT3: 600 | BU3: =IF(TRIM('Part 2'!$AU$3&" "&'Part 2'!$AU$4)=TRIM($BR3),'Part 2'!$AU$243,"CHECK") -> 566 | BV3: =IF(OR($BR3="",$BU3="CHECK"),"",ROUND($BT3-$BU3,2)) -> 34 | BW3: =IF(TRIM('Part 2'!$AU$3&" "&'Part 2'!$AU$4)=TRIM($BR3),'Part 2'!$AU$33,"CHECK") -> 600 | BY3: MAGNATTE COIL HONDA | BZ3: SD-1001A | CA3: 120 | CB3: {=IF($BY3="","",IF(TRIM(INDEX('Part 2'!$BJ$3:$CZ$3,1,ROW()-1))=TRIM($BZ3),INDEX('Part 2'!$BJ$243:$CZ$243,1,ROW()-1),"CHECK"))} -> 120 | CC3: =IF(OR($BY3="",$CB3="CHECK"),"",ROUND($CA3-$CB3,2)) -> 0 | CD3: {=IF($BY3="","",IF(TRIM(INDEX('Part 2'!$BJ$3:$CZ$3,1,ROW()-1))=TRIM($BZ3),INDEX('Part 2'!$BJ$33:$CZ$33,1,ROW()-1),"CHECK"))} -> 120 | CF3: 250G | CG3: PCS | CH3: 1704 | CI3: =IF(TRIM('Part 3'!$G$3&" "&'Part 3'!$G$4)=TRIM($CL3),'Part 3'!$G$57,"CHECK") -> 1704 | CJ3: =IF(OR($CH3="",$CI3="CHECK"),"",ROUND($CH3-$CI3,2)) -> 0 | CK3: =IF(TRIM('Part 3'!$G$3&" "&'Part 3'!$G$4)=TRIM($CL3),'Part 3'!$G$16,"CHECK") -> 1704 | CL3: 250G PCS
A4: ACCORD | C4: 0 | D4: {=IF($A4="","",IF(TRIM(INDEX('Part 1'!$F$3:$CZ$3,1,ROW()-1))=TRIM($A4),INDEX('Part 1'!$F$386:$CZ$386,1,ROW()-1),"CHECK"))} -> 0 | E4: =IF(OR($A4="",$D4="CHECK",$D4=""),"",$C4-$D4) -> 0 | F4: {=IF($A4="","",IF(TRIM(INDEX('Part 1'!$F$3:$CZ$3,1,ROW()-1))=TRIM($A4),INDEX('Part 1'!$F$38:$CZ$38,1,ROW()-1),"CHECK"))} -> 0 | J4: Accent | K4: PC-055R | L4: 258 | M4: {=IF($J4="","",IF(TRIM(INDEX('Part 1'!$CS$3:$EQ$3,1,ROW()-1))=TRIM($J4),INDEX('Part 1'!$CS$386:$EQ$386,1,ROW()-1),"CHECK"))} -> 258 | N4: =IF(OR($J4="",$M4="CHECK",$M4=""),"",$L4-$M4) -> 0 | O4: {=IF($J4="","",IF(TRIM(INDEX('Part 1'!$CS$3:$EQ$3,1,ROW()-1))=TRIM($J4),INDEX('Part 1'!$CS$38:$EQ$38,1,ROW()-1),"CHECK"))} -> 306 | Q4: BUS-UNI | R4: PC-61020 | S4: 460 | T4: {=IF($Q4="","",IF(TRIM(INDEX('Part 1'!$GD$3:$HB$3,1,ROW()-1))=TRIM($Q4),INDEX('Part 1'!$GD$386:$HB$386,1,ROW()-1),"CHECK"))} -> 460 | U4: =IF(OR($Q4="",$T4="CHECK",$T4=""),"",$S4-$T4) -> 0 | V4: {=IF($Q4="","",IF(TRIM(INDEX('Part 1'!$GD$3:$HB$3,1,ROW()-1))=TRIM($Q4),INDEX('Part 1'!$GD$38:$HB$38,1,ROW()-1),"CHECK"))} -> 460 | X4: esteem r12 ordanary | Y4: PC-1052 | Z4: 0 | AA4: {=IF($X4="","",IF(TRIM(INDEX('Part 1'!$FG$3:$GC$3,1,ROW()-1))=TRIM($X4),INDEX('Part 1'!$FG$386:$GC$386,1,ROW()-1),"CHECK"))} -> 0 | AB4: =IF(OR($X4="",$AA4="CHECK",$AA4=""),"",$Z4-$AA4) -> 0 | AC4: {=IF($X4="","",IF(TRIM(INDEX('Part 1'!$FG$3:$GC$3,1,ROW()-1))=TRIM($X4),INDEX('Part 1'!$FG$38:$GC$38,1,ROW()-1),"CHECK"))} -> 800 | AE4: MiniBus | AG4: 66 | AH4: {=IF($AE4="","",IF(TRIM(INDEX('Part 1'!$ER$3:$FF$3,1,ROW()-1))=TRIM($AE4),INDEX('Part 1'!$ER$386:$FF$386,1,ROW()-1),"CHECK"))} -> 66 | AI4: =IF(OR($AE4="",$AH4="CHECK",$AH4=""),"",ROUND($AG4-$AH4,2)) -> 0 | AJ4: {=IF($AE4="","",IF(TRIM(INDEX('Part 1'!$ER$3:$FF$3,1,ROW()-1))=TRIM($AE4),INDEX('Part 1'!$ER$38:$FF$38,1,ROW()-1),"CHECK"))} -> 66 | AK4: MINIBUS | AM4: 507 single seal | AN4: PC-7053A | AO4: 600 | AP4: {=IF($AM4="","",IF(TRIM(INDEX('Part 1'!$HC$3:$HT$3,1,ROW()-1))=TRIM($AM4),INDEX('Part 1'!$HC$386:$HT$386,1,ROW()-1),"CHECK"))} -> 600 | AQ4: =IF(OR($AM4="",$AP4="CHECK",$AP4=""),"",ROUND($AO4-$AP4,2)) -> 0 | AR4: {=IF($AM4="","",IF(TRIM(INDEX('Part 1'!$HC$3:$HT$3,1,ROW()-1))=TRIM($AM4),INDEX('Part 1'!$HC$38:$HT$38,1,ROW()-1),"CHECK"))} -> 3000 | AT4: 12" Staight -80w | AU4: TST-8801-A | AV4: 635 | AW4: {=IF($AT4="","",IF(TRIM(INDEX('Part 1'!$HU$3:$IC$3,1,ROW()-1))=TRIM($AT4),INDEX('Part 1'!$HU$386:$IC$386,1,ROW()-1),"CHECK"))} -> 635 | AX4: =IF(OR($AT4="",$AW4="CHECK",$AW4=""),"",ROUND($AV4-$AW4,2)) -> 0 | AY4: {=IF($AT4="","",IF(TRIM(INDEX('Part 1'!$HU$3:$IC$3,1,ROW()-1))=TRIM($AT4),INDEX('Part 1'!$HU$38:$IC$38,1,ROW()-1),"CHECK"))} -> 2000 | AZ4: 12" Staight -80w | BB4: WR/ALTO | BC4: FK-1089D | BD4: 0 | BE4: {=IF($BB4="","",IF(TRIM(INDEX('Part 1'!$ID$3:$IP$3,1,ROW()-1))=TRIM($BB4),INDEX('Part 1'!$ID$386:$IP$386,1,ROW()-1),"CHECK"))} -> 0 | BF4: =IF(OR($BB4="",$BE4="CHECK",$BE4=""),"",ROUND($BD4-$BE4,2)) -> 0 | BG4: {=IF($BB4="","",IF(TRIM(INDEX('Part 1'!$ID$3:$IP$3,1,ROW()-1))=TRIM($BB4),INDEX('Part 1'!$ID$38:$IP$38,1,ROW()-1),"CHECK"))} -> 200 | BH4: WR/ALTO | BJ4: BALENO | BK4: PC-E407 | BL4: 126 | BM4: {=IF($BJ4="","",IF(TRIM(INDEX('Part 2'!$F$3:$AS$3,1,ROW()-1))=TRIM($BJ4),INDEX('Part 2'!$F$243:$AS$243,1,ROW()-1),"CHECK"))} -> 126 | BN4: =IF(OR($BJ4="",$BM4="CHECK",$BM4=""),"",ROUND($BL4-$BM4,2)) -> 0 | BO4: {=IF($BJ4="","",IF(TRIM(INDEX('Part 2'!$F$3:$AS$3,1,ROW()-1))=TRIM($BJ4),INDEX('Part 2'!$F$33:$AS$33,1,ROW()-1),"CHECK"))} -> 128 | BP4: BALENO | BR4: SM-8 | BS4: AV | BT4: 200 | BU4: =IF(TRIM('Part 2'!$AV$3&" "&'Part 2'!$AV$4)=TRIM($BR4),'Part 2'!$AV$243,"CHECK") -> 234 | BV4: =IF(OR($BR4="",$BU4="CHECK"),"",ROUND($BT4-$BU4,2)) -> -34 | BW4: =IF(TRIM('Part 2'!$AV$3&" "&'Part 2'!$AV$4)=TRIM($BR4),'Part 2'!$AV$33,"CHECK") -> 200 | BY4: PULLEY PULL HONDA | BZ4: SD-1001B | CA4: 48 | CB4: {=IF($BY4="","",IF(TRIM(INDEX('Part 2'!$BJ$3:$CZ$3,1,ROW()-1))=TRIM($BZ4),INDEX('Part 2'!$BJ$243:$CZ$243,1,ROW()-1),"CHECK"))} -> 48 | CC4: =IF(OR($BY4="",$CB4="CHECK"),"",ROUND($CA4-$CB4,2)) -> 0 | CD4: {=IF($BY4="","",IF(TRIM(INDEX('Part 2'!$BJ$3:$CZ$3,1,ROW()-1))=TRIM($BZ4),INDEX('Part 2'!$BJ$33:$CZ$33,1,ROW()-1),"CHECK"))} -> 48 | CF4: 4 LTR | CG4: BOTTLE | CH4: 504 | CI4: =IF(TRIM('Part 3'!$H$3&" "&'Part 3'!$H$4)=TRIM($CL4),'Part 3'!$H$57,"CHECK") -> 504 | CJ4: =IF(OR($CH4="",$CI4="CHECK"),"",ROUND($CH4-$CI4,2)) -> 0 | CK4: =IF(TRIM('Part 3'!$H$3&" "&'Part 3'!$H$4)=TRIM($CL4),'Part 3'!$H$16,"CHECK") -> 504 | CL4: 4 LTR BOTTLE
A5: AMBASDOR | B5: PC-86041 | C5: 150 | D5: {=IF($A5="","",IF(TRIM(INDEX('Part 1'!$F$3:$CZ$3,1,ROW()-1))=TRIM($A5),INDEX('Part 1'!$F$386:$CZ$386,1,ROW()-1),"CHECK"))} -> 150 | E5: =IF(OR($A5="",$D5="CHECK",$D5=""),"",$C5-$D5) -> 0 | F5: {=IF($A5="","",IF(TRIM(INDEX('Part 1'!$F$3:$CZ$3,1,ROW()-1))=TRIM($A5),INDEX('Part 1'!$F$38:$CZ$38,1,ROW()-1),"CHECK"))} -> 150 | J5: ACCORD | K5: PC-510 | L5: 0 | M5: {=IF($J5="","",IF(TRIM(INDEX('Part 1'!$CS$3:$EQ$3,1,ROW()-1))=TRIM($J5),INDEX('Part 1'!$CS$386:$EQ$386,1,ROW()-1),"CHECK"))} -> 0 | N5: =IF(OR($J5="",$M5="CHECK",$M5=""),"",$L5-$M5) -> 0 | O5: {=IF($J5="","",IF(TRIM(INDEX('Part 1'!$CS$3:$EQ$3,1,ROW()-1))=TRIM($J5),INDEX('Part 1'!$CS$38:$EQ$38,1,ROW()-1),"CHECK"))} -> 0 | Q5: Daewoo Cielo | R5: PC-8263 | S5: 20 | T5: {=IF($Q5="","",IF(TRIM(INDEX('Part 1'!$GD$3:$HB$3,1,ROW()-1))=TRIM($Q5),INDEX('Part 1'!$GD$386:$HB$386,1,ROW()-1),"CHECK"))} -> 20 | U5: =IF(OR($Q5="",$T5="CHECK",$T5=""),"",$S5-$T5) -> 0 | V5: {=IF($Q5="","",IF(TRIM(INDEX('Part 1'!$GD$3:$HB$3,1,ROW()-1))=TRIM($Q5),INDEX('Part 1'!$GD$38:$HB$38,1,ROW()-1),"CHECK"))} -> 0 | X5: ESTEEM-R12 / Accent | Y5: PC-1046 | Z5: 149 | AA5: {=IF($X5="","",IF(TRIM(INDEX('Part 1'!$FG$3:$GC$3,1,ROW()-1))=TRIM($X5),INDEX('Part 1'!$FG$386:$GC$386,1,ROW()-1),"CHECK"))} -> 149 | AB5: =IF(OR($X5="",$AA5="CHECK",$AA5=""),"",$Z5-$AA5) -> 0 | AC5: {=IF($X5="","",IF(TRIM(INDEX('Part 1'!$FG$3:$GC$3,1,ROW()-1))=TRIM($X5),INDEX('Part 1'!$FG$38:$GC$38,1,ROW()-1),"CHECK"))} -> 1000 | AE5: SK | AG5: 550 | AH5: {=IF($AE5="","",IF(TRIM(INDEX('Part 1'!$ER$3:$FF$3,1,ROW()-1))=TRIM($AE5),INDEX('Part 1'!$ER$386:$FF$386,1,ROW()-1),"CHECK"))} -> 550 | AI5: =IF(OR($AE5="",$AH5="CHECK",$AH5=""),"",ROUND($AG5-$AH5,2)) -> 0 | AJ5: {=IF($AE5="","",IF(TRIM(INDEX('Part 1'!$ER$3:$FF$3,1,ROW()-1))=TRIM($AE5),INDEX('Part 1'!$ER$38:$FF$38,1,ROW()-1),"CHECK"))} -> 550 | AK5: SK BLOWER | AM5: 507-AA | AN5: PC-7001A | AO5: 2250 | AP5: {=IF($AM5="","",IF(TRIM(INDEX('Part 1'!$HC$3:$HT$3,1,ROW()-1))=TRIM($AM5),INDEX('Part 1'!$HC$386:$HT$386,1,ROW()-1),"CHECK"))} -> 1950 | AQ5: =IF(OR($AM5="",$AP5="CHECK",$AP5=""),"",ROUND($AO5-$AP5,2)) -> 300 | AR5: {=IF($AM5="","",IF(TRIM(INDEX('Part 1'!$HC$3:$HT$3,1,ROW()-1))=TRIM($AM5),INDEX('Part 1'!$HC$38:$HT$38,1,ROW()-1),"CHECK"))} -> 3000 | AT5: 12" 'S' 80w | AU5: TS-8805-B | AV5: 985 | AW5: {=IF($AT5="","",IF(TRIM(INDEX('Part 1'!$HU$3:$IC$3,1,ROW()-1))=TRIM($AT5),INDEX('Part 1'!$HU$386:$IC$386,1,ROW()-1),"CHECK"))} -> 985 | AX5: =IF(OR($AT5="",$AW5="CHECK",$AW5=""),"",ROUND($AV5-$AW5,2)) -> 0 | AY5: {=IF($AT5="","",IF(TRIM(INDEX('Part 1'!$HU$3:$IC$3,1,ROW()-1))=TRIM($AT5),INDEX('Part 1'!$HU$38:$IC$38,1,ROW()-1),"CHECK"))} -> 2000 | AZ5: 12" 'S' 80w | BB5: OPEL / INDICA BEHR C/ SCORPIO | BC5: FK-1181 | BD5: 200 | BE5: {=IF($BB5="","",IF(TRIM(INDEX('Part 1'!$ID$3:$IP$3,1,ROW()-1))=TRIM($BB5),INDEX('Part 1'!$ID$386:$IP$386,1,ROW()-1),"CHECK"))} -> 200 | BF5: =IF(OR($BB5="",$BE5="CHECK",$BE5=""),"",ROUND($BD5-$BE5,2)) -> 0 | BG5: {=IF($BB5="","",IF(TRIM(INDEX('Part 1'!$ID$3:$IP$3,1,ROW()-1))=TRIM($BB5),INDEX('Part 1'!$ID$38:$IP$38,1,ROW()-1),"CHECK"))} -> 200 | BH5: OPEL / INDICA BEHR C/ SCORPIO | BJ5: CAMRY | BK5: PC-E533 | BL5: 24 | BM5: {=IF($BJ5="","",IF(TRIM(INDEX('Part 2'!$F$3:$AS$3,1,ROW()-1))=TRIM($BJ5),INDEX('Part 2'!$F$243:$AS$243,1,ROW()-1),"CHECK"))} -> 24 | BN5: =IF(OR($BJ5="",$BM5="CHECK",$BM5=""),"",ROUND($BL5-$BM5,2)) -> 0 | BO5: {=IF($BJ5="","",IF(TRIM(INDEX('Part 2'!$F$3:$AS$3,1,ROW()-1))=TRIM($BJ5),INDEX('Part 2'!$F$33:$AS$33,1,ROW()-1),"CHECK"))} -> 58 | BP5: CAMRY | BR5: SM-10 | BS5: AW | BT5: 110 | BU5: =IF(TRIM('Part 2'!$AW$3&" "&'Part 2'!$AW$4)=TRIM($BR5),'Part 2'!$AW$243,"CHECK") -> 100 | BV5: =IF(OR($BR5="",$BU5="CHECK"),"",ROUND($BT5-$BU5,2)) -> 10 | BW5: =IF(TRIM('Part 2'!$AW$3&" "&'Part 2'!$AW$4)=TRIM($BR5),'Part 2'!$AW$33,"CHECK") -> 100 | BY5: PLATE HUB SONATA | BZ5: SD-1002 | CA5: 60 | CB5: {=IF($BY5="","",IF(TRIM(INDEX('Part 2'!$BJ$3:$CZ$3,1,ROW()-1))=TRIM($BZ5),INDEX('Part 2'!$BJ$243:$CZ$243,1,ROW()-1),"CHECK"))} -> 60 | CC5: =IF(OR($BY5="",$CB5="CHECK"),"",ROUND($CA5-$CB5,2)) -> 0 | CD5: {=IF($BY5="","",IF(TRIM(INDEX('Part 2'!$BJ$3:$CZ$3,1,ROW()-1))=TRIM($BZ5),INDEX('Part 2'!$BJ$33:$CZ$33,1,ROW()-1),"CHECK"))} -> 60 | CF5: 20 LTR | CG5: DRUM | CH5: 30 | CI5: =IF(TRIM('Part 3'!$I$3&" "&'Part 3'!$I$4)=TRIM($CL5),'Part 3'!$I$57,"CHECK") -> 20 | CJ5: =IF(OR($CH5="",$CI5="CHECK"),"",ROUND($CH5-$CI5,2)) -> 10 | CK5: =IF(TRIM('Part 3'!$I$3&" "&'Part 3'!$I$4)=TRIM($CL5),'Part 3'!$I$16,"CHECK") -> 30 | CL5: 20 LTR DRUM
A6: AVEO | B6: PC-86177 | C6: 67 | D6: {=IF($A6="","",IF(TRIM(INDEX('Part 1'!$F$3:$CZ$3,1,ROW()-1))=TRIM($A6),INDEX('Part 1'!$F$386:$CZ$386,1,ROW()-1),"CHECK"))} -> 65 | E6: =IF(OR($A6="",$D6="CHECK",$D6=""),"",$C6-$D6) -> 2 | F6: {=IF($A6="","",IF(TRIM(INDEX('Part 1'!$F$3:$CZ$3,1,ROW()-1))=TRIM($A6),INDEX('Part 1'!$F$38:$CZ$38,1,ROW()-1),"CHECK"))} -> 100 | J6: Baleno | K6: PC-142R | L6: 52 | M6: {=IF($J6="","",IF(TRIM(INDEX('Part 1'!$CS$3:$EQ$3,1,ROW()-1))=TRIM($J6),INDEX('Part 1'!$CS$386:$EQ$386,1,ROW()-1),"CHECK"))} -> 52 | N6: =IF(OR($J6="",$M6="CHECK",$M6=""),"",$L6-$M6) -> 0 | O6: {=IF($J6="","",IF(TRIM(INDEX('Part 1'!$CS$3:$EQ$3,1,ROW()-1))=TRIM($J6),INDEX('Part 1'!$CS$38:$EQ$38,1,ROW()-1),"CHECK"))} -> 84 | Q6: DESICCANT FILTER/DRIER | S6: 199 | T6: {=IF($Q6="","",IF(TRIM(INDEX('Part 1'!$GD$3:$HB$3,1,ROW()-1))=TRIM($Q6),INDEX('Part 1'!$GD$386:$HB$386,1,ROW()-1),"CHECK"))} -> 200 | U6: =IF(OR($Q6="",$T6="CHECK",$T6=""),"",$S6-$T6) -> -1 | V6: {=IF($Q6="","",IF(TRIM(INDEX('Part 1'!$GD$3:$HB$3,1,ROW()-1))=TRIM($Q6),INDEX('Part 1'!$GD$38:$HB$38,1,ROW()-1),"CHECK"))} -> 1200 | X6: ESTEEM-R134/Lancer | Y6: PC-1042A & 1044A | Z6: 300 | AA6: {=IF($X6="","",IF(TRIM(INDEX('Part 1'!$FG$3:$GC$3,1,ROW()-1))=TRIM($X6),INDEX('Part 1'!$FG$386:$GC$386,1,ROW()-1),"CHECK"))} -> 300 | AB6: =IF(OR($X6="",$AA6="CHECK",$AA6=""),"",$Z6-$AA6) -> 0 | AC6: {=IF($X6="","",IF(TRIM(INDEX('Part 1'!$FG$3:$GC$3,1,ROW()-1))=TRIM($X6),INDEX('Part 1'!$FG$38:$GC$38,1,ROW()-1),"CHECK"))} -> 1200 | AE6: Concord-Elec, | AG6: 1554 | AH6: {=IF($AE6="","",IF(TRIM(INDEX('Part 1'!$ER$3:$FF$3,1,ROW()-1))=TRIM($AE6),INDEX('Part 1'!$ER$386:$FF$386,1,ROW()-1),"CHECK"))} -> 1534 | AI6: =IF(OR($AE6="",$AH6="CHECK",$AH6=""),"",ROUND($AG6-$AH6,2)) -> 20 | AJ6: {=IF($AE6="","",IF(TRIM(INDEX('Part 1'!$ER$3:$FF$3,1,ROW()-1))=TRIM($AE6),INDEX('Part 1'!$ER$38:$FF$38,1,ROW()-1),"CHECK"))} -> 1600 | AK6: CONCORD BLOWER | AM6: 508-AA | AN6: PC-7004A | AO6: 400 | AP6: {=IF($AM6="","",IF(TRIM(INDEX('Part 1'!$HC$3:$HT$3,1,ROW()-1))=TRIM($AM6),INDEX('Part 1'!$HC$386:$HT$386,1,ROW()-1),"CHECK"))} -> 250 | AQ6: =IF(OR($AM6="",$AP6="CHECK",$AP6=""),"",ROUND($AO6-$AP6,2)) -> 150 | AR6: {=IF($AM6="","",IF(TRIM(INDEX('Part 1'!$HC$3:$HT$3,1,ROW()-1))=TRIM($AM6),INDEX('Part 1'!$HC$38:$HT$38,1,ROW()-1),"CHECK"))} -> 1500 | AT6: 12" 'S' 100w BEHR | AU6: TS-8805-CB | AV6: 400 | AW6: {=IF($AT6="","",IF(TRIM(INDEX('Part 1'!$HU$3:$IC$3,1,ROW()-1))=TRIM($AT6),INDEX('Part 1'!$HU$386:$IC$386,1,ROW()-1),"CHECK"))} -> 410 | AX6: =IF(OR($AT6="",$AW6="CHECK",$AW6=""),"",ROUND($AV6-$AW6,2)) -> -10 | AY6: {=IF($AT6="","",IF(TRIM(INDEX('Part 1'!$HU$3:$IC$3,1,ROW()-1))=TRIM($AT6),INDEX('Part 1'!$HU$38:$IC$38,1,ROW()-1),"CHECK"))} -> 400 | AZ6: 12" 'S' 100w BEHR | BB6: HONDA CITY | BC6: FK-1034 | BD6: 50 | BE6: {=IF($BB6="","",IF(TRIM(INDEX('Part 1'!$ID$3:$IP$3,1,ROW()-1))=TRIM($BB6),INDEX('Part 1'!$ID$386:$IP$386,1,ROW()-1),"CHECK"))} -> 50 | BF6: =IF(OR($BB6="",$BE6="CHECK",$BE6=""),"",ROUND($BD6-$BE6,2)) -> 0 | BG6: {=IF($BB6="","",IF(TRIM(INDEX('Part 1'!$ID$3:$IP$3,1,ROW()-1))=TRIM($BB6),INDEX('Part 1'!$ID$38:$IP$38,1,ROW()-1),"CHECK"))} -> 200 | BH6: HONDA CITY | BJ6: CORROLA | BK6: PC-E443 | BL6: 108 | BM6: {=IF($BJ6="","",IF(TRIM(INDEX('Part 2'!$F$3:$AS$3,1,ROW()-1))=TRIM($BJ6),INDEX('Part 2'!$F$243:$AS$243,1,ROW()-1),"CHECK"))} -> 108 | BN6: =IF(OR($BJ6="",$BM6="CHECK",$BM6=""),"",ROUND($BL6-$BM6,2)) -> 0 | BO6: {=IF($BJ6="","",IF(TRIM(INDEX('Part 2'!$F$3:$AS$3,1,ROW()-1))=TRIM($BJ6),INDEX('Part 2'!$F$33:$AS$33,1,ROW()-1),"CHECK"))} -> 109 | BP6: CORROLA | BR6: COMP BACK PLATE 505/507-F | BS6: AX | BT6: 400 | BU6: =IF(TRIM('Part 2'!$AX$3&" "&'Part 2'!$AX$4)=TRIM($BR6),'Part 2'!$AX$243,"CHECK") -> 400 | BV6: =IF(OR($BR6="",$BU6="CHECK"),"",ROUND($BT6-$BU6,2)) -> 0 | BW6: =IF(TRIM('Part 2'!$AX$3&" "&'Part 2'!$AX$4)=TRIM($BR6),'Part 2'!$AX$33,"CHECK") -> 600 | BY6: MAGNETIC COIL SONATA | BZ6: SD-1002A | CA6: 150 | CB6: {=IF($BY6="","",IF(TRIM(INDEX('Part 2'!$BJ$3:$CZ$3,1,ROW()-1))=TRIM($BZ6),INDEX('Part 2'!$BJ$243:$CZ$243,1,ROW()-1),"CHECK"))} -> 150 | CC6: =IF(OR($BY6="",$CB6="CHECK"),"",ROUND($CA6-$CB6,2)) -> 0 | CD6: {=IF($BY6="","",IF(TRIM(INDEX('Part 2'!$BJ$3:$CZ$3,1,ROW()-1))=TRIM($BZ6),INDEX('Part 2'!$BJ$33:$CZ$33,1,ROW()-1),"CHECK"))} -> 150 | CF6: AGRICULTURL HOSE (weight) - not reconcilable, see note | CG6: KG | CI6: =IF(TRIM('Part 3'!$J$3&" "&'Part 3'!$J$4)=TRIM($CL6),'Part 3'!$J$57,"CHECK") -> 1350 | CJ6: =IF(OR($CH6="",$CI6="CHECK"),"",ROUND($CH6-$CI6,2)) | CK6: =IF(TRIM('Part 3'!$J$3&" "&'Part 3'!$J$4)=TRIM($CL6),'Part 3'!$J$16,"CHECK") -> 1350 | CL6: AGRICULTURL HOSE KG
A7: A-STAR | B7: PC-86274 | C7: 25 | D7: {=IF($A7="","",IF(TRIM(INDEX('Part 1'!$F$3:$CZ$3,1,ROW()-1))=TRIM($A7),INDEX('Part 1'!$F$386:$CZ$386,1,ROW()-1),"CHECK"))} -> 25 | E7: =IF(OR($A7="",$D7="CHECK",$D7=""),"",$C7-$D7) -> 0 | F7: {=IF($A7="","",IF(TRIM(INDEX('Part 1'!$F$3:$CZ$3,1,ROW()-1))=TRIM($A7),INDEX('Part 1'!$F$38:$CZ$38,1,ROW()-1),"CHECK"))} -> 50 | J7: BOlero R134a | K7: PC-8095 | L7: 90 | M7: {=IF($J7="","",IF(TRIM(INDEX('Part 1'!$CS$3:$EQ$3,1,ROW()-1))=TRIM($J7),INDEX('Part 1'!$CS$386:$EQ$386,1,ROW()-1),"CHECK"))} -> 90 | N7: =IF(OR($J7="",$M7="CHECK",$M7=""),"",$L7-$M7) -> 0 | O7: {=IF($J7="","",IF(TRIM(INDEX('Part 1'!$CS$3:$EQ$3,1,ROW()-1))=TRIM($J7),INDEX('Part 1'!$CS$38:$EQ$38,1,ROW()-1),"CHECK"))} -> 125 | Q7: Esteem-R12 | R7: PC-8005 | S7: 4800 | T7: {=IF($Q7="","",IF(TRIM(INDEX('Part 1'!$GD$3:$HB$3,1,ROW()-1))=TRIM($Q7),INDEX('Part 1'!$GD$386:$HB$386,1,ROW()-1),"CHECK"))} -> 4800 | U7: =IF(OR($Q7="",$T7="CHECK",$T7=""),"",$S7-$T7) -> 0 | V7: {=IF($Q7="","",IF(TRIM(INDEX('Part 1'!$GD$3:$HB$3,1,ROW()-1))=TRIM($Q7),INDEX('Part 1'!$GD$38:$HB$38,1,ROW()-1),"CHECK"))} -> 7500 | X7: HONDA CITY | Y7: PC-1045B | Z7: 0 | AA7: {=IF($X7="","",IF(TRIM(INDEX('Part 1'!$FG$3:$GC$3,1,ROW()-1))=TRIM($X7),INDEX('Part 1'!$FG$386:$GC$386,1,ROW()-1),"CHECK"))} -> 0 | AB7: =IF(OR($X7="",$AA7="CHECK",$AA7=""),"",$Z7-$AA7) -> 0 | AC7: {=IF($X7="","",IF(TRIM(INDEX('Part 1'!$FG$3:$GC$3,1,ROW()-1))=TRIM($X7),INDEX('Part 1'!$FG$38:$GC$38,1,ROW()-1),"CHECK"))} -> 200 | AE7: CONCORD-AL-GREY | AG7: 162 | AH7: {=IF($AE7="","",IF(TRIM(INDEX('Part 1'!$ER$3:$FF$3,1,ROW()-1))=TRIM($AE7),INDEX('Part 1'!$ER$386:$FF$386,1,ROW()-1),"CHECK"))} -> 33 | AI7: =IF(OR($AE7="",$AH7="CHECK",$AH7=""),"",ROUND($AG7-$AH7,2)) -> 129 | AJ7: {=IF($AE7="","",IF(TRIM(INDEX('Part 1'!$ER$3:$FF$3,1,ROW()-1))=TRIM($AE7),INDEX('Part 1'!$ER$38:$FF$38,1,ROW()-1),"CHECK"))} -> 0 | AM7: BOLERO | AN7: PC-7237 | AO7: 680 | AP7: {=IF($AM7="","",IF(TRIM(INDEX('Part 1'!$HC$3:$HT$3,1,ROW()-1))=TRIM($AM7),INDEX('Part 1'!$HC$386:$HT$386,1,ROW()-1),"CHECK"))} -> 680 | AQ7: =IF(OR($AM7="",$AP7="CHECK",$AP7=""),"",ROUND($AO7-$AP7,2)) -> 0 | AR7: {=IF($AM7="","",IF(TRIM(INDEX('Part 1'!$HC$3:$HT$3,1,ROW()-1))=TRIM($AM7),INDEX('Part 1'!$HC$38:$HT$38,1,ROW()-1),"CHECK"))} -> 700 | AT7: 14" Staight -80w | AU7: TST-8801-B | AV7: 256 | AW7: {=IF($AT7="","",IF(TRIM(INDEX('Part 1'!$HU$3:$IC$3,1,ROW()-1))=TRIM($AT7),INDEX('Part 1'!$HU$386:$IC$386,1,ROW()-1),"CHECK"))} -> 256 | AX7: =IF(OR($AT7="",$AW7="CHECK",$AW7=""),"",ROUND($AV7-$AW7,2)) -> 0 | AY7: {=IF($AT7="","",IF(TRIM(INDEX('Part 1'!$HU$3:$IC$3,1,ROW()-1))=TRIM($AT7),INDEX('Part 1'!$HU$38:$IC$38,1,ROW()-1),"CHECK"))} -> 400 | AZ7: 14" Staight -80w | BB7: LANCER MMC | BC7: FK-1031B | BD7: 0 | BE7: {=IF($BB7="","",IF(TRIM(INDEX('Part 1'!$ID$3:$IP$3,1,ROW()-1))=TRIM($BB7),INDEX('Part 1'!$ID$386:$IP$386,1,ROW()-1),"CHECK"))} -> 0 | BF7: =IF(OR($BB7="",$BE7="CHECK",$BE7=""),"",ROUND($BD7-$BE7,2)) -> 0 | BG7: {=IF($BB7="","",IF(TRIM(INDEX('Part 1'!$ID$3:$IP$3,1,ROW()-1))=TRIM($BB7),INDEX('Part 1'!$ID$38:$IP$38,1,ROW()-1),"CHECK"))} -> 200 | BH7: LANCER MMC | BJ7: ESTEEM R 12 | BK7: PC-E406 | BL7: 204 | BM7: {=IF($BJ7="","",IF(TRIM(INDEX('Part 2'!$F$3:$AS$3,1,ROW()-1))=TRIM($BJ7),INDEX('Part 2'!$F$243:$AS$243,1,ROW()-1),"CHECK"))} -> 224 | BN7: =IF(OR($BJ7="",$BM7="CHECK",$BM7=""),"",ROUND($BL7-$BM7,2)) -> -20 | BO7: {=IF($BJ7="","",IF(TRIM(INDEX('Part 2'!$F$3:$AS$3,1,ROW()-1))=TRIM($BJ7),INDEX('Part 2'!$F$33:$AS$33,1,ROW()-1),"CHECK"))} -> 218 | BP7: ESTEEM R 12 | BR7: 505/507-O | BS7: AY | BT7: 180 | BU7: =IF(TRIM('Part 2'!$AY$3&" "&'Part 2'!$AY$4)=TRIM($BR7),'Part 2'!$AY$243,"CHECK") -> 195 | BV7: =IF(OR($BR7="",$BU7="CHECK"),"",ROUND($BT7-$BU7,2)) -> -15 | BW7: =IF(TRIM('Part 2'!$AY$3&" "&'Part 2'!$AY$4)=TRIM($BR7),'Part 2'!$AY$33,"CHECK") -> 600 | BY7: PULLEY PULL SONATA | BZ7: SD-1002B | CA7: 24 | CB7: {=IF($BY7="","",IF(TRIM(INDEX('Part 2'!$BJ$3:$CZ$3,1,ROW()-1))=TRIM($BZ7),INDEX('Part 2'!$BJ$243:$CZ$243,1,ROW()-1),"CHECK"))} -> 24 | CC7: =IF(OR($BY7="",$CB7="CHECK"),"",ROUND($CA7-$CB7,2)) -> 0 | CD7: {=IF($BY7="","",IF(TRIM(INDEX('Part 2'!$BJ$3:$CZ$3,1,ROW()-1))=TRIM($BZ7),INDEX('Part 2'!$BJ$33:$CZ$33,1,ROW()-1),"CHECK"))} -> 24 | CF7: AGRICULTURL HOSE (count) | CG7: ROLLS | CH7: 100 | CI7: =IF(TRIM('Part 3'!$K$3&" "&'Part 3'!$K$4)=TRIM($CL7),'Part 3'!$K$57,"CHECK") -> 100 | CJ7: =IF(OR($CH7="",$CI7="CHECK"),"",ROUND($CH7-$CI7,2)) -> 0 | CK7: =IF(TRIM('Part 3'!$K$3&" "&'Part 3'!$K$4)=TRIM($CL7),'Part 3'!$K$16,"CHECK") -> 100 | CL7: ROLLS
A8: BELANO | B8: PC-86242 | C8: 40 | D8: {=IF($A8="","",IF(TRIM(INDEX('Part 1'!$F$3:$CZ$3,1,ROW()-1))=TRIM($A8),INDEX('Part 1'!$F$386:$CZ$386,1,ROW()-1),"CHECK"))} -> 40 | E8: =IF(OR($A8="",$D8="CHECK",$D8=""),"",$C8-$D8) -> 0 | F8: {=IF($A8="","",IF(TRIM(INDEX('Part 1'!$F$3:$CZ$3,1,ROW()-1))=TRIM($A8),INDEX('Part 1'!$F$38:$CZ$38,1,ROW()-1),"CHECK"))} -> 0 | J8: Cielo | K8: PC-043R | L8: 12 | M8: {=IF($J8="","",IF(TRIM(INDEX('Part 1'!$CS$3:$EQ$3,1,ROW()-1))=TRIM($J8),INDEX('Part 1'!$CS$386:$EQ$386,1,ROW()-1),"CHECK"))} -> 12 | N8: =IF(OR($J8="",$M8="CHECK",$M8=""),"",$L8-$M8) -> 0 | O8: {=IF($J8="","",IF(TRIM(INDEX('Part 1'!$CS$3:$EQ$3,1,ROW()-1))=TRIM($J8),INDEX('Part 1'!$CS$38:$EQ$38,1,ROW()-1),"CHECK"))} -> 30 | Q8: Esteem-R134A | R8: PC-8006 | S8: 4600 | T8: {=IF($Q8="","",IF(TRIM(INDEX('Part 1'!$GD$3:$HB$3,1,ROW()-1))=TRIM($Q8),INDEX('Part 1'!$GD$386:$HB$386,1,ROW()-1),"CHECK"))} -> 4600 | U8: =IF(OR($Q8="",$T8="CHECK",$T8=""),"",$S8-$T8) -> 0 | V8: {=IF($Q8="","",IF(TRIM(INDEX('Part 1'!$GD$3:$HB$3,1,ROW()-1))=TRIM($Q8),INDEX('Part 1'!$GD$38:$HB$38,1,ROW()-1),"CHECK"))} -> 8500 | X8: INDICA R-134A-4 pin | Y8: PC-1066 | Z8: 1000 | AA8: {=IF($X8="","",IF(TRIM(INDEX('Part 1'!$FG$3:$GC$3,1,ROW()-1))=TRIM($X8),INDEX('Part 1'!$FG$386:$GC$386,1,ROW()-1),"CHECK"))} -> 1000 | AB8: =IF(OR($X8="",$AA8="CHECK",$AA8=""),"",$Z8-$AA8) -> 0 | AC8: {=IF($X8="","",IF(TRIM(INDEX('Part 1'!$FG$3:$GC$3,1,ROW()-1))=TRIM($X8),INDEX('Part 1'!$FG$38:$GC$38,1,ROW()-1),"CHECK"))} -> 1000 | AE8: CONCORD-AL-BEIGE | AG8: 0 | AH8: {=IF($AE8="","",IF(TRIM(INDEX('Part 1'!$ER$3:$FF$3,1,ROW()-1))=TRIM($AE8),INDEX('Part 1'!$ER$386:$FF$386,1,ROW()-1),"CHECK"))} -> 0 | AI8: =IF(OR($AE8="",$AH8="CHECK",$AH8=""),"",ROUND($AG8-$AH8,2)) -> 0 | AJ8: {=IF($AE8="","",IF(TRIM(INDEX('Part 1'!$ER$3:$FF$3,1,ROW()-1))=TRIM($AE8),INDEX('Part 1'!$ER$38:$FF$38,1,ROW()-1),"CHECK"))} -> 0 | AM8: Clelo | AN8: PC-7059A | AO8: 0 | AP8: {=IF($AM8="","",IF(TRIM(INDEX('Part 1'!$HC$3:$HT$3,1,ROW()-1))=TRIM($AM8),INDEX('Part 1'!$HC$386:$HT$386,1,ROW()-1),"CHECK"))} -> 0 | AQ8: =IF(OR($AM8="",$AP8="CHECK",$AP8=""),"",ROUND($AO8-$AP8,2)) -> 0 | AR8: {=IF($AM8="","",IF(TRIM(INDEX('Part 1'!$HC$3:$HT$3,1,ROW()-1))=TRIM($AM8),INDEX('Part 1'!$HC$38:$HT$38,1,ROW()-1),"CHECK"))} -> 100 | AT8: 14" 'S' 100w JPI | AU8: TS-8805-A | AV8: 305 | AW8: {=IF($AT8="","",IF(TRIM(INDEX('Part 1'!$HU$3:$IC$3,1,ROW()-1))=TRIM($AT8),INDEX('Part 1'!$HU$386:$IC$386,1,ROW()-1),"CHECK"))} -> 305 | AX8: =IF(OR($AT8="",$AW8="CHECK",$AW8=""),"",ROUND($AV8-$AW8,2)) -> 0 | AY8: {=IF($AT8="","",IF(TRIM(INDEX('Part 1'!$HU$3:$IC$3,1,ROW()-1))=TRIM($AT8),INDEX('Part 1'!$HU$38:$IC$38,1,ROW()-1),"CHECK"))} -> 200 | AZ8: 14" 'S' 100w JPI | BB8: SANTRO | BC8: FK-1023B | BD8: 50 | BE8: {=IF($BB8="","",IF(TRIM(INDEX('Part 1'!$ID$3:$IP$3,1,ROW()-1))=TRIM($BB8),INDEX('Part 1'!$ID$386:$IP$386,1,ROW()-1),"CHECK"))} -> 50 | BF8: =IF(OR($BB8="",$BE8="CHECK",$BE8=""),"",ROUND($BD8-$BE8,2)) -> 0 | BG8: {=IF($BB8="","",IF(TRIM(INDEX('Part 1'!$ID$3:$IP$3,1,ROW()-1))=TRIM($BB8),INDEX('Part 1'!$ID$38:$IP$38,1,ROW()-1),"CHECK"))} -> 400 | BH8: SANTRO | BJ8: ESTEEM R 134A | BK8: PC-E035 | BL8: 203 | BM8: {=IF($BJ8="","",IF(TRIM(INDEX('Part 2'!$F$3:$AS$3,1,ROW()-1))=TRIM($BJ8),INDEX('Part 2'!$F$243:$AS$243,1,ROW()-1),"CHECK"))} -> 207 | BN8: =IF(OR($BJ8="",$BM8="CHECK",$BM8=""),"",ROUND($BL8-$BM8,2)) -> -4 | BO8: {=IF($BJ8="","",IF(TRIM(INDEX('Part 2'!$F$3:$AS$3,1,ROW()-1))=TRIM($BJ8),INDEX('Part 2'!$F$33:$AS$33,1,ROW()-1),"CHECK"))} -> 207 | BP8: ESTEEM R 134A | BR8: 508/510-F | BS8: AZ | BT8: 50 | BU8: =IF(TRIM('Part 2'!$AZ$3&" "&'Part 2'!$AZ$4)=TRIM($BR8),'Part 2'!$AZ$243,"CHECK") -> 50 | BV8: =IF(OR($BR8="",$BU8="CHECK"),"",ROUND($BT8-$BU8,2)) -> 0 | BW8: =IF(TRIM('Part 2'!$AZ$3&" "&'Part 2'!$AZ$4)=TRIM($BR8),'Part 2'!$AZ$33,"CHECK") -> 250 | BY8: PLATE HUB QUALIS | BZ8: SD-1003 | CA8: 60 | CB8: {=IF($BY8="","",IF(TRIM(INDEX('Part 2'!$BJ$3:$CZ$3,1,ROW()-1))=TRIM($BZ8),INDEX('Part 2'!$BJ$243:$CZ$243,1,ROW()-1),"CHECK"))} -> 60 | CC8: =IF(OR($BY8="",$CB8="CHECK"),"",ROUND($CA8-$CB8,2)) -> 0 | CD8: {=IF($BY8="","",IF(TRIM(INDEX('Part 2'!$BJ$3:$CZ$3,1,ROW()-1))=TRIM($BZ8),INDEX('Part 2'!$BJ$33:$CZ$33,1,ROW()-1),"CHECK"))} -> 60
A9: BOLERO- R134A | B9: PC-86236 | C9: 105 | D9: {=IF($A9="","",IF(TRIM(INDEX('Part 1'!$F$3:$CZ$3,1,ROW()-1))=TRIM($A9),INDEX('Part 1'!$F$386:$CZ$386,1,ROW()-1),"CHECK"))} -> 105 | E9: =IF(OR($A9="",$D9="CHECK",$D9=""),"",$C9-$D9) -> 0 | F9: {=IF($A9="","",IF(TRIM(INDEX('Part 1'!$F$3:$CZ$3,1,ROW()-1))=TRIM($A9),INDEX('Part 1'!$F$38:$CZ$38,1,ROW()-1),"CHECK"))} -> 100 | J9: Corrolla | K9: PC-114R | L9: 0 | M9: {=IF($J9="","",IF(TRIM(INDEX('Part 1'!$CS$3:$EQ$3,1,ROW()-1))=TRIM($J9),INDEX('Part 1'!$CS$386:$EQ$386,1,ROW()-1),"CHECK"))} -> 0 | N9: =IF(OR($J9="",$M9="CHECK",$M9=""),"",$L9-$M9) -> 0 | O9: {=IF($J9="","",IF(TRIM(INDEX('Part 1'!$CS$3:$EQ$3,1,ROW()-1))=TRIM($J9),INDEX('Part 1'!$CS$38:$EQ$38,1,ROW()-1),"CHECK"))} -> 0 | Q9: Ford | R9: PC-8321 | S9: 87 | T9: {=IF($Q9="","",IF(TRIM(INDEX('Part 1'!$GD$3:$HB$3,1,ROW()-1))=TRIM($Q9),INDEX('Part 1'!$GD$386:$HB$386,1,ROW()-1),"CHECK"))} -> 89 | U9: =IF(OR($Q9="",$T9="CHECK",$T9=""),"",$S9-$T9) -> -2 | V9: {=IF($Q9="","",IF(TRIM(INDEX('Part 1'!$GD$3:$HB$3,1,ROW()-1))=TRIM($Q9),INDEX('Part 1'!$GD$38:$HB$38,1,ROW()-1),"CHECK"))} -> 0 | X9: Innova a/c switch | Z9: 199 | AA9: {=IF($X9="","",IF(TRIM(INDEX('Part 1'!$FG$3:$GC$3,1,ROW()-1))=TRIM($X9),INDEX('Part 1'!$FG$386:$GC$386,1,ROW()-1),"CHECK"))} -> 199 | AB9: =IF(OR($X9="",$AA9="CHECK",$AA9=""),"",$Z9-$AA9) -> 0 | AC9: {=IF($X9="","",IF(TRIM(INDEX('Part 1'!$FG$3:$GC$3,1,ROW()-1))=TRIM($X9),INDEX('Part 1'!$FG$38:$GC$38,1,ROW()-1),"CHECK"))} -> 0 | AE9: CONCORD-COPPER-GREY | AG9: 96 | AH9: {=IF($AE9="","",IF(TRIM(INDEX('Part 1'!$ER$3:$FF$3,1,ROW()-1))=TRIM($AE9),INDEX('Part 1'!$ER$386:$FF$386,1,ROW()-1),"CHECK"))} -> 27 | AI9: =IF(OR($AE9="",$AH9="CHECK",$AH9=""),"",ROUND($AG9-$AH9,2)) -> 69 | AJ9: {=IF($AE9="","",IF(TRIM(INDEX('Part 1'!$ER$3:$FF$3,1,ROW()-1))=TRIM($AE9),INDEX('Part 1'!$ER$38:$FF$38,1,ROW()-1),"CHECK"))} -> 0 | AM9: GASKET 505/507 | AO9: 0 | AP9: {=IF($AM9="","",IF(TRIM(INDEX('Part 1'!$HC$3:$HT$3,1,ROW()-1))=TRIM($AM9),INDEX('Part 1'!$HC$386:$HT$386,1,ROW()-1),"CHECK"))} -> 0 | AQ9: =IF(OR($AM9="",$AP9="CHECK",$AP9=""),"",ROUND($AO9-$AP9,2)) -> 0 | AR9: {=IF($AM9="","",IF(TRIM(INDEX('Part 1'!$HC$3:$HT$3,1,ROW()-1))=TRIM($AM9),INDEX('Part 1'!$HC$38:$HT$38,1,ROW()-1),"CHECK"))} -> 0 | AT9: 15" 'S' Scorpio | AV9: 50 | AW9: {=IF($AT9="","",IF(TRIM(INDEX('Part 1'!$HU$3:$IC$3,1,ROW()-1))=TRIM($AT9),INDEX('Part 1'!$HU$386:$IC$386,1,ROW()-1),"CHECK"))} -> 50 | AX9: =IF(OR($AT9="",$AW9="CHECK",$AW9=""),"",ROUND($AV9-$AW9,2)) -> 0 | AY9: {=IF($AT9="","",IF(TRIM(INDEX('Part 1'!$HU$3:$IC$3,1,ROW()-1))=TRIM($AT9),INDEX('Part 1'!$HU$38:$IC$38,1,ROW()-1),"CHECK"))} -> 200 | AZ9: 15" 'S' Scorpio | BB9: FLARE | BC9: FK-1011 | BD9: 100 | BE9: {=IF($BB9="","",IF(TRIM(INDEX('Part 1'!$ID$3:$IP$3,1,ROW()-1))=TRIM($BB9),INDEX('Part 1'!$ID$386:$IP$386,1,ROW()-1),"CHECK"))} -> 100 | BF9: =IF(OR($BB9="",$BE9="CHECK",$BE9=""),"",ROUND($BD9-$BE9,2)) -> 0 | BG9: {=IF($BB9="","",IF(TRIM(INDEX('Part 1'!$ID$3:$IP$3,1,ROW()-1))=TRIM($BB9),INDEX('Part 1'!$ID$38:$IP$38,1,ROW()-1),"CHECK"))} -> 600 | BH9: FLARE | BJ9: FIESTA | BK9: PC-E417 | BL9: 520 | BM9: {=IF($BJ9="","",IF(TRIM(INDEX('Part 2'!$F$3:$AS$3,1,ROW()-1))=TRIM($BJ9),INDEX('Part 2'!$F$243:$AS$243,1,ROW()-1),"CHECK"))} -> 520 | BN9: =IF(OR($BJ9="",$BM9="CHECK",$BM9=""),"",ROUND($BL9-$BM9,2)) -> 0 | BO9: {=IF($BJ9="","",IF(TRIM(INDEX('Part 2'!$F$3:$AS$3,1,ROW()-1))=TRIM($BJ9),INDEX('Part 2'!$F$33:$AS$33,1,ROW()-1),"CHECK"))} -> 518 | BP9: FIESTA | BR9: 508/510-O | BS9: BA | BT9: 70 | BU9: =IF(TRIM('Part 2'!$BA$3&" "&'Part 2'!$BA$4)=TRIM($BR9),'Part 2'!$BA$243,"CHECK") -> 55 | BV9: =IF(OR($BR9="",$BU9="CHECK"),"",ROUND($BT9-$BU9,2)) -> 15 | BW9: =IF(TRIM('Part 2'!$BA$3&" "&'Part 2'!$BA$4)=TRIM($BR9),'Part 2'!$BA$33,"CHECK") -> 100 | BY9: MAGNATTE COIL QUALIS | BZ9: SD-1003A | CA9: 120 | CB9: {=IF($BY9="","",IF(TRIM(INDEX('Part 2'!$BJ$3:$CZ$3,1,ROW()-1))=TRIM($BZ9),INDEX('Part 2'!$BJ$243:$CZ$243,1,ROW()-1),"CHECK"))} -> 120 | CC9: =IF(OR($BY9="",$CB9="CHECK"),"",ROUND($CA9-$CB9,2)) -> 0 | CD9: {=IF($BY9="","",IF(TRIM(INDEX('Part 2'!$BJ$3:$CZ$3,1,ROW()-1))=TRIM($BZ9),INDEX('Part 2'!$BJ$33:$CZ$33,1,ROW()-1),"CHECK"))} -> 120
A10: CIELO | C10: 0 | D10: {=IF($A10="","",IF(TRIM(INDEX('Part 1'!$F$3:$CZ$3,1,ROW()-1))=TRIM($A10),INDEX('Part 1'!$F$386:$CZ$386,1,ROW()-1),"CHECK"))} -> 0 | E10: =IF(OR($A10="",$D10="CHECK",$D10=""),"",$C10-$D10) -> 0 | F10: {=IF($A10="","",IF(TRIM(INDEX('Part 1'!$F$3:$CZ$3,1,ROW()-1))=TRIM($A10),INDEX('Part 1'!$F$38:$CZ$38,1,ROW()-1),"CHECK"))} -> 0 | J10: ELANTRA | K10: PC-135R | L10: 14 | M10: {=IF($J10="","",IF(TRIM(INDEX('Part 1'!$CS$3:$EQ$3,1,ROW()-1))=TRIM($J10),INDEX('Part 1'!$CS$386:$EQ$386,1,ROW()-1),"CHECK"))} -> 14 | N10: =IF(OR($J10="",$M10="CHECK",$M10=""),"",$L10-$M10) -> 0 | O10: {=IF($J10="","",IF(TRIM(INDEX('Part 1'!$CS$3:$EQ$3,1,ROW()-1))=TRIM($J10),INDEX('Part 1'!$CS$38:$EQ$38,1,ROW()-1),"CHECK"))} -> 132 | Q10: Honda City | R10: PC-8020 | S10: 500 | T10: {=IF($Q10="","",IF(TRIM(INDEX('Part 1'!$GD$3:$HB$3,1,ROW()-1))=TRIM($Q10),INDEX('Part 1'!$GD$386:$HB$386,1,ROW()-1),"CHECK"))} -> 500 | U10: =IF(OR($Q10="",$T10="CHECK",$T10=""),"",$S10-$T10) -> 0 | V10: {=IF($Q10="","",IF(TRIM(INDEX('Part 1'!$GD$3:$HB$3,1,ROW()-1))=TRIM($Q10),INDEX('Part 1'!$GD$38:$HB$38,1,ROW()-1),"CHECK"))} -> 600 | X10: LANCER BLOWER SWITCH | Y10: PC-926 | Z10: 250 | AA10: {=IF($X10="","",IF(TRIM(INDEX('Part 1'!$FG$3:$GC$3,1,ROW()-1))=TRIM($X10),INDEX('Part 1'!$FG$386:$GC$386,1,ROW()-1),"CHECK"))} -> 250 | AB10: =IF(OR($X10="",$AA10="CHECK",$AA10=""),"",$Z10-$AA10) -> 0 | AC10: {=IF($X10="","",IF(TRIM(INDEX('Part 1'!$FG$3:$GC$3,1,ROW()-1))=TRIM($X10),INDEX('Part 1'!$FG$38:$GC$38,1,ROW()-1),"CHECK"))} -> 500 | AE10: CONCORD-COPPER-BEIGE | AG10: 0 | AH10: {=IF($AE10="","",IF(TRIM(INDEX('Part 1'!$ER$3:$FF$3,1,ROW()-1))=TRIM($AE10),INDEX('Part 1'!$ER$386:$FF$386,1,ROW()-1),"CHECK"))} -> 6 | AI10: =IF(OR($AE10="",$AH10="CHECK",$AH10=""),"",ROUND($AG10-$AH10,2)) -> -6 | AJ10: {=IF($AE10="","",IF(TRIM(INDEX('Part 1'!$ER$3:$FF$3,1,ROW()-1))=TRIM($AE10),INDEX('Part 1'!$ER$38:$FF$38,1,ROW()-1),"CHECK"))} -> 0 | AM10: H.CITY | AN10: PC-7061A | AO10: 0 | AP10: {=IF($AM10="","",IF(TRIM(INDEX('Part 1'!$HC$3:$HT$3,1,ROW()-1))=TRIM($AM10),INDEX('Part 1'!$HC$386:$HT$386,1,ROW()-1),"CHECK"))} -> 0 | AQ10: =IF(OR($AM10="",$AP10="CHECK",$AP10=""),"",ROUND($AO10-$AP10,2)) -> 0 | AR10: {=IF($AM10="","",IF(TRIM(INDEX('Part 1'!$HC$3:$HT$3,1,ROW()-1))=TRIM($AM10),INDEX('Part 1'!$HC$38:$HT$38,1,ROW()-1),"CHECK"))} -> 0 | AT10: 16" 'S' Scorpio | AV10: 71 | AW10: {=IF($AT10="","",IF(TRIM(INDEX('Part 1'!$HU$3:$IC$3,1,ROW()-1))=TRIM($AT10),INDEX('Part 1'!$HU$386:$IC$386,1,ROW()-1),"CHECK"))} -> 71 | AX10: =IF(OR($AT10="",$AW10="CHECK",$AW10=""),"",ROUND($AV10-$AW10,2)) -> 0 | AY10: {=IF($AT10="","",IF(TRIM(INDEX('Part 1'!$HU$3:$IC$3,1,ROW()-1))=TRIM($AT10),INDEX('Part 1'!$HU$38:$IC$38,1,ROW()-1),"CHECK"))} -> 0 | AZ10: 16" 'S' Scorpio | BB10: O-RING | BC10: FK-1012 | BD10: 100 | BE10: {=IF($BB10="","",IF(TRIM(INDEX('Part 1'!$ID$3:$IP$3,1,ROW()-1))=TRIM($BB10),INDEX('Part 1'!$ID$386:$IP$386,1,ROW()-1),"CHECK"))} -> 100 | BF10: =IF(OR($BB10="",$BE10="CHECK",$BE10=""),"",ROUND($BD10-$BE10,2)) -> 0 | BG10: {=IF($BB10="","",IF(TRIM(INDEX('Part 1'!$ID$3:$IP$3,1,ROW()-1))=TRIM($BB10),INDEX('Part 1'!$ID$38:$IP$38,1,ROW()-1),"CHECK"))} -> 600 | BH10: O-RING | BJ10: GETZ | BK10: PC-E422 | BL10: 4 | BM10: {=IF($BJ10="","",IF(TRIM(INDEX('Part 2'!$F$3:$AS$3,1,ROW()-1))=TRIM($BJ10),INDEX('Part 2'!$F$243:$AS$243,1,ROW()-1),"CHECK"))} -> 28 | BN10: =IF(OR($BJ10="",$BM10="CHECK",$BM10=""),"",ROUND($BL10-$BM10,2)) -> -24 | BO10: {=IF($BJ10="","",IF(TRIM(INDEX('Part 2'!$F$3:$AS$3,1,ROW()-1))=TRIM($BJ10),INDEX('Part 2'!$F$33:$AS$33,1,ROW()-1),"CHECK"))} -> 72 | BP10: GETZ | BR10: HCC SANTRO | BS10: BB | BT10: 0 | BU10: =IF(TRIM('Part 2'!$BB$3&" "&'Part 2'!$BB$4)=TRIM($BR10),'Part 2'!$BB$243,"CHECK") -> 0 | BV10: =IF(OR($BR10="",$BU10="CHECK"),"",ROUND($BT10-$BU10,2)) -> 0 | BW10: =IF(TRIM('Part 2'!$BB$3&" "&'Part 2'!$BB$4)=TRIM($BR10),'Part 2'!$BB$33,"CHECK") -> 0 | BY10: PULLEY PULL QUALIS | BZ10: SD-1003B | CA10: 108 | CB10: {=IF($BY10="","",IF(TRIM(INDEX('Part 2'!$BJ$3:$CZ$3,1,ROW()-1))=TRIM($BZ10),INDEX('Part 2'!$BJ$243:$CZ$243,1,ROW()-1),"CHECK"))} -> 108 | CC10: =IF(OR($BY10="",$CB10="CHECK"),"",ROUND($CA10-$CB10,2)) -> 0 | CD10: {=IF($BY10="","",IF(TRIM(INDEX('Part 2'!$BJ$3:$CZ$3,1,ROW()-1))=TRIM($BZ10),INDEX('Part 2'!$BJ$33:$CZ$33,1,ROW()-1),"CHECK"))} -> 108
A11: COROLLA | B11: PC-86110 | C11: 85 | D11: {=IF($A11="","",IF(TRIM(INDEX('Part 1'!$F$3:$CZ$3,1,ROW()-1))=TRIM($A11),INDEX('Part 1'!$F$386:$CZ$386,1,ROW()-1),"CHECK"))} -> 85 | E11: =IF(OR($A11="",$D11="CHECK",$D11=""),"",$C11-$D11) -> 0 | F11: {=IF($A11="","",IF(TRIM(INDEX('Part 1'!$F$3:$CZ$3,1,ROW()-1))=TRIM($A11),INDEX('Part 1'!$F$38:$CZ$38,1,ROW()-1),"CHECK"))} -> 75 | J11: Esteem R-12 | K11: PC-036R12 | L11: 96 | M11: {=IF($J11="","",IF(TRIM(INDEX('Part 1'!$CS$3:$EQ$3,1,ROW()-1))=TRIM($J11),INDEX('Part 1'!$CS$386:$EQ$386,1,ROW()-1),"CHECK"))} -> 96 | N11: =IF(OR($J11="",$M11="CHECK",$M11=""),"",$L11-$M11) -> 0 | O11: {=IF($J11="","",IF(TRIM(INDEX('Part 1'!$CS$3:$EQ$3,1,ROW()-1))=TRIM($J11),INDEX('Part 1'!$CS$38:$EQ$38,1,ROW()-1),"CHECK"))} -> 96 | Q11: Indica Behr | R11: PC-8115 | S11: 100 | T11: {=IF($Q11="","",IF(TRIM(INDEX('Part 1'!$GD$3:$HB$3,1,ROW()-1))=TRIM($Q11),INDEX('Part 1'!$GD$386:$HB$386,1,ROW()-1),"CHECK"))} -> 100 | U11: =IF(OR($Q11="",$T11="CHECK",$T11=""),"",$S11-$T11) -> 0 | V11: {=IF($Q11="","",IF(TRIM(INDEX('Part 1'!$GD$3:$HB$3,1,ROW()-1))=TRIM($Q11),INDEX('Part 1'!$GD$38:$HB$38,1,ROW()-1),"CHECK"))} -> 0 | X11: LENCER | Y11: PC-1044A & 1042A | Z11: 0 | AA11: {=IF($X11="","",IF(TRIM(INDEX('Part 1'!$FG$3:$GC$3,1,ROW()-1))=TRIM($X11),INDEX('Part 1'!$FG$386:$GC$386,1,ROW()-1),"CHECK"))} -> 0 | AB11: =IF(OR($X11="",$AA11="CHECK",$AA11=""),"",$Z11-$AA11) -> 0 | AC11: {=IF($X11="","",IF(TRIM(INDEX('Part 1'!$FG$3:$GC$3,1,ROW()-1))=TRIM($X11),INDEX('Part 1'!$FG$38:$GC$38,1,ROW()-1),"CHECK"))} -> 300 | AE11: Concord-Normal | AG11: 0 | AH11: {=IF($AE11="","",IF(TRIM(INDEX('Part 1'!$ER$3:$FF$3,1,ROW()-1))=TRIM($AE11),INDEX('Part 1'!$ER$386:$FF$386,1,ROW()-1),"CHECK"))} -> 0 | AI11: =IF(OR($AE11="",$AH11="CHECK",$AH11=""),"",ROUND($AG11-$AH11,2)) -> 0 | AJ11: {=IF($AE11="","",IF(TRIM(INDEX('Part 1'!$ER$3:$FF$3,1,ROW()-1))=TRIM($AE11),INDEX('Part 1'!$ER$38:$FF$38,1,ROW()-1),"CHECK"))} -> 0 | AM11: ND | AN11: PC-7031A | AO11: 1912 | AP11: {=IF($AM11="","",IF(TRIM(INDEX('Part 1'!$HC$3:$HT$3,1,ROW()-1))=TRIM($AM11),INDEX('Part 1'!$HC$386:$HT$386,1,ROW()-1),"CHECK"))} -> 1912 | AQ11: =IF(OR($AM11="",$AP11="CHECK",$AP11=""),"",ROUND($AO11-$AP11,2)) -> 0 | AR11: {=IF($AM11="","",IF(TRIM(INDEX('Part 1'!$HC$3:$HT$3,1,ROW()-1))=TRIM($AM11),INDEX('Part 1'!$HC$38:$HT$38,1,ROW()-1),"CHECK"))} -> 3000 | BB11: QUALIS | BC11: FK-1015 | BD11: 200 | BE11: {=IF($BB11="","",IF(TRIM(INDEX('Part 1'!$ID$3:$IP$3,1,ROW()-1))=TRIM($BB11),INDEX('Part 1'!$ID$386:$IP$386,1,ROW()-1),"CHECK"))} -> 200 | BF11: =IF(OR($BB11="",$BE11="CHECK",$BE11=""),"",ROUND($BD11-$BE11,2)) -> 0 | BG11: {=IF($BB11="","",IF(TRIM(INDEX('Part 1'!$ID$3:$IP$3,1,ROW()-1))=TRIM($BB11),INDEX('Part 1'!$ID$38:$IP$38,1,ROW()-1),"CHECK"))} -> 200 | BH11: QUALIS | BJ11: HONDA ACCORD | BK11: PC-E510 | BL11: 109 | BM11: {=IF($BJ11="","",IF(TRIM(INDEX('Part 2'!$F$3:$AS$3,1,ROW()-1))=TRIM($BJ11),INDEX('Part 2'!$F$243:$AS$243,1,ROW()-1),"CHECK"))} -> 109 | BN11: =IF(OR($BJ11="",$BM11="CHECK",$BM11=""),"",ROUND($BL11-$BM11,2)) -> 0 | BO11: {=IF($BJ11="","",IF(TRIM(INDEX('Part 2'!$F$3:$AS$3,1,ROW()-1))=TRIM($BJ11),INDEX('Part 2'!$F$33:$AS$33,1,ROW()-1),"CHECK"))} -> 110 | BP11: HONDA ACCORD | BR11: HCC SONATA | BS11: BC | BT11: 0 | BU11: =IF(TRIM('Part 2'!$BC$3&" "&'Part 2'!$BC$4)=TRIM($BR11),'Part 2'!$BC$243,"CHECK") -> 0 | BV11: =IF(OR($BR11="",$BU11="CHECK"),"",ROUND($BT11-$BU11,2)) -> 0 | BW11: =IF(TRIM('Part 2'!$BC$3&" "&'Part 2'!$BC$4)=TRIM($BR11),'Part 2'!$BC$33,"CHECK") -> 0 | BY11: PLATE HUB HS-11 | BZ11: SD-1004 | CA11: 120 | CB11: {=IF($BY11="","",IF(TRIM(INDEX('Part 2'!$BJ$3:$CZ$3,1,ROW()-1))=TRIM($BZ11),INDEX('Part 2'!$BJ$243:$CZ$243,1,ROW()-1),"CHECK"))} -> 120 | CC11: =IF(OR($BY11="",$CB11="CHECK"),"",ROUND($CA11-$CB11,2)) -> 0 | CD11: {=IF($BY11="","",IF(TRIM(INDEX('Part 2'!$BJ$3:$CZ$3,1,ROW()-1))=TRIM($BZ11),INDEX('Part 2'!$BJ$33:$CZ$33,1,ROW()-1),"CHECK"))} -> 120
A12: DÉCOR | B12: PC-86273 | C12: 50 | D12: {=IF($A12="","",IF(TRIM(INDEX('Part 1'!$F$3:$CZ$3,1,ROW()-1))=TRIM($A12),INDEX('Part 1'!$F$386:$CZ$386,1,ROW()-1),"CHECK"))} -> 50 | E12: =IF(OR($A12="",$D12="CHECK",$D12=""),"",$C12-$D12) -> 0 | F12: {=IF($A12="","",IF(TRIM(INDEX('Part 1'!$F$3:$CZ$3,1,ROW()-1))=TRIM($A12),INDEX('Part 1'!$F$38:$CZ$38,1,ROW()-1),"CHECK"))} -> 50 | J12: Esteem R-134a | K12: PC-036R-134 | L12: 138 | M12: {=IF($J12="","",IF(TRIM(INDEX('Part 1'!$CS$3:$EQ$3,1,ROW()-1))=TRIM($J12),INDEX('Part 1'!$CS$386:$EQ$386,1,ROW()-1),"CHECK"))} -> 138 | N12: =IF(OR($J12="",$M12="CHECK",$M12=""),"",$L12-$M12) -> 0 | O12: {=IF($J12="","",IF(TRIM(INDEX('Part 1'!$CS$3:$EQ$3,1,ROW()-1))=TRIM($J12),INDEX('Part 1'!$CS$38:$EQ$38,1,ROW()-1),"CHECK"))} -> 138 | Q12: Lancer | R12: PC-8017 | S12: 300 | T12: {=IF($Q12="","",IF(TRIM(INDEX('Part 1'!$GD$3:$HB$3,1,ROW()-1))=TRIM($Q12),INDEX('Part 1'!$GD$386:$HB$386,1,ROW()-1),"CHECK"))} -> 300 | U12: =IF(OR($Q12="",$T12="CHECK",$T12=""),"",$S12-$T12) -> 0 | V12: {=IF($Q12="","",IF(TRIM(INDEX('Part 1'!$GD$3:$HB$3,1,ROW()-1))=TRIM($Q12),INDEX('Part 1'!$GD$38:$HB$38,1,ROW()-1),"CHECK"))} -> 500 | X12: OPEL-BIG | Y12: PC-1091 | Z12: 25 | AA12: {=IF($X12="","",IF(TRIM(INDEX('Part 1'!$FG$3:$GC$3,1,ROW()-1))=TRIM($X12),INDEX('Part 1'!$FG$386:$GC$386,1,ROW()-1),"CHECK"))} -> 25 | AB12: =IF(OR($X12="",$AA12="CHECK",$AA12=""),"",$Z12-$AA12) -> 0 | AC12: {=IF($X12="","",IF(TRIM(INDEX('Part 1'!$FG$3:$GC$3,1,ROW()-1))=TRIM($X12),INDEX('Part 1'!$FG$38:$GC$38,1,ROW()-1),"CHECK"))} -> 100 | AE12: 405 | AG12: 50 | AH12: {=IF($AE12="","",IF(TRIM(INDEX('Part 1'!$ER$3:$FF$3,1,ROW()-1))=TRIM($AE12),INDEX('Part 1'!$ER$386:$FF$386,1,ROW()-1),"CHECK"))} -> 50 | AI12: =IF(OR($AE12="",$AH12="CHECK",$AH12=""),"",ROUND($AG12-$AH12,2)) -> 0 | AJ12: {=IF($AE12="","",IF(TRIM(INDEX('Part 1'!$ER$3:$FF$3,1,ROW()-1))=TRIM($AE12),INDEX('Part 1'!$ER$38:$FF$38,1,ROW()-1),"CHECK"))} -> 50 | AK12: 405 | AM12: OPEL ASTRA | AN12: PC-7210 | AO12: 100 | AP12: {=IF($AM12="","",IF(TRIM(INDEX('Part 1'!$HC$3:$HT$3,1,ROW()-1))=TRIM($AM12),INDEX('Part 1'!$HC$386:$HT$386,1,ROW()-1),"CHECK"))} -> 100 | AQ12: =IF(OR($AM12="",$AP12="CHECK",$AP12=""),"",ROUND($AO12-$AP12,2)) -> 0 | AR12: {=IF($AM12="","",IF(TRIM(INDEX('Part 1'!$HC$3:$HT$3,1,ROW()-1))=TRIM($AM12),INDEX('Part 1'!$HC$38:$HT$38,1,ROW()-1),"CHECK"))} -> 400 | BB12: INNOVA / WR | BC12: FK-1082B | BD12: 0 | BE12: {=IF($BB12="","",IF(TRIM(INDEX('Part 1'!$ID$3:$IP$3,1,ROW()-1))=TRIM($BB12),INDEX('Part 1'!$ID$386:$IP$386,1,ROW()-1),"CHECK"))} -> 0 | BF12: =IF(OR($BB12="",$BE12="CHECK",$BE12=""),"",ROUND($BD12-$BE12,2)) -> 0 | BG12: {=IF($BB12="","",IF(TRIM(INDEX('Part 1'!$ID$3:$IP$3,1,ROW()-1))=TRIM($BB12),INDEX('Part 1'!$ID$38:$IP$38,1,ROW()-1),"CHECK"))} -> 200 | BH12: INNOVA / WR | BJ12: HONDA CIVIC | BK12: PC-E523 | BL12: 394 | BM12: {=IF($BJ12="","",IF(TRIM(INDEX('Part 2'!$F$3:$AS$3,1,ROW()-1))=TRIM($BJ12),INDEX('Part 2'!$F$243:$AS$243,1,ROW()-1),"CHECK"))} -> 410 | BN12: =IF(OR($BJ12="",$BM12="CHECK",$BM12=""),"",ROUND($BL12-$BM12,2)) -> -16 | BO12: {=IF($BJ12="","",IF(TRIM(INDEX('Part 2'!$F$3:$AS$3,1,ROW()-1))=TRIM($BJ12),INDEX('Part 2'!$F$33:$AS$33,1,ROW()-1),"CHECK"))} -> 435 | BP12: HONDA CIVIC | BR12: HCC ELANTRA-2006 | BS12: BD | BT12: 0 | BU12: =IF(TRIM('Part 2'!$BD$3&" "&'Part 2'!$BD$4)=TRIM($BR12),'Part 2'!$BD$243,"CHECK") -> 0 | BV12: =IF(OR($BR12="",$BU12="CHECK"),"",ROUND($BT12-$BU12,2)) -> 0 | BW12: =IF(TRIM('Part 2'!$BD$3&" "&'Part 2'!$BD$4)=TRIM($BR12),'Part 2'!$BD$33,"CHECK") -> 0 | BY12: MAGNATIC COIL HS-11 | BZ12: SD-1004A | CA12: 150 | CB12: {=IF($BY12="","",IF(TRIM(INDEX('Part 2'!$BJ$3:$CZ$3,1,ROW()-1))=TRIM($BZ12),INDEX('Part 2'!$BJ$243:$CZ$243,1,ROW()-1),"CHECK"))} -> 150 | CC12: =IF(OR($BY12="",$CB12="CHECK"),"",ROUND($CA12-$CB12,2)) -> 0 | CD12: {=IF($BY12="","",IF(TRIM(INDEX('Part 2'!$BJ$3:$CZ$3,1,ROW()-1))=TRIM($BZ12),INDEX('Part 2'!$BJ$33:$CZ$33,1,ROW()-1),"CHECK"))} -> 150
A13: ELANTRA | B13: PC-86066 | C13: 50 | D13: {=IF($A13="","",IF(TRIM(INDEX('Part 1'!$F$3:$CZ$3,1,ROW()-1))=TRIM($A13),INDEX('Part 1'!$F$386:$CZ$386,1,ROW()-1),"CHECK"))} -> 45 | E13: =IF(OR($A13="",$D13="CHECK",$D13=""),"",$C13-$D13) -> 5 | F13: {=IF($A13="","",IF(TRIM(INDEX('Part 1'!$F$3:$CZ$3,1,ROW()-1))=TRIM($A13),INDEX('Part 1'!$F$38:$CZ$38,1,ROW()-1),"CHECK"))} -> 100 | J13: ESTILO | K13: PC-408 | L13: 0 | M13: {=IF($J13="","",IF(TRIM(INDEX('Part 1'!$CS$3:$EQ$3,1,ROW()-1))=TRIM($J13),INDEX('Part 1'!$CS$386:$EQ$386,1,ROW()-1),"CHECK"))} -> 0 | N13: =IF(OR($J13="",$M13="CHECK",$M13=""),"",$L13-$M13) -> 0 | O13: {=IF($J13="","",IF(TRIM(INDEX('Part 1'!$CS$3:$EQ$3,1,ROW()-1))=TRIM($J13),INDEX('Part 1'!$CS$38:$EQ$38,1,ROW()-1),"CHECK"))} -> 0 | Q13: Maruti 'F'Ring | R13: PC-8047 | S13: 275 | T13: {=IF($Q13="","",IF(TRIM(INDEX('Part 1'!$GD$3:$HB$3,1,ROW()-1))=TRIM($Q13),INDEX('Part 1'!$GD$386:$HB$386,1,ROW()-1),"CHECK"))} -> 275 | U13: =IF(OR($Q13="",$T13="CHECK",$T13=""),"",$S13-$T13) -> 0 | V13: {=IF($Q13="","",IF(TRIM(INDEX('Part 1'!$GD$3:$HB$3,1,ROW()-1))=TRIM($Q13),INDEX('Part 1'!$GD$38:$HB$38,1,ROW()-1),"CHECK"))} -> 500 | X13: OPEL-SMALL-2pin | Y13: PC-1087 | Z13: 0 | AA13: {=IF($X13="","",IF(TRIM(INDEX('Part 1'!$FG$3:$GC$3,1,ROW()-1))=TRIM($X13),INDEX('Part 1'!$FG$386:$GC$386,1,ROW()-1),"CHECK"))} -> 0 | AB13: =IF(OR($X13="",$AA13="CHECK",$AA13=""),"",$Z13-$AA13) -> 0 | AC13: {=IF($X13="","",IF(TRIM(INDEX('Part 1'!$FG$3:$GC$3,1,ROW()-1))=TRIM($X13),INDEX('Part 1'!$FG$38:$GC$38,1,ROW()-1),"CHECK"))} -> 300 | AE13: 404 | AG13: 987.9999 | AH13: {=IF($AE13="","",IF(TRIM(INDEX('Part 1'!$ER$3:$FF$3,1,ROW()-1))=TRIM($AE13),INDEX('Part 1'!$ER$386:$FF$386,1,ROW()-1),"CHECK"))} -> 1000 | AI13: =IF(OR($AE13="",$AH13="CHECK",$AH13=""),"",ROUND($AG13-$AH13,2)) -> -12 | AJ13: {=IF($AE13="","",IF(TRIM(INDEX('Part 1'!$ER$3:$FF$3,1,ROW()-1))=TRIM($AE13),INDEX('Part 1'!$ER$38:$FF$38,1,ROW()-1),"CHECK"))} -> 1000 | AK13: 404 | AM13: O-RINGS | AN13: PC-7085A | AO13: 1700 | AP13: {=IF($AM13="","",IF(TRIM(INDEX('Part 1'!$HC$3:$HT$3,1,ROW()-1))=TRIM($AM13),INDEX('Part 1'!$HC$386:$HT$386,1,ROW()-1),"CHECK"))} -> 1700 | AQ13: =IF(OR($AM13="",$AP13="CHECK",$AP13=""),"",ROUND($AO13-$AP13,2)) -> 0 | AR13: {=IF($AM13="","",IF(TRIM(INDEX('Part 1'!$HC$3:$HT$3,1,ROW()-1))=TRIM($AM13),INDEX('Part 1'!$HC$38:$HT$38,1,ROW()-1),"CHECK"))} -> 3000 | BB13: ORIFICE TUBE | BC13: oringe-PC-8006 | BD13: 250 | BE13: {=IF($BB13="","",IF(TRIM(INDEX('Part 1'!$ID$3:$IP$3,1,ROW()-1))=TRIM($BB13),INDEX('Part 1'!$ID$386:$IP$386,1,ROW()-1),"CHECK"))} -> 250 | BF13: =IF(OR($BB13="",$BE13="CHECK",$BE13=""),"",ROUND($BD13-$BE13,2)) -> 0 | BG13: {=IF($BB13="","",IF(TRIM(INDEX('Part 1'!$ID$3:$IP$3,1,ROW()-1))=TRIM($BB13),INDEX('Part 1'!$ID$38:$IP$38,1,ROW()-1),"CHECK"))} -> 0 | BH13: ORIFICE TUBE (ORANGE) | BJ13: CRV | BK13: PC-E509 | BL13: 0 | BM13: {=IF($BJ13="","",IF(TRIM(INDEX('Part 2'!$F$3:$AS$3,1,ROW()-1))=TRIM($BJ13),INDEX('Part 2'!$F$243:$AS$243,1,ROW()-1),"CHECK"))} -> 24 | BN13: =IF(OR($BJ13="",$BM13="CHECK",$BM13=""),"",ROUND($BL13-$BM13,2)) -> -24 | BO13: {=IF($BJ13="","",IF(TRIM(INDEX('Part 2'!$F$3:$AS$3,1,ROW()-1))=TRIM($BJ13),INDEX('Part 2'!$F$33:$AS$33,1,ROW()-1),"CHECK"))} -> 0 | BP13: CRV | BR13: HCC ELANTRA-2000 | BS13: BE | BT13: 0 | BU13: =IF(TRIM('Part 2'!$BE$3&" "&'Part 2'!$BE$4)=TRIM($BR13),'Part 2'!$BE$243,"CHECK") -> 0 | BV13: =IF(OR($BR13="",$BU13="CHECK"),"",ROUND($BT13-$BU13,2)) -> 0 | BW13: =IF(TRIM('Part 2'!$BE$3&" "&'Part 2'!$BE$4)=TRIM($BR13),'Part 2'!$BE$33,"CHECK") -> 0 | BY13: PULLEY PULL HS-11 | BZ13: SD-1004B | CA13: 108 | CB13: {=IF($BY13="","",IF(TRIM(INDEX('Part 2'!$BJ$3:$CZ$3,1,ROW()-1))=TRIM($BZ13),INDEX('Part 2'!$BJ$243:$CZ$243,1,ROW()-1),"CHECK"))} -> 108 | CC13: =IF(OR($BY13="",$CB13="CHECK"),"",ROUND($CA13-$CB13,2)) -> 0 | CD13: {=IF($BY13="","",IF(TRIM(INDEX('Part 2'!$BJ$3:$CZ$3,1,ROW()-1))=TRIM($BZ13),INDEX('Part 2'!$BJ$33:$CZ$33,1,ROW()-1),"CHECK"))} -> 108
A14: ENDEAVOUR | B14: PC-86277 | C14: 50 | D14: {=IF($A14="","",IF(TRIM(INDEX('Part 1'!$F$3:$CZ$3,1,ROW()-1))=TRIM($A14),INDEX('Part 1'!$F$386:$CZ$386,1,ROW()-1),"CHECK"))} -> 50 | E14: =IF(OR($A14="",$D14="CHECK",$D14=""),"",$C14-$D14) -> 0 | F14: {=IF($A14="","",IF(TRIM(INDEX('Part 1'!$F$3:$CZ$3,1,ROW()-1))=TRIM($A14),INDEX('Part 1'!$F$38:$CZ$38,1,ROW()-1),"CHECK"))} -> 50 | J14: FIESTA | K14: PC-205 | L14: 360 | M14: {=IF($J14="","",IF(TRIM(INDEX('Part 1'!$CS$3:$EQ$3,1,ROW()-1))=TRIM($J14),INDEX('Part 1'!$CS$386:$EQ$386,1,ROW()-1),"CHECK"))} -> 360 | N14: =IF(OR($J14="",$M14="CHECK",$M14=""),"",$L14-$M14) -> 0 | O14: {=IF($J14="","",IF(TRIM(INDEX('Part 1'!$CS$3:$EQ$3,1,ROW()-1))=TRIM($J14),INDEX('Part 1'!$CS$38:$EQ$38,1,ROW()-1),"CHECK"))} -> 366 | Q14: Maruti 'O'Ring | R14: PC-8051 | S14: 1000 | T14: {=IF($Q14="","",IF(TRIM(INDEX('Part 1'!$GD$3:$HB$3,1,ROW()-1))=TRIM($Q14),INDEX('Part 1'!$GD$386:$HB$386,1,ROW()-1),"CHECK"))} -> 1000 | U14: =IF(OR($Q14="",$T14="CHECK",$T14=""),"",$S14-$T14) -> 0 | V14: {=IF($Q14="","",IF(TRIM(INDEX('Part 1'!$GD$3:$HB$3,1,ROW()-1))=TRIM($Q14),INDEX('Part 1'!$GD$38:$HB$38,1,ROW()-1),"CHECK"))} -> 1000 | X14: PALIO | Y14: PC-1100 | Z14: 150 | AA14: {=IF($X14="","",IF(TRIM(INDEX('Part 1'!$FG$3:$GC$3,1,ROW()-1))=TRIM($X14),INDEX('Part 1'!$FG$386:$GC$386,1,ROW()-1),"CHECK"))} -> 50 | AB14: =IF(OR($X14="",$AA14="CHECK",$AA14=""),"",$Z14-$AA14) -> 100 | AC14: {=IF($X14="","",IF(TRIM(INDEX('Part 1'!$FG$3:$GC$3,1,ROW()-1))=TRIM($X14),INDEX('Part 1'!$FG$38:$GC$38,1,ROW()-1),"CHECK"))} -> 200 | AE14: CONCORD WHEEL | AG14: 358 | AH14: {=IF($AE14="","",IF(TRIM(INDEX('Part 1'!$ER$3:$FF$3,1,ROW()-1))=TRIM($AE14),INDEX('Part 1'!$ER$386:$FF$386,1,ROW()-1),"CHECK"))} -> 358 | AI14: =IF(OR($AE14="",$AH14="CHECK",$AH14=""),"",ROUND($AG14-$AH14,2)) -> 0 | AJ14: {=IF($AE14="","",IF(TRIM(INDEX('Part 1'!$ER$3:$FF$3,1,ROW()-1))=TRIM($AE14),INDEX('Part 1'!$ER$38:$FF$38,1,ROW()-1),"CHECK"))} -> 300 | AK14: CONCORD WHEEL | AM14: Santro Large-matiz/ZEN DELPHI | AN14: PC-7058A | AO14: 150 | AP14: {=IF($AM14="","",IF(TRIM(INDEX('Part 1'!$HC$3:$HT$3,1,ROW()-1))=TRIM($AM14),INDEX('Part 1'!$HC$386:$HT$386,1,ROW()-1),"CHECK"))} -> 150 | AQ14: =IF(OR($AM14="",$AP14="CHECK",$AP14=""),"",ROUND($AO14-$AP14,2)) -> 0 | AR14: {=IF($AM14="","",IF(TRIM(INDEX('Part 1'!$HC$3:$HT$3,1,ROW()-1))=TRIM($AM14),INDEX('Part 1'!$HC$38:$HT$38,1,ROW()-1),"CHECK"))} -> 3000 | BB14: ORIFICE TUBE | BC14: white - PC-8002 | BD14: 0 | BE14: {=IF($BB14="","",IF(TRIM(INDEX('Part 1'!$ID$3:$IP$3,1,ROW()-1))=TRIM($BB14),INDEX('Part 1'!$ID$386:$IP$386,1,ROW()-1),"CHECK"))} -> 0 | BF14: =IF(OR($BB14="",$BE14="CHECK",$BE14=""),"",ROUND($BD14-$BE14,2)) -> 0 | BG14: {=IF($BB14="","",IF(TRIM(INDEX('Part 1'!$ID$3:$IP$3,1,ROW()-1))=TRIM($BB14),INDEX('Part 1'!$ID$38:$IP$38,1,ROW()-1),"CHECK"))} -> 0 | BH14: ORIFICE TUBE (WHITE) | BJ14: IKON | BK14: PC-E022 | BL14: 375 | BM14: {=IF($BJ14="","",IF(TRIM(INDEX('Part 2'!$F$3:$AS$3,1,ROW()-1))=TRIM($BJ14),INDEX('Part 2'!$F$243:$AS$243,1,ROW()-1),"CHECK"))} -> 375 | BN14: =IF(OR($BJ14="",$BM14="CHECK",$BM14=""),"",ROUND($BL14-$BM14,2)) -> 0 | BO14: {=IF($BJ14="","",IF(TRIM(INDEX('Part 2'!$F$3:$AS$3,1,ROW()-1))=TRIM($BJ14),INDEX('Part 2'!$F$33:$AS$33,1,ROW()-1),"CHECK"))} -> 465 | BP14: IKON | BR14: HOSE 8MM-LID | BS14: BF | BT14: 133 | BU14: =IF(TRIM('Part 2'!$BF$3&" "&'Part 2'!$BF$4)=TRIM($BR14),'Part 2'!$BF$243,"CHECK") -> 145 | BV14: =IF(OR($BR14="",$BU14="CHECK"),"",ROUND($BT14-$BU14,2)) -> -12 | BW14: =IF(TRIM('Part 2'!$BF$3&" "&'Part 2'!$BF$4)=TRIM($BR14),'Part 2'!$BF$33,"CHECK") -> 165 | BY14: MAGNETIC COIL MC-A HS-XING | BZ14: SD-1004C | CA14: 150 | CB14: {=IF($BY14="","",IF(TRIM(INDEX('Part 2'!$BJ$3:$CZ$3,1,ROW()-1))=TRIM($BZ14),INDEX('Part 2'!$BJ$243:$CZ$243,1,ROW()-1),"CHECK"))} -> 150 | CC14: =IF(OR($BY14="",$CB14="CHECK"),"",ROUND($CA14-$CB14,2)) -> 0 | CD14: {=IF($BY14="","",IF(TRIM(INDEX('Part 2'!$BJ$3:$CZ$3,1,ROW()-1))=TRIM($BZ14),INDEX('Part 2'!$BJ$33:$CZ$33,1,ROW()-1),"CHECK"))} -> 150
A15: Esteem-134a | B15: PC-86090 | C15: 300 | D15: {=IF($A15="","",IF(TRIM(INDEX('Part 1'!$F$3:$CZ$3,1,ROW()-1))=TRIM($A15),INDEX('Part 1'!$F$386:$CZ$386,1,ROW()-1),"CHECK"))} -> 300 | E15: =IF(OR($A15="",$D15="CHECK",$D15=""),"",$C15-$D15) -> 0 | F15: {=IF($A15="","",IF(TRIM(INDEX('Part 1'!$F$3:$CZ$3,1,ROW()-1))=TRIM($A15),INDEX('Part 1'!$F$38:$CZ$38,1,ROW()-1),"CHECK"))} -> 300 | J15: FORD IKON | K15: PC-053 | L15: 96 | M15: {=IF($J15="","",IF(TRIM(INDEX('Part 1'!$CS$3:$EQ$3,1,ROW()-1))=TRIM($J15),INDEX('Part 1'!$CS$386:$EQ$386,1,ROW()-1),"CHECK"))} -> 96 | N15: =IF(OR($J15="",$M15="CHECK",$M15=""),"",$L15-$M15) -> 0 | O15: {=IF($J15="","",IF(TRIM(INDEX('Part 1'!$CS$3:$EQ$3,1,ROW()-1))=TRIM($J15),INDEX('Part 1'!$CS$38:$EQ$38,1,ROW()-1),"CHECK"))} -> 150 | Q15: Matiz-NEW | R15: PC-8096 | S15: 0 | T15: {=IF($Q15="","",IF(TRIM(INDEX('Part 1'!$GD$3:$HB$3,1,ROW()-1))=TRIM($Q15),INDEX('Part 1'!$GD$386:$HB$386,1,ROW()-1),"CHECK"))} -> 0 | U15: =IF(OR($Q15="",$T15="CHECK",$T15=""),"",$S15-$T15) -> 0 | V15: {=IF($Q15="","",IF(TRIM(INDEX('Part 1'!$GD$3:$HB$3,1,ROW()-1))=TRIM($Q15),INDEX('Part 1'!$GD$38:$HB$38,1,ROW()-1),"CHECK"))} -> 0 | X15: SANTRO | Y15: PC-1054B | Z15: 498 | AA15: {=IF($X15="","",IF(TRIM(INDEX('Part 1'!$FG$3:$GC$3,1,ROW()-1))=TRIM($X15),INDEX('Part 1'!$FG$386:$GC$386,1,ROW()-1),"CHECK"))} -> 500 | AB15: =IF(OR($X15="",$AA15="CHECK",$AA15=""),"",$Z15-$AA15) -> -2 | AC15: {=IF($X15="","",IF(TRIM(INDEX('Part 1'!$FG$3:$GC$3,1,ROW()-1))=TRIM($X15),INDEX('Part 1'!$FG$38:$GC$38,1,ROW()-1),"CHECK"))} -> 500 | AE15: CONCORD MOTOR | AG15: 260 | AH15: {=IF($AE15="","",IF(TRIM(INDEX('Part 1'!$ER$3:$FF$3,1,ROW()-1))=TRIM($AE15),INDEX('Part 1'!$ER$386:$FF$386,1,ROW()-1),"CHECK"))} -> 260 | AI15: =IF(OR($AE15="",$AH15="CHECK",$AH15=""),"",ROUND($AG15-$AH15,2)) -> 0 | AJ15: {=IF($AE15="","",IF(TRIM(INDEX('Part 1'!$ER$3:$FF$3,1,ROW()-1))=TRIM($AE15),INDEX('Part 1'!$ER$38:$FF$38,1,ROW()-1),"CHECK"))} -> 250 | AK15: CONCORD MOTOR | AM15: SANTRO SMALL | AN15: PC-7217 | AO15: 100 | AP15: {=IF($AM15="","",IF(TRIM(INDEX('Part 1'!$HC$3:$HT$3,1,ROW()-1))=TRIM($AM15),INDEX('Part 1'!$HC$386:$HT$386,1,ROW()-1),"CHECK"))} -> 100 | AQ15: =IF(OR($AM15="",$AP15="CHECK",$AP15=""),"",ROUND($AO15-$AP15,2)) -> 0 | AR15: {=IF($AM15="","",IF(TRIM(INDEX('Part 1'!$HC$3:$HT$3,1,ROW()-1))=TRIM($AM15),INDEX('Part 1'!$HC$38:$HT$38,1,ROW()-1),"CHECK"))} -> 2000 | BJ15: I-20 | BK15: PC-E434 | BL15: 0 | BM15: {=IF($BJ15="","",IF(TRIM(INDEX('Part 2'!$F$3:$AS$3,1,ROW()-1))=TRIM($BJ15),INDEX('Part 2'!$F$243:$AS$243,1,ROW()-1),"CHECK"))} -> 0 | BN15: =IF(OR($BJ15="",$BM15="CHECK",$BM15=""),"",ROUND($BL15-$BM15,2)) -> 0 | BO15: {=IF($BJ15="","",IF(TRIM(INDEX('Part 2'!$F$3:$AS$3,1,ROW()-1))=TRIM($BJ15),INDEX('Part 2'!$F$33:$AS$33,1,ROW()-1),"CHECK"))} -> 54 | BP15: I-20 | BR15: 11MM-DIS | BS15: BG | BT15: 818 | BU15: =IF(TRIM('Part 2'!$BG$3&" "&'Part 2'!$BG$4)=TRIM($BR15),'Part 2'!$BG$243,"CHECK") -> 863 | BV15: =IF(OR($BR15="",$BU15="CHECK"),"",ROUND($BT15-$BU15,2)) -> -45 | BW15: =IF(TRIM('Part 2'!$BG$3&" "&'Part 2'!$BG$4)=TRIM($BR15),'Part 2'!$BG$33,"CHECK") -> 1077 | BY15: MAGNETIC COIL SANTRO (SP10) | BZ15: SD-1004D | CA15: 150 | CB15: {=IF($BY15="","",IF(TRIM(INDEX('Part 2'!$BJ$3:$CZ$3,1,ROW()-1))=TRIM($BZ15),INDEX('Part 2'!$BJ$243:$CZ$243,1,ROW()-1),"CHECK"))} -> 150 | CC15: =IF(OR($BY15="",$CB15="CHECK"),"",ROUND($CA15-$CB15,2)) -> 0 | CD15: {=IF($BY15="","",IF(TRIM(INDEX('Part 2'!$BJ$3:$CZ$3,1,ROW()-1))=TRIM($BZ15),INDEX('Part 2'!$BJ$33:$CZ$33,1,ROW()-1),"CHECK"))} -> 150
A16: ESTEEM-R12 | B16: PC-86040 | C16: 155 | D16: {=IF($A16="","",IF(TRIM(INDEX('Part 1'!$F$3:$CZ$3,1,ROW()-1))=TRIM($A16),INDEX('Part 1'!$F$386:$CZ$386,1,ROW()-1),"CHECK"))} -> 155 | E16: =IF(OR($A16="",$D16="CHECK",$D16=""),"",$C16-$D16) -> 0 | F16: {=IF($A16="","",IF(TRIM(INDEX('Part 1'!$F$3:$CZ$3,1,ROW()-1))=TRIM($A16),INDEX('Part 1'!$F$38:$CZ$38,1,ROW()-1),"CHECK"))} -> 250 | J16: Getz | K16: PC-024R | L16: 60 | M16: {=IF($J16="","",IF(TRIM(INDEX('Part 1'!$CS$3:$EQ$3,1,ROW()-1))=TRIM($J16),INDEX('Part 1'!$CS$386:$EQ$386,1,ROW()-1),"CHECK"))} -> 54 | N16: =IF(OR($J16="",$M16="CHECK",$M16=""),"",$L16-$M16) -> 6 | O16: {=IF($J16="","",IF(TRIM(INDEX('Part 1'!$CS$3:$EQ$3,1,ROW()-1))=TRIM($J16),INDEX('Part 1'!$CS$38:$EQ$38,1,ROW()-1),"CHECK"))} -> 106 | Q16: Opel | R16: PC-6142 | S16: 62 | T16: {=IF($Q16="","",IF(TRIM(INDEX('Part 1'!$GD$3:$HB$3,1,ROW()-1))=TRIM($Q16),INDEX('Part 1'!$GD$386:$HB$386,1,ROW()-1),"CHECK"))} -> 62 | U16: =IF(OR($Q16="",$T16="CHECK",$T16=""),"",$S16-$T16) -> 0 | V16: {=IF($Q16="","",IF(TRIM(INDEX('Part 1'!$GD$3:$HB$3,1,ROW()-1))=TRIM($Q16),INDEX('Part 1'!$GD$38:$HB$38,1,ROW()-1),"CHECK"))} -> 100 | X16: Santro-3 Speed | Z16: 1136 | AA16: {=IF($X16="","",IF(TRIM(INDEX('Part 1'!$FG$3:$GC$3,1,ROW()-1))=TRIM($X16),INDEX('Part 1'!$FG$386:$GC$386,1,ROW()-1),"CHECK"))} -> 1136 | AB16: =IF(OR($X16="",$AA16="CHECK",$AA16=""),"",$Z16-$AA16) -> 0 | AC16: {=IF($X16="","",IF(TRIM(INDEX('Part 1'!$FG$3:$GC$3,1,ROW()-1))=TRIM($X16),INDEX('Part 1'!$FG$38:$GC$38,1,ROW()-1),"CHECK"))} -> 0 | AE16: CONCORD COOLING COIL | AG16: 200 | AH16: {=IF($AE16="","",IF(TRIM(INDEX('Part 1'!$ER$3:$FF$3,1,ROW()-1))=TRIM($AE16),INDEX('Part 1'!$ER$386:$FF$386,1,ROW()-1),"CHECK"))} -> 200 | AI16: =IF(OR($AE16="",$AH16="CHECK",$AH16=""),"",ROUND($AG16-$AH16,2)) -> 0 | AJ16: {=IF($AE16="","",IF(TRIM(INDEX('Part 1'!$ER$3:$FF$3,1,ROW()-1))=TRIM($AE16),INDEX('Part 1'!$ER$38:$FF$38,1,ROW()-1),"CHECK"))} -> 200 | AK16: CONCORD COOLING COIL | AM16: ANY HCC | AN16: PC-7034A | AO16: 0 | AP16: {=IF($AM16="","",IF(TRIM(INDEX('Part 1'!$HC$3:$HT$3,1,ROW()-1))=TRIM($AM16),INDEX('Part 1'!$HC$386:$HT$386,1,ROW()-1),"CHECK"))} -> 0 | AQ16: =IF(OR($AM16="",$AP16="CHECK",$AP16=""),"",ROUND($AO16-$AP16,2)) -> 0 | AR16: {=IF($AM16="","",IF(TRIM(INDEX('Part 1'!$HC$3:$HT$3,1,ROW()-1))=TRIM($AM16),INDEX('Part 1'!$HC$38:$HT$38,1,ROW()-1),"CHECK"))} -> 0 | BJ16: LANCER MMC | BK16: PC-E111 | BL16: 160 | BM16: {=IF($BJ16="","",IF(TRIM(INDEX('Part 2'!$F$3:$AS$3,1,ROW()-1))=TRIM($BJ16),INDEX('Part 2'!$F$243:$AS$243,1,ROW()-1),"CHECK"))} -> 160 | BN16: =IF(OR($BJ16="",$BM16="CHECK",$BM16=""),"",ROUND($BL16-$BM16,2)) -> 0 | BO16: {=IF($BJ16="","",IF(TRIM(INDEX('Part 2'!$F$3:$AS$3,1,ROW()-1))=TRIM($BJ16),INDEX('Part 2'!$F$33:$AS$33,1,ROW()-1),"CHECK"))} -> 160 | BP16: LANCER MMC | BR16: 15MM-SUC | BS16: BH | BT16: 460 | BU16: =IF(TRIM('Part 2'!$BH$3&" "&'Part 2'!$BH$4)=TRIM($BR16),'Part 2'!$BH$243,"CHECK") -> 486 | BV16: =IF(OR($BR16="",$BU16="CHECK"),"",ROUND($BT16-$BU16,2)) -> -26 | BW16: =IF(TRIM('Part 2'!$BH$3&" "&'Part 2'!$BH$4)=TRIM($BR16),'Part 2'!$BH$33,"CHECK") -> 587 | BY16: PLATE SANTRO (SP10) | BZ16: SD-1004E | CA16: 120 | CB16: {=IF($BY16="","",IF(TRIM(INDEX('Part 2'!$BJ$3:$CZ$3,1,ROW()-1))=TRIM($BZ16),INDEX('Part 2'!$BJ$243:$CZ$243,1,ROW()-1),"CHECK"))} -> 120 | CC16: =IF(OR($BY16="",$CB16="CHECK"),"",ROUND($CA16-$CB16,2)) -> 0 | CD16: {=IF($BY16="","",IF(TRIM(INDEX('Part 2'!$BJ$3:$CZ$3,1,ROW()-1))=TRIM($BZ16),INDEX('Part 2'!$BJ$33:$CZ$33,1,ROW()-1),"CHECK"))} -> 120
A17: FABIA | B17: PC-86134 | C17: 51 | D17: {=IF($A17="","",IF(TRIM(INDEX('Part 1'!$F$3:$CZ$3,1,ROW()-1))=TRIM($A17),INDEX('Part 1'!$F$386:$CZ$386,1,ROW()-1),"CHECK"))} -> 50 | E17: =IF(OR($A17="",$D17="CHECK",$D17=""),"",$C17-$D17) -> 1 | F17: {=IF($A17="","",IF(TRIM(INDEX('Part 1'!$F$3:$CZ$3,1,ROW()-1))=TRIM($A17),INDEX('Part 1'!$F$38:$CZ$38,1,ROW()-1),"CHECK"))} -> 50 | J17: Honda City-III | K17: NA | L17: 0 | M17: {=IF($J17="","",IF(TRIM(INDEX('Part 1'!$CS$3:$EQ$3,1,ROW()-1))=TRIM($J17),INDEX('Part 1'!$CS$386:$EQ$386,1,ROW()-1),"CHECK"))} -> 0 | N17: =IF(OR($J17="",$M17="CHECK",$M17=""),"",$L17-$M17) -> 0 | O17: {=IF($J17="","",IF(TRIM(INDEX('Part 1'!$CS$3:$EQ$3,1,ROW()-1))=TRIM($J17),INDEX('Part 1'!$CS$38:$EQ$38,1,ROW()-1),"CHECK"))} -> 0 | Q17: OPTRA | R17: PC-8031 | S17: 50 | T17: {=IF($Q17="","",IF(TRIM(INDEX('Part 1'!$GD$3:$HB$3,1,ROW()-1))=TRIM($Q17),INDEX('Part 1'!$GD$386:$HB$386,1,ROW()-1),"CHECK"))} -> 50 | U17: =IF(OR($Q17="",$T17="CHECK",$T17=""),"",$S17-$T17) -> 0 | V17: {=IF($Q17="","",IF(TRIM(INDEX('Part 1'!$GD$3:$HB$3,1,ROW()-1))=TRIM($Q17),INDEX('Part 1'!$GD$38:$HB$38,1,ROW()-1),"CHECK"))} -> 100 | X17: Santro-4 Speed | Z17: 200 | AA17: {=IF($X17="","",IF(TRIM(INDEX('Part 1'!$FG$3:$GC$3,1,ROW()-1))=TRIM($X17),INDEX('Part 1'!$FG$386:$GC$386,1,ROW()-1),"CHECK"))} -> 200 | AB17: =IF(OR($X17="",$AA17="CHECK",$AA17=""),"",$Z17-$AA17) -> 0 | AC17: {=IF($X17="","",IF(TRIM(INDEX('Part 1'!$FG$3:$GC$3,1,ROW()-1))=TRIM($X17),INDEX('Part 1'!$FG$38:$GC$38,1,ROW()-1),"CHECK"))} -> 0 | AM17: TM-16 | AN17: PC-7046A | AO17: 0 | AP17: {=IF($AM17="","",IF(TRIM(INDEX('Part 1'!$HC$3:$HT$3,1,ROW()-1))=TRIM($AM17),INDEX('Part 1'!$HC$386:$HT$386,1,ROW()-1),"CHECK"))} -> 0 | AQ17: =IF(OR($AM17="",$AP17="CHECK",$AP17=""),"",ROUND($AO17-$AP17,2)) -> 0 | AR17: {=IF($AM17="","",IF(TRIM(INDEX('Part 1'!$HC$3:$HT$3,1,ROW()-1))=TRIM($AM17),INDEX('Part 1'!$HC$38:$HT$38,1,ROW()-1),"CHECK"))} -> 400 | BJ17: LANCER HCC | BK17: PC-E601 | BL17: 79 | BM17: {=IF($BJ17="","",IF(TRIM(INDEX('Part 2'!$F$3:$AS$3,1,ROW()-1))=TRIM($BJ17),INDEX('Part 2'!$F$243:$AS$243,1,ROW()-1),"CHECK"))} -> 79 | BN17: =IF(OR($BJ17="",$BM17="CHECK",$BM17=""),"",ROUND($BL17-$BM17,2)) -> 0 | BO17: {=IF($BJ17="","",IF(TRIM(INDEX('Part 2'!$F$3:$AS$3,1,ROW()-1))=TRIM($BJ17),INDEX('Part 2'!$F$33:$AS$33,1,ROW()-1),"CHECK"))} -> 126 | BP17: LANCER HCC | BR17: INSULATION TAPE PCS | BS17: BI | BT17: 230 | BU17: =IF(TRIM('Part 2'!$BI$3&" "&'Part 2'!$BI$4)=TRIM($BR17),'Part 2'!$BI$243,"CHECK") -> 230 | BV17: =IF(OR($BR17="",$BU17="CHECK"),"",ROUND($BT17-$BU17,2)) -> 0 | BW17: =IF(TRIM('Part 2'!$BI$3&" "&'Part 2'!$BI$4)=TRIM($BR17),'Part 2'!$BI$33,"CHECK") -> 230 | BY17: PLATE HUB SUBROS ND ESTEEM | BZ17: SD-1005 | CA17: 60 | CB17: {=IF($BY17="","",IF(TRIM(INDEX('Part 2'!$BJ$3:$CZ$3,1,ROW()-1))=TRIM($BZ17),INDEX('Part 2'!$BJ$243:$CZ$243,1,ROW()-1),"CHECK"))} -> 60 | CC17: =IF(OR($BY17="",$CB17="CHECK"),"",ROUND($CA17-$CB17,2)) -> 0 | CD17: {=IF($BY17="","",IF(TRIM(INDEX('Part 2'!$BJ$3:$CZ$3,1,ROW()-1))=TRIM($BZ17),INDEX('Part 2'!$BJ$33:$CZ$33,1,ROW()-1),"CHECK"))} -> 60
A18: FEISTA | B18: PC-86272 | C18: 0 | D18: {=IF($A18="","",IF(TRIM(INDEX('Part 1'!$F$3:$CZ$3,1,ROW()-1))=TRIM($A18),INDEX('Part 1'!$F$386:$CZ$386,1,ROW()-1),"CHECK"))} -> 0 | E18: =IF(OR($A18="",$D18="CHECK",$D18=""),"",$C18-$D18) -> 0 | F18: {=IF($A18="","",IF(TRIM(INDEX('Part 1'!$F$3:$CZ$3,1,ROW()-1))=TRIM($A18),INDEX('Part 1'!$F$38:$CZ$38,1,ROW()-1),"CHECK"))} -> 0 | J18: Honda City-I & II | K18: PC-8111R | L18: 24 | M18: {=IF($J18="","",IF(TRIM(INDEX('Part 1'!$CS$3:$EQ$3,1,ROW()-1))=TRIM($J18),INDEX('Part 1'!$CS$386:$EQ$386,1,ROW()-1),"CHECK"))} -> 24 | N18: =IF(OR($J18="",$M18="CHECK",$M18=""),"",$L18-$M18) -> 0 | O18: {=IF($J18="","",IF(TRIM(INDEX('Part 1'!$CS$3:$EQ$3,1,ROW()-1))=TRIM($J18),INDEX('Part 1'!$CS$38:$EQ$38,1,ROW()-1),"CHECK"))} -> 102 | Q18: Santro/santro xing | R18: PC-8026 | S18: 2500 | T18: {=IF($Q18="","",IF(TRIM(INDEX('Part 1'!$GD$3:$HB$3,1,ROW()-1))=TRIM($Q18),INDEX('Part 1'!$GD$386:$HB$386,1,ROW()-1),"CHECK"))} -> 2500 | U18: =IF(OR($Q18="",$T18="CHECK",$T18=""),"",$S18-$T18) -> 0 | V18: {=IF($Q18="","",IF(TRIM(INDEX('Part 1'!$GD$3:$HB$3,1,ROW()-1))=TRIM($Q18),INDEX('Part 1'!$GD$38:$HB$38,1,ROW()-1),"CHECK"))} -> 10175 | X18: skoda-3PIN | Y18: PC-1191 | Z18: 575 | AA18: {=IF($X18="","",IF(TRIM(INDEX('Part 1'!$FG$3:$GC$3,1,ROW()-1))=TRIM($X18),INDEX('Part 1'!$FG$386:$GC$386,1,ROW()-1),"CHECK"))} -> 575 | AB18: =IF(OR($X18="",$AA18="CHECK",$AA18=""),"",$Z18-$AA18) -> 0 | AC18: {=IF($X18="","",IF(TRIM(INDEX('Part 1'!$FG$3:$GC$3,1,ROW()-1))=TRIM($X18),INDEX('Part 1'!$FG$38:$GC$38,1,ROW()-1),"CHECK"))} -> 450 | AE18: CONCORD ELECTRIC BLOWER - FAMILY (rows 6-11) | AG18: =SUM($AG$6:$AG$11) -> 1812 | AH18: =SUM($AH$6:$AH$11) -> 1600 | AI18: =$AG18-$AH18 -> 212 | AJ18: =SUM($AH$6:$AH$11) -> 1600 | AM18: TQ | AN18: PC-7032A | AO18: 115 | AP18: {=IF($AM18="","",IF(TRIM(INDEX('Part 1'!$HC$3:$HT$3,1,ROW()-1))=TRIM($AM18),INDEX('Part 1'!$HC$386:$HT$386,1,ROW()-1),"CHECK"))} -> 115 | AQ18: =IF(OR($AM18="",$AP18="CHECK",$AP18=""),"",ROUND($AO18-$AP18,2)) -> 0 | AR18: {=IF($AM18="","",IF(TRIM(INDEX('Part 1'!$HC$3:$HT$3,1,ROW()-1))=TRIM($AM18),INDEX('Part 1'!$HC$38:$HT$38,1,ROW()-1),"CHECK"))} -> 500 | BJ18: LAURA | BK18: PC-E414 | BL18: 62 | BM18: {=IF($BJ18="","",IF(TRIM(INDEX('Part 2'!$F$3:$AS$3,1,ROW()-1))=TRIM($BJ18),INDEX('Part 2'!$F$243:$AS$243,1,ROW()-1),"CHECK"))} -> 62 | BN18: =IF(OR($BJ18="",$BM18="CHECK",$BM18=""),"",ROUND($BL18-$BM18,2)) -> 0 | BO18: {=IF($BJ18="","",IF(TRIM(INDEX('Part 2'!$F$3:$AS$3,1,ROW()-1))=TRIM($BJ18),INDEX('Part 2'!$F$33:$AS$33,1,ROW()-1),"CHECK"))} -> 163 | BP18: LAURA | BR18: HFC-340G | BS18: DA | BT18: 28830 | BU18: =IF(TRIM('Part 2'!$DA$3&" "&'Part 2'!$DA$4)=TRIM($BR18),'Part 2'!$DA$243,"CHECK") -> 27649.176 | BV18: =IF(OR($BR18="",$BU18="CHECK"),"",ROUND($BT18-$BU18,2)) -> 1180.82 | BW18: =IF(TRIM('Part 2'!$DA$3&" "&'Part 2'!$DA$4)=TRIM($BR18),'Part 2'!$DA$33,"CHECK") -> 36000 | BY18: MAGNETIC COIL SUBROS ND ESTEEM | BZ18: SD-1005A | CA18: 120 | CB18: {=IF($BY18="","",IF(TRIM(INDEX('Part 2'!$BJ$3:$CZ$3,1,ROW()-1))=TRIM($BZ18),INDEX('Part 2'!$BJ$243:$CZ$243,1,ROW()-1),"CHECK"))} -> 120 | CC18: =IF(OR($BY18="",$CB18="CHECK"),"",ROUND($CA18-$CB18,2)) -> 0 | CD18: {=IF($BY18="","",IF(TRIM(INDEX('Part 2'!$BJ$3:$CZ$3,1,ROW()-1))=TRIM($BZ18),INDEX('Part 2'!$BJ$33:$CZ$33,1,ROW()-1),"CHECK"))} -> 120
A19: Ford Ikon | B19: PC-86034 | C19: 276 | D19: {=IF($A19="","",IF(TRIM(INDEX('Part 1'!$F$3:$CZ$3,1,ROW()-1))=TRIM($A19),INDEX('Part 1'!$F$386:$CZ$386,1,ROW()-1),"CHECK"))} -> 270 | E19: =IF(OR($A19="",$D19="CHECK",$D19=""),"",$C19-$D19) -> 6 | F19: {=IF($A19="","",IF(TRIM(INDEX('Part 1'!$F$3:$CZ$3,1,ROW()-1))=TRIM($A19),INDEX('Part 1'!$F$38:$CZ$38,1,ROW()-1),"CHECK"))} -> 270 | J19: Honda CRV | K19: PC-113R | L19: 42 | M19: {=IF($J19="","",IF(TRIM(INDEX('Part 1'!$CS$3:$EQ$3,1,ROW()-1))=TRIM($J19),INDEX('Part 1'!$CS$386:$EQ$386,1,ROW()-1),"CHECK"))} -> 36 | N19: =IF(OR($J19="",$M19="CHECK",$M19=""),"",$L19-$M19) -> 6 | O19: {=IF($J19="","",IF(TRIM(INDEX('Part 1'!$CS$3:$EQ$3,1,ROW()-1))=TRIM($J19),INDEX('Part 1'!$CS$38:$EQ$38,1,ROW()-1),"CHECK"))} -> 48 | Q19: Scorpio-3hole | R19: PC-8115A | S19: 0 | T19: {=IF($Q19="","",IF(TRIM(INDEX('Part 1'!$GD$3:$HB$3,1,ROW()-1))=TRIM($Q19),INDEX('Part 1'!$GD$386:$HB$386,1,ROW()-1),"CHECK"))} -> 0 | U19: =IF(OR($Q19="",$T19="CHECK",$T19=""),"",$S19-$T19) -> 0 | V19: {=IF($Q19="","",IF(TRIM(INDEX('Part 1'!$GD$3:$HB$3,1,ROW()-1))=TRIM($Q19),INDEX('Part 1'!$GD$38:$HB$38,1,ROW()-1),"CHECK"))} -> 0 | X19: SONATA | Y19: PC-2126 | Z19: 0 | AA19: {=IF($X19="","",IF(TRIM(INDEX('Part 1'!$FG$3:$GC$3,1,ROW()-1))=TRIM($X19),INDEX('Part 1'!$FG$386:$GC$386,1,ROW()-1),"CHECK"))} -> 0 | AB19: =IF(OR($X19="",$AA19="CHECK",$AA19=""),"",$Z19-$AA19) -> 0 | AC19: {=IF($X19="","",IF(TRIM(INDEX('Part 1'!$FG$3:$GC$3,1,ROW()-1))=TRIM($X19),INDEX('Part 1'!$FG$38:$GC$38,1,ROW()-1),"CHECK"))} -> 0 | AM19: WR | AN19: PC-7038A | AO19: 0 | AP19: {=IF($AM19="","",IF(TRIM(INDEX('Part 1'!$HC$3:$HT$3,1,ROW()-1))=TRIM($AM19),INDEX('Part 1'!$HC$386:$HT$386,1,ROW()-1),"CHECK"))} -> 0 | AQ19: =IF(OR($AM19="",$AP19="CHECK",$AP19=""),"",ROUND($AO19-$AP19,2)) -> 0 | AR19: {=IF($AM19="","",IF(TRIM(INDEX('Part 1'!$HC$3:$HT$3,1,ROW()-1))=TRIM($AM19),INDEX('Part 1'!$HC$38:$HT$38,1,ROW()-1),"CHECK"))} -> 1500 | BJ19: LINEA | BK19: PC-E404 | BL19: 28 | BM19: {=IF($BJ19="","",IF(TRIM(INDEX('Part 2'!$F$3:$AS$3,1,ROW()-1))=TRIM($BJ19),INDEX('Part 2'!$F$243:$AS$243,1,ROW()-1),"CHECK"))} -> 28 | BN19: =IF(OR($BJ19="",$BM19="CHECK",$BM19=""),"",ROUND($BL19-$BM19,2)) -> 0 | BO19: {=IF($BJ19="","",IF(TRIM(INDEX('Part 2'!$F$3:$AS$3,1,ROW()-1))=TRIM($BJ19),INDEX('Part 2'!$F$33:$AS$33,1,ROW()-1),"CHECK"))} -> 44 | BP19: LINEA | BR19: MOTOR- MICROBUS 24V | BS19: DB | BT19: 100 | BU19: =IF(TRIM('Part 2'!$DB$3&" "&'Part 2'!$DB$4)=TRIM($BR19),'Part 2'!$DB$243,"CHECK") -> 102 | BV19: =IF(OR($BR19="",$BU19="CHECK"),"",ROUND($BT19-$BU19,2)) -> -2 | BW19: =IF(TRIM('Part 2'!$DB$3&" "&'Part 2'!$DB$4)=TRIM($BR19),'Part 2'!$DB$33,"CHECK") -> 100 | BY19: PULLEY PULL SUBROS ND ESTEEM | BZ19: SD-1005B | CA19: 60 | CB19: {=IF($BY19="","",IF(TRIM(INDEX('Part 2'!$BJ$3:$CZ$3,1,ROW()-1))=TRIM($BZ19),INDEX('Part 2'!$BJ$243:$CZ$243,1,ROW()-1),"CHECK"))} -> 60 | CC19: =IF(OR($BY19="",$CB19="CHECK"),"",ROUND($CA19-$CB19,2)) -> 0 | CD19: {=IF($BY19="","",IF(TRIM(INDEX('Part 2'!$BJ$3:$CZ$3,1,ROW()-1))=TRIM($BZ19),INDEX('Part 2'!$BJ$33:$CZ$33,1,ROW()-1),"CHECK"))} -> 60
A20: FUSION | B20: PC-86271 | C20: 0 | D20: {=IF($A20="","",IF(TRIM(INDEX('Part 1'!$F$3:$CZ$3,1,ROW()-1))=TRIM($A20),INDEX('Part 1'!$F$386:$CZ$386,1,ROW()-1),"CHECK"))} -> 0 | E20: =IF(OR($A20="",$D20="CHECK",$D20=""),"",$C20-$D20) -> 0 | F20: {=IF($A20="","",IF(TRIM(INDEX('Part 1'!$F$3:$CZ$3,1,ROW()-1))=TRIM($A20),INDEX('Part 1'!$F$38:$CZ$38,1,ROW()-1),"CHECK"))} -> 0 | J20: INDICA SUBROS R134A | K20: PC-8110R | L20: 24 | M20: {=IF($J20="","",IF(TRIM(INDEX('Part 1'!$CS$3:$EQ$3,1,ROW()-1))=TRIM($J20),INDEX('Part 1'!$CS$386:$EQ$386,1,ROW()-1),"CHECK"))} -> 24 | N20: =IF(OR($J20="",$M20="CHECK",$M20=""),"",$L20-$M20) -> 0 | O20: {=IF($J20="","",IF(TRIM(INDEX('Part 1'!$CS$3:$EQ$3,1,ROW()-1))=TRIM($J20),INDEX('Part 1'!$CS$38:$EQ$38,1,ROW()-1),"CHECK"))} -> 54 | Q20: Scorpio-4hole | R20: PC-8115B | S20: 25 | T20: {=IF($Q20="","",IF(TRIM(INDEX('Part 1'!$GD$3:$HB$3,1,ROW()-1))=TRIM($Q20),INDEX('Part 1'!$GD$386:$HB$386,1,ROW()-1),"CHECK"))} -> 25 | U20: =IF(OR($Q20="",$T20="CHECK",$T20=""),"",$S20-$T20) -> 0 | V20: {=IF($Q20="","",IF(TRIM(INDEX('Part 1'!$GD$3:$HB$3,1,ROW()-1))=TRIM($Q20),INDEX('Part 1'!$GD$38:$HB$38,1,ROW()-1),"CHECK"))} -> 0 | X20: SONATA | Y20: PC-1802B | Z20: 0 | AA20: {=IF($X20="","",IF(TRIM(INDEX('Part 1'!$FG$3:$GC$3,1,ROW()-1))=TRIM($X20),INDEX('Part 1'!$FG$386:$GC$386,1,ROW()-1),"CHECK"))} -> 0 | AB20: =IF(OR($X20="",$AA20="CHECK",$AA20=""),"",$Z20-$AA20) -> 0 | AC20: {=IF($X20="","",IF(TRIM(INDEX('Part 1'!$FG$3:$GC$3,1,ROW()-1))=TRIM($X20),INDEX('Part 1'!$FG$38:$GC$38,1,ROW()-1),"CHECK"))} -> 200 | BJ20: LOGAN | BK20: PC-E414 | BL20: 50 | BM20: {=IF($BJ20="","",IF(TRIM(INDEX('Part 2'!$F$3:$AS$3,1,ROW()-1))=TRIM($BJ20),INDEX('Part 2'!$F$243:$AS$243,1,ROW()-1),"CHECK"))} -> 50 | BN20: =IF(OR($BJ20="",$BM20="CHECK",$BM20=""),"",ROUND($BL20-$BM20,2)) -> 0 | BO20: {=IF($BJ20="","",IF(TRIM(INDEX('Part 2'!$F$3:$AS$3,1,ROW()-1))=TRIM($BJ20),INDEX('Part 2'!$F$33:$AS$33,1,ROW()-1),"CHECK"))} -> 51 | BP20: LOGAN | BR20: MOTOR-SK 12V | BS20: DC | BT20: 10 | BU20: =IF(TRIM('Part 2'!$DC$3&" "&'Part 2'!$DC$4)=TRIM($BR20),'Part 2'!$DC$243,"CHECK") -> 10 | BV20: =IF(OR($BR20="",$BU20="CHECK"),"",ROUND($BT20-$BU20,2)) -> 0 | BW20: =IF(TRIM('Part 2'!$DC$3&" "&'Part 2'!$DC$4)=TRIM($BR20),'Part 2'!$DC$33,"CHECK") -> 288 | BY20: MAGNETIC COIL SKODA | BZ20: SD-1007A | CA20: 120 | CB20: {=IF($BY20="","",IF(TRIM(INDEX('Part 2'!$BJ$3:$CZ$3,1,ROW()-1))=TRIM($BZ20),INDEX('Part 2'!$BJ$243:$CZ$243,1,ROW()-1),"CHECK"))} -> 120 | CC20: =IF(OR($BY20="",$CB20="CHECK"),"",ROUND($CA20-$CB20,2)) -> 0 | CD20: {=IF($BY20="","",IF(TRIM(INDEX('Part 2'!$BJ$3:$CZ$3,1,ROW()-1))=TRIM($BZ20),INDEX('Part 2'!$BJ$33:$CZ$33,1,ROW()-1),"CHECK"))} -> 120
A21: GETZ | B21: PC-86027B | C21: 100 | D21: {=IF($A21="","",IF(TRIM(INDEX('Part 1'!$F$3:$CZ$3,1,ROW()-1))=TRIM($A21),INDEX('Part 1'!$F$386:$CZ$386,1,ROW()-1),"CHECK"))} -> 100 | E21: =IF(OR($A21="",$D21="CHECK",$D21=""),"",$C21-$D21) -> 0 | F21: {=IF($A21="","",IF(TRIM(INDEX('Part 1'!$F$3:$CZ$3,1,ROW()-1))=TRIM($A21),INDEX('Part 1'!$F$38:$CZ$38,1,ROW()-1),"CHECK"))} -> 100 | J21: Indica Behr | L21: 0 | M21: {=IF($J21="","",IF(TRIM(INDEX('Part 1'!$CS$3:$EQ$3,1,ROW()-1))=TRIM($J21),INDEX('Part 1'!$CS$386:$EQ$386,1,ROW()-1),"CHECK"))} -> 0 | N21: =IF(OR($J21="",$M21="CHECK",$M21=""),"",$L21-$M21) -> 0 | O21: {=IF($J21="","",IF(TRIM(INDEX('Part 1'!$CS$3:$EQ$3,1,ROW()-1))=TRIM($J21),INDEX('Part 1'!$CS$38:$EQ$38,1,ROW()-1),"CHECK"))} -> 0 | Q21: Skoda | R21: PC-8053 | S21: 450 | T21: {=IF($Q21="","",IF(TRIM(INDEX('Part 1'!$GD$3:$HB$3,1,ROW()-1))=TRIM($Q21),INDEX('Part 1'!$GD$386:$HB$386,1,ROW()-1),"CHECK"))} -> 450 | U21: =IF(OR($Q21="",$T21="CHECK",$T21=""),"",$S21-$T21) -> 0 | V21: {=IF($Q21="","",IF(TRIM(INDEX('Part 1'!$GD$3:$HB$3,1,ROW()-1))=TRIM($Q21),INDEX('Part 1'!$GD$38:$HB$38,1,ROW()-1),"CHECK"))} -> 450 | X21: SWIFT | Y21: PC-1525 | Z21: 75 | AA21: {=IF($X21="","",IF(TRIM(INDEX('Part 1'!$FG$3:$GC$3,1,ROW()-1))=TRIM($X21),INDEX('Part 1'!$FG$386:$GC$386,1,ROW()-1),"CHECK"))} -> 75 | AB21: =IF(OR($X21="",$AA21="CHECK",$AA21=""),"",$Z21-$AA21) -> 0 | AC21: {=IF($X21="","",IF(TRIM(INDEX('Part 1'!$FG$3:$GC$3,1,ROW()-1))=TRIM($X21),INDEX('Part 1'!$FG$38:$GC$38,1,ROW()-1),"CHECK"))} -> 0 | AM21: 507-AA + 508-AA COMBINED (rows 5-6) | AO21: =$AO$5+$AO$6 -> 2650 | AP21: =$AP$5+$AP$6 -> 2200 | AQ21: =$AO21-$AP21 -> 450 | AR21: =$AP$5+$AP$6 -> 2200 | BJ21: OPTRA | BK21: PC-E037 | BL21: 44 | BM21: {=IF($BJ21="","",IF(TRIM(INDEX('Part 2'!$F$3:$AS$3,1,ROW()-1))=TRIM($BJ21),INDEX('Part 2'!$F$243:$AS$243,1,ROW()-1),"CHECK"))} -> 44 | BN21: =IF(OR($BJ21="",$BM21="CHECK",$BM21=""),"",ROUND($BL21-$BM21,2)) -> 0 | BO21: {=IF($BJ21="","",IF(TRIM(INDEX('Part 2'!$F$3:$AS$3,1,ROW()-1))=TRIM($BJ21),INDEX('Part 2'!$F$33:$AS$33,1,ROW()-1),"CHECK"))} -> 109 | BP21: OPTRA | BY21: PULLEY PULL SKODA | BZ21: SD-1007B | CA21: 48 | CB21: {=IF($BY21="","",IF(TRIM(INDEX('Part 2'!$BJ$3:$CZ$3,1,ROW()-1))=TRIM($BZ21),INDEX('Part 2'!$BJ$243:$CZ$243,1,ROW()-1),"CHECK"))} -> 48 | CC21: =IF(OR($BY21="",$CB21="CHECK"),"",ROUND($CA21-$CB21,2)) -> 0 | CD21: {=IF($BY21="","",IF(TRIM(INDEX('Part 2'!$BJ$3:$CZ$3,1,ROW()-1))=TRIM($BZ21),INDEX('Part 2'!$BJ$33:$CZ$33,1,ROW()-1),"CHECK"))} -> 48
A22: H.CITY-T-5 | B22: PC-86278 | C22: 50 | D22: {=IF($A22="","",IF(TRIM(INDEX('Part 1'!$F$3:$CZ$3,1,ROW()-1))=TRIM($A22),INDEX('Part 1'!$F$386:$CZ$386,1,ROW()-1),"CHECK"))} -> 50 | E22: =IF(OR($A22="",$D22="CHECK",$D22=""),"",$C22-$D22) -> 0 | F22: {=IF($A22="","",IF(TRIM(INDEX('Part 1'!$F$3:$CZ$3,1,ROW()-1))=TRIM($A22),INDEX('Part 1'!$F$38:$CZ$38,1,ROW()-1),"CHECK"))} -> 50 | J22: Indigo | K22: PC-7159 | L22: 337 | M22: {=IF($J22="","",IF(TRIM(INDEX('Part 1'!$CS$3:$EQ$3,1,ROW()-1))=TRIM($J22),INDEX('Part 1'!$CS$386:$EQ$386,1,ROW()-1),"CHECK"))} -> 337 | N22: =IF(OR($J22="",$M22="CHECK",$M22=""),"",$L22-$M22) -> 0 | O22: {=IF($J22="","",IF(TRIM(INDEX('Part 1'!$CS$3:$EQ$3,1,ROW()-1))=TRIM($J22),INDEX('Part 1'!$CS$38:$EQ$38,1,ROW()-1),"CHECK"))} -> 500 | Q22: Sonata | R22: PC-6066 | S22: 50 | T22: {=IF($Q22="","",IF(TRIM(INDEX('Part 1'!$GD$3:$HB$3,1,ROW()-1))=TRIM($Q22),INDEX('Part 1'!$GD$386:$HB$386,1,ROW()-1),"CHECK"))} -> 75 | U22: =IF(OR($Q22="",$T22="CHECK",$T22=""),"",$S22-$T22) -> -25 | V22: {=IF($Q22="","",IF(TRIM(INDEX('Part 1'!$GD$3:$HB$3,1,ROW()-1))=TRIM($Q22),INDEX('Part 1'!$GD$38:$HB$38,1,ROW()-1),"CHECK"))} -> 90 | X22: THERMO-STAT | Y22: PC-1229A | Z22: 4599 | AA22: {=IF($X22="","",IF(TRIM(INDEX('Part 1'!$FG$3:$GC$3,1,ROW()-1))=TRIM($X22),INDEX('Part 1'!$FG$386:$GC$386,1,ROW()-1),"CHECK"))} -> 4599 | AB22: =IF(OR($X22="",$AA22="CHECK",$AA22=""),"",$Z22-$AA22) -> 0 | AC22: {=IF($X22="","",IF(TRIM(INDEX('Part 1'!$FG$3:$GC$3,1,ROW()-1))=TRIM($X22),INDEX('Part 1'!$FG$38:$GC$38,1,ROW()-1),"CHECK"))} -> 5000 | BJ22: PALIO | BK22: PC-E402 | BL22: 40 | BM22: {=IF($BJ22="","",IF(TRIM(INDEX('Part 2'!$F$3:$AS$3,1,ROW()-1))=TRIM($BJ22),INDEX('Part 2'!$F$243:$AS$243,1,ROW()-1),"CHECK"))} -> 40 | BN22: =IF(OR($BJ22="",$BM22="CHECK",$BM22=""),"",ROUND($BL22-$BM22,2)) -> 0 | BO22: {=IF($BJ22="","",IF(TRIM(INDEX('Part 2'!$F$3:$AS$3,1,ROW()-1))=TRIM($BJ22),INDEX('Part 2'!$F$33:$AS$33,1,ROW()-1),"CHECK"))} -> 108 | BP22: PALIO | BY22: PLATE HUB WAGONR | BZ22: SD-1008 | CA22: 120 | CB22: {=IF($BY22="","",IF(TRIM(INDEX('Part 2'!$BJ$3:$CZ$3,1,ROW()-1))=TRIM($BZ22),INDEX('Part 2'!$BJ$243:$CZ$243,1,ROW()-1),"CHECK"))} -> 120 | CC22: =IF(OR($BY22="",$CB22="CHECK"),"",ROUND($CA22-$CB22,2)) -> 0 | CD22: {=IF($BY22="","",IF(TRIM(INDEX('Part 2'!$BJ$3:$CZ$3,1,ROW()-1))=TRIM($BZ22),INDEX('Part 2'!$BJ$33:$CZ$33,1,ROW()-1),"CHECK"))} -> 120
A23: H.CITY-T-I & 11 | B23: PC-86091 | C23: 120 | D23: {=IF($A23="","",IF(TRIM(INDEX('Part 1'!$F$3:$CZ$3,1,ROW()-1))=TRIM($A23),INDEX('Part 1'!$F$386:$CZ$386,1,ROW()-1),"CHECK"))} -> 110 | E23: =IF(OR($A23="",$D23="CHECK",$D23=""),"",$C23-$D23) -> 10 | F23: {=IF($A23="","",IF(TRIM(INDEX('Part 1'!$F$3:$CZ$3,1,ROW()-1))=TRIM($A23),INDEX('Part 1'!$F$38:$CZ$38,1,ROW()-1),"CHECK"))} -> 150 | J23: Innova | K23: PC-209 | L23: 186 | M23: {=IF($J23="","",IF(TRIM(INDEX('Part 1'!$CS$3:$EQ$3,1,ROW()-1))=TRIM($J23),INDEX('Part 1'!$CS$386:$EQ$386,1,ROW()-1),"CHECK"))} -> 241 | N23: =IF(OR($J23="",$M23="CHECK",$M23=""),"",$L23-$M23) -> -55 | O23: {=IF($J23="","",IF(TRIM(INDEX('Part 1'!$CS$3:$EQ$3,1,ROW()-1))=TRIM($J23),INDEX('Part 1'!$CS$38:$EQ$38,1,ROW()-1),"CHECK"))} -> 312 | Q23: Toyota Qualis | R23: PC-8008 | S23: 560 | T23: {=IF($Q23="","",IF(TRIM(INDEX('Part 1'!$GD$3:$HB$3,1,ROW()-1))=TRIM($Q23),INDEX('Part 1'!$GD$386:$HB$386,1,ROW()-1),"CHECK"))} -> 560 | U23: =IF(OR($Q23="",$T23="CHECK",$T23=""),"",$S23-$T23) -> 0 | V23: {=IF($Q23="","",IF(TRIM(INDEX('Part 1'!$GD$3:$HB$3,1,ROW()-1))=TRIM($Q23),INDEX('Part 1'!$GD$38:$HB$38,1,ROW()-1),"CHECK"))} -> 560 | X23: TOYOTA QUALIS | Y23: PC-1065 | Z23: 400 | AA23: {=IF($X23="","",IF(TRIM(INDEX('Part 1'!$FG$3:$GC$3,1,ROW()-1))=TRIM($X23),INDEX('Part 1'!$FG$386:$GC$386,1,ROW()-1),"CHECK"))} -> 400 | AB23: =IF(OR($X23="",$AA23="CHECK",$AA23=""),"",$Z23-$AA23) -> 0 | AC23: {=IF($X23="","",IF(TRIM(INDEX('Part 1'!$FG$3:$GC$3,1,ROW()-1))=TRIM($X23),INDEX('Part 1'!$FG$38:$GC$38,1,ROW()-1),"CHECK"))} -> 200 | BJ23: SANTRO XING | BK23: PC-E423 | BL23: 0 | BM23: {=IF($BJ23="","",IF(TRIM(INDEX('Part 2'!$F$3:$AS$3,1,ROW()-1))=TRIM($BJ23),INDEX('Part 2'!$F$243:$AS$243,1,ROW()-1),"CHECK"))} -> 0 | BN23: =IF(OR($BJ23="",$BM23="CHECK",$BM23=""),"",ROUND($BL23-$BM23,2)) -> 0 | BO23: {=IF($BJ23="","",IF(TRIM(INDEX('Part 2'!$F$3:$AS$3,1,ROW()-1))=TRIM($BJ23),INDEX('Part 2'!$F$33:$AS$33,1,ROW()-1),"CHECK"))} -> 0 | BP23: SANTRO XING | BY23: MAGNETIC COIL WAGONR | BZ23: SD-1008A | CA23: 120 | CB23: {=IF($BY23="","",IF(TRIM(INDEX('Part 2'!$BJ$3:$CZ$3,1,ROW()-1))=TRIM($BZ23),INDEX('Part 2'!$BJ$243:$CZ$243,1,ROW()-1),"CHECK"))} -> 120 | CC23: =IF(OR($BY23="",$CB23="CHECK"),"",ROUND($CA23-$CB23,2)) -> 0 | CD23: {=IF($BY23="","",IF(TRIM(INDEX('Part 2'!$BJ$3:$CZ$3,1,ROW()-1))=TRIM($BZ23),INDEX('Part 2'!$BJ$33:$CZ$33,1,ROW()-1),"CHECK"))} -> 120
A24: Honda City-TYPE-3 | B24: PC-86240 | C24: 165 | D24: {=IF($A24="","",IF(TRIM(INDEX('Part 1'!$F$3:$CZ$3,1,ROW()-1))=TRIM($A24),INDEX('Part 1'!$F$386:$CZ$386,1,ROW()-1),"CHECK"))} -> 175 | E24: =IF(OR($A24="",$D24="CHECK",$D24=""),"",$C24-$D24) -> -10 | F24: {=IF($A24="","",IF(TRIM(INDEX('Part 1'!$F$3:$CZ$3,1,ROW()-1))=TRIM($A24),INDEX('Part 1'!$F$38:$CZ$38,1,ROW()-1),"CHECK"))} -> 175 | J24: Innova-Back | K24: PC-246 | L24: 200 | M24: {=IF($J24="","",IF(TRIM(INDEX('Part 1'!$CS$3:$EQ$3,1,ROW()-1))=TRIM($J24),INDEX('Part 1'!$CS$386:$EQ$386,1,ROW()-1),"CHECK"))} -> 200 | N24: =IF(OR($J24="",$M24="CHECK",$M24=""),"",$L24-$M24) -> 0 | O24: {=IF($J24="","",IF(TRIM(INDEX('Part 1'!$CS$3:$EQ$3,1,ROW()-1))=TRIM($J24),INDEX('Part 1'!$CS$38:$EQ$38,1,ROW()-1),"CHECK"))} -> 200 | Q24: Travera | R24: PC-8122 | S24: 0 | T24: {=IF($Q24="","",IF(TRIM(INDEX('Part 1'!$GD$3:$HB$3,1,ROW()-1))=TRIM($Q24),INDEX('Part 1'!$GD$386:$HB$386,1,ROW()-1),"CHECK"))} -> 0 | U24: =IF(OR($Q24="",$T24="CHECK",$T24=""),"",$S24-$T24) -> 0 | V24: {=IF($Q24="","",IF(TRIM(INDEX('Part 1'!$GD$3:$HB$3,1,ROW()-1))=TRIM($Q24),INDEX('Part 1'!$GD$38:$HB$38,1,ROW()-1),"CHECK"))} -> 0 | X24: WAGON-R HPLP-2PIN | Y24: PC-1047B / PC-1801-A | Z24: 800 | AA24: {=IF($X24="","",IF(TRIM(INDEX('Part 1'!$FG$3:$GC$3,1,ROW()-1))=TRIM($X24),INDEX('Part 1'!$FG$386:$GC$386,1,ROW()-1),"CHECK"))} -> 800 | AB24: =IF(OR($X24="",$AA24="CHECK",$AA24=""),"",$Z24-$AA24) -> 0 | AC24: {=IF($X24="","",IF(TRIM(INDEX('Part 1'!$FG$3:$GC$3,1,ROW()-1))=TRIM($X24),INDEX('Part 1'!$FG$38:$GC$38,1,ROW()-1),"CHECK"))} -> 800 | BJ24: SANTRO | BK24: PC-E426 | BL24: 0 | BM24: {=IF($BJ24="","",IF(TRIM(INDEX('Part 2'!$F$3:$AS$3,1,ROW()-1))=TRIM($BJ24),INDEX('Part 2'!$F$243:$AS$243,1,ROW()-1),"CHECK"))} -> 0 | BN24: =IF(OR($BJ24="",$BM24="CHECK",$BM24=""),"",ROUND($BL24-$BM24,2)) -> 0 | BO24: {=IF($BJ24="","",IF(TRIM(INDEX('Part 2'!$F$3:$AS$3,1,ROW()-1))=TRIM($BJ24),INDEX('Part 2'!$F$33:$AS$33,1,ROW()-1),"CHECK"))} -> 0 | BP24: (none - code shared, see setup) | BY24: PULLEY PULL WAGONR | BZ24: SD-1008B | CA24: 60 | CB24: {=IF($BY24="","",IF(TRIM(INDEX('Part 2'!$BJ$3:$CZ$3,1,ROW()-1))=TRIM($BZ24),INDEX('Part 2'!$BJ$243:$CZ$243,1,ROW()-1),"CHECK"))} -> 60 | CC24: =IF(OR($BY24="",$CB24="CHECK"),"",ROUND($CA24-$CB24,2)) -> 0 | CD24: {=IF($BY24="","",IF(TRIM(INDEX('Part 2'!$BJ$3:$CZ$3,1,ROW()-1))=TRIM($BZ24),INDEX('Part 2'!$BJ$33:$CZ$33,1,ROW()-1),"CHECK"))} -> 60
A25: HONDA CRV | B25: PC-86101 | C25: 55 | D25: {=IF($A25="","",IF(TRIM(INDEX('Part 1'!$F$3:$CZ$3,1,ROW()-1))=TRIM($A25),INDEX('Part 1'!$F$386:$CZ$386,1,ROW()-1),"CHECK"))} -> 55 | E25: =IF(OR($A25="",$D25="CHECK",$D25=""),"",$C25-$D25) -> 0 | F25: {=IF($A25="","",IF(TRIM(INDEX('Part 1'!$F$3:$CZ$3,1,ROW()-1))=TRIM($A25),INDEX('Part 1'!$F$38:$CZ$38,1,ROW()-1),"CHECK"))} -> 50 | J25: Lancer HCC | K25: PC-206 | L25: 150 | M25: {=IF($J25="","",IF(TRIM(INDEX('Part 1'!$CS$3:$EQ$3,1,ROW()-1))=TRIM($J25),INDEX('Part 1'!$CS$386:$EQ$386,1,ROW()-1),"CHECK"))} -> 150 | N25: =IF(OR($J25="",$M25="CHECK",$M25=""),"",$L25-$M25) -> 0 | O25: {=IF($J25="","",IF(TRIM(INDEX('Part 1'!$CS$3:$EQ$3,1,ROW()-1))=TRIM($J25),INDEX('Part 1'!$CS$38:$EQ$38,1,ROW()-1),"CHECK"))} -> 210 | Q25: Uni-FLAIR | R25: PC-6001 | S25: 12300 | T25: {=IF($Q25="","",IF(TRIM(INDEX('Part 1'!$GD$3:$HB$3,1,ROW()-1))=TRIM($Q25),INDEX('Part 1'!$GD$386:$HB$386,1,ROW()-1),"CHECK"))} -> 10500 | U25: =IF(OR($Q25="",$T25="CHECK",$T25=""),"",$S25-$T25) -> 1800 | V25: {=IF($Q25="","",IF(TRIM(INDEX('Part 1'!$GD$3:$HB$3,1,ROW()-1))=TRIM($Q25),INDEX('Part 1'!$GD$38:$HB$38,1,ROW()-1),"CHECK"))} -> 14025 | BJ25: SKODA | BK25: PC-E419 | BL25: 690 | BM25: {=IF($BJ25="","",IF(TRIM(INDEX('Part 2'!$F$3:$AS$3,1,ROW()-1))=TRIM($BJ25),INDEX('Part 2'!$F$243:$AS$243,1,ROW()-1),"CHECK"))} -> 690 | BN25: =IF(OR($BJ25="",$BM25="CHECK",$BM25=""),"",ROUND($BL25-$BM25,2)) -> 0 | BO25: {=IF($BJ25="","",IF(TRIM(INDEX('Part 2'!$F$3:$AS$3,1,ROW()-1))=TRIM($BJ25),INDEX('Part 2'!$F$33:$AS$33,1,ROW()-1),"CHECK"))} -> 690 | BP25: SKODA | BY25: MAGNETIC COIL FORD IKON 1.8 | BZ25: SD-1009A | CA25: 120 | CB25: {=IF($BY25="","",IF(TRIM(INDEX('Part 2'!$BJ$3:$CZ$3,1,ROW()-1))=TRIM($BZ25),INDEX('Part 2'!$BJ$243:$CZ$243,1,ROW()-1),"CHECK"))} -> 120 | CC25: =IF(OR($BY25="",$CB25="CHECK"),"",ROUND($CA25-$CB25,2)) -> 0 | CD25: {=IF($BY25="","",IF(TRIM(INDEX('Part 2'!$BJ$3:$CZ$3,1,ROW()-1))=TRIM($BZ25),INDEX('Part 2'!$BJ$33:$CZ$33,1,ROW()-1),"CHECK"))} -> 120
A26: HONDA CIVIC | B26: PC-86251 | C26: 1 | D26: {=IF($A26="","",IF(TRIM(INDEX('Part 1'!$F$3:$CZ$3,1,ROW()-1))=TRIM($A26),INDEX('Part 1'!$F$386:$CZ$386,1,ROW()-1),"CHECK"))} -> 0 | E26: =IF(OR($A26="",$D26="CHECK",$D26=""),"",$C26-$D26) -> 1 | F26: {=IF($A26="","",IF(TRIM(INDEX('Part 1'!$F$3:$CZ$3,1,ROW()-1))=TRIM($A26),INDEX('Part 1'!$F$38:$CZ$38,1,ROW()-1),"CHECK"))} -> 0 | J26: Lancer MMC-2000 | K26: PC-051R | L26: 0 | M26: {=IF($J26="","",IF(TRIM(INDEX('Part 1'!$CS$3:$EQ$3,1,ROW()-1))=TRIM($J26),INDEX('Part 1'!$CS$386:$EQ$386,1,ROW()-1),"CHECK"))} -> 0 | N26: =IF(OR($J26="",$M26="CHECK",$M26=""),"",$L26-$M26) -> 0 | O26: {=IF($J26="","",IF(TRIM(INDEX('Part 1'!$CS$3:$EQ$3,1,ROW()-1))=TRIM($J26),INDEX('Part 1'!$CS$38:$EQ$38,1,ROW()-1),"CHECK"))} -> 0 | Q26: Universal | R26: PC-6001B | S26: 874 | T26: {=IF($Q26="","",IF(TRIM(INDEX('Part 1'!$GD$3:$HB$3,1,ROW()-1))=TRIM($Q26),INDEX('Part 1'!$GD$386:$HB$386,1,ROW()-1),"CHECK"))} -> 3300 | U26: =IF(OR($Q26="",$T26="CHECK",$T26=""),"",$S26-$T26) -> -2426 | V26: {=IF($Q26="","",IF(TRIM(INDEX('Part 1'!$GD$3:$HB$3,1,ROW()-1))=TRIM($Q26),INDEX('Part 1'!$GD$38:$HB$38,1,ROW()-1),"CHECK"))} -> 1500 | BJ26: SKODA FABIA | BK26: PC-E011 | BL26: 17 | BM26: {=IF($BJ26="","",IF(TRIM(INDEX('Part 2'!$F$3:$AS$3,1,ROW()-1))=TRIM($BJ26),INDEX('Part 2'!$F$243:$AS$243,1,ROW()-1),"CHECK"))} -> 16 | BN26: =IF(OR($BJ26="",$BM26="CHECK",$BM26=""),"",ROUND($BL26-$BM26,2)) -> 1 | BO26: {=IF($BJ26="","",IF(TRIM(INDEX('Part 2'!$F$3:$AS$3,1,ROW()-1))=TRIM($BJ26),INDEX('Part 2'!$F$33:$AS$33,1,ROW()-1),"CHECK"))} -> 52 | BP26: SKODA FABIA | BY26: PULLEY FORD IKON 1.8 | BZ26: SD-1009B | CA26: 48 | CB26: {=IF($BY26="","",IF(TRIM(INDEX('Part 2'!$BJ$3:$CZ$3,1,ROW()-1))=TRIM($BZ26),INDEX('Part 2'!$BJ$243:$CZ$243,1,ROW()-1),"CHECK"))} -> 48 | CC26: =IF(OR($BY26="",$CB26="CHECK"),"",ROUND($CA26-$CB26,2)) -> 0 | CD26: {=IF($BY26="","",IF(TRIM(INDEX('Part 2'!$BJ$3:$CZ$3,1,ROW()-1))=TRIM($BZ26),INDEX('Part 2'!$BJ$33:$CZ$33,1,ROW()-1),"CHECK"))} -> 48
A27: I-10 | C27: 0 | D27: {=IF($A27="","",IF(TRIM(INDEX('Part 1'!$F$3:$CZ$3,1,ROW()-1))=TRIM($A27),INDEX('Part 1'!$F$386:$CZ$386,1,ROW()-1),"CHECK"))} -> 0 | E27: =IF(OR($A27="",$D27="CHECK",$D27=""),"",$C27-$D27) -> 0 | F27: {=IF($A27="","",IF(TRIM(INDEX('Part 1'!$F$3:$CZ$3,1,ROW()-1))=TRIM($A27),INDEX('Part 1'!$F$38:$CZ$38,1,ROW()-1),"CHECK"))} -> 0 | J27: Logan | K27: PC-407R | L27: 180 | M27: {=IF($J27="","",IF(TRIM(INDEX('Part 1'!$CS$3:$EQ$3,1,ROW()-1))=TRIM($J27),INDEX('Part 1'!$CS$386:$EQ$386,1,ROW()-1),"CHECK"))} -> 180 | N27: =IF(OR($J27="",$M27="CHECK",$M27=""),"",$L27-$M27) -> 0 | O27: {=IF($J27="","",IF(TRIM(INDEX('Part 1'!$CS$3:$EQ$3,1,ROW()-1))=TRIM($J27),INDEX('Part 1'!$CS$38:$EQ$38,1,ROW()-1),"CHECK"))} -> 180 | BJ27: TRAVERA | BK27: PC-E036 | BL27: 285 | BM27: {=IF($BJ27="","",IF(TRIM(INDEX('Part 2'!$F$3:$AS$3,1,ROW()-1))=TRIM($BJ27),INDEX('Part 2'!$F$243:$AS$243,1,ROW()-1),"CHECK"))} -> 285 | BN27: =IF(OR($BJ27="",$BM27="CHECK",$BM27=""),"",ROUND($BL27-$BM27,2)) -> 0 | BO27: {=IF($BJ27="","",IF(TRIM(INDEX('Part 2'!$F$3:$AS$3,1,ROW()-1))=TRIM($BJ27),INDEX('Part 2'!$F$33:$AS$33,1,ROW()-1),"CHECK"))} -> 285 | BP27: TRAVERA | BY27: MAGNETIC COIL FORD 1.8 | BZ27: SD-1010A | CA27: 60 | CB27: {=IF($BY27="","",IF(TRIM(INDEX('Part 2'!$BJ$3:$CZ$3,1,ROW()-1))=TRIM($BZ27),INDEX('Part 2'!$BJ$243:$CZ$243,1,ROW()-1),"CHECK"))} -> 60 | CC27: =IF(OR($BY27="",$CB27="CHECK"),"",ROUND($CA27-$CB27,2)) -> 0 | CD27: {=IF($BY27="","",IF(TRIM(INDEX('Part 2'!$BJ$3:$CZ$3,1,ROW()-1))=TRIM($BZ27),INDEX('Part 2'!$BJ$33:$CZ$33,1,ROW()-1),"CHECK"))} -> 60
A28: I-20 | B28: PC-86268 | C28: 0 | D28: {=IF($A28="","",IF(TRIM(INDEX('Part 1'!$F$3:$CZ$3,1,ROW()-1))=TRIM($A28),INDEX('Part 1'!$F$386:$CZ$386,1,ROW()-1),"CHECK"))} -> 0 | E28: =IF(OR($A28="",$D28="CHECK",$D28=""),"",$C28-$D28) -> 0 | F28: {=IF($A28="","",IF(TRIM(INDEX('Part 1'!$F$3:$CZ$3,1,ROW()-1))=TRIM($A28),INDEX('Part 1'!$F$38:$CZ$38,1,ROW()-1),"CHECK"))} -> 0 | J28: MATIZ | K28: PC-8084 | L28: 6 | M28: {=IF($J28="","",IF(TRIM(INDEX('Part 1'!$CS$3:$EQ$3,1,ROW()-1))=TRIM($J28),INDEX('Part 1'!$CS$386:$EQ$386,1,ROW()-1),"CHECK"))} -> 6 | N28: =IF(OR($J28="",$M28="CHECK",$M28=""),"",$L28-$M28) -> 0 | O28: {=IF($J28="","",IF(TRIM(INDEX('Part 1'!$CS$3:$EQ$3,1,ROW()-1))=TRIM($J28),INDEX('Part 1'!$CS$38:$EQ$38,1,ROW()-1),"CHECK"))} -> 30 | BJ28: WR/ALTO | BK28: PC-E416 | BL28: 0 | BM28: {=IF($BJ28="","",IF(TRIM(INDEX('Part 2'!$F$3:$AS$3,1,ROW()-1))=TRIM($BJ28),INDEX('Part 2'!$F$243:$AS$243,1,ROW()-1),"CHECK"))} -> 0 | BN28: =IF(OR($BJ28="",$BM28="CHECK",$BM28=""),"",ROUND($BL28-$BM28,2)) -> 0 | BO28: {=IF($BJ28="","",IF(TRIM(INDEX('Part 2'!$F$3:$AS$3,1,ROW()-1))=TRIM($BJ28),INDEX('Part 2'!$F$33:$AS$33,1,ROW()-1),"CHECK"))} -> 0 | BP28: WR/ALTO | BY28: PULLEY PULL FORD 1.8 | BZ28: SD-1010B | CA28: 24 | CB28: {=IF($BY28="","",IF(TRIM(INDEX('Part 2'!$BJ$3:$CZ$3,1,ROW()-1))=TRIM($BZ28),INDEX('Part 2'!$BJ$243:$CZ$243,1,ROW()-1),"CHECK"))} -> 24 | CC28: =IF(OR($BY28="",$CB28="CHECK"),"",ROUND($CA28-$CB28,2)) -> 0 | CD28: {=IF($BY28="","",IF(TRIM(INDEX('Part 2'!$BJ$3:$CZ$3,1,ROW()-1))=TRIM($BZ28),INDEX('Part 2'!$BJ$33:$CZ$33,1,ROW()-1),"CHECK"))} -> 24
A29: INDICA / BEHR-R134A | B29: PC-86233 | C29: 1000 | D29: {=IF($A29="","",IF(TRIM(INDEX('Part 1'!$F$3:$CZ$3,1,ROW()-1))=TRIM($A29),INDEX('Part 1'!$F$386:$CZ$386,1,ROW()-1),"CHECK"))} -> 950 | E29: =IF(OR($A29="",$D29="CHECK",$D29=""),"",$C29-$D29) -> 50 | F29: {=IF($A29="","",IF(TRIM(INDEX('Part 1'!$F$3:$CZ$3,1,ROW()-1))=TRIM($A29),INDEX('Part 1'!$F$38:$CZ$38,1,ROW()-1),"CHECK"))} -> 1000 | J29: MITSUBISHI PAJERO | L29: 0 | M29: {=IF($J29="","",IF(TRIM(INDEX('Part 1'!$CS$3:$EQ$3,1,ROW()-1))=TRIM($J29),INDEX('Part 1'!$CS$386:$EQ$386,1,ROW()-1),"CHECK"))} -> 0 | N29: =IF(OR($J29="",$M29="CHECK",$M29=""),"",$L29-$M29) -> 0 | O29: {=IF($J29="","",IF(TRIM(INDEX('Part 1'!$CS$3:$EQ$3,1,ROW()-1))=TRIM($J29),INDEX('Part 1'!$CS$38:$EQ$38,1,ROW()-1),"CHECK"))} -> 0 | BJ29: HCT | BK29: PC-E424 | BL29: 142 | BM29: {=IF($BJ29="","",IF(TRIM(INDEX('Part 2'!$F$3:$AS$3,1,ROW()-1))=TRIM($BJ29),INDEX('Part 2'!$F$243:$AS$243,1,ROW()-1),"CHECK"))} -> 142 | BN29: =IF(OR($BJ29="",$BM29="CHECK",$BM29=""),"",ROUND($BL29-$BM29,2)) -> 0 | BO29: {=IF($BJ29="","",IF(TRIM(INDEX('Part 2'!$F$3:$AS$3,1,ROW()-1))=TRIM($BJ29),INDEX('Part 2'!$F$33:$AS$33,1,ROW()-1),"CHECK"))} -> 154 | BP29: HCT | BY29: PLATE HUB HYUNDAI ACCENT CRD | BZ29: SD-1011 | CA29: 60 | CB29: {=IF($BY29="","",IF(TRIM(INDEX('Part 2'!$BJ$3:$CZ$3,1,ROW()-1))=TRIM($BZ29),INDEX('Part 2'!$BJ$243:$CZ$243,1,ROW()-1),"CHECK"))} -> 60 | CC29: =IF(OR($BY29="",$CB29="CHECK"),"",ROUND($CA29-$CB29,2)) -> 0 | CD29: {=IF($BY29="","",IF(TRIM(INDEX('Part 2'!$BJ$3:$CZ$3,1,ROW()-1))=TRIM($BZ29),INDEX('Part 2'!$BJ$33:$CZ$33,1,ROW()-1),"CHECK"))} -> 60
A30: INDICA-134A-SUBROS | B30: PC-86036 | C30: 656 | D30: {=IF($A30="","",IF(TRIM(INDEX('Part 1'!$F$3:$CZ$3,1,ROW()-1))=TRIM($A30),INDEX('Part 1'!$F$386:$CZ$386,1,ROW()-1),"CHECK"))} -> 650 | E30: =IF(OR($A30="",$D30="CHECK",$D30=""),"",$C30-$D30) -> 6 | F30: {=IF($A30="","",IF(TRIM(INDEX('Part 1'!$F$3:$CZ$3,1,ROW()-1))=TRIM($A30),INDEX('Part 1'!$F$38:$CZ$38,1,ROW()-1),"CHECK"))} -> 1000 | J30: Opel | K30: PC-052R | L30: 102 | M30: {=IF($J30="","",IF(TRIM(INDEX('Part 1'!$CS$3:$EQ$3,1,ROW()-1))=TRIM($J30),INDEX('Part 1'!$CS$386:$EQ$386,1,ROW()-1),"CHECK"))} -> 102 | N30: =IF(OR($J30="",$M30="CHECK",$M30=""),"",$L30-$M30) -> 0 | O30: {=IF($J30="","",IF(TRIM(INDEX('Part 1'!$CS$3:$EQ$3,1,ROW()-1))=TRIM($J30),INDEX('Part 1'!$CS$38:$EQ$38,1,ROW()-1),"CHECK"))} -> 312 | BJ30: ESTILO | BK30: PC-E408 | BL30: 0 | BM30: {=IF($BJ30="","",IF(TRIM(INDEX('Part 2'!$F$3:$AS$3,1,ROW()-1))=TRIM($BJ30),INDEX('Part 2'!$F$243:$AS$243,1,ROW()-1),"CHECK"))} -> 0 | BN30: =IF(OR($BJ30="",$BM30="CHECK",$BM30=""),"",ROUND($BL30-$BM30,2)) -> 0 | BO30: {=IF($BJ30="","",IF(TRIM(INDEX('Part 2'!$F$3:$AS$3,1,ROW()-1))=TRIM($BJ30),INDEX('Part 2'!$F$33:$AS$33,1,ROW()-1),"CHECK"))} -> 0 | BP30: ESTILO | BY30: MAGNETIC COIL HYUNDAI ACCENT CRD | BZ30: SD-1011A | CA30: 60 | CB30: {=IF($BY30="","",IF(TRIM(INDEX('Part 2'!$BJ$3:$CZ$3,1,ROW()-1))=TRIM($BZ30),INDEX('Part 2'!$BJ$243:$CZ$243,1,ROW()-1),"CHECK"))} -> 60 | CC30: =IF(OR($BY30="",$CB30="CHECK"),"",ROUND($CA30-$CB30,2)) -> 0 | CD30: {=IF($BY30="","",IF(TRIM(INDEX('Part 2'!$BJ$3:$CZ$3,1,ROW()-1))=TRIM($BZ30),INDEX('Part 2'!$BJ$33:$CZ$33,1,ROW()-1),"CHECK"))} -> 60
A31: Indigo | B31: PC-86237 | C31: 160 | D31: {=IF($A31="","",IF(TRIM(INDEX('Part 1'!$F$3:$CZ$3,1,ROW()-1))=TRIM($A31),INDEX('Part 1'!$F$386:$CZ$386,1,ROW()-1),"CHECK"))} -> 165 | E31: =IF(OR($A31="",$D31="CHECK",$D31=""),"",$C31-$D31) -> -5 | F31: {=IF($A31="","",IF(TRIM(INDEX('Part 1'!$F$3:$CZ$3,1,ROW()-1))=TRIM($A31),INDEX('Part 1'!$F$38:$CZ$38,1,ROW()-1),"CHECK"))} -> 300 | J31: Opel Corsa | K31: PC-8096 | L31: 18 | M31: {=IF($J31="","",IF(TRIM(INDEX('Part 1'!$CS$3:$EQ$3,1,ROW()-1))=TRIM($J31),INDEX('Part 1'!$CS$386:$EQ$386,1,ROW()-1),"CHECK"))} -> 18 | N31: =IF(OR($J31="",$M31="CHECK",$M31=""),"",$L31-$M31) -> 0 | O31: {=IF($J31="","",IF(TRIM(INDEX('Part 1'!$CS$3:$EQ$3,1,ROW()-1))=TRIM($J31),INDEX('Part 1'!$CS$38:$EQ$38,1,ROW()-1),"CHECK"))} -> 108 | BJ31: INNOVA | BK31: PC-E567 | BL31: 0 | BM31: {=IF($BJ31="","",IF(TRIM(INDEX('Part 2'!$F$3:$AS$3,1,ROW()-1))=TRIM($BJ31),INDEX('Part 2'!$F$243:$AS$243,1,ROW()-1),"CHECK"))} -> 0 | BN31: =IF(OR($BJ31="",$BM31="CHECK",$BM31=""),"",ROUND($BL31-$BM31,2)) -> 0 | BO31: {=IF($BJ31="","",IF(TRIM(INDEX('Part 2'!$F$3:$AS$3,1,ROW()-1))=TRIM($BJ31),INDEX('Part 2'!$F$33:$AS$33,1,ROW()-1),"CHECK"))} -> 0 | BP31: INNOVA | BY31: PULLEY PULL HYUNDAI ACCENT CRD | BZ31: SD-1011B | CA31: 48 | CB31: {=IF($BY31="","",IF(TRIM(INDEX('Part 2'!$BJ$3:$CZ$3,1,ROW()-1))=TRIM($BZ31),INDEX('Part 2'!$BJ$243:$CZ$243,1,ROW()-1),"CHECK"))} -> 48 | CC31: =IF(OR($BY31="",$CB31="CHECK"),"",ROUND($CA31-$CB31,2)) -> 0 | CD31: {=IF($BY31="","",IF(TRIM(INDEX('Part 2'!$BJ$3:$CZ$3,1,ROW()-1))=TRIM($BZ31),INDEX('Part 2'!$BJ$33:$CZ$33,1,ROW()-1),"CHECK"))} -> 48
A32: INNOVA | B32: PC-86046 | C32: 500 | D32: {=IF($A32="","",IF(TRIM(INDEX('Part 1'!$F$3:$CZ$3,1,ROW()-1))=TRIM($A32),INDEX('Part 1'!$F$386:$CZ$386,1,ROW()-1),"CHECK"))} -> 500 | E32: =IF(OR($A32="",$D32="CHECK",$D32=""),"",$C32-$D32) -> 0 | F32: {=IF($A32="","",IF(TRIM(INDEX('Part 1'!$F$3:$CZ$3,1,ROW()-1))=TRIM($A32),INDEX('Part 1'!$F$38:$CZ$38,1,ROW()-1),"CHECK"))} -> 500 | J32: Optra | K32: PC-210 | L32: 36 | M32: {=IF($J32="","",IF(TRIM(INDEX('Part 1'!$CS$3:$EQ$3,1,ROW()-1))=TRIM($J32),INDEX('Part 1'!$CS$386:$EQ$386,1,ROW()-1),"CHECK"))} -> 36 | N32: =IF(OR($J32="",$M32="CHECK",$M32=""),"",$L32-$M32) -> 0 | O32: {=IF($J32="","",IF(TRIM(INDEX('Part 1'!$CS$3:$EQ$3,1,ROW()-1))=TRIM($J32),INDEX('Part 1'!$CS$38:$EQ$38,1,ROW()-1),"CHECK"))} -> 216 | BJ32: SWIFT | BK32: PC-E404 | BL32: 0 | BM32: {=IF($BJ32="","",IF(TRIM(INDEX('Part 2'!$F$3:$AS$3,1,ROW()-1))=TRIM($BJ32),INDEX('Part 2'!$F$243:$AS$243,1,ROW()-1),"CHECK"))} -> 0 | BN32: =IF(OR($BJ32="",$BM32="CHECK",$BM32=""),"",ROUND($BL32-$BM32,2)) -> 0 | BO32: {=IF($BJ32="","",IF(TRIM(INDEX('Part 2'!$F$3:$AS$3,1,ROW()-1))=TRIM($BJ32),INDEX('Part 2'!$F$33:$AS$33,1,ROW()-1),"CHECK"))} -> 0 | BP32: (none - code shared, see setup) | BY32: MAGNETIC COIL TOYOTA SCORPIO II | BZ32: SD-1012 | CA32: 60 | CB32: {=IF($BY32="","",IF(TRIM(INDEX('Part 2'!$BJ$3:$CZ$3,1,ROW()-1))=TRIM($BZ32),INDEX('Part 2'!$BJ$243:$CZ$243,1,ROW()-1),"CHECK"))} -> 60 | CC32: =IF(OR($BY32="",$CB32="CHECK"),"",ROUND($CA32-$CB32,2)) -> 0 | CD32: {=IF($BY32="","",IF(TRIM(INDEX('Part 2'!$BJ$3:$CZ$3,1,ROW()-1))=TRIM($BZ32),INDEX('Part 2'!$BJ$33:$CZ$33,1,ROW()-1),"CHECK"))} -> 60
A33: LANCER | B33: PC-86246B | C33: 150 | D33: {=IF($A33="","",IF(TRIM(INDEX('Part 1'!$F$3:$CZ$3,1,ROW()-1))=TRIM($A33),INDEX('Part 1'!$F$386:$CZ$386,1,ROW()-1),"CHECK"))} -> 150 | E33: =IF(OR($A33="",$D33="CHECK",$D33=""),"",$C33-$D33) -> 0 | F33: {=IF($A33="","",IF(TRIM(INDEX('Part 1'!$F$3:$CZ$3,1,ROW()-1))=TRIM($A33),INDEX('Part 1'!$F$38:$CZ$38,1,ROW()-1),"CHECK"))} -> 150 | J33: Palio | K33: PC-054 | L33: 78 | M33: {=IF($J33="","",IF(TRIM(INDEX('Part 1'!$CS$3:$EQ$3,1,ROW()-1))=TRIM($J33),INDEX('Part 1'!$CS$386:$EQ$386,1,ROW()-1),"CHECK"))} -> 78 | N33: =IF(OR($J33="",$M33="CHECK",$M33=""),"",$L33-$M33) -> 0 | O33: {=IF($J33="","",IF(TRIM(INDEX('Part 1'!$CS$3:$EQ$3,1,ROW()-1))=TRIM($J33),INDEX('Part 1'!$CS$38:$EQ$38,1,ROW()-1),"CHECK"))} -> 114 | BJ33: SCORPIO | BK33: PC-E039 | BL33: 60 | BM33: {=IF($BJ33="","",IF(TRIM(INDEX('Part 2'!$F$3:$AS$3,1,ROW()-1))=TRIM($BJ33),INDEX('Part 2'!$F$243:$AS$243,1,ROW()-1),"CHECK"))} -> 60 | BN33: =IF(OR($BJ33="",$BM33="CHECK",$BM33=""),"",ROUND($BL33-$BM33,2)) -> 0 | BO33: {=IF($BJ33="","",IF(TRIM(INDEX('Part 2'!$F$3:$AS$3,1,ROW()-1))=TRIM($BJ33),INDEX('Part 2'!$F$33:$AS$33,1,ROW()-1),"CHECK"))} -> 60 | BP33: SCORPIO | BY33: PULLEY PULL TOYOTA SCORPIO II | BZ33: SD-1012A | CA33: 60 | CB33: {=IF($BY33="","",IF(TRIM(INDEX('Part 2'!$BJ$3:$CZ$3,1,ROW()-1))=TRIM($BZ33),INDEX('Part 2'!$BJ$243:$CZ$243,1,ROW()-1),"CHECK"))} -> 60 | CC33: =IF(OR($BY33="",$CB33="CHECK"),"",ROUND($CA33-$CB33,2)) -> 0 | CD33: {=IF($BY33="","",IF(TRIM(INDEX('Part 2'!$BJ$3:$CZ$3,1,ROW()-1))=TRIM($BZ33),INDEX('Part 2'!$BJ$33:$CZ$33,1,ROW()-1),"CHECK"))} -> 60
A34: LAURA | B34: PC-86026B | C34: 101 | D34: {=IF($A34="","",IF(TRIM(INDEX('Part 1'!$F$3:$CZ$3,1,ROW()-1))=TRIM($A34),INDEX('Part 1'!$F$386:$CZ$386,1,ROW()-1),"CHECK"))} -> 100 | E34: =IF(OR($A34="",$D34="CHECK",$D34=""),"",$C34-$D34) -> 1 | F34: {=IF($A34="","",IF(TRIM(INDEX('Part 1'!$F$3:$CZ$3,1,ROW()-1))=TRIM($A34),INDEX('Part 1'!$F$38:$CZ$38,1,ROW()-1),"CHECK"))} -> 100 | J34: QUALIS | K34: PC-8904R | L34: 78 | M34: {=IF($J34="","",IF(TRIM(INDEX('Part 1'!$CS$3:$EQ$3,1,ROW()-1))=TRIM($J34),INDEX('Part 1'!$CS$386:$EQ$386,1,ROW()-1),"CHECK"))} -> 78 | N34: =IF(OR($J34="",$M34="CHECK",$M34=""),"",$L34-$M34) -> 0 | O34: {=IF($J34="","",IF(TRIM(INDEX('Part 1'!$CS$3:$EQ$3,1,ROW()-1))=TRIM($J34),INDEX('Part 1'!$CS$38:$EQ$38,1,ROW()-1),"CHECK"))} -> 77 | BJ34: M-HAWK | BK34: PC-E502 | BL34: 126 | BM34: {=IF($BJ34="","",IF(TRIM(INDEX('Part 2'!$F$3:$AS$3,1,ROW()-1))=TRIM($BJ34),INDEX('Part 2'!$F$243:$AS$243,1,ROW()-1),"CHECK"))} -> 102 | BN34: =IF(OR($BJ34="",$BM34="CHECK",$BM34=""),"",ROUND($BL34-$BM34,2)) -> 24 | BO34: {=IF($BJ34="","",IF(TRIM(INDEX('Part 2'!$F$3:$AS$3,1,ROW()-1))=TRIM($BJ34),INDEX('Part 2'!$F$33:$AS$33,1,ROW()-1),"CHECK"))} -> 102 | BP34: M-HAWK | BY34: MAGNETIC COIL TOYOTA INNOVA S/AC | BZ34: SD-1012B | CA34: 60 | CB34: {=IF($BY34="","",IF(TRIM(INDEX('Part 2'!$BJ$3:$CZ$3,1,ROW()-1))=TRIM($BZ34),INDEX('Part 2'!$BJ$243:$CZ$243,1,ROW()-1),"CHECK"))} -> 60 | CC34: =IF(OR($BY34="",$CB34="CHECK"),"",ROUND($CA34-$CB34,2)) -> 0 | CD34: {=IF($BY34="","",IF(TRIM(INDEX('Part 2'!$BJ$3:$CZ$3,1,ROW()-1))=TRIM($BZ34),INDEX('Part 2'!$BJ$33:$CZ$33,1,ROW()-1),"CHECK"))} -> 60
A35: LOGAN-PAD | B35: PC-86087 | C35: 35 | D35: {=IF($A35="","",IF(TRIM(INDEX('Part 1'!$F$3:$CZ$3,1,ROW()-1))=TRIM($A35),INDEX('Part 1'!$F$386:$CZ$386,1,ROW()-1),"CHECK"))} -> 35 | E35: =IF(OR($A35="",$D35="CHECK",$D35=""),"",$C35-$D35) -> 0 | F35: {=IF($A35="","",IF(TRIM(INDEX('Part 1'!$F$3:$CZ$3,1,ROW()-1))=TRIM($A35),INDEX('Part 1'!$F$38:$CZ$38,1,ROW()-1),"CHECK"))} -> 75 | J35: Safari | K35: PC-8083 | L35: 108 | M35: {=IF($J35="","",IF(TRIM(INDEX('Part 1'!$CS$3:$EQ$3,1,ROW()-1))=TRIM($J35),INDEX('Part 1'!$CS$386:$EQ$386,1,ROW()-1),"CHECK"))} -> 108 | N35: =IF(OR($J35="",$M35="CHECK",$M35=""),"",$L35-$M35) -> 0 | O35: {=IF($J35="","",IF(TRIM(INDEX('Part 1'!$CS$3:$EQ$3,1,ROW()-1))=TRIM($J35),INDEX('Part 1'!$CS$38:$EQ$38,1,ROW()-1),"CHECK"))} -> 167 | BJ35: M-BENZ W203 | BK35: PC-E429 | BL35: 9 | BM35: {=IF($BJ35="","",IF(TRIM(INDEX('Part 2'!$F$3:$AS$3,1,ROW()-1))=TRIM($BJ35),INDEX('Part 2'!$F$243:$AS$243,1,ROW()-1),"CHECK"))} -> 9 | BN35: =IF(OR($BJ35="",$BM35="CHECK",$BM35=""),"",ROUND($BL35-$BM35,2)) -> 0 | BO35: {=IF($BJ35="","",IF(TRIM(INDEX('Part 2'!$F$3:$AS$3,1,ROW()-1))=TRIM($BJ35),INDEX('Part 2'!$F$33:$AS$33,1,ROW()-1),"CHECK"))} -> 32 | BP35: M-BENZ W203 | BY35: MAGNETIC COIL TATA SUMO SD7H13 | BZ35: SD-1014 | CA35: 120 | CB35: {=IF($BY35="","",IF(TRIM(INDEX('Part 2'!$BJ$3:$CZ$3,1,ROW()-1))=TRIM($BZ35),INDEX('Part 2'!$BJ$243:$CZ$243,1,ROW()-1),"CHECK"))} -> 120 | CC35: =IF(OR($BY35="",$CB35="CHECK"),"",ROUND($CA35-$CB35,2)) -> 0 | CD35: {=IF($BY35="","",IF(TRIM(INDEX('Part 2'!$BJ$3:$CZ$3,1,ROW()-1))=TRIM($BZ35),INDEX('Part 2'!$BJ$33:$CZ$33,1,ROW()-1),"CHECK"))} -> 120
A36: Maruti Car-800 MPFI | B36: PC-86092 | C36: 725 | D36: {=IF($A36="","",IF(TRIM(INDEX('Part 1'!$F$3:$CZ$3,1,ROW()-1))=TRIM($A36),INDEX('Part 1'!$F$386:$CZ$386,1,ROW()-1),"CHECK"))} -> 700 | E36: =IF(OR($A36="",$D36="CHECK",$D36=""),"",$C36-$D36) -> 25 | F36: {=IF($A36="","",IF(TRIM(INDEX('Part 1'!$F$3:$CZ$3,1,ROW()-1))=TRIM($A36),INDEX('Part 1'!$F$38:$CZ$38,1,ROW()-1),"CHECK"))} -> 1000 | J36: Santro Xing | K36: PC-250R | L36: 174 | M36: {=IF($J36="","",IF(TRIM(INDEX('Part 1'!$CS$3:$EQ$3,1,ROW()-1))=TRIM($J36),INDEX('Part 1'!$CS$386:$EQ$386,1,ROW()-1),"CHECK"))} -> 174 | N36: =IF(OR($J36="",$M36="CHECK",$M36=""),"",$L36-$M36) -> 0 | O36: {=IF($J36="","",IF(TRIM(INDEX('Part 1'!$CS$3:$EQ$3,1,ROW()-1))=TRIM($J36),INDEX('Part 1'!$CS$38:$EQ$38,1,ROW()-1),"CHECK"))} -> 174 | BJ36: M-BENZ W211 | BK36: PC-E431 | BL36: 9 | BM36: {=IF($BJ36="","",IF(TRIM(INDEX('Part 2'!$F$3:$AS$3,1,ROW()-1))=TRIM($BJ36),INDEX('Part 2'!$F$243:$AS$243,1,ROW()-1),"CHECK"))} -> 9 | BN36: =IF(OR($BJ36="",$BM36="CHECK",$BM36=""),"",ROUND($BL36-$BM36,2)) -> 0 | BO36: {=IF($BJ36="","",IF(TRIM(INDEX('Part 2'!$F$3:$AS$3,1,ROW()-1))=TRIM($BJ36),INDEX('Part 2'!$F$33:$AS$33,1,ROW()-1),"CHECK"))} -> 33 | BP36: M-BENZ W211 | BY36: MAGNETIC COIL TOYOTA COROLLA | BZ36: SD-1015 | CA36: 60 | CB36: {=IF($BY36="","",IF(TRIM(INDEX('Part 2'!$BJ$3:$CZ$3,1,ROW()-1))=TRIM($BZ36),INDEX('Part 2'!$BJ$243:$CZ$243,1,ROW()-1),"CHECK"))} -> 60 | CC36: =IF(OR($BY36="",$CB36="CHECK"),"",ROUND($CA36-$CB36,2)) -> 0 | CD36: {=IF($BY36="","",IF(TRIM(INDEX('Part 2'!$BJ$3:$CZ$3,1,ROW()-1))=TRIM($BZ36),INDEX('Part 2'!$BJ$33:$CZ$33,1,ROW()-1),"CHECK"))} -> 60
A37: MATIZ | B37: PC-86042 | C37: 25 | D37: {=IF($A37="","",IF(TRIM(INDEX('Part 1'!$F$3:$CZ$3,1,ROW()-1))=TRIM($A37),INDEX('Part 1'!$F$386:$CZ$386,1,ROW()-1),"CHECK"))} -> 25 | E37: =IF(OR($A37="",$D37="CHECK",$D37=""),"",$C37-$D37) -> 0 | F37: {=IF($A37="","",IF(TRIM(INDEX('Part 1'!$F$3:$CZ$3,1,ROW()-1))=TRIM($A37),INDEX('Part 1'!$F$38:$CZ$38,1,ROW()-1),"CHECK"))} -> 25 | J37: Scorpio | K37: PC-7157 | L37: 182 | M37: {=IF($J37="","",IF(TRIM(INDEX('Part 1'!$CS$3:$EQ$3,1,ROW()-1))=TRIM($J37),INDEX('Part 1'!$CS$386:$EQ$386,1,ROW()-1),"CHECK"))} -> 182 | N37: =IF(OR($J37="",$M37="CHECK",$M37=""),"",$L37-$M37) -> 0 | O37: {=IF($J37="","",IF(TRIM(INDEX('Part 1'!$CS$3:$EQ$3,1,ROW()-1))=TRIM($J37),INDEX('Part 1'!$CS$38:$EQ$38,1,ROW()-1),"CHECK"))} -> 134 | BJ37: M-BENZ W210 | BK37: PC-E372 | BL37: 5 | BM37: {=IF($BJ37="","",IF(TRIM(INDEX('Part 2'!$F$3:$AS$3,1,ROW()-1))=TRIM($BJ37),INDEX('Part 2'!$F$243:$AS$243,1,ROW()-1),"CHECK"))} -> 1 | BN37: =IF(OR($BJ37="",$BM37="CHECK",$BM37=""),"",ROUND($BL37-$BM37,2)) -> 4 | BO37: {=IF($BJ37="","",IF(TRIM(INDEX('Part 2'!$F$3:$AS$3,1,ROW()-1))=TRIM($BJ37),INDEX('Part 2'!$F$33:$AS$33,1,ROW()-1),"CHECK"))} -> 33 | BP37: M-BENZ W210 | BY37: MAGNETIC COIL OL-FI | BZ37: SD-1018A | CA37: 60 | CB37: {=IF($BY37="","",IF(TRIM(INDEX('Part 2'!$BJ$3:$CZ$3,1,ROW()-1))=TRIM($BZ37),INDEX('Part 2'!$BJ$243:$CZ$243,1,ROW()-1),"CHECK"))} -> 60 | CC37: =IF(OR($BY37="",$CB37="CHECK"),"",ROUND($CA37-$CB37,2)) -> 0 | CD37: {=IF($BY37="","",IF(TRIM(INDEX('Part 2'!$BJ$3:$CZ$3,1,ROW()-1))=TRIM($BZ37),INDEX('Part 2'!$BJ$33:$CZ$33,1,ROW()-1),"CHECK"))} -> 60
A38: OPEL CORSA | B38: PC-86038 | C38: 55 | D38: {=IF($A38="","",IF(TRIM(INDEX('Part 1'!$F$3:$CZ$3,1,ROW()-1))=TRIM($A38),INDEX('Part 1'!$F$386:$CZ$386,1,ROW()-1),"CHECK"))} -> 55 | E38: =IF(OR($A38="",$D38="CHECK",$D38=""),"",$C38-$D38) -> 0 | F38: {=IF($A38="","",IF(TRIM(INDEX('Part 1'!$F$3:$CZ$3,1,ROW()-1))=TRIM($A38),INDEX('Part 1'!$F$38:$CZ$38,1,ROW()-1),"CHECK"))} -> 0 | J38: SANTRO | K38: PC-144R | L38: 186 | M38: {=IF($J38="","",IF(TRIM(INDEX('Part 1'!$CS$3:$EQ$3,1,ROW()-1))=TRIM($J38),INDEX('Part 1'!$CS$386:$EQ$386,1,ROW()-1),"CHECK"))} -> 250 | N38: =IF(OR($J38="",$M38="CHECK",$M38=""),"",$L38-$M38) -> -64 | O38: {=IF($J38="","",IF(TRIM(INDEX('Part 1'!$CS$3:$EQ$3,1,ROW()-1))=TRIM($J38),INDEX('Part 1'!$CS$38:$EQ$38,1,ROW()-1),"CHECK"))} -> 150 | BJ38: M-BENZ W220 | BK38: PC-E426 | BL38: 4 | BM38: {=IF($BJ38="","",IF(TRIM(INDEX('Part 2'!$F$3:$AS$3,1,ROW()-1))=TRIM($BJ38),INDEX('Part 2'!$F$243:$AS$243,1,ROW()-1),"CHECK"))} -> 5 | BN38: =IF(OR($BJ38="",$BM38="CHECK",$BM38=""),"",ROUND($BL38-$BM38,2)) -> -1 | BO38: {=IF($BJ38="","",IF(TRIM(INDEX('Part 2'!$F$3:$AS$3,1,ROW()-1))=TRIM($BJ38),INDEX('Part 2'!$F$33:$AS$33,1,ROW()-1),"CHECK"))} -> 32 | BP38: M-BENZ W220 | BY38: PULLEY -PL-INO-S | BZ38: SD-1019 | CA38: 60 | CB38: {=IF($BY38="","",IF(TRIM(INDEX('Part 2'!$BJ$3:$CZ$3,1,ROW()-1))=TRIM($BZ38),INDEX('Part 2'!$BJ$243:$CZ$243,1,ROW()-1),"CHECK"))} -> 60 | CC38: =IF(OR($BY38="",$CB38="CHECK"),"",ROUND($CA38-$CB38,2)) -> 0 | CD38: {=IF($BY38="","",IF(TRIM(INDEX('Part 2'!$BJ$3:$CZ$3,1,ROW()-1))=TRIM($BZ38),INDEX('Part 2'!$BJ$33:$CZ$33,1,ROW()-1),"CHECK"))} -> 60
A39: OPEL-ASTRA | B39: PC-86243 | C39: 0 | D39: {=IF($A39="","",IF(TRIM(INDEX('Part 1'!$F$3:$CZ$3,1,ROW()-1))=TRIM($A39),INDEX('Part 1'!$F$386:$CZ$386,1,ROW()-1),"CHECK"))} -> 0 | E39: =IF(OR($A39="",$D39="CHECK",$D39=""),"",$C39-$D39) -> 0 | F39: {=IF($A39="","",IF(TRIM(INDEX('Part 1'!$F$3:$CZ$3,1,ROW()-1))=TRIM($A39),INDEX('Part 1'!$F$38:$CZ$38,1,ROW()-1),"CHECK"))} -> 25 | J39: Sk-Coil | K39: PC-7029 | L39: 184 | M39: {=IF($J39="","",IF(TRIM(INDEX('Part 1'!$CS$3:$EQ$3,1,ROW()-1))=TRIM($J39),INDEX('Part 1'!$CS$386:$EQ$386,1,ROW()-1),"CHECK"))} -> 184 | N39: =IF(OR($J39="",$M39="CHECK",$M39=""),"",$L39-$M39) -> 0 | O39: {=IF($J39="","",IF(TRIM(INDEX('Part 1'!$CS$3:$EQ$3,1,ROW()-1))=TRIM($J39),INDEX('Part 1'!$CS$38:$EQ$38,1,ROW()-1),"CHECK"))} -> 304 | BJ39: VISTA BEHR | BK39: PC-E001 | BL39: 104 | BM39: {=IF($BJ39="","",IF(TRIM(INDEX('Part 2'!$F$3:$AS$3,1,ROW()-1))=TRIM($BJ39),INDEX('Part 2'!$F$243:$AS$243,1,ROW()-1),"CHECK"))} -> 106 | BN39: =IF(OR($BJ39="",$BM39="CHECK",$BM39=""),"",ROUND($BL39-$BM39,2)) -> -2 | BO39: {=IF($BJ39="","",IF(TRIM(INDEX('Part 2'!$F$3:$AS$3,1,ROW()-1))=TRIM($BJ39),INDEX('Part 2'!$F$33:$AS$33,1,ROW()-1),"CHECK"))} -> 358 | BP39: VISTA BEHR | BY39: MAGNETIC COIL MC-INO-B | BZ39: SD-1020 | CA39: 120 | CB39: {=IF($BY39="","",IF(TRIM(INDEX('Part 2'!$BJ$3:$CZ$3,1,ROW()-1))=TRIM($BZ39),INDEX('Part 2'!$BJ$243:$CZ$243,1,ROW()-1),"CHECK"))} -> 120 | CC39: =IF(OR($BY39="",$CB39="CHECK"),"",ROUND($CA39-$CB39,2)) -> 0 | CD39: {=IF($BY39="","",IF(TRIM(INDEX('Part 2'!$BJ$3:$CZ$3,1,ROW()-1))=TRIM($BZ39),INDEX('Part 2'!$BJ$33:$CZ$33,1,ROW()-1),"CHECK"))} -> 120
A40: OPTRA | B40: PC-86186 | C40: 20 | D40: {=IF($A40="","",IF(TRIM(INDEX('Part 1'!$F$3:$CZ$3,1,ROW()-1))=TRIM($A40),INDEX('Part 1'!$F$386:$CZ$386,1,ROW()-1),"CHECK"))} -> 20 | E40: =IF(OR($A40="",$D40="CHECK",$D40=""),"",$C40-$D40) -> 0 | F40: {=IF($A40="","",IF(TRIM(INDEX('Part 1'!$F$3:$CZ$3,1,ROW()-1))=TRIM($A40),INDEX('Part 1'!$F$38:$CZ$38,1,ROW()-1),"CHECK"))} -> 75 | J40: Skoda | K40: PC-143R | L40: 275 | M40: {=IF($J40="","",IF(TRIM(INDEX('Part 1'!$CS$3:$EQ$3,1,ROW()-1))=TRIM($J40),INDEX('Part 1'!$CS$386:$EQ$386,1,ROW()-1),"CHECK"))} -> 285 | N40: =IF(OR($J40="",$M40="CHECK",$M40=""),"",$L40-$M40) -> -10 | O40: {=IF($J40="","",IF(TRIM(INDEX('Part 1'!$CS$3:$EQ$3,1,ROW()-1))=TRIM($J40),INDEX('Part 1'!$CS$38:$EQ$38,1,ROW()-1),"CHECK"))} -> 327 | BJ40: VISTA | BK40: PC-E401 | BL40: 56 | BM40: {=IF($BJ40="","",IF(TRIM(INDEX('Part 2'!$F$3:$AS$3,1,ROW()-1))=TRIM($BJ40),INDEX('Part 2'!$F$243:$AS$243,1,ROW()-1),"CHECK"))} -> 56 | BN40: =IF(OR($BJ40="",$BM40="CHECK",$BM40=""),"",ROUND($BL40-$BM40,2)) -> 0 | BO40: {=IF($BJ40="","",IF(TRIM(INDEX('Part 2'!$F$3:$AS$3,1,ROW()-1))=TRIM($BJ40),INDEX('Part 2'!$F$33:$AS$33,1,ROW()-1),"CHECK"))} -> 56 | BP40: VISTA | BY40: PULLEY-PL-INO-B | BZ40: SD-1020A | CA40: 60 | CB40: {=IF($BY40="","",IF(TRIM(INDEX('Part 2'!$BJ$3:$CZ$3,1,ROW()-1))=TRIM($BZ40),INDEX('Part 2'!$BJ$243:$CZ$243,1,ROW()-1),"CHECK"))} -> 60 | CC40: =IF(OR($BY40="",$CB40="CHECK"),"",ROUND($CA40-$CB40,2)) -> 0 | CD40: {=IF($BY40="","",IF(TRIM(INDEX('Part 2'!$BJ$3:$CZ$3,1,ROW()-1))=TRIM($BZ40),INDEX('Part 2'!$BJ$33:$CZ$33,1,ROW()-1),"CHECK"))} -> 60
A41: PALIO | B41: PC-86039 | C41: 45 | D41: {=IF($A41="","",IF(TRIM(INDEX('Part 1'!$F$3:$CZ$3,1,ROW()-1))=TRIM($A41),INDEX('Part 1'!$F$386:$CZ$386,1,ROW()-1),"CHECK"))} -> 45 | E41: =IF(OR($A41="",$D41="CHECK",$D41=""),"",$C41-$D41) -> 0 | F41: {=IF($A41="","",IF(TRIM(INDEX('Part 1'!$F$3:$CZ$3,1,ROW()-1))=TRIM($A41),INDEX('Part 1'!$F$38:$CZ$38,1,ROW()-1),"CHECK"))} -> 100 | J41: SONATA | K41: PC-079R | L41: 18 | M41: {=IF($J41="","",IF(TRIM(INDEX('Part 1'!$CS$3:$EQ$3,1,ROW()-1))=TRIM($J41),INDEX('Part 1'!$CS$386:$EQ$386,1,ROW()-1),"CHECK"))} -> 18 | N41: =IF(OR($J41="",$M41="CHECK",$M41=""),"",$L41-$M41) -> 0 | O41: {=IF($J41="","",IF(TRIM(INDEX('Part 1'!$CS$3:$EQ$3,1,ROW()-1))=TRIM($J41),INDEX('Part 1'!$CS$38:$EQ$38,1,ROW()-1),"CHECK"))} -> 108 | BJ41: VERNA | BK41: PC-E428 | BL41: 8 | BM41: {=IF($BJ41="","",IF(TRIM(INDEX('Part 2'!$F$3:$AS$3,1,ROW()-1))=TRIM($BJ41),INDEX('Part 2'!$F$243:$AS$243,1,ROW()-1),"CHECK"))} -> 8 | BN41: =IF(OR($BJ41="",$BM41="CHECK",$BM41=""),"",ROUND($BL41-$BM41,2)) -> 0 | BO41: {=IF($BJ41="","",IF(TRIM(INDEX('Part 2'!$F$3:$AS$3,1,ROW()-1))=TRIM($BJ41),INDEX('Part 2'!$F$33:$AS$33,1,ROW()-1),"CHECK"))} -> 58 | BP41: VERNA | BY41: PLATE CP-INO-B | BZ41: SD-1020B | CA41: 60 | CB41: {=IF($BY41="","",IF(TRIM(INDEX('Part 2'!$BJ$3:$CZ$3,1,ROW()-1))=TRIM($BZ41),INDEX('Part 2'!$BJ$243:$CZ$243,1,ROW()-1),"CHECK"))} -> 60 | CC41: =IF(OR($BY41="",$CB41="CHECK"),"",ROUND($CA41-$CB41,2)) -> 0 | CD41: {=IF($BY41="","",IF(TRIM(INDEX('Part 2'!$BJ$3:$CZ$3,1,ROW()-1))=TRIM($BZ41),INDEX('Part 2'!$BJ$33:$CZ$33,1,ROW()-1),"CHECK"))} -> 60
A42: PALIO STILE | B42: PC-86269 | C42: 0 | D42: {=IF($A42="","",IF(TRIM(INDEX('Part 1'!$F$3:$CZ$3,1,ROW()-1))=TRIM($A42),INDEX('Part 1'!$F$386:$CZ$386,1,ROW()-1),"CHECK"))} -> 0 | E42: =IF(OR($A42="",$D42="CHECK",$D42=""),"",$C42-$D42) -> 0 | F42: {=IF($A42="","",IF(TRIM(INDEX('Part 1'!$F$3:$CZ$3,1,ROW()-1))=TRIM($A42),INDEX('Part 1'!$F$38:$CZ$38,1,ROW()-1),"CHECK"))} -> 0 | J42: Spark | K42: PC-249R | L42: 206 | M42: {=IF($J42="","",IF(TRIM(INDEX('Part 1'!$CS$3:$EQ$3,1,ROW()-1))=TRIM($J42),INDEX('Part 1'!$CS$386:$EQ$386,1,ROW()-1),"CHECK"))} -> 206 | N42: =IF(OR($J42="",$M42="CHECK",$M42=""),"",$L42-$M42) -> 0 | O42: {=IF($J42="","",IF(TRIM(INDEX('Part 1'!$CS$3:$EQ$3,1,ROW()-1))=TRIM($J42),INDEX('Part 1'!$CS$38:$EQ$38,1,ROW()-1),"CHECK"))} -> 254 | BY42: MAGNETIC COIL MC-CRV | BZ42: SD-1021 | CA42: 60 | CB42: {=IF($BY42="","",IF(TRIM(INDEX('Part 2'!$BJ$3:$CZ$3,1,ROW()-1))=TRIM($BZ42),INDEX('Part 2'!$BJ$243:$CZ$243,1,ROW()-1),"CHECK"))} -> 60 | CC42: =IF(OR($BY42="",$CB42="CHECK"),"",ROUND($CA42-$CB42,2)) -> 0 | CD42: {=IF($BY42="","",IF(TRIM(INDEX('Part 2'!$BJ$3:$CZ$3,1,ROW()-1))=TRIM($BZ42),INDEX('Part 2'!$BJ$33:$CZ$33,1,ROW()-1),"CHECK"))} -> 60
A43: QUALIS-FLARE | B43: PC-86234 | C43: 90 | D43: {=IF($A43="","",IF(TRIM(INDEX('Part 1'!$F$3:$CZ$3,1,ROW()-1))=TRIM($A43),INDEX('Part 1'!$F$386:$CZ$386,1,ROW()-1),"CHECK"))} -> 90 | E43: =IF(OR($A43="",$D43="CHECK",$D43=""),"",$C43-$D43) -> 0 | F43: {=IF($A43="","",IF(TRIM(INDEX('Part 1'!$F$3:$CZ$3,1,ROW()-1))=TRIM($A43),INDEX('Part 1'!$F$38:$CZ$38,1,ROW()-1),"CHECK"))} -> 95 | J43: SUMO VECTA | K43: PC-8905R | L43: 22 | M43: {=IF($J43="","",IF(TRIM(INDEX('Part 1'!$CS$3:$EQ$3,1,ROW()-1))=TRIM($J43),INDEX('Part 1'!$CS$386:$EQ$386,1,ROW()-1),"CHECK"))} -> 22 | N43: =IF(OR($J43="",$M43="CHECK",$M43=""),"",$L43-$M43) -> 0 | O43: {=IF($J43="","",IF(TRIM(INDEX('Part 1'!$CS$3:$EQ$3,1,ROW()-1))=TRIM($J43),INDEX('Part 1'!$CS$38:$EQ$38,1,ROW()-1),"CHECK"))} -> 125 | BY43: PULLEY-PL-CRV | BZ43: SD-1021A | CA43: 24 | CB43: {=IF($BY43="","",IF(TRIM(INDEX('Part 2'!$BJ$3:$CZ$3,1,ROW()-1))=TRIM($BZ43),INDEX('Part 2'!$BJ$243:$CZ$243,1,ROW()-1),"CHECK"))} -> 24 | CC43: =IF(OR($BY43="",$CB43="CHECK"),"",ROUND($CA43-$CB43,2)) -> 0 | CD43: {=IF($BY43="","",IF(TRIM(INDEX('Part 2'!$BJ$3:$CZ$3,1,ROW()-1))=TRIM($BZ43),INDEX('Part 2'!$BJ$33:$CZ$33,1,ROW()-1),"CHECK"))} -> 24
A44: Qualis-O Ring | B44: PC-86244 | C44: 255 | D44: {=IF($A44="","",IF(TRIM(INDEX('Part 1'!$F$3:$CZ$3,1,ROW()-1))=TRIM($A44),INDEX('Part 1'!$F$386:$CZ$386,1,ROW()-1),"CHECK"))} -> 255 | E44: =IF(OR($A44="",$D44="CHECK",$D44=""),"",$C44-$D44) -> 0 | F44: {=IF($A44="","",IF(TRIM(INDEX('Part 1'!$F$3:$CZ$3,1,ROW()-1))=TRIM($A44),INDEX('Part 1'!$F$38:$CZ$38,1,ROW()-1),"CHECK"))} -> 255 | J44: Swift | K44: PC-211 | L44: 54 | M44: {=IF($J44="","",IF(TRIM(INDEX('Part 1'!$CS$3:$EQ$3,1,ROW()-1))=TRIM($J44),INDEX('Part 1'!$CS$386:$EQ$386,1,ROW()-1),"CHECK"))} -> 54 | N44: =IF(OR($J44="",$M44="CHECK",$M44=""),"",$L44-$M44) -> 0 | O44: {=IF($J44="","",IF(TRIM(INDEX('Part 1'!$CS$3:$EQ$3,1,ROW()-1))=TRIM($J44),INDEX('Part 1'!$CS$38:$EQ$38,1,ROW()-1),"CHECK"))} -> 406 | BY44: PLATE CP-CRV | BZ44: SD-1021B | CA44: 60 | CB44: {=IF($BY44="","",IF(TRIM(INDEX('Part 2'!$BJ$3:$CZ$3,1,ROW()-1))=TRIM($BZ44),INDEX('Part 2'!$BJ$243:$CZ$243,1,ROW()-1),"CHECK"))} -> 60 | CC44: =IF(OR($BY44="",$CB44="CHECK"),"",ROUND($CA44-$CB44,2)) -> 0 | CD44: {=IF($BY44="","",IF(TRIM(INDEX('Part 2'!$BJ$3:$CZ$3,1,ROW()-1))=TRIM($BZ44),INDEX('Part 2'!$BJ$33:$CZ$33,1,ROW()-1),"CHECK"))} -> 60
A45: Qualis-PAD | B45: PC-86235 | C45: 300 | D45: {=IF($A45="","",IF(TRIM(INDEX('Part 1'!$F$3:$CZ$3,1,ROW()-1))=TRIM($A45),INDEX('Part 1'!$F$386:$CZ$386,1,ROW()-1),"CHECK"))} -> 300 | E45: =IF(OR($A45="",$D45="CHECK",$D45=""),"",$C45-$D45) -> 0 | F45: {=IF($A45="","",IF(TRIM(INDEX('Part 1'!$F$3:$CZ$3,1,ROW()-1))=TRIM($A45),INDEX('Part 1'!$F$38:$CZ$38,1,ROW()-1),"CHECK"))} -> 300 | J45: Tavera | K45: PC-012 | L45: 402 | M45: {=IF($J45="","",IF(TRIM(INDEX('Part 1'!$CS$3:$EQ$3,1,ROW()-1))=TRIM($J45),INDEX('Part 1'!$CS$386:$EQ$386,1,ROW()-1),"CHECK"))} -> 402 | N45: =IF(OR($J45="",$M45="CHECK",$M45=""),"",$L45-$M45) -> 0 | O45: {=IF($J45="","",IF(TRIM(INDEX('Part 1'!$CS$3:$EQ$3,1,ROW()-1))=TRIM($J45),INDEX('Part 1'!$CS$38:$EQ$38,1,ROW()-1),"CHECK"))} -> 402
A46: SAFARI | B46: PC-86238 | C46: 200 | D46: {=IF($A46="","",IF(TRIM(INDEX('Part 1'!$F$3:$CZ$3,1,ROW()-1))=TRIM($A46),INDEX('Part 1'!$F$386:$CZ$386,1,ROW()-1),"CHECK"))} -> 200 | E46: =IF(OR($A46="",$D46="CHECK",$D46=""),"",$C46-$D46) -> 0 | F46: {=IF($A46="","",IF(TRIM(INDEX('Part 1'!$F$3:$CZ$3,1,ROW()-1))=TRIM($A46),INDEX('Part 1'!$F$38:$CZ$38,1,ROW()-1),"CHECK"))} -> 200 | J46: Varna (D) | K46: PC-439R | L46: 132 | M46: {=IF($J46="","",IF(TRIM(INDEX('Part 1'!$CS$3:$EQ$3,1,ROW()-1))=TRIM($J46),INDEX('Part 1'!$CS$386:$EQ$386,1,ROW()-1),"CHECK"))} -> 132 | N46: =IF(OR($J46="",$M46="CHECK",$M46=""),"",$L46-$M46) -> 0 | O46: {=IF($J46="","",IF(TRIM(INDEX('Part 1'!$CS$3:$EQ$3,1,ROW()-1))=TRIM($J46),INDEX('Part 1'!$CS$38:$EQ$38,1,ROW()-1),"CHECK"))} -> 258
A47: SANTRO | B47: PC-86125 | C47: 1000 | D47: {=IF($A47="","",IF(TRIM(INDEX('Part 1'!$F$3:$CZ$3,1,ROW()-1))=TRIM($A47),INDEX('Part 1'!$F$386:$CZ$386,1,ROW()-1),"CHECK"))} -> 1000 | E47: =IF(OR($A47="",$D47="CHECK",$D47=""),"",$C47-$D47) -> 0 | F47: {=IF($A47="","",IF(TRIM(INDEX('Part 1'!$F$3:$CZ$3,1,ROW()-1))=TRIM($A47),INDEX('Part 1'!$F$38:$CZ$38,1,ROW()-1),"CHECK"))} -> 1000 | J47: VISTA (DSL) NEW | K47: PC-451R | L47: 24 | M47: {=IF($J47="","",IF(TRIM(INDEX('Part 1'!$CS$3:$EQ$3,1,ROW()-1))=TRIM($J47),INDEX('Part 1'!$CS$386:$EQ$386,1,ROW()-1),"CHECK"))} -> 24 | N47: =IF(OR($J47="",$M47="CHECK",$M47=""),"",$L47-$M47) -> 0 | O47: {=IF($J47="","",IF(TRIM(INDEX('Part 1'!$CS$3:$EQ$3,1,ROW()-1))=TRIM($J47),INDEX('Part 1'!$CS$38:$EQ$38,1,ROW()-1),"CHECK"))} -> 54
A48: SANTRO (PREMIUM) | B48: PC-868404 | C48: 460 | D48: {=IF($A48="","",IF(TRIM(INDEX('Part 1'!$F$3:$CZ$3,1,ROW()-1))=TRIM($A48),INDEX('Part 1'!$F$386:$CZ$386,1,ROW()-1),"CHECK"))} -> 450 | E48: =IF(OR($A48="",$D48="CHECK",$D48=""),"",$C48-$D48) -> 10 | F48: {=IF($A48="","",IF(TRIM(INDEX('Part 1'!$F$3:$CZ$3,1,ROW()-1))=TRIM($A48),INDEX('Part 1'!$F$38:$CZ$38,1,ROW()-1),"CHECK"))} -> 975 | J48: ZEN R12 | K48: PC-8109R | L48: 54 | M48: {=IF($J48="","",IF(TRIM(INDEX('Part 1'!$CS$3:$EQ$3,1,ROW()-1))=TRIM($J48),INDEX('Part 1'!$CS$386:$EQ$386,1,ROW()-1),"CHECK"))} -> 54 | N48: =IF(OR($J48="",$M48="CHECK",$M48=""),"",$L48-$M48) -> 0 | O48: {=IF($J48="","",IF(TRIM(INDEX('Part 1'!$CS$3:$EQ$3,1,ROW()-1))=TRIM($J48),INDEX('Part 1'!$CS$38:$EQ$38,1,ROW()-1),"CHECK"))} -> 54
A49: Santro-ZING | B49: PC-86239 | C49: 450 | D49: {=IF($A49="","",IF(TRIM(INDEX('Part 1'!$F$3:$CZ$3,1,ROW()-1))=TRIM($A49),INDEX('Part 1'!$F$386:$CZ$386,1,ROW()-1),"CHECK"))} -> 450 | E49: =IF(OR($A49="",$D49="CHECK",$D49=""),"",$C49-$D49) -> 0 | F49: {=IF($A49="","",IF(TRIM(INDEX('Part 1'!$F$3:$CZ$3,1,ROW()-1))=TRIM($A49),INDEX('Part 1'!$F$38:$CZ$38,1,ROW()-1),"CHECK"))} -> 500 | J49: Wagan R / Alto | K49: PC-208 | L49: 456 | M49: {=IF($J49="","",IF(TRIM(INDEX('Part 1'!$CS$3:$EQ$3,1,ROW()-1))=TRIM($J49),INDEX('Part 1'!$CS$386:$EQ$386,1,ROW()-1),"CHECK"))} -> 456 | N49: =IF(OR($J49="",$M49="CHECK",$M49=""),"",$L49-$M49) -> 0 | O49: {=IF($J49="","",IF(TRIM(INDEX('Part 1'!$CS$3:$EQ$3,1,ROW()-1))=TRIM($J49),INDEX('Part 1'!$CS$38:$EQ$38,1,ROW()-1),"CHECK"))} -> 456
A50: SCORPIO | B50: PC-86093 | C50: 300 | D50: {=IF($A50="","",IF(TRIM(INDEX('Part 1'!$F$3:$CZ$3,1,ROW()-1))=TRIM($A50),INDEX('Part 1'!$F$386:$CZ$386,1,ROW()-1),"CHECK"))} -> 300 | E50: =IF(OR($A50="",$D50="CHECK",$D50=""),"",$C50-$D50) -> 0 | F50: {=IF($A50="","",IF(TRIM(INDEX('Part 1'!$F$3:$CZ$3,1,ROW()-1))=TRIM($A50),INDEX('Part 1'!$F$38:$CZ$38,1,ROW()-1),"CHECK"))} -> 300 | J50: Zen Delphi R-12 | K50: PC-050R | L50: 48 | M50: {=IF($J50="","",IF(TRIM(INDEX('Part 1'!$CS$3:$EQ$3,1,ROW()-1))=TRIM($J50),INDEX('Part 1'!$CS$386:$EQ$386,1,ROW()-1),"CHECK"))} -> 48 | N50: =IF(OR($J50="",$M50="CHECK",$M50=""),"",$L50-$M50) -> 0 | O50: {=IF($J50="","",IF(TRIM(INDEX('Part 1'!$CS$3:$EQ$3,1,ROW()-1))=TRIM($J50),INDEX('Part 1'!$CS$38:$EQ$38,1,ROW()-1),"CHECK"))} -> 156
A51: SKODA | B51: PC-86004 | C51: 59 | D51: {=IF($A51="","",IF(TRIM(INDEX('Part 1'!$F$3:$CZ$3,1,ROW()-1))=TRIM($A51),INDEX('Part 1'!$F$386:$CZ$386,1,ROW()-1),"CHECK"))} -> 59 | E51: =IF(OR($A51="",$D51="CHECK",$D51=""),"",$C51-$D51) -> 0 | F51: {=IF($A51="","",IF(TRIM(INDEX('Part 1'!$F$3:$CZ$3,1,ROW()-1))=TRIM($A51),INDEX('Part 1'!$F$38:$CZ$38,1,ROW()-1),"CHECK"))} -> 50 | J51: Zen Delphi R-134a | K51: PC-204-2 | L51: 108 | M51: {=IF($J51="","",IF(TRIM(INDEX('Part 1'!$CS$3:$EQ$3,1,ROW()-1))=TRIM($J51),INDEX('Part 1'!$CS$386:$EQ$386,1,ROW()-1),"CHECK"))} -> 108 | N51: =IF(OR($J51="",$M51="CHECK",$M51=""),"",$L51-$M51) -> 0 | O51: {=IF($J51="","",IF(TRIM(INDEX('Part 1'!$CS$3:$EQ$3,1,ROW()-1))=TRIM($J51),INDEX('Part 1'!$CS$38:$EQ$38,1,ROW()-1),"CHECK"))} -> 108
A52: SPARK | B52: PC-86013 | C52: 0 | D52: {=IF($A52="","",IF(TRIM(INDEX('Part 1'!$F$3:$CZ$3,1,ROW()-1))=TRIM($A52),INDEX('Part 1'!$F$386:$CZ$386,1,ROW()-1),"CHECK"))} -> 0 | E52: =IF(OR($A52="",$D52="CHECK",$D52=""),"",$C52-$D52) -> 0 | F52: {=IF($A52="","",IF(TRIM(INDEX('Part 1'!$F$3:$CZ$3,1,ROW()-1))=TRIM($A52),INDEX('Part 1'!$F$38:$CZ$38,1,ROW()-1),"CHECK"))} -> 0 | J52: Zen R-134-SUBROS | K52: PC-8082 | L52: 14 | M52: {=IF($J52="","",IF(TRIM(INDEX('Part 1'!$CS$3:$EQ$3,1,ROW()-1))=TRIM($J52),INDEX('Part 1'!$CS$386:$EQ$386,1,ROW()-1),"CHECK"))} -> 12 | N52: =IF(OR($J52="",$M52="CHECK",$M52=""),"",$L52-$M52) -> 2 | O52: {=IF($J52="","",IF(TRIM(INDEX('Part 1'!$CS$3:$EQ$3,1,ROW()-1))=TRIM($J52),INDEX('Part 1'!$CS$38:$EQ$38,1,ROW()-1),"CHECK"))} -> 114
A53: Sumo VECTA | B53: PC-86241 | C53: 30 | D53: {=IF($A53="","",IF(TRIM(INDEX('Part 1'!$F$3:$CZ$3,1,ROW()-1))=TRIM($A53),INDEX('Part 1'!$F$386:$CZ$386,1,ROW()-1),"CHECK"))} -> 30 | E53: =IF(OR($A53="",$D53="CHECK",$D53=""),"",$C53-$D53) -> 0 | F53: {=IF($A53="","",IF(TRIM(INDEX('Part 1'!$F$3:$CZ$3,1,ROW()-1))=TRIM($A53),INDEX('Part 1'!$F$38:$CZ$38,1,ROW()-1),"CHECK"))} -> 100
A54: SWIFT | B54: PC-86207 | C54: 300 | D54: {=IF($A54="","",IF(TRIM(INDEX('Part 1'!$F$3:$CZ$3,1,ROW()-1))=TRIM($A54),INDEX('Part 1'!$F$386:$CZ$386,1,ROW()-1),"CHECK"))} -> 300 | E54: =IF(OR($A54="",$D54="CHECK",$D54=""),"",$C54-$D54) -> 0 | F54: {=IF($A54="","",IF(TRIM(INDEX('Part 1'!$F$3:$CZ$3,1,ROW()-1))=TRIM($A54),INDEX('Part 1'!$F$38:$CZ$38,1,ROW()-1),"CHECK"))} -> 300
A55: SX4 | B55: PC-86025 | C55: 0 | D55: {=IF($A55="","",IF(TRIM(INDEX('Part 1'!$F$3:$CZ$3,1,ROW()-1))=TRIM($A55),INDEX('Part 1'!$F$386:$CZ$386,1,ROW()-1),"CHECK"))} -> 0 | E55: =IF(OR($A55="",$D55="CHECK",$D55=""),"",$C55-$D55) -> 0 | F55: {=IF($A55="","",IF(TRIM(INDEX('Part 1'!$F$3:$CZ$3,1,ROW()-1))=TRIM($A55),INDEX('Part 1'!$F$38:$CZ$38,1,ROW()-1),"CHECK"))} -> 0
A56: TRAVERA | B56: PC-86247 | C56: 500 | D56: {=IF($A56="","",IF(TRIM(INDEX('Part 1'!$F$3:$CZ$3,1,ROW()-1))=TRIM($A56),INDEX('Part 1'!$F$386:$CZ$386,1,ROW()-1),"CHECK"))} -> 500 | E56: =IF(OR($A56="",$D56="CHECK",$D56=""),"",$C56-$D56) -> 0 | F56: {=IF($A56="","",IF(TRIM(INDEX('Part 1'!$F$3:$CZ$3,1,ROW()-1))=TRIM($A56),INDEX('Part 1'!$F$38:$CZ$38,1,ROW()-1),"CHECK"))} -> 500
A57: VARNA-PETROL | B57: PC-86027 | C57: 20 | D57: {=IF($A57="","",IF(TRIM(INDEX('Part 1'!$F$3:$CZ$3,1,ROW()-1))=TRIM($A57),INDEX('Part 1'!$F$386:$CZ$386,1,ROW()-1),"CHECK"))} -> 20 | E57: =IF(OR($A57="",$D57="CHECK",$D57=""),"",$C57-$D57) -> 0 | F57: {=IF($A57="","",IF(TRIM(INDEX('Part 1'!$F$3:$CZ$3,1,ROW()-1))=TRIM($A57),INDEX('Part 1'!$F$38:$CZ$38,1,ROW()-1),"CHECK"))} -> 0
A58: VISTA-BEHR | B58: PC-86276 | C58: 91 | D58: {=IF($A58="","",IF(TRIM(INDEX('Part 1'!$F$3:$CZ$3,1,ROW()-1))=TRIM($A58),INDEX('Part 1'!$F$386:$CZ$386,1,ROW()-1),"CHECK"))} -> 90 | E58: =IF(OR($A58="",$D58="CHECK",$D58=""),"",$C58-$D58) -> 1 | F58: {=IF($A58="","",IF(TRIM(INDEX('Part 1'!$F$3:$CZ$3,1,ROW()-1))=TRIM($A58),INDEX('Part 1'!$F$38:$CZ$38,1,ROW()-1),"CHECK"))} -> 100
A59: VOLVO | B59: PC-86255B | C59: 80 | D59: {=IF($A59="","",IF(TRIM(INDEX('Part 1'!$F$3:$CZ$3,1,ROW()-1))=TRIM($A59),INDEX('Part 1'!$F$386:$CZ$386,1,ROW()-1),"CHECK"))} -> 80 | E59: =IF(OR($A59="",$D59="CHECK",$D59=""),"",$C59-$D59) -> 0 | F59: {=IF($A59="","",IF(TRIM(INDEX('Part 1'!$F$3:$CZ$3,1,ROW()-1))=TRIM($A59),INDEX('Part 1'!$F$38:$CZ$38,1,ROW()-1),"CHECK"))} -> 100
A60: WAGON-R / ALTO | B60: PC-86037 | C60: 1000 | D60: {=IF($A60="","",IF(TRIM(INDEX('Part 1'!$F$3:$CZ$3,1,ROW()-1))=TRIM($A60),INDEX('Part 1'!$F$386:$CZ$386,1,ROW()-1),"CHECK"))} -> 1000 | E60: =IF(OR($A60="",$D60="CHECK",$D60=""),"",$C60-$D60) -> 0 | F60: {=IF($A60="","",IF(TRIM(INDEX('Part 1'!$F$3:$CZ$3,1,ROW()-1))=TRIM($A60),INDEX('Part 1'!$F$38:$CZ$38,1,ROW()-1),"CHECK"))} -> 1000
A61: WR / ALTO (PREMIUM) | B61: PC-868412 | C61: 449.35 | D61: {=IF($A61="","",IF(TRIM(INDEX('Part 1'!$F$3:$CZ$3,1,ROW()-1))=TRIM($A61),INDEX('Part 1'!$F$386:$CZ$386,1,ROW()-1),"CHECK"))} -> 430 | E61: =IF(OR($A61="",$D61="CHECK",$D61=""),"",$C61-$D61) -> 19.35 | F61: {=IF($A61="","",IF(TRIM(INDEX('Part 1'!$F$3:$CZ$3,1,ROW()-1))=TRIM($A61),INDEX('Part 1'!$F$38:$CZ$38,1,ROW()-1),"CHECK"))} -> 1092
A62: ZEN DEISAL | B62: PC-86279 | C62: 40 | D62: {=IF($A62="","",IF(TRIM(INDEX('Part 1'!$F$3:$CZ$3,1,ROW()-1))=TRIM($A62),INDEX('Part 1'!$F$386:$CZ$386,1,ROW()-1),"CHECK"))} -> 40 | E62: =IF(OR($A62="",$D62="CHECK",$D62=""),"",$C62-$D62) -> 0 | F62: {=IF($A62="","",IF(TRIM(INDEX('Part 1'!$F$3:$CZ$3,1,ROW()-1))=TRIM($A62),INDEX('Part 1'!$F$38:$CZ$38,1,ROW()-1),"CHECK"))} -> 50
A63: ZEN DELPHI R12 | B63: PC-86270-R12 | C63: 95 | D63: {=IF($A63="","",IF(TRIM(INDEX('Part 1'!$F$3:$CZ$3,1,ROW()-1))=TRIM($A63),INDEX('Part 1'!$F$386:$CZ$386,1,ROW()-1),"CHECK"))} -> 95 | E63: =IF(OR($A63="",$D63="CHECK",$D63=""),"",$C63-$D63) -> 0 | F63: {=IF($A63="","",IF(TRIM(INDEX('Part 1'!$F$3:$CZ$3,1,ROW()-1))=TRIM($A63),INDEX('Part 1'!$F$38:$CZ$38,1,ROW()-1),"CHECK"))} -> 110
A64: ZEN DELPHI R134A | B64: PC-86270R-134A | C64: 135 | D64: {=IF($A64="","",IF(TRIM(INDEX('Part 1'!$F$3:$CZ$3,1,ROW()-1))=TRIM($A64),INDEX('Part 1'!$F$386:$CZ$386,1,ROW()-1),"CHECK"))} -> 135 | E64: =IF(OR($A64="",$D64="CHECK",$D64=""),"",$C64-$D64) -> 0 | F64: {=IF($A64="","",IF(TRIM(INDEX('Part 1'!$F$3:$CZ$3,1,ROW()-1))=TRIM($A64),INDEX('Part 1'!$F$38:$CZ$38,1,ROW()-1),"CHECK"))} -> 125
... A66: ZEN-R12 | B66: PC-86043 | C66: 1110 | D66: {=IF($A66="","",IF(TRIM(INDEX('Part 1'!$F$3:$CZ$3,1,ROW()-1))=TRIM($A66),INDEX('Part 1'!$F$386:$CZ$386,1,ROW()-1),"CHECK"))} -> 1110 | E66: =IF(OR($A66="",$D66="CHECK",$D66=""),"",$C66-$D66) -> 0 | F66: {=IF($A66="","",IF(TRIM(INDEX('Part 1'!$F$3:$CZ$3,1,ROW()-1))=TRIM($A66),INDEX('Part 1'!$F$38:$CZ$38,1,ROW()-1),"CHECK"))} -> 1100
A67: ZEN-R134A | B67: PC-86245 | C67: 400 | D67: {=IF($A67="","",IF(TRIM(INDEX('Part 1'!$F$3:$CZ$3,1,ROW()-1))=TRIM($A67),INDEX('Part 1'!$F$386:$CZ$386,1,ROW()-1),"CHECK"))} -> 400 | E67: =IF(OR($A67="",$D67="CHECK",$D67=""),"",$C67-$D67) -> 0 | F67: {=IF($A67="","",IF(TRIM(INDEX('Part 1'!$F$3:$CZ$3,1,ROW()-1))=TRIM($A67),INDEX('Part 1'!$F$38:$CZ$38,1,ROW()-1),"CHECK"))} -> 400 | H67: F/O
A68: PF/UNI 25X28X26MM | B68: PC-086101 | C68: 0 | D68: {=IF($A68="","",IF(TRIM(INDEX('Part 1'!$F$3:$CZ$3,1,ROW()-1))=TRIM($A68),INDEX('Part 1'!$F$386:$CZ$386,1,ROW()-1),"CHECK"))} -> 0 | E68: =IF(OR($A68="",$D68="CHECK",$D68=""),"",$C68-$D68) -> 0 | F68: {=IF($A68="","",IF(TRIM(INDEX('Part 1'!$F$3:$CZ$3,1,ROW()-1))=TRIM($A68),INDEX('Part 1'!$F$38:$CZ$38,1,ROW()-1),"CHECK"))} -> 0 | H68: N
A69: PF/UNI 25X28X20MM | B69: PC-086102 | C69: 350 | D69: {=IF($A69="","",IF(TRIM(INDEX('Part 1'!$F$3:$CZ$3,1,ROW()-1))=TRIM($A69),INDEX('Part 1'!$F$386:$CZ$386,1,ROW()-1),"CHECK"))} -> 350 | E69: =IF(OR($A69="",$D69="CHECK",$D69=""),"",$C69-$D69) -> 0 | F69: {=IF($A69="","",IF(TRIM(INDEX('Part 1'!$F$3:$CZ$3,1,ROW()-1))=TRIM($A69),INDEX('Part 1'!$F$38:$CZ$38,1,ROW()-1),"CHECK"))} -> 350 | H69: N
A70: PF/UNI 14X14X20MM | B70: "F" | C70: 0 | D70: {=IF($A70="","",IF(TRIM(INDEX('Part 1'!$F$3:$CZ$3,1,ROW()-1))=TRIM($A70),INDEX('Part 1'!$F$386:$CZ$386,1,ROW()-1),"CHECK"))} -> 0 | E70: =IF(OR($A70="",$D70="CHECK",$D70=""),"",$C70-$D70) -> 0 | F70: {=IF($A70="","",IF(TRIM(INDEX('Part 1'!$F$3:$CZ$3,1,ROW()-1))=TRIM($A70),INDEX('Part 1'!$F$38:$CZ$38,1,ROW()-1),"CHECK"))} -> 0
A71: PF/UNI 14X14X20MM | B71: "O" | C71: 0 | D71: {=IF($A71="","",IF(TRIM(INDEX('Part 1'!$F$3:$CZ$3,1,ROW()-1))=TRIM($A71),INDEX('Part 1'!$F$386:$CZ$386,1,ROW()-1),"CHECK"))} -> 0 | E71: =IF(OR($A71="",$D71="CHECK",$D71=""),"",$C71-$D71) -> 0 | F71: {=IF($A71="","",IF(TRIM(INDEX('Part 1'!$F$3:$CZ$3,1,ROW()-1))=TRIM($A71),INDEX('Part 1'!$F$38:$CZ$38,1,ROW()-1),"CHECK"))} -> 0
A72: PF/UNI 14X14X20MM | B72: "F" | C72: 150 | D72: {=IF($A72="","",IF(TRIM(INDEX('Part 1'!$F$3:$CZ$3,1,ROW()-1))=TRIM($A72),INDEX('Part 1'!$F$386:$CZ$386,1,ROW()-1),"CHECK"))} -> 230 | E72: =IF(OR($A72="",$D72="CHECK",$D72=""),"",$C72-$D72) -> -80 | F72: {=IF($A72="","",IF(TRIM(INDEX('Part 1'!$F$3:$CZ$3,1,ROW()-1))=TRIM($A72),INDEX('Part 1'!$F$38:$CZ$38,1,ROW()-1),"CHECK"))} -> 500 | H72: F
A73: PF/UNI 14X14X20MM | B73: "O" | C73: 50 | D73: {=IF($A73="","",IF(TRIM(INDEX('Part 1'!$F$3:$CZ$3,1,ROW()-1))=TRIM($A73),INDEX('Part 1'!$F$386:$CZ$386,1,ROW()-1),"CHECK"))} -> 50 | E73: =IF(OR($A73="",$D73="CHECK",$D73=""),"",$C73-$D73) -> 0 | F73: {=IF($A73="","",IF(TRIM(INDEX('Part 1'!$F$3:$CZ$3,1,ROW()-1))=TRIM($A73),INDEX('Part 1'!$F$38:$CZ$38,1,ROW()-1),"CHECK"))} -> 300 | H73: O
A74: PF/UNI 14X18X16MM | C74: 400 | D74: {=IF($A74="","",IF(TRIM(INDEX('Part 1'!$F$3:$CZ$3,1,ROW()-1))=TRIM($A74),INDEX('Part 1'!$F$386:$CZ$386,1,ROW()-1),"CHECK"))} -> 400 | E74: =IF(OR($A74="",$D74="CHECK",$D74=""),"",$C74-$D74) -> 0 | F74: {=IF($A74="","",IF(TRIM(INDEX('Part 1'!$F$3:$CZ$3,1,ROW()-1))=TRIM($A74),INDEX('Part 1'!$F$38:$CZ$38,1,ROW()-1),"CHECK"))} -> 400 | H74: N
A75: PF/UNI 14X18X20MM | C75: 700 | D75: {=IF($A75="","",IF(TRIM(INDEX('Part 1'!$F$3:$CZ$3,1,ROW()-1))=TRIM($A75),INDEX('Part 1'!$F$386:$CZ$386,1,ROW()-1),"CHECK"))} -> 700 | E75: =IF(OR($A75="",$D75="CHECK",$D75=""),"",$C75-$D75) -> 0 | F75: {=IF($A75="","",IF(TRIM(INDEX('Part 1'!$F$3:$CZ$3,1,ROW()-1))=TRIM($A75),INDEX('Part 1'!$F$38:$CZ$38,1,ROW()-1),"CHECK"))} -> 700 | H75: N
A76: PF/UNI 14X21X16MM | C76: 250 | D76: {=IF($A76="","",IF(TRIM(INDEX('Part 1'!$F$3:$CZ$3,1,ROW()-1))=TRIM($A76),INDEX('Part 1'!$F$386:$CZ$386,1,ROW()-1),"CHECK"))} -> 250 | E76: =IF(OR($A76="",$D76="CHECK",$D76=""),"",$C76-$D76) -> 0 | F76: {=IF($A76="","",IF(TRIM(INDEX('Part 1'!$F$3:$CZ$3,1,ROW()-1))=TRIM($A76),INDEX('Part 1'!$F$38:$CZ$38,1,ROW()-1),"CHECK"))} -> 300 | H76: N
A77: PF/UNI 14X21X20MM | C77: 550 | D77: {=IF($A77="","",IF(TRIM(INDEX('Part 1'!$F$3:$CZ$3,1,ROW()-1))=TRIM($A77),INDEX('Part 1'!$F$386:$CZ$386,1,ROW()-1),"CHECK"))} -> 550 | E77: =IF(OR($A77="",$D77="CHECK",$D77=""),"",$C77-$D77) -> 0 | F77: {=IF($A77="","",IF(TRIM(INDEX('Part 1'!$F$3:$CZ$3,1,ROW()-1))=TRIM($A77),INDEX('Part 1'!$F$38:$CZ$38,1,ROW()-1),"CHECK"))} -> 550 | H77: N
A78: PF/UNI 14X23X16MM | C78: 300 | D78: {=IF($A78="","",IF(TRIM(INDEX('Part 1'!$F$3:$CZ$3,1,ROW()-1))=TRIM($A78),INDEX('Part 1'!$F$386:$CZ$386,1,ROW()-1),"CHECK"))} -> 300 | E78: =IF(OR($A78="",$D78="CHECK",$D78=""),"",$C78-$D78) -> 0 | F78: {=IF($A78="","",IF(TRIM(INDEX('Part 1'!$F$3:$CZ$3,1,ROW()-1))=TRIM($A78),INDEX('Part 1'!$F$38:$CZ$38,1,ROW()-1),"CHECK"))} -> 300 | H78: N
A79: PF/UNI 14X23X20MM | C79: 300 | D79: {=IF($A79="","",IF(TRIM(INDEX('Part 1'!$F$3:$CZ$3,1,ROW()-1))=TRIM($A79),INDEX('Part 1'!$F$386:$CZ$386,1,ROW()-1),"CHECK"))} -> 300 | E79: =IF(OR($A79="",$D79="CHECK",$D79=""),"",$C79-$D79) -> 0 | F79: {=IF($A79="","",IF(TRIM(INDEX('Part 1'!$F$3:$CZ$3,1,ROW()-1))=TRIM($A79),INDEX('Part 1'!$F$38:$CZ$38,1,ROW()-1),"CHECK"))} -> 300 | H79: N
A80: SP/UNI 14X15X22MM (O) | C80: 795 | D80: {=IF($A80="","",IF(TRIM(INDEX('Part 1'!$F$3:$CZ$3,1,ROW()-1))=TRIM($A80),INDEX('Part 1'!$F$386:$CZ$386,1,ROW()-1),"CHECK"))} -> 790 | E80: =IF(OR($A80="",$D80="CHECK",$D80=""),"",$C80-$D80) -> 5 | F80: {=IF($A80="","",IF(TRIM(INDEX('Part 1'!$F$3:$CZ$3,1,ROW()-1))=TRIM($A80),INDEX('Part 1'!$F$38:$CZ$38,1,ROW()-1),"CHECK"))} -> 800 | H80: O
A81: SP/UNI 14X15X22MM (F) | C81: 1465 | D81: {=IF($A81="","",IF(TRIM(INDEX('Part 1'!$F$3:$CZ$3,1,ROW()-1))=TRIM($A81),INDEX('Part 1'!$F$386:$CZ$386,1,ROW()-1),"CHECK"))} -> 1375 | E81: =IF(OR($A81="",$D81="CHECK",$D81=""),"",$C81-$D81) -> 90 | F81: {=IF($A81="","",IF(TRIM(INDEX('Part 1'!$F$3:$CZ$3,1,ROW()-1))=TRIM($A81),INDEX('Part 1'!$F$38:$CZ$38,1,ROW()-1),"CHECK"))} -> 1500 | H81: F
A82: SP/UNI 14X15X26MM (F) | C82: 175 | D82: {=IF($A82="","",IF(TRIM(INDEX('Part 1'!$F$3:$CZ$3,1,ROW()-1))=TRIM($A82),INDEX('Part 1'!$F$386:$CZ$386,1,ROW()-1),"CHECK"))} -> 175 | E82: =IF(OR($A82="",$D82="CHECK",$D82=""),"",$C82-$D82) -> 0 | F82: {=IF($A82="","",IF(TRIM(INDEX('Part 1'!$F$3:$CZ$3,1,ROW()-1))=TRIM($A82),INDEX('Part 1'!$F$38:$CZ$38,1,ROW()-1),"CHECK"))} -> 300 | H82: F
A83: SP/UNI 14X18X22MM (F) | C83: 1095 | D83: {=IF($A83="","",IF(TRIM(INDEX('Part 1'!$F$3:$CZ$3,1,ROW()-1))=TRIM($A83),INDEX('Part 1'!$F$386:$CZ$386,1,ROW()-1),"CHECK"))} -> 1195 | E83: =IF(OR($A83="",$D83="CHECK",$D83=""),"",$C83-$D83) -> -100 | F83: {=IF($A83="","",IF(TRIM(INDEX('Part 1'!$F$3:$CZ$3,1,ROW()-1))=TRIM($A83),INDEX('Part 1'!$F$38:$CZ$38,1,ROW()-1),"CHECK"))} -> 2300 | H83: F
A84: SP/UNI 14X18X26MM (F) | C84: 25 | D84: {=IF($A84="","",IF(TRIM(INDEX('Part 1'!$F$3:$CZ$3,1,ROW()-1))=TRIM($A84),INDEX('Part 1'!$F$386:$CZ$386,1,ROW()-1),"CHECK"))} -> 55 | E84: =IF(OR($A84="",$D84="CHECK",$D84=""),"",$C84-$D84) -> -30 | F84: {=IF($A84="","",IF(TRIM(INDEX('Part 1'!$F$3:$CZ$3,1,ROW()-1))=TRIM($A84),INDEX('Part 1'!$F$38:$CZ$38,1,ROW()-1),"CHECK"))} -> 100 | H84: F
A85: SP/UNI 14X21X22MM (F) | C85: 245 | D85: {=IF($A85="","",IF(TRIM(INDEX('Part 1'!$F$3:$CZ$3,1,ROW()-1))=TRIM($A85),INDEX('Part 1'!$F$386:$CZ$386,1,ROW()-1),"CHECK"))} -> 245 | E85: =IF(OR($A85="",$D85="CHECK",$D85=""),"",$C85-$D85) -> 0 | F85: {=IF($A85="","",IF(TRIM(INDEX('Part 1'!$F$3:$CZ$3,1,ROW()-1))=TRIM($A85),INDEX('Part 1'!$F$38:$CZ$38,1,ROW()-1),"CHECK"))} -> 300 | H85: F
... A92: SP/UNI 14X28X44MM (F) | C92: 35 | D92: {=IF($A92="","",IF(TRIM(INDEX('Part 1'!$F$3:$CZ$3,1,ROW()-1))=TRIM($A92),INDEX('Part 1'!$F$386:$CZ$386,1,ROW()-1),"CHECK"))} -> 35 | E92: =IF(OR($A92="",$D92="CHECK",$D92=""),"",$C92-$D92) -> 0 | F92: {=IF($A92="","",IF(TRIM(INDEX('Part 1'!$F$3:$CZ$3,1,ROW()-1))=TRIM($A92),INDEX('Part 1'!$F$38:$CZ$38,1,ROW()-1),"CHECK"))} -> 100 | H92: F

Sheet Part Summary
A1: PART-WISE CHALLAN QUANTITY SUMMARY
A2: Grouped from CHALLAN column B (part name) and column C (part number). Two quantity bases side by side: D x E (cartons x pcs per carton) and column F (Qty in PCs as typed). Neither is adjusted to match the other.
A4: Part Name | B4: Part Number | C4: Total Qty (DxE) | D4: Total Qty (col F)
B5: LESS 35KG SHORT QTY | C5: {=SUMPRODUCT(--EXACT(CHALLAN!$B$1:$B$16071&"",A5&""),--EXACT(IFERROR(CHALLAN!$C$1:$C$16071&"",""),B5&""),IFERROR(CHALLAN!$D$1:$D$16071*CHALLAN!$E$1:$E$16071,0))} -> 0 | D5: {=SUMPRODUCT(--EXACT(CHALLAN!$B$1:$B$16071&"",A5&""),--EXACT(IFERROR(CHALLAN!$C$1:$C$16071&"",""),B5&""),IFERROR(CHALLAN!$F$1:$F$16071+0,0))} -> 35
B6: RTN EMPTY CAN | C6: {=SUMPRODUCT(--EXACT(CHALLAN!$B$1:$B$16071&"",A6&""),--EXACT(IFERROR(CHALLAN!$C$1:$C$16071&"",""),B6&""),IFERROR(CHALLAN!$D$1:$D$16071*CHALLAN!$E$1:$E$16071,0))} -> 0 | D6: {=SUMPRODUCT(--EXACT(CHALLAN!$B$1:$B$16071&"",A6&""),--EXACT(IFERROR(CHALLAN!$C$1:$C$16071&"",""),B6&""),IFERROR(CHALLAN!$F$1:$F$16071+0,0))} -> 630
B7: RTN EMPTY CANS | C7: {=SUMPRODUCT(--EXACT(CHALLAN!$B$1:$B$16071&"",A7&""),--EXACT(IFERROR(CHALLAN!$C$1:$C$16071&"",""),B7&""),IFERROR(CHALLAN!$D$1:$D$16071*CHALLAN!$E$1:$E$16071,0))} -> 0 | D7: {=SUMPRODUCT(--EXACT(CHALLAN!$B$1:$B$16071&"",A7&""),--EXACT(IFERROR(CHALLAN!$C$1:$C$16071&"",""),B7&""),IFERROR(CHALLAN!$F$1:$F$16071+0,0))} -> 639
B8: TOTAL PAGE-1 | C8: {=SUMPRODUCT(--EXACT(CHALLAN!$B$1:$B$16071&"",A8&""),--EXACT(IFERROR(CHALLAN!$C$1:$C$16071&"",""),B8&""),IFERROR(CHALLAN!$D$1:$D$16071*CHALLAN!$E$1:$E$16071,0))} -> 0 | D8: {=SUMPRODUCT(--EXACT(CHALLAN!$B$1:$B$16071&"",A8&""),--EXACT(IFERROR(CHALLAN!$C$1:$C$16071&"",""),B8&""),IFERROR(CHALLAN!$F$1:$F$16071+0,0))} -> 450
A9: 1 PCS FREE MICROBUS OF GG/297/09-10 DT.03.03.10 | C9: {=SUMPRODUCT(--EXACT(CHALLAN!$B$1:$B$16071&"",A9&""),--EXACT(IFERROR(CHALLAN!$C$1:$C$16071&"",""),B9&""),IFERROR(CHALLAN!$D$1:$D$16071*CHALLAN!$E$1:$E$16071,0))} -> 1 | D9: {=SUMPRODUCT(--EXACT(CHALLAN!$B$1:$B$16071&"",A9&""),--EXACT(IFERROR(CHALLAN!$C$1:$C$16071&"",""),B9&""),IFERROR(CHALLAN!$F$1:$F$16071+0,0))} -> 1
A10: 10" (S) | B10: TS-8805 | C10: {=SUMPRODUCT(--EXACT(CHALLAN!$B$1:$B$16071&"",A10&""),--EXACT(IFERROR(CHALLAN!$C$1:$C$16071&"",""),B10&""),IFERROR(CHALLAN!$D$1:$D$16071*CHALLAN!$E$1:$E$16071,0))} -> 100 | D10: {=SUMPRODUCT(--EXACT(CHALLAN!$B$1:$B$16071&"",A10&""),--EXACT(IFERROR(CHALLAN!$C$1:$C$16071&"",""),B10&""),IFERROR(CHALLAN!$F$1:$F$16071+0,0))} -> 85
A11: 10" (S) BLADE | C11: {=SUMPRODUCT(--EXACT(CHALLAN!$B$1:$B$16071&"",A11&""),--EXACT(IFERROR(CHALLAN!$C$1:$C$16071&"",""),B11&""),IFERROR(CHALLAN!$D$1:$D$16071*CHALLAN!$E$1:$E$16071,0))} -> 110 | D11: {=SUMPRODUCT(--EXACT(CHALLAN!$B$1:$B$16071&"",A11&""),--EXACT(IFERROR(CHALLAN!$C$1:$C$16071&"",""),B11&""),IFERROR(CHALLAN!$F$1:$F$16071+0,0))} -> 110
A12: 10" (S) BLADE 80W | C12: {=SUMPRODUCT(--EXACT(CHALLAN!$B$1:$B$16071&"",A12&""),--EXACT(IFERROR(CHALLAN!$C$1:$C$16071&"",""),B12&""),IFERROR(CHALLAN!$D$1:$D$16071*CHALLAN!$E$1:$E$16071,0))} -> 110 | D12: {=SUMPRODUCT(--EXACT(CHALLAN!$B$1:$B$16071&"",A12&""),--EXACT(IFERROR(CHALLAN!$C$1:$C$16071&"",""),B12&""),IFERROR(CHALLAN!$F$1:$F$16071+0,0))} -> 105
A13: 10" (STRAIGHT) | B13: TST-8801 | C13: {=SUMPRODUCT(--EXACT(CHALLAN!$B$1:$B$16071&"",A13&""),--EXACT(IFERROR(CHALLAN!$C$1:$C$16071&"",""),B13&""),IFERROR(CHALLAN!$D$1:$D$16071*CHALLAN!$E$1:$E$16071,0))} -> 20 | D13: {=SUMPRODUCT(--EXACT(CHALLAN!$B$1:$B$16071&"",A13&""),--EXACT(IFERROR(CHALLAN!$C$1:$C$16071&"",""),B13&""),IFERROR(CHALLAN!$F$1:$F$16071+0,0))} -> 20
A14: 10" S BLADE | C14: {=SUMPRODUCT(--EXACT(CHALLAN!$B$1:$B$16071&"",A14&""),--EXACT(IFERROR(CHALLAN!$C$1:$C$16071&"",""),B14&""),IFERROR(CHALLAN!$D$1:$D$16071*CHALLAN!$E$1:$E$16071,0))} -> 1 | D14: {=SUMPRODUCT(--EXACT(CHALLAN!$B$1:$B$16071&"",A14&""),--EXACT(IFERROR(CHALLAN!$C$1:$C$16071&"",""),B14&""),IFERROR(CHALLAN!$F$1:$F$16071+0,0))} -> 1
A15: 10" S-BLADE | B15: TS-8805 | C15: {=SUMPRODUCT(--EXACT(CHALLAN!$B$1:$B$16071&"",A15&""),--EXACT(IFERROR(CHALLAN!$C$1:$C$16071&"",""),B15&""),IFERROR(CHALLAN!$D$1:$D$16071*CHALLAN!$E$1:$E$16071,0))} -> 40 | D15: {=SUMPRODUCT(--EXACT(CHALLAN!$B$1:$B$16071&"",A15&""),--EXACT(IFERROR(CHALLAN!$C$1:$C$16071&"",""),B15&""),IFERROR(CHALLAN!$F$1:$F$16071+0,0))} -> 40
A16: 10" STRAIGHT | B16: TST-8801 | C16: {=SUMPRODUCT(--EXACT(CHALLAN!$B$1:$B$16071&"",A16&""),--EXACT(IFERROR(CHALLAN!$C$1:$C$16071&"",""),B16&""),IFERROR(CHALLAN!$D$1:$D$16071*CHALLAN!$E$1:$E$16071,0))} -> 290 | D16: {=SUMPRODUCT(--EXACT(CHALLAN!$B$1:$B$16071&"",A16&""),--EXACT(IFERROR(CHALLAN!$C$1:$C$16071&"",""),B16&""),IFERROR(CHALLAN!$F$1:$F$16071+0,0))} -> 105
A17: 10" STRAIGHT BLADE | C17: {=SUMPRODUCT(--EXACT(CHALLAN!$B$1:$B$16071&"",A17&""),--EXACT(IFERROR(CHALLAN!$C$1:$C$16071&"",""),B17&""),IFERROR(CHALLAN!$D$1:$D$16071*CHALLAN!$E$1:$E$16071,0))} -> 100 | D17: {=SUMPRODUCT(--EXACT(CHALLAN!$B$1:$B$16071&"",A17&""),--EXACT(IFERROR(CHALLAN!$C$1:$C$16071&"",""),B17&""),IFERROR(CHALLAN!$F$1:$F$16071+0,0))} -> 100
A18: 10" STRIGHT BLADE 80W | C18: {=SUMPRODUCT(--EXACT(CHALLAN!$B$1:$B$16071&"",A18&""),--EXACT(IFERROR(CHALLAN!$C$1:$C$16071&"",""),B18&""),IFERROR(CHALLAN!$D$1:$D$16071*CHALLAN!$E$1:$E$16071,0))} -> 100 | D18: {=SUMPRODUCT(--EXACT(CHALLAN!$B$1:$B$16071&"",A18&""),--EXACT(IFERROR(CHALLAN!$C$1:$C$16071&"",""),B18&""),IFERROR(CHALLAN!$F$1:$F$16071+0,0))} -> 105
A19: 10"X10 B (ST. BLADE) | B19: TST-8801 | C19: {=SUMPRODUCT(--EXACT(CHALLAN!$B$1:$B$16071&"",A19&""),--EXACT(IFERROR(CHALLAN!$C$1:$C$16071&"",""),B19&""),IFERROR(CHALLAN!$D$1:$D$16071*CHALLAN!$E$1:$E$16071,0))} -> 100 | D19: {=SUMPRODUCT(--EXACT(CHALLAN!$B$1:$B$16071&"",A19&""),--EXACT(IFERROR(CHALLAN!$C$1:$C$16071&"",""),B19&""),IFERROR(CHALLAN!$F$1:$F$16071+0,0))} -> 0
A20: 10"X10 B- (S Blade) | C20: {=SUMPRODUCT(--EXACT(CHALLAN!$B$1:$B$16071&"",A20&""),--EXACT(IFERROR(CHALLAN!$C$1:$C$16071&"",""),B20&""),IFERROR(CHALLAN!$D$1:$D$16071*CHALLAN!$E$1:$E$16071,0))} -> 300 | D20: {=SUMPRODUCT(--EXACT(CHALLAN!$B$1:$B$16071&"",A20&""),--EXACT(IFERROR(CHALLAN!$C$1:$C$16071&"",""),B20&""),IFERROR(CHALLAN!$F$1:$F$16071+0,0))} -> 300
A21: 10"X10 B- (S Blade) | B21: TS-8805 | C21: {=SUMPRODUCT(--EXACT(CHALLAN!$B$1:$B$16071&"",A21&""),--EXACT(IFERROR(CHALLAN!$C$1:$C$16071&"",""),B21&""),IFERROR(CHALLAN!$D$1:$D$16071*CHALLAN!$E$1:$E$16071,0))} -> 100 | D21: {=SUMPRODUCT(--EXACT(CHALLAN!$B$1:$B$16071&"",A21&""),--EXACT(IFERROR(CHALLAN!$C$1:$C$16071&"",""),B21&""),IFERROR(CHALLAN!$F$1:$F$16071+0,0))} -> 100
A22: 10"X10 B- (Straight Blade) | B22: TST-8801 | C22: {=SUMPRODUCT(--EXACT(CHALLAN!$B$1:$B$16071&"",A22&""),--EXACT(IFERROR(CHALLAN!$C$1:$C$16071&"",""),B22&""),IFERROR(CHALLAN!$D$1:$D$16071*CHALLAN!$E$1:$E$16071,0))} -> 410 | D22: {=SUMPRODUCT(--EXACT(CHALLAN!$B$1:$B$16071&"",A22&""),--EXACT(IFERROR(CHALLAN!$C$1:$C$16071&"",""),B22&""),IFERROR(CHALLAN!$F$1:$F$16071+0,0))} -> 410
A23: 11MM | C23: {=SUMPRODUCT(--EXACT(CHALLAN!$B$1:$B$16071&"",A23&""),--EXACT(IFERROR(CHALLAN!$C$1:$C$16071&"",""),B23&""),IFERROR(CHALLAN!$D$1:$D$16071*CHALLAN!$E$1:$E$16071,0))} -> 42000 | D23: {=SUMPRODUCT(--EXACT(CHALLAN!$B$1:$B$16071&"",A23&""),--EXACT(IFERROR(CHALLAN!$C$1:$C$16071&"",""),B23&""),IFERROR(CHALLAN!$F$1:$F$16071+0,0))} -> 41200
A24: 12" (S) | B24: TS-8805-B | C24: {=SUMPRODUCT(--EXACT(CHALLAN!$B$1:$B$16071&"",A24&""),--EXACT(IFERROR(CHALLAN!$C$1:$C$16071&"",""),B24&""),IFERROR(CHALLAN!$D$1:$D$16071*CHALLAN!$E$1:$E$16071,0))} -> 210 | D24: {=SUMPRODUCT(--EXACT(CHALLAN!$B$1:$B$16071&"",A24&""),--EXACT(IFERROR(CHALLAN!$C$1:$C$16071&"",""),B24&""),IFERROR(CHALLAN!$F$1:$F$16071+0,0))} -> 147.5
A25: 12" (S) BLADE 80W | C25: {=SUMPRODUCT(--EXACT(CHALLAN!$B$1:$B$16071&"",A25&""),--EXACT(IFERROR(CHALLAN!$C$1:$C$16071&"",""),B25&""),IFERROR(CHALLAN!$D$1:$D$16071*CHALLAN!$E$1:$E$16071,0))} -> 110 | D25: {=SUMPRODUCT(--EXACT(CHALLAN!$B$1:$B$16071&"",A25&""),--EXACT(IFERROR(CHALLAN!$C$1:$C$16071&"",""),B25&""),IFERROR(CHALLAN!$F$1:$F$16071+0,0))} -> 105
A26: 12" (S) BLADE BEHR | C26: {=SUMPRODUCT(--EXACT(CHALLAN!$B$1:$B$16071&"",A26&""),--EXACT(IFERROR(CHALLAN!$C$1:$C$16071&"",""),B26&""),IFERROR(CHALLAN!$D$1:$D$16071*CHALLAN!$E$1:$E$16071,0))} -> 400 | D26: {=SUMPRODUCT(--EXACT(CHALLAN!$B$1:$B$16071&"",A26&""),--EXACT(IFERROR(CHALLAN!$C$1:$C$16071&"",""),B26&""),IFERROR(CHALLAN!$F$1:$F$16071+0,0))} -> 400
A27: 12" S BLADE | B27: TS-8805-B | C27: {=SUMPRODUCT(--EXACT(CHALLAN!$B$1:$B$16071&"",A27&""),--EXACT(IFERROR(CHALLAN!$C$1:$C$16071&"",""),B27&""),IFERROR(CHALLAN!$D$1:$D$16071*CHALLAN!$E$1:$E$16071,0))} -> 205 | D27: {=SUMPRODUCT(--EXACT(CHALLAN!$B$1:$B$16071&"",A27&""),--EXACT(IFERROR(CHALLAN!$C$1:$C$16071&"",""),B27&""),IFERROR(CHALLAN!$F$1:$F$16071+0,0))} -> 105
A28: 12" S- BLADE | B28: TS-8805-B | C28: {=SUMPRODUCT(--EXACT(CHALLAN!$B$1:$B$16071&"",A28&""),--EXACT(IFERROR(CHALLAN!$C$1:$C$16071&"",""),B28&""),IFERROR(CHALLAN!$D$1:$D$16071*CHALLAN!$E$1:$E$16071,0))} -> 10 | D28: {=SUMPRODUCT(--EXACT(CHALLAN!$B$1:$B$16071&"",A28&""),--EXACT(IFERROR(CHALLAN!$C$1:$C$16071&"",""),B28&""),IFERROR(CHALLAN!$F$1:$F$16071+0,0))} -> 10
A29: 12" STRAIGHT | B29: TST-8801-A | C29: {=SUMPRODUCT(--EXACT(CHALLAN!$B$1:$B$16071&"",A29&""),--EXACT(IFERROR(CHALLAN!$C$1:$C$16071&"",""),B29&""),IFERROR(CHALLAN!$D$1:$D$16071*CHALLAN!$E$1:$E$16071,0))} -> 140 | D29: {=SUMPRODUCT(--EXACT(CHALLAN!$B$1:$B$16071&"",A29&""),--EXACT(IFERROR(CHALLAN!$C$1:$C$16071&"",""),B29&""),IFERROR(CHALLAN!$F$1:$F$16071+0,0))} -> 0
A30: 12" STRIGHT BLADE 80W | C30: {=SUMPRODUCT(--EXACT(CHALLAN!$B$1:$B$16071&"",A30&""),--EXACT(IFERROR(CHALLAN!$C$1:$C$16071&"",""),B30&""),IFERROR(CHALLAN!$D$1:$D$16071*CHALLAN!$E$1:$E$16071,0))} -> 100 | D30: {=SUMPRODUCT(--EXACT(CHALLAN!$B$1:$B$16071&"",A30&""),--EXACT(IFERROR(CHALLAN!$C$1:$C$16071&"",""),B30&""),IFERROR(CHALLAN!$F$1:$F$16071+0,0))} -> 105
A31: 12"X10 B- (S Blade) | C31: {=SUMPRODUCT(--EXACT(CHALLAN!$B$1:$B$16071&"",A31&""),--EXACT(IFERROR(CHALLAN!$C$1:$C$16071&"",""),B31&""),IFERROR(CHALLAN!$D$1:$D$16071*CHALLAN!$E$1:$E$16071,0))} -> 300 | D31: {=SUMPRODUCT(--EXACT(CHALLAN!$B$1:$B$16071&"",A31&""),--EXACT(IFERROR(CHALLAN!$C$1:$C$16071&"",""),B31&""),IFERROR(CHALLAN!$F$1:$F$16071+0,0))} -> 300
A32: 12"X10 B- (S Blade) | B32: TS-8805B | C32: {=SUMPRODUCT(--EXACT(CHALLAN!$B$1:$B$16071&"",A32&""),--EXACT(IFERROR(CHALLAN!$C$1:$C$16071&"",""),B32&""),IFERROR(CHALLAN!$D$1:$D$16071*CHALLAN!$E$1:$E$16071,0))} -> 200 | D32: {=SUMPRODUCT(--EXACT(CHALLAN!$B$1:$B$16071&"",A32&""),--EXACT(IFERROR(CHALLAN!$C$1:$C$16071&"",""),B32&""),IFERROR(CHALLAN!$F$1:$F$16071+0,0))} -> 200
A33: 12"X10 B- Straight Blade) | B33: TST-8801-A | C33: {=SUMPRODUCT(--EXACT(CHALLAN!$B$1:$B$16071&"",A33&""),--EXACT(IFERROR(CHALLAN!$C$1:$C$16071&"",""),B33&""),IFERROR(CHALLAN!$D$1:$D$16071*CHALLAN!$E$1:$E$16071,0))} -> 390 | D33: {=SUMPRODUCT(--EXACT(CHALLAN!$B$1:$B$16071&"",A33&""),--EXACT(IFERROR(CHALLAN!$C$1:$C$16071&"",""),B33&""),IFERROR(CHALLAN!$F$1:$F$16071+0,0))} -> 390
A34: 1200 | B34: (broken ref - CHALLAN!C13694) | C34: {=SUMPRODUCT(--EXACT(CHALLAN!$B$1:$B$16071&"",A34&""),--EXACT(IFERROR(CHALLAN!$C$1:$C$16071&"",""),B34&""),IFERROR(CHALLAN!$D$1:$D$16071*CHALLAN!$E$1:$E$16071,0))} -> 0 | D34: {=SUMPRODUCT(--EXACT(CHALLAN!$B$1:$B$16071&"",A34&""),--EXACT(IFERROR(CHALLAN!$C$1:$C$16071&"",""),B34&""),IFERROR(CHALLAN!$F$1:$F$16071+0,0))} -> 0
A35: 14" JPI (S) | C35: {=SUMPRODUCT(--EXACT(CHALLAN!$B$1:$B$16071&"",A35&""),--EXACT(IFERROR(CHALLAN!$C$1:$C$16071&"",""),B35&""),IFERROR(CHALLAN!$D$1:$D$16071*CHALLAN!$E$1:$E$16071,0))} -> 305 | D35: {=SUMPRODUCT(--EXACT(CHALLAN!$B$1:$B$16071&"",A35&""),--EXACT(IFERROR(CHALLAN!$C$1:$C$16071&"",""),B35&""),IFERROR(CHALLAN!$F$1:$F$16071+0,0))} -> 305
A36: 14" ST BLADE | C36: {=SUMPRODUCT(--EXACT(CHALLAN!$B$1:$B$16071&"",A36&""),--EXACT(IFERROR(CHALLAN!$C$1:$C$16071&"",""),B36&""),IFERROR(CHALLAN!$D$1:$D$16071*CHALLAN!$E$1:$E$16071,0))} -> 1 | D36: {=SUMPRODUCT(--EXACT(CHALLAN!$B$1:$B$16071&"",A36&""),--EXACT(IFERROR(CHALLAN!$C$1:$C$16071&"",""),B36&""),IFERROR(CHALLAN!$F$1:$F$16071+0,0))} -> 1
A37: 14" STRAIGHT | B37: TST-8801-B | C37: {=SUMPRODUCT(--EXACT(CHALLAN!$B$1:$B$16071&"",A37&""),--EXACT(IFERROR(CHALLAN!$C$1:$C$16071&"",""),B37&""),IFERROR(CHALLAN!$D$1:$D$16071*CHALLAN!$E$1:$E$16071,0))} -> 20 | D37: {=SUMPRODUCT(--EXACT(CHALLAN!$B$1:$B$16071&"",A37&""),--EXACT(IFERROR(CHALLAN!$C$1:$C$16071&"",""),B37&""),IFERROR(CHALLAN!$F$1:$F$16071+0,0))} -> 20
A38: 14" STRAIGHT BLADE | C38: {=SUMPRODUCT(--EXACT(CHALLAN!$B$1:$B$16071&"",A38&""),--EXACT(IFERROR(CHALLAN!$C$1:$C$16071&"",""),B38&""),IFERROR(CHALLAN!$D$1:$D$16071*CHALLAN!$E$1:$E$16071,0))} -> 130 | D38: {=SUMPRODUCT(--EXACT(CHALLAN!$B$1:$B$16071&"",A38&""),--EXACT(IFERROR(CHALLAN!$C$1:$C$16071&"",""),B38&""),IFERROR(CHALLAN!$F$1:$F$16071+0,0))} -> 130
A39: 14"X10 B-(Straight Blade) | B39: TST-8801-B | C39: {=SUMPRODUCT(--EXACT(CHALLAN!$B$1:$B$16071&"",A39&""),--EXACT(IFERROR(CHALLAN!$C$1:$C$16071&"",""),B39&""),IFERROR(CHALLAN!$D$1:$D$16071*CHALLAN!$E$1:$E$16071,0))} -> 100 | D39: {=SUMPRODUCT(--EXACT(CHALLAN!$B$1:$B$16071&"",A39&""),--EXACT(IFERROR(CHALLAN!$C$1:$C$16071&"",""),B39&""),IFERROR(CHALLAN!$F$1:$F$16071+0,0))} -> 0
A40: 141522 (O) | C40: {=SUMPRODUCT(--EXACT(CHALLAN!$B$1:$B$16071&"",A40&""),--EXACT(IFERROR(CHALLAN!$C$1:$C$16071&"",""),B40&""),IFERROR(CHALLAN!$D$1:$D$16071*CHALLAN!$E$1:$E$16071,0))} -> 30 | D40: {=SUMPRODUCT(--EXACT(CHALLAN!$B$1:$B$16071&"",A40&""),--EXACT(IFERROR(CHALLAN!$C$1:$C$16071&"",""),B40&""),IFERROR(CHALLAN!$F$1:$F$16071+0,0))} -> 0
A41: 141522 (O) | B41: PC141522(O) | C41: {=SUMPRODUCT(--EXACT(CHALLAN!$B$1:$B$16071&"",A41&""),--EXACT(IFERROR(CHALLAN!$C$1:$C$16071&"",""),B41&""),IFERROR(CHALLAN!$D$1:$D$16071*CHALLAN!$E$1:$E$16071,0))} -> 30 | D41: {=SUMPRODUCT(--EXACT(CHALLAN!$B$1:$B$16071&"",A41&""),--EXACT(IFERROR(CHALLAN!$C$1:$C$16071&"",""),B41&""),IFERROR(CHALLAN!$F$1:$F$16071+0,0))} -> 0
A42: 141522(F) | C42: {=SUMPRODUCT(--EXACT(CHALLAN!$B$1:$B$16071&"",A42&""),--EXACT(IFERROR(CHALLAN!$C$1:$C$16071&"",""),B42&""),IFERROR(CHALLAN!$D$1:$D$16071*CHALLAN!$E$1:$E$16071,0))} -> 30 | D42: {=SUMPRODUCT(--EXACT(CHALLAN!$B$1:$B$16071&"",A42&""),--EXACT(IFERROR(CHALLAN!$C$1:$C$16071&"",""),B42&""),IFERROR(CHALLAN!$F$1:$F$16071+0,0))} -> 0
A43: 141522(F) | B43: PC141522(F) | C43: {=SUMPRODUCT(--EXACT(CHALLAN!$B$1:$B$16071&"",A43&""),--EXACT(IFERROR(CHALLAN!$C$1:$C$16071&"",""),B43&""),IFERROR(CHALLAN!$D$1:$D$16071*CHALLAN!$E$1:$E$16071,0))} -> 30 | D43: {=SUMPRODUCT(--EXACT(CHALLAN!$B$1:$B$16071&"",A43&""),--EXACT(IFERROR(CHALLAN!$C$1:$C$16071&"",""),B43&""),IFERROR(CHALLAN!$F$1:$F$16071+0,0))} -> 0
A44: 141822 | B44: PC141822 | C44: {=SUMPRODUCT(--EXACT(CHALLAN!$B$1:$B$16071&"",A44&""),--EXACT(IFERROR(CHALLAN!$C$1:$C$16071&"",""),B44&""),IFERROR(CHALLAN!$D$1:$D$16071*CHALLAN!$E$1:$E$16071,0))} -> 30 | D44: {=SUMPRODUCT(--EXACT(CHALLAN!$B$1:$B$16071&"",A44&""),--EXACT(IFERROR(CHALLAN!$C$1:$C$16071&"",""),B44&""),IFERROR(CHALLAN!$F$1:$F$16071+0,0))} -> 0
A45: 142122 | B45: PC142122 | C45: {=SUMPRODUCT(--EXACT(CHALLAN!$B$1:$B$16071&"",A45&""),--EXACT(IFERROR(CHALLAN!$C$1:$C$16071&"",""),B45&""),IFERROR(CHALLAN!$D$1:$D$16071*CHALLAN!$E$1:$E$16071,0))} -> 30 | D45: {=SUMPRODUCT(--EXACT(CHALLAN!$B$1:$B$16071&"",A45&""),--EXACT(IFERROR(CHALLAN!$C$1:$C$16071&"",""),B45&""),IFERROR(CHALLAN!$F$1:$F$16071+0,0))} -> 0
A46: 142126 | B46: PC142126 | C46: {=SUMPRODUCT(--EXACT(CHALLAN!$B$1:$B$16071&"",A46&""),--EXACT(IFERROR(CHALLAN!$C$1:$C$16071&"",""),B46&""),IFERROR(CHALLAN!$D$1:$D$16071*CHALLAN!$E$1:$E$16071,0))} -> 30 | D46: {=SUMPRODUCT(--EXACT(CHALLAN!$B$1:$B$16071&"",A46&""),--EXACT(IFERROR(CHALLAN!$C$1:$C$16071&"",""),B46&""),IFERROR(CHALLAN!$F$1:$F$16071+0,0))} -> 0
A47: 14X14X20 | C47: {=SUMPRODUCT(--EXACT(CHALLAN!$B$1:$B$16071&"",A47&""),--EXACT(IFERROR(CHALLAN!$C$1:$C$16071&"",""),B47&""),IFERROR(CHALLAN!$D$1:$D$16071*CHALLAN!$E$1:$E$16071,0))} -> 25 | D47: {=SUMPRODUCT(--EXACT(CHALLAN!$B$1:$B$16071&"",A47&""),--EXACT(IFERROR(CHALLAN!$C$1:$C$16071&"",""),B47&""),IFERROR(CHALLAN!$F$1:$F$16071+0,0))} -> 25
A48: 14X14X20 (F) | B48: PC141420F | C48: {=SUMPRODUCT(--EXACT(CHALLAN!$B$1:$B$16071&"",A48&""),--EXACT(IFERROR(CHALLAN!$C$1:$C$16071&"",""),B48&""),IFERROR(CHALLAN!$D$1:$D$16071*CHALLAN!$E$1:$E$16071,0))} -> 25 | D48: {=SUMPRODUCT(--EXACT(CHALLAN!$B$1:$B$16071&"",A48&""),--EXACT(IFERROR(CHALLAN!$C$1:$C$16071&"",""),B48&""),IFERROR(CHALLAN!$F$1:$F$16071+0,0))} -> 25
A49: 14X14X20 F | B49: PC 141420(F) | C49: {=SUMPRODUCT(--EXACT(CHALLAN!$B$1:$B$16071&"",A49&""),--EXACT(IFERROR(CHALLAN!$C$1:$C$16071&"",""),B49&""),IFERROR(CHALLAN!$D$1:$D$16071*CHALLAN!$E$1:$E$16071,0))} -> 100 | D49: {=SUMPRODUCT(--EXACT(CHALLAN!$B$1:$B$16071&"",A49&""),--EXACT(IFERROR(CHALLAN!$C$1:$C$16071&"",""),B49&""),IFERROR(CHALLAN!$F$1:$F$16071+0,0))} -> 100
A50: 14X14X20 O | B50: PC 141420(O) | C50: {=SUMPRODUCT(--EXACT(CHALLAN!$B$1:$B$16071&"",A50&""),--EXACT(IFERROR(CHALLAN!$C$1:$C$16071&"",""),B50&""),IFERROR(CHALLAN!$D$1:$D$16071*CHALLAN!$E$1:$E$16071,0))} -> 50 | D50: {=SUMPRODUCT(--EXACT(CHALLAN!$B$1:$B$16071&"",A50&""),--EXACT(IFERROR(CHALLAN!$C$1:$C$16071&"",""),B50&""),IFERROR(CHALLAN!$F$1:$F$16071+0,0))} -> 50
A51: 14X15X20 F | B51: 141520F | C51: {=SUMPRODUCT(--EXACT(CHALLAN!$B$1:$B$16071&"",A51&""),--EXACT(IFERROR(CHALLAN!$C$1:$C$16071&"",""),B51&""),IFERROR(CHALLAN!$D$1:$D$16071*CHALLAN!$E$1:$E$16071,0))} -> 30 | D51: {=SUMPRODUCT(--EXACT(CHALLAN!$B$1:$B$16071&"",A51&""),--EXACT(IFERROR(CHALLAN!$C$1:$C$16071&"",""),B51&""),IFERROR(CHALLAN!$F$1:$F$16071+0,0))} -> 0
A52: 14X15X20F | C52: {=SUMPRODUCT(--EXACT(CHALLAN!$B$1:$B$16071&"",A52&""),--EXACT(IFERROR(CHALLAN!$C$1:$C$16071&"",""),B52&""),IFERROR(CHALLAN!$D$1:$D$16071*CHALLAN!$E$1:$E$16071,0))} -> 30 | D52: {=SUMPRODUCT(--EXACT(CHALLAN!$B$1:$B$16071&"",A52&""),--EXACT(IFERROR(CHALLAN!$C$1:$C$16071&"",""),B52&""),IFERROR(CHALLAN!$F$1:$F$16071+0,0))} -> 0
A53: 14X15X22 | C53: {=SUMPRODUCT(--EXACT(CHALLAN!$B$1:$B$16071&"",A53&""),--EXACT(IFERROR(CHALLAN!$C$1:$C$16071&"",""),B53&""),IFERROR(CHALLAN!$D$1:$D$16071*CHALLAN!$E$1:$E$16071,0))} -> 25 | D53: {=SUMPRODUCT(--EXACT(CHALLAN!$B$1:$B$16071&"",A53&""),--EXACT(IFERROR(CHALLAN!$C$1:$C$16071&"",""),B53&""),IFERROR(CHALLAN!$F$1:$F$16071+0,0))} -> 25
A54: 14X15X22 | B54: FLARE | C54: {=SUMPRODUCT(--EXACT(CHALLAN!$B$1:$B$16071&"",A54&""),--EXACT(IFERROR(CHALLAN!$C$1:$C$16071&"",""),B54&""),IFERROR(CHALLAN!$D$1:$D$16071*CHALLAN!$E$1:$E$16071,0))} -> 50 | D54: {=SUMPRODUCT(--EXACT(CHALLAN!$B$1:$B$16071&"",A54&""),--EXACT(IFERROR(CHALLAN!$C$1:$C$16071&"",""),B54&""),IFERROR(CHALLAN!$F$1:$F$16071+0,0))} -> 50
A55: 14X15X22 (F) | C55: {=SUMPRODUCT(--EXACT(CHALLAN!$B$1:$B$16071&"",A55&""),--EXACT(IFERROR(CHALLAN!$C$1:$C$16071&"",""),B55&""),IFERROR(CHALLAN!$D$1:$D$16071*CHALLAN!$E$1:$E$16071,0))} -> 105 | D55: {=SUMPRODUCT(--EXACT(CHALLAN!$B$1:$B$16071&"",A55&""),--EXACT(IFERROR(CHALLAN!$C$1:$C$16071&"",""),B55&""),IFERROR(CHALLAN!$F$1:$F$16071+0,0))} -> 75
A56: 14X15X22 (F) | B56: PC 141522F | C56: {=SUMPRODUCT(--EXACT(CHALLAN!$B$1:$B$16071&"",A56&""),--EXACT(IFERROR(CHALLAN!$C$1:$C$16071&"",""),B56&""),IFERROR(CHALLAN!$D$1:$D$16071*CHALLAN!$E$1:$E$16071,0))} -> 150 | D56: {=SUMPRODUCT(--EXACT(CHALLAN!$B$1:$B$16071&"",A56&""),--EXACT(IFERROR(CHALLAN!$C$1:$C$16071&"",""),B56&""),IFERROR(CHALLAN!$F$1:$F$16071+0,0))} -> 150
A57: 14X15X22 (F) | B57: PC141522F | C57: {=SUMPRODUCT(--EXACT(CHALLAN!$B$1:$B$16071&"",A57&""),--EXACT(IFERROR(CHALLAN!$C$1:$C$16071&"",""),B57&""),IFERROR(CHALLAN!$D$1:$D$16071*CHALLAN!$E$1:$E$16071,0))} -> 25 | D57: {=SUMPRODUCT(--EXACT(CHALLAN!$B$1:$B$16071&"",A57&""),--EXACT(IFERROR(CHALLAN!$C$1:$C$16071&"",""),B57&""),IFERROR(CHALLAN!$F$1:$F$16071+0,0))} -> 25
A58: 14X15X22 (O) | C58: {=SUMPRODUCT(--EXACT(CHALLAN!$B$1:$B$16071&"",A58&""),--EXACT(IFERROR(CHALLAN!$C$1:$C$16071&"",""),B58&""),IFERROR(CHALLAN!$D$1:$D$16071*CHALLAN!$E$1:$E$16071,0))} -> 115 | D58: {=SUMPRODUCT(--EXACT(CHALLAN!$B$1:$B$16071&"",A58&""),--EXACT(IFERROR(CHALLAN!$C$1:$C$16071&"",""),B58&""),IFERROR(CHALLAN!$F$1:$F$16071+0,0))} -> 25
A59: 14X15X22 (O) | B59: PC 141522O | C59: {=SUMPRODUCT(--EXACT(CHALLAN!$B$1:$B$16071&"",A59&""),--EXACT(IFERROR(CHALLAN!$C$1:$C$16071&"",""),B59&""),IFERROR(CHALLAN!$D$1:$D$16071*CHALLAN!$E$1:$E$16071,0))} -> 25 | D59: {=SUMPRODUCT(--EXACT(CHALLAN!$B$1:$B$16071&"",A59&""),--EXACT(IFERROR(CHALLAN!$C$1:$C$16071&"",""),B59&""),IFERROR(CHALLAN!$F$1:$F$16071+0,0))} -> 25
A60: 14X15X22 (O) | B60: PC-141522O | C60: {=SUMPRODUCT(--EXACT(CHALLAN!$B$1:$B$16071&"",A60&""),--EXACT(IFERROR(CHALLAN!$C$1:$C$16071&"",""),B60&""),IFERROR(CHALLAN!$D$1:$D$16071*CHALLAN!$E$1:$E$16071,0))} -> 45 | D60: {=SUMPRODUCT(--EXACT(CHALLAN!$B$1:$B$16071&"",A60&""),--EXACT(IFERROR(CHALLAN!$C$1:$C$16071&"",""),B60&""),IFERROR(CHALLAN!$F$1:$F$16071+0,0))} -> 0
A61: 14X15X22 (O) | B61: PC141522O | C61: {=SUMPRODUCT(--EXACT(CHALLAN!$B$1:$B$16071&"",A61&""),--EXACT(IFERROR(CHALLAN!$C$1:$C$16071&"",""),B61&""),IFERROR(CHALLAN!$D$1:$D$16071*CHALLAN!$E$1:$E$16071,0))} -> 75 | D61: {=SUMPRODUCT(--EXACT(CHALLAN!$B$1:$B$16071&"",A61&""),--EXACT(IFERROR(CHALLAN!$C$1:$C$16071&"",""),B61&""),IFERROR(CHALLAN!$F$1:$F$16071+0,0))} -> 75
A62: 14X15X22 F | C62: {=SUMPRODUCT(--EXACT(CHALLAN!$B$1:$B$16071&"",A62&""),--EXACT(IFERROR(CHALLAN!$C$1:$C$16071&"",""),B62&""),IFERROR(CHALLAN!$D$1:$D$16071*CHALLAN!$E$1:$E$16071,0))} -> 100 | D62: {=SUMPRODUCT(--EXACT(CHALLAN!$B$1:$B$16071&"",A62&""),--EXACT(IFERROR(CHALLAN!$C$1:$C$16071&"",""),B62&""),IFERROR(CHALLAN!$F$1:$F$16071+0,0))} -> 100
A63: 14X15X22 F | B63: PC 141522(F) | C63: {=SUMPRODUCT(--EXACT(CHALLAN!$B$1:$B$16071&"",A63&""),--EXACT(IFERROR(CHALLAN!$C$1:$C$16071&"",""),B63&""),IFERROR(CHALLAN!$D$1:$D$16071*CHALLAN!$E$1:$E$16071,0))} -> 150 | D63: {=SUMPRODUCT(--EXACT(CHALLAN!$B$1:$B$16071&"",A63&""),--EXACT(IFERROR(CHALLAN!$C$1:$C$16071&"",""),B63&""),IFERROR(CHALLAN!$F$1:$F$16071+0,0))} -> 150
A64: 14X15X22 O | C64: {=SUMPRODUCT(--EXACT(CHALLAN!$B$1:$B$16071&"",A64&""),--EXACT(IFERROR(CHALLAN!$C$1:$C$16071&"",""),B64&""),IFERROR(CHALLAN!$D$1:$D$16071*CHALLAN!$E$1:$E$16071,0))} -> 50 | D64: {=SUMPRODUCT(--EXACT(CHALLAN!$B$1:$B$16071&"",A64&""),--EXACT(IFERROR(CHALLAN!$C$1:$C$16071&"",""),B64&""),IFERROR(CHALLAN!$F$1:$F$16071+0,0))} -> 50
A65: 14X15X22 O | B65: PC 141522(O) | C65: {=SUMPRODUCT(--EXACT(CHALLAN!$B$1:$B$16071&"",A65&""),--EXACT(IFERROR(CHALLAN!$C$1:$C$16071&"",""),B65&""),IFERROR(CHALLAN!$D$1:$D$16071*CHALLAN!$E$1:$E$16071,0))} -> 125 | D65: {=SUMPRODUCT(--EXACT(CHALLAN!$B$1:$B$16071&"",A65&""),--EXACT(IFERROR(CHALLAN!$C$1:$C$16071&"",""),B65&""),IFERROR(CHALLAN!$F$1:$F$16071+0,0))} -> 125
A66: 14X15X22 ORING | B66: PC141522O | C66: {=SUMPRODUCT(--EXACT(CHALLAN!$B$1:$B$16071&"",A66&""),--EXACT(IFERROR(CHALLAN!$C$1:$C$16071&"",""),B66&""),IFERROR(CHALLAN!$D$1:$D$16071*CHALLAN!$E$1:$E$16071,0))} -> 30 | D66: {=SUMPRODUCT(--EXACT(CHALLAN!$B$1:$B$16071&"",A66&""),--EXACT(IFERROR(CHALLAN!$C$1:$C$16071&"",""),B66&""),IFERROR(CHALLAN!$F$1:$F$16071+0,0))} -> 30
A67: 14X15X22(F) | B67: PC-141522F | C67: {=SUMPRODUCT(--EXACT(CHALLAN!$B$1:$B$16071&"",A67&""),--EXACT(IFERROR(CHALLAN!$C$1:$C$16071&"",""),B67&""),IFERROR(CHALLAN!$D$1:$D$16071*CHALLAN!$E$1:$E$16071,0))} -> 120 | D67: {=SUMPRODUCT(--EXACT(CHALLAN!$B$1:$B$16071&"",A67&""),--EXACT(IFERROR(CHALLAN!$C$1:$C$16071&"",""),B67&""),IFERROR(CHALLAN!$F$1:$F$16071+0,0))} -> 0
A68: 14X15X22(O) | C68: {=SUMPRODUCT(--EXACT(CHALLAN!$B$1:$B$16071&"",A68&""),--EXACT(IFERROR(CHALLAN!$C$1:$C$16071&"",""),B68&""),IFERROR(CHALLAN!$D$1:$D$16071*CHALLAN!$E$1:$E$16071,0))} -> 30 | D68: {=SUMPRODUCT(--EXACT(CHALLAN!$B$1:$B$16071&"",A68&""),--EXACT(IFERROR(CHALLAN!$C$1:$C$16071&"",""),B68&""),IFERROR(CHALLAN!$F$1:$F$16071+0,0))} -> 0
A69: 14X15X22F | C69: {=SUMPRODUCT(--EXACT(CHALLAN!$B$1:$B$16071&"",A69&""),--EXACT(IFERROR(CHALLAN!$C$1:$C$16071&"",""),B69&""),IFERROR(CHALLAN!$D$1:$D$16071*CHALLAN!$E$1:$E$16071,0))} -> 110 | D69: {=SUMPRODUCT(--EXACT(CHALLAN!$B$1:$B$16071&"",A69&""),--EXACT(IFERROR(CHALLAN!$C$1:$C$16071&"",""),B69&""),IFERROR(CHALLAN!$F$1:$F$16071+0,0))} -> 50
A70: 14X15X22MM (O) | C70: {=SUMPRODUCT(--EXACT(CHALLAN!$B$1:$B$16071&"",A70&""),--EXACT(IFERROR(CHALLAN!$C$1:$C$16071&"",""),B70&""),IFERROR(CHALLAN!$D$1:$D$16071*CHALLAN!$E$1:$E$16071,0))} -> 55 | D70: {=SUMPRODUCT(--EXACT(CHALLAN!$B$1:$B$16071&"",A70&""),--EXACT(IFERROR(CHALLAN!$C$1:$C$16071&"",""),B70&""),IFERROR(CHALLAN!$F$1:$F$16071+0,0))} -> 25
A71: 14X15X26 | B71: PC141526 | C71: {=SUMPRODUCT(--EXACT(CHALLAN!$B$1:$B$16071&"",A71&""),--EXACT(IFERROR(CHALLAN!$C$1:$C$16071&"",""),B71&""),IFERROR(CHALLAN!$D$1:$D$16071*CHALLAN!$E$1:$E$16071,0))} -> 25 | D71: {=SUMPRODUCT(--EXACT(CHALLAN!$B$1:$B$16071&"",A71&""),--EXACT(IFERROR(CHALLAN!$C$1:$C$16071&"",""),B71&""),IFERROR(CHALLAN!$F$1:$F$16071+0,0))} -> 25
A72: 14X15X26MM | C72: {=SUMPRODUCT(--EXACT(CHALLAN!$B$1:$B$16071&"",A72&""),--EXACT(IFERROR(CHALLAN!$C$1:$C$16071&"",""),B72&""),IFERROR(CHALLAN!$D$1:$D$16071*CHALLAN!$E$1:$E$16071,0))} -> 100 | D72: {=SUMPRODUCT(--EXACT(CHALLAN!$B$1:$B$16071&"",A72&""),--EXACT(IFERROR(CHALLAN!$C$1:$C$16071&"",""),B72&""),IFERROR(CHALLAN!$F$1:$F$16071+0,0))} -> 100
A73: 14X18X16 | C73: {=SUMPRODUCT(--EXACT(CHALLAN!$B$1:$B$16071&"",A73&""),--EXACT(IFERROR(CHALLAN!$C$1:$C$16071&"",""),B73&""),IFERROR(CHALLAN!$D$1:$D$16071*CHALLAN!$E$1:$E$16071,0))} -> 75 | D73: {=SUMPRODUCT(--EXACT(CHALLAN!$B$1:$B$16071&"",A73&""),--EXACT(IFERROR(CHALLAN!$C$1:$C$16071&"",""),B73&""),IFERROR(CHALLAN!$F$1:$F$16071+0,0))} -> 75
A74: 14X18X16 F | B74: PC141816F | C74: {=SUMPRODUCT(--EXACT(CHALLAN!$B$1:$B$16071&"",A74&""),--EXACT(IFERROR(CHALLAN!$C$1:$C$16071&"",""),B74&""),IFERROR(CHALLAN!$D$1:$D$16071*CHALLAN!$E$1:$E$16071,0))} -> 100 | D74: {=SUMPRODUCT(--EXACT(CHALLAN!$B$1:$B$16071&"",A74&""),--EXACT(IFERROR(CHALLAN!$C$1:$C$16071&"",""),B74&""),IFERROR(CHALLAN!$F$1:$F$16071+0,0))} -> 100
A75: 14X18X16MM | C75: {=SUMPRODUCT(--EXACT(CHALLAN!$B$1:$B$16071&"",A75&""),--EXACT(IFERROR(CHALLAN!$C$1:$C$16071&"",""),B75&""),IFERROR(CHALLAN!$D$1:$D$16071*CHALLAN!$E$1:$E$16071,0))} -> 100 | D75: {=SUMPRODUCT(--EXACT(CHALLAN!$B$1:$B$16071&"",A75&""),--EXACT(IFERROR(CHALLAN!$C$1:$C$16071&"",""),B75&""),IFERROR(CHALLAN!$F$1:$F$16071+0,0))} -> 100
A76: 14X18X20 | C76: {=SUMPRODUCT(--EXACT(CHALLAN!$B$1:$B$16071&"",A76&""),--EXACT(IFERROR(CHALLAN!$C$1:$C$16071&"",""),B76&""),IFERROR(CHALLAN!$D$1:$D$16071*CHALLAN!$E$1:$E$16071,0))} -> 200 | D76: {=SUMPRODUCT(--EXACT(CHALLAN!$B$1:$B$16071&"",A76&""),--EXACT(IFERROR(CHALLAN!$C$1:$C$16071&"",""),B76&""),IFERROR(CHALLAN!$F$1:$F$16071+0,0))} -> 200
A77: 14X18X20 | B77: 141820 | C77: {=SUMPRODUCT(--EXACT(CHALLAN!$B$1:$B$16071&"",A77&""),--EXACT(IFERROR(CHALLAN!$C$1:$C$16071&"",""),B77&""),IFERROR(CHALLAN!$D$1:$D$16071*CHALLAN!$E$1:$E$16071,0))} -> 30 | D77: {=SUMPRODUCT(--EXACT(CHALLAN!$B$1:$B$16071&"",A77&""),--EXACT(IFERROR(CHALLAN!$C$1:$C$16071&"",""),B77&""),IFERROR(CHALLAN!$F$1:$F$16071+0,0))} -> 0
A78: 14X18X20 | B78: PC 141820 | C78: {=SUMPRODUCT(--EXACT(CHALLAN!$B$1:$B$16071&"",A78&""),--EXACT(IFERROR(CHALLAN!$C$1:$C$16071&"",""),B78&""),IFERROR(CHALLAN!$D$1:$D$16071*CHALLAN!$E$1:$E$16071,0))} -> 50 | D78: {=SUMPRODUCT(--EXACT(CHALLAN!$B$1:$B$16071&"",A78&""),--EXACT(IFERROR(CHALLAN!$C$1:$C$16071&"",""),B78&""),IFERROR(CHALLAN!$F$1:$F$16071+0,0))} -> 50
A79: 14X18X20 | B79: PC141820 | C79: {=SUMPRODUCT(--EXACT(CHALLAN!$B$1:$B$16071&"",A79&""),--EXACT(IFERROR(CHALLAN!$C$1:$C$16071&"",""),B79&""),IFERROR(CHALLAN!$D$1:$D$16071*CHALLAN!$E$1:$E$16071,0))} -> 50 | D79: {=SUMPRODUCT(--EXACT(CHALLAN!$B$1:$B$16071&"",A79&""),--EXACT(IFERROR(CHALLAN!$C$1:$C$16071&"",""),B79&""),IFERROR(CHALLAN!$F$1:$F$16071+0,0))} -> 50
A80: 14X18X20 F | C80: {=SUMPRODUCT(--EXACT(CHALLAN!$B$1:$B$16071&"",A80&""),--EXACT(IFERROR(CHALLAN!$C$1:$C$16071&"",""),B80&""),IFERROR(CHALLAN!$D$1:$D$16071*CHALLAN!$E$1:$E$16071,0))} -> 10 | D80: {=SUMPRODUCT(--EXACT(CHALLAN!$B$1:$B$16071&"",A80&""),--EXACT(IFERROR(CHALLAN!$C$1:$C$16071&"",""),B80&""),IFERROR(CHALLAN!$F$1:$F$16071+0,0))} -> 10
A81: 14X18X20 F | B81: PC141820F | C81: {=SUMPRODUCT(--EXACT(CHALLAN!$B$1:$B$16071&"",A81&""),--EXACT(IFERROR(CHALLAN!$C$1:$C$16071&"",""),B81&""),IFERROR(CHALLAN!$D$1:$D$16071*CHALLAN!$E$1:$E$16071,0))} -> 140 | D81: {=SUMPRODUCT(--EXACT(CHALLAN!$B$1:$B$16071&"",A81&""),--EXACT(IFERROR(CHALLAN!$C$1:$C$16071&"",""),B81&""),IFERROR(CHALLAN!$F$1:$F$16071+0,0))} -> 140
A82: 14X18X22 | C82: {=SUMPRODUCT(--EXACT(CHALLAN!$B$1:$B$16071&"",A82&""),--EXACT(IFERROR(CHALLAN!$C$1:$C$16071&"",""),B82&""),IFERROR(CHALLAN!$D$1:$D$16071*CHALLAN!$E$1:$E$16071,0))} -> 50 | D82: {=SUMPRODUCT(--EXACT(CHALLAN!$B$1:$B$16071&"",A82&""),--EXACT(IFERROR(CHALLAN!$C$1:$C$16071&"",""),B82&""),IFERROR(CHALLAN!$F$1:$F$16071+0,0))} -> 50
A83: 14X18X22 | B83: PC 141822 | C83: {=SUMPRODUCT(--EXACT(CHALLAN!$B$1:$B$16071&"",A83&""),--EXACT(IFERROR(CHALLAN!$C$1:$C$16071&"",""),B83&""),IFERROR(CHALLAN!$D$1:$D$16071*CHALLAN!$E$1:$E$16071,0))} -> 50 | D83: {=SUMPRODUCT(--EXACT(CHALLAN!$B$1:$B$16071&"",A83&""),--EXACT(IFERROR(CHALLAN!$C$1:$C$16071&"",""),B83&""),IFERROR(CHALLAN!$F$1:$F$16071+0,0))} -> 50
A84: 14X18X22 | B84: PC141822 | C84: {=SUMPRODUCT(--EXACT(CHALLAN!$B$1:$B$16071&"",A84&""),--EXACT(IFERROR(CHALLAN!$C$1:$C$16071&"",""),B84&""),IFERROR(CHALLAN!$D$1:$D$16071*CHALLAN!$E$1:$E$16071,0))} -> 25 | D84: {=SUMPRODUCT(--EXACT(CHALLAN!$B$1:$B$16071&"",A84&""),--EXACT(IFERROR(CHALLAN!$C$1:$C$16071&"",""),B84&""),IFERROR(CHALLAN!$F$1:$F$16071+0,0))} -> 25
A85: 14X18X22 | B85: FLARE | C85: {=SUMPRODUCT(--EXACT(CHALLAN!$B$1:$B$16071&"",A85&""),--EXACT(IFERROR(CHALLAN!$C$1:$C$16071&"",""),B85&""),IFERROR(CHALLAN!$D$1:$D$16071*CHALLAN!$E$1:$E$16071,0))} -> 50 | D85: {=SUMPRODUCT(--EXACT(CHALLAN!$B$1:$B$16071&"",A85&""),--EXACT(IFERROR(CHALLAN!$C$1:$C$16071&"",""),B85&""),IFERROR(CHALLAN!$F$1:$F$16071+0,0))} -> 50
A86: 14X18X22 (F) | C86: {=SUMPRODUCT(--EXACT(CHALLAN!$B$1:$B$16071&"",A86&""),--EXACT(IFERROR(CHALLAN!$C$1:$C$16071&"",""),B86&""),IFERROR(CHALLAN!$D$1:$D$16071*CHALLAN!$E$1:$E$16071,0))} -> 50 | D86: {=SUMPRODUCT(--EXACT(CHALLAN!$B$1:$B$16071&"",A86&""),--EXACT(IFERROR(CHALLAN!$C$1:$C$16071&"",""),B86&""),IFERROR(CHALLAN!$F$1:$F$16071+0,0))} -> 50
A87: 14X18X22 (F) | B87: PC141822F | C87: {=SUMPRODUCT(--EXACT(CHALLAN!$B$1:$B$16071&"",A87&""),--EXACT(IFERROR(CHALLAN!$C$1:$C$16071&"",""),B87&""),IFERROR(CHALLAN!$D$1:$D$16071*CHALLAN!$E$1:$E$16071,0))} -> 25 | D87: {=SUMPRODUCT(--EXACT(CHALLAN!$B$1:$B$16071&"",A87&""),--EXACT(IFERROR(CHALLAN!$C$1:$C$16071&"",""),B87&""),IFERROR(CHALLAN!$F$1:$F$16071+0,0))} -> 25
A88: 14X18X22(F) | C88: {=SUMPRODUCT(--EXACT(CHALLAN!$B$1:$B$16071&"",A88&""),--EXACT(IFERROR(CHALLAN!$C$1:$C$16071&"",""),B88&""),IFERROR(CHALLAN!$D$1:$D$16071*CHALLAN!$E$1:$E$16071,0))} -> 30 | D88: {=SUMPRODUCT(--EXACT(CHALLAN!$B$1:$B$16071&"",A88&""),--EXACT(IFERROR(CHALLAN!$C$1:$C$16071&"",""),B88&""),IFERROR(CHALLAN!$F$1:$F$16071+0,0))} -> 0
A89: 14X18X22F | C89: {=SUMPRODUCT(--EXACT(CHALLAN!$B$1:$B$16071&"",A89&""),--EXACT(IFERROR(CHALLAN!$C$1:$C$16071&"",""),B89&""),IFERROR(CHALLAN!$D$1:$D$16071*CHALLAN!$E$1:$E$16071,0))} -> 60 | D89: {=SUMPRODUCT(--EXACT(CHALLAN!$B$1:$B$16071&"",A89&""),--EXACT(IFERROR(CHALLAN!$C$1:$C$16071&"",""),B89&""),IFERROR(CHALLAN!$F$1:$F$16071+0,0))} -> 0
A90: 14X18X22MM | C90: {=SUMPRODUCT(--EXACT(CHALLAN!$B$1:$B$16071&"",A90&""),--EXACT(IFERROR(CHALLAN!$C$1:$C$16071&"",""),B90&""),IFERROR(CHALLAN!$D$1:$D$16071*CHALLAN!$E$1:$E$16071,0))} -> 325 | D90: {=SUMPRODUCT(--EXACT(CHALLAN!$B$1:$B$16071&"",A90&""),--EXACT(IFERROR(CHALLAN!$C$1:$C$16071&"",""),B90&""),IFERROR(CHALLAN!$F$1:$F$16071+0,0))} -> 325
A91: 14X18X26 F | B91: PC141826F | C91: {=SUMPRODUCT(--EXACT(CHALLAN!$B$1:$B$16071&"",A91&""),--EXACT(IFERROR(CHALLAN!$C$1:$C$16071&"",""),B91&""),IFERROR(CHALLAN!$D$1:$D$16071*CHALLAN!$E$1:$E$16071,0))} -> 25 | D91: {=SUMPRODUCT(--EXACT(CHALLAN!$B$1:$B$16071&"",A91&""),--EXACT(IFERROR(CHALLAN!$C$1:$C$16071&"",""),B91&""),IFERROR(CHALLAN!$F$1:$F$16071+0,0))} -> 25
A92: 14X21X16 | C92: {=SUMPRODUCT(--EXACT(CHALLAN!$B$1:$B$16071&"",A92&""),--EXACT(IFERROR(CHALLAN!$C$1:$C$16071&"",""),B92&""),IFERROR(CHALLAN!$D$1:$D$16071*CHALLAN!$E$1:$E$16071,0))} -> 100 | D92: {=SUMPRODUCT(--EXACT(CHALLAN!$B$1:$B$16071&"",A92&""),--EXACT(IFERROR(CHALLAN!$C$1:$C$16071&"",""),B92&""),IFERROR(CHALLAN!$F$1:$F$16071+0,0))} -> 100
A93: 14X21X16 F | B93: PC142116F | C93: {=SUMPRODUCT(--EXACT(CHALLAN!$B$1:$B$16071&"",A93&""),--EXACT(IFERROR(CHALLAN!$C$1:$C$16071&"",""),B93&""),IFERROR(CHALLAN!$D$1:$D$16071*CHALLAN!$E$1:$E$16071,0))} -> 100 | D93: {=SUMPRODUCT(--EXACT(CHALLAN!$B$1:$B$16071&"",A93&""),--EXACT(IFERROR(CHALLAN!$C$1:$C$16071&"",""),B93&""),IFERROR(CHALLAN!$F$1:$F$16071+0,0))} -> 100
A94: 14X21X16MM | C94: {=SUMPRODUCT(--EXACT(CHALLAN!$B$1:$B$16071&"",A94&""),--EXACT(IFERROR(CHALLAN!$C$1:$C$16071&"",""),B94&""),IFERROR(CHALLAN!$D$1:$D$16071*CHALLAN!$E$1:$E$16071,0))} -> 50 | D94: {=SUMPRODUCT(--EXACT(CHALLAN!$B$1:$B$16071&"",A94&""),--EXACT(IFERROR(CHALLAN!$C$1:$C$16071&"",""),B94&""),IFERROR(CHALLAN!$F$1:$F$16071+0,0))} -> 50
A95: 14X21X20 | C95: {=SUMPRODUCT(--EXACT(CHALLAN!$B$1:$B$16071&"",A95&""),--EXACT(IFERROR(CHALLAN!$C$1:$C$16071&"",""),B95&""),IFERROR(CHALLAN!$D$1:$D$16071*CHALLAN!$E$1:$E$16071,0))} -> 200 | D95: {=SUMPRODUCT(--EXACT(CHALLAN!$B$1:$B$16071&"",A95&""),--EXACT(IFERROR(CHALLAN!$C$1:$C$16071&"",""),B95&""),IFERROR(CHALLAN!$F$1:$F$16071+0,0))} -> 200
A96: 14X21X20 F | B96: PC 142120(F) | C96: {=SUMPRODUCT(--EXACT(CHALLAN!$B$1:$B$16071&"",A96&""),--EXACT(IFERROR(CHALLAN!$C$1:$C$16071&"",""),B96&""),IFERROR(CHALLAN!$D$1:$D$16071*CHALLAN!$E$1:$E$16071,0))} -> 50 | D96: {=SUMPRODUCT(--EXACT(CHALLAN!$B$1:$B$16071&"",A96&""),--EXACT(IFERROR(CHALLAN!$C$1:$C$16071&"",""),B96&""),IFERROR(CHALLAN!$F$1:$F$16071+0,0))} -> 50
A97: 14X21X20 F | B97: PC142120F | C97: {=SUMPRODUCT(--EXACT(CHALLAN!$B$1:$B$16071&"",A97&""),--EXACT(IFERROR(CHALLAN!$C$1:$C$16071&"",""),B97&""),IFERROR(CHALLAN!$D$1:$D$16071*CHALLAN!$E$1:$E$16071,0))} -> 250 | D97: {=SUMPRODUCT(--EXACT(CHALLAN!$B$1:$B$16071&"",A97&""),--EXACT(IFERROR(CHALLAN!$C$1:$C$16071&"",""),B97&""),IFERROR(CHALLAN!$F$1:$F$16071+0,0))} -> 250
A98: 14X21X20MM | C98: {=SUMPRODUCT(--EXACT(CHALLAN!$B$1:$B$16071&"",A98&""),--EXACT(IFERROR(CHALLAN!$C$1:$C$16071&"",""),B98&""),IFERROR(CHALLAN!$D$1:$D$16071*CHALLAN!$E$1:$E$16071,0))} -> 50 | D98: {=SUMPRODUCT(--EXACT(CHALLAN!$B$1:$B$16071&"",A98&""),--EXACT(IFERROR(CHALLAN!$C$1:$C$16071&"",""),B98&""),IFERROR(CHALLAN!$F$1:$F$16071+0,0))} -> 50
A99: 14X21X22 | B99: PC142122 | C99: {=SUMPRODUCT(--EXACT(CHALLAN!$B$1:$B$16071&"",A99&""),--EXACT(IFERROR(CHALLAN!$C$1:$C$16071&"",""),B99&""),IFERROR(CHALLAN!$D$1:$D$16071*CHALLAN!$E$1:$E$16071,0))} -> 50 | D99: {=SUMPRODUCT(--EXACT(CHALLAN!$B$1:$B$16071&"",A99&""),--EXACT(IFERROR(CHALLAN!$C$1:$C$16071&"",""),B99&""),IFERROR(CHALLAN!$F$1:$F$16071+0,0))} -> 50
A100: 14X21X22 | B100: FLARE | C100: {=SUMPRODUCT(--EXACT(CHALLAN!$B$1:$B$16071&"",A100&""),--EXACT(IFERROR(CHALLAN!$C$1:$C$16071&"",""),B100&""),IFERROR(CHALLAN!$D$1:$D$16071*CHALLAN!$E$1:$E$16071,0))} -> 25 | D100: {=SUMPRODUCT(--EXACT(CHALLAN!$B$1:$B$16071&"",A100&""),--EXACT(IFERROR(CHALLAN!$C$1:$C$16071&"",""),B100&""),IFERROR(CHALLAN!$F$1:$F$16071+0,0))} -> 25
A101: 14X21X22(F) | C101: {=SUMPRODUCT(--EXACT(CHALLAN!$B$1:$B$16071&"",A101&""),--EXACT(IFERROR(CHALLAN!$C$1:$C$16071&"",""),B101&""),IFERROR(CHALLAN!$D$1:$D$16071*CHALLAN!$E$1:$E$16071,0))} -> 30 | D101: {=SUMPRODUCT(--EXACT(CHALLAN!$B$1:$B$16071&"",A101&""),--EXACT(IFERROR(CHALLAN!$C$1:$C$16071&"",""),B101&""),IFERROR(CHALLAN!$F$1:$F$16071+0,0))} -> 0
...

Sheet PIVOT_SUMMARY
A1: Challan quantities by part number
A3: Description | B3: Part # | C3: Sum of D x E | D3: Sum of Qty in PCs
A4: COMPRESSOR OIL | B4: 1 LTR | C4: 1032 | D4: 1032
A5: UNICLA COMPRESSOR OIL | B5: 1 LTR | C5: 120 | D5: 120
A6: Grand Total | C6: 1152 | D6: 1152

Sheet Part 1
F1: Condensers | CS1: COOLING COIL | ER1: Blowers | FG1: SWITCHES | GD1: R.Drier | HC1: SEAL | HU1: FAN | ID1: EXPENSION VALVE
F2: 1 | G2: 2 | H2: 3 | I2: 4 | J2: 5 | K2: 6 | L2: 7 | M2: 8 | N2: 9 | O2: 10 | P2: 11 | Q2: 12 | R2: 13 | S2: 14 | T2: 15 | U2: 16 | V2: 17 | W2: 18 | X2: 19 | Y2: 20 | Z2: 21 | AA2: 22 | AB2: 23 | AC2: 24 | AD2: 25 | AE2: 26 | AF2: 27 | AG2: 28 | AH2: 29 | AI2: 30 | AJ2: 31 | AK2: 32 | AL2: 33 | AM2: 34 | AN2: 35 | AO2: 36 | AP2: 37 | AQ2: 38 | AR2: 39 | AS2: 40 | AT2: 41 | AU2: 42 | AV2: 43 | AW2: 44 | AX2: 45 | AY2: 46 | AZ2: 47 | BA2: 48 | BB2: 49 | BC2: 50 | BD2: 51 | BE2: 52 | BF2: 53 | BG2: 54 | BH2: 55 | BI2: 56 | BJ2: 57 | BK2: 58 | BL2: 59 | BM2: 60 | BN2: 61 | BO2: 62 | BP2: 63 | BQ2: 64 | BR2: 65 | BS2: 66 | BT2: 67 | BU2: 68 | BV2: 69 | BW2: 70 | BX2: 71 | BY2: 72 | BZ2: 73 | CA2: 74 | CB2: 75 | CC2: 76 | CD2: 77 | CE2: 78 | CF2: 79 | CG2: 80 | CH2: 81 | CI2: 82 | CJ2: 83 | CK2: 84 | CL2: 85 | CM2: 86 | CN2: 87 | CO2: 88 | CP2: 89 | CQ2: 90 | CR2: 91 | CS2: 92 | CT2: 93 | CU2: 94 | CV2: 95 | CW2: 96 | CX2: 97 | CY2: 98 | CZ2: 99 | DA2: 100 | DB2: 101 | DC2: 102 | DD2: 103 | DE2: 104 | DF2: 105 | DG2: 106 | DH2: 107 | DI2: 108 | DJ2: 109 | DK2: 110 | DL2: 111 | DM2: 112 | DN2: 113 | DO2: 114 | DP2: 115 | DQ2: 116 | DR2: 117 | DS2: 118 | DT2: 119 | DU2: 120 | DV2: 121 | DW2: 122 | DX2: 123 | DY2: 124 | DZ2: 125 | EA2: 126 | EB2: 127 | EC2: 128 | ED2: 129 | EE2: 130 | EF2: 131 | EG2: 132 | EH2: 133 | EI2: 134 | EJ2: 135 | EK2: 136 | EL2: 137 | EM2: 138 | EN2: 139 | EO2: 140 | EP2: 141 | EQ2: 142 | ER2: 143 | ES2: 144 | ET2: 145 | EU2: 146 | EV2: 147 | EW2: 148 | EX2: 149 | EY2: 150 | EZ2: 151 | FA2: 152 | FB2: 153 | FC2: 154 | FD2: 155 | FE2: 156 | FF2: 157 | FG2: 158 | FH2: 159 | FI2: 160 | FJ2: 161 | FK2: 162 | FL2: 163 | FM2: 164 | FN2: 165 | FO2: 166 | FP2: 167 | FQ2: 168 | FR2: 169 | FS2: 170 | FT2: 171 | FU2: 172 | FV2: 173 | FW2: 174 | FX2: 175 | FY2: 176 | FZ2: 177 | GA2: 178 | GB2: 179 | GC2: 180 | GD2: 181 | GE2: 182 | GF2: 183 | GG2: 184 | GH2: 185 | GI2: 186 | GJ2: 187 | GK2: 188 | GL2: 189 | GM2: 190 | GN2: 191 | GO2: 192 | GP2: 193 | GQ2: 194 | GR2: 195 | GS2: 196 | GT2: 197 | GU2: 198 | GV2: 199 | GW2: 200 | GX2: 201 | GY2: 202 | GZ2: 203 | HA2: 204 | HB2: 205 | HC2: 206 | HD2: 207 | HE2: 208 | HF2: 209 | HG2: 210 | HH2: 211 | HI2: 212 | HJ2: 213 | HK2: 214 | HL2: 215 | HM2: 216 | HN2: 217 | HO2: 218 | HP2: 219 | HQ2: 220 | HR2: 221 | HS2: 222 | HT2: 223 | HU2: 224 | HV2: 225 | HW2: 226 | HX2: 227 | HY2: 228 | HZ2: 229 | IA2: 230 | IB2: 231 | IC2: 232 | ID2: 233 | IE2: 234 | IF2: 235 | IG2: 236 | IH2: 237 | II2: 238 | IJ2: 239 | IK2: 240 | IL2: 241 | IM2: 242 | IN2: 243 | IO2: 244 | IP2: 245 | IQ2: 246 | IR2: 247 | IS2: 248 | IT2: 249 | IU2: 250 | IV2: 251
A3: S.NO | B3: BUYER /SUPPLIER NAME | C3: DATE | D3: CHALLAN / BE NO | E3: AMOUNT | F3: ACCENT CRD-I | G3: ACCENT-PETROL | H3: ACCORD | I3: AMBASDOR | J3: AVEO | K3: A-STAR | L3: BELANO | M3: BOLERO- R134A | N3: CIELO | O3: COROLLA | P3: DÉCOR | Q3: ELANTRA | R3: ENDEAVOUR | S3: Esteem-134a | T3: ESTEEM-R12 | U3: FABIA | V3: FEISTA | W3: Ford Ikon | X3: FUSION | Y3: GETZ | Z3: H.CITY-T-5 | AA3: H.CITY-T-I & 11 | AB3: Honda City-TYPE-3 | AC3: HONDA CRV | AD3: HONDA CIVIC | AE3: I-10 | AF3: I-20 | AG3: INDICA / BEHR-R134A | AH3: INDICA-134A-SUBROS | AI3: Indigo | AJ3: INNOVA | AK3: LANCER | AL3: LAURA | AM3: LOGAN-PAD | AN3: Maruti Car-800 MPFI | AO3: MATIZ | AP3: OPEL CORSA | AQ3: OPEL-ASTRA | AR3: OPTRA | AS3: PALIO | AT3: PALIO STILE | AU3: QUALIS-FLARE | AV3: Qualis-O Ring | AW3: Qualis-PAD | AX3: SAFARI | AY3: SANTRO | AZ3: SANTRO (PREMIUM) | BA3: Santro-ZING | BB3: SCORPIO | BC3: SKODA | BD3: SPARK | BE3: Sumo VECTA | BF3: SWIFT | BG3: SX4 | BH3: TRAVERA | BI3: VARNA-PETROL | BJ3: VISTA-BEHR | BK3: VOLVO | BL3: WAGON-R / ALTO | BM3: WR / ALTO (PREMIUM) | BN3: ZEN DEISAL | BO3: ZEN DELPHI R12 | BP3: ZEN DELPHI R134A | BQ3: ZEN ESTILO | BR3: ZEN-R12 | BS3: ZEN-R134A | BT3: PF/UNI 25X28X26MM | BU3: PF/UNI 25X28X20MM | BV3: PF/UNI 14X14X20MM | BW3: PF/UNI 14X14X20MM | BX3: PF/UNI 14X14X20MM | BY3: PF/UNI 14X14X20MM | BZ3: PF/UNI 14X18X16MM | CA3: PF/UNI 14X18X20MM | CB3: PF/UNI 14X21X16MM | CC3: PF/UNI 14X21X20MM | CD3: PF/UNI 14X23X16MM | CE3: PF/UNI 14X23X20MM | CF3: SP/UNI 14X15X22MM (O) | CG3: SP/UNI 14X15X22MM (F) | CH3: SP/UNI 14X15X26MM (F) | CI3: SP/UNI 14X18X22MM (F) | CJ3: SP/UNI 14X18X26MM (F) | CK3: SP/UNI 14X21X22MM (F) | CL3: SP/UNI 14X21X26MM (F) | CM3: SP/UNI 14X23X22MM (F) | CN3: SP/UNI 14X23X26MM (F) | CO3: SP/UNI 14X23X44MM (F) | CP3: SP/UNI 14X25X26MM (F) | CQ3: SP/UNI 14X25X44MM (F) | CR3: SP/UNI 14X28X44MM (F) | CS3: A6 | CT3: 848L MICROBUS COIL | CU3: Accent | CV3: ACCORD | CW3: Baleno | CX3: BOlero R134a | CY3: Cielo | CZ3: Corrolla | DA3: ELANTRA | DB3: Esteem R-12 | DC3: Esteem R-134a | DD3: ESTILO | DE3: FIESTA | DF3: FORD IKON | DG3: Getz | DH3: Honda City-III | DI3: Honda City-I & II | DJ3: Honda CRV | DK3: INDICA SUBROS R134A | DL3: Indica Behr | DM3: Indigo | DN3: Innova | DO3: Innova-Back | DP3: Lancer HCC | DQ3: Lancer MMC-2000 | DR3: Logan | DS3: MATIZ | DT3: MITSUBISHI PAJERO | DU3: Opel | DV3: Opel Corsa | DW3: Optra | DX3: Palio | DY3: QUALIS | DZ3: Safari | EA3: Santro Xing | EB3: Scorpio | EC3: SANTRO | ED3: Sk-Coil | EE3: Skoda | EF3: SONATA | EG3: Spark | EH3: SUMO VECTA | EI3: Swift | EJ3: Tavera | EK3: Varna (D) | EL3: VISTA (DSL) NEW | EM3: ZEN R12 | EN3: Wagan R / Alto | EO3: Zen Delphi R-12 | EP3: Zen Delphi R-134a | EQ3: Zen R-134-SUBROS | ER3: MICROBUS-Tubefin | ES3: MICROBUS-PF | ET3: MiniBus | EU3: SK | EV3: Concord-Elec, | EW3: CONCORD-AL-GREY | EX3: CONCORD-AL-BEIGE | EY3: CONCORD-COPPER-GREY | EZ3: CONCORD-COPPER-BEIGE | FA3: Concord-Normal | FB3: 405 | FC3: 404 | FD3: CONCORD WHEEL | FE3: CONCORD MOTOR | FF3: CONCORD COOLING COIL | FG3: CONCORD A/C SWITCH | FH3: CONCORD RESISTANCE | FI3: esteem r12 ordanary | FJ3: ESTEEM-R12 / Accent | FK3: ESTEEM-R134/Lancer | FL3: HONDA CITY | FM3: INDICA R-134A-4 pin | FN3: Innova a/c switch | FO3: LANCER BLOWER SWITCH | FP3: LENCER | FQ3: OPEL-BIG | FR3: OPEL-SMALL-2pin | FS3: PALIO | FT3: SANTRO | FU3: Santro-3 Speed | FV3: Santro-4 Speed | FW3: skoda-3PIN | FX3: SONATA | FY3: SONATA | FZ3: SWIFT | GA3: THERMO-STAT | GB3: TOYOTA QUALIS | GC3: WAGON-R HPLP-2PIN | GD3: Ambasdor/ BOlero | GE3: AVEO | GF3: BUS-UNI | GG3: Daewoo Cielo | GH3: DESICCANT FILTER/DRIER | GI3: Esteem-R12 | GJ3: Esteem-R134A | GK3: Ford | GL3: Honda City | GM3: Indica Behr | GN3: Lancer | GO3: Maruti 'F'Ring | GP3: Maruti 'O'Ring | GQ3: Matiz-NEW | GR3: Opel | GS3: OPTRA | GT3: Santro/santro xing | GU3: Scorpio-3hole | GV3: Scorpio-4hole | GW3: Skoda | GX3: Sonata | GY3: Toyota Qualis | GZ3: Travera | HA3: Uni-FLAIR | HB3: Universal | HC3: 507 | HD3: 508 | HE3: 507 single seal | HF3: 507-AA | HG3: 508-AA | HH3: BOLERO | HI3: Clelo | HJ3: GASKET 505/507 | HK3: H.CITY | HL3: ND | HM3: OPEL ASTRA | HN3: O-RINGS | HO3: Santro Large-matiz/ZEN DELPHI | HP3: SANTRO SMALL | HQ3: ANY HCC | HR3: TM-16 | HS3: TQ | HT3: WR | HU3: 10" Staight -80w | HV3: 10" 'S' 80w | HW3: 12" Staight -80w | HX3: 12" 'S' 80w | HY3: 12" 'S' 100w BEHR | HZ3: 14" Staight -80w | IA3: 14" 'S' 100w JPI | IB3: 15" 'S' Scorpio | IC3: 16" 'S' Scorpio | ID3: TRAVERA / ACCENT | IE3: SKODA | IF3: WR/ALTO | IG3: OPEL / INDICA BEHR C/ SCORPIO | IH3: HONDA CITY | II3: LANCER MMC | IJ3: SANTRO | IK3: FLARE | IL3: O-RING | IM3: QUALIS | IN3: INNOVA / WR | IO3: ORIFICE TUBE | IP3: ORIFICE TUBE
F4: PC-86064B | G4: PC-86248 | I4: PC-86041 | J4: PC-86177 | K4: PC-86274 | L4: PC-86242 | M4: PC-86236 | O4: PC-86110 | P4: PC-86273 | Q4: PC-86066 | R4: PC-86277 | S4: PC-86090 | T4: PC-86040 | U4: PC-86134 | V4: PC-86272 | W4: PC-86034 | X4: PC-86271 | Y4: PC-86027B | Z4: PC-86278 | AA4: PC-86091 | AB4: PC-86240 | AC4: PC-86101 | AD4: PC-86251 | AF4: PC-86268 | AG4: PC-86233 | AH4: PC-86036 | AI4: PC-86237 | AJ4: PC-86046 | AK4: PC-86246B | AL4: PC-86026B | AM4: PC-86087 | AN4: PC-86092 | AO4: PC-86042 | AP4: PC-86038 | AQ4: PC-86243 | AR4: PC-86186 | AS4: PC-86039 | AT4: PC-86269 | AU4: PC-86234 | AV4: PC-86244 | AW4: PC-86235 | AX4: PC-86238 | AY4: PC-86125 | AZ4: PC-868404 | BA4: PC-86239 | BB4: PC-86093 | BC4: PC-86004 | BD4: PC-86013 | BE4: PC-86241 | BF4: PC-86207 | BG4: PC-86025 | BH4: PC-86247 | BI4: PC-86027 | BJ4: PC-86276 | BK4: PC-86255B | BL4: PC-86037 | BM4: PC-868412 | BN4: PC-86279 | BO4: PC-86270 R12 | BP4: PC-86270 R134 | BQ4: PC-86275 | BR4: PC-86043 | BS4: PC-86245 | BT4: PC-086101 | BU4: PC-086102 | BV4: "F" | BW4: "O" | BX4: "F" | BY4: "O" | CS4: PC-A6 | CU4: PC-055R | CV4: PC-510 | CW4: PC-142R | CX4: PC-8095 | CY4: PC-043R | CZ4: PC-114R | DA4: PC-135R | DB4: PC-036R12 | DC4: PC-036R-134 | DD4: PC-408 | DE4: PC-205 | DF4: PC-053 | DG4: PC-024R | DH4: NA | DI4: PC-8111R | DJ4: PC-113R | DK4: PC-8110R | DM4: PC-7159 | DN4: PC-209 | DO4: PC-246 | DP4: PC-206 | DQ4: PC-051R | DR4: PC-407R | DS4: PC-8084 | DU4: PC-052R | DV4: PC-8096 | DW4: PC-210 | DX4: PC-054 | DY4: PC-8904R | DZ4: PC-8083 | EA4: PC-250R | EB4: PC-7157 | EC4: PC-144R | ED4: PC-7029 | EE4: PC-143R | EF4: PC-079R | EG4: PC-249R | EH4: PC-8905R | EI4: PC-211 | EJ4: PC-012 | EK4: PC-439R | EL4: PC-451R | EM4: PC-8109R | EN4: PC-208 | EO4: PC-050R | EP4: PC-204-2 | EQ4: PC-8082 | FI4: PC-1052 | FJ4: PC-1046 | FK4: PC-1042A & 1044A | FL4: PC-1045B | FM4: PC-1066 | FO4: PC-926 | FP4: PC-1044A & 1042A | FQ4: PC-1091 | FR4: PC-1087 | FS4: PC-1100 | FT4: PC-1054B | FW4: PC-1191 | FX4: PC-2126 | FY4: PC-1802B | FZ4: PC-1525 | GA4: PC-1229A | GB4: PC-1065 | GC4: PC-1047B / PC-1801-A | GD4: PC-8120 | GE4: PC-8797 | GF4: PC-61020 | GG4: PC-8263 | GI4: PC-8005 | GJ4: PC-8006 | GK4: PC-8321 | GL4: PC-8020 | GM4: PC-8115 | GN4: PC-8017 | GO4: PC-8047 | GP4: PC-8051 | GQ4: PC-8096 | GR4: PC-6142 | GS4: PC-8031 | GT4: PC-8026 | GU4: PC-8115A | GV4: PC-8115B | GW4: PC-8053 | GX4: PC-6066 | GY4: PC-8008 | GZ4: PC-8122 | HA4: PC-6001 | HB4: PC-6001B | HC4: PC-7001A | HD4: PC-7004A | HE4: PC-7053A | HF4: PC-7001A | HG4: PC-7004A | HH4: PC-7237 | HI4: PC-7059A | HK4: PC-7061A | HL4: PC-7031A | HM4: PC-7210 | HN4: PC-7085A | HO4: PC-7058A | HP4: PC-7217 | HQ4: PC-7034A | HR4: PC-7046A | HS4: PC-7032A | HT4: PC-7038A | HU4: TST-8801 | HV4: TS-8805 | HW4: TST-8801-A | HX4: TS-8805-B | HY4: TS-8805-CB | HZ4: TST-8801-B | IA4: TS-8805-A | ID4: FK-C906 | IE4: FK-1080 | IF4: FK-1089D | IG4: FK-1181 | IH4: FK-1034 | II4: FK-1031B | IJ4: FK-1023B | IK4: FK-1011 | IL4: FK-1012 | IM4: FK-1015 | IN4: FK-1082B | IO4: oringe-PC-8006 | IP4: white - PC-8002
A7: 01.04.10 | C7: OPENING STOCK | F7: 0 | G7: 0 | H7: 0 | I7: 0 | J7: 0 | K7: 0 | L7: 0 | M7: 0 | N7: 0 | O7: 0 | Q7: 0 | R7: 0 | S7: 0 | T7: 0 | U7: 0 | V7: 0 | W7: 0 | X7: 0 | Y7: 0 | Z7: 0 | AB7: 0 | AC7: 0 | AE7: 0 | AF7: 0 | AG7: 0 | AH7: 0 | AI7: 0 | AJ7: 0 | AK7: 0 | AL7: 0 | AM7: 0 | AN7: 0 | AO7: 0 | AP7: 0 | AQ7: 0 | AR7: 0 | AS7: 0 | AT7: 0 | AU7: 0 | AV7: 0 | AW7: 0 | AX7: 0 | AY7: 0 | BA7: 0 | BB7: 0 | BC7: 0 | BD7: 0 | BE7: 0 | BF7: 0 | BG7: 0 | BH7: 0 | BI7: 0 | BJ7: 0 | BK7: 0 | BL7: 0 | BN7: 0 | BO7: 60 | BP7: 25 | BQ7: 0 | BR7: 0 | BS7: 0 | BT7: 0 | BU7: 0 | BV7: 0 | BW7: 0 | BX7: 0 | BY7: 0 | BZ7: 0 | CA7: 0 | CB7: 0 | CC7: 0 | CD7: 0 | CE7: 0 | CF7: 0 | CG7: 0 | CH7: 0 | CI7: 0 | CJ7: 0 | CK7: 0 | CL7: 0 | CM7: 0 | CN7: 0 | CO7: 0 | CP7: 0 | CQ7: 0 | CR7: 0 | CS7: 0 | CT7: 0 | CU7: 0 | CV7: 0 | CW7: 0 | CX7: 0 | CY7: 0 | CZ7: 0 | DA7: 0 | DB7: 0 | DC7: 0 | DD7: 0 | DE7: 0 | DF7: 0 | DG7: 0 | DH7: 0 | DJ7: 0 | DK7: 0 | DL7: 0 | DM7: 0 | DN7: 0 | DP7: 0 | DQ7: 0 | DR7: 0 | DS7: 0 | DT7: 0 | DU7: 0 | DV7: 0 | DW7: 0 | DX7: 0 | DY7: 0 | DZ7: 0 | EA7: 0 | EB7: 0 | EC7: 0 | ED7: 0 | EE7: 0 | EF7: 0 | EG7: 0 | EH7: 0 | EI7: 0 | EJ7: 0 | EK7: 0 | EN7: 0 | EO7: 0 | EP7: 0 | EQ7: 0 | ER7: 0 | ES7: 0 | ET7: =33*2 -> 66 | EU7: 0 | EV7: 0 | FA7: 0 | FB7: 0 | FC7: 0 | FD7: 0 | FE7: 0 | FG7: 0 | FH7: 0 | FI7: 0 | FJ7: 0 | FK7: 0 | FL7: 0 | FM7: 0 | FN7: 0 | FO7: 0 | FP7: 0 | FQ7: 0 | FR7: 0 | FS7: 0 | FT7: 0 | FU7: 0 | FV7: 0 | FW7: 0 | FX7: 0 | FY7: 0 | FZ7: 0 | GA7: 0 | GB7: 0 | GC7: 0 | GD7: 0 | GE7: 0 | GF7: 0 | GG7: 0 | GI7: 0 | GJ7: 0 | GK7: 0 | GL7: 0 | GM7: 0 | GN7: 0 | GO7: 0 | GP7: 0 | GQ7: 0 | GR7: 0 | GS7: 0 | GT7: 0 | GU7: 0 | GV7: 0 | GW7: 0 | GX7: 0 | GY7: 0 | GZ7: 0 | HA7: 0 | HB7: 0 | HC7: 0 | HD7: 0 | HE7: 0 | HF7: 0 | HG7: 0 | HH7: 0 | HI7: 0 | HJ7: 0 | HK7: 0 | HL7: 0 | HM7: 0 | HN7: 0 | HO7: 0 | HP7: 0 | HQ7: 0 | HR7: 0 | HS7: 0 | HT7: 0 | HU7: 0 | HV7: 0 | HW7: 0 | HX7: 0 | HY7: 0 | HZ7: 0 | IA7: 0 | IB7: 0 | IC7: 0 | ID7: 0 | IE7: 0 | IF7: 0 | IG7: 0 | IH7: 0 | II7: 0 | IJ7: 0 | IK7: 0 | IL7: 0 | IM7: 0 | IN7: 0 | IO7: 0 | IP7: 0
A10: 1 | B10: GLOBAL | C10: 24.04.10 | D10: 106812 DT.21.04.10 | FC10: 500 | FD10: 300 | FE10: 250
A11: 2 | B11: PK | C11: 21.04.10 | D11: 2039833/13.04.10 | J11: 25 | S11: 100 | T11: 50 | W11: 75 | AB11: 50 | AI11: 75 | AM11: 75 | AN11: 200 | AR11: 25 | AS11: 100 | AV11: 50 | AW11: 75 | AX11: 50 | AY11: 200 | BA11: 315 | BB11: 75 | BF11: 100 | BH11: 75 | BK11: 25 | BL11: 200 | BR11: 600 | BS11: 100 | CC11: 50 | CH11: 100 | CI11: 700 | CR11: 25
A12: 3 | B12: PK | C12: 28.04.10 | D12: NOT HAVE BE NO | J12: 75 | Q12: 50 | S12: 50 | T12: 50 | W12: 100 | Y12: 75 | AB12: 50 | AI12: 100 | AN12: 150 | AR12: 50 | AW12: 75 | AX12: 75 | BB12: 50 | BH12: 25 | BS12: 100 | CU12: 156 | CX12: 77 | CY12: 18 | DB12: 96 | DC12: 138 | DE12: 216 | DN12: 108 | DP12: 54 | DR12: 72 | DU12: 150 | DV12: 54 | DZ12: 72 | EF12: 36 | EH12: 23 | EJ12: 204 | EN12: 108 | EO12: 48 | EQ12: 60 | GA12: 3000 | HE12: 2000 | HF12: 1500 | HH12: 100 | HL12: 2000 | HM12: 100 | HN12: 2000 | HP12: 1000 | HR12: 200 | HS12: 300 | HT12: 500
A13: 4 | B13: SURENDER | C13: PAGE 2 | D13: 107446/03.05.10
A14: 5 | B14: KHURANA | C14: 30.05.10 | D14: 2066278/21.05.10 | CS14: 504 | EV14: 400
A15: 6 | B15: GLOBAL | C15: 04.06.10 | D15: 2078984/28.05.10 | AZ15: 512 | BM15: 574
A16: 7 | B16: PREETI | C16: 03.06.10 | D16: 2071085/28.05.10
A17: 8 | B17: KHURANA | C17: 03.06.10 | D17: 2070871/28.05.10 | EV17: 400
A18: 9 | B18: PK INTL | C18: 03.07.10 | D18: 2089921/22.06.10 | EV18: 800 | FF18: 200
A19: 10 | B19: KHURANA | C19: 04.07.10 | D19: 2089922/22.06.10 | DA19: 78 | DM19: 500 | DY19: 47 | DZ19: 95 | ED19: 102 | EG19: 102 | EO19: 54 | EP19: 108 | EQ19: 54 | ER19: 55 | EU19: 250 | GD19: =25*20 -> 500 | GI19: 2500 | GJ19: =140*25 -> 3500 | GL19: =12*25 -> 300 | GN19: =25*8 -> 200 | GP19: =20*25 -> 500 | GT19: =120*25 -> 3000 | GW19: =12*25 -> 300 | GX19: 50 | GY19: =15*20 -> 300 | HA19: =160*25 -> 4000 | HB19: =20*25 -> 500 | HU19: 500 | HV19: 500 | HW19: 500 | HX19: 500
A20: 11 | B20: SURENDER | C20: 15.07.10 | D20: 2101459/06.07.10 | CS20: 504 | FB20: 50 | FC20: 500
A21: 12 | B21: PREETI | C21: 19.07.10 | D21: 2096551/30.06.10 | DJ21: 48 | DO21: 200 | DU21: 162 | DW21: 216 | FI21: =300+500 -> 800 | FJ21: 1000 | FK21: 1000 | FL21: 200 | FM21: 1000 | FO21: 500 | FP21: 300 | FQ21: 100 | FR21: 300 | FS21: 200 | FT21: 500 | FW21: =200+250 -> 450 | FY21: 200 | GA21: 2000 | GB21: 200 | GC21: =300+500 -> 800 | GE21: 50 | GI21: 500 | GL21: 150 | GN21: 150 | GR21: 60 | GS21: 50 | GT21: 500 | GW21: 150 | GX21: 40 | HB21: 500 | HE21: 1000 | HF21: 1500 | HG21: 1500 | HH21: =100+500 -> 600 | HI21: 100 | HL21: 1000 | HM21: 300 | HN21: 1000 | HO21: 3000 | HP21: 1000 | HR21: 200 | HS21: 200 | HT21: 1000 | HU21: 1400 | HV21: 1250 | HW21: 1400 | HX21: 1400 | HY21: 400 | HZ21: 400 | IB21: 200
A22: 13 | B22: KHURANA | C22: 25.07.10 | D22: 2103638/14.07.10
A23: 14 | B23: PREETI | C23: 29.07.10 | D23: 2112043/16.07.10 | AB23: 25 | AI23: 25 | AJ23: 400 | AN23: 315 | AV23: 180 | AW23: 25 | AZ23: 463 | BM23: 518 | EB23: 80 | ED23: 202
A24: 15 | B24: GLOBAL | C24: 06.08.10 | D24: 2123593/29.07.10 | G24: 20 | M24: 50 | O24: 75 | S24: 150 | AA24: 150 | AC24: 50 | AG24: 775 | AJ24: 90 | AK24: 50 | AU24: 50 | AV24: 25 | AW24: 125 | AY24: 600 | BB24: 110 | BH24: 300 | BL24: 200 | BP24: 35 | BR24: 200 | BX24: 270 | BY24: 190 | CA24: 160 | CC24: 50 | CF24: 600 | CG24: 700 | CK24: 200 | CM24: 200 | GD24: 100 | GF24: 240 | GI24: 1500 | GJ24: 1500 | GP24: 500 | GT24: 2800 | GY24: 260 | HA24: 2500
A25: 16 | B25: GLOBAL | C25: 12.08.10 | D25: 2128472/03.08.10 | AG25: 225 | AH25: 795 | AJ25: 10 | AK25: 50 | AN25: 100 | AQ25: 25 | AY25: 150 | BC25: 30 | BH25: 100 | BK25: 25 | BL25: 480 | BR25: 160 | BU25: 50 | BX25: 30 | CE25: 90 | CF25: 190 | CG25: 780 | CH25: 70 | CK25: 90 | CM25: 70 | CN25: 30 | CO25: 50 | GH25: 1200
A26: 17 | B26: SURENDER | C26: 15.08.10 | D26: 2133323/07.08.10
A27: 18 | B27: GLOBAL | C27: 19.08.10 | D27: 2132836/07.08.10 | G27: 30 | I27: 150 | K27: 50 | Q27: 50 | T27: 150 | W27: 75 | Y27: 25 | AH27: 205 | AI27: 100 | AN27: 135 | AO27: 25 | AX27: 75 | AY27: 50 | BA27: 185 | BB27: 65 | BE27: 50 | BN27: 50 | BP27: 15 | BR27: 140 | BY27: 10 | BZ27: 100 | CB27: 100 | CD27: 100 | CE27: 10 | CF27: 10 | CG27: 20 | CH27: 30 | CI27: 1600 | CJ27: 50 | CK27: 10 | CL27: 50 | CM27: 30 | CN27: 20 | CQ27: 50 | CR27: 75
A28: 19 | B28: PREETI | C28: 01.09.10 | D28: 2145903/20.08.10
A29: 20 | B29: PREETI | C29: 10.10.10 | D29: 2224349/01.10.10 | F29: 50 | G29: 0 | AN29: 100 | BC29: 20 | BE29: 50 | BF29: 200 | BL29: 120 | BS29: 100 | CY29: 12 | DA29: 54 | DN29: 150 | DP29: 54 | EA29: 120 | EC29: 30 | EE29: 87 | EF29: 72 | EG29: 60 | EI29: =312+16 -> 328 | EK29: 120 | EN29: 150 | EU29: 300 | GD29: 150 | GF29: 220 | GI29: 2400 | GJ29: 2775 | GL29: 150 | GN29: 150 | GR29: 40 | GS29: 50 | GT29: 3875 | HA29: 825 | HB29: 500 | ID29: 200 | IE29: 200 | IF29: 200 | IG29: 200 | IH29: 200 | II29: 200 | IJ29: 400 | IK29: 600 | IL29: 600 | IM29: 200 | IN29: 200
A30: 21 | B30: GLOBAL | C30: 31.10.10 | D30: 2280025/25.10.10 | P30: 50 | R30: 50 | U30: 50 | Z30: 50 | AL30: 100 | BJ30: 100 | BK30: 50 | BS30: 100 | BU30: 100 | BX30: 200 | BY30: 100 | BZ30: 100 | CA30: 140 | CB30: 100 | CC30: 250 | CD30: 100 | CE30: 200 | CH30: 100 | CJ30: 50 | CL30: 50 | CU30: 6 | CX30: 48 | DG30: 72 | DR30: 54 | DV30: 54 | DX30: 12 | EH30: 102 | EO30: 48 | ER30: 100 | GI30: 600 | GJ30: 725 | GO30: 500 | HA30: 6700 | HU30: 100 | HV30: 250 | HW30: 100 | HX30: 100 | IA30: 200
A31: 22 | B31: VIMAL-BOM | C31: 10.11.10 | D31: GG/145/10-11 DT.10.08.10 | E31: RTND | W31: 20
A32: 23 | B32: GLOBAL | C32: 16.1.11 | D32: 2555141/10.1.11 | F32: 50 | G32: 50 | M32: 50 | AB32: 50 | AK32: 50 | AU32: 45 | BO32: 50 | BP32: 50 | BU32: 200 | BZ32: 200 | CA32: 400 | CB32: 100 | CC32: 200 | CD32: 100 | CO32: 50 | CU32: 144 | CW32: 54 | DE32: 150 | DF32: 150 | DG32: 34 | DI32: 102 | DK32: 54 | DN32: 54 | DP32: 102 | DR32: 54 | DS32: 30 | DX32: 102 | DY32: 30 | EA32: 54 | EB32: 54 | EC32: 120 | EE32: 240 | EG32: 92 | EI32: 78 | EJ32: 198 | EK32: 138 | EL32: 54 | EM32: 54 | EN32: 198 | EO32: 6
A33: 24 | B33: PK INTL | C33: 17.1.11 | D33: 2556472/10.1.11
A34: 25 | B34: Contact-004 | C34: 08.03.11 | D34: GOODS RTN | FK34: 200
A35: 26 | B35: Contact-004 | C35: 16.03.11 | D35: GOODS RTN | CW35: 30
A36: 27 | B36: P INTL | C36: 31.03.11 | D36: 3053918/26.03.11
A38: TOTAL | C38: PUR | F38: =SUM(F7:F37) -> 100 | G38: =SUM(G7:G37) -> 100 | H38: =SUM(H7:H37) -> 0 | I38: =SUM(I7:I37) -> 150 | J38: =SUM(J7:J37) -> 100 | K38: =SUM(K7:K37) -> 50 | L38: =SUM(L7:L37) -> 0 | M38: =SUM(M7:M37) -> 100 | ... IP38: =SUM(IP7:IP37) -> 0
A40: sale
A41: 1 | B41: Contact-004 | C41: 03.04.10 | D41: GG/001/10-11 | E41: 47000 | BO41: 15 | BP41: 15 | FS41: 25
A42: 2 | B42: SONU | C42: 03.04.10 | D42: GG/002/10-11 | E42: 73080
A43: 3 | B43: Transporter-005 | C43: SAMPLES | D43: GG/003/10-11 | E43: 0
A44: 4 | B44: Transporter-005 | C44: SAMPLES | D44: GG/004/10-11 | E44: 0
A45: 5 | B45: Transporter-005 | C45: 07.04.10 | D45: GG/005/10-11 | E45: 306000
A46: 6 | B46: EMX | C46: 07.04.10 | D46: GG/006/10-11 | E46: 459000
A47: 7 | B47: SONU | C47: 07.04.10 | D47: 0 | E47: 459000
A48: 8 | B48: ARIES | C48: 07.04.10 | D48: GD/002/10-11 | E48: 137394
A49: 9 | B49: Contact-004 | C49: 07.04.10 | D49: GG/008/10-11 | E49: 306000
A50: 10 | B50: Dealer-014 | C50: 07.04.10 | D50: GG/009/10-11 | E50: 306000
A51: 11 | B51: BHATIA | C51: 08.04.10 | D51: GG/010/10-11 | E51: 918000
A52: 12 | B52: SONU | C52: 09.04.10 | D52: GG/011/10-11 | E52: 438700 | HL52: 187
A53: 13 | B53: BHATIA | C53: 17.04.10 | D53: GD/008/10-11 | E53: =15300*60 -> 918000
A54: 14 | B54: Dealer-014 | C54: 19.04.10 | D54: GG/012/10-11 | E54: =15300*30 -> 459000
A55: 15 | B55: EMX | C55: 24.04.10 | D55: GG/013/10-11 | E55: 193300 | FE55: 20
A56: 16 | B56: Transporter-005 | C56: 24.04.10 | D56: GG/014/10-11 | E56: 143750 | FD56: 60 | FE56: 25
A57: 17 | B57: Dealer-026 | C57: 24.04.10 | D57: GG/015/10-11 | E57: 149490 | FC57: 5
A58: 18 | B58: SONU | C58: 24.04.10 | D58: GG/016/10-11 | E58: 1779445 | S58: 15 | W58: 10 | AB58: 15 | AI58: 10 | AN58: 20 | AP58: 10 | AV58: 5 | AW58: 20 | AX58: 10 | AY58: 35 | BB58: 15 | BF58: 15 | BH58: 20 | BK58: 10 | BR58: 100 | BS58: 15 | CH58: 50 | CI58: 200 | CU58: 48 | CX58: 24 | CY58: 6 | DB58: 48 | DC58: 48 | DE58: 48 | DN58: 48 | DP58: 18 | DR58: 30 | DU58: 30 | DV58: 12 | DX58: 24 | DZ58: 24 | EF58: 6 | EH58: 11 | EJ58: 48 | EN58: 42 | FD58: =120+58 -> 178 | FE58: 50 | FV58: 200 | GA58: 700 | GV58: 25 | HF58: 500 | HH58: 100 | HL58: 500 | HM58: 100 | HN58: =285+15 -> 300 | HS58: 115
A59: 19 | B59: Dealer-024 | C59: 24.04.10 | D59: GG/017/10-11 | E59: 109900 | FC59: 25 | FD59: 60 | FE59: 25 | FZ59: 25 | GA59: 300
A60: 20 | B60: Dealer-029 | C60: 24.04.10 | D60: GG/018/10-11 | E60: 217725 | FC60: 10 | FD60: 60 | FE60: 25 | FJ60: 25 | FN60: 10 | FS60: 25 | FW60: 25 | FZ60: 25 | GA60: 300 | HE60: 100 | HF60: 10 | HL60: 100 | HP60: 100
A61: 21 | B61: Contact-004 | C61: 24.04.10 | D61: GG/019/10-11 | E61: 845700 | S61: 20 | AI61: 10 | AN61: 50 | AP61: 5 | AW61: 20 | AY61: 50 | BB61: 25 | BF61: 20 | BH61: 40 | BL61: 20 | BO61: 20 | BR61: 50 | BS61: 20 | CU61: 18 | DA61: 12 | DE61: 18 | DR61: 12 | DV61: 6 | EJ61: 18 | EN61: 18 | FC61: 100 | GA61: 700 | GR61: 20 | HN61: 200
A62: 22 | B62: HEM | C62: 24.04.10 | D62: GG/020/10-11 | E62: 226500 | BK62: 15
A63: 23 | B63: EMX | C63: 26.04.10 | D63: GG/021/10-11 | E63: 994750 | O63: 10 | Q63: 10 | S63: 50 | Y63: 10 | AC63: 5 | AM63: 5 | AN63: 100 | AP63: 5 | AV63: 25 | AW63: 25 | AX63: 50 | BB63: 20 | BP63: 10 | BR63: 200 | BS63: 50 | CR63: 25 | GK63: 2 | HF63: 500 | IA63: 150
A64: 24 | B64: VIMAL | C64: 27.04.10 | D64: GG/022/10-11 | E64: 80000 | ET64: 20
A65: 25 | B65: EMX | C65: 27.04.10 | D65: GG/023/10-11 | E65: 382250 | AP65: 15 | CU65: 24 | DB65: 48 | DE65: 48 | DP65: 24 | DR65: 12 | DX65: 12 | DY65: 12 | GA65: 1000 | HN65: 200
A66: 26 | B66: Dealer-016 | C66: 27.04.10 | D66: GG/024/10-11 | E66: 235000
A67: 27 | B67: Transporter-005 | C67: 28.04.10 | D67: GG/025/10-11 | E67: 1144100 | J67: 5 | S67: 30 | W67: 10 | AB67: 30 | AN67: 100 | AV67: 20 | AX67: 30 | AY67: 100 | BA67: 20 | BB67: 20 | BF67: 30 | BL67: 100 | BR67: 50 | CC67: 50 | CH67: 50 | CU67: 24 | DE67: 48 | DN67: 48 | DP67: 12 | DU67: 30 | EB67: 8 | EJ67: 48 | EN67: 48 | EO67: 12
